Workbook

Sheet Projections
BD2: =Draft!AK3 | BE2: =Draft!AL3 | BF2: =Draft!AM3 | BG2: =Draft!AN3 | BH2: =Draft!AO3
J3: Current Player Auctioned | L3: Draft Average | BD3: =Draft!AK4 | BE3: =Draft!AL4 | BF3: =Draft!AM4 | BG3: =Draft!AN4 | BH3: =Draft!AO4
F4: Total $ Left | G4: =200*13 -> 2600 | J4: $ Value | BD4: =Draft!AK5 | BE4: =Draft!AL5 | BF4: =Draft!AM5 | BG4: =Draft!AN5 | BH4: =Draft!AO5
F5: Total LeagV/$ Left | J5: LeagV/$ | BD5: =Draft!AK6 | BE5: =Draft!AL6 | BF5: =Draft!AM6 | BG5: =Draft!AN6 | BH5: =Draft!AO6
F6: Total PuntV/$ Left | J6: PuntV/$ | BD6: =Draft!AK7 | BE6: =Draft!AL7 | BF6: =Draft!AM7 | BG6: =Draft!AN7 | BH6: =Draft!AO7
BD7: =Draft!AK8 | BE7: =Draft!AL8 | BF7: =Draft!AM8 | BG7: =Draft!AN8 | BH7: =Draft!AO8
BD8: =Draft!AK15 | BE8: =Draft!AL15 | BF8: =Draft!AM15 | BG8: =Draft!AN15 | BH8: =Draft!AO15
J9: Avg Zscore Available | K9: =SUM(Y14:Y1009)/ COUNT($K$14:$K1009) -> -0.016206118 | L9: =SUM(Z14:Z1009)/ COUNT($K$14:$K1009) -> -0.012146398 | M9: =SUM(AA14:AA1009)/ COUNT($K$14:$K1009) -> -0.030786282 | N9: =SUM(AB14:AB1009)/ COUNT($K$14:$K1009) -> 0.033647248 | O9: =SUM(AC14:AC1009)/ COUNT($K$14:$K1009) -> -0.064760135 | P9: =SUM(AD14:AD1009)/ COUNT($K$14:$K1009) -> -0.0051344442 | Q9: =SUM(AE14:AE1009)/ COUNT($K$14:$K1009) -> 0.15190162 | R9: =SUM(AF14:AF1009)/ COUNT($K$14:$K1009) -> 0.15278051 | S9: =SUM(AG14:AG1009)/ COUNT($K$14:$K1009) -> 0
I10: -1 Cat | J10: -2 Cat | K10: PTS | L10: 3P | M10: REB | N10: AST | O10: STL | P10: BLK | Q10: FG% | R10: FT% | S10: TO | T10: PG | U10: SG | V10: SF | W10: PF | X10: C | Z10: Sort by | AB10: Remove Drafted | AE10: Top | AG10: Projections
I11: TRUE | J11: FALSE | K11: 1 | L11: 1 | M11: 1 | N11: 1 | O11: 1 | P11: 1 | Q11: 1 | R11: 1 | S11: 0 | T11: PG | U11: SG | V11: SF | W11: PF | X11: C | Z11: PuntV | AB11: FALSE | AE11: 156 | AG11: BBM
A13: W18 | B13: W19 | C13: W20 | D13: Total | F13: Team | G13: PuntRank | H13: LgRank | I13: Auction $ | J13: Player | K13: GP | L13: Pos | M13: LeagV | N13: PuntV | O13: Punt+ | P13: PTS | Q13: 3P | R13: REB | S13: AST | T13: STL | U13: BLK | V13: FG% | W13: FT% | X13: TO | Y13: z p/g | Z13: z 3/g | AA13: z r/g | AB13: z a/g | AC13: z s/g | AD13: z b/g | AE13: z fg% | AF13: z ft% | AG13: z to/g
A14: =VLOOKUP($F14,UpdateHashtag!$V$3:$Y$32,COLUMN(B$9),0) -> #N/A | B14: =VLOOKUP($F14,UpdateHashtag!$V$3:$Y$32,COLUMN(#REF!),0) -> #REF! | C14: =VLOOKUP($F14,UpdateHashtag!$V$3:$Y$32,COLUMN(#REF!),0) -> #REF! | D14: =SUM(A14:C14) -> #N/A | F14: =VLOOKUP(J14,UpdateBBM!$C$2:E1009,3,0) -> SAS | G14: 1 | H14: =IFERROR(__xludf.DUMMYFUNCTION("Filter('NO USAR3'!B5:AA420,IF('NO USAR3'!AB5:AB420="""",FALSE,TRUE),NOT(COUNTIF('NO USAR3'!A5:A200,'NO USAR3'!D5:D420)),IF('NO USAR3'!B5:B420>AE11,FALSE,TRUE))"),1.0) -> 1 | J14: =IFERROR(__xludf.DUMMYFUNCTION("""COMPUTED_VALUE"""),"Victor Wembanyama") -> Victor Wembanyama | K14: =IFERROR(__xludf.DUMMYFUNCTION("""COMPUTED_VALUE"""),73.0) -> 73 | L14: =IFERROR(__xludf.DUMMYFUNCTION("""COMPUTED_VALUE"""),"C") -> C | M14: =IFERROR(__xludf.DUMMYFUNCTION("""COMPUTED_VALUE"""),11.3425419387325) -> 11.342542 | N14: =IFERROR(__xludf.DUMMYFUNCTION("""COMPUTED_VALUE"""),11.589733589107464) -> 11.589734 | O14: =IFERROR(__xludf.DUMMYFUNCTION("""COMPUTED_VALUE"""),0.2471916503749636) -> 0.24719165 | P14: =IFERROR(__xludf.DUMMYFUNCTION("""COMPUTED_VALUE"""),25.83918) -> 25.83918 | Q14: =IFERROR(__xludf.DUMMYFUNCTION("""COMPUTED_VALUE"""),3.049863) -> 3.049863 | R14: =IFERROR(__xludf.DUMMYFUNCTION("""COMPUTED_VALUE"""),11.92123) -> 11.92123 | S14: =IFERROR(__xludf.DUMMYFUNCTION("""COMPUTED_VALUE"""),3.829315) -> 3.829315 | T14: =IFERROR(__xludf.DUMMYFUNCTION("""COMPUTED_VALUE"""),1.158356) -> 1.158356 | U14: =IFERROR(__xludf.DUMMYFUNCTION("""COMPUTED_VALUE"""),3.901507) -> 3.901507 | V14: =IFERROR(__xludf.DUMMYFUNCTION("""COMPUTED_VALUE"""),0.491121) -> 0.491121 | W14: =IFERROR(__xludf.DUMMYFUNCTION("""COMPUTED_VALUE"""),0.816988) -> 0.816988 | X14: =IFERROR(__xludf.DUMMYFUNCTION("""COMPUTED_VALUE"""),2.745479) -> 2.745479 | Y14: =IFERROR(__xludf.DUMMYFUNCTION("""COMPUTED_VALUE"""),1.520135093083864) -> 1.5201351 | Z14: =IFERROR(__xludf.DUMMYFUNCTION("""COMPUTED_VALUE"""),1.2365655716765753) -> 1.2365656 | AA14: =IFERROR(__xludf.DUMMYFUNCTION("""COMPUTED_VALUE"""),2.348916477230807) -> 2.3489165 | AB14: =IFERROR(__xludf.DUMMYFUNCTION("""COMPUTED_VALUE"""),-0.003704573661539899) -> -0.0037045737 | AC14: =IFERROR(__xludf.DUMMYFUNCTION("""COMPUTED_VALUE"""),0.34484979672257154) -> 0.3448498 | AD14: =IFERROR(__xludf.DUMMYFUNCTION("""COMPUTED_VALUE"""),5.76537101565873) -> 5.765371 | AE14: =IFERROR(__xludf.DUMMYFUNCTION("""COMPUTED_VALUE"""),-0.059921646652902165) -> -0.059921647 | AF14: =IFERROR(__xludf.DUMMYFUNCTION("""COMPUTED_VALUE"""),0.3776002083964553) -> 0.37760021 | AG14: =IFERROR(__xludf.DUMMYFUNCTION("""COMPUTED_VALUE"""),0.0) -> 0 | AK14: 1 | AL14: 2 | AM14: 3 | AN14: 4 | AO14: 5 | AP14: 6 | AQ14: 7 | AR14: 8 | AS14: 9 | AT14: 10 | AU14: 11 | AV14: 12
A15: =VLOOKUP($F15,UpdateHashtag!$V$3:$Y$32,COLUMN(B$9),0) -> 3 | B15: =VLOOKUP($F15,UpdateHashtag!$V$3:$Y$32,COLUMN(#REF!),0) -> #REF! | C15: =VLOOKUP($F15,UpdateHashtag!$V$3:$Y$32,COLUMN(#REF!),0) -> #REF! | D15: =SUM(A15:C15) -> #REF! | F15: =VLOOKUP(J15,UpdateBBM!$C$2:E1009,3,0) -> DEN | G15: 2 | H15: =IFERROR(__xludf.DUMMYFUNCTION("""COMPUTED_VALUE"""),2.0) -> 2 | J15: =IFERROR(__xludf.DUMMYFUNCTION("""COMPUTED_VALUE"""),"Nikola Jokic") -> Nikola Jokic | K15: =IFERROR(__xludf.DUMMYFUNCTION("""COMPUTED_VALUE"""),73.0) -> 73 | L15: =IFERROR(__xludf.DUMMYFUNCTION("""COMPUTED_VALUE"""),"C") -> C | M15: =IFERROR(__xludf.DUMMYFUNCTION("""COMPUTED_VALUE"""),9.4823258240044) -> 9.4823258 | N15: =IFERROR(__xludf.DUMMYFUNCTION("""COMPUTED_VALUE"""),9.821236890688052) -> 9.8212369 | O15: =IFERROR(__xludf.DUMMYFUNCTION("""COMPUTED_VALUE"""),0.3389110666836519) -> 0.33891107 | P15: =IFERROR(__xludf.DUMMYFUNCTION("""COMPUTED_VALUE"""),27.67616) -> 27.67616 | Q15: =IFERROR(__xludf.DUMMYFUNCTION("""COMPUTED_VALUE"""),1.596849) -> 1.596849 | R15: =IFERROR(__xludf.DUMMYFUNCTION("""COMPUTED_VALUE"""),12.16205) -> 12.16205 | S15: =IFERROR(__xludf.DUMMYFUNCTION("""COMPUTED_VALUE"""),8.994658) -> 8.994658 | T15: =IFERROR(__xludf.DUMMYFUNCTION("""COMPUTED_VALUE"""),1.430822) -> 1.430822 | U15: =IFERROR(__xludf.DUMMYFUNCTION("""COMPUTED_VALUE"""),0.715479) -> 0.715479 | V15: =IFERROR(__xludf.DUMMYFUNCTION("""COMPUTED_VALUE"""),0.585091) -> 0.585091 | W15: =IFERROR(__xludf.DUMMYFUNCTION("""COMPUTED_VALUE"""),0.810004) -> 0.810004 | X15: =IFERROR(__xludf.DUMMYFUNCTION("""COMPUTED_VALUE"""),3.115342) -> 3.115342 | Y15: =IFERROR(__xludf.DUMMYFUNCTION("""COMPUTED_VALUE"""),1.842419662370102) -> 1.8424197 | Z15: =IFERROR(__xludf.DUMMYFUNCTION("""COMPUTED_VALUE"""),-0.1668039380108046) -> -0.16680394 | AA15: =IFERROR(__xludf.DUMMYFUNCTION("""COMPUTED_VALUE"""),2.446533732690303) -> 2.4465337 | AB15: =IFERROR(__xludf.DUMMYFUNCTION("""COMPUTED_VALUE"""),2.51964036424524) -> 2.5196404 | AC15: =IFERROR(__xludf.DUMMYFUNCTION("""COMPUTED_VALUE"""),1.1751163763235453) -> 1.1751164 | AD15: =IFERROR(__xludf.DUMMYFUNCTION("""COMPUTED_VALUE"""),-0.02680311688072257) -> -0.026803117 | AE15: =IFERROR(__xludf.DUMMYFUNCTION("""COMPUTED_VALUE"""),1.5802315736235906) -> 1.5802316 | AF15: =IFERROR(__xludf.DUMMYFUNCTION("""COMPUTED_VALUE"""),0.28409829831599426) -> 0.2840983 | AG15: =IFERROR(__xludf.DUMMYFUNCTION("""COMPUTED_VALUE"""),0.0) -> 0 | AJ15: % Games/Week | AK15: Categories won | AW15: Round | AX15: Player Name | AZ15: PTS | BA15: 3P | BB15: REB | BC15: AST | BD15: STL | BE15: BLK | BF15: FG% | BG15: FT% | BH15: TO | BI15: POS | BJ15: Count | BK15: POS
A16: =VLOOKUP($F16,UpdateHashtag!$V$3:$Y$32,COLUMN(B$9),0) -> 3 | B16: =VLOOKUP($F16,UpdateHashtag!$V$3:$Y$32,COLUMN(#REF!),0) -> #REF! | C16: =VLOOKUP($F16,UpdateHashtag!$V$3:$Y$32,COLUMN(#REF!),0) -> #REF! | D16: =SUM(A16:C16) -> #REF! | F16: =VLOOKUP(J16,UpdateBBM!$C$2:E1009,3,0) -> LAL | G16: 3 | H16: =IFERROR(__xludf.DUMMYFUNCTION("""COMPUTED_VALUE"""),3.0) -> 3 | J16: =IFERROR(__xludf.DUMMYFUNCTION("""COMPUTED_VALUE"""),"Luka Doncic") -> Luka Doncic | K16: =IFERROR(__xludf.DUMMYFUNCTION("""COMPUTED_VALUE"""),68.0) -> 68 | L16: =IFERROR(__xludf.DUMMYFUNCTION("""COMPUTED_VALUE"""),"G") -> G | M16: =IFERROR(__xludf.DUMMYFUNCTION("""COMPUTED_VALUE"""),7.082632867736175) -> 7.0826329 | N16: =IFERROR(__xludf.DUMMYFUNCTION("""COMPUTED_VALUE"""),7.5056636902266645) -> 7.5056637 | O16: =IFERROR(__xludf.DUMMYFUNCTION("""COMPUTED_VALUE"""),0.42303082249048973) -> 0.42303082 | P16: =IFERROR(__xludf.DUMMYFUNCTION("""COMPUTED_VALUE"""),29.94368) -> 29.94368 | Q16: =IFERROR(__xludf.DUMMYFUNCTION("""COMPUTED_VALUE"""),3.678088) -> 3.678088 | R16: =IFERROR(__xludf.DUMMYFUNCTION("""COMPUTED_VALUE"""),7.791029) -> 7.791029 | S16: =IFERROR(__xludf.DUMMYFUNCTION("""COMPUTED_VALUE"""),7.497059) -> 7.497059 | T16: =IFERROR(__xludf.DUMMYFUNCTION("""COMPUTED_VALUE"""),1.47) -> 1.47 | U16: =IFERROR(__xludf.DUMMYFUNCTION("""COMPUTED_VALUE"""),0.44) -> 0.44 | V16: =IFERROR(__xludf.DUMMYFUNCTION("""COMPUTED_VALUE"""),0.468707) -> 0.468707 | W16: =IFERROR(__xludf.DUMMYFUNCTION("""COMPUTED_VALUE"""),0.791004) -> 0.791004 | X16: =IFERROR(__xludf.DUMMYFUNCTION("""COMPUTED_VALUE"""),3.454559) -> 3.454559 | Y16: =IFERROR(__xludf.DUMMYFUNCTION("""COMPUTED_VALUE"""),2.2402392938020883) -> 2.2402393 | Z16: =IFERROR(__xludf.DUMMYFUNCTION("""COMPUTED_VALUE"""),1.8433262843905296) -> 1.8433263 | AA16: =IFERROR(__xludf.DUMMYFUNCTION("""COMPUTED_VALUE"""),0.6747246073027928) -> 0.67472461 | AB16: =IFERROR(__xludf.DUMMYFUNCTION("""COMPUTED_VALUE"""),1.788041541928067) -> 1.7880415 | AC16: =IFERROR(__xludf.DUMMYFUNCTION("""COMPUTED_VALUE"""),1.2945007547619811) -> 1.2945008 | AD16: =IFERROR(__xludf.DUMMYFUNCTION("""COMPUTED_VALUE"""),-0.5276217970234695) -> -0.5276218 | AE16: =IFERROR(__xludf.DUMMYFUNCTION("""COMPUTED_VALUE"""),-0.3727730401818931) -> -0.37277304 | AF16: =IFERROR(__xludf.DUMMYFUNCTION("""COMPUTED_VALUE"""),0.03760424822309971) -> 0.037604248 | AG16: =IFERROR(__xludf.DUMMYFUNCTION("""COMPUTED_VALUE"""),0.0) -> 0 | AJ16: 100 | AK16: {=if(AK$14=$J3,"-", countif(indirect(address(row($J$2)+ VLOOKUP(AK$14,$J$3:$J$8,1),COLUMN($K$4))):indirect(address(row($J$2)+ VLOOKUP(AK$14,$J$3:$J$8,1),COLUMN($S$2)))>indirect(address(row($J3),COLUMN($K$2))):indirect(address(row($J3),COLUMN($S$2))),TRUE()))} -> 0 | AL16: {=if(AL$14=$J3,"-", countif(indirect(address(row($J$2)+ VLOOKUP(AL$14,$J$3:$J$8,1),COLUMN($K$4))):indirect(address(row($J$2)+ VLOOKUP(AL$14,$J$3:$J$8,1),COLUMN($S$2)))>indirect(address(row($J3),COLUMN($K$2))):indirect(address(row($J3),COLUMN($S$2))),TRUE()))} -> 0 | AM16: {=if(AM$14=$J3,"-", countif(indirect(address(row($J$2)+ VLOOKUP(AM$14,$J$3:$J$8,1),COLUMN($K$4))):indirect(address(row($J$2)+ VLOOKUP(AM$14,$J$3:$J$8,1),COLUMN($S$2)))>indirect(address(row($J3),COLUMN($K$2))):indirect(address(row($J3),COLUMN($S$2))),TRUE()))} -> 0 | AN16: {=if(AN$14=$J3,"-", countif(indirect(address(row($J$2)+ VLOOKUP(AN$14,$J$3:$J$8,1),COLUMN($K$4))):indirect(address(row($J$2)+ VLOOKUP(AN$14,$J$3:$J$8,1),COLUMN($S$2)))>indirect(address(row($J3),COLUMN($K$2))):indirect(address(row($J3),COLUMN($S$2))),TRUE()))} -> 0 | AO16: {=if(AO$14=$J3,"-", countif(indirect(address(row($J$2)+ VLOOKUP(AO$14,$J$3:$J$8,1),COLUMN($K$4))):indirect(address(row($J$2)+ VLOOKUP(AO$14,$J$3:$J$8,1),COLUMN($S$2)))>indirect(address(row($J3),COLUMN($K$2))):indirect(address(row($J3),COLUMN($S$2))),TRUE()))} -> 0 | AP16: {=if(AP$14=$J3,"-", countif(indirect(address(row($J$2)+ VLOOKUP(AP$14,$J$3:$J$8,1),COLUMN($K$4))):indirect(address(row($J$2)+ VLOOKUP(AP$14,$J$3:$J$8,1),COLUMN($S$2)))>indirect(address(row($J3),COLUMN($K$2))):indirect(address(row($J3),COLUMN($S$2))),TRUE()))} -> 0 | AQ16: {=if(AQ$14=$J3,"-", countif(indirect(address(row($J$2)+ VLOOKUP(AQ$14,$J$3:$J$8,1),COLUMN($K$4))):indirect(address(row($J$2)+ VLOOKUP(AQ$14,$J$3:$J$8,1),COLUMN($S$2)))>indirect(address(row($J3),COLUMN($K$2))):indirect(address(row($J3),COLUMN($S$2))),TRUE()))} -> 0 | AR16: {=if(AR$14=$J3,"-", countif(indirect(address(row($J$2)+ VLOOKUP(AR$14,$J$3:$J$8,1),COLUMN($K$4))):indirect(address(row($J$2)+ VLOOKUP(AR$14,$J$3:$J$8,1),COLUMN($S$2)))>indirect(address(row($J3),COLUMN($K$2))):indirect(address(row($J3),COLUMN($S$2))),TRUE()))} -> 0 | ... AV16: {=if(AV$14=$J3,"-", countif(indirect(address(row($J$2)+ VLOOKUP(AV$14,$J$3:$J$8,1),COLUMN($K$4))):indirect(address(row($J$2)+ VLOOKUP(AV$14,$J$3:$J$8,1),COLUMN($S$2)))>indirect(address(row($J3),COLUMN($K$2))):indirect(address(row($J3),COLUMN($S$2))),TRUE()))} -> 0 | AW16: 1 | AX16: {=INDIRECT("Draft!D"&TEXT(VLOOKUP(TRUE,I3:J8,2,0)+2,"0"))} -> #N/A | AZ16: =IF($AX16="","", VLOOKUP($AX16,'Final Update'!$Q$21:$AE1009,Column(G1),False)) -> #N/A | BA16: =IF($AX16="","", VLOOKUP($AX16,'Final Update'!$Q$21:$AE1009,Column(H1),False)) -> #N/A | BB16: =IF($AX16="","", VLOOKUP($AX16,'Final Update'!$Q$21:$AE1009,Column(I1),False)) -> #N/A | BC16: =IF($AX16="","", VLOOKUP($AX16,'Final Update'!$Q$21:$AE1009,Column(J1),False)) -> #N/A | BD16: =IF($AX16="","", VLOOKUP($AX16,'Final Update'!$Q$21:$AE1009,Column(K1),False)) -> #N/A | BE16: =IF($AX16="","", VLOOKUP($AX16,'Final Update'!$Q$21:$AE1009,Column(L1),False)) -> #N/A | BF16: =IF($AX16="","", VLOOKUP($AX16,'Final Update'!$Q$21:$AE1009,Column(M1),False)) -> #N/A | BG16: =IF($AX16="","", VLOOKUP($AX16,'Final Update'!$Q$21:$AE1009,Column(N1),False)) -> #N/A | BH16: =IF($AX16="","", VLOOKUP($AX16,'Final Update'!$Q$21:$AE1009,Column(O1),False)) -> #N/A | BI16: =IF($AX16="","", VLOOKUP($AX16,'Final Update'!$Q$21:$AE1009,Column(C1),False)) -> #N/A | BJ16: {=COUNTIF(FIND(BK16,$BI$16:$BI$27),">0")} -> 0 | BK16: PG
A17: =VLOOKUP($F17,UpdateHashtag!$V$3:$Y$32,COLUMN(B$9),0) -> 4 | B17: =VLOOKUP($F17,UpdateHashtag!$V$3:$Y$32,COLUMN(#REF!),0) -> #REF! | C17: =VLOOKUP($F17,UpdateHashtag!$V$3:$Y$32,COLUMN(#REF!),0) -> #REF! | D17: =SUM(A17:C17) -> #REF! | F17: =VLOOKUP(J17,UpdateBBM!$C$2:E1009,3,0) -> OKC | G17: 4 | H17: =IFERROR(__xludf.DUMMYFUNCTION("""COMPUTED_VALUE"""),4.0) -> 4 | J17: =IFERROR(__xludf.DUMMYFUNCTION("""COMPUTED_VALUE"""),"Shai Gilgeous-Alexander") -> Shai Gilgeous-Alexander | K17: =IFERROR(__xludf.DUMMYFUNCTION("""COMPUTED_VALUE"""),73.0) -> 73 | L17: =IFERROR(__xludf.DUMMYFUNCTION("""COMPUTED_VALUE"""),"G") -> G | M17: =IFERROR(__xludf.DUMMYFUNCTION("""COMPUTED_VALUE"""),6.761339091582645) -> 6.7613391 | N17: =IFERROR(__xludf.DUMMYFUNCTION("""COMPUTED_VALUE"""),6.7798438491212725) -> 6.7798438 | O17: =IFERROR(__xludf.DUMMYFUNCTION("""COMPUTED_VALUE"""),0.01850475753862746) -> 0.018504758 | P17: =IFERROR(__xludf.DUMMYFUNCTION("""COMPUTED_VALUE"""),30.51822) -> 30.51822 | Q17: =IFERROR(__xludf.DUMMYFUNCTION("""COMPUTED_VALUE"""),1.935479) -> 1.935479 | R17: =IFERROR(__xludf.DUMMYFUNCTION("""COMPUTED_VALUE"""),4.558082) -> 4.558082 | S17: =IFERROR(__xludf.DUMMYFUNCTION("""COMPUTED_VALUE"""),6.030685) -> 6.030685 | T17: =IFERROR(__xludf.DUMMYFUNCTION("""COMPUTED_VALUE"""),1.462877) -> 1.462877 | U17: =IFERROR(__xludf.DUMMYFUNCTION("""COMPUTED_VALUE"""),0.91589) -> 0.91589 | V17: =IFERROR(__xludf.DUMMYFUNCTION("""COMPUTED_VALUE"""),0.505971) -> 0.505971 | W17: =IFERROR(__xludf.DUMMYFUNCTION("""COMPUTED_VALUE"""),0.889004) -> 0.889004 | X17: =IFERROR(__xludf.DUMMYFUNCTION("""COMPUTED_VALUE"""),1.823288) -> 1.823288 | Y17: =IFERROR(__xludf.DUMMYFUNCTION("""COMPUTED_VALUE"""),2.341038092067565) -> 2.3410381 | Z17: =IFERROR(__xludf.DUMMYFUNCTION("""COMPUTED_VALUE"""),0.16025623970629752) -> 0.16025624 | AA17: =IFERROR(__xludf.DUMMYFUNCTION("""COMPUTED_VALUE"""),-0.6357621179941515) -> -0.63576212 | AB17: =IFERROR(__xludf.DUMMYFUNCTION("""COMPUTED_VALUE"""),1.0716965847823137) -> 1.0716966 | AC17: =IFERROR(__xludf.DUMMYFUNCTION("""COMPUTED_VALUE"""),1.2727953351995487) -> 1.2727953 | AD17: =IFERROR(__xludf.DUMMYFUNCTION("""COMPUTED_VALUE"""),0.33754252291791204) -> 0.33754252 | AE17: =IFERROR(__xludf.DUMMYFUNCTION("""COMPUTED_VALUE"""),0.1639756592911051) -> 0.16397566 | AF17: =IFERROR(__xludf.DUMMYFUNCTION("""COMPUTED_VALUE"""),1.4325394151565307) -> 1.4325394 | AG17: =IFERROR(__xludf.DUMMYFUNCTION("""COMPUTED_VALUE"""),0.0) -> 0 | AJ17: 100 | AK17: {=if(AK$14=$J4,"-", countif(indirect(address(row($J$2)+ VLOOKUP(AK$14,$J$3:$J$8,1),COLUMN($K$4))):indirect(address(row($J$2)+ VLOOKUP(AK$14,$J$3:$J$8,1),COLUMN($S$2)))>indirect(address(row($J4),COLUMN($K$2))):indirect(address(row($J4),COLUMN($S$2))),TRUE()))} -> 0 | AL17: {=if(AL$14=$J4,"-", countif(indirect(address(row($J$2)+ VLOOKUP(AL$14,$J$3:$J$8,1),COLUMN($K$4))):indirect(address(row($J$2)+ VLOOKUP(AL$14,$J$3:$J$8,1),COLUMN($S$2)))>indirect(address(row($J4),COLUMN($K$2))):indirect(address(row($J4),COLUMN($S$2))),TRUE()))} -> 0 | AM17: {=if(AM$14=$J4,"-", countif(indirect(address(row($J$2)+ VLOOKUP(AM$14,$J$3:$J$8,1),COLUMN($K$4))):indirect(address(row($J$2)+ VLOOKUP(AM$14,$J$3:$J$8,1),COLUMN($S$2)))>indirect(address(row($J4),COLUMN($K$2))):indirect(address(row($J4),COLUMN($S$2))),TRUE()))} -> 0 | AN17: {=if(AN$14=$J4,"-", countif(indirect(address(row($J$2)+ VLOOKUP(AN$14,$J$3:$J$8,1),COLUMN($K$4))):indirect(address(row($J$2)+ VLOOKUP(AN$14,$J$3:$J$8,1),COLUMN($S$2)))>indirect(address(row($J4),COLUMN($K$2))):indirect(address(row($J4),COLUMN($S$2))),TRUE()))} -> 0 | AO17: {=if(AO$14=$J4,"-", countif(indirect(address(row($J$2)+ VLOOKUP(AO$14,$J$3:$J$8,1),COLUMN($K$4))):indirect(address(row($J$2)+ VLOOKUP(AO$14,$J$3:$J$8,1),COLUMN($S$2)))>indirect(address(row($J4),COLUMN($K$2))):indirect(address(row($J4),COLUMN($S$2))),TRUE()))} -> 0 | AP17: {=if(AP$14=$J4,"-", countif(indirect(address(row($J$2)+ VLOOKUP(AP$14,$J$3:$J$8,1),COLUMN($K$4))):indirect(address(row($J$2)+ VLOOKUP(AP$14,$J$3:$J$8,1),COLUMN($S$2)))>indirect(address(row($J4),COLUMN($K$2))):indirect(address(row($J4),COLUMN($S$2))),TRUE()))} -> 0 | AQ17: {=if(AQ$14=$J4,"-", countif(indirect(address(row($J$2)+ VLOOKUP(AQ$14,$J$3:$J$8,1),COLUMN($K$4))):indirect(address(row($J$2)+ VLOOKUP(AQ$14,$J$3:$J$8,1),COLUMN($S$2)))>indirect(address(row($J4),COLUMN($K$2))):indirect(address(row($J4),COLUMN($S$2))),TRUE()))} -> 0 | AR17: {=if(AR$14=$J4,"-", countif(indirect(address(row($J$2)+ VLOOKUP(AR$14,$J$3:$J$8,1),COLUMN($K$4))):indirect(address(row($J$2)+ VLOOKUP(AR$14,$J$3:$J$8,1),COLUMN($S$2)))>indirect(address(row($J4),COLUMN($K$2))):indirect(address(row($J4),COLUMN($S$2))),TRUE()))} -> 0 | ... AV17: {=if(AV$14=$J4,"-", countif(indirect(address(row($J$2)+ VLOOKUP(AV$14,$J$3:$J$8,1),COLUMN($K$4))):indirect(address(row($J$2)+ VLOOKUP(AV$14,$J$3:$J$8,1),COLUMN($S$2)))>indirect(address(row($J4),COLUMN($K$2))):indirect(address(row($J4),COLUMN($S$2))),TRUE()))} -> 0 | AW17: 2 | AX17: {=INDIRECT("Draft!E"&TEXT(15-VLOOKUP(TRUE,I3:J8,2,0),"0"))} -> #N/A | AZ17: =IF($AX17="","", VLOOKUP($AX17,'Final Update'!$Q$21:$AE1009,Column(G2),False)) -> #N/A | BA17: =IF($AX17="","", VLOOKUP($AX17,'Final Update'!$Q$21:$AE1009,Column(H2),False)) -> #N/A | BB17: =IF($AX17="","", VLOOKUP($AX17,'Final Update'!$Q$21:$AE1009,Column(I2),False)) -> #N/A | BC17: =IF($AX17="","", VLOOKUP($AX17,'Final Update'!$Q$21:$AE1009,Column(J2),False)) -> #N/A | BD17: =IF($AX17="","", VLOOKUP($AX17,'Final Update'!$Q$21:$AE1009,Column(K2),False)) -> #N/A | BE17: =IF($AX17="","", VLOOKUP($AX17,'Final Update'!$Q$21:$AE1009,Column(L3),False)) -> #N/A | BF17: =IF($AX17="","", VLOOKUP($AX17,'Final Update'!$Q$21:$AE1009,Column(M2),False)) -> #N/A | BG17: =IF($AX17="","", VLOOKUP($AX17,'Final Update'!$Q$21:$AE1009,Column(N2),False)) -> #N/A | BH17: =IF($AX17="","", VLOOKUP($AX17,'Final Update'!$Q$21:$AE1009,Column(O2),False)) -> #N/A | BI17: =IF($AX17="","", VLOOKUP($AX17,'Final Update'!$Q$21:$AE1009,Column(C2),False)) -> #N/A | BJ17: {=COUNTIF(FIND(BK17,$BI$16:$BI$27),">0")} -> 0 | BK17: SG
A18: =VLOOKUP($F18,UpdateHashtag!$V$3:$Y$32,COLUMN(B$9),0) -> 4 | B18: =VLOOKUP($F18,UpdateHashtag!$V$3:$Y$32,COLUMN(#REF!),0) -> #REF! | C18: =VLOOKUP($F18,UpdateHashtag!$V$3:$Y$32,COLUMN(#REF!),0) -> #REF! | D18: =SUM(A18:C18) -> #REF! | F18: =VLOOKUP(J18,UpdateBBM!$C$2:E1009,3,0) -> MIL | G18: 5 | H18: =IFERROR(__xludf.DUMMYFUNCTION("""COMPUTED_VALUE"""),5.0) -> 5 | J18: =IFERROR(__xludf.DUMMYFUNCTION("""COMPUTED_VALUE"""),"Giannis Antetokounmpo") -> Giannis Antetokounmpo | K18: =IFERROR(__xludf.DUMMYFUNCTION("""COMPUTED_VALUE"""),61.0) -> 61 | L18: =IFERROR(__xludf.DUMMYFUNCTION("""COMPUTED_VALUE"""),"F,C") -> F,C | M18: =IFERROR(__xludf.DUMMYFUNCTION("""COMPUTED_VALUE"""),6.561425853867311) -> 6.5614259 | N18: =IFERROR(__xludf.DUMMYFUNCTION("""COMPUTED_VALUE"""),6.83742310901598) -> 6.8374231 | O18: =IFERROR(__xludf.DUMMYFUNCTION("""COMPUTED_VALUE"""),0.2759972551486687) -> 0.27599726 | P18: =IFERROR(__xludf.DUMMYFUNCTION("""COMPUTED_VALUE"""),31.87295) -> 31.87295 | Q18: =IFERROR(__xludf.DUMMYFUNCTION("""COMPUTED_VALUE"""),0.322951) -> 0.322951 | R18: =IFERROR(__xludf.DUMMYFUNCTION("""COMPUTED_VALUE"""),11.01738) -> 11.01738 | S18: =IFERROR(__xludf.DUMMYFUNCTION("""COMPUTED_VALUE"""),8.227213) -> 8.227213 | T18: =IFERROR(__xludf.DUMMYFUNCTION("""COMPUTED_VALUE"""),0.929508) -> 0.929508 | U18: =IFERROR(__xludf.DUMMYFUNCTION("""COMPUTED_VALUE"""),0.93) -> 0.93 | V18: =IFERROR(__xludf.DUMMYFUNCTION("""COMPUTED_VALUE"""),0.582004) -> 0.582004 | W18: =IFERROR(__xludf.DUMMYFUNCTION("""COMPUTED_VALUE"""),0.638995) -> 0.638995 | X18: =IFERROR(__xludf.DUMMYFUNCTION("""COMPUTED_VALUE"""),2.861639) -> 2.861639 | Y18: =IFERROR(__xludf.DUMMYFUNCTION("""COMPUTED_VALUE"""),2.5787154617445047) -> 2.5787155 | Z18: =IFERROR(__xludf.DUMMYFUNCTION("""COMPUTED_VALUE"""),-1.397177225296222) -> -1.3971772 | AA18: =IFERROR(__xludf.DUMMYFUNCTION("""COMPUTED_VALUE"""),1.9825376202128466) -> 1.9825376 | AB18: =IFERROR(__xludf.DUMMYFUNCTION("""COMPUTED_VALUE"""),2.144732356031291) -> 2.1447324 | AC18: =IFERROR(__xludf.DUMMYFUNCTION("""COMPUTED_VALUE"""),-0.3525027030701494) -> -0.3525027 | AD18: =IFERROR(__xludf.DUMMYFUNCTION("""COMPUTED_VALUE"""),0.363194393212251) -> 0.36319439 | AE18: =IFERROR(__xludf.DUMMYFUNCTION("""COMPUTED_VALUE"""),1.5179232061814574) -> 1.5179232 | AF18: =IFERROR(__xludf.DUMMYFUNCTION("""COMPUTED_VALUE"""),-1.519645010763219) -> -1.519645 | AG18: =IFERROR(__xludf.DUMMYFUNCTION("""COMPUTED_VALUE"""),0.0) -> 0 | AJ18: 100 | AK18: {=if(AK$14=$J5,"-", countif(indirect(address(row($J$2)+ VLOOKUP(AK$14,$J$3:$J$8,1),COLUMN($K$4))):indirect(address(row($J$2)+ VLOOKUP(AK$14,$J$3:$J$8,1),COLUMN($S$2)))>indirect(address(row($J5),COLUMN($K$2))):indirect(address(row($J5),COLUMN($S$2))),TRUE()))} -> 0 | AL18: {=if(AL$14=$J5,"-", countif(indirect(address(row($J$2)+ VLOOKUP(AL$14,$J$3:$J$8,1),COLUMN($K$4))):indirect(address(row($J$2)+ VLOOKUP(AL$14,$J$3:$J$8,1),COLUMN($S$2)))>indirect(address(row($J5),COLUMN($K$2))):indirect(address(row($J5),COLUMN($S$2))),TRUE()))} -> 0 | AM18: {=if(AM$14=$J5,"-", countif(indirect(address(row($J$2)+ VLOOKUP(AM$14,$J$3:$J$8,1),COLUMN($K$4))):indirect(address(row($J$2)+ VLOOKUP(AM$14,$J$3:$J$8,1),COLUMN($S$2)))>indirect(address(row($J5),COLUMN($K$2))):indirect(address(row($J5),COLUMN($S$2))),TRUE()))} -> 0 | AN18: {=if(AN$14=$J5,"-", countif(indirect(address(row($J$2)+ VLOOKUP(AN$14,$J$3:$J$8,1),COLUMN($K$4))):indirect(address(row($J$2)+ VLOOKUP(AN$14,$J$3:$J$8,1),COLUMN($S$2)))>indirect(address(row($J5),COLUMN($K$2))):indirect(address(row($J5),COLUMN($S$2))),TRUE()))} -> 0 | AO18: {=if(AO$14=$J5,"-", countif(indirect(address(row($J$2)+ VLOOKUP(AO$14,$J$3:$J$8,1),COLUMN($K$4))):indirect(address(row($J$2)+ VLOOKUP(AO$14,$J$3:$J$8,1),COLUMN($S$2)))>indirect(address(row($J5),COLUMN($K$2))):indirect(address(row($J5),COLUMN($S$2))),TRUE()))} -> 0 | AP18: {=if(AP$14=$J5,"-", countif(indirect(address(row($J$2)+ VLOOKUP(AP$14,$J$3:$J$8,1),COLUMN($K$4))):indirect(address(row($J$2)+ VLOOKUP(AP$14,$J$3:$J$8,1),COLUMN($S$2)))>indirect(address(row($J5),COLUMN($K$2))):indirect(address(row($J5),COLUMN($S$2))),TRUE()))} -> 0 | AQ18: {=if(AQ$14=$J5,"-", countif(indirect(address(row($J$2)+ VLOOKUP(AQ$14,$J$3:$J$8,1),COLUMN($K$4))):indirect(address(row($J$2)+ VLOOKUP(AQ$14,$J$3:$J$8,1),COLUMN($S$2)))>indirect(address(row($J5),COLUMN($K$2))):indirect(address(row($J5),COLUMN($S$2))),TRUE()))} -> 0 | AR18: {=if(AR$14=$J5,"-", countif(indirect(address(row($J$2)+ VLOOKUP(AR$14,$J$3:$J$8,1),COLUMN($K$4))):indirect(address(row($J$2)+ VLOOKUP(AR$14,$J$3:$J$8,1),COLUMN($S$2)))>indirect(address(row($J5),COLUMN($K$2))):indirect(address(row($J5),COLUMN($S$2))),TRUE()))} -> 0 | ... AV18: {=if(AV$14=$J5,"-", countif(indirect(address(row($J$2)+ VLOOKUP(AV$14,$J$3:$J$8,1),COLUMN($K$4))):indirect(address(row($J$2)+ VLOOKUP(AV$14,$J$3:$J$8,1),COLUMN($S$2)))>indirect(address(row($J5),COLUMN($K$2))):indirect(address(row($J5),COLUMN($S$2))),TRUE()))} -> 0 | AW18: 3 | AX18: {=INDIRECT("Draft!F"&TEXT(VLOOKUP(TRUE,I3:J8,2,0)+2,"0"))} -> #N/A | AZ18: =IF($AX18="","", VLOOKUP($AX18,'Final Update'!$Q$21:$AE1009,Column(#REF!),False)) -> #N/A | BA18: =IF($AX18="","", VLOOKUP($AX18,'Final Update'!$Q$21:$AE1009,Column(H3),False)) -> #N/A | BB18: =IF($AX18="","", VLOOKUP($AX18,'Final Update'!$Q$21:$AE1009,Column(I3),False)) -> #N/A | BC18: =IF($AX18="","", VLOOKUP($AX18,'Final Update'!$Q$21:$AE1009,Column(J3),False)) -> #N/A | BD18: =IF($AX18="","", VLOOKUP($AX18,'Final Update'!$Q$21:$AE1009,Column(K3),False)) -> #N/A | BE18: =IF($AX18="","", VLOOKUP($AX18,'Final Update'!$Q$21:$AE1009,Column(#REF!),False)) -> #N/A | BF18: =IF($AX18="","", VLOOKUP($AX18,'Final Update'!$Q$21:$AE1009,Column(M3),False)) -> #N/A | BG18: =IF($AX18="","", VLOOKUP($AX18,'Final Update'!$Q$21:$AE1009,Column(#REF!),False)) -> #N/A | BH18: =IF($AX18="","", VLOOKUP($AX18,'Final Update'!$Q$21:$AE1009,Column(#REF!),False)) -> #N/A | BI18: =IF($AX18="","", VLOOKUP($AX18,'Final Update'!$Q$21:$AE1009,Column(C3),False)) -> #N/A | BJ18: {=COUNTIF(FIND(BK18,$BI$16:$BI$27),">0")} -> 0 | BK18: SF
A19: =VLOOKUP($F19,UpdateHashtag!$V$3:$Y$32,COLUMN(B$9),0) -> 4 | B19: =VLOOKUP($F19,UpdateHashtag!$V$3:$Y$32,COLUMN(#REF!),0) -> #REF! | C19: =VLOOKUP($F19,UpdateHashtag!$V$3:$Y$32,COLUMN(#REF!),0) -> #REF! | D19: =SUM(A19:C19) -> #REF! | F19: =VLOOKUP(J19,UpdateBBM!$C$2:E1009,3,0) -> ATL | G19: 6 | H19: =IFERROR(__xludf.DUMMYFUNCTION("""COMPUTED_VALUE"""),6.0) -> 6 | J19: =IFERROR(__xludf.DUMMYFUNCTION("""COMPUTED_VALUE"""),"Trae Young") -> Trae Young | K19: =IFERROR(__xludf.DUMMYFUNCTION("""COMPUTED_VALUE"""),77.0) -> 77 | L19: =IFERROR(__xludf.DUMMYFUNCTION("""COMPUTED_VALUE"""),"G") -> G | M19: =IFERROR(__xludf.DUMMYFUNCTION("""COMPUTED_VALUE"""),5.693887490632928) -> 5.6938875 | N19: =IFERROR(__xludf.DUMMYFUNCTION("""COMPUTED_VALUE"""),6.324092755769335) -> 6.3240928 | O19: =IFERROR(__xludf.DUMMYFUNCTION("""COMPUTED_VALUE"""),0.6302052651364072) -> 0.63020527 | P19: =IFERROR(__xludf.DUMMYFUNCTION("""COMPUTED_VALUE"""),25.69468) -> 25.69468 | Q19: =IFERROR(__xludf.DUMMYFUNCTION("""COMPUTED_VALUE"""),3.18987) -> 3.18987 | R19: =IFERROR(__xludf.DUMMYFUNCTION("""COMPUTED_VALUE"""),2.885974) -> 2.885974 | S19: =IFERROR(__xludf.DUMMYFUNCTION("""COMPUTED_VALUE"""),11.73519) -> 11.73519 | T19: =IFERROR(__xludf.DUMMYFUNCTION("""COMPUTED_VALUE"""),1.171558) -> 1.171558 | U19: =IFERROR(__xludf.DUMMYFUNCTION("""COMPUTED_VALUE"""),0.077922) -> 0.077922 | V19: =IFERROR(__xludf.DUMMYFUNCTION("""COMPUTED_VALUE"""),0.419483) -> 0.419483 | W19: =IFERROR(__xludf.DUMMYFUNCTION("""COMPUTED_VALUE"""),0.883994) -> 0.883994 | X19: =IFERROR(__xludf.DUMMYFUNCTION("""COMPUTED_VALUE"""),4.29) -> 4.29 | Y19: =IFERROR(__xludf.DUMMYFUNCTION("""COMPUTED_VALUE"""),1.494783635658165) -> 1.4947836 | Z19: =IFERROR(__xludf.DUMMYFUNCTION("""COMPUTED_VALUE"""),1.371789014081673) -> 1.371789 | AA19: =IFERROR(__xludf.DUMMYFUNCTION("""COMPUTED_VALUE"""),-1.3135571258500867) -> -1.3135571 | AB19: =IFERROR(__xludf.DUMMYFUNCTION("""COMPUTED_VALUE"""),3.8584299759654193) -> 3.85843 | AC19: =IFERROR(__xludf.DUMMYFUNCTION("""COMPUTED_VALUE"""),0.38507932768750724) -> 0.38507933 | AD19: =IFERROR(__xludf.DUMMYFUNCTION("""COMPUTED_VALUE"""),-1.1858767858564676) -> -1.1858768 | AE19: =IFERROR(__xludf.DUMMYFUNCTION("""COMPUTED_VALUE"""),-0.9539049358971645) -> -0.95390494 | AF19: =IFERROR(__xludf.DUMMYFUNCTION("""COMPUTED_VALUE"""),1.3537925241302025) -> 1.3537925 | AG19: =IFERROR(__xludf.DUMMYFUNCTION("""COMPUTED_VALUE"""),0.0) -> 0 | AJ19: 100 | AK19: {=if(AK$14=$J6,"-", countif(indirect(address(row($J$2)+ VLOOKUP(AK$14,$J$3:$J$8,1),COLUMN($K$4))):indirect(address(row($J$2)+ VLOOKUP(AK$14,$J$3:$J$8,1),COLUMN($S$2)))>indirect(address(row($J6),COLUMN($K$2))):indirect(address(row($J6),COLUMN($S$2))),TRUE()))} -> 0 | AL19: {=if(AL$14=$J6,"-", countif(indirect(address(row($J$2)+ VLOOKUP(AL$14,$J$3:$J$8,1),COLUMN($K$4))):indirect(address(row($J$2)+ VLOOKUP(AL$14,$J$3:$J$8,1),COLUMN($S$2)))>indirect(address(row($J6),COLUMN($K$2))):indirect(address(row($J6),COLUMN($S$2))),TRUE()))} -> 0 | AM19: {=if(AM$14=$J6,"-", countif(indirect(address(row($J$2)+ VLOOKUP(AM$14,$J$3:$J$8,1),COLUMN($K$4))):indirect(address(row($J$2)+ VLOOKUP(AM$14,$J$3:$J$8,1),COLUMN($S$2)))>indirect(address(row($J6),COLUMN($K$2))):indirect(address(row($J6),COLUMN($S$2))),TRUE()))} -> 0 | AN19: {=if(AN$14=$J6,"-", countif(indirect(address(row($J$2)+ VLOOKUP(AN$14,$J$3:$J$8,1),COLUMN($K$4))):indirect(address(row($J$2)+ VLOOKUP(AN$14,$J$3:$J$8,1),COLUMN($S$2)))>indirect(address(row($J6),COLUMN($K$2))):indirect(address(row($J6),COLUMN($S$2))),TRUE()))} -> 0 | AO19: {=if(AO$14=$J6,"-", countif(indirect(address(row($J$2)+ VLOOKUP(AO$14,$J$3:$J$8,1),COLUMN($K$4))):indirect(address(row($J$2)+ VLOOKUP(AO$14,$J$3:$J$8,1),COLUMN($S$2)))>indirect(address(row($J6),COLUMN($K$2))):indirect(address(row($J6),COLUMN($S$2))),TRUE()))} -> 0 | AP19: {=if(AP$14=$J6,"-", countif(indirect(address(row($J$2)+ VLOOKUP(AP$14,$J$3:$J$8,1),COLUMN($K$4))):indirect(address(row($J$2)+ VLOOKUP(AP$14,$J$3:$J$8,1),COLUMN($S$2)))>indirect(address(row($J6),COLUMN($K$2))):indirect(address(row($J6),COLUMN($S$2))),TRUE()))} -> 0 | AQ19: {=if(AQ$14=$J6,"-", countif(indirect(address(row($J$2)+ VLOOKUP(AQ$14,$J$3:$J$8,1),COLUMN($K$4))):indirect(address(row($J$2)+ VLOOKUP(AQ$14,$J$3:$J$8,1),COLUMN($S$2)))>indirect(address(row($J6),COLUMN($K$2))):indirect(address(row($J6),COLUMN($S$2))),TRUE()))} -> 0 | AR19: {=if(AR$14=$J6,"-", countif(indirect(address(row($J$2)+ VLOOKUP(AR$14,$J$3:$J$8,1),COLUMN($K$4))):indirect(address(row($J$2)+ VLOOKUP(AR$14,$J$3:$J$8,1),COLUMN($S$2)))>indirect(address(row($J6),COLUMN($K$2))):indirect(address(row($J6),COLUMN($S$2))),TRUE()))} -> 0 | ... AV19: {=if(AV$14=$J6,"-", countif(indirect(address(row($J$2)+ VLOOKUP(AV$14,$J$3:$J$8,1),COLUMN($K$4))):indirect(address(row($J$2)+ VLOOKUP(AV$14,$J$3:$J$8,1),COLUMN($S$2)))>indirect(address(row($J6),COLUMN($K$2))):indirect(address(row($J6),COLUMN($S$2))),TRUE()))} -> 0 | AW19: 4 | AX19: {=INDIRECT("Draft!G"&TEXT(15-VLOOKUP(TRUE,I3:J8,2,0),"0"))} -> #N/A | AZ19: =IF($AX19="","", VLOOKUP($AX19,'Final Update'!$Q$21:$AE1009,Column(#REF!),False)) -> #N/A | BA19: =IF($AX19="","", VLOOKUP($AX19,'Final Update'!$Q$21:$AE1009,Column(#REF!),False)) -> #N/A | BB19: =IF($AX19="","", VLOOKUP($AX19,'Final Update'!$Q$21:$AE1009,Column(I4),False)) -> #N/A | BC19: =IF($AX19="","", VLOOKUP($AX19,'Final Update'!$Q$21:$AE1009,Column(J4),False)) -> #N/A | BD19: =IF($AX19="","", VLOOKUP($AX19,'Final Update'!$Q$21:$AE1009,Column(K4),False)) -> #N/A | BE19: =IF($AX19="","", VLOOKUP($AX19,'Final Update'!$Q$21:$AE1009,Column(L4),False)) -> #N/A | BF19: =IF($AX19="","", VLOOKUP($AX19,'Final Update'!$Q$21:$AE1009,Column(M4),False)) -> #N/A | BG19: =IF($AX19="","", VLOOKUP($AX19,'Final Update'!$Q$21:$AE1009,Column(#REF!),False)) -> #N/A | BH19: =IF($AX19="","", VLOOKUP($AX19,'Final Update'!$Q$21:$AE1009,Column(O3),False)) -> #N/A | BI19: =IF($AX19="","", VLOOKUP($AX19,'Final Update'!$Q$21:$AE1009,Column(C4),False)) -> #N/A | BJ19: {=COUNTIF(FIND(BK19,$BI$16:$BI$27),">0")} -> 0 | BK19: PF
A20: =VLOOKUP($F20,UpdateHashtag!$V$3:$Y$32,COLUMN(B$9),0) -> #N/A | B20: =VLOOKUP($F20,UpdateHashtag!$V$3:$Y$32,COLUMN(#REF!),0) -> #REF! | C20: =VLOOKUP($F20,UpdateHashtag!$V$3:$Y$32,COLUMN(#REF!),0) -> #REF! | D20: =SUM(A20:C20) -> #N/A | F20: =VLOOKUP(J20,UpdateBBM!$C$2:E1009,3,0) -> GSW | G20: 7 | H20: =IFERROR(__xludf.DUMMYFUNCTION("""COMPUTED_VALUE"""),7.0) -> 7 | J20: =IFERROR(__xludf.DUMMYFUNCTION("""COMPUTED_VALUE"""),"Stephen Curry") -> Stephen Curry | K20: =IFERROR(__xludf.DUMMYFUNCTION("""COMPUTED_VALUE"""),68.0) -> 68 | L20: =IFERROR(__xludf.DUMMYFUNCTION("""COMPUTED_VALUE"""),"G") -> G | M20: =IFERROR(__xludf.DUMMYFUNCTION("""COMPUTED_VALUE"""),5.645798593164934) -> 5.6457986 | N20: =IFERROR(__xludf.DUMMYFUNCTION("""COMPUTED_VALUE"""),5.903191980581784) -> 5.903192 | O20: =IFERROR(__xludf.DUMMYFUNCTION("""COMPUTED_VALUE"""),0.25739338741685014) -> 0.25739339 | P20: =IFERROR(__xludf.DUMMYFUNCTION("""COMPUTED_VALUE"""),25.34912) -> 25.34912 | Q20: =IFERROR(__xludf.DUMMYFUNCTION("""COMPUTED_VALUE"""),4.625882) -> 4.625882 | R20: =IFERROR(__xludf.DUMMYFUNCTION("""COMPUTED_VALUE"""),4.492059) -> 4.492059 | S20: =IFERROR(__xludf.DUMMYFUNCTION("""COMPUTED_VALUE"""),5.887794) -> 5.887794 | T20: =IFERROR(__xludf.DUMMYFUNCTION("""COMPUTED_VALUE"""),1.020882) -> 1.020882 | U20: =IFERROR(__xludf.DUMMYFUNCTION("""COMPUTED_VALUE"""),0.407647) -> 0.407647 | V20: =IFERROR(__xludf.DUMMYFUNCTION("""COMPUTED_VALUE"""),0.453424) -> 0.453424 | W20: =IFERROR(__xludf.DUMMYFUNCTION("""COMPUTED_VALUE"""),0.920009) -> 0.920009 | X20: =IFERROR(__xludf.DUMMYFUNCTION("""COMPUTED_VALUE"""),2.786618) -> 2.786618 | Y20: =IFERROR(__xludf.DUMMYFUNCTION("""COMPUTED_VALUE"""),1.4341576866752945) -> 1.4341577 | Z20: =IFERROR(__xludf.DUMMYFUNCTION("""COMPUTED_VALUE"""),2.758737423625692) -> 2.7587374 | AA20: =IFERROR(__xludf.DUMMYFUNCTION("""COMPUTED_VALUE"""),-0.662524779140245) -> -0.66252478 | AB20: =IFERROR(__xludf.DUMMYFUNCTION("""COMPUTED_VALUE"""),1.0018922597796107) -> 1.0018923 | AC20: =IFERROR(__xludf.DUMMYFUNCTION("""COMPUTED_VALUE"""),-0.07406510555537915) -> -0.074065106 | AD20: =IFERROR(__xludf.DUMMYFUNCTION("""COMPUTED_VALUE"""),-0.5864392994779517) -> -0.5864393 | AE20: =IFERROR(__xludf.DUMMYFUNCTION("""COMPUTED_VALUE"""),-0.5687843301986628) -> -0.56878433 | AF20: =IFERROR(__xludf.DUMMYFUNCTION("""COMPUTED_VALUE"""),1.9376933457331804) -> 1.9376933 | AG20: =IFERROR(__xludf.DUMMYFUNCTION("""COMPUTED_VALUE"""),0.0) -> 0 | AJ20: 100 | AK20: {=if(AK$14=$F4,"-", countif(indirect(address(row($J$2)+ VLOOKUP(AK$14,$J$3:$J$8,1),COLUMN($K$4))):indirect(address(row($J$2)+ VLOOKUP(AK$14,$J$3:$J$8,1),COLUMN($S$2)))>indirect(address(row($F4),COLUMN($K$2))):indirect(address(row($F4),COLUMN($S$2))),TRUE()))} -> 0 | AL20: {=if(AL$14=$F4,"-", countif(indirect(address(row($J$2)+ VLOOKUP(AL$14,$J$3:$J$8,1),COLUMN($K$4))):indirect(address(row($J$2)+ VLOOKUP(AL$14,$J$3:$J$8,1),COLUMN($S$2)))>indirect(address(row($F4),COLUMN($K$2))):indirect(address(row($F4),COLUMN($S$2))),TRUE()))} -> 0 | AM20: {=if(AM$14=$F4,"-", countif(indirect(address(row($J$2)+ VLOOKUP(AM$14,$J$3:$J$8,1),COLUMN($K$4))):indirect(address(row($J$2)+ VLOOKUP(AM$14,$J$3:$J$8,1),COLUMN($S$2)))>indirect(address(row($F4),COLUMN($K$2))):indirect(address(row($F4),COLUMN($S$2))),TRUE()))} -> 0 | AN20: {=if(AN$14=$F4,"-", countif(indirect(address(row($J$2)+ VLOOKUP(AN$14,$J$3:$J$8,1),COLUMN($K$4))):indirect(address(row($J$2)+ VLOOKUP(AN$14,$J$3:$J$8,1),COLUMN($S$2)))>indirect(address(row($F4),COLUMN($K$2))):indirect(address(row($F4),COLUMN($S$2))),TRUE()))} -> 0 | AO20: {=if(AO$14=$F4,"-", countif(indirect(address(row($J$2)+ VLOOKUP(AO$14,$J$3:$J$8,1),COLUMN($K$4))):indirect(address(row($J$2)+ VLOOKUP(AO$14,$J$3:$J$8,1),COLUMN($S$2)))>indirect(address(row($F4),COLUMN($K$2))):indirect(address(row($F4),COLUMN($S$2))),TRUE()))} -> 0 | AP20: {=if(AP$14=$F4,"-", countif(indirect(address(row($J$2)+ VLOOKUP(AP$14,$J$3:$J$8,1),COLUMN($K$4))):indirect(address(row($J$2)+ VLOOKUP(AP$14,$J$3:$J$8,1),COLUMN($S$2)))>indirect(address(row($F4),COLUMN($K$2))):indirect(address(row($F4),COLUMN($S$2))),TRUE()))} -> 0 | AQ20: {=if(AQ$14=$F4,"-", countif(indirect(address(row($J$2)+ VLOOKUP(AQ$14,$J$3:$J$8,1),COLUMN($K$4))):indirect(address(row($J$2)+ VLOOKUP(AQ$14,$J$3:$J$8,1),COLUMN($S$2)))>indirect(address(row($F4),COLUMN($K$2))):indirect(address(row($F4),COLUMN($S$2))),TRUE()))} -> 0 | AR20: {=if(AR$14=$F4,"-", countif(indirect(address(row($J$2)+ VLOOKUP(AR$14,$J$3:$J$8,1),COLUMN($K$4))):indirect(address(row($J$2)+ VLOOKUP(AR$14,$J$3:$J$8,1),COLUMN($S$2)))>indirect(address(row($F4),COLUMN($K$2))):indirect(address(row($F4),COLUMN($S$2))),TRUE()))} -> 0 | ... AV20: {=if(AV$14=$F4,"-", countif(indirect(address(row($J$2)+ VLOOKUP(AV$14,$J$3:$J$8,1),COLUMN($K$4))):indirect(address(row($J$2)+ VLOOKUP(AV$14,$J$3:$J$8,1),COLUMN($S$2)))>indirect(address(row($F4),COLUMN($K$2))):indirect(address(row($F4),COLUMN($S$2))),TRUE()))} -> 0 | AW20: 5 | AX20: {=INDIRECT("Draft!H"&TEXT(VLOOKUP(TRUE,I3:J8,2,0)+2,"0"))} -> #N/A | AZ20: =IF($AX20="","", VLOOKUP($AX20,'Final Update'!$Q$21:$AE1009,Column(F6),False)) -> #N/A | BA20: =IF($AX20="","", VLOOKUP($AX20,'Final Update'!$Q$21:$AE1009,Column(#REF!),False)) -> #N/A | BB20: =IF($AX20="","", VLOOKUP($AX20,'Final Update'!$Q$21:$AE1009,Column(I5),False)) -> #N/A | BC20: =IF($AX20="","", VLOOKUP($AX20,'Final Update'!$Q$21:$AE1009,Column(J5),False)) -> #N/A | BD20: =IF($AX20="","", VLOOKUP($AX20,'Final Update'!$Q$21:$AE1009,Column(K5),False)) -> #N/A | BE20: =IF($AX20="","", VLOOKUP($AX20,'Final Update'!$Q$21:$AE1009,Column(L5),False)) -> #N/A | BF20: =IF($AX20="","", VLOOKUP($AX20,'Final Update'!$Q$21:$AE1009,Column(M5),False)) -> #N/A | BG20: =IF($AX20="","", VLOOKUP($AX20,'Final Update'!$Q$21:$AE1009,Column(#REF!),False)) -> #N/A | BH20: =IF($AX20="","", VLOOKUP($AX20,'Final Update'!$Q$21:$AE1009,Column(G5),False)) -> #N/A | BI20: =IF($AX20="","", VLOOKUP($AX20,'Final Update'!$Q$21:$AE1009,Column(C5),False)) -> #N/A | BJ20: {=COUNTIF(FIND(BK20,$BI$16:$BI$27),">0")} -> 0 | BK20: C
A21: =VLOOKUP($F21,UpdateHashtag!$V$3:$Y$32,COLUMN(B$9),0) -> 4 | B21: =VLOOKUP($F21,UpdateHashtag!$V$3:$Y$32,COLUMN(#REF!),0) -> #REF! | C21: =VLOOKUP($F21,UpdateHashtag!$V$3:$Y$32,COLUMN(#REF!),0) -> #REF! | D21: =SUM(A21:C21) -> #REF! | F21: =VLOOKUP(J21,UpdateBBM!$C$2:E1009,3,0) -> LAC | G21: 8 | H21: =IFERROR(__xludf.DUMMYFUNCTION("""COMPUTED_VALUE"""),8.0) -> 8 | J21: =IFERROR(__xludf.DUMMYFUNCTION("""COMPUTED_VALUE"""),"James Harden") -> James Harden | K21: =IFERROR(__xludf.DUMMYFUNCTION("""COMPUTED_VALUE"""),73.0) -> 73 | L21: =IFERROR(__xludf.DUMMYFUNCTION("""COMPUTED_VALUE"""),"G") -> G | M21: =IFERROR(__xludf.DUMMYFUNCTION("""COMPUTED_VALUE"""),5.187333301395962) -> 5.1873333 | N21: =IFERROR(__xludf.DUMMYFUNCTION("""COMPUTED_VALUE"""),5.630668653098455) -> 5.6306687 | O21: =IFERROR(__xludf.DUMMYFUNCTION("""COMPUTED_VALUE"""),0.44333535170249316) -> 0.44333535 | P21: =IFERROR(__xludf.DUMMYFUNCTION("""COMPUTED_VALUE"""),23.15562) -> 23.15562 | Q21: =IFERROR(__xludf.DUMMYFUNCTION("""COMPUTED_VALUE"""),3.018356) -> 3.018356 | R21: =IFERROR(__xludf.DUMMYFUNCTION("""COMPUTED_VALUE"""),5.304658) -> 5.304658 | S21: =IFERROR(__xludf.DUMMYFUNCTION("""COMPUTED_VALUE"""),8.091781) -> 8.091781 | T21: =IFERROR(__xludf.DUMMYFUNCTION("""COMPUTED_VALUE"""),1.202329) -> 1.202329 | U21: =IFERROR(__xludf.DUMMYFUNCTION("""COMPUTED_VALUE"""),0.712192) -> 0.712192 | V21: =IFERROR(__xludf.DUMMYFUNCTION("""COMPUTED_VALUE"""),0.443798) -> 0.443798 | W21: =IFERROR(__xludf.DUMMYFUNCTION("""COMPUTED_VALUE"""),0.872994) -> 0.872994 | X21: =IFERROR(__xludf.DUMMYFUNCTION("""COMPUTED_VALUE"""),3.536438) -> 3.536438 | Y21: =IFERROR(__xludf.DUMMYFUNCTION("""COMPUTED_VALUE"""),1.0493243173792963) -> 1.0493243 | Z21: =IFERROR(__xludf.DUMMYFUNCTION("""COMPUTED_VALUE"""),1.206135057489017) -> 1.2061351 | AA21: =IFERROR(__xludf.DUMMYFUNCTION("""COMPUTED_VALUE"""),-0.3331348440471021) -> -0.33313484 | AB21: =IFERROR(__xludf.DUMMYFUNCTION("""COMPUTED_VALUE"""),2.07857186066233) -> 2.0785719 | AC21: =IFERROR(__xludf.DUMMYFUNCTION("""COMPUTED_VALUE"""),0.47884564319440154) -> 0.47884564 | AD21: =IFERROR(__xludf.DUMMYFUNCTION("""COMPUTED_VALUE"""),-0.032778857324201646) -> -0.032778857 | AE21: =IFERROR(__xludf.DUMMYFUNCTION("""COMPUTED_VALUE"""),-0.6850393076828555) -> -0.68503931 | AF21: =IFERROR(__xludf.DUMMYFUNCTION("""COMPUTED_VALUE"""),1.1837054757447134) -> 1.1837055 | AG21: =IFERROR(__xludf.DUMMYFUNCTION("""COMPUTED_VALUE"""),0.0) -> 0 | AJ21: 100 | AK21: {=if(AK$14=#REF!,"-", countif(indirect(address(row($J$2)+ VLOOKUP(AK$14,$J$3:$J$8,1),COLUMN($K$4))):indirect(address(row($J$2)+ VLOOKUP(AK$14,$J$3:$J$8,1),COLUMN($S$2)))>indirect(address(row(#REF!),COLUMN($K$2))):indirect(address(row(#REF!),COLUMN($S$2))),TRUE()))} -> #REF! | AL21: {=if(AL$14=#REF!,"-", countif(indirect(address(row($J$2)+ VLOOKUP(AL$14,$J$3:$J$8,1),COLUMN($K$4))):indirect(address(row($J$2)+ VLOOKUP(AL$14,$J$3:$J$8,1),COLUMN($S$2)))>indirect(address(row(#REF!),COLUMN($K$2))):indirect(address(row(#REF!),COLUMN($S$2))),TRUE()))} -> #REF! | AM21: {=if(AM$14=#REF!,"-", countif(indirect(address(row($J$2)+ VLOOKUP(AM$14,$J$3:$J$8,1),COLUMN($K$4))):indirect(address(row($J$2)+ VLOOKUP(AM$14,$J$3:$J$8,1),COLUMN($S$2)))>indirect(address(row(#REF!),COLUMN($K$2))):indirect(address(row(#REF!),COLUMN($S$2))),TRUE()))} -> #REF! | AN21: {=if(AN$14=#REF!,"-", countif(indirect(address(row($J$2)+ VLOOKUP(AN$14,$J$3:$J$8,1),COLUMN($K$4))):indirect(address(row($J$2)+ VLOOKUP(AN$14,$J$3:$J$8,1),COLUMN($S$2)))>indirect(address(row(#REF!),COLUMN($K$2))):indirect(address(row(#REF!),COLUMN($S$2))),TRUE()))} -> #REF! | AO21: {=if(AO$14=#REF!,"-", countif(indirect(address(row($J$2)+ VLOOKUP(AO$14,$J$3:$J$8,1),COLUMN($K$4))):indirect(address(row($J$2)+ VLOOKUP(AO$14,$J$3:$J$8,1),COLUMN($S$2)))>indirect(address(row(#REF!),COLUMN($K$2))):indirect(address(row(#REF!),COLUMN($S$2))),TRUE()))} -> #REF! | AP21: {=if(AP$14=#REF!,"-", countif(indirect(address(row($J$2)+ VLOOKUP(AP$14,$J$3:$J$8,1),COLUMN($K$4))):indirect(address(row($J$2)+ VLOOKUP(AP$14,$J$3:$J$8,1),COLUMN($S$2)))>indirect(address(row(#REF!),COLUMN($K$2))):indirect(address(row(#REF!),COLUMN($S$2))),TRUE()))} -> #REF! | AQ21: {=if(AQ$14=#REF!,"-", countif(indirect(address(row($J$2)+ VLOOKUP(AQ$14,$J$3:$J$8,1),COLUMN($K$4))):indirect(address(row($J$2)+ VLOOKUP(AQ$14,$J$3:$J$8,1),COLUMN($S$2)))>indirect(address(row(#REF!),COLUMN($K$2))):indirect(address(row(#REF!),COLUMN($S$2))),TRUE()))} -> #REF! | AR21: {=if(AR$14=#REF!,"-", countif(indirect(address(row($J$2)+ VLOOKUP(AR$14,$J$3:$J$8,1),COLUMN($K$4))):indirect(address(row($J$2)+ VLOOKUP(AR$14,$J$3:$J$8,1),COLUMN($S$2)))>indirect(address(row(#REF!),COLUMN($K$2))):indirect(address(row(#REF!),COLUMN($S$2))),TRUE()))} -> #REF! | ... AV21: {=if(AV$14=#REF!,"-", countif(indirect(address(row($J$2)+ VLOOKUP(AV$14,$J$3:$J$8,1),COLUMN($K$4))):indirect(address(row($J$2)+ VLOOKUP(AV$14,$J$3:$J$8,1),COLUMN($S$2)))>indirect(address(row(#REF!),COLUMN($K$2))):indirect(address(row(#REF!),COLUMN($S$2))),TRUE()))} -> #REF! | AW21: 6 | AX21: {=INDIRECT("Draft!I"&TEXT(15-VLOOKUP(TRUE,I3:J8,2,0),"0"))} -> #N/A | AZ21: =IF($AX21="","", VLOOKUP($AX21,'Final Update'!$Q$21:$AE1009,Column(#REF!),False)) -> #N/A | BA21: =IF($AX21="","", VLOOKUP($AX21,'Final Update'!$Q$21:$AE1009,Column(#REF!),False)) -> #N/A | BB21: =IF($AX21="","", VLOOKUP($AX21,'Final Update'!$Q$21:$AE1009,Column(I6),False)) -> #N/A | BC21: =IF($AX21="","", VLOOKUP($AX21,'Final Update'!$Q$21:$AE1009,Column(J6),False)) -> #N/A | BD21: =IF($AX21="","", VLOOKUP($AX21,'Final Update'!$Q$21:$AE1009,Column(K6),False)) -> #N/A | BE21: =IF($AX21="","", VLOOKUP($AX21,'Final Update'!$Q$21:$AE1009,Column(L6),False)) -> #N/A | BF21: =IF($AX21="","", VLOOKUP($AX21,'Final Update'!$Q$21:$AE1009,Column(M6),False)) -> #N/A | BG21: =IF($AX21="","", VLOOKUP($AX21,'Final Update'!$Q$21:$AE1009,Column(#REF!),False)) -> #N/A | BH21: =IF($AX21="","", VLOOKUP($AX21,'Final Update'!$Q$21:$AE1009,Column(G6),False)) -> #N/A | BI21: =IF($AX21="","", VLOOKUP($AX21,'Final Update'!$Q$21:$AE1009,Column(C6),False)) -> #N/A
A22: =VLOOKUP($F22,UpdateHashtag!$V$3:$Y$32,COLUMN(B$9),0) -> 4 | B22: =VLOOKUP($F22,UpdateHashtag!$V$3:$Y$32,COLUMN(#REF!),0) -> #REF! | C22: =VLOOKUP($F22,UpdateHashtag!$V$3:$Y$32,COLUMN(#REF!),0) -> #REF! | D22: =SUM(A22:C22) -> #REF! | F22: =VLOOKUP(J22,UpdateBBM!$C$2:E1009,3,0) -> DAL | G22: 9 | H22: =IFERROR(__xludf.DUMMYFUNCTION("""COMPUTED_VALUE"""),9.0) -> 9 | J22: =IFERROR(__xludf.DUMMYFUNCTION("""COMPUTED_VALUE"""),"Anthony Davis") -> Anthony Davis | K22: =IFERROR(__xludf.DUMMYFUNCTION("""COMPUTED_VALUE"""),62.0) -> 62 | L22: =IFERROR(__xludf.DUMMYFUNCTION("""COMPUTED_VALUE"""),"F,C") -> F,C | M22: =IFERROR(__xludf.DUMMYFUNCTION("""COMPUTED_VALUE"""),5.142238350012554) -> 5.1422384 | N22: =IFERROR(__xludf.DUMMYFUNCTION("""COMPUTED_VALUE"""),5.400510338132858) -> 5.4005103 | O22: =IFERROR(__xludf.DUMMYFUNCTION("""COMPUTED_VALUE"""),0.2582719881203044) -> 0.25827199 | P22: =IFERROR(__xludf.DUMMYFUNCTION("""COMPUTED_VALUE"""),22.60968) -> 22.60968 | Q22: =IFERROR(__xludf.DUMMYFUNCTION("""COMPUTED_VALUE"""),0.879677) -> 0.879677 | R22: =IFERROR(__xludf.DUMMYFUNCTION("""COMPUTED_VALUE"""),10.01581) -> 10.01581 | S22: =IFERROR(__xludf.DUMMYFUNCTION("""COMPUTED_VALUE"""),4.149355) -> 4.149355 | T22: =IFERROR(__xludf.DUMMYFUNCTION("""COMPUTED_VALUE"""),1.227258) -> 1.227258 | U22: =IFERROR(__xludf.DUMMYFUNCTION("""COMPUTED_VALUE"""),2.074677) -> 2.074677 | V22: =IFERROR(__xludf.DUMMYFUNCTION("""COMPUTED_VALUE"""),0.494364) -> 0.494364 | W22: =IFERROR(__xludf.DUMMYFUNCTION("""COMPUTED_VALUE"""),0.766012) -> 0.766012 | X22: =IFERROR(__xludf.DUMMYFUNCTION("""COMPUTED_VALUE"""),2.790161) -> 2.790161 | Y22: =IFERROR(__xludf.DUMMYFUNCTION("""COMPUTED_VALUE"""),0.9535431778153772) -> 0.95354318 | Z22: =IFERROR(__xludf.DUMMYFUNCTION("""COMPUTED_VALUE"""),-0.8594726376940267) -> -0.85947264 | AA22: =IFERROR(__xludf.DUMMYFUNCTION("""COMPUTED_VALUE"""),1.576547608791175) -> 1.5765476 | AB22: =IFERROR(__xludf.DUMMYFUNCTION("""COMPUTED_VALUE"""),0.15263960598493978) -> 0.15263961 | AC22: =IFERROR(__xludf.DUMMYFUNCTION("""COMPUTED_VALUE"""),0.5548100408178579) -> 0.55481004 | AD22: =IFERROR(__xludf.DUMMYFUNCTION("""COMPUTED_VALUE"""),2.4442082793152173) -> 2.4442083 | AE22: =IFERROR(__xludf.DUMMYFUNCTION("""COMPUTED_VALUE"""),-0.012156836884575905) -> -0.012156837 | AF22: =IFERROR(__xludf.DUMMYFUNCTION("""COMPUTED_VALUE"""),-0.2690815377071333) -> -0.26908154 | AG22: =IFERROR(__xludf.DUMMYFUNCTION("""COMPUTED_VALUE"""),0.0) -> 0 | AJ22: 100 | AK22: {=if(AK$14=#REF!,"-", countif(indirect(address(row($J$2)+ VLOOKUP(AK$14,$J$3:$J$8,1),COLUMN($K$4))):indirect(address(row($J$2)+ VLOOKUP(AK$14,$J$3:$J$8,1),COLUMN($S$2)))>indirect(address(row(#REF!),COLUMN($K$2))):indirect(address(row(#REF!),COLUMN($S$2))),TRUE()))} -> #REF! | AL22: {=if(AL$14=#REF!,"-", countif(indirect(address(row($J$2)+ VLOOKUP(AL$14,$J$3:$J$8,1),COLUMN($K$4))):indirect(address(row($J$2)+ VLOOKUP(AL$14,$J$3:$J$8,1),COLUMN($S$2)))>indirect(address(row(#REF!),COLUMN($K$2))):indirect(address(row(#REF!),COLUMN($S$2))),TRUE()))} -> #REF! | AM22: {=if(AM$14=#REF!,"-", countif(indirect(address(row($J$2)+ VLOOKUP(AM$14,$J$3:$J$8,1),COLUMN($K$4))):indirect(address(row($J$2)+ VLOOKUP(AM$14,$J$3:$J$8,1),COLUMN($S$2)))>indirect(address(row(#REF!),COLUMN($K$2))):indirect(address(row(#REF!),COLUMN($S$2))),TRUE()))} -> #REF! | AN22: {=if(AN$14=#REF!,"-", countif(indirect(address(row($J$2)+ VLOOKUP(AN$14,$J$3:$J$8,1),COLUMN($K$4))):indirect(address(row($J$2)+ VLOOKUP(AN$14,$J$3:$J$8,1),COLUMN($S$2)))>indirect(address(row(#REF!),COLUMN($K$2))):indirect(address(row(#REF!),COLUMN($S$2))),TRUE()))} -> #REF! | AO22: {=if(AO$14=#REF!,"-", countif(indirect(address(row($J$2)+ VLOOKUP(AO$14,$J$3:$J$8,1),COLUMN($K$4))):indirect(address(row($J$2)+ VLOOKUP(AO$14,$J$3:$J$8,1),COLUMN($S$2)))>indirect(address(row(#REF!),COLUMN($K$2))):indirect(address(row(#REF!),COLUMN($S$2))),TRUE()))} -> #REF! | AP22: {=if(AP$14=#REF!,"-", countif(indirect(address(row($J$2)+ VLOOKUP(AP$14,$J$3:$J$8,1),COLUMN($K$4))):indirect(address(row($J$2)+ VLOOKUP(AP$14,$J$3:$J$8,1),COLUMN($S$2)))>indirect(address(row(#REF!),COLUMN($K$2))):indirect(address(row(#REF!),COLUMN($S$2))),TRUE()))} -> #REF! | AQ22: {=if(AQ$14=#REF!,"-", countif(indirect(address(row($J$2)+ VLOOKUP(AQ$14,$J$3:$J$8,1),COLUMN($K$4))):indirect(address(row($J$2)+ VLOOKUP(AQ$14,$J$3:$J$8,1),COLUMN($S$2)))>indirect(address(row(#REF!),COLUMN($K$2))):indirect(address(row(#REF!),COLUMN($S$2))),TRUE()))} -> #REF! | AR22: {=if(AR$14=#REF!,"-", countif(indirect(address(row($J$2)+ VLOOKUP(AR$14,$J$3:$J$8,1),COLUMN($K$4))):indirect(address(row($J$2)+ VLOOKUP(AR$14,$J$3:$J$8,1),COLUMN($S$2)))>indirect(address(row(#REF!),COLUMN($K$2))):indirect(address(row(#REF!),COLUMN($S$2))),TRUE()))} -> #REF! | ... AV22: {=if(AV$14=#REF!,"-", countif(indirect(address(row($J$2)+ VLOOKUP(AV$14,$J$3:$J$8,1),COLUMN($K$4))):indirect(address(row($J$2)+ VLOOKUP(AV$14,$J$3:$J$8,1),COLUMN($S$2)))>indirect(address(row(#REF!),COLUMN($K$2))):indirect(address(row(#REF!),COLUMN($S$2))),TRUE()))} -> #REF! | AW22: 7 | AX22: {=INDIRECT("Draft!J"&TEXT(VLOOKUP(TRUE,I3:J8,2,0)+2,"0"))} -> #N/A | AZ22: =IF($AX22="","", VLOOKUP($AX22,'Final Update'!$Q$21:$AE1009,Column(G7),False)) -> #N/A | BA22: =IF($AX22="","", VLOOKUP($AX22,'Final Update'!$Q$21:$AE1009,Column(H7),False)) -> #N/A | BB22: =IF($AX22="","", VLOOKUP($AX22,'Final Update'!$Q$21:$AE1009,Column(I7),False)) -> #N/A | BC22: =IF($AX22="","", VLOOKUP($AX22,'Final Update'!$Q$21:$AE1009,Column(F4),False)) -> #N/A | BD22: =IF($AX22="","", VLOOKUP($AX22,'Final Update'!$Q$21:$AE1009,Column(K7),False)) -> #N/A | BE22: =IF($AX22="","", VLOOKUP($AX22,'Final Update'!$Q$21:$AE1009,Column(L7),False)) -> #N/A | BF22: =IF($AX22="","", VLOOKUP($AX22,'Final Update'!$Q$21:$AE1009,Column(M7),False)) -> #N/A | BG22: =IF($AX22="","", VLOOKUP($AX22,'Final Update'!$Q$21:$AE1009,Column(N7),False)) -> #N/A | BH22: =IF($AX22="","", VLOOKUP($AX22,'Final Update'!$Q$21:$AE1009,Column(O7),False)) -> #N/A | BI22: =IF($AX22="","", VLOOKUP($AX22,'Final Update'!$Q$21:$AE1009,Column(C7),False)) -> #N/A
A23: =VLOOKUP($F23,UpdateHashtag!$V$3:$Y$32,COLUMN(B$9),0) -> 4 | B23: =VLOOKUP($F23,UpdateHashtag!$V$3:$Y$32,COLUMN(#REF!),0) -> #REF! | C23: =VLOOKUP($F23,UpdateHashtag!$V$3:$Y$32,COLUMN(#REF!),0) -> #REF! | D23: =SUM(A23:C23) -> #REF! | F23: =VLOOKUP(J23,UpdateBBM!$C$2:E1009,3,0) -> CHA | G23: 10 | H23: =IFERROR(__xludf.DUMMYFUNCTION("""COMPUTED_VALUE"""),10.0) -> 10 | J23: =IFERROR(__xludf.DUMMYFUNCTION("""COMPUTED_VALUE"""),"LaMelo Ball") -> LaMelo Ball | K23: =IFERROR(__xludf.DUMMYFUNCTION("""COMPUTED_VALUE"""),59.0) -> 59 | L23: =IFERROR(__xludf.DUMMYFUNCTION("""COMPUTED_VALUE"""),"G") -> G | M23: =IFERROR(__xludf.DUMMYFUNCTION("""COMPUTED_VALUE"""),4.884388546694007) -> 4.8843885 | N23: =IFERROR(__xludf.DUMMYFUNCTION("""COMPUTED_VALUE"""),5.331128941088887) -> 5.3311289 | O23: =IFERROR(__xludf.DUMMYFUNCTION("""COMPUTED_VALUE"""),0.44674039439488045) -> 0.44674039 | P23: =IFERROR(__xludf.DUMMYFUNCTION("""COMPUTED_VALUE"""),23.88695) -> 23.88695 | Q23: =IFERROR(__xludf.DUMMYFUNCTION("""COMPUTED_VALUE"""),3.725254) -> 3.725254 | R23: =IFERROR(__xludf.DUMMYFUNCTION("""COMPUTED_VALUE"""),4.95) -> 4.95 | S23: =IFERROR(__xludf.DUMMYFUNCTION("""COMPUTED_VALUE"""),8.13678) -> 8.13678 | T23: =IFERROR(__xludf.DUMMYFUNCTION("""COMPUTED_VALUE"""),1.252542) -> 1.252542 | U23: =IFERROR(__xludf.DUMMYFUNCTION("""COMPUTED_VALUE"""),0.272712) -> 0.272712 | V23: =IFERROR(__xludf.DUMMYFUNCTION("""COMPUTED_VALUE"""),0.416645) -> 0.416645 | W23: =IFERROR(__xludf.DUMMYFUNCTION("""COMPUTED_VALUE"""),0.850015) -> 0.850015 | X23: =IFERROR(__xludf.DUMMYFUNCTION("""COMPUTED_VALUE"""),3.550169) -> 3.550169 | Y23: =IFERROR(__xludf.DUMMYFUNCTION("""COMPUTED_VALUE"""),1.1776307627712463) -> 1.1776308 | Z23: =IFERROR(__xludf.DUMMYFUNCTION("""COMPUTED_VALUE"""),1.8888807844118063) -> 1.8888808 | AA23: =IFERROR(__xludf.DUMMYFUNCTION("""COMPUTED_VALUE"""),-0.47689674333600574) -> -0.47689674 | AB23: =IFERROR(__xludf.DUMMYFUNCTION("""COMPUTED_VALUE"""),2.100554524516573) -> 2.1005545 | AC23: =IFERROR(__xludf.DUMMYFUNCTION("""COMPUTED_VALUE"""),0.6318562051048922) -> 0.63185621 | AD23: =IFERROR(__xludf.DUMMYFUNCTION("""COMPUTED_VALUE"""),-0.8317500803543943) -> -0.83175008 | AE23: =IFERROR(__xludf.DUMMYFUNCTION("""COMPUTED_VALUE"""),-0.9829715408115209) -> -0.98297154 | AF23: =IFERROR(__xludf.DUMMYFUNCTION("""COMPUTED_VALUE"""),0.8408534879747702) -> 0.84085349 | AG23: =IFERROR(__xludf.DUMMYFUNCTION("""COMPUTED_VALUE"""),0.0) -> 0 | AJ23: 100 | AK23: {=if(AK$14=#REF!,"-", countif(indirect(address(row($J$2)+ VLOOKUP(AK$14,$J$3:$J$8,1),COLUMN($K$4))):indirect(address(row($J$2)+ VLOOKUP(AK$14,$J$3:$J$8,1),COLUMN($S$2)))>indirect(address(row(#REF!),COLUMN($K$2))):indirect(address(row(#REF!),COLUMN($S$2))),TRUE()))} -> #REF! | AL23: {=if(AL$14=#REF!,"-", countif(indirect(address(row($J$2)+ VLOOKUP(AL$14,$J$3:$J$8,1),COLUMN($K$4))):indirect(address(row($J$2)+ VLOOKUP(AL$14,$J$3:$J$8,1),COLUMN($S$2)))>indirect(address(row(#REF!),COLUMN($K$2))):indirect(address(row(#REF!),COLUMN($S$2))),TRUE()))} -> #REF! | AM23: {=if(AM$14=#REF!,"-", countif(indirect(address(row($J$2)+ VLOOKUP(AM$14,$J$3:$J$8,1),COLUMN($K$4))):indirect(address(row($J$2)+ VLOOKUP(AM$14,$J$3:$J$8,1),COLUMN($S$2)))>indirect(address(row(#REF!),COLUMN($K$2))):indirect(address(row(#REF!),COLUMN($S$2))),TRUE()))} -> #REF! | AN23: {=if(AN$14=#REF!,"-", countif(indirect(address(row($J$2)+ VLOOKUP(AN$14,$J$3:$J$8,1),COLUMN($K$4))):indirect(address(row($J$2)+ VLOOKUP(AN$14,$J$3:$J$8,1),COLUMN($S$2)))>indirect(address(row(#REF!),COLUMN($K$2))):indirect(address(row(#REF!),COLUMN($S$2))),TRUE()))} -> #REF! | AO23: {=if(AO$14=#REF!,"-", countif(indirect(address(row($J$2)+ VLOOKUP(AO$14,$J$3:$J$8,1),COLUMN($K$4))):indirect(address(row($J$2)+ VLOOKUP(AO$14,$J$3:$J$8,1),COLUMN($S$2)))>indirect(address(row(#REF!),COLUMN($K$2))):indirect(address(row(#REF!),COLUMN($S$2))),TRUE()))} -> #REF! | AP23: {=if(AP$14=#REF!,"-", countif(indirect(address(row($J$2)+ VLOOKUP(AP$14,$J$3:$J$8,1),COLUMN($K$4))):indirect(address(row($J$2)+ VLOOKUP(AP$14,$J$3:$J$8,1),COLUMN($S$2)))>indirect(address(row(#REF!),COLUMN($K$2))):indirect(address(row(#REF!),COLUMN($S$2))),TRUE()))} -> #REF! | AQ23: {=if(AQ$14=#REF!,"-", countif(indirect(address(row($J$2)+ VLOOKUP(AQ$14,$J$3:$J$8,1),COLUMN($K$4))):indirect(address(row($J$2)+ VLOOKUP(AQ$14,$J$3:$J$8,1),COLUMN($S$2)))>indirect(address(row(#REF!),COLUMN($K$2))):indirect(address(row(#REF!),COLUMN($S$2))),TRUE()))} -> #REF! | AR23: {=if(AR$14=#REF!,"-", countif(indirect(address(row($J$2)+ VLOOKUP(AR$14,$J$3:$J$8,1),COLUMN($K$4))):indirect(address(row($J$2)+ VLOOKUP(AR$14,$J$3:$J$8,1),COLUMN($S$2)))>indirect(address(row(#REF!),COLUMN($K$2))):indirect(address(row(#REF!),COLUMN($S$2))),TRUE()))} -> #REF! | ... AV23: {=if(AV$14=#REF!,"-", countif(indirect(address(row($J$2)+ VLOOKUP(AV$14,$J$3:$J$8,1),COLUMN($K$4))):indirect(address(row($J$2)+ VLOOKUP(AV$14,$J$3:$J$8,1),COLUMN($S$2)))>indirect(address(row(#REF!),COLUMN($K$2))):indirect(address(row(#REF!),COLUMN($S$2))),TRUE()))} -> #REF! | AW23: 8 | AX23: {=INDIRECT("Draft!K"&TEXT(15-VLOOKUP(TRUE,I3:J8,2,0),"0"))} -> #N/A | AZ23: =IF($AX23="","", VLOOKUP($AX23,'Final Update'!$Q$21:$AE1009,Column(#REF!),False)) -> #N/A | BA23: =IF($AX23="","", VLOOKUP($AX23,'Final Update'!$Q$21:$AE1009,Column(#REF!),False)) -> #N/A | BB23: =IF($AX23="","", VLOOKUP($AX23,'Final Update'!$Q$21:$AE1009,Column(#REF!),False)) -> #N/A | BC23: =IF($AX23="","", VLOOKUP($AX23,'Final Update'!$Q$21:$AE1009,Column(#REF!),False)) -> #N/A | BD23: =IF($AX23="","", VLOOKUP($AX23,'Final Update'!$Q$21:$AE1009,Column(#REF!),False)) -> #N/A | BE23: =IF($AX23="","", VLOOKUP($AX23,'Final Update'!$Q$21:$AE1009,Column(#REF!),False)) -> #N/A | BF23: =IF($AX23="","", VLOOKUP($AX23,'Final Update'!$Q$21:$AE1009,Column(#REF!),False)) -> #N/A | BG23: =IF($AX23="","", VLOOKUP($AX23,'Final Update'!$Q$21:$AE1009,Column(#REF!),False)) -> #N/A | ... BI23: =IF($AX23="","", VLOOKUP($AX23,'Final Update'!$Q$21:$AE1009,Column(#REF!),False)) -> #N/A
A24: =VLOOKUP($F24,UpdateHashtag!$V$3:$Y$32,COLUMN(B$9),0) -> 4 | B24: =VLOOKUP($F24,UpdateHashtag!$V$3:$Y$32,COLUMN(#REF!),0) -> #REF! | C24: =VLOOKUP($F24,UpdateHashtag!$V$3:$Y$32,COLUMN(#REF!),0) -> #REF! | D24: =SUM(A24:C24) -> #REF! | F24: =VLOOKUP(J24,UpdateBBM!$C$2:E1009,3,0) -> UTA | G24: 11 | H24: =IFERROR(__xludf.DUMMYFUNCTION("""COMPUTED_VALUE"""),11.0) -> 11 | J24: =IFERROR(__xludf.DUMMYFUNCTION("""COMPUTED_VALUE"""),"Walker Kessler") -> Walker Kessler | K24: =IFERROR(__xludf.DUMMYFUNCTION("""COMPUTED_VALUE"""),63.0) -> 63 | L24: =IFERROR(__xludf.DUMMYFUNCTION("""COMPUTED_VALUE"""),"C") -> C | M24: =IFERROR(__xludf.DUMMYFUNCTION("""COMPUTED_VALUE"""),4.731795949516306) -> 4.731796 | N24: =IFERROR(__xludf.DUMMYFUNCTION("""COMPUTED_VALUE"""),4.692685529793366) -> 4.6926855 | O24: =IFERROR(__xludf.DUMMYFUNCTION("""COMPUTED_VALUE"""),-0.039110419722940826) -> -0.03911042 | P24: =IFERROR(__xludf.DUMMYFUNCTION("""COMPUTED_VALUE"""),13.72825) -> 13.72825 | Q24: =IFERROR(__xludf.DUMMYFUNCTION("""COMPUTED_VALUE"""),0.132698) -> 0.132698 | R24: =IFERROR(__xludf.DUMMYFUNCTION("""COMPUTED_VALUE"""),11.97381) -> 11.97381 | S24: =IFERROR(__xludf.DUMMYFUNCTION("""COMPUTED_VALUE"""),1.995556) -> 1.995556 | T24: =IFERROR(__xludf.DUMMYFUNCTION("""COMPUTED_VALUE"""),0.669365) -> 0.669365 | U24: =IFERROR(__xludf.DUMMYFUNCTION("""COMPUTED_VALUE"""),2.252381) -> 2.252381 | V24: =IFERROR(__xludf.DUMMYFUNCTION("""COMPUTED_VALUE"""),0.680393) -> 0.680393 | W24: =IFERROR(__xludf.DUMMYFUNCTION("""COMPUTED_VALUE"""),0.528016) -> 0.528016 | X24: =IFERROR(__xludf.DUMMYFUNCTION("""COMPUTED_VALUE"""),1.590952) -> 1.590952 | Y24: =IFERROR(__xludf.DUMMYFUNCTION("""COMPUTED_VALUE"""),-0.6046380991696051) -> -0.6046381 | Z24: =IFERROR(__xludf.DUMMYFUNCTION("""COMPUTED_VALUE"""),-1.5809299347171588) -> -1.5809299 | AA24: =IFERROR(__xludf.DUMMYFUNCTION("""COMPUTED_VALUE"""),2.3702299698479496) -> 2.37023 | AB24: =IFERROR(__xludf.DUMMYFUNCTION("""COMPUTED_VALUE"""),-0.8995224293181727) -> -0.89952243 | AC24: =IFERROR(__xludf.DUMMYFUNCTION("""COMPUTED_VALUE"""),-1.1452182669098065) -> -1.1452183 | AD24: =IFERROR(__xludf.DUMMYFUNCTION("""COMPUTED_VALUE"""),2.767272769661439) -> 2.7672728 | AE24: =IFERROR(__xludf.DUMMYFUNCTION("""COMPUTED_VALUE"""),3.78549152039872) -> 3.7854915 | AF24: =IFERROR(__xludf.DUMMYFUNCTION("""COMPUTED_VALUE"""),-2.190819465438121) -> -2.1908195 | AG24: =IFERROR(__xludf.DUMMYFUNCTION("""COMPUTED_VALUE"""),0.0) -> 0 | AJ24: 100 | AK24: {=if(AK$14=#REF!,"-", countif(indirect(address(row($J$2)+ VLOOKUP(AK$14,$J$3:$J$8,1),COLUMN($K$4))):indirect(address(row($J$2)+ VLOOKUP(AK$14,$J$3:$J$8,1),COLUMN($S$2)))>indirect(address(row(#REF!),COLUMN($K$2))):indirect(address(row(#REF!),COLUMN($S$2))),TRUE()))} -> #REF! | AL24: {=if(AL$14=#REF!,"-", countif(indirect(address(row($J$2)+ VLOOKUP(AL$14,$J$3:$J$8,1),COLUMN($K$4))):indirect(address(row($J$2)+ VLOOKUP(AL$14,$J$3:$J$8,1),COLUMN($S$2)))>indirect(address(row(#REF!),COLUMN($K$2))):indirect(address(row(#REF!),COLUMN($S$2))),TRUE()))} -> #REF! | AM24: {=if(AM$14=#REF!,"-", countif(indirect(address(row($J$2)+ VLOOKUP(AM$14,$J$3:$J$8,1),COLUMN($K$4))):indirect(address(row($J$2)+ VLOOKUP(AM$14,$J$3:$J$8,1),COLUMN($S$2)))>indirect(address(row(#REF!),COLUMN($K$2))):indirect(address(row(#REF!),COLUMN($S$2))),TRUE()))} -> #REF! | AN24: {=if(AN$14=#REF!,"-", countif(indirect(address(row($J$2)+ VLOOKUP(AN$14,$J$3:$J$8,1),COLUMN($K$4))):indirect(address(row($J$2)+ VLOOKUP(AN$14,$J$3:$J$8,1),COLUMN($S$2)))>indirect(address(row(#REF!),COLUMN($K$2))):indirect(address(row(#REF!),COLUMN($S$2))),TRUE()))} -> #REF! | AO24: {=if(AO$14=#REF!,"-", countif(indirect(address(row($J$2)+ VLOOKUP(AO$14,$J$3:$J$8,1),COLUMN($K$4))):indirect(address(row($J$2)+ VLOOKUP(AO$14,$J$3:$J$8,1),COLUMN($S$2)))>indirect(address(row(#REF!),COLUMN($K$2))):indirect(address(row(#REF!),COLUMN($S$2))),TRUE()))} -> #REF! | AP24: {=if(AP$14=#REF!,"-", countif(indirect(address(row($J$2)+ VLOOKUP(AP$14,$J$3:$J$8,1),COLUMN($K$4))):indirect(address(row($J$2)+ VLOOKUP(AP$14,$J$3:$J$8,1),COLUMN($S$2)))>indirect(address(row(#REF!),COLUMN($K$2))):indirect(address(row(#REF!),COLUMN($S$2))),TRUE()))} -> #REF! | AQ24: {=if(AQ$14=#REF!,"-", countif(indirect(address(row($J$2)+ VLOOKUP(AQ$14,$J$3:$J$8,1),COLUMN($K$4))):indirect(address(row($J$2)+ VLOOKUP(AQ$14,$J$3:$J$8,1),COLUMN($S$2)))>indirect(address(row(#REF!),COLUMN($K$2))):indirect(address(row(#REF!),COLUMN($S$2))),TRUE()))} -> #REF! | AR24: {=if(AR$14=#REF!,"-", countif(indirect(address(row($J$2)+ VLOOKUP(AR$14,$J$3:$J$8,1),COLUMN($K$4))):indirect(address(row($J$2)+ VLOOKUP(AR$14,$J$3:$J$8,1),COLUMN($S$2)))>indirect(address(row(#REF!),COLUMN($K$2))):indirect(address(row(#REF!),COLUMN($S$2))),TRUE()))} -> #REF! | ... AV24: {=if(AV$14=#REF!,"-", countif(indirect(address(row($J$2)+ VLOOKUP(AV$14,$J$3:$J$8,1),COLUMN($K$4))):indirect(address(row($J$2)+ VLOOKUP(AV$14,$J$3:$J$8,1),COLUMN($S$2)))>indirect(address(row(#REF!),COLUMN($K$2))):indirect(address(row(#REF!),COLUMN($S$2))),TRUE()))} -> #REF! | AW24: 9 | AX24: {=INDIRECT("Draft!L"&TEXT(VLOOKUP(TRUE,I3:J8,2,0)+2,"0"))} -> #N/A | AZ24: =IF($AX24="","", VLOOKUP($AX24,'Final Update'!$Q$21:$AE1009,Column(#REF!),False)) -> #N/A | BA24: =IF($AX24="","", VLOOKUP($AX24,'Final Update'!$Q$21:$AE1009,Column(#REF!),False)) -> #N/A | BB24: =IF($AX24="","", VLOOKUP($AX24,'Final Update'!$Q$21:$AE1009,Column(#REF!),False)) -> #N/A | BC24: =IF($AX24="","", VLOOKUP($AX24,'Final Update'!$Q$21:$AE1009,Column(#REF!),False)) -> #N/A | BD24: =IF($AX24="","", VLOOKUP($AX24,'Final Update'!$Q$21:$AE1009,Column(#REF!),False)) -> #N/A | BE24: =IF($AX24="","", VLOOKUP($AX24,'Final Update'!$Q$21:$AE1009,Column(#REF!),False)) -> #N/A | BF24: =IF($AX24="","", VLOOKUP($AX24,'Final Update'!$Q$21:$AE1009,Column(#REF!),False)) -> #N/A | BG24: =IF($AX24="","", VLOOKUP($AX24,'Final Update'!$Q$21:$AE1009,Column(#REF!),False)) -> #N/A | ... BI24: =IF($AX24="","", VLOOKUP($AX24,'Final Update'!$Q$21:$AE1009,Column(#REF!),False)) -> #N/A
A25: =VLOOKUP($F25,UpdateHashtag!$V$3:$Y$32,COLUMN(B$9),0) -> 4 | B25: =VLOOKUP($F25,UpdateHashtag!$V$3:$Y$32,COLUMN(#REF!),0) -> #REF! | C25: =VLOOKUP($F25,UpdateHashtag!$V$3:$Y$32,COLUMN(#REF!),0) -> #REF! | D25: =SUM(A25:C25) -> #REF! | F25: =VLOOKUP(J25,UpdateBBM!$C$2:E1009,3,0) -> PHI | G25: 12 | H25: =IFERROR(__xludf.DUMMYFUNCTION("""COMPUTED_VALUE"""),12.0) -> 12 | J25: =IFERROR(__xludf.DUMMYFUNCTION("""COMPUTED_VALUE"""),"Tyrese Maxey") -> Tyrese Maxey | K25: =IFERROR(__xludf.DUMMYFUNCTION("""COMPUTED_VALUE"""),73.0) -> 73 | L25: =IFERROR(__xludf.DUMMYFUNCTION("""COMPUTED_VALUE"""),"G") -> G | M25: =IFERROR(__xludf.DUMMYFUNCTION("""COMPUTED_VALUE"""),4.698406980725171) -> 4.698407 | N25: =IFERROR(__xludf.DUMMYFUNCTION("""COMPUTED_VALUE"""),4.8089708900971075) -> 4.8089709 | O25: =IFERROR(__xludf.DUMMYFUNCTION("""COMPUTED_VALUE"""),0.11056390937193683) -> 0.11056391 | P25: =IFERROR(__xludf.DUMMYFUNCTION("""COMPUTED_VALUE"""),25.30397) -> 25.30397 | Q25: =IFERROR(__xludf.DUMMYFUNCTION("""COMPUTED_VALUE"""),3.17) -> 3.17 | R25: =IFERROR(__xludf.DUMMYFUNCTION("""COMPUTED_VALUE"""),3.291781) -> 3.291781 | S25: =IFERROR(__xludf.DUMMYFUNCTION("""COMPUTED_VALUE"""),6.363562) -> 6.363562 | T25: =IFERROR(__xludf.DUMMYFUNCTION("""COMPUTED_VALUE"""),1.332329) -> 1.332329 | U25: =IFERROR(__xludf.DUMMYFUNCTION("""COMPUTED_VALUE"""),0.393151) -> 0.393151 | V25: =IFERROR(__xludf.DUMMYFUNCTION("""COMPUTED_VALUE"""),0.449281) -> 0.449281 | W25: =IFERROR(__xludf.DUMMYFUNCTION("""COMPUTED_VALUE"""),0.87099) -> 0.87099 | X25: =IFERROR(__xludf.DUMMYFUNCTION("""COMPUTED_VALUE"""),2.194521) -> 2.194521 | Y25: =IFERROR(__xludf.DUMMYFUNCTION("""COMPUTED_VALUE"""),1.4262364527460882) -> 1.4262365 | Z25: =IFERROR(__xludf.DUMMYFUNCTION("""COMPUTED_VALUE"""),1.3525979036329863) -> 1.3525979 | AA25: =IFERROR(__xludf.DUMMYFUNCTION("""COMPUTED_VALUE"""),-1.1490617949545983) -> -1.1490618 | AB25: =IFERROR(__xludf.DUMMYFUNCTION("""COMPUTED_VALUE"""),1.234311825027849) -> 1.2343118 | AC25: =IFERROR(__xludf.DUMMYFUNCTION("""COMPUTED_VALUE"""),0.8749855481664958) -> 0.87498555 | AD25: =IFERROR(__xludf.DUMMYFUNCTION("""COMPUTED_VALUE"""),-0.6127929147711293) -> -0.61279291 | AE25: =IFERROR(__xludf.DUMMYFUNCTION("""COMPUTED_VALUE"""),-0.6195024916189793) -> -0.61950249 | AF25: =IFERROR(__xludf.DUMMYFUNCTION("""COMPUTED_VALUE"""),1.153134566913797) -> 1.1531346 | AG25: =IFERROR(__xludf.DUMMYFUNCTION("""COMPUTED_VALUE"""),0.0) -> 0 | AJ25: 100 | AK25: {=if(AK$14=#REF!,"-", countif(indirect(address(row($J$2)+ VLOOKUP(AK$14,$J$3:$J$8,1),COLUMN($K$4))):indirect(address(row($J$2)+ VLOOKUP(AK$14,$J$3:$J$8,1),COLUMN($S$2)))>indirect(address(row(#REF!),COLUMN($K$2))):indirect(address(row(#REF!),COLUMN($S$2))),TRUE()))} -> #REF! | AL25: {=if(AL$14=#REF!,"-", countif(indirect(address(row($J$2)+ VLOOKUP(AL$14,$J$3:$J$8,1),COLUMN($K$4))):indirect(address(row($J$2)+ VLOOKUP(AL$14,$J$3:$J$8,1),COLUMN($S$2)))>indirect(address(row(#REF!),COLUMN($K$2))):indirect(address(row(#REF!),COLUMN($S$2))),TRUE()))} -> #REF! | AM25: {=if(AM$14=#REF!,"-", countif(indirect(address(row($J$2)+ VLOOKUP(AM$14,$J$3:$J$8,1),COLUMN($K$4))):indirect(address(row($J$2)+ VLOOKUP(AM$14,$J$3:$J$8,1),COLUMN($S$2)))>indirect(address(row(#REF!),COLUMN($K$2))):indirect(address(row(#REF!),COLUMN($S$2))),TRUE()))} -> #REF! | AN25: {=if(AN$14=#REF!,"-", countif(indirect(address(row($J$2)+ VLOOKUP(AN$14,$J$3:$J$8,1),COLUMN($K$4))):indirect(address(row($J$2)+ VLOOKUP(AN$14,$J$3:$J$8,1),COLUMN($S$2)))>indirect(address(row(#REF!),COLUMN($K$2))):indirect(address(row(#REF!),COLUMN($S$2))),TRUE()))} -> #REF! | AO25: {=if(AO$14=#REF!,"-", countif(indirect(address(row($J$2)+ VLOOKUP(AO$14,$J$3:$J$8,1),COLUMN($K$4))):indirect(address(row($J$2)+ VLOOKUP(AO$14,$J$3:$J$8,1),COLUMN($S$2)))>indirect(address(row(#REF!),COLUMN($K$2))):indirect(address(row(#REF!),COLUMN($S$2))),TRUE()))} -> #REF! | AP25: {=if(AP$14=#REF!,"-", countif(indirect(address(row($J$2)+ VLOOKUP(AP$14,$J$3:$J$8,1),COLUMN($K$4))):indirect(address(row($J$2)+ VLOOKUP(AP$14,$J$3:$J$8,1),COLUMN($S$2)))>indirect(address(row(#REF!),COLUMN($K$2))):indirect(address(row(#REF!),COLUMN($S$2))),TRUE()))} -> #REF! | AQ25: {=if(AQ$14=#REF!,"-", countif(indirect(address(row($J$2)+ VLOOKUP(AQ$14,$J$3:$J$8,1),COLUMN($K$4))):indirect(address(row($J$2)+ VLOOKUP(AQ$14,$J$3:$J$8,1),COLUMN($S$2)))>indirect(address(row(#REF!),COLUMN($K$2))):indirect(address(row(#REF!),COLUMN($S$2))),TRUE()))} -> #REF! | AR25: {=if(AR$14=#REF!,"-", countif(indirect(address(row($J$2)+ VLOOKUP(AR$14,$J$3:$J$8,1),COLUMN($K$4))):indirect(address(row($J$2)+ VLOOKUP(AR$14,$J$3:$J$8,1),COLUMN($S$2)))>indirect(address(row(#REF!),COLUMN($K$2))):indirect(address(row(#REF!),COLUMN($S$2))),TRUE()))} -> #REF! | ... AV25: {=if(AV$14=#REF!,"-", countif(indirect(address(row($J$2)+ VLOOKUP(AV$14,$J$3:$J$8,1),COLUMN($K$4))):indirect(address(row($J$2)+ VLOOKUP(AV$14,$J$3:$J$8,1),COLUMN($S$2)))>indirect(address(row(#REF!),COLUMN($K$2))):indirect(address(row(#REF!),COLUMN($S$2))),TRUE()))} -> #REF! | AW25: 10 | AX25: {=INDIRECT("Draft!M"&TEXT(15-VLOOKUP(TRUE,I3:J8,2,0),"0"))} -> #N/A | AZ25: =IF($AX25="","", VLOOKUP($AX25,'Final Update'!$Q$21:$AE1009,Column(#REF!),False)) -> #N/A | BA25: =IF($AX25="","", VLOOKUP($AX25,'Final Update'!$Q$21:$AE1009,Column(#REF!),False)) -> #N/A | BB25: =IF($AX25="","", VLOOKUP($AX25,'Final Update'!$Q$21:$AE1009,Column(#REF!),False)) -> #N/A | BC25: =IF($AX25="","", VLOOKUP($AX25,'Final Update'!$Q$21:$AE1009,Column(#REF!),False)) -> #N/A | BD25: =IF($AX25="","", VLOOKUP($AX25,'Final Update'!$Q$21:$AE1009,Column(#REF!),False)) -> #N/A | BE25: =IF($AX25="","", VLOOKUP($AX25,'Final Update'!$Q$21:$AE1009,Column(#REF!),False)) -> #N/A | BF25: =IF($AX25="","", VLOOKUP($AX25,'Final Update'!$Q$21:$AE1009,Column(#REF!),False)) -> #N/A | BG25: =IF($AX25="","", VLOOKUP($AX25,'Final Update'!$Q$21:$AE1009,Column(#REF!),False)) -> #N/A | ... BI25: =IF($AX25="","", VLOOKUP($AX25,'Final Update'!$Q$21:$AE1009,Column(#REF!),False)) -> #N/A
A26: =VLOOKUP($F26,UpdateHashtag!$V$3:$Y$32,COLUMN(B$9),0) -> 4 | B26: =VLOOKUP($F26,UpdateHashtag!$V$3:$Y$32,COLUMN(#REF!),0) -> #REF! | C26: =VLOOKUP($F26,UpdateHashtag!$V$3:$Y$32,COLUMN(#REF!),0) -> #REF! | D26: =SUM(A26:C26) -> #REF! | F26: =VLOOKUP(J26,UpdateBBM!$C$2:E1009,3,0) -> LAC | G26: 13 | H26: =IFERROR(__xludf.DUMMYFUNCTION("""COMPUTED_VALUE"""),13.0) -> 13 | J26: =IFERROR(__xludf.DUMMYFUNCTION("""COMPUTED_VALUE"""),"Kawhi Leonard") -> Kawhi Leonard | K26: =IFERROR(__xludf.DUMMYFUNCTION("""COMPUTED_VALUE"""),60.0) -> 60 | L26: =IFERROR(__xludf.DUMMYFUNCTION("""COMPUTED_VALUE"""),"F") -> F | M26: =IFERROR(__xludf.DUMMYFUNCTION("""COMPUTED_VALUE"""),4.6090876914442) -> 4.6090877 | N26: =IFERROR(__xludf.DUMMYFUNCTION("""COMPUTED_VALUE"""),4.618428269192777) -> 4.6184283 | O26: =IFERROR(__xludf.DUMMYFUNCTION("""COMPUTED_VALUE"""),0.009340577748576884) -> 0.0093405777 | P26: =IFERROR(__xludf.DUMMYFUNCTION("""COMPUTED_VALUE"""),24.568) -> 24.568 | Q26: =IFERROR(__xludf.DUMMYFUNCTION("""COMPUTED_VALUE"""),2.273333) -> 2.273333 | R26: =IFERROR(__xludf.DUMMYFUNCTION("""COMPUTED_VALUE"""),6.321167) -> 6.321167 | S26: =IFERROR(__xludf.DUMMYFUNCTION("""COMPUTED_VALUE"""),3.1605) -> 3.1605 | T26: =IFERROR(__xludf.DUMMYFUNCTION("""COMPUTED_VALUE"""),1.653333) -> 1.653333 | U26: =IFERROR(__xludf.DUMMYFUNCTION("""COMPUTED_VALUE"""),0.617167) -> 0.617167 | V26: =IFERROR(__xludf.DUMMYFUNCTION("""COMPUTED_VALUE"""),0.504101) -> 0.504101 | W26: =IFERROR(__xludf.DUMMYFUNCTION("""COMPUTED_VALUE"""),0.859017) -> 0.859017 | X26: =IFERROR(__xludf.DUMMYFUNCTION("""COMPUTED_VALUE"""),1.786333) -> 1.786333 | Y26: =IFERROR(__xludf.DUMMYFUNCTION("""COMPUTED_VALUE"""),1.297115953634725) -> 1.297116 | Z26: =IFERROR(__xludf.DUMMYFUNCTION("""COMPUTED_VALUE"""),0.4865669306741203) -> 0.48656693 | AA26: =IFERROR(__xludf.DUMMYFUNCTION("""COMPUTED_VALUE"""),0.07891074489848583) -> 0.078910745 | AB26: =IFERROR(__xludf.DUMMYFUNCTION("""COMPUTED_VALUE"""),-0.3304303970281824) -> -0.3304304 | AC26: =IFERROR(__xludf.DUMMYFUNCTION("""COMPUTED_VALUE"""),1.8531585793638956) -> 1.8531586 | AD26: =IFERROR(__xludf.DUMMYFUNCTION("""COMPUTED_VALUE"""),-0.20553356850205748) -> -0.20553357 | AE26: =IFERROR(__xludf.DUMMYFUNCTION("""COMPUTED_VALUE"""),0.1350520395842976) -> 0.13505204 | AF26: =IFERROR(__xludf.DUMMYFUNCTION("""COMPUTED_VALUE"""),0.9731575895393098) -> 0.97315759 | AG26: =IFERROR(__xludf.DUMMYFUNCTION("""COMPUTED_VALUE"""),0.0) -> 0 | AJ26: 100 | AK26: {=if(AK$14=#REF!,"-", countif(indirect(address(row($J$2)+ VLOOKUP(AK$14,$J$3:$J$8,1),COLUMN($K$4))):indirect(address(row($J$2)+ VLOOKUP(AK$14,$J$3:$J$8,1),COLUMN($S$2)))>indirect(address(row(#REF!),COLUMN($K$2))):indirect(address(row(#REF!),COLUMN($S$2))),TRUE()))} -> #REF! | AL26: {=if(AL$14=#REF!,"-", countif(indirect(address(row($J$2)+ VLOOKUP(AL$14,$J$3:$J$8,1),COLUMN($K$4))):indirect(address(row($J$2)+ VLOOKUP(AL$14,$J$3:$J$8,1),COLUMN($S$2)))>indirect(address(row(#REF!),COLUMN($K$2))):indirect(address(row(#REF!),COLUMN($S$2))),TRUE()))} -> #REF! | AM26: {=if(AM$14=#REF!,"-", countif(indirect(address(row($J$2)+ VLOOKUP(AM$14,$J$3:$J$8,1),COLUMN($K$4))):indirect(address(row($J$2)+ VLOOKUP(AM$14,$J$3:$J$8,1),COLUMN($S$2)))>indirect(address(row(#REF!),COLUMN($K$2))):indirect(address(row(#REF!),COLUMN($S$2))),TRUE()))} -> #REF! | AN26: {=if(AN$14=#REF!,"-", countif(indirect(address(row($J$2)+ VLOOKUP(AN$14,$J$3:$J$8,1),COLUMN($K$4))):indirect(address(row($J$2)+ VLOOKUP(AN$14,$J$3:$J$8,1),COLUMN($S$2)))>indirect(address(row(#REF!),COLUMN($K$2))):indirect(address(row(#REF!),COLUMN($S$2))),TRUE()))} -> #REF! | AO26: {=if(AO$14=#REF!,"-", countif(indirect(address(row($J$2)+ VLOOKUP(AO$14,$J$3:$J$8,1),COLUMN($K$4))):indirect(address(row($J$2)+ VLOOKUP(AO$14,$J$3:$J$8,1),COLUMN($S$2)))>indirect(address(row(#REF!),COLUMN($K$2))):indirect(address(row(#REF!),COLUMN($S$2))),TRUE()))} -> #REF! | AP26: {=if(AP$14=#REF!,"-", countif(indirect(address(row($J$2)+ VLOOKUP(AP$14,$J$3:$J$8,1),COLUMN($K$4))):indirect(address(row($J$2)+ VLOOKUP(AP$14,$J$3:$J$8,1),COLUMN($S$2)))>indirect(address(row(#REF!),COLUMN($K$2))):indirect(address(row(#REF!),COLUMN($S$2))),TRUE()))} -> #REF! | AQ26: {=if(AQ$14=#REF!,"-", countif(indirect(address(row($J$2)+ VLOOKUP(AQ$14,$J$3:$J$8,1),COLUMN($K$4))):indirect(address(row($J$2)+ VLOOKUP(AQ$14,$J$3:$J$8,1),COLUMN($S$2)))>indirect(address(row(#REF!),COLUMN($K$2))):indirect(address(row(#REF!),COLUMN($S$2))),TRUE()))} -> #REF! | AR26: {=if(AR$14=#REF!,"-", countif(indirect(address(row($J$2)+ VLOOKUP(AR$14,$J$3:$J$8,1),COLUMN($K$4))):indirect(address(row($J$2)+ VLOOKUP(AR$14,$J$3:$J$8,1),COLUMN($S$2)))>indirect(address(row(#REF!),COLUMN($K$2))):indirect(address(row(#REF!),COLUMN($S$2))),TRUE()))} -> #REF! | ... AV26: {=if(AV$14=#REF!,"-", countif(indirect(address(row($J$2)+ VLOOKUP(AV$14,$J$3:$J$8,1),COLUMN($K$4))):indirect(address(row($J$2)+ VLOOKUP(AV$14,$J$3:$J$8,1),COLUMN($S$2)))>indirect(address(row(#REF!),COLUMN($K$2))):indirect(address(row(#REF!),COLUMN($S$2))),TRUE()))} -> #REF! | AW26: 11 | AX26: {=INDIRECT("Draft!N"&TEXT(VLOOKUP(TRUE,I3:J8,2,0)+2,"0"))} -> #N/A | AZ26: =IF($AX26="","", VLOOKUP($AX26,'Final Update'!$Q$21:$AE1009,Column(#REF!),False)) -> #N/A | BA26: =IF($AX26="","", VLOOKUP($AX26,'Final Update'!$Q$21:$AE1009,Column(#REF!),False)) -> #N/A | BB26: =IF($AX26="","", VLOOKUP($AX26,'Final Update'!$Q$21:$AE1009,Column(#REF!),False)) -> #N/A | BC26: =IF($AX26="","", VLOOKUP($AX26,'Final Update'!$Q$21:$AE1009,Column(#REF!),False)) -> #N/A | BD26: =IF($AX26="","", VLOOKUP($AX26,'Final Update'!$Q$21:$AE1009,Column(#REF!),False)) -> #N/A | BE26: =IF($AX26="","", VLOOKUP($AX26,'Final Update'!$Q$21:$AE1009,Column(#REF!),False)) -> #N/A | BF26: =IF($AX26="","", VLOOKUP($AX26,'Final Update'!$Q$21:$AE1009,Column(#REF!),False)) -> #N/A | BG26: =IF($AX26="","", VLOOKUP($AX26,'Final Update'!$Q$21:$AE1009,Column(#REF!),False)) -> #N/A | ... BI26: =IF($AX26="","", VLOOKUP($AX26,'Final Update'!$Q$21:$AE1009,Column(#REF!),False)) -> #N/A
A27: =VLOOKUP($F27,UpdateHashtag!$V$3:$Y$32,COLUMN(B$9),0) -> 4 | B27: =VLOOKUP($F27,UpdateHashtag!$V$3:$Y$32,COLUMN(#REF!),0) -> #REF! | C27: =VLOOKUP($F27,UpdateHashtag!$V$3:$Y$32,COLUMN(#REF!),0) -> #REF! | D27: =SUM(A27:C27) -> #REF! | F27: =VLOOKUP(J27,UpdateBBM!$C$2:E1009,3,0) -> HOU | G27: 14 | H27: =IFERROR(__xludf.DUMMYFUNCTION("""COMPUTED_VALUE"""),14.0) -> 14 | J27: =IFERROR(__xludf.DUMMYFUNCTION("""COMPUTED_VALUE"""),"Amen Thompson") -> Amen Thompson | K27: =IFERROR(__xludf.DUMMYFUNCTION("""COMPUTED_VALUE"""),68.0) -> 68 | L27: =IFERROR(__xludf.DUMMYFUNCTION("""COMPUTED_VALUE"""),"G,F") -> G,F | M27: =IFERROR(__xludf.DUMMYFUNCTION("""COMPUTED_VALUE"""),4.538513622577234) -> 4.5385136 | N27: =IFERROR(__xludf.DUMMYFUNCTION("""COMPUTED_VALUE"""),4.705977032769822) -> 4.705977 | O27: =IFERROR(__xludf.DUMMYFUNCTION("""COMPUTED_VALUE"""),0.16746341019258804) -> 0.16746341 | P27: =IFERROR(__xludf.DUMMYFUNCTION("""COMPUTED_VALUE"""),17.87471) -> 17.87471 | Q27: =IFERROR(__xludf.DUMMYFUNCTION("""COMPUTED_VALUE"""),0.473382) -> 0.473382 | R27: =IFERROR(__xludf.DUMMYFUNCTION("""COMPUTED_VALUE"""),8.483971) -> 8.483971 | S27: =IFERROR(__xludf.DUMMYFUNCTION("""COMPUTED_VALUE"""),6.590294) -> 6.590294 | T27: =IFERROR(__xludf.DUMMYFUNCTION("""COMPUTED_VALUE"""),1.515) -> 1.515 | U27: =IFERROR(__xludf.DUMMYFUNCTION("""COMPUTED_VALUE"""),1.287794) -> 1.287794 | V27: =IFERROR(__xludf.DUMMYFUNCTION("""COMPUTED_VALUE"""),0.55993) -> 0.55993 | W27: =IFERROR(__xludf.DUMMYFUNCTION("""COMPUTED_VALUE"""),0.649986) -> 0.649986 | X27: =IFERROR(__xludf.DUMMYFUNCTION("""COMPUTED_VALUE"""),2.423971) -> 2.423971 | Y27: =IFERROR(__xludf.DUMMYFUNCTION("""COMPUTED_VALUE"""),0.12282767354572907) -> 0.12282767 | Z27: =IFERROR(__xludf.DUMMYFUNCTION("""COMPUTED_VALUE"""),-1.251885935114722) -> -1.2518859 | AA27: =IFERROR(__xludf.DUMMYFUNCTION("""COMPUTED_VALUE"""),0.9556111459317018) -> 0.95561115 | AB27: =IFERROR(__xludf.DUMMYFUNCTION("""COMPUTED_VALUE"""),1.3450736939804977) -> 1.3450737 | AC27: =IFERROR(__xludf.DUMMYFUNCTION("""COMPUTED_VALUE"""),1.4316261064830904) -> 1.4316261 | AD27: =IFERROR(__xludf.DUMMYFUNCTION("""COMPUTED_VALUE"""),1.0136611033534741) -> 1.0136611 | AE27: =IFERROR(__xludf.DUMMYFUNCTION("""COMPUTED_VALUE"""),1.0890632445900514) -> 1.0890632 | AF27: =IFERROR(__xludf.DUMMYFUNCTION("""COMPUTED_VALUE"""),-1.4317815706235524) -> -1.4317816 | AG27: =IFERROR(__xludf.DUMMYFUNCTION("""COMPUTED_VALUE"""),0.0) -> 0 | AJ27: 100 | AK27: {=if(AK$14=$F5,"-", countif(indirect(address(row($J$2)+ VLOOKUP(AK$14,$J$3:$J$8,1),COLUMN($K$4))):indirect(address(row($J$2)+ VLOOKUP(AK$14,$J$3:$J$8,1),COLUMN($S$2)))>indirect(address(row($F5),COLUMN($K$2))):indirect(address(row($F5),COLUMN($S$2))),TRUE()))} -> 0 | AL27: {=if(AL$14=$F5,"-", countif(indirect(address(row($J$2)+ VLOOKUP(AL$14,$J$3:$J$8,1),COLUMN($K$4))):indirect(address(row($J$2)+ VLOOKUP(AL$14,$J$3:$J$8,1),COLUMN($S$2)))>indirect(address(row($F5),COLUMN($K$2))):indirect(address(row($F5),COLUMN($S$2))),TRUE()))} -> 0 | AM27: {=if(AM$14=$F5,"-", countif(indirect(address(row($J$2)+ VLOOKUP(AM$14,$J$3:$J$8,1),COLUMN($K$4))):indirect(address(row($J$2)+ VLOOKUP(AM$14,$J$3:$J$8,1),COLUMN($S$2)))>indirect(address(row($F5),COLUMN($K$2))):indirect(address(row($F5),COLUMN($S$2))),TRUE()))} -> 0 | AN27: {=if(AN$14=$F5,"-", countif(indirect(address(row($J$2)+ VLOOKUP(AN$14,$J$3:$J$8,1),COLUMN($K$4))):indirect(address(row($J$2)+ VLOOKUP(AN$14,$J$3:$J$8,1),COLUMN($S$2)))>indirect(address(row($F5),COLUMN($K$2))):indirect(address(row($F5),COLUMN($S$2))),TRUE()))} -> 0 | AO27: {=if(AO$14=$F5,"-", countif(indirect(address(row($J$2)+ VLOOKUP(AO$14,$J$3:$J$8,1),COLUMN($K$4))):indirect(address(row($J$2)+ VLOOKUP(AO$14,$J$3:$J$8,1),COLUMN($S$2)))>indirect(address(row($F5),COLUMN($K$2))):indirect(address(row($F5),COLUMN($S$2))),TRUE()))} -> 0 | AP27: {=if(AP$14=$F5,"-", countif(indirect(address(row($J$2)+ VLOOKUP(AP$14,$J$3:$J$8,1),COLUMN($K$4))):indirect(address(row($J$2)+ VLOOKUP(AP$14,$J$3:$J$8,1),COLUMN($S$2)))>indirect(address(row($F5),COLUMN($K$2))):indirect(address(row($F5),COLUMN($S$2))),TRUE()))} -> 0 | AQ27: {=if(AQ$14=$F5,"-", countif(indirect(address(row($J$2)+ VLOOKUP(AQ$14,$J$3:$J$8,1),COLUMN($K$4))):indirect(address(row($J$2)+ VLOOKUP(AQ$14,$J$3:$J$8,1),COLUMN($S$2)))>indirect(address(row($F5),COLUMN($K$2))):indirect(address(row($F5),COLUMN($S$2))),TRUE()))} -> 0 | AR27: {=if(AR$14=$F5,"-", countif(indirect(address(row($J$2)+ VLOOKUP(AR$14,$J$3:$J$8,1),COLUMN($K$4))):indirect(address(row($J$2)+ VLOOKUP(AR$14,$J$3:$J$8,1),COLUMN($S$2)))>indirect(address(row($F5),COLUMN($K$2))):indirect(address(row($F5),COLUMN($S$2))),TRUE()))} -> 0 | ... AV27: {=if(AV$14=$F5,"-", countif(indirect(address(row($J$2)+ VLOOKUP(AV$14,$J$3:$J$8,1),COLUMN($K$4))):indirect(address(row($J$2)+ VLOOKUP(AV$14,$J$3:$J$8,1),COLUMN($S$2)))>indirect(address(row($F5),COLUMN($K$2))):indirect(address(row($F5),COLUMN($S$2))),TRUE()))} -> 0 | AW27: 12 | AX27: {=INDIRECT("Draft!O"&TEXT(15-VLOOKUP(TRUE,I3:J8,2,0),"0"))} -> #N/A | AZ27: =IF($AX27="","", VLOOKUP($AX27,'Final Update'!$Q$21:$AE1009,Column(#REF!),False)) -> #N/A | BA27: =IF($AX27="","", VLOOKUP($AX27,'Final Update'!$Q$21:$AE1009,Column(#REF!),False)) -> #N/A | BB27: =IF($AX27="","", VLOOKUP($AX27,'Final Update'!$Q$21:$AE1009,Column(#REF!),False)) -> #N/A | BC27: =IF($AX27="","", VLOOKUP($AX27,'Final Update'!$Q$21:$AE1009,Column(#REF!),False)) -> #N/A | BD27: =IF($AX27="","", VLOOKUP($AX27,'Final Update'!$Q$21:$AE1009,Column(#REF!),False)) -> #N/A | BE27: =IF($AX27="","", VLOOKUP($AX27,'Final Update'!$Q$21:$AE1009,Column(#REF!),False)) -> #N/A | BF27: =IF($AX27="","", VLOOKUP($AX27,'Final Update'!$Q$21:$AE1009,Column(#REF!),False)) -> #N/A | BG27: =IF($AX27="","", VLOOKUP($AX27,'Final Update'!$Q$21:$AE1009,Column(#REF!),False)) -> #N/A | ... BI27: =IF($AX27="","", VLOOKUP($AX27,'Final Update'!$Q$21:$AE1009,Column(#REF!),False)) -> #N/A
A28: =VLOOKUP($F28,UpdateHashtag!$V$3:$Y$32,COLUMN(B$9),0) -> 4 | B28: =VLOOKUP($F28,UpdateHashtag!$V$3:$Y$32,COLUMN(#REF!),0) -> #REF! | C28: =VLOOKUP($F28,UpdateHashtag!$V$3:$Y$32,COLUMN(#REF!),0) -> #REF! | D28: =SUM(A28:C28) -> #REF! | F28: =VLOOKUP(J28,UpdateBBM!$C$2:E1009,3,0) -> MIN | G28: 15 | H28: =IFERROR(__xludf.DUMMYFUNCTION("""COMPUTED_VALUE"""),15.0) -> 15 | J28: =IFERROR(__xludf.DUMMYFUNCTION("""COMPUTED_VALUE"""),"Anthony Edwards") -> Anthony Edwards | K28: =IFERROR(__xludf.DUMMYFUNCTION("""COMPUTED_VALUE"""),77.0) -> 77 | L28: =IFERROR(__xludf.DUMMYFUNCTION("""COMPUTED_VALUE"""),"G,F") -> G,F | M28: =IFERROR(__xludf.DUMMYFUNCTION("""COMPUTED_VALUE"""),4.434595825645324) -> 4.4345958 | N28: =IFERROR(__xludf.DUMMYFUNCTION("""COMPUTED_VALUE"""),4.792696989827369) -> 4.792697 | O28: =IFERROR(__xludf.DUMMYFUNCTION("""COMPUTED_VALUE"""),0.3581011641820444) -> 0.35810116 | P28: =IFERROR(__xludf.DUMMYFUNCTION("""COMPUTED_VALUE"""),28.19805) -> 28.19805 | Q28: =IFERROR(__xludf.DUMMYFUNCTION("""COMPUTED_VALUE"""),3.818701) -> 3.818701 | R28: =IFERROR(__xludf.DUMMYFUNCTION("""COMPUTED_VALUE"""),5.42026) -> 5.42026 | S28: =IFERROR(__xludf.DUMMYFUNCTION("""COMPUTED_VALUE"""),4.974805) -> 4.974805 | T28: =IFERROR(__xludf.DUMMYFUNCTION("""COMPUTED_VALUE"""),1.113506) -> 1.113506 | U28: =IFERROR(__xludf.DUMMYFUNCTION("""COMPUTED_VALUE"""),0.668312) -> 0.668312 | V28: =IFERROR(__xludf.DUMMYFUNCTION("""COMPUTED_VALUE"""),0.44995) -> 0.44995 | W28: =IFERROR(__xludf.DUMMYFUNCTION("""COMPUTED_VALUE"""),0.826999) -> 0.826999 | X28: =IFERROR(__xludf.DUMMYFUNCTION("""COMPUTED_VALUE"""),3.192727) -> 3.192727 | Y28: =IFERROR(__xludf.DUMMYFUNCTION("""COMPUTED_VALUE"""),1.9339814071168029) -> 1.9339814 | Z28: =IFERROR(__xludf.DUMMYFUNCTION("""COMPUTED_VALUE"""),1.979135021860142) -> 1.979135 | AA28: =IFERROR(__xludf.DUMMYFUNCTION("""COMPUTED_VALUE"""),-0.28627515645625157) -> -0.28627516 | AB28: =IFERROR(__xludf.DUMMYFUNCTION("""COMPUTED_VALUE"""),0.5558838976021958) -> 0.5558839 | AC28: =IFERROR(__xludf.DUMMYFUNCTION("""COMPUTED_VALUE"""),0.20818152950719962) -> 0.20818153 | AD28: =IFERROR(__xludf.DUMMYFUNCTION("""COMPUTED_VALUE"""),-0.11255235615592295) -> -0.11255236 | AE28: =IFERROR(__xludf.DUMMYFUNCTION("""COMPUTED_VALUE"""),-0.6113824810968774) -> -0.61138248 | AF28: =IFERROR(__xludf.DUMMYFUNCTION("""COMPUTED_VALUE"""),0.5143426463532014) -> 0.51434265 | AG28: =IFERROR(__xludf.DUMMYFUNCTION("""COMPUTED_VALUE"""),0.0) -> 0 | AJ28: 100 | AW28: 13 | AX28: {=INDIRECT("Draft!P"&TEXT(VLOOKUP(TRUE,I3:J8,2,0)+2,"0"))} -> #N/A | AZ28: =IF($AX28="","", VLOOKUP($AX28,'Final Update'!$Q$21:$AE1009,Column(#REF!),False)) -> #N/A | BA28: =IF($AX28="","", VLOOKUP($AX28,'Final Update'!$Q$21:$AE1009,Column(#REF!),False)) -> #N/A | BB28: =IF($AX28="","", VLOOKUP($AX28,'Final Update'!$Q$21:$AE1009,Column(#REF!),False)) -> #N/A | BC28: =IF($AX28="","", VLOOKUP($AX28,'Final Update'!$Q$21:$AE1009,Column(#REF!),False)) -> #N/A | BD28: =IF($AX28="","", VLOOKUP($AX28,'Final Update'!$Q$21:$AE1009,Column(#REF!),False)) -> #N/A | BE28: =IF($AX28="","", VLOOKUP($AX28,'Final Update'!$Q$21:$AE1009,Column(#REF!),False)) -> #N/A | BF28: =IF($AX28="","", VLOOKUP($AX28,'Final Update'!$Q$21:$AE1009,Column(#REF!),False)) -> #N/A | BG28: =IF($AX28="","", VLOOKUP($AX28,'Final Update'!$Q$21:$AE1009,Column(#REF!),False)) -> #N/A | ... BI28: =IF($AX28="","", VLOOKUP($AX28,'Final Update'!$Q$21:$AE1009,Column(#REF!),False)) -> #N/A
A29: =VLOOKUP($F29,UpdateHashtag!$V$3:$Y$32,COLUMN(B$9),0) -> 4 | B29: =VLOOKUP($F29,UpdateHashtag!$V$3:$Y$32,COLUMN(#REF!),0) -> #REF! | C29: =VLOOKUP($F29,UpdateHashtag!$V$3:$Y$32,COLUMN(#REF!),0) -> #REF! | D29: =SUM(A29:C29) -> #REF! | F29: =VLOOKUP(J29,UpdateBBM!$C$2:E1009,3,0) -> CLE | G29: 16 | H29: =IFERROR(__xludf.DUMMYFUNCTION("""COMPUTED_VALUE"""),16.0) -> 16 | J29: =IFERROR(__xludf.DUMMYFUNCTION("""COMPUTED_VALUE"""),"Donovan Mitchell") -> Donovan Mitchell | K29: =IFERROR(__xludf.DUMMYFUNCTION("""COMPUTED_VALUE"""),68.0) -> 68 | L29: =IFERROR(__xludf.DUMMYFUNCTION("""COMPUTED_VALUE"""),"G") -> G | M29: =IFERROR(__xludf.DUMMYFUNCTION("""COMPUTED_VALUE"""),4.263374273939553) -> 4.2633743 | N29: =IFERROR(__xludf.DUMMYFUNCTION("""COMPUTED_VALUE"""),4.41413534340966) -> 4.4141353 | O29: =IFERROR(__xludf.DUMMYFUNCTION("""COMPUTED_VALUE"""),0.15076106947010715) -> 0.15076107 | P29: =IFERROR(__xludf.DUMMYFUNCTION("""COMPUTED_VALUE"""),26.15735) -> 26.15735 | Q29: =IFERROR(__xludf.DUMMYFUNCTION("""COMPUTED_VALUE"""),3.337647) -> 3.337647 | R29: =IFERROR(__xludf.DUMMYFUNCTION("""COMPUTED_VALUE"""),4.578676) -> 4.578676 | S29: =IFERROR(__xludf.DUMMYFUNCTION("""COMPUTED_VALUE"""),5.656029) -> 5.656029 | T29: =IFERROR(__xludf.DUMMYFUNCTION("""COMPUTED_VALUE"""),1.274706) -> 1.274706 | U29: =IFERROR(__xludf.DUMMYFUNCTION("""COMPUTED_VALUE"""),0.27) -> 0.27 | V29: =IFERROR(__xludf.DUMMYFUNCTION("""COMPUTED_VALUE"""),0.460659) -> 0.460659 | W29: =IFERROR(__xludf.DUMMYFUNCTION("""COMPUTED_VALUE"""),0.850008) -> 0.850008 | X29: =IFERROR(__xludf.DUMMYFUNCTION("""COMPUTED_VALUE"""),2.356618) -> 2.356618 | Y29: =IFERROR(__xludf.DUMMYFUNCTION("""COMPUTED_VALUE"""),1.5759556689256276) -> 1.5759557 | Z29: =IFERROR(__xludf.DUMMYFUNCTION("""COMPUTED_VALUE"""),1.5145169823139626) -> 1.514517 | AA29: =IFERROR(__xludf.DUMMYFUNCTION("""COMPUTED_VALUE"""),-0.6274142658268362) -> -0.62741427 | AB29: =IFERROR(__xludf.DUMMYFUNCTION("""COMPUTED_VALUE"""),0.8886716973631428) -> 0.8886717 | AC29: =IFERROR(__xludf.DUMMYFUNCTION("""COMPUTED_VALUE"""),0.6993950116725954) -> 0.69939501 | AD29: =IFERROR(__xludf.DUMMYFUNCTION("""COMPUTED_VALUE"""),-0.8366804752685153) -> -0.83668048 | AE29: =IFERROR(__xludf.DUMMYFUNCTION("""COMPUTED_VALUE"""),-0.47774136502858905) -> -0.47774136 | AF29: =IFERROR(__xludf.DUMMYFUNCTION("""COMPUTED_VALUE"""),0.8407516139897564) -> 0.84075161 | AG29: =IFERROR(__xludf.DUMMYFUNCTION("""COMPUTED_VALUE"""),0.0) -> 0 | AJ29: 50 | AW29: 14 | AX29: {=INDIRECT("Draft!Q"&TEXT(15-VLOOKUP(TRUE,I3:J8,2,0),"0"))} -> #N/A
A30: =VLOOKUP($F30,UpdateHashtag!$V$3:$Y$32,COLUMN(B$9),0) -> 4 | B30: =VLOOKUP($F30,UpdateHashtag!$V$3:$Y$32,COLUMN(#REF!),0) -> #REF! | C30: =VLOOKUP($F30,UpdateHashtag!$V$3:$Y$32,COLUMN(#REF!),0) -> #REF! | D30: =SUM(A30:C30) -> #REF! | F30: =VLOOKUP(J30,UpdateBBM!$C$2:E1009,3,0) -> HOU | G30: 17 | H30: =IFERROR(__xludf.DUMMYFUNCTION("""COMPUTED_VALUE"""),17.0) -> 17 | J30: =IFERROR(__xludf.DUMMYFUNCTION("""COMPUTED_VALUE"""),"Kevin Durant") -> Kevin Durant | K30: =IFERROR(__xludf.DUMMYFUNCTION("""COMPUTED_VALUE"""),64.0) -> 64 | L30: =IFERROR(__xludf.DUMMYFUNCTION("""COMPUTED_VALUE"""),"F") -> F | M30: =IFERROR(__xludf.DUMMYFUNCTION("""COMPUTED_VALUE"""),4.1577032402455725) -> 4.1577032 | N30: =IFERROR(__xludf.DUMMYFUNCTION("""COMPUTED_VALUE"""),4.54589356473084) -> 4.5458936 | O30: =IFERROR(__xludf.DUMMYFUNCTION("""COMPUTED_VALUE"""),0.3881903244852678) -> 0.38819032 | P30: =IFERROR(__xludf.DUMMYFUNCTION("""COMPUTED_VALUE"""),28.26391) -> 28.26391 | Q30: =IFERROR(__xludf.DUMMYFUNCTION("""COMPUTED_VALUE"""),2.716563) -> 2.716563 | R30: =IFERROR(__xludf.DUMMYFUNCTION("""COMPUTED_VALUE"""),5.3025) -> 5.3025 | S30: =IFERROR(__xludf.DUMMYFUNCTION("""COMPUTED_VALUE"""),4.860625) -> 4.860625 | T30: =IFERROR(__xludf.DUMMYFUNCTION("""COMPUTED_VALUE"""),0.807969) -> 0.807969 | U30: =IFERROR(__xludf.DUMMYFUNCTION("""COMPUTED_VALUE"""),0.88375) -> 0.88375 | V30: =IFERROR(__xludf.DUMMYFUNCTION("""COMPUTED_VALUE"""),0.514412) -> 0.514412 | W30: =IFERROR(__xludf.DUMMYFUNCTION("""COMPUTED_VALUE"""),0.857004) -> 0.857004 | X30: =IFERROR(__xludf.DUMMYFUNCTION("""COMPUTED_VALUE"""),3.314063) -> 3.314063 | Y30: =IFERROR(__xludf.DUMMYFUNCTION("""COMPUTED_VALUE"""),1.9455360575393397) -> 1.9455361 | Z30: =IFERROR(__xludf.DUMMYFUNCTION("""COMPUTED_VALUE"""),0.9146532861935696) -> 0.91465329 | AA30: =IFERROR(__xludf.DUMMYFUNCTION("""COMPUTED_VALUE"""),-0.33400959712941064) -> -0.3340096 | AB30: =IFERROR(__xludf.DUMMYFUNCTION("""COMPUTED_VALUE"""),0.5001053123252458) -> 0.50010531 | AC30: =IFERROR(__xludf.DUMMYFUNCTION("""COMPUTED_VALUE"""),-0.7228599946886364) -> -0.72285999 | AD30: =IFERROR(__xludf.DUMMYFUNCTION("""COMPUTED_VALUE"""),0.27911225280734875) -> 0.27911225 | AE30: =IFERROR(__xludf.DUMMYFUNCTION("""COMPUTED_VALUE"""),0.2971486134220053) -> 0.29714861 | AF30: =IFERROR(__xludf.DUMMYFUNCTION("""COMPUTED_VALUE"""),0.9433476395727419) -> 0.94334764 | AG30: =IFERROR(__xludf.DUMMYFUNCTION("""COMPUTED_VALUE"""),0.0) -> 0 | AY30: Average | AZ30: =IFERROR(AVERAGE(SUMPRODUCT(AZ$16:AZ$29,$AJ$16:$AJ$29/100))/(SUM(OFFSET($AJ$16,0,0,COUNT($AZ$16:$AZ$29)))/100),"") | BA30: =IFERROR(AVERAGE(SUMPRODUCT(BA$16:BA$29,$AJ$16:$AJ$29/100))/(SUM(OFFSET($AJ$16,0,0,COUNT($AZ$16:$AZ$29)))/100),"") | BB30: =IFERROR(AVERAGE(SUMPRODUCT(BB$16:BB$29,$AJ$16:$AJ$29/100))/(SUM(OFFSET($AJ$16,0,0,COUNT($AZ$16:$AZ$29)))/100),"") | BC30: =IFERROR(AVERAGE(SUMPRODUCT(BC$16:BC$29,$AJ$16:$AJ$29/100))/(SUM(OFFSET($AJ$16,0,0,COUNT($AZ$16:$AZ$29)))/100),"") | BD30: =IFERROR(AVERAGE(SUMPRODUCT(BD$16:BD$29,$AJ$16:$AJ$29/100))/(SUM(OFFSET($AJ$16,0,0,COUNT($AZ$16:$AZ$29)))/100),"") | BE30: =IFERROR(AVERAGE(SUMPRODUCT(BE$16:BE$29,$AJ$16:$AJ$29/100))/(SUM(OFFSET($AJ$16,0,0,COUNT($AZ$16:$AZ$29)))/100),"") | BF30: {=IFERROR(100*SUMPRODUCT(IFERROR(VLOOKUP(AX16:AX29,UpdateHashtag!$C:$S,6,False),"")*AJ16:AJ29/100)/SUMPRODUCT(IFERROR(VLOOKUP(AX16:AX29,UpdateHashtag!$C:$S,17,False),"")*AJ16:AJ29/100),"")} | BG30: {=IFERROR(100*SUMPRODUCT(IFERROR(VLOOKUP(AX16:AX29,UpdateHashtag!$C:$T,8,False),"")*AJ16:AJ29/100)/SUMPRODUCT(IFERROR(VLOOKUP(AX16:AX29,UpdateHashtag!$C:$T,18,False),"")*AJ16:AJ29/100),"")} | BH30: =AVERAGE(SUMPRODUCT(BG16:BG29,$B16:$B29/100))/(SUM(OFFSET($B16,0,0,COUNT(BG16:BG29)))/100) -> #N/A
A31: =VLOOKUP($F31,UpdateHashtag!$V$3:$Y$32,COLUMN(B$9),0) -> 3 | B31: =VLOOKUP($F31,UpdateHashtag!$V$3:$Y$32,COLUMN(#REF!),0) -> #REF! | C31: =VLOOKUP($F31,UpdateHashtag!$V$3:$Y$32,COLUMN(#REF!),0) -> #REF! | D31: =SUM(A31:C31) -> #REF! | F31: =VLOOKUP(J31,UpdateBBM!$C$2:E1009,3,0) -> PHO | G31: 18 | H31: =IFERROR(__xludf.DUMMYFUNCTION("""COMPUTED_VALUE"""),18.0) -> 18 | J31: =IFERROR(__xludf.DUMMYFUNCTION("""COMPUTED_VALUE"""),"Devin Booker") -> Devin Booker | K31: =IFERROR(__xludf.DUMMYFUNCTION("""COMPUTED_VALUE"""),68.0) -> 68 | L31: =IFERROR(__xludf.DUMMYFUNCTION("""COMPUTED_VALUE"""),"G,F") -> G,F | M31: =IFERROR(__xludf.DUMMYFUNCTION("""COMPUTED_VALUE"""),4.144406288966499) -> 4.1444063 | N31: =IFERROR(__xludf.DUMMYFUNCTION("""COMPUTED_VALUE"""),4.53932015307151) -> 4.5393202 | O31: =IFERROR(__xludf.DUMMYFUNCTION("""COMPUTED_VALUE"""),0.3949138641050114) -> 0.39491386 | P31: =IFERROR(__xludf.DUMMYFUNCTION("""COMPUTED_VALUE"""),26.84118) -> 26.84118 | Q31: =IFERROR(__xludf.DUMMYFUNCTION("""COMPUTED_VALUE"""),2.306176) -> 2.306176 | R31: =IFERROR(__xludf.DUMMYFUNCTION("""COMPUTED_VALUE"""),4.752059) -> 4.752059 | S31: =IFERROR(__xludf.DUMMYFUNCTION("""COMPUTED_VALUE"""),8.093235) -> 8.093235 | T31: =IFERROR(__xludf.DUMMYFUNCTION("""COMPUTED_VALUE"""),0.891029) -> 0.891029 | U31: =IFERROR(__xludf.DUMMYFUNCTION("""COMPUTED_VALUE"""),0.297059) -> 0.297059 | V31: =IFERROR(__xludf.DUMMYFUNCTION("""COMPUTED_VALUE"""),0.476236) -> 0.476236 | W31: =IFERROR(__xludf.DUMMYFUNCTION("""COMPUTED_VALUE"""),0.895995) -> 0.895995 | X31: =IFERROR(__xludf.DUMMYFUNCTION("""COMPUTED_VALUE"""),3.341176) -> 3.341176 | Y31: =IFERROR(__xludf.DUMMYFUNCTION("""COMPUTED_VALUE"""),1.6959285902503063) -> 1.6959286 | Z31: =IFERROR(__xludf.DUMMYFUNCTION("""COMPUTED_VALUE"""),0.5182877983372415) -> 0.5182878 | AA31: =IFERROR(__xludf.DUMMYFUNCTION("""COMPUTED_VALUE"""),-0.5571328415126856) -> -0.55713284 | AB31: =IFERROR(__xludf.DUMMYFUNCTION("""COMPUTED_VALUE"""),2.079282160741089) -> 2.0792822 | AC31: =IFERROR(__xludf.DUMMYFUNCTION("""COMPUTED_VALUE"""),-0.4697570677118511) -> -0.46975707 | AD31: =IFERROR(__xludf.DUMMYFUNCTION("""COMPUTED_VALUE"""),-0.7874874236530288) -> -0.78748742 | AE31: =IFERROR(__xludf.DUMMYFUNCTION("""COMPUTED_VALUE"""),-0.27105087502285174) -> -0.27105088 | AF31: =IFERROR(__xludf.DUMMYFUNCTION("""COMPUTED_VALUE"""),1.5437623879902618) -> 1.5437624 | AG31: =IFERROR(__xludf.DUMMYFUNCTION("""COMPUTED_VALUE"""),0.0) -> 0 | AY31: ZScore | AZ31: =IFERROR((SUM(OFFSET(AJ16,0,0,COUNT(AZ16:AZ29)))/100)*(AZ30-'Final Update'!$B$1)/'Final Update'!$B$2,"") | BA31: =IFERROR((SUM(OFFSET(AJ16,0,0,COUNT(AZ16:AZ29)))/100)*(BA30-'Final Update'!$C$1)/'Final Update'!$C$2,"") | BB31: =IFERROR((SUM(OFFSET(AJ16,0,0,COUNT(AZ16:AZ29)))/100)*(BB30-'Final Update'!$D$1)/'Final Update'!$D$2,"") | BC31: =IFERROR((SUM(OFFSET(AJ16,0,0,COUNT(AZ16:AZ29)))/100)*(BC30-'Final Update'!$E$1)/'Final Update'!$E$2,"") | BD31: =IFERROR((SUM(OFFSET(AJ16,0,0,COUNT(AZ16:AZ29)))/100)*(BD30-'Final Update'!$F$1)/'Final Update'!$F$2,"") | BE31: =IFERROR((SUM(OFFSET(AJ16,0,0,COUNT(AZ16:AZ29)))/100)*(BE30-'Final Update'!$G$1)/'Final Update'!$G$2,"") | BF31: {=SUMPRODUCT(IFERROR(VLOOKUP(AX16:AX29,'Final Update'!$A$4:$L$403,8,False)*AJ16:AJ29/100,""))} -> 0 | BG31: {=SUMPRODUCT(IFERROR(VLOOKUP(AX16:AX29,'Final Update'!$A$4:$L$403,10,False)*AJ16:AJ29/100,""))} -> 0 | BH31: =-(SUM(OFFSET(AJ16,0,0,COUNT(AZ16:AZ29)))/100)*(BH30-'Final Update'!$L$1)/'Final Update'!$L$2 -> #VALUE!
A32: =VLOOKUP($F32,UpdateHashtag!$V$3:$Y$32,COLUMN(B$9),0) -> 4 | B32: =VLOOKUP($F32,UpdateHashtag!$V$3:$Y$32,COLUMN(#REF!),0) -> #REF! | C32: =VLOOKUP($F32,UpdateHashtag!$V$3:$Y$32,COLUMN(#REF!),0) -> #REF! | D32: =SUM(A32:C32) -> #REF! | F32: =VLOOKUP(J32,UpdateBBM!$C$2:E1009,3,0) -> DET | G32: 19 | H32: =IFERROR(__xludf.DUMMYFUNCTION("""COMPUTED_VALUE"""),19.0) -> 19 | J32: =IFERROR(__xludf.DUMMYFUNCTION("""COMPUTED_VALUE"""),"Cade Cunningham") -> Cade Cunningham | K32: =IFERROR(__xludf.DUMMYFUNCTION("""COMPUTED_VALUE"""),73.0) -> 73 | L32: =IFERROR(__xludf.DUMMYFUNCTION("""COMPUTED_VALUE"""),"G") -> G | M32: =IFERROR(__xludf.DUMMYFUNCTION("""COMPUTED_VALUE"""),4.027455577850566) -> 4.0274556 | N32: =IFERROR(__xludf.DUMMYFUNCTION("""COMPUTED_VALUE"""),4.551843890299321) -> 4.5518439 | O32: =IFERROR(__xludf.DUMMYFUNCTION("""COMPUTED_VALUE"""),0.524388312448755) -> 0.52438831 | P32: =IFERROR(__xludf.DUMMYFUNCTION("""COMPUTED_VALUE"""),26.39342) -> 26.39342 | Q32: =IFERROR(__xludf.DUMMYFUNCTION("""COMPUTED_VALUE"""),1.808219) -> 1.808219 | R32: =IFERROR(__xludf.DUMMYFUNCTION("""COMPUTED_VALUE"""),5.580274) -> 5.580274 | S32: =IFERROR(__xludf.DUMMYFUNCTION("""COMPUTED_VALUE"""),8.584932) -> 8.584932 | T32: =IFERROR(__xludf.DUMMYFUNCTION("""COMPUTED_VALUE"""),1.0) -> 1 | U32: =IFERROR(__xludf.DUMMYFUNCTION("""COMPUTED_VALUE"""),0.644521) -> 0.644521 | V32: =IFERROR(__xludf.DUMMYFUNCTION("""COMPUTED_VALUE"""),0.479295) -> 0.479295 | W32: =IFERROR(__xludf.DUMMYFUNCTION("""COMPUTED_VALUE"""),0.866994) -> 0.866994 | X32: =IFERROR(__xludf.DUMMYFUNCTION("""COMPUTED_VALUE"""),3.863288) -> 3.863288 | Y32: =IFERROR(__xludf.DUMMYFUNCTION("""COMPUTED_VALUE"""),1.6173724063269066) -> 1.6173724 | Z32: =IFERROR(__xludf.DUMMYFUNCTION("""COMPUTED_VALUE"""),0.03734427615824096) -> 0.037344276 | AA32: =IFERROR(__xludf.DUMMYFUNCTION("""COMPUTED_VALUE"""),-0.22141290450418874) -> -0.2214129 | AB32: =IFERROR(__xludf.DUMMYFUNCTION("""COMPUTED_VALUE"""),2.319483273413365) -> 2.3194833 | AC32: =IFERROR(__xludf.DUMMYFUNCTION("""COMPUTED_VALUE"""),-0.13769736321405063) -> -0.13769736 | AD32: =IFERROR(__xludf.DUMMYFUNCTION("""COMPUTED_VALUE"""),-0.15580420918020466) -> -0.15580421 | AE32: =IFERROR(__xludf.DUMMYFUNCTION("""COMPUTED_VALUE"""),-0.2287486511636934) -> -0.22874865 | AF32: =IFERROR(__xludf.DUMMYFUNCTION("""COMPUTED_VALUE"""),1.0925584112992535) -> 1.0925584 | AG32: =IFERROR(__xludf.DUMMYFUNCTION("""COMPUTED_VALUE"""),0.0) -> 0
A33: =VLOOKUP($F33,UpdateHashtag!$V$3:$Y$32,COLUMN(B$9),0) -> #N/A | B33: =VLOOKUP($F33,UpdateHashtag!$V$3:$Y$32,COLUMN(#REF!),0) -> #REF! | C33: =VLOOKUP($F33,UpdateHashtag!$V$3:$Y$32,COLUMN(#REF!),0) -> #REF! | D33: =SUM(A33:C33) -> #N/A | F33: =VLOOKUP(J33,UpdateBBM!$C$2:E1009,3,0) -> NOR | G33: 20 | H33: =IFERROR(__xludf.DUMMYFUNCTION("""COMPUTED_VALUE"""),20.0) -> 20 | J33: =IFERROR(__xludf.DUMMYFUNCTION("""COMPUTED_VALUE"""),"Zion Williamson") -> Zion Williamson | K33: =IFERROR(__xludf.DUMMYFUNCTION("""COMPUTED_VALUE"""),58.0) -> 58 | L33: =IFERROR(__xludf.DUMMYFUNCTION("""COMPUTED_VALUE"""),"F") -> F | M33: =IFERROR(__xludf.DUMMYFUNCTION("""COMPUTED_VALUE"""),3.9433883894009893) -> 3.9433884 | N33: =IFERROR(__xludf.DUMMYFUNCTION("""COMPUTED_VALUE"""),4.28828599279988) -> 4.288286 | O33: =IFERROR(__xludf.DUMMYFUNCTION("""COMPUTED_VALUE"""),0.3448976033988904) -> 0.3448976 | P33: =IFERROR(__xludf.DUMMYFUNCTION("""COMPUTED_VALUE"""),27.48466) -> 27.48466 | Q33: =IFERROR(__xludf.DUMMYFUNCTION("""COMPUTED_VALUE"""),0.157241) -> 0.157241 | R33: =IFERROR(__xludf.DUMMYFUNCTION("""COMPUTED_VALUE"""),7.07) -> 7.07 | S33: =IFERROR(__xludf.DUMMYFUNCTION("""COMPUTED_VALUE"""),5.992586) -> 5.992586 | T33: =IFERROR(__xludf.DUMMYFUNCTION("""COMPUTED_VALUE"""),1.212069) -> 1.212069 | U33: =IFERROR(__xludf.DUMMYFUNCTION("""COMPUTED_VALUE"""),0.875345) -> 0.875345 | V33: =IFERROR(__xludf.DUMMYFUNCTION("""COMPUTED_VALUE"""),0.578747) -> 0.578747 | W33: =IFERROR(__xludf.DUMMYFUNCTION("""COMPUTED_VALUE"""),0.679009) -> 0.679009 | X33: =IFERROR(__xludf.DUMMYFUNCTION("""COMPUTED_VALUE"""),3.139483) -> 3.139483 | Y33: =IFERROR(__xludf.DUMMYFUNCTION("""COMPUTED_VALUE"""),1.8088224021831028) -> 1.8088224 | Z33: =IFERROR(__xludf.DUMMYFUNCTION("""COMPUTED_VALUE"""),-1.5572254846043194) -> -1.5572255 | AA33: =IFERROR(__xludf.DUMMYFUNCTION("""COMPUTED_VALUE"""),0.3824529019348638) -> 0.3824529 | AB33: =IFERROR(__xludf.DUMMYFUNCTION("""COMPUTED_VALUE"""),1.0530846709579442) -> 1.0530847 | AC33: =IFERROR(__xludf.DUMMYFUNCTION("""COMPUTED_VALUE"""),0.5085256637669263) -> 0.50852566 | AD33: =IFERROR(__xludf.DUMMYFUNCTION("""COMPUTED_VALUE"""),0.2638320281564687) -> 0.26383203 | AE33: =IFERROR(__xludf.DUMMYFUNCTION("""COMPUTED_VALUE"""),1.4528042336288405) -> 1.4528042 | AF33: =IFERROR(__xludf.DUMMYFUNCTION("""COMPUTED_VALUE"""),-1.181235907828266) -> -1.1812359 | AG33: =IFERROR(__xludf.DUMMYFUNCTION("""COMPUTED_VALUE"""),0.0) -> 0
A34: =VLOOKUP($F34,UpdateHashtag!$V$3:$Y$32,COLUMN(B$9),0) -> 3 | B34: =VLOOKUP($F34,UpdateHashtag!$V$3:$Y$32,COLUMN(#REF!),0) -> #REF! | C34: =VLOOKUP($F34,UpdateHashtag!$V$3:$Y$32,COLUMN(#REF!),0) -> #REF! | D34: =SUM(A34:C34) -> #REF! | F34: =VLOOKUP(J34,UpdateBBM!$C$2:E1009,3,0) -> TOR | G34: 21 | H34: =IFERROR(__xludf.DUMMYFUNCTION("""COMPUTED_VALUE"""),21.0) -> 21 | J34: =IFERROR(__xludf.DUMMYFUNCTION("""COMPUTED_VALUE"""),"Jakob Poeltl") -> Jakob Poeltl | K34: =IFERROR(__xludf.DUMMYFUNCTION("""COMPUTED_VALUE"""),68.0) -> 68 | L34: =IFERROR(__xludf.DUMMYFUNCTION("""COMPUTED_VALUE"""),"C") -> C | M34: =IFERROR(__xludf.DUMMYFUNCTION("""COMPUTED_VALUE"""),3.8911043092258524) -> 3.8911043 | N34: =IFERROR(__xludf.DUMMYFUNCTION("""COMPUTED_VALUE"""),3.8863659492555724) -> 3.8863659 | O34: =IFERROR(__xludf.DUMMYFUNCTION("""COMPUTED_VALUE"""),-0.004738359970279937) -> -0.00473836 | P34: =IFERROR(__xludf.DUMMYFUNCTION("""COMPUTED_VALUE"""),13.36265) -> 13.36265 | Q34: =IFERROR(__xludf.DUMMYFUNCTION("""COMPUTED_VALUE"""),0.025735) -> 0.025735 | R34: =IFERROR(__xludf.DUMMYFUNCTION("""COMPUTED_VALUE"""),10.17765) -> 10.17765 | S34: =IFERROR(__xludf.DUMMYFUNCTION("""COMPUTED_VALUE"""),2.993382) -> 2.993382 | T34: =IFERROR(__xludf.DUMMYFUNCTION("""COMPUTED_VALUE"""),1.064265) -> 1.064265 | U34: =IFERROR(__xludf.DUMMYFUNCTION("""COMPUTED_VALUE"""),1.445735) -> 1.445735 | V34: =IFERROR(__xludf.DUMMYFUNCTION("""COMPUTED_VALUE"""),0.65981) -> 0.65981 | W34: =IFERROR(__xludf.DUMMYFUNCTION("""COMPUTED_VALUE"""),0.665999) -> 0.665999 | X34: =IFERROR(__xludf.DUMMYFUNCTION("""COMPUTED_VALUE"""),1.729559) -> 1.729559 | Y34: =IFERROR(__xludf.DUMMYFUNCTION("""COMPUTED_VALUE"""),-0.6687799180958036) -> -0.66877992 | Z34: =IFERROR(__xludf.DUMMYFUNCTION("""COMPUTED_VALUE"""),-1.684238376937737) -> -1.6842384 | AA34: =IFERROR(__xludf.DUMMYFUNCTION("""COMPUTED_VALUE"""),1.6421500364282682) -> 1.64215 | AB34: =IFERROR(__xludf.DUMMYFUNCTION("""COMPUTED_VALUE"""),-0.4120699627517181) -> -0.41206996 | AC34: =IFERROR(__xludf.DUMMYFUNCTION("""COMPUTED_VALUE"""),0.05813287519388493) -> 0.058132875 | AD34: =IFERROR(__xludf.DUMMYFUNCTION("""COMPUTED_VALUE"""),1.3007966133575963) -> 1.3007966 | AE34: =IFERROR(__xludf.DUMMYFUNCTION("""COMPUTED_VALUE"""),3.263007568386341) -> 3.2630076 | AF34: =IFERROR(__xludf.DUMMYFUNCTION("""COMPUTED_VALUE"""),-1.296871263262997) -> -1.2968713 | AG34: =IFERROR(__xludf.DUMMYFUNCTION("""COMPUTED_VALUE"""),0.0) -> 0
A35: =VLOOKUP($F35,UpdateHashtag!$V$3:$Y$32,COLUMN(B$9),0) -> 3 | B35: =VLOOKUP($F35,UpdateHashtag!$V$3:$Y$32,COLUMN(#REF!),0) -> #REF! | C35: =VLOOKUP($F35,UpdateHashtag!$V$3:$Y$32,COLUMN(#REF!),0) -> #REF! | D35: =SUM(A35:C35) -> #REF! | F35: =VLOOKUP(J35,UpdateBBM!$C$2:E1009,3,0) -> PHO | G35: 22 | H35: =IFERROR(__xludf.DUMMYFUNCTION("""COMPUTED_VALUE"""),22.0) -> 22 | J35: =IFERROR(__xludf.DUMMYFUNCTION("""COMPUTED_VALUE"""),"Mark Williams") -> Mark Williams | K35: =IFERROR(__xludf.DUMMYFUNCTION("""COMPUTED_VALUE"""),62.0) -> 62 | L35: =IFERROR(__xludf.DUMMYFUNCTION("""COMPUTED_VALUE"""),"C") -> C | M35: =IFERROR(__xludf.DUMMYFUNCTION("""COMPUTED_VALUE"""),3.759771074228932) -> 3.7597711 | N35: =IFERROR(__xludf.DUMMYFUNCTION("""COMPUTED_VALUE"""),3.8324963815863997) -> 3.8324964 | O35: =IFERROR(__xludf.DUMMYFUNCTION("""COMPUTED_VALUE"""),0.07272530735746763) -> 0.072725307 | P35: =IFERROR(__xludf.DUMMYFUNCTION("""COMPUTED_VALUE"""),15.2979) -> 15.2979 | Q35: =IFERROR(__xludf.DUMMYFUNCTION("""COMPUTED_VALUE"""),0.023387) -> 0.023387 | R35: =IFERROR(__xludf.DUMMYFUNCTION("""COMPUTED_VALUE"""),10.76629) -> 10.76629 | S35: =IFERROR(__xludf.DUMMYFUNCTION("""COMPUTED_VALUE"""),2.908065) -> 2.908065 | T35: =IFERROR(__xludf.DUMMYFUNCTION("""COMPUTED_VALUE"""),0.823065) -> 0.823065 | U35: =IFERROR(__xludf.DUMMYFUNCTION("""COMPUTED_VALUE"""),1.279677) -> 1.279677 | V35: =IFERROR(__xludf.DUMMYFUNCTION("""COMPUTED_VALUE"""),0.61651) -> 0.61651 | W35: =IFERROR(__xludf.DUMMYFUNCTION("""COMPUTED_VALUE"""),0.800991) -> 0.800991 | X35: =IFERROR(__xludf.DUMMYFUNCTION("""COMPUTED_VALUE"""),2.041935) -> 2.041935 | Y35: =IFERROR(__xludf.DUMMYFUNCTION("""COMPUTED_VALUE"""),-0.32925460333397066) -> -0.3292546 | Z35: =IFERROR(__xludf.DUMMYFUNCTION("""COMPUTED_VALUE"""),-1.6865061538543709) -> -1.6865062 | AA35: =IFERROR(__xludf.DUMMYFUNCTION("""COMPUTED_VALUE"""),1.8807573832170625) -> 1.8807574 | AB35: =IFERROR(__xludf.DUMMYFUNCTION("""COMPUTED_VALUE"""),-0.453748554099358) -> -0.45374855 | AC35: =IFERROR(__xludf.DUMMYFUNCTION("""COMPUTED_VALUE"""),-0.6768590100312615) -> -0.67685901 | AD35: =IFERROR(__xludf.DUMMYFUNCTION("""COMPUTED_VALUE"""),0.9989044604633855) -> 0.99890446 | AE35: =IFERROR(__xludf.DUMMYFUNCTION("""COMPUTED_VALUE"""),2.246963801519729) -> 2.2469638 | AF35: =IFERROR(__xludf.DUMMYFUNCTION("""COMPUTED_VALUE"""),0.16573290385081327) -> 0.1657329 | AG35: =IFERROR(__xludf.DUMMYFUNCTION("""COMPUTED_VALUE"""),0.0) -> 0
A36: =VLOOKUP($F36,UpdateHashtag!$V$3:$Y$32,COLUMN(B$9),0) -> 3 | B36: =VLOOKUP($F36,UpdateHashtag!$V$3:$Y$32,COLUMN(#REF!),0) -> #REF! | C36: =VLOOKUP($F36,UpdateHashtag!$V$3:$Y$32,COLUMN(#REF!),0) -> #REF! | D36: =SUM(A36:C36) -> #REF! | F36: =VLOOKUP(J36,UpdateBBM!$C$2:E1009,3,0) -> BOS | G36: 23 | H36: =IFERROR(__xludf.DUMMYFUNCTION("""COMPUTED_VALUE"""),23.0) -> 23 | J36: =IFERROR(__xludf.DUMMYFUNCTION("""COMPUTED_VALUE"""),"Derrick White") -> Derrick White | K36: =IFERROR(__xludf.DUMMYFUNCTION("""COMPUTED_VALUE"""),57.0) -> 57 | L36: =IFERROR(__xludf.DUMMYFUNCTION("""COMPUTED_VALUE"""),"G") -> G | M36: =IFERROR(__xludf.DUMMYFUNCTION("""COMPUTED_VALUE"""),3.596461694832573) -> 3.5964617 | N36: =IFERROR(__xludf.DUMMYFUNCTION("""COMPUTED_VALUE"""),3.742318669605669) -> 3.7423187 | O36: =IFERROR(__xludf.DUMMYFUNCTION("""COMPUTED_VALUE"""),0.14585697477309623) -> 0.14585697 | P36: =IFERROR(__xludf.DUMMYFUNCTION("""COMPUTED_VALUE"""),17.76579) -> 17.76579 | Q36: =IFERROR(__xludf.DUMMYFUNCTION("""COMPUTED_VALUE"""),3.402982) -> 3.402982 | R36: =IFERROR(__xludf.DUMMYFUNCTION("""COMPUTED_VALUE"""),4.744386) -> 4.744386 | S36: =IFERROR(__xludf.DUMMYFUNCTION("""COMPUTED_VALUE"""),6.939649) -> 6.939649 | T36: =IFERROR(__xludf.DUMMYFUNCTION("""COMPUTED_VALUE"""),1.056316) -> 1.056316 | U36: =IFERROR(__xludf.DUMMYFUNCTION("""COMPUTED_VALUE"""),0.920526) -> 0.920526 | V36: =IFERROR(__xludf.DUMMYFUNCTION("""COMPUTED_VALUE"""),0.429917) -> 0.429917 | W36: =IFERROR(__xludf.DUMMYFUNCTION("""COMPUTED_VALUE"""),0.842026) -> 0.842026 | X36: =IFERROR(__xludf.DUMMYFUNCTION("""COMPUTED_VALUE"""),2.336842) -> 2.336842 | Y36: =IFERROR(__xludf.DUMMYFUNCTION("""COMPUTED_VALUE"""),0.10371846425294556) -> 0.10371846 | Z36: =IFERROR(__xludf.DUMMYFUNCTION("""COMPUTED_VALUE"""),1.5776197101028382) -> 1.5776197 | AA36: =IFERROR(__xludf.DUMMYFUNCTION("""COMPUTED_VALUE"""),-0.5602431197335171) -> -0.56024312 | AB36: =IFERROR(__xludf.DUMMYFUNCTION("""COMPUTED_VALUE"""),1.5157386761089688) -> 1.5157387 | AC36: =IFERROR(__xludf.DUMMYFUNCTION("""COMPUTED_VALUE"""),0.03391044361986056) -> 0.033910444 | AD36: =IFERROR(__xludf.DUMMYFUNCTION("""COMPUTED_VALUE"""),0.3459707348728769) -> 0.34597073 | AE36: =IFERROR(__xludf.DUMMYFUNCTION("""COMPUTED_VALUE"""),-0.8428806969475443) -> -0.8428807 | AF36: =IFERROR(__xludf.DUMMYFUNCTION("""COMPUTED_VALUE"""),0.7256037603816964) -> 0.72560376 | AG36: =IFERROR(__xludf.DUMMYFUNCTION("""COMPUTED_VALUE"""),0.0) -> 0
A37: =VLOOKUP($F37,UpdateHashtag!$V$3:$Y$32,COLUMN(B$9),0) -> 2 | B37: =VLOOKUP($F37,UpdateHashtag!$V$3:$Y$32,COLUMN(#REF!),0) -> #REF! | C37: =VLOOKUP($F37,UpdateHashtag!$V$3:$Y$32,COLUMN(#REF!),0) -> #REF! | D37: =SUM(A37:C37) -> #REF! | F37: =VLOOKUP(J37,UpdateBBM!$C$2:E1009,3,0) -> CHI | G37: 24 | H37: =IFERROR(__xludf.DUMMYFUNCTION("""COMPUTED_VALUE"""),24.0) -> 24 | J37: =IFERROR(__xludf.DUMMYFUNCTION("""COMPUTED_VALUE"""),"Josh Giddey") -> Josh Giddey | K37: =IFERROR(__xludf.DUMMYFUNCTION("""COMPUTED_VALUE"""),73.0) -> 73 | L37: =IFERROR(__xludf.DUMMYFUNCTION("""COMPUTED_VALUE"""),"G") -> G | M37: =IFERROR(__xludf.DUMMYFUNCTION("""COMPUTED_VALUE"""),3.5767025539639867) -> 3.5767026 | N37: =IFERROR(__xludf.DUMMYFUNCTION("""COMPUTED_VALUE"""),4.011885245004114) -> 4.0118852 | O37: =IFERROR(__xludf.DUMMYFUNCTION("""COMPUTED_VALUE"""),0.4351826910401275) -> 0.43518269 | P37: =IFERROR(__xludf.DUMMYFUNCTION("""COMPUTED_VALUE"""),18.93918) -> 18.93918 | Q37: =IFERROR(__xludf.DUMMYFUNCTION("""COMPUTED_VALUE"""),1.564658) -> 1.564658 | R37: =IFERROR(__xludf.DUMMYFUNCTION("""COMPUTED_VALUE"""),9.295068) -> 9.295068 | S37: =IFERROR(__xludf.DUMMYFUNCTION("""COMPUTED_VALUE"""),8.508493) -> 8.508493 | T37: =IFERROR(__xludf.DUMMYFUNCTION("""COMPUTED_VALUE"""),1.143973) -> 1.143973 | U37: =IFERROR(__xludf.DUMMYFUNCTION("""COMPUTED_VALUE"""),0.713562) -> 0.713562 | V37: =IFERROR(__xludf.DUMMYFUNCTION("""COMPUTED_VALUE"""),0.472402) -> 0.472402 | W37: =IFERROR(__xludf.DUMMYFUNCTION("""COMPUTED_VALUE"""),0.792998) -> 0.792998 | X37: =IFERROR(__xludf.DUMMYFUNCTION("""COMPUTED_VALUE"""),3.503562) -> 3.503562 | Y37: =IFERROR(__xludf.DUMMYFUNCTION("""COMPUTED_VALUE"""),0.3095810706802225) -> 0.30958107 | Z37: =IFERROR(__xludf.DUMMYFUNCTION("""COMPUTED_VALUE"""),-0.19789508227118077) -> -0.19789508 | AA37: =IFERROR(__xludf.DUMMYFUNCTION("""COMPUTED_VALUE"""),1.2843922399082426) -> 1.2843922 | AB37: =IFERROR(__xludf.DUMMYFUNCTION("""COMPUTED_VALUE"""),2.2821417137708284) -> 2.2821417 | AC37: =IFERROR(__xludf.DUMMYFUNCTION("""COMPUTED_VALUE"""),0.3010214870824666) -> 0.30102149 | AD37: =IFERROR(__xludf.DUMMYFUNCTION("""COMPUTED_VALUE"""),-0.030288207975991605) -> -0.030288208 | AE37: =IFERROR(__xludf.DUMMYFUNCTION("""COMPUTED_VALUE"""),-0.32327651500706567) -> -0.32327651 | AF37: =IFERROR(__xludf.DUMMYFUNCTION("""COMPUTED_VALUE"""),0.06293202380952635) -> 0.062932024 | AG37: =IFERROR(__xludf.DUMMYFUNCTION("""COMPUTED_VALUE"""),0.0) -> 0
A38: =VLOOKUP($F38,UpdateHashtag!$V$3:$Y$32,COLUMN(B$9),0) -> 4 | B38: =VLOOKUP($F38,UpdateHashtag!$V$3:$Y$32,COLUMN(#REF!),0) -> #REF! | C38: =VLOOKUP($F38,UpdateHashtag!$V$3:$Y$32,COLUMN(#REF!),0) -> #REF! | D38: =SUM(A38:C38) -> #REF! | F38: =VLOOKUP(J38,UpdateBBM!$C$2:E1009,3,0) -> PHI | G38: 25 | H38: =IFERROR(__xludf.DUMMYFUNCTION("""COMPUTED_VALUE"""),25.0) -> 25 | J38: =IFERROR(__xludf.DUMMYFUNCTION("""COMPUTED_VALUE"""),"Joel Embiid") -> Joel Embiid | K38: =IFERROR(__xludf.DUMMYFUNCTION("""COMPUTED_VALUE"""),40.0) -> 40 | L38: =IFERROR(__xludf.DUMMYFUNCTION("""COMPUTED_VALUE"""),"C") -> C | M38: =IFERROR(__xludf.DUMMYFUNCTION("""COMPUTED_VALUE"""),3.494873778669361) -> 3.4948738 | N38: =IFERROR(__xludf.DUMMYFUNCTION("""COMPUTED_VALUE"""),3.8909219130587647) -> 3.8909219 | O38: =IFERROR(__xludf.DUMMYFUNCTION("""COMPUTED_VALUE"""),0.39604813438940356) -> 0.39604813 | P38: =IFERROR(__xludf.DUMMYFUNCTION("""COMPUTED_VALUE"""),24.878) -> 24.878 | Q38: =IFERROR(__xludf.DUMMYFUNCTION("""COMPUTED_VALUE"""),1.10175) -> 1.10175 | R38: =IFERROR(__xludf.DUMMYFUNCTION("""COMPUTED_VALUE"""),8.415) -> 8.415 | S38: =IFERROR(__xludf.DUMMYFUNCTION("""COMPUTED_VALUE"""),4.6145) -> 4.6145 | T38: =IFERROR(__xludf.DUMMYFUNCTION("""COMPUTED_VALUE"""),0.86425) -> 0.86425 | U38: =IFERROR(__xludf.DUMMYFUNCTION("""COMPUTED_VALUE"""),1.11375) -> 1.11375 | V38: =IFERROR(__xludf.DUMMYFUNCTION("""COMPUTED_VALUE"""),0.487457) -> 0.487457 | W38: =IFERROR(__xludf.DUMMYFUNCTION("""COMPUTED_VALUE"""),0.874002) -> 0.874002 | X38: =IFERROR(__xludf.DUMMYFUNCTION("""COMPUTED_VALUE"""),3.34575) -> 3.34575 | Y38: =IFERROR(__xludf.DUMMYFUNCTION("""COMPUTED_VALUE"""),1.3515031633369174) -> 1.3515032 | Z38: =IFERROR(__xludf.DUMMYFUNCTION("""COMPUTED_VALUE"""),-0.6449871082188768) -> -0.64498711 | AA38: =IFERROR(__xludf.DUMMYFUNCTION("""COMPUTED_VALUE"""),0.9276535023543536) -> 0.9276535 | AB38: =IFERROR(__xludf.DUMMYFUNCTION("""COMPUTED_VALUE"""),0.37986968173066443) -> 0.37986968 | AC38: =IFERROR(__xludf.DUMMYFUNCTION("""COMPUTED_VALUE"""),-0.5513588409060641) -> -0.55135884 | AD38: =IFERROR(__xludf.DUMMYFUNCTION("""COMPUTED_VALUE"""),0.6972504645506461) -> 0.69725046 | AE38: =IFERROR(__xludf.DUMMYFUNCTION("""COMPUTED_VALUE"""),-0.11312696705790615) -> -0.11312697 | AF38: =IFERROR(__xludf.DUMMYFUNCTION("""COMPUTED_VALUE"""),1.1991309090501532) -> 1.1991309 | AG38: =IFERROR(__xludf.DUMMYFUNCTION("""COMPUTED_VALUE"""),0.0) -> 0
A39: =VLOOKUP($F39,UpdateHashtag!$V$3:$Y$32,COLUMN(B$9),0) -> 3 | B39: =VLOOKUP($F39,UpdateHashtag!$V$3:$Y$32,COLUMN(#REF!),0) -> #REF! | C39: =VLOOKUP($F39,UpdateHashtag!$V$3:$Y$32,COLUMN(#REF!),0) -> #REF! | D39: =SUM(A39:C39) -> #REF! | F39: =VLOOKUP(J39,UpdateBBM!$C$2:E1009,3,0) -> DEN | G39: 26 | H39: =IFERROR(__xludf.DUMMYFUNCTION("""COMPUTED_VALUE"""),26.0) -> 26 | J39: =IFERROR(__xludf.DUMMYFUNCTION("""COMPUTED_VALUE"""),"Jamal Murray") -> Jamal Murray | K39: =IFERROR(__xludf.DUMMYFUNCTION("""COMPUTED_VALUE"""),68.0) -> 68 | L39: =IFERROR(__xludf.DUMMYFUNCTION("""COMPUTED_VALUE"""),"G") -> G | M39: =IFERROR(__xludf.DUMMYFUNCTION("""COMPUTED_VALUE"""),3.454701502176612) -> 3.4547015 | N39: =IFERROR(__xludf.DUMMYFUNCTION("""COMPUTED_VALUE"""),3.623732903407287) -> 3.6237329 | O39: =IFERROR(__xludf.DUMMYFUNCTION("""COMPUTED_VALUE"""),0.16903140123067528) -> 0.1690314 | P39: =IFERROR(__xludf.DUMMYFUNCTION("""COMPUTED_VALUE"""),22.03706) -> 22.03706 | Q39: =IFERROR(__xludf.DUMMYFUNCTION("""COMPUTED_VALUE"""),2.417353) -> 2.417353 | R39: =IFERROR(__xludf.DUMMYFUNCTION("""COMPUTED_VALUE"""),4.124118) -> 4.124118 | S39: =IFERROR(__xludf.DUMMYFUNCTION("""COMPUTED_VALUE"""),6.407206) -> 6.407206 | T39: =IFERROR(__xludf.DUMMYFUNCTION("""COMPUTED_VALUE"""),1.169118) -> 1.169118 | U39: =IFERROR(__xludf.DUMMYFUNCTION("""COMPUTED_VALUE"""),0.444265) -> 0.444265 | V39: =IFERROR(__xludf.DUMMYFUNCTION("""COMPUTED_VALUE"""),0.472484) -> 0.472484 | W39: =IFERROR(__xludf.DUMMYFUNCTION("""COMPUTED_VALUE"""),0.883991) -> 0.883991 | X39: =IFERROR(__xludf.DUMMYFUNCTION("""COMPUTED_VALUE"""),2.430294) -> 2.430294 | Y39: =IFERROR(__xludf.DUMMYFUNCTION("""COMPUTED_VALUE"""),0.8530812293648302) -> 0.85308123 | Z39: =IFERROR(__xludf.DUMMYFUNCTION("""COMPUTED_VALUE"""),0.6256662626731074) -> 0.62566626 | AA39: =IFERROR(__xludf.DUMMYFUNCTION("""COMPUTED_VALUE"""),-0.8116709903810982) -> -0.81167099 | AB39: =IFERROR(__xludf.DUMMYFUNCTION("""COMPUTED_VALUE"""),1.2556325517385447) -> 1.2556326 | AC39: =IFERROR(__xludf.DUMMYFUNCTION("""COMPUTED_VALUE"""),0.3776440863941849) -> 0.37764409 | AD39: =IFERROR(__xludf.DUMMYFUNCTION("""COMPUTED_VALUE"""),-0.5198680601839688) -> -0.51986806 | AE39: =IFERROR(__xludf.DUMMYFUNCTION("""COMPUTED_VALUE"""),-0.32216877687106565) -> -0.32216878 | AF39: =IFERROR(__xludf.DUMMYFUNCTION("""COMPUTED_VALUE"""),1.3537456102916543) -> 1.3537456 | AG39: =IFERROR(__xludf.DUMMYFUNCTION("""COMPUTED_VALUE"""),0.0) -> 0
A40: =VLOOKUP($F40,UpdateHashtag!$V$3:$Y$32,COLUMN(B$9),0) -> 4 | B40: =VLOOKUP($F40,UpdateHashtag!$V$3:$Y$32,COLUMN(#REF!),0) -> #REF! | C40: =VLOOKUP($F40,UpdateHashtag!$V$3:$Y$32,COLUMN(#REF!),0) -> #REF! | D40: =SUM(A40:C40) -> #REF! | F40: =VLOOKUP(J40,UpdateBBM!$C$2:E1009,3,0) -> ATL | G40: 27 | H40: =IFERROR(__xludf.DUMMYFUNCTION("""COMPUTED_VALUE"""),27.0) -> 27 | J40: =IFERROR(__xludf.DUMMYFUNCTION("""COMPUTED_VALUE"""),"Dyson Daniels") -> Dyson Daniels | K40: =IFERROR(__xludf.DUMMYFUNCTION("""COMPUTED_VALUE"""),73.0) -> 73 | L40: =IFERROR(__xludf.DUMMYFUNCTION("""COMPUTED_VALUE"""),"G,F") -> G,F | M40: =IFERROR(__xludf.DUMMYFUNCTION("""COMPUTED_VALUE"""),3.432847732301266) -> 3.4328477 | N40: =IFERROR(__xludf.DUMMYFUNCTION("""COMPUTED_VALUE"""),3.4602185951039632) -> 3.4602186 | O40: =IFERROR(__xludf.DUMMYFUNCTION("""COMPUTED_VALUE"""),0.027370862802697182) -> 0.027370863 | P40: =IFERROR(__xludf.DUMMYFUNCTION("""COMPUTED_VALUE"""),13.23932) -> 13.23932 | Q40: =IFERROR(__xludf.DUMMYFUNCTION("""COMPUTED_VALUE"""),0.888356) -> 0.888356 | R40: =IFERROR(__xludf.DUMMYFUNCTION("""COMPUTED_VALUE"""),5.791507) -> 5.791507 | S40: =IFERROR(__xludf.DUMMYFUNCTION("""COMPUTED_VALUE"""),4.433014) -> 4.433014 | T40: =IFERROR(__xludf.DUMMYFUNCTION("""COMPUTED_VALUE"""),2.573973) -> 2.573973 | U40: =IFERROR(__xludf.DUMMYFUNCTION("""COMPUTED_VALUE"""),0.645616) -> 0.645616 | V40: =IFERROR(__xludf.DUMMYFUNCTION("""COMPUTED_VALUE"""),0.517168) -> 0.517168 | W40: =IFERROR(__xludf.DUMMYFUNCTION("""COMPUTED_VALUE"""),0.615955) -> 0.615955 | X40: =IFERROR(__xludf.DUMMYFUNCTION("""COMPUTED_VALUE"""),1.859041) -> 1.859041 | Y40: =IFERROR(__xludf.DUMMYFUNCTION("""COMPUTED_VALUE"""),-0.6904172554266793) -> -0.69041726 | Z40: =IFERROR(__xludf.DUMMYFUNCTION("""COMPUTED_VALUE"""),-0.8510901692700633) -> -0.85109017 | AA40: =IFERROR(__xludf.DUMMYFUNCTION("""COMPUTED_VALUE"""),-0.1357888461931031) -> -0.13578885 | AB40: =IFERROR(__xludf.DUMMYFUNCTION("""COMPUTED_VALUE"""),0.2912111397130387) -> 0.29121114 | AC40: =IFERROR(__xludf.DUMMYFUNCTION("""COMPUTED_VALUE"""),4.6585604417755) -> 4.6585604 | AD40: =IFERROR(__xludf.DUMMYFUNCTION("""COMPUTED_VALUE"""),-0.15381350769386162) -> -0.15381351 | AE40: =IFERROR(__xludf.DUMMYFUNCTION("""COMPUTED_VALUE"""),0.34155679219913165) -> 0.34155679 | AF40: =IFERROR(__xludf.DUMMYFUNCTION("""COMPUTED_VALUE"""),-1.6913176256141311) -> -1.6913176 | AG40: =IFERROR(__xludf.DUMMYFUNCTION("""COMPUTED_VALUE"""),0.0) -> 0
A41: =VLOOKUP($F41,UpdateHashtag!$V$3:$Y$32,COLUMN(B$9),0) -> 4 | B41: =VLOOKUP($F41,UpdateHashtag!$V$3:$Y$32,COLUMN(#REF!),0) -> #REF! | C41: =VLOOKUP($F41,UpdateHashtag!$V$3:$Y$32,COLUMN(#REF!),0) -> #REF! | D41: =SUM(A41:C41) -> #REF! | F41: =VLOOKUP(J41,UpdateBBM!$C$2:E1009,3,0) -> CHA | G41: 28 | H41: =IFERROR(__xludf.DUMMYFUNCTION("""COMPUTED_VALUE"""),28.0) -> 28 | J41: =IFERROR(__xludf.DUMMYFUNCTION("""COMPUTED_VALUE"""),"Brandon Miller") -> Brandon Miller | K41: =IFERROR(__xludf.DUMMYFUNCTION("""COMPUTED_VALUE"""),64.0) -> 64 | L41: =IFERROR(__xludf.DUMMYFUNCTION("""COMPUTED_VALUE"""),"F") -> F | M41: =IFERROR(__xludf.DUMMYFUNCTION("""COMPUTED_VALUE"""),3.4259028855265443) -> 3.4259029 | N41: =IFERROR(__xludf.DUMMYFUNCTION("""COMPUTED_VALUE"""),3.626130439310011) -> 3.6261304 | O41: =IFERROR(__xludf.DUMMYFUNCTION("""COMPUTED_VALUE"""),0.20022755378346657) -> 0.20022755 | P41: =IFERROR(__xludf.DUMMYFUNCTION("""COMPUTED_VALUE"""),22.05984) -> 22.05984 | Q41: =IFERROR(__xludf.DUMMYFUNCTION("""COMPUTED_VALUE"""),3.9725) -> 3.9725 | R41: =IFERROR(__xludf.DUMMYFUNCTION("""COMPUTED_VALUE"""),4.958281) -> 4.958281 | S41: =IFERROR(__xludf.DUMMYFUNCTION("""COMPUTED_VALUE"""),3.966719) -> 3.966719 | T41: =IFERROR(__xludf.DUMMYFUNCTION("""COMPUTED_VALUE"""),1.058281) -> 1.058281 | U41: =IFERROR(__xludf.DUMMYFUNCTION("""COMPUTED_VALUE"""),0.710313) -> 0.710313 | V41: =IFERROR(__xludf.DUMMYFUNCTION("""COMPUTED_VALUE"""),0.420572) -> 0.420572 | W41: =IFERROR(__xludf.DUMMYFUNCTION("""COMPUTED_VALUE"""),0.864019) -> 0.864019 | X41: =IFERROR(__xludf.DUMMYFUNCTION("""COMPUTED_VALUE"""),2.556094) -> 2.556094 | Y41: =IFERROR(__xludf.DUMMYFUNCTION("""COMPUTED_VALUE"""),0.8570778120648819) -> 0.85707781 | Z41: =IFERROR(__xludf.DUMMYFUNCTION("""COMPUTED_VALUE"""),2.127679239066865) -> 2.1276792 | AA41: =IFERROR(__xludf.DUMMYFUNCTION("""COMPUTED_VALUE"""),-0.47354001012256786) -> -0.47354001 | AB41: =IFERROR(__xludf.DUMMYFUNCTION("""COMPUTED_VALUE"""),0.06341927229566825) -> 0.063419272 | AC41: =IFERROR(__xludf.DUMMYFUNCTION("""COMPUTED_VALUE"""),0.039898250645015655) -> 0.039898251 | AD41: =IFERROR(__xludf.DUMMYFUNCTION("""COMPUTED_VALUE"""),-0.036194864714922025) -> -0.036194865 | AE41: =IFERROR(__xludf.DUMMYFUNCTION("""COMPUTED_VALUE"""),-0.9426230059093429) -> -0.94262301 | AF41: =IFERROR(__xludf.DUMMYFUNCTION("""COMPUTED_VALUE"""),1.0477907400750697) -> 1.0477907 | AG41: =IFERROR(__xludf.DUMMYFUNCTION("""COMPUTED_VALUE"""),0.0) -> 0
A42: =VLOOKUP($F42,UpdateHashtag!$V$3:$Y$32,COLUMN(B$9),0) -> #N/A | B42: =VLOOKUP($F42,UpdateHashtag!$V$3:$Y$32,COLUMN(#REF!),0) -> #REF! | C42: =VLOOKUP($F42,UpdateHashtag!$V$3:$Y$32,COLUMN(#REF!),0) -> #REF! | D42: =SUM(A42:C42) -> #N/A | F42: =VLOOKUP(J42,UpdateBBM!$C$2:E1009,3,0) -> NYK | G42: 29 | H42: =IFERROR(__xludf.DUMMYFUNCTION("""COMPUTED_VALUE"""),29.0) -> 29 | J42: =IFERROR(__xludf.DUMMYFUNCTION("""COMPUTED_VALUE"""),"Karl-Anthony Towns") -> Karl-Anthony Towns | K42: =IFERROR(__xludf.DUMMYFUNCTION("""COMPUTED_VALUE"""),68.0) -> 68 | L42: =IFERROR(__xludf.DUMMYFUNCTION("""COMPUTED_VALUE"""),"C") -> C | M42: =IFERROR(__xludf.DUMMYFUNCTION("""COMPUTED_VALUE"""),3.416527446359273) -> 3.4165274 | N42: =IFERROR(__xludf.DUMMYFUNCTION("""COMPUTED_VALUE"""),3.7306648497982797) -> 3.7306649 | O42: =IFERROR(__xludf.DUMMYFUNCTION("""COMPUTED_VALUE"""),0.31413740343900676) -> 0.3141374 | P42: =IFERROR(__xludf.DUMMYFUNCTION("""COMPUTED_VALUE"""),23.65838) -> 23.65838 | Q42: =IFERROR(__xludf.DUMMYFUNCTION("""COMPUTED_VALUE"""),2.223676) -> 2.223676 | R42: =IFERROR(__xludf.DUMMYFUNCTION("""COMPUTED_VALUE"""),10.51882) -> 10.51882 | S42: =IFERROR(__xludf.DUMMYFUNCTION("""COMPUTED_VALUE"""),3.506176) -> 3.506176 | T42: =IFERROR(__xludf.DUMMYFUNCTION("""COMPUTED_VALUE"""),0.905294) -> 0.905294 | U42: =IFERROR(__xludf.DUMMYFUNCTION("""COMPUTED_VALUE"""),0.563676) -> 0.563676 | V42: =IFERROR(__xludf.DUMMYFUNCTION("""COMPUTED_VALUE"""),0.513486) -> 0.513486 | W42: =IFERROR(__xludf.DUMMYFUNCTION("""COMPUTED_VALUE"""),0.83001) -> 0.83001 | X42: =IFERROR(__xludf.DUMMYFUNCTION("""COMPUTED_VALUE"""),3.015441) -> 3.015441 | Y42: =IFERROR(__xludf.DUMMYFUNCTION("""COMPUTED_VALUE"""),1.1375298449595366) -> 1.1375298 | Z42: =IFERROR(__xludf.DUMMYFUNCTION("""COMPUTED_VALUE"""),0.4386065395543197) -> 0.43860654 | AA42: =IFERROR(__xludf.DUMMYFUNCTION("""COMPUTED_VALUE"""),1.7804445262759392) -> 1.7804445 | AB42: =IFERROR(__xludf.DUMMYFUNCTION("""COMPUTED_VALUE"""),-0.16156265973448) -> -0.16156266 | AC42: =IFERROR(__xludf.DUMMYFUNCTION("""COMPUTED_VALUE"""),-0.42628833121625914) -> -0.42628833 | AD42: =IFERROR(__xludf.DUMMYFUNCTION("""COMPUTED_VALUE"""),-0.3027797906079738) -> -0.30277979 | AE42: =IFERROR(__xludf.DUMMYFUNCTION("""COMPUTED_VALUE"""),0.28233014483782864) -> 0.28233014 | AF42: =IFERROR(__xludf.DUMMYFUNCTION("""COMPUTED_VALUE"""),0.556096244513109) -> 0.55609624 | AG42: =IFERROR(__xludf.DUMMYFUNCTION("""COMPUTED_VALUE"""),0.0) -> 0
A43: =VLOOKUP($F43,UpdateHashtag!$V$3:$Y$32,COLUMN(B$9),0) -> 4 | B43: =VLOOKUP($F43,UpdateHashtag!$V$3:$Y$32,COLUMN(#REF!),0) -> #REF! | C43: =VLOOKUP($F43,UpdateHashtag!$V$3:$Y$32,COLUMN(#REF!),0) -> #REF! | D43: =SUM(A43:C43) -> #REF! | F43: =VLOOKUP(J43,UpdateBBM!$C$2:E1009,3,0) -> MEM | G43: 30 | H43: =IFERROR(__xludf.DUMMYFUNCTION("""COMPUTED_VALUE"""),30.0) -> 30 | J43: =IFERROR(__xludf.DUMMYFUNCTION("""COMPUTED_VALUE"""),"Ja Morant") -> Ja Morant | K43: =IFERROR(__xludf.DUMMYFUNCTION("""COMPUTED_VALUE"""),60.0) -> 60 | L43: =IFERROR(__xludf.DUMMYFUNCTION("""COMPUTED_VALUE"""),"G") -> G | M43: =IFERROR(__xludf.DUMMYFUNCTION("""COMPUTED_VALUE"""),3.3451789310669007) -> 3.3451789 | N43: =IFERROR(__xludf.DUMMYFUNCTION("""COMPUTED_VALUE"""),3.8299012611501415) -> 3.8299013 | O43: =IFERROR(__xludf.DUMMYFUNCTION("""COMPUTED_VALUE"""),0.48472233008324084) -> 0.48472233 | P43: =IFERROR(__xludf.DUMMYFUNCTION("""COMPUTED_VALUE"""),27.12117) -> 27.12117 | Q43: =IFERROR(__xludf.DUMMYFUNCTION("""COMPUTED_VALUE"""),2.123333) -> 2.123333 | R43: =IFERROR(__xludf.DUMMYFUNCTION("""COMPUTED_VALUE"""),5.148) -> 5.148 | S43: =IFERROR(__xludf.DUMMYFUNCTION("""COMPUTED_VALUE"""),7.7935) -> 7.7935 | T43: =IFERROR(__xludf.DUMMYFUNCTION("""COMPUTED_VALUE"""),1.144) -> 1.144 | U43: =IFERROR(__xludf.DUMMYFUNCTION("""COMPUTED_VALUE"""),0.284667) -> 0.284667 | V43: =IFERROR(__xludf.DUMMYFUNCTION("""COMPUTED_VALUE"""),0.469307) -> 0.469307 | W43: =IFERROR(__xludf.DUMMYFUNCTION("""COMPUTED_VALUE"""),0.808988) -> 0.808988 | X43: =IFERROR(__xludf.DUMMYFUNCTION("""COMPUTED_VALUE"""),3.703333) -> 3.703333 | Y43: =IFERROR(__xludf.DUMMYFUNCTION("""COMPUTED_VALUE"""),1.7450507671681024) -> 1.7450508 | Z43: =IFERROR(__xludf.DUMMYFUNCTION("""COMPUTED_VALUE"""),0.3416919147051711) -> 0.34169191 | AA43: =IFERROR(__xludf.DUMMYFUNCTION("""COMPUTED_VALUE"""),-0.3966367292965568) -> -0.39663673 | AB43: =IFERROR(__xludf.DUMMYFUNCTION("""COMPUTED_VALUE"""),1.9328572679578822) -> 1.9328573 | AC43: =IFERROR(__xludf.DUMMYFUNCTION("""COMPUTED_VALUE"""),0.3011037622934993) -> 0.30110376 | AD43: =IFERROR(__xludf.DUMMYFUNCTION("""COMPUTED_VALUE"""),-0.8100159833048678) -> -0.81001598 | AE43: =IFERROR(__xludf.DUMMYFUNCTION("""COMPUTED_VALUE"""),-0.3647914993061033) -> -0.3647915 | AF43: =IFERROR(__xludf.DUMMYFUNCTION("""COMPUTED_VALUE"""),0.27062577762814677) -> 0.27062578 | AG43: =IFERROR(__xludf.DUMMYFUNCTION("""COMPUTED_VALUE"""),0.0) -> 0
A44: =VLOOKUP($F44,UpdateHashtag!$V$3:$Y$32,COLUMN(B$9),0) -> 4 | B44: =VLOOKUP($F44,UpdateHashtag!$V$3:$Y$32,COLUMN(#REF!),0) -> #REF! | C44: =VLOOKUP($F44,UpdateHashtag!$V$3:$Y$32,COLUMN(#REF!),0) -> #REF! | D44: =SUM(A44:C44) -> #REF! | F44: =VLOOKUP(J44,UpdateBBM!$C$2:E1009,3,0) -> ATL | G44: 31 | H44: =IFERROR(__xludf.DUMMYFUNCTION("""COMPUTED_VALUE"""),31.0) -> 31 | J44: =IFERROR(__xludf.DUMMYFUNCTION("""COMPUTED_VALUE"""),"Kristaps Porzingis") -> Kristaps Porzingis | K44: =IFERROR(__xludf.DUMMYFUNCTION("""COMPUTED_VALUE"""),55.0) -> 55 | L44: =IFERROR(__xludf.DUMMYFUNCTION("""COMPUTED_VALUE"""),"C") -> C | M44: =IFERROR(__xludf.DUMMYFUNCTION("""COMPUTED_VALUE"""),3.2821345453158175) -> 3.2821345 | N44: =IFERROR(__xludf.DUMMYFUNCTION("""COMPUTED_VALUE"""),3.1912980280675853) -> 3.191298 | O44: =IFERROR(__xludf.DUMMYFUNCTION("""COMPUTED_VALUE"""),-0.09083651724823216) -> -0.090836517 | P44: =IFERROR(__xludf.DUMMYFUNCTION("""COMPUTED_VALUE"""),21.42764) -> 21.42764 | Q44: =IFERROR(__xludf.DUMMYFUNCTION("""COMPUTED_VALUE"""),2.510909) -> 2.510909 | R44: =IFERROR(__xludf.DUMMYFUNCTION("""COMPUTED_VALUE"""),7.54) -> 7.54 | S44: =IFERROR(__xludf.DUMMYFUNCTION("""COMPUTED_VALUE"""),2.136364) -> 2.136364 | T44: =IFERROR(__xludf.DUMMYFUNCTION("""COMPUTED_VALUE"""),0.762545) -> 0.762545 | U44: =IFERROR(__xludf.DUMMYFUNCTION("""COMPUTED_VALUE"""),1.633636) -> 1.633636 | V44: =IFERROR(__xludf.DUMMYFUNCTION("""COMPUTED_VALUE"""),0.470257) -> 0.470257 | W44: =IFERROR(__xludf.DUMMYFUNCTION("""COMPUTED_VALUE"""),0.839992) -> 0.839992 | X44: =IFERROR(__xludf.DUMMYFUNCTION("""COMPUTED_VALUE"""),1.382364) -> 1.382364 | Y44: =IFERROR(__xludf.DUMMYFUNCTION("""COMPUTED_VALUE"""),0.7461629927947973) -> 0.74616299 | Z44: =IFERROR(__xludf.DUMMYFUNCTION("""COMPUTED_VALUE"""),0.7160257759663808) -> 0.71602578 | AA44: =IFERROR(__xludf.DUMMYFUNCTION("""COMPUTED_VALUE"""),0.5729690968769904) -> 0.5729691 | AB44: =IFERROR(__xludf.DUMMYFUNCTION("""COMPUTED_VALUE"""),-0.8307356800128938) -> -0.83073568 | AC44: =IFERROR(__xludf.DUMMYFUNCTION("""COMPUTED_VALUE"""),-0.8612773719459625) -> -0.86127737 | AD44: =IFERROR(__xludf.DUMMYFUNCTION("""COMPUTED_VALUE"""),1.6423991704218457) -> 1.6423992 | AE44: =IFERROR(__xludf.DUMMYFUNCTION("""COMPUTED_VALUE"""),-0.3521098259748993) -> -0.35210983 | AF44: =IFERROR(__xludf.DUMMYFUNCTION("""COMPUTED_VALUE"""),0.6965864979953642) -> 0.6965865 | AG44: =IFERROR(__xludf.DUMMYFUNCTION("""COMPUTED_VALUE"""),0.0) -> 0
A45: =VLOOKUP($F45,UpdateHashtag!$V$3:$Y$32,COLUMN(B$9),0) -> 4 | B45: =VLOOKUP($F45,UpdateHashtag!$V$3:$Y$32,COLUMN(#REF!),0) -> #REF! | C45: =VLOOKUP($F45,UpdateHashtag!$V$3:$Y$32,COLUMN(#REF!),0) -> #REF! | D45: =SUM(A45:C45) -> #REF! | F45: =VLOOKUP(J45,UpdateBBM!$C$2:E1009,3,0) -> MIN | G45: 32 | H45: =IFERROR(__xludf.DUMMYFUNCTION("""COMPUTED_VALUE"""),32.0) -> 32 | J45: =IFERROR(__xludf.DUMMYFUNCTION("""COMPUTED_VALUE"""),"Rudy Gobert") -> Rudy Gobert | K45: =IFERROR(__xludf.DUMMYFUNCTION("""COMPUTED_VALUE"""),73.0) -> 73 | L45: =IFERROR(__xludf.DUMMYFUNCTION("""COMPUTED_VALUE"""),"C") -> C | M45: =IFERROR(__xludf.DUMMYFUNCTION("""COMPUTED_VALUE"""),3.278584080343165) -> 3.2785841 | N45: =IFERROR(__xludf.DUMMYFUNCTION("""COMPUTED_VALUE"""),3.090448300772013) -> 3.0904483 | O45: =IFERROR(__xludf.DUMMYFUNCTION("""COMPUTED_VALUE"""),-0.18813577957115202) -> -0.18813578 | P45: =IFERROR(__xludf.DUMMYFUNCTION("""COMPUTED_VALUE"""),12.37959) -> 12.37959 | Q45: =IFERROR(__xludf.DUMMYFUNCTION("""COMPUTED_VALUE"""),0.0) -> 0 | R45: =IFERROR(__xludf.DUMMYFUNCTION("""COMPUTED_VALUE"""),11.41795) -> 11.41795 | S45: =IFERROR(__xludf.DUMMYFUNCTION("""COMPUTED_VALUE"""),1.517945) -> 1.517945 | T45: =IFERROR(__xludf.DUMMYFUNCTION("""COMPUTED_VALUE"""),0.853699) -> 0.853699 | U45: =IFERROR(__xludf.DUMMYFUNCTION("""COMPUTED_VALUE"""),1.253973) -> 1.253973 | V45: =IFERROR(__xludf.DUMMYFUNCTION("""COMPUTED_VALUE"""),0.679039) -> 0.679039 | W45: =IFERROR(__xludf.DUMMYFUNCTION("""COMPUTED_VALUE"""),0.677008) -> 0.677008 | X45: =IFERROR(__xludf.DUMMYFUNCTION("""COMPUTED_VALUE"""),0.99) -> 0.99 | Y45: =IFERROR(__xludf.DUMMYFUNCTION("""COMPUTED_VALUE"""),-0.8412505321920535) -> -0.84125053 | Z45: =IFERROR(__xludf.DUMMYFUNCTION("""COMPUTED_VALUE"""),-1.7090941005108098) -> -1.7090941 | AA45: =IFERROR(__xludf.DUMMYFUNCTION("""COMPUTED_VALUE"""),2.1449101142723523) -> 2.1449101 | AB45: =IFERROR(__xludf.DUMMYFUNCTION("""COMPUTED_VALUE"""),-1.1328423267845356) -> -1.1328423 | AC45: =IFERROR(__xludf.DUMMYFUNCTION("""COMPUTED_VALUE"""),-0.5835101650396068) -> -0.58351016 | AD45: =IFERROR(__xludf.DUMMYFUNCTION("""COMPUTED_VALUE"""),0.9521747883127346) -> 0.95217479 | AE45: =IFERROR(__xludf.DUMMYFUNCTION("""COMPUTED_VALUE"""),3.7503391319068333) -> 3.7503391 | AF45: =IFERROR(__xludf.DUMMYFUNCTION("""COMPUTED_VALUE"""),-1.1993727097037112) -> -1.1993727 | AG45: =IFERROR(__xludf.DUMMYFUNCTION("""COMPUTED_VALUE"""),0.0) -> 0
A46: =VLOOKUP($F46,UpdateHashtag!$V$3:$Y$32,COLUMN(B$9),0) -> 4 | B46: =VLOOKUP($F46,UpdateHashtag!$V$3:$Y$32,COLUMN(#REF!),0) -> #REF! | C46: =VLOOKUP($F46,UpdateHashtag!$V$3:$Y$32,COLUMN(#REF!),0) -> #REF! | D46: =SUM(A46:C46) -> #REF! | F46: =VLOOKUP(J46,UpdateBBM!$C$2:E1009,3,0) -> MEM | G46: 33 | H46: =IFERROR(__xludf.DUMMYFUNCTION("""COMPUTED_VALUE"""),33.0) -> 33 | J46: =IFERROR(__xludf.DUMMYFUNCTION("""COMPUTED_VALUE"""),"Jaren Jackson Jr.") -> Jaren Jackson Jr. | K46: =IFERROR(__xludf.DUMMYFUNCTION("""COMPUTED_VALUE"""),62.0) -> 62 | L46: =IFERROR(__xludf.DUMMYFUNCTION("""COMPUTED_VALUE"""),"F,C") -> F,C | M46: =IFERROR(__xludf.DUMMYFUNCTION("""COMPUTED_VALUE"""),3.2167988930686735) -> 3.2167989 | N46: =IFERROR(__xludf.DUMMYFUNCTION("""COMPUTED_VALUE"""),3.1958110077539836) -> 3.195811 | O46: =IFERROR(__xludf.DUMMYFUNCTION("""COMPUTED_VALUE"""),-0.02098788531468987) -> -0.020987885 | P46: =IFERROR(__xludf.DUMMYFUNCTION("""COMPUTED_VALUE"""),23.20919) -> 23.20919 | Q46: =IFERROR(__xludf.DUMMYFUNCTION("""COMPUTED_VALUE"""),2.403871) -> 2.403871 | R46: =IFERROR(__xludf.DUMMYFUNCTION("""COMPUTED_VALUE"""),6.170645) -> 6.170645 | S46: =IFERROR(__xludf.DUMMYFUNCTION("""COMPUTED_VALUE"""),1.733387) -> 1.733387 | T46: =IFERROR(__xludf.DUMMYFUNCTION("""COMPUTED_VALUE"""),1.191129) -> 1.191129 | U46: =IFERROR(__xludf.DUMMYFUNCTION("""COMPUTED_VALUE"""),1.514516) -> 1.514516 | V46: =IFERROR(__xludf.DUMMYFUNCTION("""COMPUTED_VALUE"""),0.473105) -> 0.473105 | W46: =IFERROR(__xludf.DUMMYFUNCTION("""COMPUTED_VALUE"""),0.784009) -> 0.784009 | X46: =IFERROR(__xludf.DUMMYFUNCTION("""COMPUTED_VALUE"""),1.664032) -> 1.664032 | Y46: =IFERROR(__xludf.DUMMYFUNCTION("""COMPUTED_VALUE"""),1.058722778101059) -> 1.0587228 | Z46: =IFERROR(__xludf.DUMMYFUNCTION("""COMPUTED_VALUE"""),0.6126448962378185) -> 0.6126449 | AA46: =IFERROR(__xludf.DUMMYFUNCTION("""COMPUTED_VALUE"""),0.017896109377041745) -> 0.017896109 | AB46: =IFERROR(__xludf.DUMMYFUNCTION("""COMPUTED_VALUE"""),-1.0275957865039556) -> -1.0275958 | AC46: =IFERROR(__xludf.DUMMYFUNCTION("""COMPUTED_VALUE"""),0.4447166667660369) -> 0.44471667 | AD46: =IFERROR(__xludf.DUMMYFUNCTION("""COMPUTED_VALUE"""),1.4258399365833168) -> 1.4258399 | AE46: =IFERROR(__xludf.DUMMYFUNCTION("""COMPUTED_VALUE"""),-0.3137665725742191) -> -0.31376657 | AF46: =IFERROR(__xludf.DUMMYFUNCTION("""COMPUTED_VALUE"""),-0.05024280673707034) -> -0.050242807 | AG46: =IFERROR(__xludf.DUMMYFUNCTION("""COMPUTED_VALUE"""),0.0) -> 0
A47: =VLOOKUP($F47,UpdateHashtag!$V$3:$Y$32,COLUMN(B$9),0) -> 4 | B47: =VLOOKUP($F47,UpdateHashtag!$V$3:$Y$32,COLUMN(#REF!),0) -> #REF! | C47: =VLOOKUP($F47,UpdateHashtag!$V$3:$Y$32,COLUMN(#REF!),0) -> #REF! | D47: =SUM(A47:C47) -> #REF! | F47: =VLOOKUP(J47,UpdateBBM!$C$2:E1009,3,0) -> CLE | G47: 34 | H47: =IFERROR(__xludf.DUMMYFUNCTION("""COMPUTED_VALUE"""),34.0) -> 34 | J47: =IFERROR(__xludf.DUMMYFUNCTION("""COMPUTED_VALUE"""),"Evan Mobley") -> Evan Mobley | K47: =IFERROR(__xludf.DUMMYFUNCTION("""COMPUTED_VALUE"""),73.0) -> 73 | L47: =IFERROR(__xludf.DUMMYFUNCTION("""COMPUTED_VALUE"""),"F,C") -> F,C | M47: =IFERROR(__xludf.DUMMYFUNCTION("""COMPUTED_VALUE"""),3.1736384988155177) -> 3.1736385 | N47: =IFERROR(__xludf.DUMMYFUNCTION("""COMPUTED_VALUE"""),3.2577734641932876) -> 3.2577735 | O47: =IFERROR(__xludf.DUMMYFUNCTION("""COMPUTED_VALUE"""),0.08413496537776988) -> 0.084134965 | P47: =IFERROR(__xludf.DUMMYFUNCTION("""COMPUTED_VALUE"""),19.13356) -> 19.13356 | Q47: =IFERROR(__xludf.DUMMYFUNCTION("""COMPUTED_VALUE"""),1.494247) -> 1.494247 | R47: =IFERROR(__xludf.DUMMYFUNCTION("""COMPUTED_VALUE"""),9.58863) -> 9.58863 | S47: =IFERROR(__xludf.DUMMYFUNCTION("""COMPUTED_VALUE"""),3.587671) -> 3.587671 | T47: =IFERROR(__xludf.DUMMYFUNCTION("""COMPUTED_VALUE"""),0.847534) -> 0.847534 | U47: =IFERROR(__xludf.DUMMYFUNCTION("""COMPUTED_VALUE"""),1.696575) -> 1.696575 | V47: =IFERROR(__xludf.DUMMYFUNCTION("""COMPUTED_VALUE"""),0.540956) -> 0.540956 | W47: =IFERROR(__xludf.DUMMYFUNCTION("""COMPUTED_VALUE"""),0.694007) -> 0.694007 | X47: =IFERROR(__xludf.DUMMYFUNCTION("""COMPUTED_VALUE"""),2.087945) -> 2.087945 | Y47: =IFERROR(__xludf.DUMMYFUNCTION("""COMPUTED_VALUE"""),0.34368360558961647) -> 0.34368361 | Z47: =IFERROR(__xludf.DUMMYFUNCTION("""COMPUTED_VALUE"""),-0.2659003806004454) -> -0.26590038 | AA47: =IFERROR(__xludf.DUMMYFUNCTION("""COMPUTED_VALUE"""),1.4033886552690948) -> 1.4033887 | AB47: =IFERROR(__xludf.DUMMYFUNCTION("""COMPUTED_VALUE"""),-0.12175117079469175) -> -0.12175117 | AC47: =IFERROR(__xludf.DUMMYFUNCTION("""COMPUTED_VALUE"""),-0.6022963382253989) -> -0.60229634 | AD47: =IFERROR(__xludf.DUMMYFUNCTION("""COMPUTED_VALUE"""),1.7568217830692863) -> 1.7568218 | AE47: =IFERROR(__xludf.DUMMYFUNCTION("""COMPUTED_VALUE"""),0.7438273098858259) -> 0.74382731 | AF47: =IFERROR(__xludf.DUMMYFUNCTION("""COMPUTED_VALUE"""),-1.0412275593667863) -> -1.0412276 | AG47: =IFERROR(__xludf.DUMMYFUNCTION("""COMPUTED_VALUE"""),0.0) -> 0
A48: =VLOOKUP($F48,UpdateHashtag!$V$3:$Y$32,COLUMN(B$9),0) -> 3 | B48: =VLOOKUP($F48,UpdateHashtag!$V$3:$Y$32,COLUMN(#REF!),0) -> #REF! | C48: =VLOOKUP($F48,UpdateHashtag!$V$3:$Y$32,COLUMN(#REF!),0) -> #REF! | D48: =SUM(A48:C48) -> #REF! | F48: =VLOOKUP(J48,UpdateBBM!$C$2:E1009,3,0) -> TOR | G48: 35 | H48: =IFERROR(__xludf.DUMMYFUNCTION("""COMPUTED_VALUE"""),35.0) -> 35 | J48: =IFERROR(__xludf.DUMMYFUNCTION("""COMPUTED_VALUE"""),"Scottie Barnes") -> Scottie Barnes | K48: =IFERROR(__xludf.DUMMYFUNCTION("""COMPUTED_VALUE"""),64.0) -> 64 | L48: =IFERROR(__xludf.DUMMYFUNCTION("""COMPUTED_VALUE"""),"F") -> F | M48: =IFERROR(__xludf.DUMMYFUNCTION("""COMPUTED_VALUE"""),3.148091343392539) -> 3.1480913 | N48: =IFERROR(__xludf.DUMMYFUNCTION("""COMPUTED_VALUE"""),3.4311216198651335) -> 3.4311216 | O48: =IFERROR(__xludf.DUMMYFUNCTION("""COMPUTED_VALUE"""),0.2830302764725947) -> 0.28303028 | P48: =IFERROR(__xludf.DUMMYFUNCTION("""COMPUTED_VALUE"""),20.02125) -> 20.02125 | Q48: =IFERROR(__xludf.DUMMYFUNCTION("""COMPUTED_VALUE"""),1.262188) -> 1.262188 | R48: =IFERROR(__xludf.DUMMYFUNCTION("""COMPUTED_VALUE"""),8.486719) -> 8.486719 | S48: =IFERROR(__xludf.DUMMYFUNCTION("""COMPUTED_VALUE"""),6.008281) -> 6.008281 | T48: =IFERROR(__xludf.DUMMYFUNCTION("""COMPUTED_VALUE"""),1.427031) -> 1.427031 | U48: =IFERROR(__xludf.DUMMYFUNCTION("""COMPUTED_VALUE"""),1.10875) -> 1.10875 | V48: =IFERROR(__xludf.DUMMYFUNCTION("""COMPUTED_VALUE"""),0.462938) -> 0.462938 | W48: =IFERROR(__xludf.DUMMYFUNCTION("""COMPUTED_VALUE"""),0.746995) -> 0.746995 | X48: =IFERROR(__xludf.DUMMYFUNCTION("""COMPUTED_VALUE"""),2.89) -> 2.89 | Y48: =IFERROR(__xludf.DUMMYFUNCTION("""COMPUTED_VALUE"""),0.49942225778490457) -> 0.49942226 | Z48: =IFERROR(__xludf.DUMMYFUNCTION("""COMPUTED_VALUE"""),-0.49003072280536814) -> -0.49003072 | AA48: =IFERROR(__xludf.DUMMYFUNCTION("""COMPUTED_VALUE"""),0.956725057641704) -> 0.95672506 | AB48: =IFERROR(__xludf.DUMMYFUNCTION("""COMPUTED_VALUE"""),1.0607519059896635) -> 1.0607519 | AC48: =IFERROR(__xludf.DUMMYFUNCTION("""COMPUTED_VALUE"""),1.163564327248551) -> 1.1635643 | AD48: =IFERROR(__xludf.DUMMYFUNCTION("""COMPUTED_VALUE"""),0.6881605034257916) -> 0.6881605 | AE48: =IFERROR(__xludf.DUMMYFUNCTION("""COMPUTED_VALUE"""),-0.4484118103684189) -> -0.44841181 | AF48: =IFERROR(__xludf.DUMMYFUNCTION("""COMPUTED_VALUE"""),-0.48909062185706226) -> -0.48909062 | AG48: =IFERROR(__xludf.DUMMYFUNCTION("""COMPUTED_VALUE"""),0.0) -> 0
A49: =VLOOKUP($F49,UpdateHashtag!$V$3:$Y$32,COLUMN(B$9),0) -> 4 | B49: =VLOOKUP($F49,UpdateHashtag!$V$3:$Y$32,COLUMN(#REF!),0) -> #REF! | C49: =VLOOKUP($F49,UpdateHashtag!$V$3:$Y$32,COLUMN(#REF!),0) -> #REF! | D49: =SUM(A49:C49) -> #REF! | F49: =VLOOKUP(J49,UpdateBBM!$C$2:E1009,3,0) -> ATL | G49: 36 | H49: =IFERROR(__xludf.DUMMYFUNCTION("""COMPUTED_VALUE"""),36.0) -> 36 | J49: =IFERROR(__xludf.DUMMYFUNCTION("""COMPUTED_VALUE"""),"Jalen Johnson") -> Jalen Johnson | K49: =IFERROR(__xludf.DUMMYFUNCTION("""COMPUTED_VALUE"""),68.0) -> 68 | L49: =IFERROR(__xludf.DUMMYFUNCTION("""COMPUTED_VALUE"""),"F") -> F | M49: =IFERROR(__xludf.DUMMYFUNCTION("""COMPUTED_VALUE"""),3.1277998924942625) -> 3.1277999 | N49: =IFERROR(__xludf.DUMMYFUNCTION("""COMPUTED_VALUE"""),3.3899704077551265) -> 3.3899704 | O49: =IFERROR(__xludf.DUMMYFUNCTION("""COMPUTED_VALUE"""),0.262170515260864) -> 0.26217052 | P49: =IFERROR(__xludf.DUMMYFUNCTION("""COMPUTED_VALUE"""),19.61265) -> 19.61265 | Q49: =IFERROR(__xludf.DUMMYFUNCTION("""COMPUTED_VALUE"""),1.142059) -> 1.142059 | R49: =IFERROR(__xludf.DUMMYFUNCTION("""COMPUTED_VALUE"""),9.251618) -> 9.251618 | S49: =IFERROR(__xludf.DUMMYFUNCTION("""COMPUTED_VALUE"""),5.156618) -> 5.156618 | T49: =IFERROR(__xludf.DUMMYFUNCTION("""COMPUTED_VALUE"""),1.372206) -> 1.372206 | U49: =IFERROR(__xludf.DUMMYFUNCTION("""COMPUTED_VALUE"""),0.834118) -> 0.834118 | V49: =IFERROR(__xludf.DUMMYFUNCTION("""COMPUTED_VALUE"""),0.51443) -> 0.51443 | W49: =IFERROR(__xludf.DUMMYFUNCTION("""COMPUTED_VALUE"""),0.752021) -> 0.752021 | X49: =IFERROR(__xludf.DUMMYFUNCTION("""COMPUTED_VALUE"""),2.805882) -> 2.805882 | Y49: =IFERROR(__xludf.DUMMYFUNCTION("""COMPUTED_VALUE"""),0.42773640654517586) -> 0.42773641 | Z49: =IFERROR(__xludf.DUMMYFUNCTION("""COMPUTED_VALUE"""),-0.6060553280942611) -> -0.60605533 | AA49: =IFERROR(__xludf.DUMMYFUNCTION("""COMPUTED_VALUE"""),1.2667796257162525) -> 1.2667796 | AB49: =IFERROR(__xludf.DUMMYFUNCTION("""COMPUTED_VALUE"""),0.6447021838603678) -> 0.64470218 | AC49: =IFERROR(__xludf.DUMMYFUNCTION("""COMPUTED_VALUE"""),0.9964999404016663) -> 0.99649994 | AD49: =IFERROR(__xludf.DUMMYFUNCTION("""COMPUTED_VALUE"""),0.18888166269759513) -> 0.18888166 | AE49: =IFERROR(__xludf.DUMMYFUNCTION("""COMPUTED_VALUE"""),0.2974371718437915) -> 0.29743717 | AF49: =IFERROR(__xludf.DUMMYFUNCTION("""COMPUTED_VALUE"""),-0.4320665833097232) -> -0.43206658 | AG49: =IFERROR(__xludf.DUMMYFUNCTION("""COMPUTED_VALUE"""),0.0) -> 0
A50: =VLOOKUP($F50,UpdateHashtag!$V$3:$Y$32,COLUMN(B$9),0) -> 4 | B50: =VLOOKUP($F50,UpdateHashtag!$V$3:$Y$32,COLUMN(#REF!),0) -> #REF! | C50: =VLOOKUP($F50,UpdateHashtag!$V$3:$Y$32,COLUMN(#REF!),0) -> #REF! | D50: =SUM(A50:C50) -> #REF! | F50: =VLOOKUP(J50,UpdateBBM!$C$2:E1009,3,0) -> DET | G50: 37 | H50: =IFERROR(__xludf.DUMMYFUNCTION("""COMPUTED_VALUE"""),37.0) -> 37 | J50: =IFERROR(__xludf.DUMMYFUNCTION("""COMPUTED_VALUE"""),"Jalen Duren") -> Jalen Duren | K50: =IFERROR(__xludf.DUMMYFUNCTION("""COMPUTED_VALUE"""),73.0) -> 73 | L50: =IFERROR(__xludf.DUMMYFUNCTION("""COMPUTED_VALUE"""),"C") -> C | M50: =IFERROR(__xludf.DUMMYFUNCTION("""COMPUTED_VALUE"""),3.0779464973686106) -> 3.0779465 | N50: =IFERROR(__xludf.DUMMYFUNCTION("""COMPUTED_VALUE"""),3.0806210673527072) -> 3.0806211 | O50: =IFERROR(__xludf.DUMMYFUNCTION("""COMPUTED_VALUE"""),0.002674569984096653) -> 0.00267457 | P50: =IFERROR(__xludf.DUMMYFUNCTION("""COMPUTED_VALUE"""),12.57548) -> 12.57548 | Q50: =IFERROR(__xludf.DUMMYFUNCTION("""COMPUTED_VALUE"""),0.006712) -> 0.006712 | R50: =IFERROR(__xludf.DUMMYFUNCTION("""COMPUTED_VALUE"""),10.73753) -> 10.73753 | S50: =IFERROR(__xludf.DUMMYFUNCTION("""COMPUTED_VALUE"""),2.853699) -> 2.853699 | T50: =IFERROR(__xludf.DUMMYFUNCTION("""COMPUTED_VALUE"""),0.796849) -> 0.796849 | U50: =IFERROR(__xludf.DUMMYFUNCTION("""COMPUTED_VALUE"""),1.078219) -> 1.078219 | V50: =IFERROR(__xludf.DUMMYFUNCTION("""COMPUTED_VALUE"""),0.681451) -> 0.681451 | W50: =IFERROR(__xludf.DUMMYFUNCTION("""COMPUTED_VALUE"""),0.678018) -> 0.678018 | X50: =IFERROR(__xludf.DUMMYFUNCTION("""COMPUTED_VALUE"""),1.759452) -> 1.759452 | Y50: =IFERROR(__xludf.DUMMYFUNCTION("""COMPUTED_VALUE"""),-0.806883078938626) -> -0.80688308 | Z50: =IFERROR(__xludf.DUMMYFUNCTION("""COMPUTED_VALUE"""),-1.702611426462919) -> -1.7026114 | AA50: =IFERROR(__xludf.DUMMYFUNCTION("""COMPUTED_VALUE"""),1.8690994135010295) -> 1.8690994 | AB50: =IFERROR(__xludf.DUMMYFUNCTION("""COMPUTED_VALUE"""),-0.48030713324777846) -> -0.48030713 | AC50: =IFERROR(__xludf.DUMMYFUNCTION("""COMPUTED_VALUE"""),-0.7567451927139417) -> -0.75674519 | AD50: =IFERROR(__xludf.DUMMYFUNCTION("""COMPUTED_VALUE"""),0.6326553828052065) -> 0.63265538 | AE50: =IFERROR(__xludf.DUMMYFUNCTION("""COMPUTED_VALUE"""),3.813035850216261) -> 3.8130358 | AF50: =IFERROR(__xludf.DUMMYFUNCTION("""COMPUTED_VALUE"""),-1.1902341742694436) -> -1.1902342 | AG50: =IFERROR(__xludf.DUMMYFUNCTION("""COMPUTED_VALUE"""),0.0) -> 0
A51: =VLOOKUP($F51,UpdateHashtag!$V$3:$Y$32,COLUMN(B$9),0) -> 4 | B51: =VLOOKUP($F51,UpdateHashtag!$V$3:$Y$32,COLUMN(#REF!),0) -> #REF! | C51: =VLOOKUP($F51,UpdateHashtag!$V$3:$Y$32,COLUMN(#REF!),0) -> #REF! | D51: =SUM(A51:C51) -> #REF! | F51: =VLOOKUP(J51,UpdateBBM!$C$2:E1009,3,0) -> MIA | G51: 38 | H51: =IFERROR(__xludf.DUMMYFUNCTION("""COMPUTED_VALUE"""),38.0) -> 38 | J51: =IFERROR(__xludf.DUMMYFUNCTION("""COMPUTED_VALUE"""),"Tyler Herro") -> Tyler Herro | K51: =IFERROR(__xludf.DUMMYFUNCTION("""COMPUTED_VALUE"""),47.0) -> 47 | L51: =IFERROR(__xludf.DUMMYFUNCTION("""COMPUTED_VALUE"""),"G") -> G | M51: =IFERROR(__xludf.DUMMYFUNCTION("""COMPUTED_VALUE"""),3.049674242398632) -> 3.0496742 | N51: =IFERROR(__xludf.DUMMYFUNCTION("""COMPUTED_VALUE"""),3.236202519111559) -> 3.2362025 | O51: =IFERROR(__xludf.DUMMYFUNCTION("""COMPUTED_VALUE"""),0.18652827671292727) -> 0.18652828 | P51: =IFERROR(__xludf.DUMMYFUNCTION("""COMPUTED_VALUE"""),23.14511) -> 23.14511 | Q51: =IFERROR(__xludf.DUMMYFUNCTION("""COMPUTED_VALUE"""),2.425745) -> 2.425745 | R51: =IFERROR(__xludf.DUMMYFUNCTION("""COMPUTED_VALUE"""),4.789787) -> 4.789787 | S51: =IFERROR(__xludf.DUMMYFUNCTION("""COMPUTED_VALUE"""),5.553404) -> 5.553404 | T51: =IFERROR(__xludf.DUMMYFUNCTION("""COMPUTED_VALUE"""),1.04) -> 1.04 | U51: =IFERROR(__xludf.DUMMYFUNCTION("""COMPUTED_VALUE"""),0.277872) -> 0.277872 | V51: =IFERROR(__xludf.DUMMYFUNCTION("""COMPUTED_VALUE"""),0.483199) -> 0.483199 | W51: =IFERROR(__xludf.DUMMYFUNCTION("""COMPUTED_VALUE"""),0.889982) -> 0.889982 | X51: =IFERROR(__xludf.DUMMYFUNCTION("""COMPUTED_VALUE"""),2.500851) -> 2.500851 | Y51: =IFERROR(__xludf.DUMMYFUNCTION("""COMPUTED_VALUE"""),1.0474804155277802) -> 1.0474804 | Z51: =IFERROR(__xludf.DUMMYFUNCTION("""COMPUTED_VALUE"""),0.6337715368998503) -> 0.63377154 | AA51: =IFERROR(__xludf.DUMMYFUNCTION("""COMPUTED_VALUE"""),-0.5418396606557143) -> -0.54183966 | AB51: =IFERROR(__xludf.DUMMYFUNCTION("""COMPUTED_VALUE"""),0.8385378970999879) -> 0.8385379 | AC51: =IFERROR(__xludf.DUMMYFUNCTION("""COMPUTED_VALUE"""),-0.015808161684175464) -> -0.015808162 | AD51: =IFERROR(__xludf.DUMMYFUNCTION("""COMPUTED_VALUE"""),-0.8223692404735448) -> -0.82236924 | AE51: =IFERROR(__xludf.DUMMYFUNCTION("""COMPUTED_VALUE"""),-0.17394452354558984) -> -0.17394452 | AF51: =IFERROR(__xludf.DUMMYFUNCTION("""COMPUTED_VALUE"""),1.4480050154694202) -> 1.448005 | AG51: =IFERROR(__xludf.DUMMYFUNCTION("""COMPUTED_VALUE"""),0.0) -> 0
A52: =VLOOKUP($F52,UpdateHashtag!$V$3:$Y$32,COLUMN(B$9),0) -> 4 | B52: =VLOOKUP($F52,UpdateHashtag!$V$3:$Y$32,COLUMN(#REF!),0) -> #REF! | C52: =VLOOKUP($F52,UpdateHashtag!$V$3:$Y$32,COLUMN(#REF!),0) -> #REF! | D52: =SUM(A52:C52) -> #REF! | F52: =VLOOKUP(J52,UpdateBBM!$C$2:E1009,3,0) -> MIL | G52: 39 | H52: =IFERROR(__xludf.DUMMYFUNCTION("""COMPUTED_VALUE"""),39.0) -> 39 | J52: =IFERROR(__xludf.DUMMYFUNCTION("""COMPUTED_VALUE"""),"Myles Turner") -> Myles Turner | K52: =IFERROR(__xludf.DUMMYFUNCTION("""COMPUTED_VALUE"""),73.0) -> 73 | L52: =IFERROR(__xludf.DUMMYFUNCTION("""COMPUTED_VALUE"""),"C") -> C | M52: =IFERROR(__xludf.DUMMYFUNCTION("""COMPUTED_VALUE"""),2.9193975552791693) -> 2.9193976 | N52: =IFERROR(__xludf.DUMMYFUNCTION("""COMPUTED_VALUE"""),2.886505287585332) -> 2.8865053 | O52: =IFERROR(__xludf.DUMMYFUNCTION("""COMPUTED_VALUE"""),-0.03289226769383724) -> -0.032892268 | P52: =IFERROR(__xludf.DUMMYFUNCTION("""COMPUTED_VALUE"""),17.20205) -> 17.20205 | Q52: =IFERROR(__xludf.DUMMYFUNCTION("""COMPUTED_VALUE"""),2.200137) -> 2.200137 | R52: =IFERROR(__xludf.DUMMYFUNCTION("""COMPUTED_VALUE"""),6.867945) -> 6.867945 | S52: =IFERROR(__xludf.DUMMYFUNCTION("""COMPUTED_VALUE"""),1.749589) -> 1.749589 | T52: =IFERROR(__xludf.DUMMYFUNCTION("""COMPUTED_VALUE"""),0.752603) -> 0.752603 | U52: =IFERROR(__xludf.DUMMYFUNCTION("""COMPUTED_VALUE"""),2.356712) -> 2.356712 | V52: =IFERROR(__xludf.DUMMYFUNCTION("""COMPUTED_VALUE"""),0.506691) -> 0.506691 | W52: =IFERROR(__xludf.DUMMYFUNCTION("""COMPUTED_VALUE"""),0.781993) -> 0.781993 | X52: =IFERROR(__xludf.DUMMYFUNCTION("""COMPUTED_VALUE"""),1.616027) -> 1.616027 | Y52: =IFERROR(__xludf.DUMMYFUNCTION("""COMPUTED_VALUE"""),0.004814446196448743) -> 0.0048144462 | Z52: =IFERROR(__xludf.DUMMYFUNCTION("""COMPUTED_VALUE"""),0.41587178621503196) -> 0.41587179 | AA52: =IFERROR(__xludf.DUMMYFUNCTION("""COMPUTED_VALUE"""),0.30054917902203077) -> 0.30054918 | AB52: =IFERROR(__xludf.DUMMYFUNCTION("""COMPUTED_VALUE"""),-1.0196808746222148) -> -1.0196809 | AC52: =IFERROR(__xludf.DUMMYFUNCTION("""COMPUTED_VALUE"""),-0.891572932986213) -> -0.89157293 | AD52: =IFERROR(__xludf.DUMMYFUNCTION("""COMPUTED_VALUE"""),2.9569457164848734) -> 2.9569457 | AE52: =IFERROR(__xludf.DUMMYFUNCTION("""COMPUTED_VALUE"""),0.17516804446330547) -> 0.17516804 | AF52: =IFERROR(__xludf.DUMMYFUNCTION("""COMPUTED_VALUE"""),-0.07527095181014538) -> -0.075270952 | AG52: =IFERROR(__xludf.DUMMYFUNCTION("""COMPUTED_VALUE"""),0.0) -> 0
A53: =VLOOKUP($F53,UpdateHashtag!$V$3:$Y$32,COLUMN(B$9),0) -> 3 | B53: =VLOOKUP($F53,UpdateHashtag!$V$3:$Y$32,COLUMN(#REF!),0) -> #REF! | C53: =VLOOKUP($F53,UpdateHashtag!$V$3:$Y$32,COLUMN(#REF!),0) -> #REF! | D53: =SUM(A53:C53) -> #REF! | F53: =VLOOKUP(J53,UpdateBBM!$C$2:E1009,3,0) -> BOS | G53: 40 | H53: =IFERROR(__xludf.DUMMYFUNCTION("""COMPUTED_VALUE"""),40.0) -> 40 | J53: =IFERROR(__xludf.DUMMYFUNCTION("""COMPUTED_VALUE"""),"Payton Pritchard") -> Payton Pritchard | K53: =IFERROR(__xludf.DUMMYFUNCTION("""COMPUTED_VALUE"""),66.0) -> 66 | L53: =IFERROR(__xludf.DUMMYFUNCTION("""COMPUTED_VALUE"""),"G") -> G | M53: =IFERROR(__xludf.DUMMYFUNCTION("""COMPUTED_VALUE"""),2.852011912127984) -> 2.8520119 | N53: =IFERROR(__xludf.DUMMYFUNCTION("""COMPUTED_VALUE"""),2.810035314891489) -> 2.8100353 | O53: =IFERROR(__xludf.DUMMYFUNCTION("""COMPUTED_VALUE"""),-0.04197659723649494) -> -0.041976597 | P53: =IFERROR(__xludf.DUMMYFUNCTION("""COMPUTED_VALUE"""),19.52621) -> 19.52621 | Q53: =IFERROR(__xludf.DUMMYFUNCTION("""COMPUTED_VALUE"""),4.231364) -> 4.231364 | R53: =IFERROR(__xludf.DUMMYFUNCTION("""COMPUTED_VALUE"""),4.73803) -> 4.73803 | S53: =IFERROR(__xludf.DUMMYFUNCTION("""COMPUTED_VALUE"""),4.943939) -> 4.943939 | T53: =IFERROR(__xludf.DUMMYFUNCTION("""COMPUTED_VALUE"""),0.892727) -> 0.892727 | U53: =IFERROR(__xludf.DUMMYFUNCTION("""COMPUTED_VALUE"""),0.205303) -> 0.205303 | V53: =IFERROR(__xludf.DUMMYFUNCTION("""COMPUTED_VALUE"""),0.47378) -> 0.47378 | W53: =IFERROR(__xludf.DUMMYFUNCTION("""COMPUTED_VALUE"""),0.847957) -> 0.847957 | X53: =IFERROR(__xludf.DUMMYFUNCTION("""COMPUTED_VALUE"""),1.579394) -> 1.579394 | Y53: =IFERROR(__xludf.DUMMYFUNCTION("""COMPUTED_VALUE"""),0.41257114716886134) -> 0.41257115 | Z53: =IFERROR(__xludf.DUMMYFUNCTION("""COMPUTED_VALUE"""),2.3776987466254393) -> 2.3776987 | AA53: =IFERROR(__xludf.DUMMYFUNCTION("""COMPUTED_VALUE"""),-0.5628195472549049) -> -0.56281955 | AB53: =IFERROR(__xludf.DUMMYFUNCTION("""COMPUTED_VALUE"""),0.5408054091352286) -> 0.54080541 | AC53: =IFERROR(__xludf.DUMMYFUNCTION("""COMPUTED_VALUE"""),-0.4645828711069076) -> -0.46458287 | AD53: =IFERROR(__xludf.DUMMYFUNCTION("""COMPUTED_VALUE"""),-0.954299118247455) -> -0.95429912 | AE53: =IFERROR(__xludf.DUMMYFUNCTION("""COMPUTED_VALUE"""),-0.304607462996349) -> -0.30460746 | AF53: =IFERROR(__xludf.DUMMYFUNCTION("""COMPUTED_VALUE"""),0.8109698933201209) -> 0.81096989 | AG53: =IFERROR(__xludf.DUMMYFUNCTION("""COMPUTED_VALUE"""),0.0) -> 0
A54: =VLOOKUP($F54,UpdateHashtag!$V$3:$Y$32,COLUMN(B$9),0) -> 4 | B54: =VLOOKUP($F54,UpdateHashtag!$V$3:$Y$32,COLUMN(#REF!),0) -> #REF! | C54: =VLOOKUP($F54,UpdateHashtag!$V$3:$Y$32,COLUMN(#REF!),0) -> #REF! | D54: =SUM(A54:C54) -> #REF! | F54: =VLOOKUP(J54,UpdateBBM!$C$2:E1009,3,0) -> SAC | G54: 41 | H54: =IFERROR(__xludf.DUMMYFUNCTION("""COMPUTED_VALUE"""),41.0) -> 41 | J54: =IFERROR(__xludf.DUMMYFUNCTION("""COMPUTED_VALUE"""),"Domantas Sabonis") -> Domantas Sabonis | K54: =IFERROR(__xludf.DUMMYFUNCTION("""COMPUTED_VALUE"""),73.0) -> 73 | L54: =IFERROR(__xludf.DUMMYFUNCTION("""COMPUTED_VALUE"""),"C") -> C | M54: =IFERROR(__xludf.DUMMYFUNCTION("""COMPUTED_VALUE"""),2.7661187324764396) -> 2.7661187 | N54: =IFERROR(__xludf.DUMMYFUNCTION("""COMPUTED_VALUE"""),3.046601240496511) -> 3.0466012 | O54: =IFERROR(__xludf.DUMMYFUNCTION("""COMPUTED_VALUE"""),0.28048250802007146) -> 0.28048251 | P54: =IFERROR(__xludf.DUMMYFUNCTION("""COMPUTED_VALUE"""),18.12329) -> 18.12329 | Q54: =IFERROR(__xludf.DUMMYFUNCTION("""COMPUTED_VALUE"""),0.792329) -> 0.792329 | R54: =IFERROR(__xludf.DUMMYFUNCTION("""COMPUTED_VALUE"""),13.9337) -> 13.9337 | S54: =IFERROR(__xludf.DUMMYFUNCTION("""COMPUTED_VALUE"""),5.446164) -> 5.446164 | T54: =IFERROR(__xludf.DUMMYFUNCTION("""COMPUTED_VALUE"""),0.715753) -> 0.715753 | U54: =IFERROR(__xludf.DUMMYFUNCTION("""COMPUTED_VALUE"""),0.280548) -> 0.280548 | V54: =IFERROR(__xludf.DUMMYFUNCTION("""COMPUTED_VALUE"""),0.569938) -> 0.569938 | W54: =IFERROR(__xludf.DUMMYFUNCTION("""COMPUTED_VALUE"""),0.737994) -> 0.737994 | X54: =IFERROR(__xludf.DUMMYFUNCTION("""COMPUTED_VALUE"""),2.879726) -> 2.879726 | Y54: =IFERROR(__xludf.DUMMYFUNCTION("""COMPUTED_VALUE"""),0.16643919802240992) -> 0.1664392 | Z54: =IFERROR(__xludf.DUMMYFUNCTION("""COMPUTED_VALUE"""),-0.9438362569930654) -> -0.94383626 | AA54: =IFERROR(__xludf.DUMMYFUNCTION("""COMPUTED_VALUE"""),3.1646784492205553) -> 3.1646784 | AB54: =IFERROR(__xludf.DUMMYFUNCTION("""COMPUTED_VALUE"""),0.7861496024327949) -> 0.7861496 | AC54: =IFERROR(__xludf.DUMMYFUNCTION("""COMPUTED_VALUE"""),-1.0038633598956106) -> -1.0038634 | AD54: =IFERROR(__xludf.DUMMYFUNCTION("""COMPUTED_VALUE"""),-0.8175042932795227) -> -0.81750429 | AE54: =IFERROR(__xludf.DUMMYFUNCTION("""COMPUTED_VALUE"""),1.2798740177731) -> 1.279874 | AF54: =IFERROR(__xludf.DUMMYFUNCTION("""COMPUTED_VALUE"""),-0.5891994766797606) -> -0.58919948 | AG54: =IFERROR(__xludf.DUMMYFUNCTION("""COMPUTED_VALUE"""),0.0) -> 0
A55: =VLOOKUP($F55,UpdateHashtag!$V$3:$Y$32,COLUMN(B$9),0) -> 4 | B55: =VLOOKUP($F55,UpdateHashtag!$V$3:$Y$32,COLUMN(#REF!),0) -> #REF! | C55: =VLOOKUP($F55,UpdateHashtag!$V$3:$Y$32,COLUMN(#REF!),0) -> #REF! | D55: =SUM(A55:C55) -> #REF! | F55: =VLOOKUP(J55,UpdateBBM!$C$2:E1009,3,0) -> DET | G55: 42 | H55: =IFERROR(__xludf.DUMMYFUNCTION("""COMPUTED_VALUE"""),42.0) -> 42 | J55: =IFERROR(__xludf.DUMMYFUNCTION("""COMPUTED_VALUE"""),"Ausar Thompson") -> Ausar Thompson | K55: =IFERROR(__xludf.DUMMYFUNCTION("""COMPUTED_VALUE"""),68.0) -> 68 | L55: =IFERROR(__xludf.DUMMYFUNCTION("""COMPUTED_VALUE"""),"F") -> F | M55: =IFERROR(__xludf.DUMMYFUNCTION("""COMPUTED_VALUE"""),2.5233258027140844) -> 2.5233258 | N55: =IFERROR(__xludf.DUMMYFUNCTION("""COMPUTED_VALUE"""),2.4730752815513264) -> 2.4730753 | O55: =IFERROR(__xludf.DUMMYFUNCTION("""COMPUTED_VALUE"""),-0.050250521162757966) -> -0.050250521 | P55: =IFERROR(__xludf.DUMMYFUNCTION("""COMPUTED_VALUE"""),13.51956) -> 13.51956 | Q55: =IFERROR(__xludf.DUMMYFUNCTION("""COMPUTED_VALUE"""),0.255147) -> 0.255147 | R55: =IFERROR(__xludf.DUMMYFUNCTION("""COMPUTED_VALUE"""),6.565) -> 6.565 | S55: =IFERROR(__xludf.DUMMYFUNCTION("""COMPUTED_VALUE"""),3.117206) -> 3.117206 | T55: =IFERROR(__xludf.DUMMYFUNCTION("""COMPUTED_VALUE"""),2.096912) -> 2.096912 | U55: =IFERROR(__xludf.DUMMYFUNCTION("""COMPUTED_VALUE"""),1.136176) -> 1.136176 | V55: =IFERROR(__xludf.DUMMYFUNCTION("""COMPUTED_VALUE"""),0.523389) -> 0.523389 | W55: =IFERROR(__xludf.DUMMYFUNCTION("""COMPUTED_VALUE"""),0.687998) -> 0.687998 | X55: =IFERROR(__xludf.DUMMYFUNCTION("""COMPUTED_VALUE"""),1.546029) -> 1.546029 | Y55: =IFERROR(__xludf.DUMMYFUNCTION("""COMPUTED_VALUE"""),-0.6412512178558971) -> -0.64125122 | Z55: =IFERROR(__xludf.DUMMYFUNCTION("""COMPUTED_VALUE"""),-1.4626645958479463) -> -1.4626646 | AA55: =IFERROR(__xludf.DUMMYFUNCTION("""COMPUTED_VALUE"""),0.17774933077364258) -> 0.17774933 | AB55: =IFERROR(__xludf.DUMMYFUNCTION("""COMPUTED_VALUE"""),-0.35158014366489865) -> -0.35158014 | AC55: =IFERROR(__xludf.DUMMYFUNCTION("""COMPUTED_VALUE"""),3.2048458324994074) -> 3.2048458 | AD55: =IFERROR(__xludf.DUMMYFUNCTION("""COMPUTED_VALUE"""),0.7380207581878426) -> 0.73802076 | AE55: =IFERROR(__xludf.DUMMYFUNCTION("""COMPUTED_VALUE"""),0.44347506028976824) -> 0.44347506 | AF55: =IFERROR(__xludf.DUMMYFUNCTION("""COMPUTED_VALUE"""),-1.0981843386785384) -> -1.0981843 | AG55: =IFERROR(__xludf.DUMMYFUNCTION("""COMPUTED_VALUE"""),0.0) -> 0
A56: =VLOOKUP($F56,UpdateHashtag!$V$3:$Y$32,COLUMN(B$9),0) -> 3 | B56: =VLOOKUP($F56,UpdateHashtag!$V$3:$Y$32,COLUMN(#REF!),0) -> #REF! | C56: =VLOOKUP($F56,UpdateHashtag!$V$3:$Y$32,COLUMN(#REF!),0) -> #REF! | D56: =SUM(A56:C56) -> #REF! | F56: =VLOOKUP(J56,UpdateBBM!$C$2:E1009,3,0) -> LAL | G56: 43 | H56: =IFERROR(__xludf.DUMMYFUNCTION("""COMPUTED_VALUE"""),43.0) -> 43 | J56: =IFERROR(__xludf.DUMMYFUNCTION("""COMPUTED_VALUE"""),"Austin Reaves") -> Austin Reaves | K56: =IFERROR(__xludf.DUMMYFUNCTION("""COMPUTED_VALUE"""),68.0) -> 68 | L56: =IFERROR(__xludf.DUMMYFUNCTION("""COMPUTED_VALUE"""),"G,F") -> G,F | M56: =IFERROR(__xludf.DUMMYFUNCTION("""COMPUTED_VALUE"""),2.522468710453807) -> 2.5224687 | N56: =IFERROR(__xludf.DUMMYFUNCTION("""COMPUTED_VALUE"""),2.6204239681838786) -> 2.620424 | O56: =IFERROR(__xludf.DUMMYFUNCTION("""COMPUTED_VALUE"""),0.09795525773007174) -> 0.097955258 | P56: =IFERROR(__xludf.DUMMYFUNCTION("""COMPUTED_VALUE"""),20.53868) -> 20.53868 | Q56: =IFERROR(__xludf.DUMMYFUNCTION("""COMPUTED_VALUE"""),2.782353) -> 2.782353 | R56: =IFERROR(__xludf.DUMMYFUNCTION("""COMPUTED_VALUE"""),4.501912) -> 4.501912 | S56: =IFERROR(__xludf.DUMMYFUNCTION("""COMPUTED_VALUE"""),4.859118) -> 4.859118 | T56: =IFERROR(__xludf.DUMMYFUNCTION("""COMPUTED_VALUE"""),1.066176) -> 1.066176 | U56: =IFERROR(__xludf.DUMMYFUNCTION("""COMPUTED_VALUE"""),0.358676) -> 0.358676 | V56: =IFERROR(__xludf.DUMMYFUNCTION("""COMPUTED_VALUE"""),0.475197) -> 0.475197 | W56: =IFERROR(__xludf.DUMMYFUNCTION("""COMPUTED_VALUE"""),0.889003) -> 0.889003 | X56: =IFERROR(__xludf.DUMMYFUNCTION("""COMPUTED_VALUE"""),2.143676) -> 2.143676 | Y56: =IFERROR(__xludf.DUMMYFUNCTION("""COMPUTED_VALUE"""),0.5902015284823419) -> 0.59020153 | Z56: =IFERROR(__xludf.DUMMYFUNCTION("""COMPUTED_VALUE"""),0.978195468197551) -> 0.97819547 | AA56: =IFERROR(__xludf.DUMMYFUNCTION("""COMPUTED_VALUE"""),-0.6585308300577668) -> -0.65853083 | AB56: =IFERROR(__xludf.DUMMYFUNCTION("""COMPUTED_VALUE"""),0.49936912097814146) -> 0.49936912 | AC56: =IFERROR(__xludf.DUMMYFUNCTION("""COMPUTED_VALUE"""),0.0639561317969747) -> 0.063956132 | AD56: =IFERROR(__xludf.DUMMYFUNCTION("""COMPUTED_VALUE"""),-0.6754681967269995) -> -0.6754682 | AE56: =IFERROR(__xludf.DUMMYFUNCTION("""COMPUTED_VALUE"""),-0.2852910684952662) -> -0.28529107 | AF56: =IFERROR(__xludf.DUMMYFUNCTION("""COMPUTED_VALUE"""),1.4325236172819027) -> 1.4325236 | AG56: =IFERROR(__xludf.DUMMYFUNCTION("""COMPUTED_VALUE"""),0.0) -> 0
A57: =VLOOKUP($F57,UpdateHashtag!$V$3:$Y$32,COLUMN(B$9),0) -> 4 | B57: =VLOOKUP($F57,UpdateHashtag!$V$3:$Y$32,COLUMN(#REF!),0) -> #REF! | C57: =VLOOKUP($F57,UpdateHashtag!$V$3:$Y$32,COLUMN(#REF!),0) -> #REF! | D57: =SUM(A57:C57) -> #REF! | F57: =VLOOKUP(J57,UpdateBBM!$C$2:E1009,3,0) -> LAC | G57: 44 | H57: =IFERROR(__xludf.DUMMYFUNCTION("""COMPUTED_VALUE"""),44.0) -> 44 | J57: =IFERROR(__xludf.DUMMYFUNCTION("""COMPUTED_VALUE"""),"Ivica Zubac") -> Ivica Zubac | K57: =IFERROR(__xludf.DUMMYFUNCTION("""COMPUTED_VALUE"""),73.0) -> 73 | L57: =IFERROR(__xludf.DUMMYFUNCTION("""COMPUTED_VALUE"""),"C") -> C | M57: =IFERROR(__xludf.DUMMYFUNCTION("""COMPUTED_VALUE"""),2.496259925370503) -> 2.4962599 | N57: =IFERROR(__xludf.DUMMYFUNCTION("""COMPUTED_VALUE"""),2.3733129454386206) -> 2.3733129 | O57: =IFERROR(__xludf.DUMMYFUNCTION("""COMPUTED_VALUE"""),-0.12294697993188253) -> -0.12294698 | P57: =IFERROR(__xludf.DUMMYFUNCTION("""COMPUTED_VALUE"""),16.56041) -> 16.56041 | Q57: =IFERROR(__xludf.DUMMYFUNCTION("""COMPUTED_VALUE"""),0.0) -> 0 | R57: =IFERROR(__xludf.DUMMYFUNCTION("""COMPUTED_VALUE"""),11.58945) -> 11.58945 | S57: =IFERROR(__xludf.DUMMYFUNCTION("""COMPUTED_VALUE"""),2.004658) -> 2.004658 | T57: =IFERROR(__xludf.DUMMYFUNCTION("""COMPUTED_VALUE"""),0.555068) -> 0.555068 | U57: =IFERROR(__xludf.DUMMYFUNCTION("""COMPUTED_VALUE"""),1.076301) -> 1.076301 | V57: =IFERROR(__xludf.DUMMYFUNCTION("""COMPUTED_VALUE"""),0.647396) -> 0.647396 | W57: =IFERROR(__xludf.DUMMYFUNCTION("""COMPUTED_VALUE"""),0.704991) -> 0.704991 | X57: =IFERROR(__xludf.DUMMYFUNCTION("""COMPUTED_VALUE"""),1.252877) -> 1.252877 | Y57: =IFERROR(__xludf.DUMMYFUNCTION("""COMPUTED_VALUE"""),-0.1077565513303732) -> -0.10775655 | Z57: =IFERROR(__xludf.DUMMYFUNCTION("""COMPUTED_VALUE"""),-1.7090941005108098) -> -1.7090941 | AA57: =IFERROR(__xludf.DUMMYFUNCTION("""COMPUTED_VALUE"""),2.2144282577459156) -> 2.2144283 | AB57: =IFERROR(__xludf.DUMMYFUNCTION("""COMPUTED_VALUE"""),-0.8950759703657223) -> -0.89507597 | AC57: =IFERROR(__xludf.DUMMYFUNCTION("""COMPUTED_VALUE"""),-1.4935075185913098) -> -1.4935075 | AD57: =IFERROR(__xludf.DUMMYFUNCTION("""COMPUTED_VALUE"""),0.6291684737177123) -> 0.62916847 | AE57: =IFERROR(__xludf.DUMMYFUNCTION("""COMPUTED_VALUE"""),2.9601925759258214) -> 2.9601926 | AF57: =IFERROR(__xludf.DUMMYFUNCTION("""COMPUTED_VALUE"""),-0.9341363216634235) -> -0.93413632 | AG57: =IFERROR(__xludf.DUMMYFUNCTION("""COMPUTED_VALUE"""),0.0) -> 0
A58: =VLOOKUP($F58,UpdateHashtag!$V$3:$Y$32,COLUMN(B$9),0) -> #N/A | B58: =VLOOKUP($F58,UpdateHashtag!$V$3:$Y$32,COLUMN(#REF!),0) -> #REF! | C58: =VLOOKUP($F58,UpdateHashtag!$V$3:$Y$32,COLUMN(#REF!),0) -> #REF! | D58: =SUM(A58:C58) -> #N/A | F58: =VLOOKUP(J58,UpdateBBM!$C$2:E1009,3,0) -> GSW | G58: 45 | H58: =IFERROR(__xludf.DUMMYFUNCTION("""COMPUTED_VALUE"""),45.0) -> 45 | J58: =IFERROR(__xludf.DUMMYFUNCTION("""COMPUTED_VALUE"""),"Jimmy Butler") -> Jimmy Butler | K58: =IFERROR(__xludf.DUMMYFUNCTION("""COMPUTED_VALUE"""),68.0) -> 68 | L58: =IFERROR(__xludf.DUMMYFUNCTION("""COMPUTED_VALUE"""),"F") -> F | M58: =IFERROR(__xludf.DUMMYFUNCTION("""COMPUTED_VALUE"""),2.4496164124755073) -> 2.4496164 | N58: =IFERROR(__xludf.DUMMYFUNCTION("""COMPUTED_VALUE"""),2.369498675020136) -> 2.3694987 | O58: =IFERROR(__xludf.DUMMYFUNCTION("""COMPUTED_VALUE"""),-0.08011773745537143) -> -0.080117737 | P58: =IFERROR(__xludf.DUMMYFUNCTION("""COMPUTED_VALUE"""),16.69765) -> 16.69765 | Q58: =IFERROR(__xludf.DUMMYFUNCTION("""COMPUTED_VALUE"""),0.740294) -> 0.740294 | R58: =IFERROR(__xludf.DUMMYFUNCTION("""COMPUTED_VALUE"""),5.376912) -> 5.376912 | S58: =IFERROR(__xludf.DUMMYFUNCTION("""COMPUTED_VALUE"""),5.847353) -> 5.847353 | T58: =IFERROR(__xludf.DUMMYFUNCTION("""COMPUTED_VALUE"""),1.565441) -> 1.565441 | U58: =IFERROR(__xludf.DUMMYFUNCTION("""COMPUTED_VALUE"""),0.271471) -> 0.271471 | V58: =IFERROR(__xludf.DUMMYFUNCTION("""COMPUTED_VALUE"""),0.498564) -> 0.498564 | W58: =IFERROR(__xludf.DUMMYFUNCTION("""COMPUTED_VALUE"""),0.859001) -> 0.859001 | X58: =IFERROR(__xludf.DUMMYFUNCTION("""COMPUTED_VALUE"""),1.425588) -> 1.425588 | Y58: =IFERROR(__xludf.DUMMYFUNCTION("""COMPUTED_VALUE"""),-0.08367880726737696) -> -0.083678807 | Z58: =IFERROR(__xludf.DUMMYFUNCTION("""COMPUTED_VALUE"""),-0.9940934000326939) -> -0.9940934 | AA58: =IFERROR(__xludf.DUMMYFUNCTION("""COMPUTED_VALUE"""),-0.3038464245804033) -> -0.30384642 | AB58: =IFERROR(__xludf.DUMMYFUNCTION("""COMPUTED_VALUE"""),0.9821362450030723) -> 0.98213624 | AC58: =IFERROR(__xludf.DUMMYFUNCTION("""COMPUTED_VALUE"""),1.5853314368423015) -> 1.5853314 | AD58: =IFERROR(__xludf.DUMMYFUNCTION("""COMPUTED_VALUE"""),-0.8340062087055832) -> -0.83400621 | AE58: =IFERROR(__xludf.DUMMYFUNCTION("""COMPUTED_VALUE"""),0.05064229356347107) -> 0.050642294 | AF58: =IFERROR(__xludf.DUMMYFUNCTION("""COMPUTED_VALUE"""),0.9729201401646548) -> 0.97292014 | AG58: =IFERROR(__xludf.DUMMYFUNCTION("""COMPUTED_VALUE"""),0.0) -> 0
A59: =VLOOKUP($F59,UpdateHashtag!$V$3:$Y$32,COLUMN(B$9),0) -> 4 | B59: =VLOOKUP($F59,UpdateHashtag!$V$3:$Y$32,COLUMN(#REF!),0) -> #REF! | C59: =VLOOKUP($F59,UpdateHashtag!$V$3:$Y$32,COLUMN(#REF!),0) -> #REF! | D59: =SUM(A59:C59) -> #REF! | F59: =VLOOKUP(J59,UpdateBBM!$C$2:E1009,3,0) -> MEM | G59: 46 | H59: =IFERROR(__xludf.DUMMYFUNCTION("""COMPUTED_VALUE"""),46.0) -> 46 | J59: =IFERROR(__xludf.DUMMYFUNCTION("""COMPUTED_VALUE"""),"Zach Edey") -> Zach Edey | K59: =IFERROR(__xludf.DUMMYFUNCTION("""COMPUTED_VALUE"""),47.0) -> 47 | L59: =IFERROR(__xludf.DUMMYFUNCTION("""COMPUTED_VALUE"""),"C") -> C | M59: =IFERROR(__xludf.DUMMYFUNCTION("""COMPUTED_VALUE"""),2.310851257362038) -> 2.3108513 | N59: =IFERROR(__xludf.DUMMYFUNCTION("""COMPUTED_VALUE"""),2.262324212035861) -> 2.2623242 | O59: =IFERROR(__xludf.DUMMYFUNCTION("""COMPUTED_VALUE"""),-0.04852704532617702) -> -0.048527045 | P59: =IFERROR(__xludf.DUMMYFUNCTION("""COMPUTED_VALUE"""),14.4817) -> 14.4817 | Q59: =IFERROR(__xludf.DUMMYFUNCTION("""COMPUTED_VALUE"""),0.311702) -> 0.311702 | R59: =IFERROR(__xludf.DUMMYFUNCTION("""COMPUTED_VALUE"""),10.99809) -> 10.99809 | S59: =IFERROR(__xludf.DUMMYFUNCTION("""COMPUTED_VALUE"""),1.331489) -> 1.331489 | T59: =IFERROR(__xludf.DUMMYFUNCTION("""COMPUTED_VALUE"""),0.664255) -> 0.664255 | U59: =IFERROR(__xludf.DUMMYFUNCTION("""COMPUTED_VALUE"""),1.605532) -> 1.605532 | V59: =IFERROR(__xludf.DUMMYFUNCTION("""COMPUTED_VALUE"""),0.619996) -> 0.619996 | W59: =IFERROR(__xludf.DUMMYFUNCTION("""COMPUTED_VALUE"""),0.721003) -> 0.721003 | X59: =IFERROR(__xludf.DUMMYFUNCTION("""COMPUTED_VALUE"""),1.552979) -> 1.552979 | Y59: =IFERROR(__xludf.DUMMYFUNCTION("""COMPUTED_VALUE"""),-0.47245086320148555) -> -0.47245086 | Z59: =IFERROR(__xludf.DUMMYFUNCTION("""COMPUTED_VALUE"""),-1.4080418856604535) -> -1.4080419 | AA59: =IFERROR(__xludf.DUMMYFUNCTION("""COMPUTED_VALUE"""),1.9747183491480944) -> 1.9747183 | AB59: =IFERROR(__xludf.DUMMYFUNCTION("""COMPUTED_VALUE"""),-1.2239287858526646) -> -1.2239288 | AC59: =IFERROR(__xludf.DUMMYFUNCTION("""COMPUTED_VALUE"""),-1.160789612405248) -> -1.1607896 | AD59: =IFERROR(__xludf.DUMMYFUNCTION("""COMPUTED_VALUE"""),1.5913063169312645) -> 1.5913063 | AE59: =IFERROR(__xludf.DUMMYFUNCTION("""COMPUTED_VALUE"""),2.3245942650140092) -> 2.3245943 | AF59: =IFERROR(__xludf.DUMMYFUNCTION("""COMPUTED_VALUE"""),-0.7711254575981092) -> -0.77112546 | AG59: =IFERROR(__xludf.DUMMYFUNCTION("""COMPUTED_VALUE"""),0.0) -> 0
A60: =VLOOKUP($F60,UpdateHashtag!$V$3:$Y$32,COLUMN(B$9),0) -> 4 | B60: =VLOOKUP($F60,UpdateHashtag!$V$3:$Y$32,COLUMN(#REF!),0) -> #REF! | C60: =VLOOKUP($F60,UpdateHashtag!$V$3:$Y$32,COLUMN(#REF!),0) -> #REF! | D60: =SUM(A60:C60) -> #REF! | F60: =VLOOKUP(J60,UpdateBBM!$C$2:E1009,3,0) -> CLE | G60: 47 | H60: =IFERROR(__xludf.DUMMYFUNCTION("""COMPUTED_VALUE"""),47.0) -> 47 | J60: =IFERROR(__xludf.DUMMYFUNCTION("""COMPUTED_VALUE"""),"Darius Garland") -> Darius Garland | K60: =IFERROR(__xludf.DUMMYFUNCTION("""COMPUTED_VALUE"""),56.0) -> 56 | L60: =IFERROR(__xludf.DUMMYFUNCTION("""COMPUTED_VALUE"""),"G") -> G | M60: =IFERROR(__xludf.DUMMYFUNCTION("""COMPUTED_VALUE"""),2.3067288310379728) -> 2.3067288 | N60: =IFERROR(__xludf.DUMMYFUNCTION("""COMPUTED_VALUE"""),2.501946897717155) -> 2.5019469 | O60: =IFERROR(__xludf.DUMMYFUNCTION("""COMPUTED_VALUE"""),0.1952180666791823) -> 0.19521807 | P60: =IFERROR(__xludf.DUMMYFUNCTION("""COMPUTED_VALUE"""),19.45268) -> 19.45268 | Q60: =IFERROR(__xludf.DUMMYFUNCTION("""COMPUTED_VALUE"""),2.715357) -> 2.715357 | R60: =IFERROR(__xludf.DUMMYFUNCTION("""COMPUTED_VALUE"""),2.588036) -> 2.588036 | S60: =IFERROR(__xludf.DUMMYFUNCTION("""COMPUTED_VALUE"""),6.3125) -> 6.3125 | T60: =IFERROR(__xludf.DUMMYFUNCTION("""COMPUTED_VALUE"""),1.252857) -> 1.252857 | U60: =IFERROR(__xludf.DUMMYFUNCTION("""COMPUTED_VALUE"""),0.126964) -> 0.126964 | V60: =IFERROR(__xludf.DUMMYFUNCTION("""COMPUTED_VALUE"""),0.458946) -> 0.458946 | W60: =IFERROR(__xludf.DUMMYFUNCTION("""COMPUTED_VALUE"""),0.856974) -> 0.856974 | X60: =IFERROR(__xludf.DUMMYFUNCTION("""COMPUTED_VALUE"""),2.535893) -> 2.535893 | Y60: =IFERROR(__xludf.DUMMYFUNCTION("""COMPUTED_VALUE"""),0.39967085191272544) -> 0.39967085 | Z60: =IFERROR(__xludf.DUMMYFUNCTION("""COMPUTED_VALUE"""),0.9134884910651794) -> 0.91348849 | AA60: =IFERROR(__xludf.DUMMYFUNCTION("""COMPUTED_VALUE"""),-1.4343273685919322) -> -1.4343274 | AB60: =IFERROR(__xludf.DUMMYFUNCTION("""COMPUTED_VALUE"""),1.2093672977777912) -> 1.2093673 | AC60: =IFERROR(__xludf.DUMMYFUNCTION("""COMPUTED_VALUE"""),0.6328160825669401) -> 0.63281608 | AD60: =IFERROR(__xludf.DUMMYFUNCTION("""COMPUTED_VALUE"""),-1.096718811159447) -> -1.0967188 | AE60: =IFERROR(__xludf.DUMMYFUNCTION("""COMPUTED_VALUE"""),-0.4995813705190771) -> -0.49958137 | AF60: =IFERROR(__xludf.DUMMYFUNCTION("""COMPUTED_VALUE"""),0.942904356073043) -> 0.94290436 | AG60: =IFERROR(__xludf.DUMMYFUNCTION("""COMPUTED_VALUE"""),0.0) -> 0
A61: =VLOOKUP($F61,UpdateHashtag!$V$3:$Y$32,COLUMN(B$9),0) -> 4 | B61: =VLOOKUP($F61,UpdateHashtag!$V$3:$Y$32,COLUMN(#REF!),0) -> #REF! | C61: =VLOOKUP($F61,UpdateHashtag!$V$3:$Y$32,COLUMN(#REF!),0) -> #REF! | D61: =SUM(A61:C61) -> #REF! | F61: =VLOOKUP(J61,UpdateBBM!$C$2:E1009,3,0) -> DAL | G61: 48 | H61: =IFERROR(__xludf.DUMMYFUNCTION("""COMPUTED_VALUE"""),48.0) -> 48 | J61: =IFERROR(__xludf.DUMMYFUNCTION("""COMPUTED_VALUE"""),"Dereck Lively II") -> Dereck Lively II | K61: =IFERROR(__xludf.DUMMYFUNCTION("""COMPUTED_VALUE"""),61.0) -> 61 | L61: =IFERROR(__xludf.DUMMYFUNCTION("""COMPUTED_VALUE"""),"C") -> C | M61: =IFERROR(__xludf.DUMMYFUNCTION("""COMPUTED_VALUE"""),2.303840731718489) -> 2.3038407 | N61: =IFERROR(__xludf.DUMMYFUNCTION("""COMPUTED_VALUE"""),2.1321692300204487) -> 2.1321692 | O61: =IFERROR(__xludf.DUMMYFUNCTION("""COMPUTED_VALUE"""),-0.17167150169804035) -> -0.1716715 | P61: =IFERROR(__xludf.DUMMYFUNCTION("""COMPUTED_VALUE"""),9.158197) -> 9.158197 | Q61: =IFERROR(__xludf.DUMMYFUNCTION("""COMPUTED_VALUE"""),0.0) -> 0 | R61: =IFERROR(__xludf.DUMMYFUNCTION("""COMPUTED_VALUE"""),7.827541) -> 7.827541 | S61: =IFERROR(__xludf.DUMMYFUNCTION("""COMPUTED_VALUE"""),1.90377) -> 1.90377 | T61: =IFERROR(__xludf.DUMMYFUNCTION("""COMPUTED_VALUE"""),0.610492) -> 0.610492 | U61: =IFERROR(__xludf.DUMMYFUNCTION("""COMPUTED_VALUE"""),1.508197) -> 1.508197 | V61: =IFERROR(__xludf.DUMMYFUNCTION("""COMPUTED_VALUE"""),0.72299) -> 0.72299 | W61: =IFERROR(__xludf.DUMMYFUNCTION("""COMPUTED_VALUE"""),0.67203) -> 0.67203 | X61: =IFERROR(__xludf.DUMMYFUNCTION("""COMPUTED_VALUE"""),1.056393) -> 1.056393 | Y61: =IFERROR(__xludf.DUMMYFUNCTION("""COMPUTED_VALUE"""),-1.4064201342055225) -> -1.4064201 | Z61: =IFERROR(__xludf.DUMMYFUNCTION("""COMPUTED_VALUE"""),-1.7090941005108098) -> -1.7090941 | AA61: =IFERROR(__xludf.DUMMYFUNCTION("""COMPUTED_VALUE"""),0.6895248781745522) -> 0.68952488 | AB61: =IFERROR(__xludf.DUMMYFUNCTION("""COMPUTED_VALUE"""),-0.9443612209474435) -> -0.94436122 | AC61: =IFERROR(__xludf.DUMMYFUNCTION("""COMPUTED_VALUE"""),-1.3246178409515148) -> -1.3246178 | AD61: =IFERROR(__xludf.DUMMYFUNCTION("""COMPUTED_VALUE"""),1.414352043713726) -> 1.414352 | AE61: =IFERROR(__xludf.DUMMYFUNCTION("""COMPUTED_VALUE"""),4.94762975870936) -> 4.9476298 | AF61: =IFERROR(__xludf.DUMMYFUNCTION("""COMPUTED_VALUE"""),-1.2439382544727091) -> -1.2439383 | AG61: =IFERROR(__xludf.DUMMYFUNCTION("""COMPUTED_VALUE"""),0.0) -> 0
A62: =VLOOKUP($F62,UpdateHashtag!$V$3:$Y$32,COLUMN(B$9),0) -> 3 | B62: =VLOOKUP($F62,UpdateHashtag!$V$3:$Y$32,COLUMN(#REF!),0) -> #REF! | C62: =VLOOKUP($F62,UpdateHashtag!$V$3:$Y$32,COLUMN(#REF!),0) -> #REF! | D62: =SUM(A62:C62) -> #REF! | F62: =VLOOKUP(J62,UpdateBBM!$C$2:E1009,3,0) -> LAL | G62: 49 | H62: =IFERROR(__xludf.DUMMYFUNCTION("""COMPUTED_VALUE"""),49.0) -> 49 | J62: =IFERROR(__xludf.DUMMYFUNCTION("""COMPUTED_VALUE"""),"LeBron James") -> LeBron James | K62: =IFERROR(__xludf.DUMMYFUNCTION("""COMPUTED_VALUE"""),61.0) -> 61 | L62: =IFERROR(__xludf.DUMMYFUNCTION("""COMPUTED_VALUE"""),"F") -> F | M62: =IFERROR(__xludf.DUMMYFUNCTION("""COMPUTED_VALUE"""),2.298940247123706) -> 2.2989402 | N62: =IFERROR(__xludf.DUMMYFUNCTION("""COMPUTED_VALUE"""),2.6055084918634375) -> 2.6055085 | O62: =IFERROR(__xludf.DUMMYFUNCTION("""COMPUTED_VALUE"""),0.30656824473973154) -> 0.30656824 | P62: =IFERROR(__xludf.DUMMYFUNCTION("""COMPUTED_VALUE"""),21.74148) -> 21.74148 | Q62: =IFERROR(__xludf.DUMMYFUNCTION("""COMPUTED_VALUE"""),1.939672) -> 1.939672 | R62: =IFERROR(__xludf.DUMMYFUNCTION("""COMPUTED_VALUE"""),6.941639) -> 6.941639 | S62: =IFERROR(__xludf.DUMMYFUNCTION("""COMPUTED_VALUE"""),6.455738) -> 6.455738 | T62: =IFERROR(__xludf.DUMMYFUNCTION("""COMPUTED_VALUE"""),1.033115) -> 1.033115 | U62: =IFERROR(__xludf.DUMMYFUNCTION("""COMPUTED_VALUE"""),0.558361) -> 0.558361 | V62: =IFERROR(__xludf.DUMMYFUNCTION("""COMPUTED_VALUE"""),0.494596) -> 0.494596 | W62: =IFERROR(__xludf.DUMMYFUNCTION("""COMPUTED_VALUE"""),0.794001) -> 0.794001 | X62: =IFERROR(__xludf.DUMMYFUNCTION("""COMPUTED_VALUE"""),2.984918) -> 2.984918 | Y62: =IFERROR(__xludf.DUMMYFUNCTION("""COMPUTED_VALUE"""),0.8012239021268491) -> 0.8012239 | Z62: =IFERROR(__xludf.DUMMYFUNCTION("""COMPUTED_VALUE"""),0.16430597931934965) -> 0.16430598 | AA62: =IFERROR(__xludf.DUMMYFUNCTION("""COMPUTED_VALUE"""),0.33042130768174394) -> 0.33042131 | AB62: =IFERROR(__xludf.DUMMYFUNCTION("""COMPUTED_VALUE"""),1.2793411373109822) -> 1.2793411 | AC62: =IFERROR(__xludf.DUMMYFUNCTION("""COMPUTED_VALUE"""),-0.0367883404975053) -> -0.036788341 | AD62: =IFERROR(__xludf.DUMMYFUNCTION("""COMPUTED_VALUE"""),-0.31244241928369376) -> -0.31244242 | AE62: =IFERROR(__xludf.DUMMYFUNCTION("""COMPUTED_VALUE"""),-0.008715586458508026) -> -0.0087155865 | AF62: =IFERROR(__xludf.DUMMYFUNCTION("""COMPUTED_VALUE"""),0.07572009238052593) -> 0.075720092 | AG62: =IFERROR(__xludf.DUMMYFUNCTION("""COMPUTED_VALUE"""),0.0) -> 0
A63: =VLOOKUP($F63,UpdateHashtag!$V$3:$Y$32,COLUMN(B$9),0) -> 4 | B63: =VLOOKUP($F63,UpdateHashtag!$V$3:$Y$32,COLUMN(#REF!),0) -> #REF! | C63: =VLOOKUP($F63,UpdateHashtag!$V$3:$Y$32,COLUMN(#REF!),0) -> #REF! | D63: =SUM(A63:C63) -> #REF! | F63: =VLOOKUP(J63,UpdateBBM!$C$2:E1009,3,0) -> CLE | G63: 50 | H63: =IFERROR(__xludf.DUMMYFUNCTION("""COMPUTED_VALUE"""),50.0) -> 50 | J63: =IFERROR(__xludf.DUMMYFUNCTION("""COMPUTED_VALUE"""),"Jarrett Allen") -> Jarrett Allen | K63: =IFERROR(__xludf.DUMMYFUNCTION("""COMPUTED_VALUE"""),77.0) -> 77 | L63: =IFERROR(__xludf.DUMMYFUNCTION("""COMPUTED_VALUE"""),"C") -> C | M63: =IFERROR(__xludf.DUMMYFUNCTION("""COMPUTED_VALUE"""),2.2981056001357256) -> 2.2981056 | N63: =IFERROR(__xludf.DUMMYFUNCTION("""COMPUTED_VALUE"""),2.1713855720234716) -> 2.1713856 | O63: =IFERROR(__xludf.DUMMYFUNCTION("""COMPUTED_VALUE"""),-0.12672002811225402) -> -0.12672003 | P63: =IFERROR(__xludf.DUMMYFUNCTION("""COMPUTED_VALUE"""),13.5139) -> 13.5139 | Q63: =IFERROR(__xludf.DUMMYFUNCTION("""COMPUTED_VALUE"""),0.0) -> 0 | R63: =IFERROR(__xludf.DUMMYFUNCTION("""COMPUTED_VALUE"""),9.24987) -> 9.24987 | S63: =IFERROR(__xludf.DUMMYFUNCTION("""COMPUTED_VALUE"""),1.941688) -> 1.941688 | T63: =IFERROR(__xludf.DUMMYFUNCTION("""COMPUTED_VALUE"""),0.824805) -> 0.824805 | U63: =IFERROR(__xludf.DUMMYFUNCTION("""COMPUTED_VALUE"""),0.825065) -> 0.825065 | V63: =IFERROR(__xludf.DUMMYFUNCTION("""COMPUTED_VALUE"""),0.683118) -> 0.683118 | W63: =IFERROR(__xludf.DUMMYFUNCTION("""COMPUTED_VALUE"""),0.709998) -> 0.709998 | X63: =IFERROR(__xludf.DUMMYFUNCTION("""COMPUTED_VALUE"""),1.237662) -> 1.237662 | Y63: =IFERROR(__xludf.DUMMYFUNCTION("""COMPUTED_VALUE"""),-0.642244223039492) -> -0.64224422 | Z63: =IFERROR(__xludf.DUMMYFUNCTION("""COMPUTED_VALUE"""),-1.7090941005108098) -> -1.7090941 | AA63: =IFERROR(__xludf.DUMMYFUNCTION("""COMPUTED_VALUE"""),1.2660710676125098) -> 1.2660711 | AB63: =IFERROR(__xludf.DUMMYFUNCTION("""COMPUTED_VALUE"""),-0.9258377282470459) -> -0.92583773 | AC63: =IFERROR(__xludf.DUMMYFUNCTION("""COMPUTED_VALUE"""),-0.6715568297647121) -> -0.67155683 | AD63: =IFERROR(__xludf.DUMMYFUNCTION("""COMPUTED_VALUE"""),0.172423379084934) -> 0.17242338 | AE63: =IFERROR(__xludf.DUMMYFUNCTION("""COMPUTED_VALUE"""),3.8565715500607975) -> 3.8565715 | AF63: =IFERROR(__xludf.DUMMYFUNCTION("""COMPUTED_VALUE"""),-0.8840416436835197) -> -0.88404164 | AG63: =IFERROR(__xludf.DUMMYFUNCTION("""COMPUTED_VALUE"""),0.0) -> 0
A64: =VLOOKUP($F64,UpdateHashtag!$V$3:$Y$32,COLUMN(B$9),0) -> 4 | B64: =VLOOKUP($F64,UpdateHashtag!$V$3:$Y$32,COLUMN(#REF!),0) -> #REF! | C64: =VLOOKUP($F64,UpdateHashtag!$V$3:$Y$32,COLUMN(#REF!),0) -> #REF! | D64: =SUM(A64:C64) -> #REF! | F64: =VLOOKUP(J64,UpdateBBM!$C$2:E1009,3,0) -> PHI | G64: 51 | H64: =IFERROR(__xludf.DUMMYFUNCTION("""COMPUTED_VALUE"""),51.0) -> 51 | J64: =IFERROR(__xludf.DUMMYFUNCTION("""COMPUTED_VALUE"""),"Paul George") -> Paul George | K64: =IFERROR(__xludf.DUMMYFUNCTION("""COMPUTED_VALUE"""),53.0) -> 53 | L64: =IFERROR(__xludf.DUMMYFUNCTION("""COMPUTED_VALUE"""),"F") -> F | M64: =IFERROR(__xludf.DUMMYFUNCTION("""COMPUTED_VALUE"""),2.2248703413136077) -> 2.2248703 | N64: =IFERROR(__xludf.DUMMYFUNCTION("""COMPUTED_VALUE"""),2.3661765959317256) -> 2.3661766 | O64: =IFERROR(__xludf.DUMMYFUNCTION("""COMPUTED_VALUE"""),0.14130625461811785) -> 0.14130625 | P64: =IFERROR(__xludf.DUMMYFUNCTION("""COMPUTED_VALUE"""),16.63868) -> 16.63868 | Q64: =IFERROR(__xludf.DUMMYFUNCTION("""COMPUTED_VALUE"""),2.455849) -> 2.455849 | R64: =IFERROR(__xludf.DUMMYFUNCTION("""COMPUTED_VALUE"""),5.016038) -> 5.016038 | S64: =IFERROR(__xludf.DUMMYFUNCTION("""COMPUTED_VALUE"""),3.901509) -> 3.901509 | T64: =IFERROR(__xludf.DUMMYFUNCTION("""COMPUTED_VALUE"""),1.639623) -> 1.639623 | U64: =IFERROR(__xludf.DUMMYFUNCTION("""COMPUTED_VALUE"""),0.530189) -> 0.530189 | V64: =IFERROR(__xludf.DUMMYFUNCTION("""COMPUTED_VALUE"""),0.448288) -> 0.448288 | W64: =IFERROR(__xludf.DUMMYFUNCTION("""COMPUTED_VALUE"""),0.844995) -> 0.844995 | X64: =IFERROR(__xludf.DUMMYFUNCTION("""COMPUTED_VALUE"""),2.318491) -> 2.318491 | Y64: =IFERROR(__xludf.DUMMYFUNCTION("""COMPUTED_VALUE"""),-0.0940246580936293) -> -0.094024658 | Z64: =IFERROR(__xludf.DUMMYFUNCTION("""COMPUTED_VALUE"""),0.6628469867713789) -> 0.66284699 | AA64: =IFERROR(__xludf.DUMMYFUNCTION("""COMPUTED_VALUE"""),-0.4501280018858182) -> -0.450128 | AB64: =IFERROR(__xludf.DUMMYFUNCTION("""COMPUTED_VALUE"""),0.031563241940878436) -> 0.031563242 | AC64: =IFERROR(__xludf.DUMMYFUNCTION("""COMPUTED_VALUE"""),1.8113810555395313) -> 1.8113811 | AD64: =IFERROR(__xludf.DUMMYFUNCTION("""COMPUTED_VALUE"""),-0.36365889624557274) -> -0.3636589 | AE64: =IFERROR(__xludf.DUMMYFUNCTION("""COMPUTED_VALUE"""),-0.6315054866198391) -> -0.63150549 | AF64: =IFERROR(__xludf.DUMMYFUNCTION("""COMPUTED_VALUE"""),0.7681968679049571) -> 0.76819687 | AG64: =IFERROR(__xludf.DUMMYFUNCTION("""COMPUTED_VALUE"""),0.0) -> 0
A65: =VLOOKUP($F65,UpdateHashtag!$V$3:$Y$32,COLUMN(B$9),0) -> #N/A | B65: =VLOOKUP($F65,UpdateHashtag!$V$3:$Y$32,COLUMN(#REF!),0) -> #REF! | C65: =VLOOKUP($F65,UpdateHashtag!$V$3:$Y$32,COLUMN(#REF!),0) -> #REF! | D65: =SUM(A65:C65) -> #N/A | F65: =VLOOKUP(J65,UpdateBBM!$C$2:E1009,3,0) -> NOR | G65: 52 | H65: =IFERROR(__xludf.DUMMYFUNCTION("""COMPUTED_VALUE"""),52.0) -> 52 | J65: =IFERROR(__xludf.DUMMYFUNCTION("""COMPUTED_VALUE"""),"Jordan Poole") -> Jordan Poole | K65: =IFERROR(__xludf.DUMMYFUNCTION("""COMPUTED_VALUE"""),68.0) -> 68 | L65: =IFERROR(__xludf.DUMMYFUNCTION("""COMPUTED_VALUE"""),"G") -> G | M65: =IFERROR(__xludf.DUMMYFUNCTION("""COMPUTED_VALUE"""),2.1809019605265503) -> 2.180902 | N65: =IFERROR(__xludf.DUMMYFUNCTION("""COMPUTED_VALUE"""),2.4266255566637356) -> 2.4266256 | O65: =IFERROR(__xludf.DUMMYFUNCTION("""COMPUTED_VALUE"""),0.2457235961371853) -> 0.2457236 | P65: =IFERROR(__xludf.DUMMYFUNCTION("""COMPUTED_VALUE"""),18.92559) -> 18.92559 | Q65: =IFERROR(__xludf.DUMMYFUNCTION("""COMPUTED_VALUE"""),3.177794) -> 3.177794 | R65: =IFERROR(__xludf.DUMMYFUNCTION("""COMPUTED_VALUE"""),2.935294) -> 2.935294 | S65: =IFERROR(__xludf.DUMMYFUNCTION("""COMPUTED_VALUE"""),4.305147) -> 4.305147 | T65: =IFERROR(__xludf.DUMMYFUNCTION("""COMPUTED_VALUE"""),1.196324) -> 1.196324 | U65: =IFERROR(__xludf.DUMMYFUNCTION("""COMPUTED_VALUE"""),0.326176) -> 0.326176 | V65: =IFERROR(__xludf.DUMMYFUNCTION("""COMPUTED_VALUE"""),0.43492) -> 0.43492 | W65: =IFERROR(__xludf.DUMMYFUNCTION("""COMPUTED_VALUE"""),0.89899) -> 0.89899 | X65: =IFERROR(__xludf.DUMMYFUNCTION("""COMPUTED_VALUE"""),2.739559) -> 2.739559 | Y65: =IFERROR(__xludf.DUMMYFUNCTION("""COMPUTED_VALUE"""),0.30719680558392304) -> 0.30719681 | Z65: =IFERROR(__xludf.DUMMYFUNCTION("""COMPUTED_VALUE"""),1.360125609462733) -> 1.3601256 | AA65: =IFERROR(__xludf.DUMMYFUNCTION("""COMPUTED_VALUE"""),-1.2935650859893513) -> -1.2935651 | AB65: =IFERROR(__xludf.DUMMYFUNCTION("""COMPUTED_VALUE"""),0.22874625651451214) -> 0.22874626 | AC65: =IFERROR(__xludf.DUMMYFUNCTION("""COMPUTED_VALUE"""),0.4605470268147289) -> 0.46054703 | AD65: =IFERROR(__xludf.DUMMYFUNCTION("""COMPUTED_VALUE"""),-0.7345529440385524) -> -0.73455294 | AE65: =IFERROR(__xludf.DUMMYFUNCTION("""COMPUTED_VALUE"""),-0.7873256569198599) -> -0.78732566 | AF65: =IFERROR(__xludf.DUMMYFUNCTION("""COMPUTED_VALUE"""),1.5918884592462506) -> 1.5918885 | AG65: =IFERROR(__xludf.DUMMYFUNCTION("""COMPUTED_VALUE"""),0.0) -> 0
A66: =VLOOKUP($F66,UpdateHashtag!$V$3:$Y$32,COLUMN(B$9),0) -> 4 | B66: =VLOOKUP($F66,UpdateHashtag!$V$3:$Y$32,COLUMN(#REF!),0) -> #REF! | C66: =VLOOKUP($F66,UpdateHashtag!$V$3:$Y$32,COLUMN(#REF!),0) -> #REF! | D66: =SUM(A66:C66) -> #REF! | F66: =VLOOKUP(J66,UpdateBBM!$C$2:E1009,3,0) -> HOU | G66: 53 | H66: =IFERROR(__xludf.DUMMYFUNCTION("""COMPUTED_VALUE"""),53.0) -> 53 | J66: =IFERROR(__xludf.DUMMYFUNCTION("""COMPUTED_VALUE"""),"Alperen Sengun") -> Alperen Sengun | K66: =IFERROR(__xludf.DUMMYFUNCTION("""COMPUTED_VALUE"""),73.0) -> 73 | L66: =IFERROR(__xludf.DUMMYFUNCTION("""COMPUTED_VALUE"""),"C") -> C | M66: =IFERROR(__xludf.DUMMYFUNCTION("""COMPUTED_VALUE"""),2.1722127714274655) -> 2.1722128 | N66: =IFERROR(__xludf.DUMMYFUNCTION("""COMPUTED_VALUE"""),2.392092413426382) -> 2.3920924 | O66: =IFERROR(__xludf.DUMMYFUNCTION("""COMPUTED_VALUE"""),0.2198796419989164) -> 0.21987964 | P66: =IFERROR(__xludf.DUMMYFUNCTION("""COMPUTED_VALUE"""),21.69712) -> 21.69712 | Q66: =IFERROR(__xludf.DUMMYFUNCTION("""COMPUTED_VALUE"""),0.259589) -> 0.259589 | R66: =IFERROR(__xludf.DUMMYFUNCTION("""COMPUTED_VALUE"""),9.897945) -> 9.897945 | S66: =IFERROR(__xludf.DUMMYFUNCTION("""COMPUTED_VALUE"""),5.252055) -> 5.252055 | T66: =IFERROR(__xludf.DUMMYFUNCTION("""COMPUTED_VALUE"""),1.01) -> 1.01 | U66: =IFERROR(__xludf.DUMMYFUNCTION("""COMPUTED_VALUE"""),0.81137) -> 0.81137 | V66: =IFERROR(__xludf.DUMMYFUNCTION("""COMPUTED_VALUE"""),0.525203) -> 0.525203 | W66: =IFERROR(__xludf.DUMMYFUNCTION("""COMPUTED_VALUE"""),0.684007) -> 0.684007 | X66: =IFERROR(__xludf.DUMMYFUNCTION("""COMPUTED_VALUE"""),2.635342) -> 2.635342 | Y66: =IFERROR(__xludf.DUMMYFUNCTION("""COMPUTED_VALUE"""),0.7934412678610777) -> 0.79344127 | Z66: =IFERROR(__xludf.DUMMYFUNCTION("""COMPUTED_VALUE"""),-1.4583743637083857) -> -1.4583744 | AA66: =IFERROR(__xludf.DUMMYFUNCTION("""COMPUTED_VALUE"""),1.5287706059893584) -> 1.5287706 | AB66: =IFERROR(__xludf.DUMMYFUNCTION("""COMPUTED_VALUE"""),0.6913245419184891) -> 0.69132454 | AC66: =IFERROR(__xludf.DUMMYFUNCTION("""COMPUTED_VALUE"""),-0.10722506283158183) -> -0.10722506 | AD66: =IFERROR(__xludf.DUMMYFUNCTION("""COMPUTED_VALUE"""),0.14752597556395808) -> 0.14752598 | AE66: =IFERROR(__xludf.DUMMYFUNCTION("""COMPUTED_VALUE"""),0.4736315578297787) -> 0.47363156 | AF66: =IFERROR(__xludf.DUMMYFUNCTION("""COMPUTED_VALUE"""),-1.135376472904698) -> -1.1353765 | AG66: =IFERROR(__xludf.DUMMYFUNCTION("""COMPUTED_VALUE"""),0.0) -> 0
A67: =VLOOKUP($F67,UpdateHashtag!$V$3:$Y$32,COLUMN(B$9),0) -> 4 | B67: =VLOOKUP($F67,UpdateHashtag!$V$3:$Y$32,COLUMN(#REF!),0) -> #REF! | C67: =VLOOKUP($F67,UpdateHashtag!$V$3:$Y$32,COLUMN(#REF!),0) -> #REF! | D67: =SUM(A67:C67) -> #REF! | F67: =VLOOKUP(J67,UpdateBBM!$C$2:E1009,3,0) -> OKC | G67: 54 | H67: =IFERROR(__xludf.DUMMYFUNCTION("""COMPUTED_VALUE"""),54.0) -> 54 | J67: =IFERROR(__xludf.DUMMYFUNCTION("""COMPUTED_VALUE"""),"Chet Holmgren") -> Chet Holmgren | K67: =IFERROR(__xludf.DUMMYFUNCTION("""COMPUTED_VALUE"""),62.0) -> 62 | L67: =IFERROR(__xludf.DUMMYFUNCTION("""COMPUTED_VALUE"""),"F,C") -> F,C | M67: =IFERROR(__xludf.DUMMYFUNCTION("""COMPUTED_VALUE"""),2.170239002023937) -> 2.170239 | N67: =IFERROR(__xludf.DUMMYFUNCTION("""COMPUTED_VALUE"""),2.1755692126891777) -> 2.1755692 | O67: =IFERROR(__xludf.DUMMYFUNCTION("""COMPUTED_VALUE"""),0.005330210665240642) -> 0.0053302107 | P67: =IFERROR(__xludf.DUMMYFUNCTION("""COMPUTED_VALUE"""),16.75968) -> 16.75968 | Q67: =IFERROR(__xludf.DUMMYFUNCTION("""COMPUTED_VALUE"""),1.498226) -> 1.498226 | R67: =IFERROR(__xludf.DUMMYFUNCTION("""COMPUTED_VALUE"""),8.287419) -> 8.287419 | S67: =IFERROR(__xludf.DUMMYFUNCTION("""COMPUTED_VALUE"""),2.248065) -> 2.248065 | T67: =IFERROR(__xludf.DUMMYFUNCTION("""COMPUTED_VALUE"""),0.776452) -> 0.776452 | U67: =IFERROR(__xludf.DUMMYFUNCTION("""COMPUTED_VALUE"""),2.04) -> 2.04 | V67: =IFERROR(__xludf.DUMMYFUNCTION("""COMPUTED_VALUE"""),0.515974) -> 0.515974 | W67: =IFERROR(__xludf.DUMMYFUNCTION("""COMPUTED_VALUE"""),0.764011) -> 0.764011 | X67: =IFERROR(__xludf.DUMMYFUNCTION("""COMPUTED_VALUE"""),1.770161) -> 1.770161 | Y67: =IFERROR(__xludf.DUMMYFUNCTION("""COMPUTED_VALUE"""),-0.07279610204858016) -> -0.072796102 | Z67: =IFERROR(__xludf.DUMMYFUNCTION("""COMPUTED_VALUE"""),-0.2620573293435091) -> -0.26205733 | AA67: =IFERROR(__xludf.DUMMYFUNCTION("""COMPUTED_VALUE"""),0.8759380839141168) -> 0.87593808 | AB67: =IFERROR(__xludf.DUMMYFUNCTION("""COMPUTED_VALUE"""),-0.7761681221742129) -> -0.77616812 | AC67: =IFERROR(__xludf.DUMMYFUNCTION("""COMPUTED_VALUE"""),-0.8188995438040632) -> -0.81889954 | AD67: =IFERROR(__xludf.DUMMYFUNCTION("""COMPUTED_VALUE"""),2.3811657629299035) -> 2.3811658 | AE67: =IFERROR(__xludf.DUMMYFUNCTION("""COMPUTED_VALUE"""),0.3222615198596845) -> 0.32226152 | AF67: =IFERROR(__xludf.DUMMYFUNCTION("""COMPUTED_VALUE"""),-0.29277460044822506) -> -0.2927746 | AG67: =IFERROR(__xludf.DUMMYFUNCTION("""COMPUTED_VALUE"""),0.0) -> 0
A68: =VLOOKUP($F68,UpdateHashtag!$V$3:$Y$32,COLUMN(B$9),0) -> #N/A | B68: =VLOOKUP($F68,UpdateHashtag!$V$3:$Y$32,COLUMN(#REF!),0) -> #REF! | C68: =VLOOKUP($F68,UpdateHashtag!$V$3:$Y$32,COLUMN(#REF!),0) -> #REF! | D68: =SUM(A68:C68) -> #N/A | F68: =VLOOKUP(J68,UpdateBBM!$C$2:E1009,3,0) -> NYK | G68: 55 | H68: =IFERROR(__xludf.DUMMYFUNCTION("""COMPUTED_VALUE"""),55.0) -> 55 | J68: =IFERROR(__xludf.DUMMYFUNCTION("""COMPUTED_VALUE"""),"O.G. Anunoby") -> O.G. Anunoby | K68: =IFERROR(__xludf.DUMMYFUNCTION("""COMPUTED_VALUE"""),68.0) -> 68 | L68: =IFERROR(__xludf.DUMMYFUNCTION("""COMPUTED_VALUE"""),"F") -> F | M68: =IFERROR(__xludf.DUMMYFUNCTION("""COMPUTED_VALUE"""),2.117592930222621) -> 2.1175929 | N68: =IFERROR(__xludf.DUMMYFUNCTION("""COMPUTED_VALUE"""),2.059866491643257) -> 2.0598665 | O68: =IFERROR(__xludf.DUMMYFUNCTION("""COMPUTED_VALUE"""),-0.05772643857936366) -> -0.057726439 | P68: =IFERROR(__xludf.DUMMYFUNCTION("""COMPUTED_VALUE"""),18.63368) -> 18.63368 | Q68: =IFERROR(__xludf.DUMMYFUNCTION("""COMPUTED_VALUE"""),2.3825) -> 2.3825 | R68: =IFERROR(__xludf.DUMMYFUNCTION("""COMPUTED_VALUE"""),4.62) -> 4.62 | S68: =IFERROR(__xludf.DUMMYFUNCTION("""COMPUTED_VALUE"""),2.382206) -> 2.382206 | T68: =IFERROR(__xludf.DUMMYFUNCTION("""COMPUTED_VALUE"""),1.510882) -> 1.510882 | U68: =IFERROR(__xludf.DUMMYFUNCTION("""COMPUTED_VALUE"""),0.868382) -> 0.868382 | V68: =IFERROR(__xludf.DUMMYFUNCTION("""COMPUTED_VALUE"""),0.476605) -> 0.476605 | W68: =IFERROR(__xludf.DUMMYFUNCTION("""COMPUTED_VALUE"""),0.81999) -> 0.81999 | X68: =IFERROR(__xludf.DUMMYFUNCTION("""COMPUTED_VALUE"""),1.515882) -> 1.515882 | Y68: =IFERROR(__xludf.DUMMYFUNCTION("""COMPUTED_VALUE"""),0.25598335273177103) -> 0.25598335 | Z68: =IFERROR(__xludf.DUMMYFUNCTION("""COMPUTED_VALUE"""),0.5920040697960021) -> 0.59200407 | AA68: =IFERROR(__xludf.DUMMYFUNCTION("""COMPUTED_VALUE"""),-0.6106634334017543) -> -0.61066343 | AB68: =IFERROR(__xludf.DUMMYFUNCTION("""COMPUTED_VALUE"""),-0.710638299020987) -> -0.7106383 | AC68: =IFERROR(__xludf.DUMMYFUNCTION("""COMPUTED_VALUE"""),1.4190776131855902) -> 1.4190776 | AD68: =IFERROR(__xludf.DUMMYFUNCTION("""COMPUTED_VALUE"""),0.25117334829399657) -> 0.25117335 | AE68: =IFERROR(__xludf.DUMMYFUNCTION("""COMPUTED_VALUE"""),-0.26597787472076323) -> -0.26597787 | AF68: =IFERROR(__xludf.DUMMYFUNCTION("""COMPUTED_VALUE"""),0.41826941575841486) -> 0.41826942 | AG68: =IFERROR(__xludf.DUMMYFUNCTION("""COMPUTED_VALUE"""),0.0) -> 0
A69: =VLOOKUP($F69,UpdateHashtag!$V$3:$Y$32,COLUMN(B$9),0) -> 4 | B69: =VLOOKUP($F69,UpdateHashtag!$V$3:$Y$32,COLUMN(#REF!),0) -> #REF! | C69: =VLOOKUP($F69,UpdateHashtag!$V$3:$Y$32,COLUMN(#REF!),0) -> #REF! | D69: =SUM(A69:C69) -> #REF! | F69: =VLOOKUP(J69,UpdateBBM!$C$2:E1009,3,0) -> OKC | G69: 56 | H69: =IFERROR(__xludf.DUMMYFUNCTION("""COMPUTED_VALUE"""),56.0) -> 56 | J69: =IFERROR(__xludf.DUMMYFUNCTION("""COMPUTED_VALUE"""),"Jalen Williams") -> Jalen Williams | K69: =IFERROR(__xludf.DUMMYFUNCTION("""COMPUTED_VALUE"""),73.0) -> 73 | L69: =IFERROR(__xludf.DUMMYFUNCTION("""COMPUTED_VALUE"""),"G,F") -> G,F | M69: =IFERROR(__xludf.DUMMYFUNCTION("""COMPUTED_VALUE"""),2.004798053519622) -> 2.0047981 | N69: =IFERROR(__xludf.DUMMYFUNCTION("""COMPUTED_VALUE"""),2.0433112496013495) -> 2.0433112 | O69: =IFERROR(__xludf.DUMMYFUNCTION("""COMPUTED_VALUE"""),0.03851319608172732) -> 0.038513196 | P69: =IFERROR(__xludf.DUMMYFUNCTION("""COMPUTED_VALUE"""),22.20082) -> 22.20082 | Q69: =IFERROR(__xludf.DUMMYFUNCTION("""COMPUTED_VALUE"""),1.76274) -> 1.76274 | R69: =IFERROR(__xludf.DUMMYFUNCTION("""COMPUTED_VALUE"""),5.032055) -> 5.032055 | S69: =IFERROR(__xludf.DUMMYFUNCTION("""COMPUTED_VALUE"""),4.76) -> 4.76 | T69: =IFERROR(__xludf.DUMMYFUNCTION("""COMPUTED_VALUE"""),1.36) -> 1.36 | U69: =IFERROR(__xludf.DUMMYFUNCTION("""COMPUTED_VALUE"""),0.476027) -> 0.476027 | V69: =IFERROR(__xludf.DUMMYFUNCTION("""COMPUTED_VALUE"""),0.498437) -> 0.498437 | W69: =IFERROR(__xludf.DUMMYFUNCTION("""COMPUTED_VALUE"""),0.799989) -> 0.799989 | X69: =IFERROR(__xludf.DUMMYFUNCTION("""COMPUTED_VALUE"""),1.903973) -> 1.903973 | Y69: =IFERROR(__xludf.DUMMYFUNCTION("""COMPUTED_VALUE"""),0.8818117114965434) -> 0.88181171 | Z69: =IFERROR(__xludf.DUMMYFUNCTION("""COMPUTED_VALUE"""),-0.0065808628501047356) -> -0.0065808628 | AA69: =IFERROR(__xludf.DUMMYFUNCTION("""COMPUTED_VALUE"""),-0.4436354531743544) -> -0.44363545 | AB69: =IFERROR(__xludf.DUMMYFUNCTION("""COMPUTED_VALUE"""),0.45094854105625753) -> 0.45094854 | AC69: =IFERROR(__xludf.DUMMYFUNCTION("""COMPUTED_VALUE"""),0.9593054505548251) -> 0.95930545 | AD69: =IFERROR(__xludf.DUMMYFUNCTION("""COMPUTED_VALUE"""),-0.46212499113444444) -> -0.46212499 | AE69: =IFERROR(__xludf.DUMMYFUNCTION("""COMPUTED_VALUE"""),0.04872782875672441) -> 0.048727829 | AF69: =IFERROR(__xludf.DUMMYFUNCTION("""COMPUTED_VALUE"""),0.1527340337614584) -> 0.15273403 | AG69: =IFERROR(__xludf.DUMMYFUNCTION("""COMPUTED_VALUE"""),0.0) -> 0
A70: =VLOOKUP($F70,UpdateHashtag!$V$3:$Y$32,COLUMN(B$9),0) -> 4 | B70: =VLOOKUP($F70,UpdateHashtag!$V$3:$Y$32,COLUMN(#REF!),0) -> #REF! | C70: =VLOOKUP($F70,UpdateHashtag!$V$3:$Y$32,COLUMN(#REF!),0) -> #REF! | D70: =SUM(A70:C70) -> #REF! | F70: =VLOOKUP(J70,UpdateBBM!$C$2:E1009,3,0) -> MIA | G70: 57 | H70: =IFERROR(__xludf.DUMMYFUNCTION("""COMPUTED_VALUE"""),57.0) -> 57 | J70: =IFERROR(__xludf.DUMMYFUNCTION("""COMPUTED_VALUE"""),"Bam Adebayo") -> Bam Adebayo | K70: =IFERROR(__xludf.DUMMYFUNCTION("""COMPUTED_VALUE"""),73.0) -> 73 | L70: =IFERROR(__xludf.DUMMYFUNCTION("""COMPUTED_VALUE"""),"F,C") -> F,C | M70: =IFERROR(__xludf.DUMMYFUNCTION("""COMPUTED_VALUE"""),1.9946263248309755) -> 1.9946263 | N70: =IFERROR(__xludf.DUMMYFUNCTION("""COMPUTED_VALUE"""),1.991356019098474) -> 1.991356 | O70: =IFERROR(__xludf.DUMMYFUNCTION("""COMPUTED_VALUE"""),-0.0032703057325014218) -> -0.0032703057 | P70: =IFERROR(__xludf.DUMMYFUNCTION("""COMPUTED_VALUE"""),19.5174) -> 19.5174 | Q70: =IFERROR(__xludf.DUMMYFUNCTION("""COMPUTED_VALUE"""),1.322055) -> 1.322055 | R70: =IFERROR(__xludf.DUMMYFUNCTION("""COMPUTED_VALUE"""),8.468767) -> 8.468767 | S70: =IFERROR(__xludf.DUMMYFUNCTION("""COMPUTED_VALUE"""),4.373288) -> 4.373288 | T70: =IFERROR(__xludf.DUMMYFUNCTION("""COMPUTED_VALUE"""),1.318904) -> 1.318904 | U70: =IFERROR(__xludf.DUMMYFUNCTION("""COMPUTED_VALUE"""),0.556164) -> 0.556164 | V70: =IFERROR(__xludf.DUMMYFUNCTION("""COMPUTED_VALUE"""),0.47959) -> 0.47959 | W70: =IFERROR(__xludf.DUMMYFUNCTION("""COMPUTED_VALUE"""),0.794011) -> 0.794011 | X70: =IFERROR(__xludf.DUMMYFUNCTION("""COMPUTED_VALUE"""),1.735479) -> 1.735479 | Y70: =IFERROR(__xludf.DUMMYFUNCTION("""COMPUTED_VALUE"""),0.41102549775764735) -> 0.4110255 | Z70: =IFERROR(__xludf.DUMMYFUNCTION("""COMPUTED_VALUE"""),-0.432209172265281) -> -0.43220917 | AA70: =IFERROR(__xludf.DUMMYFUNCTION("""COMPUTED_VALUE"""),0.9494481497021269) -> 0.94944815 | AB70: =IFERROR(__xludf.DUMMYFUNCTION("""COMPUTED_VALUE"""),0.26203412286025246) -> 0.26203412 | AC70: =IFERROR(__xludf.DUMMYFUNCTION("""COMPUTED_VALUE"""),0.8340764849030314) -> 0.83407648 | AD70: =IFERROR(__xludf.DUMMYFUNCTION("""COMPUTED_VALUE"""),-0.31643654820195477) -> -0.31643655 | AE70: =IFERROR(__xludf.DUMMYFUNCTION("""COMPUTED_VALUE"""),-0.22463944014617288) -> -0.22463944 | AF70: =IFERROR(__xludf.DUMMYFUNCTION("""COMPUTED_VALUE"""),0.07584775222354366) -> 0.075847752 | AG70: =IFERROR(__xludf.DUMMYFUNCTION("""COMPUTED_VALUE"""),0.0) -> 0
A71: =VLOOKUP($F71,UpdateHashtag!$V$3:$Y$32,COLUMN(B$9),0) -> 4 | B71: =VLOOKUP($F71,UpdateHashtag!$V$3:$Y$32,COLUMN(#REF!),0) -> #REF! | C71: =VLOOKUP($F71,UpdateHashtag!$V$3:$Y$32,COLUMN(#REF!),0) -> #REF! | D71: =SUM(A71:C71) -> #REF! | F71: =VLOOKUP(J71,UpdateBBM!$C$2:E1009,3,0) -> POR | G71: 58 | H71: =IFERROR(__xludf.DUMMYFUNCTION("""COMPUTED_VALUE"""),58.0) -> 58 | J71: =IFERROR(__xludf.DUMMYFUNCTION("""COMPUTED_VALUE"""),"Deni Avdija") -> Deni Avdija | K71: =IFERROR(__xludf.DUMMYFUNCTION("""COMPUTED_VALUE"""),73.0) -> 73 | L71: =IFERROR(__xludf.DUMMYFUNCTION("""COMPUTED_VALUE"""),"G,F") -> G,F | M71: =IFERROR(__xludf.DUMMYFUNCTION("""COMPUTED_VALUE"""),1.920973517360369) -> 1.9209735 | N71: =IFERROR(__xludf.DUMMYFUNCTION("""COMPUTED_VALUE"""),2.304657262510646) -> 2.3046573 | O71: =IFERROR(__xludf.DUMMYFUNCTION("""COMPUTED_VALUE"""),0.3836837451502768) -> 0.38368375 | P71: =IFERROR(__xludf.DUMMYFUNCTION("""COMPUTED_VALUE"""),22.23795) -> 22.23795 | Q71: =IFERROR(__xludf.DUMMYFUNCTION("""COMPUTED_VALUE"""),2.328904) -> 2.328904 | R71: =IFERROR(__xludf.DUMMYFUNCTION("""COMPUTED_VALUE"""),8.344932) -> 8.344932 | S71: =IFERROR(__xludf.DUMMYFUNCTION("""COMPUTED_VALUE"""),4.658767) -> 4.658767 | T71: =IFERROR(__xludf.DUMMYFUNCTION("""COMPUTED_VALUE"""),1.054795) -> 1.054795 | U71: =IFERROR(__xludf.DUMMYFUNCTION("""COMPUTED_VALUE"""),0.42) -> 0.42 | V71: =IFERROR(__xludf.DUMMYFUNCTION("""COMPUTED_VALUE"""),0.477298) -> 0.477298 | W71: =IFERROR(__xludf.DUMMYFUNCTION("""COMPUTED_VALUE"""),0.771993) -> 0.771993 | X71: =IFERROR(__xludf.DUMMYFUNCTION("""COMPUTED_VALUE"""),3.29589) -> 3.29589 | Y71: =IFERROR(__xludf.DUMMYFUNCTION("""COMPUTED_VALUE"""),0.8883258956779707) -> 0.8883259 | Z71: =IFERROR(__xludf.DUMMYFUNCTION("""COMPUTED_VALUE"""),0.5402392607568569) -> 0.54023926 | AA71: =IFERROR(__xludf.DUMMYFUNCTION("""COMPUTED_VALUE"""),0.8992511858709392) -> 0.89925119 | AB71: =IFERROR(__xludf.DUMMYFUNCTION("""COMPUTED_VALUE"""),0.4014947529730428) -> 0.40149475 | AC71: =IFERROR(__xludf.DUMMYFUNCTION("""COMPUTED_VALUE"""),0.029275606731686738) -> 0.029275607 | AD71: =IFERROR(__xludf.DUMMYFUNCTION("""COMPUTED_VALUE"""),-0.5639816415228867) -> -0.56398164 | AE71: =IFERROR(__xludf.DUMMYFUNCTION("""COMPUTED_VALUE"""),-0.25642842441571473) -> -0.25642842 | AF71: =IFERROR(__xludf.DUMMYFUNCTION("""COMPUTED_VALUE"""),-0.197501015084136) -> -0.19750102 | AG71: =IFERROR(__xludf.DUMMYFUNCTION("""COMPUTED_VALUE"""),0.0) -> 0
A72: =VLOOKUP($F72,UpdateHashtag!$V$3:$Y$32,COLUMN(B$9),0) -> 3 | B72: =VLOOKUP($F72,UpdateHashtag!$V$3:$Y$32,COLUMN(#REF!),0) -> #REF! | C72: =VLOOKUP($F72,UpdateHashtag!$V$3:$Y$32,COLUMN(#REF!),0) -> #REF! | D72: =SUM(A72:C72) -> #REF! | F72: =VLOOKUP(J72,UpdateBBM!$C$2:E1009,3,0) -> TOR | G72: 59 | H72: =IFERROR(__xludf.DUMMYFUNCTION("""COMPUTED_VALUE"""),59.0) -> 59 | J72: =IFERROR(__xludf.DUMMYFUNCTION("""COMPUTED_VALUE"""),"Immanuel Quickley") -> Immanuel Quickley | K72: =IFERROR(__xludf.DUMMYFUNCTION("""COMPUTED_VALUE"""),73.0) -> 73 | L72: =IFERROR(__xludf.DUMMYFUNCTION("""COMPUTED_VALUE"""),"G") -> G | M72: =IFERROR(__xludf.DUMMYFUNCTION("""COMPUTED_VALUE"""),1.9116785037857609) -> 1.9116785 | N72: =IFERROR(__xludf.DUMMYFUNCTION("""COMPUTED_VALUE"""),1.9037543173302212) -> 1.9037543 | O72: =IFERROR(__xludf.DUMMYFUNCTION("""COMPUTED_VALUE"""),-0.007924186455539717) -> -0.0079241865 | P72: =IFERROR(__xludf.DUMMYFUNCTION("""COMPUTED_VALUE"""),17.72644) -> 17.72644 | Q72: =IFERROR(__xludf.DUMMYFUNCTION("""COMPUTED_VALUE"""),2.901644) -> 2.901644 | R72: =IFERROR(__xludf.DUMMYFUNCTION("""COMPUTED_VALUE"""),4.463288) -> 4.463288 | S72: =IFERROR(__xludf.DUMMYFUNCTION("""COMPUTED_VALUE"""),6.24863) -> 6.24863 | T72: =IFERROR(__xludf.DUMMYFUNCTION("""COMPUTED_VALUE"""),0.96137) -> 0.96137 | U72: =IFERROR(__xludf.DUMMYFUNCTION("""COMPUTED_VALUE"""),0.13589) -> 0.13589 | V72: =IFERROR(__xludf.DUMMYFUNCTION("""COMPUTED_VALUE"""),0.436883) -> 0.436883 | W72: =IFERROR(__xludf.DUMMYFUNCTION("""COMPUTED_VALUE"""),0.876018) -> 0.876018 | X72: =IFERROR(__xludf.DUMMYFUNCTION("""COMPUTED_VALUE"""),1.716712) -> 1.716712 | Y72: =IFERROR(__xludf.DUMMYFUNCTION("""COMPUTED_VALUE"""),0.09681479747300616) -> 0.096814797 | Z72: =IFERROR(__xludf.DUMMYFUNCTION("""COMPUTED_VALUE"""),1.0934107050638973) -> 1.0934107 | AA72: =IFERROR(__xludf.DUMMYFUNCTION("""COMPUTED_VALUE"""),-0.6741872077459469) -> -0.67418721 | AB72: =IFERROR(__xludf.DUMMYFUNCTION("""COMPUTED_VALUE"""),1.178165876849093) -> 1.1781659 | AC72: =IFERROR(__xludf.DUMMYFUNCTION("""COMPUTED_VALUE"""),-0.2554118595915276) -> -0.25541186 | AD72: =IFERROR(__xludf.DUMMYFUNCTION("""COMPUTED_VALUE"""),-1.080491412559357) -> -1.0804914 | AE72: =IFERROR(__xludf.DUMMYFUNCTION("""COMPUTED_VALUE"""),-0.7651170548745709) -> -0.76511705 | AF72: =IFERROR(__xludf.DUMMYFUNCTION("""COMPUTED_VALUE"""),1.2300790601562699) -> 1.2300791 | AG72: =IFERROR(__xludf.DUMMYFUNCTION("""COMPUTED_VALUE"""),0.0) -> 0
A73: =VLOOKUP($F73,UpdateHashtag!$V$3:$Y$32,COLUMN(B$9),0) -> #N/A | B73: =VLOOKUP($F73,UpdateHashtag!$V$3:$Y$32,COLUMN(#REF!),0) -> #REF! | C73: =VLOOKUP($F73,UpdateHashtag!$V$3:$Y$32,COLUMN(#REF!),0) -> #REF! | D73: =SUM(A73:C73) -> #N/A | F73: =VLOOKUP(J73,UpdateBBM!$C$2:E1009,3,0) -> NOR | G73: 60 | H73: =IFERROR(__xludf.DUMMYFUNCTION("""COMPUTED_VALUE"""),60.0) -> 60 | J73: =IFERROR(__xludf.DUMMYFUNCTION("""COMPUTED_VALUE"""),"Trey Murphy") -> Trey Murphy | K73: =IFERROR(__xludf.DUMMYFUNCTION("""COMPUTED_VALUE"""),66.0) -> 66 | L73: =IFERROR(__xludf.DUMMYFUNCTION("""COMPUTED_VALUE"""),"F") -> F | M73: =IFERROR(__xludf.DUMMYFUNCTION("""COMPUTED_VALUE"""),1.8894886352866078) -> 1.8894886 | N73: =IFERROR(__xludf.DUMMYFUNCTION("""COMPUTED_VALUE"""),1.8461592955049975) -> 1.8461593 | O73: =IFERROR(__xludf.DUMMYFUNCTION("""COMPUTED_VALUE"""),-0.043329339781610354) -> -0.04332934 | P73: =IFERROR(__xludf.DUMMYFUNCTION("""COMPUTED_VALUE"""),19.88212) -> 19.88212 | Q73: =IFERROR(__xludf.DUMMYFUNCTION("""COMPUTED_VALUE"""),3.000303) -> 3.000303 | R73: =IFERROR(__xludf.DUMMYFUNCTION("""COMPUTED_VALUE"""),5.079394) -> 5.079394 | S73: =IFERROR(__xludf.DUMMYFUNCTION("""COMPUTED_VALUE"""),3.219394) -> 3.219394 | T73: =IFERROR(__xludf.DUMMYFUNCTION("""COMPUTED_VALUE"""),0.995303) -> 0.995303 | U73: =IFERROR(__xludf.DUMMYFUNCTION("""COMPUTED_VALUE"""),0.646667) -> 0.646667 | V73: =IFERROR(__xludf.DUMMYFUNCTION("""COMPUTED_VALUE"""),0.468123) -> 0.468123 | W73: =IFERROR(__xludf.DUMMYFUNCTION("""COMPUTED_VALUE"""),0.872001) -> 0.872001 | X73: =IFERROR(__xludf.DUMMYFUNCTION("""COMPUTED_VALUE"""),1.573939) -> 1.573939 | Y73: =IFERROR(__xludf.DUMMYFUNCTION("""COMPUTED_VALUE"""),0.475012927185337) -> 0.47501293 | Z73: =IFERROR(__xludf.DUMMYFUNCTION("""COMPUTED_VALUE"""),1.1886988664004345) -> 1.1886989 | AA73: =IFERROR(__xludf.DUMMYFUNCTION("""COMPUTED_VALUE"""),-0.42444641880761963) -> -0.42444642 | AB73: =IFERROR(__xludf.DUMMYFUNCTION("""COMPUTED_VALUE"""),-0.30165982423696946) -> -0.30165982 | AC73: =IFERROR(__xludf.DUMMYFUNCTION("""COMPUTED_VALUE"""),-0.15201020270369606) -> -0.1520102 | AD73: =IFERROR(__xludf.DUMMYFUNCTION("""COMPUTED_VALUE"""),-0.15190279786541722) -> -0.1519028 | AE73: =IFERROR(__xludf.DUMMYFUNCTION("""COMPUTED_VALUE"""),-0.38052096876503483) -> -0.38052097 | AF73: =IFERROR(__xludf.DUMMYFUNCTION("""COMPUTED_VALUE"""),1.1685412954903436) -> 1.1685413 | AG73: =IFERROR(__xludf.DUMMYFUNCTION("""COMPUTED_VALUE"""),0.0) -> 0
A74: =VLOOKUP($F74,UpdateHashtag!$V$3:$Y$32,COLUMN(B$9),0) -> #N/A | B74: =VLOOKUP($F74,UpdateHashtag!$V$3:$Y$32,COLUMN(#REF!),0) -> #REF! | C74: =VLOOKUP($F74,UpdateHashtag!$V$3:$Y$32,COLUMN(#REF!),0) -> #REF! | D74: =SUM(A74:C74) -> #N/A | F74: =VLOOKUP(J74,UpdateBBM!$C$2:E1009,3,0) -> NYK | G74: 61 | H74: =IFERROR(__xludf.DUMMYFUNCTION("""COMPUTED_VALUE"""),61.0) -> 61 | J74: =IFERROR(__xludf.DUMMYFUNCTION("""COMPUTED_VALUE"""),"Jalen Brunson") -> Jalen Brunson | K74: =IFERROR(__xludf.DUMMYFUNCTION("""COMPUTED_VALUE"""),68.0) -> 68 | L74: =IFERROR(__xludf.DUMMYFUNCTION("""COMPUTED_VALUE"""),"G") -> G | M74: =IFERROR(__xludf.DUMMYFUNCTION("""COMPUTED_VALUE"""),1.8758865971042749) -> 1.8758866 | N74: =IFERROR(__xludf.DUMMYFUNCTION("""COMPUTED_VALUE"""),2.0886796536381587) -> 2.0886797 | O74: =IFERROR(__xludf.DUMMYFUNCTION("""COMPUTED_VALUE"""),0.2127930565338838) -> 0.21279306 | P74: =IFERROR(__xludf.DUMMYFUNCTION("""COMPUTED_VALUE"""),24.84897) -> 24.84897 | Q74: =IFERROR(__xludf.DUMMYFUNCTION("""COMPUTED_VALUE"""),2.247647) -> 2.247647 | R74: =IFERROR(__xludf.DUMMYFUNCTION("""COMPUTED_VALUE"""),2.815294) -> 2.815294 | S74: =IFERROR(__xludf.DUMMYFUNCTION("""COMPUTED_VALUE"""),6.713382) -> 6.713382 | T74: =IFERROR(__xludf.DUMMYFUNCTION("""COMPUTED_VALUE"""),0.933676) -> 0.933676 | U74: =IFERROR(__xludf.DUMMYFUNCTION("""COMPUTED_VALUE"""),0.144853) -> 0.144853 | V74: =IFERROR(__xludf.DUMMYFUNCTION("""COMPUTED_VALUE"""),0.482759) -> 0.482759 | W74: =IFERROR(__xludf.DUMMYFUNCTION("""COMPUTED_VALUE"""),0.82301) -> 0.82301 | X74: =IFERROR(__xludf.DUMMYFUNCTION("""COMPUTED_VALUE"""),2.606765) -> 2.606765 | Y74: =IFERROR(__xludf.DUMMYFUNCTION("""COMPUTED_VALUE"""),1.3464100643122252) -> 1.3464101 | Z74: =IFERROR(__xludf.DUMMYFUNCTION("""COMPUTED_VALUE"""),0.46175853293959757) -> 0.46175853 | AA74: =IFERROR(__xludf.DUMMYFUNCTION("""COMPUTED_VALUE"""),-1.3422075187405325) -> -1.3422075 | AB74: =IFERROR(__xludf.DUMMYFUNCTION("""COMPUTED_VALUE"""),1.405203966397464) -> 1.405204 | AC74: =IFERROR(__xludf.DUMMYFUNCTION("""COMPUTED_VALUE"""),-0.33980184827073656) -> -0.33980185 | AD74: =IFERROR(__xludf.DUMMYFUNCTION("""COMPUTED_VALUE"""),-1.0641967482469432) -> -1.0641967 | AE74: =IFERROR(__xludf.DUMMYFUNCTION("""COMPUTED_VALUE"""),-0.18016700372411776) -> -0.180167 | AF74: =IFERROR(__xludf.DUMMYFUNCTION("""COMPUTED_VALUE"""),0.4594726902306693) -> 0.45947269 | AG74: =IFERROR(__xludf.DUMMYFUNCTION("""COMPUTED_VALUE"""),0.0) -> 0
