Workbook

Sheet Draft
B2: Pick | C2: Your Pick | D2: Round 1 | E2: Round 2 | F2: Round 3 | G2: Round 4 | H2: Round 5 | I2: Round 6 | J2: Round 7 | K2: Round 8 | L2: Round 9 | M2: Round 10 | N2: Round 11 | O2: Round 12 | P2: Round 13 | Q2: Round 14
B3: 1 | C3: =IF(B3=Projections!$G$3,TRUE) -> FALSE | D3: Victor Wembanyama
B4: 2 | C4: =IF(B4=Projections!$G$3,TRUE) -> FALSE
B5: 3 | C5: =IF(B5=Projections!$G$3,TRUE) -> FALSE
B6: 4 | C6: =IF(B6=Projections!$G$3,TRUE) -> FALSE
B7: 5 | C7: =IF(B7=Projections!$G$3,TRUE) -> FALSE
B8: 6 | C8: =IF(B8=Projections!$G$3,TRUE) -> TRUE
B9: 7 | C9: =IF(B9=Projections!$G$3,TRUE) -> FALSE
B10: 8 | C10: =IF(B10=Projections!$G$3,TRUE) -> FALSE
B11: 9 | C11: =IF(B11=Projections!$G$3,TRUE) -> FALSE
B12: 10 | C12: =IF(B12=Projections!$G$3,TRUE) -> FALSE
B13: 11 | C13: =IF(B13=Projections!$G$3,TRUE) -> FALSE
B14: 12 | C14: =IF(B14=Projections!$G$3,TRUE) -> FALSE
C16: Pick # | D16: =IF(C3=TRUE,"1",IF(C4=TRUE,"2", IF(C5=True, "3",IF(C6=True, "4",IF(C7=True, "5",IF(C8=True, "6",IF(C9=True, "7",IF(C10=True, "8",IF(C11=True, "9",IF(C12=True, "10",IF(C13=True, "11",IF(C14=True, "12"))))))))))))*1 -> 6 | E16: =IF(C3=TRUE,"24",IF(C4=TRUE,"23", IF(C5=True, "22",IF(C6=True, "21",IF(C7=True, "20",IF(C8=True, "19",IF(C9=True, "18",IF(C10=True, "17",IF(C11=True, "16",IF(C12=True, "15",IF(C13=True, "14",IF(C14=True, "13"))))))))))))*1 -> 19 | F16: =IF(C3=TRUE,"25",IF(C4=TRUE,"26", IF(C5=True, "27",IF(C6=True, "28",IF(C7=True, "29",IF(C8=True, "30",IF(C9=True, "31",IF(C10=True, "32",IF(C11=True, "33",IF(C12=True, "34",IF(C13=True, "35",IF(C14=True, "36"))))))))))))*1 -> 30 | G16: =IF(C3=TRUE,"48",IF(C4=TRUE,"47", IF(C5=True, "46",IF(C6=True, "45",IF(C7=True, "44",IF(C8=True, "43",IF(C9=True, "42",IF(C10=True, "41",IF(C11=True, "40",IF(C12=True, "39",IF(C13=True, "38",IF(C14=True, "37"))))))))))))*1 -> 43 | H16: =IF(C3=TRUE,"49",IF(C4=TRUE,"50", IF(C5=True, "51",IF(C6=True, "52",IF(C7=True, "53",IF(C8=True, "54",IF(C9=True, "55",IF(C10=True, "56",IF(C11=True, "57",IF(C12=True, "58",IF(C13=True, "59",IF(C14=True, "60"))))))))))))*1 -> 54 | I16: =IF(C3=TRUE,"72",IF(C4=TRUE,"71", IF(C5=True, "70",IF(C6=True, "69",IF(C7=True, "68",IF(C8=True, "67",IF(C9=True, "66",IF(C10=True, "65",IF(C11=True, "64",IF(C12=True, "63",IF(C13=True, "62",IF(C14=True, "61"))))))))))))*1 -> 67 | J16: =IF(C3=TRUE,"73",IF(C4=TRUE,"74", IF(C5=True, "75",IF(C6=True, "76",IF(C7=True, "77",IF(C8=True, "78",IF(C9=True, "79",IF(C10=True, "80",IF(C11=True, "81",IF(C12=True, "82",IF(C13=True, "83",IF(C14=True, "84"))))))))))))*1 -> 78 | K16: =IF(C3=TRUE,"96",IF(C4=TRUE,"95", IF(C5=True, "94",IF(C6=True, "93",IF(C7=True, "92",IF(C8=True, "91",IF(C9=True, "90",IF(C10=True, "89",IF(C11=True, "88",IF(C12=True, "87",IF(C13=True, "86",IF(C14=True, "85"))))))))))))*1 -> 91 | L16: =IF(C3=TRUE,"97",IF(C4=TRUE,"98", IF(C5=True, "99",IF(C6=True, "100",IF(C7=True, "101",IF(C8=True, "102",IF(C9=True, "103",IF(C10=True, "104",IF(C11=True, "105",IF(C12=True, "106",IF(C13=True, "107",IF(C14=True, "108"))))))))))))*1 -> 102 | M16: =IF(C3=TRUE,"120",IF(C4=TRUE,"119", IF(C5=True, "118",IF(C6=True, "117",IF(C7=True, "116",IF(C8=True, "115",IF(C9=True, "114",IF(C10=True, "113",IF(C11=True, "112",IF(C12=True, "111",IF(C13=True, "110",IF(C14=True, "109"))))))))))))*1 -> 115 | N16: =IF(C3=TRUE,"121",IF(C4=TRUE,"122", IF(C5=True, "123",IF(C6=True, "124",IF(C7=True, "125",IF(C8=True, "126",IF(C9=True, "127",IF(C10=True, "128",IF(C11=True, "129",IF(C12=True, "130",IF(C13=True, "131",IF(C14=True, "132"))))))))))))*1 -> 126 | O16: =IF(C3=TRUE,"144",IF(C4=TRUE,"143", IF(C5=True, "142",IF(C6=True, "141",IF(C7=True, "140",IF(C8=True, "139",IF(C9=True, "138",IF(C10=True, "137",IF(C11=True, "136",IF(C12=True, "135",IF(C13=True, "134",IF(C14=True, "133"))))))))))))*1 -> 139 | P16: =IF(C3=TRUE,"145",IF(C4=TRUE,"146", IF(C5=True, "147",IF(C6=True, "148",IF(C7=True, "149",IF(C8=True, "150",IF(C9=True, "151",IF(C10=True, "152",IF(C11=True, "153",IF(C12=True, "154",IF(C13=True, "155",IF(C14=True, "156")))))))))))) -> 150 | Q16: =IF(C3=TRUE,"168",IF(C4=TRUE,"167", IF(C5=True, "166",IF(C6=True, "165",IF(C7=True, "164",IF(C8=True, "163",IF(C9=True, "162",IF(C10=True, "161",IF(C11=True, "160",IF(C12=True, "159",IF(C13=True, "158",IF(C14=True, "157")))))))))))) -> 163
C17: 3RR | D17: =D16 -> 6 | E17: =E16 -> 19 | F17: =F16+IF($C$3,11, IF($C$4,9,IF($C$5,7,IF($C$6,5,IF($C$7,3,IF($C$8,1,IF($C$9,-1,IF($C$10,-3,IF($C$11,-5,IF($C$12,-7, IF($C$13,-9, IF($C$14,-11))))))))))))*1 -> 31 | G17: =G16-IF($C$3,11, IF($C$4,9,IF($C$5,7,IF($C$6,5,IF($C$7,3,IF($C$8,1,IF($C$9,-1,IF($C$10,-3,IF($C$11,-5,IF($C$12,-7, IF($C$13,-9, IF($C$14,-11))))))))))))*1 -> 42 | H17: =H16+IF($C$3,11, IF($C$4,9,IF($C$5,7,IF($C$6,5,IF($C$7,3,IF($C$8,1,IF($C$9,-1,IF($C$10,-3,IF($C$11,-5,IF($C$12,-7, IF($C$13,-9, IF($C$14,-11))))))))))))*1 -> 55 | I17: =I16-IF($C$3,11, IF($C$4,9,IF($C$5,7,IF($C$6,5,IF($C$7,3,IF($C$8,1,IF($C$9,-1,IF($C$10,-3,IF($C$11,-5,IF($C$12,-7, IF($C$13,-9, IF($C$14,-11))))))))))))*1 -> 66 | J17: =J16+IF($C$3,11, IF($C$4,9,IF($C$5,7,IF($C$6,5,IF($C$7,3,IF($C$8,1,IF($C$9,-1,IF($C$10,-3,IF($C$11,-5,IF($C$12,-7, IF($C$13,-9, IF($C$14,-11))))))))))))*1 -> 79 | K17: =K16-IF($C$3,11, IF($C$4,9,IF($C$5,7,IF($C$6,5,IF($C$7,3,IF($C$8,1,IF($C$9,-1,IF($C$10,-3,IF($C$11,-5,IF($C$12,-7, IF($C$13,-9, IF($C$14,-11))))))))))))*1 -> 90 | L17: =L16+IF($C$3,11, IF($C$4,9,IF($C$5,7,IF($C$6,5,IF($C$7,3,IF($C$8,1,IF($C$9,-1,IF($C$10,-3,IF($C$11,-5,IF($C$12,-7, IF($C$13,-9, IF($C$14,-11))))))))))))*1 -> 103 | M17: =M16-IF($C$3,11, IF($C$4,9,IF($C$5,7,IF($C$6,5,IF($C$7,3,IF($C$8,1,IF($C$9,-1,IF($C$10,-3,IF($C$11,-5,IF($C$12,-7, IF($C$13,-9, IF($C$14,-11))))))))))))*1 -> 114 | N17: =N16+IF($C$3,11, IF($C$4,9,IF($C$5,7,IF($C$6,5,IF($C$7,3,IF($C$8,1,IF($C$9,-1,IF($C$10,-3,IF($C$11,-5,IF($C$12,-7, IF($C$13,-9, IF($C$14,-11))))))))))))*1 -> 127 | O17: =O16-IF($C$3,11, IF($C$4,9,IF($C$5,7,IF($C$6,5,IF($C$7,3,IF($C$8,1,IF($C$9,-1,IF($C$10,-3,IF($C$11,-5,IF($C$12,-7, IF($C$13,-9, IF($C$14,-11))))))))))))*1 -> 138 | P17: =P16+IF($B$3,11, IF($B$4,9,IF($B$5,7,IF($B$6,5,IF($B$7,3,IF($B$8,1,IF($B$9,-1,IF($B$10,-3,IF($B$11,-5,IF($B$12,-7, IF($B$13,-9, IF($B$14,-11)))))))))))) -> 161 | Q17: =Q16-IF($B$3,11, IF($B$4,9,IF($B$5,7,IF($B$6,5,IF($B$7,3,IF($B$8,1,IF($B$9,-1,IF($B$10,-3,IF($B$11,-5,IF($B$12,-7, IF($B$13,-9, IF($B$14,-11)))))))))))) -> 152
D19: MAKE A COPY
D20: File -> Make a copy

Sheet Projections
I2: Pick # | J2: Team | K2: PTS | L2: 3P | M2: REB | N2: AST | O2: STL | P2: BLK | Q2: FG% | R2: FT% | S2: TO | T2: Cats Won | U2: Winrate | V2: Punt Sum | W2: ="Round "&Column(A1) -> Round 1 | Y2: ="Round "&Column(B1) -> Round 2 | AA2: ="Round "&Column(C1) -> Round 3 | AC2: ="Round "&Column(D1) -> Round 4 | AE2: ="Round "&Column(F1) -> Round 6 | AG2: ="Round "&Column(G1) -> Round 7 | AI2: ="Round "&Column(H1) -> Round 8 | AK2: ="Round "&Column(P1) -> Round 16 | AM2: ="Round "&Column(R1) -> Round 18 | AO2: ="Round "&Column(T1) -> Round 20 | AQ2: ="Round "&Column(V1) -> Round 22 | AS2: ="Round "&Column(X1) -> Round 24 | AU2: ="Round "&Column(Z1) -> Round 26 | AW2: ="Round "&Column(I1) -> Round 9 | AX2: ="Round "&Column(J1) -> Round 10 | AY2: ="Round "&Column(K1) -> Round 11 | AZ2: ="Round "&Column(L1) -> Round 12 | BA2: ="Round "&Column(M1) -> Round 13 | BB2: ="Round "&Column(N1) -> Round 14 | BC2: ="Round "&Column(O1) -> Round 15 | BD2: =Draft!AK3 | BE2: =Draft!AL3 | BF2: =Draft!AM3 | BG2: =Draft!AN3 | BH2: =Draft!AO3
F3: Your Pick # | G3: 6 | I3: =Draft!C3 -> FALSE | J3: 1 | K3: ='All Teams'!E18 -> 1.3900854 | L3: ='All Teams'!F18 -> 0.55639491 | M3: ='All Teams'!G18 -> 2.446126 | N3: ='All Teams'!H18 -> 0.5619911 | O3: ='All Teams'!I18 -> 0.9889591 | P3: ='All Teams'!J18 -> 6.0230448 | Q3: ='All Teams'!K18 -> -0.52457188 | R3: ='All Teams'!L18 -> 0.13810553 | S3: ='All Teams'!M18 -> -1.9190058 | T3: {=if(Team!D$1=$J3,"-", countif(indirect(address(row($J$2)+ VLOOKUP(Team!D$1,$J$3:$J$14,1),COLUMN($K$2))):indirect(address(row($J$2)+ VLOOKUP(Team!D$1,$J$3:$J$14,1),COLUMN($S$2)))>indirect(address(row($J3),COLUMN($K$2))):indirect(address(row($J3),COLUMN($S$2))),TRUE()))} -> 2 | U3: =SUM(AK$22:AK$33)/99 -> 0.77777778 | V3: =IF(I3, SUMIF(K3:R3,">-1.5"),) | W3: =Draft!D3 -> Victor Wembanyama | Y3: =Draft!E3 | AA3: =Draft!F3 | AC3: =Draft!G3 | AE3: =Draft!H3 | AG3: =Draft!I3 | AI3: =Draft!J3 | AK3: =Draft!R4 | AL3: =Draft!S4 | AM3: =Draft!T4 | AN3: =Draft!U4 | AO3: =Draft!V4 | AP3: =Draft!W4 | AQ3: =Draft!X4 | AR3: =Draft!Y4 | ... AV3: =Draft!AC4 | AW3: =Draft!K3 | AX3: =Draft!L3 | AY3: =Draft!M3 | AZ3: =Draft!N3 | BA3: =Draft!O3 | BB3: =Draft!P3 | BC3: =Draft!AJ4 | BD3: =Draft!AK4 | BE3: =Draft!AL4 | BF3: =Draft!AM4 | BG3: =Draft!AN4 | BH3: =Draft!AO4
I4: =Draft!C4 -> FALSE | J4: 2 | K4: ='All Teams'!E35 | L4: ='All Teams'!F35 | M4: ='All Teams'!G35 | N4: ='All Teams'!H35 | O4: ='All Teams'!I35 | P4: ='All Teams'!J35 | Q4: ='All Teams'!K35 -> 0 | R4: ='All Teams'!L35 -> 0 | S4: ='All Teams'!M35 | T4: {=if(Team!D$1=$J4,"-", countif(indirect(address(row($J$2)+ VLOOKUP(Team!D$1,$J$3:$J$14,1),COLUMN($K$2))):indirect(address(row($J$2)+ VLOOKUP(Team!D$1,$J$3:$J$14,1),COLUMN($S$2)))>indirect(address(row($J4),COLUMN($K$2))):indirect(address(row($J4),COLUMN($S$2))),TRUE()))} -> 0 | U4: =SUM(AL$22:AL$33)/99 -> 0.02020202 | V4: =IF(I4, SUMIF(K4:R4,">-1.5"),) | W4: =Draft!D4 | Y4: =Draft!E4 | AA4: =Draft!F4 | AC4: =Draft!G4 | AE4: =Draft!H4 | AG4: =Draft!I4 | AI4: =Draft!J4 | AK4: =Draft!R5 | AL4: =Draft!S5 | AM4: =Draft!T5 | AN4: =Draft!U5 | AO4: =Draft!V5 | AP4: =Draft!W5 | AQ4: =Draft!X5 | AR4: =Draft!Y5 | ... AT4: =Draft!AA5 | AV4: =Draft!AC5 | AW4: =Draft!K4 | AX4: =Draft!L4 | AY4: =Draft!M4 | AZ4: =Draft!N4 | BA4: =Draft!O4 | BB4: =Draft!P4 | BC4: =Draft!AJ5 | BD4: =Draft!AK5 | BE4: =Draft!AL5 | BF4: =Draft!AM5 | BG4: =Draft!AN5 | BH4: =Draft!AO5
F5: Next Pick Simulation | I5: =Draft!C5 -> FALSE | J5: 3 | K5: ='All Teams'!E52 | L5: ='All Teams'!F52 | M5: ='All Teams'!G52 | N5: ='All Teams'!H52 | O5: ='All Teams'!I52 | P5: ='All Teams'!J52 | Q5: ='All Teams'!K52 -> 0 | R5: ='All Teams'!L52 -> 0 | S5: ='All Teams'!M52 | T5: {=if(Team!D$1=$J5,"-", countif(indirect(address(row($J$2)+ VLOOKUP(Team!D$1,$J$3:$J$14,1),COLUMN($K$2))):indirect(address(row($J$2)+ VLOOKUP(Team!D$1,$J$3:$J$14,1),COLUMN($S$2)))>indirect(address(row($J5),COLUMN($K$2))):indirect(address(row($J5),COLUMN($S$2))),TRUE()))} -> 0 | U5: =SUM(AM$22:AM$33)/99 -> 0.02020202 | V5: =IF(I5, SUMIF(K5:R5,">-1.5"),) | W5: =Draft!D5 | Y5: =Draft!E5 | AA5: =Draft!F5 | AC5: =Draft!G5 | AE5: =Draft!H5 | AG5: =Draft!I5 | AI5: =Draft!J5 | AK5: =Draft!R6 | AL5: =Draft!S6 | AM5: =Draft!T6 | AN5: =Draft!U6 | AO5: =Draft!V6 | AP5: =Draft!W6 | AQ5: =Draft!X6 | AR5: =Draft!Y6 | ... AV5: =Draft!AC6 | AW5: =Draft!K5 | AX5: =Draft!L5 | AY5: =Draft!M5 | AZ5: =Draft!N5 | BA5: =Draft!O5 | BB5: =Draft!P5 | BC5: =Draft!AJ6 | BD5: =Draft!AK6 | BE5: =Draft!AL6 | BF5: =Draft!AM6 | BG5: =Draft!AN6 | BH5: =Draft!AO6
F6: Round # | G6: 1 | I6: =Draft!C6 -> FALSE | J6: 4 | K6: ='All Teams'!E69 | L6: ='All Teams'!F69 | M6: ='All Teams'!G69 | N6: ='All Teams'!H69 | O6: ='All Teams'!I69 | P6: ='All Teams'!J69 | Q6: ='All Teams'!K69 -> 0 | R6: ='All Teams'!L69 -> 0 | S6: ='All Teams'!M69 | T6: {=if(Team!D$1=$J6,"-", countif(indirect(address(row($J$2)+ VLOOKUP(Team!D$1,$J$3:$J$14,1),COLUMN($K$2))):indirect(address(row($J$2)+ VLOOKUP(Team!D$1,$J$3:$J$14,1),COLUMN($S$2)))>indirect(address(row($J6),COLUMN($K$2))):indirect(address(row($J6),COLUMN($S$2))),TRUE()))} -> 0 | U6: =SUM(AN$22:AN$33)/99 -> 0.02020202 | V6: =IF(I6, SUMIF(K6:R6,">-1.5"),) | W6: =Draft!D6 | Y6: =Draft!E6 | AA6: =Draft!F6 | AC6: =Draft!G6 | AE6: =Draft!H6 | AG6: =Draft!I6 | AI6: =Draft!J6 | AK6: =Draft!R7 | AL6: =Draft!S7 | AM6: =Draft!T7 | AN6: =Draft!U7 | AO6: =Draft!V7 | AP6: =Draft!W7 | AQ6: =Draft!X7 | AR6: =Draft!Y7 | ... AV6: =Draft!AC7 | AW6: =Draft!K6 | AX6: =Draft!L6 | AY6: =Draft!M6 | AZ6: =Draft!N6 | BA6: =Draft!O6 | BB6: =Draft!P6 | BC6: =Draft!AJ7 | BD6: =Draft!AK7 | BE6: =Draft!AL7 | BF6: =Draft!AM7 | BG6: =Draft!AN7 | BH6: =Draft!AO7
F7: Victor Wembanyama | I7: =Draft!C7 -> FALSE | J7: 5 | K7: ='All Teams'!E86 | L7: ='All Teams'!F86 | M7: ='All Teams'!G86 | N7: ='All Teams'!H86 | O7: ='All Teams'!I86 | P7: ='All Teams'!J86 | Q7: ='All Teams'!K86 -> 0 | R7: ='All Teams'!L86 -> 0 | S7: ='All Teams'!M86 | T7: {=if(Team!D$1=$J7,"-", countif(indirect(address(row($J$2)+ VLOOKUP(Team!D$1,$J$3:$J$14,1),COLUMN($K$2))):indirect(address(row($J$2)+ VLOOKUP(Team!D$1,$J$3:$J$14,1),COLUMN($S$2)))>indirect(address(row($J7),COLUMN($K$2))):indirect(address(row($J7),COLUMN($S$2))),TRUE()))} -> 0 | U7: =SUM(AO$22:AO$33)/99 -> 0.02020202 | V7: =IF(I7, SUMIF(K7:R7,">-1.5"),) | W7: =Draft!D7 | Y7: =Draft!E7 | AA7: =Draft!F7 | AC7: =Draft!G7 | AE7: =Draft!H7 | AG7: =Draft!I7 | AI7: =Draft!J7 | AK7: =Draft!R8 | AL7: =Draft!S8 | AM7: =Draft!T8 | AN7: =Draft!U8 | AO7: =Draft!V8 | AP7: =Draft!W8 | AQ7: =Draft!X8 | AR7: =Draft!Y8 | ... AV7: =Draft!AC8 | AW7: =Draft!K7 | AX7: =Draft!L7 | AY7: =Draft!M7 | AZ7: =Draft!N7 | BA7: =Draft!O7 | BB7: =Draft!P7 | BC7: =Draft!AJ8 | BD7: =Draft!AK8 | BE7: =Draft!AL8 | BF7: =Draft!AM8 | BG7: =Draft!AN8 | BH7: =Draft!AO8
I8: =Draft!C8 -> TRUE | J8: 6 | K8: ='All Teams'!E103 | L8: ='All Teams'!F103 | M8: ='All Teams'!G103 | N8: ='All Teams'!H103 | O8: ='All Teams'!I103 | P8: ='All Teams'!J103 | Q8: ='All Teams'!K103 -> 0 | R8: ='All Teams'!L103 -> 0 | S8: ='All Teams'!M103 | T8: {=if(Team!D$1=$J8,"-", countif(indirect(address(row($J$2)+ VLOOKUP(Team!D$1,$J$3:$J$14,1),COLUMN($K$2))):indirect(address(row($J$2)+ VLOOKUP(Team!D$1,$J$3:$J$14,1),COLUMN($S$2)))>indirect(address(row($J8),COLUMN($K$2))):indirect(address(row($J8),COLUMN($S$2))),TRUE()))} -> - | U8: =SUM(AP$22:AP$33)/99 -> 0.02020202 | V8: =IF(I8, SUMIF(K8:R8,">-2.5"),) -> 0 | W8: =Draft!D8 | Y8: =Draft!E8 | AA8: =Draft!F8 | AC8: =Draft!G8 | AE8: =Draft!H8 | AG8: =Draft!I8 | AI8: =Draft!J8 | AK8: =Draft!R9 | AL8: =Draft!S9 | AM8: =Draft!T9 | AN8: =Draft!U9 | AO8: =Draft!V9 | AP8: =Draft!W9 | AQ8: =Draft!X9 | AR8: =Draft!Y9 | ... AV8: =Draft!AC9 | AW8: =Draft!K8 | AX8: =Draft!L8 | AY8: =Draft!M8 | AZ8: =Draft!N8 | BA8: =Draft!O8 | BB8: =Draft!P8 | BC8: =Draft!AJ9 | BD8: =Draft!AK9 | BE8: =Draft!AL9 | BF8: =Draft!AM9 | BG8: =Draft!AN9 | BH8: =Draft!AO9
I9: =Draft!C9 -> FALSE | J9: 7 | K9: ='All Teams'!E120 | L9: ='All Teams'!F120 | M9: ='All Teams'!G120 | N9: ='All Teams'!H120 | O9: ='All Teams'!I120 | P9: ='All Teams'!J120 | Q9: ='All Teams'!K120 -> 0 | R9: ='All Teams'!L120 -> 0 | S9: ='All Teams'!M120 | T9: {=if(Team!D$1=$J9,"-", countif(indirect(address(row($J$2)+ VLOOKUP(Team!D$1,$J$3:$J$14,1),COLUMN($K$2))):indirect(address(row($J$2)+ VLOOKUP(Team!D$1,$J$3:$J$14,1),COLUMN($S$2)))>indirect(address(row($J9),COLUMN($K$2))):indirect(address(row($J9),COLUMN($S$2))),TRUE()))} -> 0 | U9: =SUM(AQ$22:AQ$33)/99 -> 0.02020202 | V9: =IF(I9, SUMIF(K9:R9,">-1.5"),) | W9: =Draft!D9 | Y9: =Draft!E9 | AA9: =Draft!F9 | AC9: =Draft!G9 | AE9: =Draft!H9 | AG9: =Draft!I9 | AI9: =Draft!J9 | AK9: =Draft!R10 | AL9: =Draft!S10 | AM9: =Draft!T10 | AN9: =Draft!U10 | AO9: =Draft!V10 | AP9: =Draft!W10 | AQ9: =Draft!X10 | AR9: =Draft!Y10 | ... AV9: =Draft!AC10 | AW9: =Draft!K9 | AX9: =Draft!L9 | AY9: =Draft!M9 | AZ9: =Draft!N9 | BA9: =Draft!O9 | BB9: =Draft!P9 | BC9: =Draft!AJ10 | BD9: =Draft!AK10 | BE9: =Draft!AL10 | BF9: =Draft!AM10 | BG9: =Draft!AN10 | BH9: =Draft!AO10
I10: =Draft!C10 -> FALSE | J10: 8 | K10: ='All Teams'!E137 | L10: ='All Teams'!F137 | M10: ='All Teams'!G137 | N10: ='All Teams'!H137 | O10: ='All Teams'!I137 | P10: ='All Teams'!J137 | Q10: ='All Teams'!K137 -> 0 | R10: ='All Teams'!L137 -> 0 | S10: ='All Teams'!M137 | T10: {=if(Team!D$1=$J10,"-", countif(indirect(address(row($J$2)+ VLOOKUP(Team!D$1,$J$3:$J$14,1),COLUMN($K$2))):indirect(address(row($J$2)+ VLOOKUP(Team!D$1,$J$3:$J$14,1),COLUMN($S$2)))>indirect(address(row($J10),COLUMN($K$2))):indirect(address(row($J10),COLUMN($S$2))),TRUE()))} -> 0 | U10: =SUM(AR$22:AR$33)/99 -> 0.02020202 | V10: =IF(I10, SUMIF(K10:R10,">-1.5"),) | W10: =Draft!D10 | Y10: =Draft!E10 | AA10: =Draft!F10 | AC10: =Draft!G10 | AE10: =Draft!H10 | AG10: =Draft!I10 | AI10: =Draft!J10 | AK10: =Draft!R11 | AL10: =Draft!S11 | AM10: =Draft!T11 | AN10: =Draft!U11 | AO10: =Draft!V11 | AP10: =Draft!W11 | AQ10: =Draft!X11 | AR10: =Draft!Y11 | ... AV10: =Draft!AC11 | AW10: =Draft!K10 | AX10: =Draft!L10 | AY10: =Draft!M10 | AZ10: =Draft!N10 | BA10: =Draft!O10 | BB10: =Draft!P10 | BC10: =Draft!AJ11 | BD10: =Draft!AK11 | BE10: =Draft!AL11 | BF10: =Draft!AM11 | BG10: =Draft!AN11 | BH10: =Draft!AO11
F11: Input Draft Picks | I11: =Draft!C11 -> FALSE | J11: 9 | K11: ='All Teams'!E154 | L11: ='All Teams'!F154 | M11: ='All Teams'!G154 | N11: ='All Teams'!H154 | O11: ='All Teams'!I154 | P11: ='All Teams'!J154 | Q11: ='All Teams'!K154 -> 0 | R11: ='All Teams'!L154 -> 0 | S11: ='All Teams'!M154 | T11: {=if(Team!D$1=$J11,"-", countif(indirect(address(row($J$2)+ VLOOKUP(Team!D$1,$J$3:$J$14,1),COLUMN($K$2))):indirect(address(row($J$2)+ VLOOKUP(Team!D$1,$J$3:$J$14,1),COLUMN($S$2)))>indirect(address(row($J11),COLUMN($K$2))):indirect(address(row($J11),COLUMN($S$2))),TRUE()))} -> 0 | U11: =SUM(AS$22:AS$33)/99 -> 0.02020202 | V11: =IF(I11, SUMIF(K11:R11,">-1.5"),) | W11: =Draft!D11 | Y11: =Draft!E11 | AA11: =Draft!F11 | AC11: =Draft!G11 | AE11: =Draft!H11 | AG11: =Draft!I11 | AI11: =Draft!J11 | AK11: =Draft!R12 | AL11: =Draft!S12 | AM11: =Draft!T12 | AN11: =Draft!U12 | AO11: =Draft!V12 | AP11: =Draft!W12 | AQ11: =Draft!X12 | AR11: =Draft!Y12 | ... AV11: =Draft!AC12 | AW11: =Draft!K11 | AX11: =Draft!L11 | AY11: =Draft!M11 | AZ11: =Draft!N11 | BA11: =Draft!O11 | BB11: =Draft!P11 | BC11: =Draft!AJ12 | BD11: =Draft!AK12 | BE11: =Draft!AL12 | BF11: =Draft!AM12 | BG11: =Draft!AN12 | BH11: =Draft!AO12
F12: 3RR | G12: TRUE | I12: =Draft!C12 -> FALSE | J12: 10 | K12: ='All Teams'!E171 | L12: ='All Teams'!F171 | M12: ='All Teams'!G171 | N12: ='All Teams'!H171 | O12: ='All Teams'!I171 | P12: ='All Teams'!J171 | Q12: ='All Teams'!K171 -> 0 | R12: ='All Teams'!L171 -> 0 | S12: ='All Teams'!M171 | T12: {=if(Team!D$1=$J12,"-", countif(indirect(address(row($J$2)+ VLOOKUP(Team!D$1,$J$3:$J$14,1),COLUMN($K$2))):indirect(address(row($J$2)+ VLOOKUP(Team!D$1,$J$3:$J$14,1),COLUMN($S$2)))>indirect(address(row($J12),COLUMN($K$2))):indirect(address(row($J12),COLUMN($S$2))),TRUE()))} -> 0 | U12: =SUM(AT$22:AT$33)/99 -> 0.02020202 | V12: =IF(I12, SUMIF(K12:R12,">-1.5"),) | W12: =Draft!D12 | Y12: =Draft!E12 | AA12: =Draft!F12 | AC12: =Draft!G12 | AE12: =Draft!H12 | AG12: =Draft!I12 | AI12: =Draft!J12 | AK12: =Draft!R13 | AL12: =Draft!S13 | AM12: =Draft!T13 | AN12: =Draft!U13 | AO12: =Draft!V13 | AP12: =Draft!W13 | AQ12: =Draft!X13 | AR12: =Draft!Y13 | ... AV12: =Draft!AC13 | AW12: =Draft!K12 | AX12: =Draft!L12 | AY12: =Draft!M12 | AZ12: =Draft!N12 | BA12: =Draft!O12 | BB12: =Draft!P12 | BC12: =Draft!AJ13 | BD12: =Draft!AK13 | BE12: =Draft!AL13 | BF12: =Draft!AM13 | BG12: =Draft!AN13 | BH12: =Draft!AO13
F13: Current Pick #1 | G13: 2 | I13: =Draft!C13 -> FALSE | J13: 11 | K13: ='All Teams'!E188 | L13: ='All Teams'!F188 | M13: ='All Teams'!G188 | N13: ='All Teams'!H188 | O13: ='All Teams'!I188 | P13: ='All Teams'!J188 | Q13: ='All Teams'!K188 -> 0 | R13: ='All Teams'!L188 -> 0 | S13: ='All Teams'!M188 | T13: {=if(Team!D$1=$J13,"-", countif(indirect(address(row($J$2)+ VLOOKUP(Team!D$1,$J$3:$J$14,1),COLUMN($K$2))):indirect(address(row($J$2)+ VLOOKUP(Team!D$1,$J$3:$J$14,1),COLUMN($S$2)))>indirect(address(row($J13),COLUMN($K$2))):indirect(address(row($J13),COLUMN($S$2))),TRUE()))} -> 0 | U13: =SUM(AU$22:AU$33)/99 -> 0.02020202 | V13: =IF(I13, SUMIF(K13:R13,">-1.5"),) | W13: =Draft!D13 | Y13: =Draft!E13 | AA13: =Draft!F13 | AC13: =Draft!G13 | AE13: =Draft!H13 | AG13: =Draft!I13 | AI13: =Draft!J13 | AK13: =Draft!R14 | AL13: =Draft!S14 | AM13: =Draft!T14 | AN13: =Draft!U14 | AO13: =Draft!V14 | AP13: =Draft!W14 | AQ13: =Draft!X14 | AR13: =Draft!Y14 | ... AV13: =Draft!AC14 | AW13: =Draft!K13 | AX13: =Draft!L13 | AY13: =Draft!M13 | AZ13: =Draft!N13 | BA13: =Draft!O13 | BB13: =Draft!P13 | BC13: =Draft!AJ14 | BD13: =Draft!AK14 | BE13: =Draft!AL14 | BF13: =Draft!AM14 | BG13: =Draft!AN14 | BH13: =Draft!AO14
F14: Your Next Pick # | G14: =IFERROR(__xludf.DUMMYFUNCTION("MIN(FILTER(IF(G12,Draft!D17:O17,Draft!D16:O16),IF(G12,Draft!D17:O17,Draft!D16:O16)>G13))"),6.0) -> 6 | I14: =Draft!C14 -> FALSE | J14: 12 | K14: ='All Teams'!E205 | L14: ='All Teams'!F205 | M14: ='All Teams'!G205 | N14: ='All Teams'!H205 | O14: ='All Teams'!I205 | P14: ='All Teams'!J205 | Q14: ='All Teams'!K205 -> 0 | R14: ='All Teams'!L205 -> 0 | S14: ='All Teams'!M205 | T14: {=if(Team!D$1=$J14,"-", countif(indirect(address(row($J$2)+ VLOOKUP(Team!D$1,$J$3:$J$14,1),COLUMN($K$2))):indirect(address(row($J$2)+ VLOOKUP(Team!D$1,$J$3:$J$14,1),COLUMN($S$2)))>indirect(address(row($J14),COLUMN($K$2))):indirect(address(row($J14),COLUMN($S$2))),TRUE()))} -> 0 | U14: =SUM(AV$22:AV$33)/99 -> 0.02020202 | V14: =IF(I14, SUMIF(K14:R14,">-1.5"),) | W14: =Draft!D14 | Y14: =Draft!E14 | AA14: =Draft!F14 | AC14: =Draft!G14 | AE14: =Draft!H14 | AG14: =Draft!I14 | AI14: =Draft!J14 | AK14: =Draft!R15 | AL14: =Draft!S15 | AM14: =Draft!T15 | AN14: =Draft!U15 | AO14: =Draft!V15 | AP14: =Draft!W15 | AQ14: =Draft!X15 | AR14: =Draft!Y15 | ... AV14: =Draft!AC15 | AW14: =Draft!K14 | AX14: =Draft!L14 | AY14: =Draft!M14 | AZ14: =Draft!N14 | BA14: =Draft!O14 | BB14: =Draft!P14 | BC14: =Draft!AJ15 | BD14: =Draft!AK15 | BE14: =Draft!AL15 | BF14: =Draft!AM15 | BG14: =Draft!AN15 | BH14: =Draft!AO15
F15: Player Name | G15: Victor Wembanyama | W15: =IF($G$12,Draft!D17,Draft!D16) -> 6 | Y15: =IF($G$12,Draft!E17,Draft!E16) -> 19 | AA15: =IF($G$12,Draft!F17,Draft!F16) -> 31 | AC15: =IF($G$12,Draft!G17,Draft!G16) -> 42 | AE15: =IF($G$12,Draft!H17,Draft!H16) -> 55 | AG15: =IF($G$12,Draft!I17,Draft!I16) -> 66 | AI15: =IF($G$12,Draft!J17,Draft!J16) -> 79 | AK15: =IF($G$12,Draft!R16,Draft!R16) | AM15: =IF($G$12,Draft!T16,Draft!T16) | AO15: =IF($G$12,Draft!V16,Draft!V16) | AQ15: =IF($G$12,Draft!X16,Draft!X16) | AS15: =IF($G$12,Draft!Z16,Draft!Z16) | AU15: =IF($G$12,Draft!AB16,Draft!AB16) | AW15: =IF($G$12,Draft!K17,Draft!K16) -> 90 | AX15: =IF($G$12,Draft!L17,Draft!L16) -> 103 | AY15: =IF($G$12,Draft!M17,Draft!M16) -> 114 | AZ15: =IF($G$12,Draft!N17,Draft!N16) -> 127 | BA15: =IF($G$12,Draft!O17,Draft!O16) -> 138 | BB15: =IF($G$12,Draft!P17,Draft!P16) -> 161 | BC15: =IF($G$12,Draft!Q17,Draft!Q16) -> 152
I16: -1 Cat | J16: -2 Cat | K16: PTS | L16: 3P | M16: REB | N16: AST | O16: STL | P16: BLK | Q16: FG% | R16: FT% | S16: TO | T16: PG | U16: SG | V16: SF | W16: PF | X16: C | Z16: Sort by | AB16: Remove Drafted | AE16: Top | AG16: Projections
I17: FALSE | J17: FALSE | K17: 1 | L17: 1 | M17: 1 | N17: 1 | O17: 1 | P17: 1 | Q17: 1 | R17: 1 | S17: 0 | T17: PG | U17: SG | V17: SF | W17: PF | X17: C | Z17: PuntV | AB17: TRUE | AE17: 200 | AG17: BBM
A19: W18 | B19: W19 | C19: W20 | D19: Total | F19: Team | G19: PuntRank | H19: LgRank | I19: ADP | J19: Player | K19: GP | L19: Pos | M19: LeagV | N19: PuntV | O19: Punt+ | P19: PTS | Q19: 3P | R19: REB | S19: AST | T19: STL | U19: BLK | V19: FG% | W19: FT% | X19: TO | Y19: z p/g | Z19: z 3/g | AA19: z r/g | AB19: z a/g | AC19: z s/g | AD19: z b/g | AE19: z fg% | AF19: z ft% | AG19: z to/g
A20: =VLOOKUP($F20,UpdateHashtag!$V$3:$Y$32,COLUMN(B$15),0) -> 4 | B20: =VLOOKUP($F20,UpdateHashtag!$V$3:$Y$32,COLUMN(C$13),0) -> 4 | C20: =VLOOKUP($F20,UpdateHashtag!$V$3:$Y$32,COLUMN(D$13),0) -> 4 | D20: =SUM(A20:C20) -> 12 | F20: =IF(VLOOKUP(J20,PasteHashtag!$C$2:$P1015,3,)="BRO","BKN",IF(VLOOKUP(J20,PasteHashtag!$C$2:$P1015,3,)="OKL","OKC",VLOOKUP(J20,PasteHashtag!$C$2:$P1015,3,))) -> PHI | G20: 1 | H20: =IFERROR(__xludf.DUMMYFUNCTION("Filter('NO USAR3'!B5:AA420,IF('NO USAR3'!AB5:AB420="""",FALSE,TRUE),NOT(COUNTIF('NO USAR3'!A5:A200,'NO USAR3'!D5:D420)),IF('NO USAR3'!B5:B420>AE17,FALSE,TRUE))"),2.0) -> 2 | I20: =IFERROR(__xludf.DUMMYFUNCTION("""COMPUTED_VALUE"""),9.6) -> 9.6 | J20: =IFERROR(__xludf.DUMMYFUNCTION("""COMPUTED_VALUE"""),"Joel Embiid") -> Joel Embiid | K20: =IFERROR(__xludf.DUMMYFUNCTION("""COMPUTED_VALUE"""),68.0) -> 68 | L20: =IFERROR(__xludf.DUMMYFUNCTION("""COMPUTED_VALUE"""),"C") -> C | M20: =IFERROR(__xludf.DUMMYFUNCTION("""COMPUTED_VALUE"""),8.957904690194928) -> 8.9579047 | N20: =IFERROR(__xludf.DUMMYFUNCTION("""COMPUTED_VALUE"""),9.410476436812917) -> 9.4104764 | O20: =IFERROR(__xludf.DUMMYFUNCTION("""COMPUTED_VALUE"""),0.4525717466179895) -> 0.45257175 | P20: =IFERROR(__xludf.DUMMYFUNCTION("""COMPUTED_VALUE"""),30.23877193) -> 30.238772 | Q20: =IFERROR(__xludf.DUMMYFUNCTION("""COMPUTED_VALUE"""),1.142982456) -> 1.1429825 | R20: =IFERROR(__xludf.DUMMYFUNCTION("""COMPUTED_VALUE"""),10.51052632) -> 10.510526 | S20: =IFERROR(__xludf.DUMMYFUNCTION("""COMPUTED_VALUE"""),5.037368421) -> 5.0373684 | T20: =IFERROR(__xludf.DUMMYFUNCTION("""COMPUTED_VALUE"""),1.143859649) -> 1.1438596 | U20: =IFERROR(__xludf.DUMMYFUNCTION("""COMPUTED_VALUE"""),1.551052632) -> 1.5510526 | V20: =IFERROR(__xludf.DUMMYFUNCTION("""COMPUTED_VALUE"""),0.5367911594) -> 0.53679116 | W20: =IFERROR(__xludf.DUMMYFUNCTION("""COMPUTED_VALUE"""),0.8699991153) -> 0.86999912 | X20: =IFERROR(__xludf.DUMMYFUNCTION("""COMPUTED_VALUE"""),3.573684211) -> 3.5736842 | Y20: =IFERROR(__xludf.DUMMYFUNCTION("""COMPUTED_VALUE"""),2.2982783682718377) -> 2.2982784 | Z20: =IFERROR(__xludf.DUMMYFUNCTION("""COMPUTED_VALUE"""),-0.6007954542058588) -> -0.60079545 | AA20: =IFERROR(__xludf.DUMMYFUNCTION("""COMPUTED_VALUE"""),1.7350479056104444) -> 1.7350479 | AB20: =IFERROR(__xludf.DUMMYFUNCTION("""COMPUTED_VALUE"""),0.5013847387233921) -> 0.50138474 | AC20: =IFERROR(__xludf.DUMMYFUNCTION("""COMPUTED_VALUE"""),0.5553323226280126) -> 0.55533232 | AD20: =IFERROR(__xludf.DUMMYFUNCTION("""COMPUTED_VALUE"""),1.4311739809683646) -> 1.431174 | AE20: =IFERROR(__xludf.DUMMYFUNCTION("""COMPUTED_VALUE"""),0.8770105201052155) -> 0.87701052 | AF20: =IFERROR(__xludf.DUMMYFUNCTION("""COMPUTED_VALUE"""),2.61304405471151) -> 2.6130441 | AG20: =IFERROR(__xludf.DUMMYFUNCTION("""COMPUTED_VALUE"""),0.0) -> 0 | AK20: 1 | AL20: 2 | AM20: 3 | AN20: 4 | AO20: 5 | AP20: 6 | AQ20: 7 | AR20: 8 | AS20: 9 | AT20: 10 | AU20: 11 | AV20: 12
A21: =VLOOKUP($F21,UpdateHashtag!$V$3:$Y$32,COLUMN(B$15),0) -> 3 | B21: =VLOOKUP($F21,UpdateHashtag!$V$3:$Y$32,COLUMN(C$13),0) -> 4 | C21: =VLOOKUP($F21,UpdateHashtag!$V$3:$Y$32,COLUMN(D$13),0) -> 4 | D21: =SUM(A21:C21) -> 11 | F21: =IF(VLOOKUP(J21,PasteHashtag!$C$2:$P1015,3,)="BRO","BKN",IF(VLOOKUP(J21,PasteHashtag!$C$2:$P1015,3,)="OKL","OKC",VLOOKUP(J21,PasteHashtag!$C$2:$P1015,3,))) -> DEN | G21: 2 | H21: =IFERROR(__xludf.DUMMYFUNCTION("""COMPUTED_VALUE"""),3.0) -> 3 | I21: =IFERROR(__xludf.DUMMYFUNCTION("""COMPUTED_VALUE"""),2.4) -> 2.4 | J21: =IFERROR(__xludf.DUMMYFUNCTION("""COMPUTED_VALUE"""),"Nikola Jokic") -> Nikola Jokic | K21: =IFERROR(__xludf.DUMMYFUNCTION("""COMPUTED_VALUE"""),67.0) -> 67 | L21: =IFERROR(__xludf.DUMMYFUNCTION("""COMPUTED_VALUE"""),"PF,C") -> PF,C | M21: =IFERROR(__xludf.DUMMYFUNCTION("""COMPUTED_VALUE"""),8.517820594732509) -> 8.5178206 | N21: =IFERROR(__xludf.DUMMYFUNCTION("""COMPUTED_VALUE"""),8.881589989729328) -> 8.88159 | O21: =IFERROR(__xludf.DUMMYFUNCTION("""COMPUTED_VALUE"""),0.3637693949968188) -> 0.36376939 | P21: =IFERROR(__xludf.DUMMYFUNCTION("""COMPUTED_VALUE"""),25.55948052) -> 25.559481 | Q21: =IFERROR(__xludf.DUMMYFUNCTION("""COMPUTED_VALUE"""),0.9916883117) -> 0.99168831 | R21: =IFERROR(__xludf.DUMMYFUNCTION("""COMPUTED_VALUE"""),11.79064935) -> 11.790649 | S21: =IFERROR(__xludf.DUMMYFUNCTION("""COMPUTED_VALUE"""),8.360649351) -> 8.3606494 | T21: =IFERROR(__xludf.DUMMYFUNCTION("""COMPUTED_VALUE"""),1.492597403) -> 1.4925974 | U21: =IFERROR(__xludf.DUMMYFUNCTION("""COMPUTED_VALUE"""),0.788961039) -> 0.78896104 | V21: =IFERROR(__xludf.DUMMYFUNCTION("""COMPUTED_VALUE"""),0.5897010341) -> 0.58970103 | W21: =IFERROR(__xludf.DUMMYFUNCTION("""COMPUTED_VALUE"""),0.8110073214) -> 0.81100732 | X21: =IFERROR(__xludf.DUMMYFUNCTION("""COMPUTED_VALUE"""),3.215584416) -> 3.2155844 | Y21: =IFERROR(__xludf.DUMMYFUNCTION("""COMPUTED_VALUE"""),1.4548097063016192) -> 1.4548097 | Z21: =IFERROR(__xludf.DUMMYFUNCTION("""COMPUTED_VALUE"""),-0.7508684337265839) -> -0.75086843 | AA21: =IFERROR(__xludf.DUMMYFUNCTION("""COMPUTED_VALUE"""),2.2367370772400488) -> 2.2367371 | AB21: =IFERROR(__xludf.DUMMYFUNCTION("""COMPUTED_VALUE"""),2.0106142545298287) -> 2.0106143 | AC21: =IFERROR(__xludf.DUMMYFUNCTION("""COMPUTED_VALUE"""),1.7090661000464076) -> 1.7090661 | AD21: =IFERROR(__xludf.DUMMYFUNCTION("""COMPUTED_VALUE"""),0.07187096952644342) -> 0.07187097 | AE21: =IFERROR(__xludf.DUMMYFUNCTION("""COMPUTED_VALUE"""),1.8597186873550178) -> 1.8597187 | AF21: =IFERROR(__xludf.DUMMYFUNCTION("""COMPUTED_VALUE"""),0.2896416284565464) -> 0.28964163 | AG21: =IFERROR(__xludf.DUMMYFUNCTION("""COMPUTED_VALUE"""),0.0) -> 0 | AJ21: % Games/Week | AK21: Categories won | AW21: Round | AX21: Player Name | AZ21: PTS | BA21: 3P | BB21: REB | BC21: AST | BD21: STL | BE21: BLK | BF21: FG% | BG21: FT% | BH21: TO | BI21: POS | BJ21: Count | BK21: POS
A22: =VLOOKUP($F22,UpdateHashtag!$V$3:$Y$32,COLUMN(B$15),0) -> 4 | B22: =VLOOKUP($F22,UpdateHashtag!$V$3:$Y$32,COLUMN(C$13),0) -> 4 | C22: =VLOOKUP($F22,UpdateHashtag!$V$3:$Y$32,COLUMN(D$13),0) -> 2 | D22: =SUM(A22:C22) -> 10 | F22: =IF(VLOOKUP(J22,PasteHashtag!$C$2:$P1015,3,)="BRO","BKN",IF(VLOOKUP(J22,PasteHashtag!$C$2:$P1015,3,)="OKL","OKC",VLOOKUP(J22,PasteHashtag!$C$2:$P1015,3,))) -> DAL | G22: 3 | H22: =IFERROR(__xludf.DUMMYFUNCTION("""COMPUTED_VALUE"""),4.0) -> 4 | I22: =IFERROR(__xludf.DUMMYFUNCTION("""COMPUTED_VALUE"""),3.8) -> 3.8 | J22: =IFERROR(__xludf.DUMMYFUNCTION("""COMPUTED_VALUE"""),"Luka Doncic") -> Luka Doncic | K22: =IFERROR(__xludf.DUMMYFUNCTION("""COMPUTED_VALUE"""),68.0) -> 68 | L22: =IFERROR(__xludf.DUMMYFUNCTION("""COMPUTED_VALUE"""),"PG,SG") -> PG,SG | M22: =IFERROR(__xludf.DUMMYFUNCTION("""COMPUTED_VALUE"""),8.299053452451961) -> 8.2990535 | N22: =IFERROR(__xludf.DUMMYFUNCTION("""COMPUTED_VALUE"""),8.833457384158983) -> 8.8334574 | O22: =IFERROR(__xludf.DUMMYFUNCTION("""COMPUTED_VALUE"""),0.5344039317070219) -> 0.53440393 | P22: =IFERROR(__xludf.DUMMYFUNCTION("""COMPUTED_VALUE"""),31.87132353) -> 31.871324 | Q22: =IFERROR(__xludf.DUMMYFUNCTION("""COMPUTED_VALUE"""),3.974117647) -> 3.9741176 | R22: =IFERROR(__xludf.DUMMYFUNCTION("""COMPUTED_VALUE"""),9.108970588) -> 9.1089706 | S22: =IFERROR(__xludf.DUMMYFUNCTION("""COMPUTED_VALUE"""),9.498235294) -> 9.4982353 | T22: =IFERROR(__xludf.DUMMYFUNCTION("""COMPUTED_VALUE"""),1.394852941) -> 1.3948529 | U22: =IFERROR(__xludf.DUMMYFUNCTION("""COMPUTED_VALUE"""),0.5467647059) -> 0.54676471 | V22: =IFERROR(__xludf.DUMMYFUNCTION("""COMPUTED_VALUE"""),0.4797165326) -> 0.47971653 | W22: =IFERROR(__xludf.DUMMYFUNCTION("""COMPUTED_VALUE"""),0.7859938088) -> 0.78599381 | X22: =IFERROR(__xludf.DUMMYFUNCTION("""COMPUTED_VALUE"""),3.903676471) -> 3.9036765 | Y22: =IFERROR(__xludf.DUMMYFUNCTION("""COMPUTED_VALUE"""),2.5925549997093618) -> 2.592555 | Z22: =IFERROR(__xludf.DUMMYFUNCTION("""COMPUTED_VALUE"""),2.2074883396259914) -> 2.2074883 | AA22: =IFERROR(__xludf.DUMMYFUNCTION("""COMPUTED_VALUE"""),1.185768408482888) -> 1.1857684 | AB22: =IFERROR(__xludf.DUMMYFUNCTION("""COMPUTED_VALUE"""),2.5272357253310047) -> 2.5272357 | AC22: =IFERROR(__xludf.DUMMYFUNCTION("""COMPUTED_VALUE"""),1.3856967886612432) -> 1.3856968 | AD22: =IFERROR(__xludf.DUMMYFUNCTION("""COMPUTED_VALUE"""),-0.36012199295598174) -> -0.36012199 | AE22: =IFERROR(__xludf.DUMMYFUNCTION("""COMPUTED_VALUE"""),-0.46671174701275525) -> -0.46671175 | AF22: =IFERROR(__xludf.DUMMYFUNCTION("""COMPUTED_VALUE"""),-0.23845313768276888) -> -0.23845314 | AG22: =IFERROR(__xludf.DUMMYFUNCTION("""COMPUTED_VALUE"""),0.0) -> 0 | AJ22: 100 | AK22: {=if(AK$20=$J3,"-", countif(indirect(address(row($J$2)+ VLOOKUP(AK$20,$J$3:$J$14,1),COLUMN($K$4))):indirect(address(row($J$2)+ VLOOKUP(AK$20,$J$3:$J$14,1),COLUMN($S$2)))>indirect(address(row($J3),COLUMN($K$2))):indirect(address(row($J3),COLUMN($S$2))),TRUE()))} -> - | AL22: {=if(AL$20=$J3,"-", countif(indirect(address(row($J$2)+ VLOOKUP(AL$20,$J$3:$J$14,1),COLUMN($K$4))):indirect(address(row($J$2)+ VLOOKUP(AL$20,$J$3:$J$14,1),COLUMN($S$2)))>indirect(address(row($J3),COLUMN($K$2))):indirect(address(row($J3),COLUMN($S$2))),TRUE()))} -> 2 | AM22: {=if(AM$20=$J3,"-", countif(indirect(address(row($J$2)+ VLOOKUP(AM$20,$J$3:$J$14,1),COLUMN($K$4))):indirect(address(row($J$2)+ VLOOKUP(AM$20,$J$3:$J$14,1),COLUMN($S$2)))>indirect(address(row($J3),COLUMN($K$2))):indirect(address(row($J3),COLUMN($S$2))),TRUE()))} -> 2 | AN22: {=if(AN$20=$J3,"-", countif(indirect(address(row($J$2)+ VLOOKUP(AN$20,$J$3:$J$14,1),COLUMN($K$4))):indirect(address(row($J$2)+ VLOOKUP(AN$20,$J$3:$J$14,1),COLUMN($S$2)))>indirect(address(row($J3),COLUMN($K$2))):indirect(address(row($J3),COLUMN($S$2))),TRUE()))} -> 2 | AO22: {=if(AO$20=$J3,"-", countif(indirect(address(row($J$2)+ VLOOKUP(AO$20,$J$3:$J$14,1),COLUMN($K$4))):indirect(address(row($J$2)+ VLOOKUP(AO$20,$J$3:$J$14,1),COLUMN($S$2)))>indirect(address(row($J3),COLUMN($K$2))):indirect(address(row($J3),COLUMN($S$2))),TRUE()))} -> 2 | AP22: {=if(AP$20=$J3,"-", countif(indirect(address(row($J$2)+ VLOOKUP(AP$20,$J$3:$J$14,1),COLUMN($K$4))):indirect(address(row($J$2)+ VLOOKUP(AP$20,$J$3:$J$14,1),COLUMN($S$2)))>indirect(address(row($J3),COLUMN($K$2))):indirect(address(row($J3),COLUMN($S$2))),TRUE()))} -> 2 | AQ22: {=if(AQ$20=$J3,"-", countif(indirect(address(row($J$2)+ VLOOKUP(AQ$20,$J$3:$J$14,1),COLUMN($K$4))):indirect(address(row($J$2)+ VLOOKUP(AQ$20,$J$3:$J$14,1),COLUMN($S$2)))>indirect(address(row($J3),COLUMN($K$2))):indirect(address(row($J3),COLUMN($S$2))),TRUE()))} -> 2 | AR22: {=if(AR$20=$J3,"-", countif(indirect(address(row($J$2)+ VLOOKUP(AR$20,$J$3:$J$14,1),COLUMN($K$4))):indirect(address(row($J$2)+ VLOOKUP(AR$20,$J$3:$J$14,1),COLUMN($S$2)))>indirect(address(row($J3),COLUMN($K$2))):indirect(address(row($J3),COLUMN($S$2))),TRUE()))} -> 2 | ... AV22: {=if(AV$20=$J3,"-", countif(indirect(address(row($J$2)+ VLOOKUP(AV$20,$J$3:$J$14,1),COLUMN($K$4))):indirect(address(row($J$2)+ VLOOKUP(AV$20,$J$3:$J$14,1),COLUMN($S$2)))>indirect(address(row($J3),COLUMN($K$2))):indirect(address(row($J3),COLUMN($S$2))),TRUE()))} -> 2 | AW22: 1 | AX22: {=INDIRECT("Draft!D"&TEXT(VLOOKUP(TRUE,I3:J14,2,0)+2,"0"))} | AZ22: =IF($AX22="","", VLOOKUP($AX22,'Final Update'!$P$21:$AD1015,Column(H1),False)) | BA22: =IF($AX22="","", VLOOKUP($AX22,'Final Update'!$P$21:$AD1015,Column(I1),False)) | BB22: =IF($AX22="","", VLOOKUP($AX22,'Final Update'!$P$21:$AD1015,Column(J1),False)) | BC22: =IF($AX22="","", VLOOKUP($AX22,'Final Update'!$P$21:$AD1015,Column(K1),False)) | BD22: =IF($AX22="","", VLOOKUP($AX22,'Final Update'!$P$21:$AD1015,Column(L1),False)) | BE22: =IF($AX22="","", VLOOKUP($AX22,'Final Update'!$P$21:$AD1015,Column(M1),False)) | BF22: =IF($AX22="","", VLOOKUP($AX22,'Final Update'!$P$21:$AD1015,Column(N1),False)) | BG22: =IF($AX22="","", VLOOKUP($AX22,'Final Update'!$P$21:$AD1015,Column(O1),False)) | BH22: =IF($AX22="","", VLOOKUP($AX22,'Final Update'!$P$21:$AD1015,Column(P1),False)) | BI22: =IF($AX22="","", VLOOKUP($AX22,'Final Update'!$P$21:$AD1015,Column(C1),False)) | BJ22: {=COUNTIF(FIND(BK22,$BI$22:$BI$33),">0")} -> 0 | BK22: PG
A23: =VLOOKUP($F23,UpdateHashtag!$V$3:$Y$32,COLUMN(B$15),0) -> 3 | B23: =VLOOKUP($F23,UpdateHashtag!$V$3:$Y$32,COLUMN(C$13),0) -> 4 | C23: =VLOOKUP($F23,UpdateHashtag!$V$3:$Y$32,COLUMN(D$13),0) -> 3 | D23: =SUM(A23:C23) -> 10 | F23: =IF(VLOOKUP(J23,PasteHashtag!$C$2:$P1015,3,)="BRO","BKN",IF(VLOOKUP(J23,PasteHashtag!$C$2:$P1015,3,)="OKL","OKC",VLOOKUP(J23,PasteHashtag!$C$2:$P1015,3,))) -> LAL | G23: 4 | H23: =IFERROR(__xludf.DUMMYFUNCTION("""COMPUTED_VALUE"""),5.0) -> 5 | I23: =IFERROR(__xludf.DUMMYFUNCTION("""COMPUTED_VALUE"""),7.4) -> 7.4 | J23: =IFERROR(__xludf.DUMMYFUNCTION("""COMPUTED_VALUE"""),"Anthony Davis") -> Anthony Davis | K23: =IFERROR(__xludf.DUMMYFUNCTION("""COMPUTED_VALUE"""),74.0) -> 74 | L23: =IFERROR(__xludf.DUMMYFUNCTION("""COMPUTED_VALUE"""),"SF,PF") -> SF,PF | M23: =IFERROR(__xludf.DUMMYFUNCTION("""COMPUTED_VALUE"""),7.557301441135948) -> 7.5573014 | N23: =IFERROR(__xludf.DUMMYFUNCTION("""COMPUTED_VALUE"""),7.711756738160858) -> 7.7117567 | O23: =IFERROR(__xludf.DUMMYFUNCTION("""COMPUTED_VALUE"""),0.15445529702491) -> 0.1544553 | P23: =IFERROR(__xludf.DUMMYFUNCTION("""COMPUTED_VALUE"""),25.12242424) -> 25.122424 | Q23: =IFERROR(__xludf.DUMMYFUNCTION("""COMPUTED_VALUE"""),0.5036363636) -> 0.50363636 | R23: =IFERROR(__xludf.DUMMYFUNCTION("""COMPUTED_VALUE"""),13.46393939) -> 13.463939 | S23: =IFERROR(__xludf.DUMMYFUNCTION("""COMPUTED_VALUE"""),3.366060606) -> 3.3660606 | T23: =IFERROR(__xludf.DUMMYFUNCTION("""COMPUTED_VALUE"""),1.307878788) -> 1.3078788 | U23: =IFERROR(__xludf.DUMMYFUNCTION("""COMPUTED_VALUE"""),2.065454545) -> 2.0654545 | V23: =IFERROR(__xludf.DUMMYFUNCTION("""COMPUTED_VALUE"""),0.556141401) -> 0.5561414 | W23: =IFERROR(__xludf.DUMMYFUNCTION("""COMPUTED_VALUE"""),0.8080080528) -> 0.80800805 | X23: =IFERROR(__xludf.DUMMYFUNCTION("""COMPUTED_VALUE"""),2.371515152) -> 2.3715152 | Y23: =IFERROR(__xludf.DUMMYFUNCTION("""COMPUTED_VALUE"""),1.37602784738395) -> 1.3760278 | Z23: =IFERROR(__xludf.DUMMYFUNCTION("""COMPUTED_VALUE"""),-1.2349810895807822) -> -1.2349811 | AA23: =IFERROR(__xludf.DUMMYFUNCTION("""COMPUTED_VALUE"""),2.8925111508177013) -> 2.8925112 | AB23: =IFERROR(__xludf.DUMMYFUNCTION("""COMPUTED_VALUE"""),-0.2576203341327158) -> -0.25762033 | AC23: =IFERROR(__xludf.DUMMYFUNCTION("""COMPUTED_VALUE"""),1.0979590346397636) -> 1.097959 | AD23: =IFERROR(__xludf.DUMMYFUNCTION("""COMPUTED_VALUE"""),2.3486858336839282) -> 2.3486858 | AE23: =IFERROR(__xludf.DUMMYFUNCTION("""COMPUTED_VALUE"""),1.1791629477595917) -> 1.1791629 | AF23: =IFERROR(__xludf.DUMMYFUNCTION("""COMPUTED_VALUE"""),0.31001134758942167) -> 0.31001135 | AG23: =IFERROR(__xludf.DUMMYFUNCTION("""COMPUTED_VALUE"""),0.0) -> 0 | AJ23: 100 | AK23: {=if(AK$20=$J4,"-", countif(indirect(address(row($J$2)+ VLOOKUP(AK$20,$J$3:$J$14,1),COLUMN($K$4))):indirect(address(row($J$2)+ VLOOKUP(AK$20,$J$3:$J$14,1),COLUMN($S$2)))>indirect(address(row($J4),COLUMN($K$2))):indirect(address(row($J4),COLUMN($S$2))),TRUE()))} -> 7 | AL23: {=if(AL$20=$J4,"-", countif(indirect(address(row($J$2)+ VLOOKUP(AL$20,$J$3:$J$14,1),COLUMN($K$4))):indirect(address(row($J$2)+ VLOOKUP(AL$20,$J$3:$J$14,1),COLUMN($S$2)))>indirect(address(row($J4),COLUMN($K$2))):indirect(address(row($J4),COLUMN($S$2))),TRUE()))} -> - | AM23: {=if(AM$20=$J4,"-", countif(indirect(address(row($J$2)+ VLOOKUP(AM$20,$J$3:$J$14,1),COLUMN($K$4))):indirect(address(row($J$2)+ VLOOKUP(AM$20,$J$3:$J$14,1),COLUMN($S$2)))>indirect(address(row($J4),COLUMN($K$2))):indirect(address(row($J4),COLUMN($S$2))),TRUE()))} -> 0 | AN23: {=if(AN$20=$J4,"-", countif(indirect(address(row($J$2)+ VLOOKUP(AN$20,$J$3:$J$14,1),COLUMN($K$4))):indirect(address(row($J$2)+ VLOOKUP(AN$20,$J$3:$J$14,1),COLUMN($S$2)))>indirect(address(row($J4),COLUMN($K$2))):indirect(address(row($J4),COLUMN($S$2))),TRUE()))} -> 0 | AO23: {=if(AO$20=$J4,"-", countif(indirect(address(row($J$2)+ VLOOKUP(AO$20,$J$3:$J$14,1),COLUMN($K$4))):indirect(address(row($J$2)+ VLOOKUP(AO$20,$J$3:$J$14,1),COLUMN($S$2)))>indirect(address(row($J4),COLUMN($K$2))):indirect(address(row($J4),COLUMN($S$2))),TRUE()))} -> 0 | AP23: {=if(AP$20=$J4,"-", countif(indirect(address(row($J$2)+ VLOOKUP(AP$20,$J$3:$J$14,1),COLUMN($K$4))):indirect(address(row($J$2)+ VLOOKUP(AP$20,$J$3:$J$14,1),COLUMN($S$2)))>indirect(address(row($J4),COLUMN($K$2))):indirect(address(row($J4),COLUMN($S$2))),TRUE()))} -> 0 | AQ23: {=if(AQ$20=$J4,"-", countif(indirect(address(row($J$2)+ VLOOKUP(AQ$20,$J$3:$J$14,1),COLUMN($K$4))):indirect(address(row($J$2)+ VLOOKUP(AQ$20,$J$3:$J$14,1),COLUMN($S$2)))>indirect(address(row($J4),COLUMN($K$2))):indirect(address(row($J4),COLUMN($S$2))),TRUE()))} -> 0 | AR23: {=if(AR$20=$J4,"-", countif(indirect(address(row($J$2)+ VLOOKUP(AR$20,$J$3:$J$14,1),COLUMN($K$4))):indirect(address(row($J$2)+ VLOOKUP(AR$20,$J$3:$J$14,1),COLUMN($S$2)))>indirect(address(row($J4),COLUMN($K$2))):indirect(address(row($J4),COLUMN($S$2))),TRUE()))} -> 0 | ... AV23: {=if(AV$20=$J4,"-", countif(indirect(address(row($J$2)+ VLOOKUP(AV$20,$J$3:$J$14,1),COLUMN($K$4))):indirect(address(row($J$2)+ VLOOKUP(AV$20,$J$3:$J$14,1),COLUMN($S$2)))>indirect(address(row($J4),COLUMN($K$2))):indirect(address(row($J4),COLUMN($S$2))),TRUE()))} -> 0 | AW23: 2 | AX23: {=INDIRECT("Draft!E"&TEXT(15-VLOOKUP(TRUE,I3:J14,2,0),"0"))} | AZ23: =IF($AX23="","", VLOOKUP($AX23,'Final Update'!$P$21:$AD1015,Column(H2),False)) | BA23: =IF($AX23="","", VLOOKUP($AX23,'Final Update'!$P$21:$AD1015,Column(I2),False)) | BB23: =IF($AX23="","", VLOOKUP($AX23,'Final Update'!$P$21:$AD1015,Column(J2),False)) | BC23: =IF($AX23="","", VLOOKUP($AX23,'Final Update'!$P$21:$AD1015,Column(K2),False)) | BD23: =IF($AX23="","", VLOOKUP($AX23,'Final Update'!$P$21:$AD1015,Column(L2),False)) | BE23: =IF($AX23="","", VLOOKUP($AX23,'Final Update'!$P$21:$AD1015,Column(M2),False)) | BF23: =IF($AX23="","", VLOOKUP($AX23,'Final Update'!$P$21:$AD1015,Column(N2),False)) | BG23: =IF($AX23="","", VLOOKUP($AX23,'Final Update'!$P$21:$AD1015,Column(O2),False)) | BH23: =IF($AX23="","", VLOOKUP($AX23,'Final Update'!$P$21:$AD1015,Column(P2),False)) | BI23: =IF($AX23="","", VLOOKUP($AX23,'Final Update'!$P$21:$AD1015,Column(C2),False)) | BJ23: {=COUNTIF(FIND(BK23,$BI$22:$BI$33),">0")} -> 0 | BK23: SG
A24: =VLOOKUP($F24,UpdateHashtag!$V$3:$Y$32,COLUMN(B$15),0) -> 4 | B24: =VLOOKUP($F24,UpdateHashtag!$V$3:$Y$32,COLUMN(C$13),0) -> 4 | C24: =VLOOKUP($F24,UpdateHashtag!$V$3:$Y$32,COLUMN(D$13),0) -> 3 | D24: =SUM(A24:C24) -> 11 | F24: =IF(VLOOKUP(J24,PasteHashtag!$C$2:$P1015,3,)="BRO","BKN",IF(VLOOKUP(J24,PasteHashtag!$C$2:$P1015,3,)="OKL","OKC",VLOOKUP(J24,PasteHashtag!$C$2:$P1015,3,))) -> OKC | G24: 5 | H24: =IFERROR(__xludf.DUMMYFUNCTION("""COMPUTED_VALUE"""),6.0) -> 6 | I24: =IFERROR(__xludf.DUMMYFUNCTION("""COMPUTED_VALUE"""),4.5) -> 4.5 | J24: =IFERROR(__xludf.DUMMYFUNCTION("""COMPUTED_VALUE"""),"Shai Gilgeous-Alexander") -> Shai Gilgeous-Alexander | K24: =IFERROR(__xludf.DUMMYFUNCTION("""COMPUTED_VALUE"""),64.0) -> 64 | L24: =IFERROR(__xludf.DUMMYFUNCTION("""COMPUTED_VALUE"""),"SG,SF") -> SG,SF | M24: =IFERROR(__xludf.DUMMYFUNCTION("""COMPUTED_VALUE"""),6.736591490731338) -> 6.7365915 | N24: =IFERROR(__xludf.DUMMYFUNCTION("""COMPUTED_VALUE"""),6.959358711350021) -> 6.9593587 | O24: =IFERROR(__xludf.DUMMYFUNCTION("""COMPUTED_VALUE"""),0.2227672206186826) -> 0.22276722 | P24: =IFERROR(__xludf.DUMMYFUNCTION("""COMPUTED_VALUE"""),29.18123288) -> 29.181233 | Q24: =IFERROR(__xludf.DUMMYFUNCTION("""COMPUTED_VALUE"""),1.557945205) -> 1.5579452 | R24: =IFERROR(__xludf.DUMMYFUNCTION("""COMPUTED_VALUE"""),5.437123288) -> 5.4371233 | S24: =IFERROR(__xludf.DUMMYFUNCTION("""COMPUTED_VALUE"""),6.939589041) -> 6.939589 | T24: =IFERROR(__xludf.DUMMYFUNCTION("""COMPUTED_VALUE"""),1.502328767) -> 1.5023288 | U24: =IFERROR(__xludf.DUMMYFUNCTION("""COMPUTED_VALUE"""),0.7869863014) -> 0.7869863 | V24: =IFERROR(__xludf.DUMMYFUNCTION("""COMPUTED_VALUE"""),0.5123976584) -> 0.51239766 | W24: =IFERROR(__xludf.DUMMYFUNCTION("""COMPUTED_VALUE"""),0.8549952613) -> 0.85499526 | X24: =IFERROR(__xludf.DUMMYFUNCTION("""COMPUTED_VALUE"""),2.646986301) -> 2.6469863 | Y24: =IFERROR(__xludf.DUMMYFUNCTION("""COMPUTED_VALUE"""),2.107650991319318) -> 2.107651 | Z24: =IFERROR(__xludf.DUMMYFUNCTION("""COMPUTED_VALUE"""),-0.18918206083448794) -> -0.18918206 | AA24: =IFERROR(__xludf.DUMMYFUNCTION("""COMPUTED_VALUE"""),-0.2532542378696264) -> -0.25325424 | AB24: =IFERROR(__xludf.DUMMYFUNCTION("""COMPUTED_VALUE"""),1.365256185570836) -> 1.3652562 | AC24: =IFERROR(__xludf.DUMMYFUNCTION("""COMPUTED_VALUE"""),1.7412605017662555) -> 1.7412605 | AD24: =IFERROR(__xludf.DUMMYFUNCTION("""COMPUTED_VALUE"""),0.06834873310349474) -> 0.068348733 | AE24: =IFERROR(__xludf.DUMMYFUNCTION("""COMPUTED_VALUE"""),0.35176815797639455) -> 0.35176816 | AF24: =IFERROR(__xludf.DUMMYFUNCTION("""COMPUTED_VALUE"""),1.7675104403178359) -> 1.7675104 | AG24: =IFERROR(__xludf.DUMMYFUNCTION("""COMPUTED_VALUE"""),0.0) -> 0 | AJ24: 100 | AK24: {=if(AK$20=$J5,"-", countif(indirect(address(row($J$2)+ VLOOKUP(AK$20,$J$3:$J$14,1),COLUMN($K$4))):indirect(address(row($J$2)+ VLOOKUP(AK$20,$J$3:$J$14,1),COLUMN($S$2)))>indirect(address(row($J5),COLUMN($K$2))):indirect(address(row($J5),COLUMN($S$2))),TRUE()))} -> 7 | AL24: {=if(AL$20=$J5,"-", countif(indirect(address(row($J$2)+ VLOOKUP(AL$20,$J$3:$J$14,1),COLUMN($K$4))):indirect(address(row($J$2)+ VLOOKUP(AL$20,$J$3:$J$14,1),COLUMN($S$2)))>indirect(address(row($J5),COLUMN($K$2))):indirect(address(row($J5),COLUMN($S$2))),TRUE()))} -> 0 | AM24: {=if(AM$20=$J5,"-", countif(indirect(address(row($J$2)+ VLOOKUP(AM$20,$J$3:$J$14,1),COLUMN($K$4))):indirect(address(row($J$2)+ VLOOKUP(AM$20,$J$3:$J$14,1),COLUMN($S$2)))>indirect(address(row($J5),COLUMN($K$2))):indirect(address(row($J5),COLUMN($S$2))),TRUE()))} -> - | AN24: {=if(AN$20=$J5,"-", countif(indirect(address(row($J$2)+ VLOOKUP(AN$20,$J$3:$J$14,1),COLUMN($K$4))):indirect(address(row($J$2)+ VLOOKUP(AN$20,$J$3:$J$14,1),COLUMN($S$2)))>indirect(address(row($J5),COLUMN($K$2))):indirect(address(row($J5),COLUMN($S$2))),TRUE()))} -> 0 | AO24: {=if(AO$20=$J5,"-", countif(indirect(address(row($J$2)+ VLOOKUP(AO$20,$J$3:$J$14,1),COLUMN($K$4))):indirect(address(row($J$2)+ VLOOKUP(AO$20,$J$3:$J$14,1),COLUMN($S$2)))>indirect(address(row($J5),COLUMN($K$2))):indirect(address(row($J5),COLUMN($S$2))),TRUE()))} -> 0 | AP24: {=if(AP$20=$J5,"-", countif(indirect(address(row($J$2)+ VLOOKUP(AP$20,$J$3:$J$14,1),COLUMN($K$4))):indirect(address(row($J$2)+ VLOOKUP(AP$20,$J$3:$J$14,1),COLUMN($S$2)))>indirect(address(row($J5),COLUMN($K$2))):indirect(address(row($J5),COLUMN($S$2))),TRUE()))} -> 0 | AQ24: {=if(AQ$20=$J5,"-", countif(indirect(address(row($J$2)+ VLOOKUP(AQ$20,$J$3:$J$14,1),COLUMN($K$4))):indirect(address(row($J$2)+ VLOOKUP(AQ$20,$J$3:$J$14,1),COLUMN($S$2)))>indirect(address(row($J5),COLUMN($K$2))):indirect(address(row($J5),COLUMN($S$2))),TRUE()))} -> 0 | AR24: {=if(AR$20=$J5,"-", countif(indirect(address(row($J$2)+ VLOOKUP(AR$20,$J$3:$J$14,1),COLUMN($K$4))):indirect(address(row($J$2)+ VLOOKUP(AR$20,$J$3:$J$14,1),COLUMN($S$2)))>indirect(address(row($J5),COLUMN($K$2))):indirect(address(row($J5),COLUMN($S$2))),TRUE()))} -> 0 | ... AV24: {=if(AV$20=$J5,"-", countif(indirect(address(row($J$2)+ VLOOKUP(AV$20,$J$3:$J$14,1),COLUMN($K$4))):indirect(address(row($J$2)+ VLOOKUP(AV$20,$J$3:$J$14,1),COLUMN($S$2)))>indirect(address(row($J5),COLUMN($K$2))):indirect(address(row($J5),COLUMN($S$2))),TRUE()))} -> 0 | AW24: 3 | AX24: {=INDIRECT("Draft!F"&TEXT(VLOOKUP(TRUE,I3:J14,2,0)+2,"0"))} | AZ24: =IF($AX24="","", VLOOKUP($AX24,'Final Update'!$P$21:$AD1015,Column(H3),False)) | BA24: =IF($AX24="","", VLOOKUP($AX24,'Final Update'!$P$21:$AD1015,Column(I3),False)) | BB24: =IF($AX24="","", VLOOKUP($AX24,'Final Update'!$P$21:$AD1015,Column(J3),False)) | BC24: =IF($AX24="","", VLOOKUP($AX24,'Final Update'!$P$21:$AD1015,Column(K3),False)) | BD24: =IF($AX24="","", VLOOKUP($AX24,'Final Update'!$P$21:$AD1015,Column(L3),False)) | BE24: =IF($AX24="","", VLOOKUP($AX24,'Final Update'!$P$21:$AD1015,Column(M3),False)) | BF24: =IF($AX24="","", VLOOKUP($AX24,'Final Update'!$P$21:$AD1015,Column(N3),False)) | BG24: =IF($AX24="","", VLOOKUP($AX24,'Final Update'!$P$21:$AD1015,Column(O3),False)) | BH24: =IF($AX24="","", VLOOKUP($AX24,'Final Update'!$P$21:$AD1015,Column(P3),False)) | BI24: =IF($AX24="","", VLOOKUP($AX24,'Final Update'!$P$21:$AD1015,Column(C3),False)) | BJ24: {=COUNTIF(FIND(BK24,$BI$22:$BI$33),">0")} -> 0 | BK24: SF
A25: =VLOOKUP($F25,UpdateHashtag!$V$3:$Y$32,COLUMN(B$15),0) -> 4 | B25: =VLOOKUP($F25,UpdateHashtag!$V$3:$Y$32,COLUMN(C$13),0) -> 3 | C25: =VLOOKUP($F25,UpdateHashtag!$V$3:$Y$32,COLUMN(D$13),0) -> 4 | D25: =SUM(A25:C25) -> 11 | F25: =IF(VLOOKUP(J25,PasteHashtag!$C$2:$P1015,3,)="BRO","BKN",IF(VLOOKUP(J25,PasteHashtag!$C$2:$P1015,3,)="OKL","OKC",VLOOKUP(J25,PasteHashtag!$C$2:$P1015,3,))) -> CHA | G25: 6 | H25: =IFERROR(__xludf.DUMMYFUNCTION("""COMPUTED_VALUE"""),7.0) -> 7 | I25: =IFERROR(__xludf.DUMMYFUNCTION("""COMPUTED_VALUE"""),22.3) -> 22.3 | J25: =IFERROR(__xludf.DUMMYFUNCTION("""COMPUTED_VALUE"""),"LaMelo Ball") -> LaMelo Ball | K25: =IFERROR(__xludf.DUMMYFUNCTION("""COMPUTED_VALUE"""),77.0) -> 77 | L25: =IFERROR(__xludf.DUMMYFUNCTION("""COMPUTED_VALUE"""),"PG,SG") -> PG,SG | M25: =IFERROR(__xludf.DUMMYFUNCTION("""COMPUTED_VALUE"""),6.171957496592203) -> 6.1719575 | N25: =IFERROR(__xludf.DUMMYFUNCTION("""COMPUTED_VALUE"""),6.588658143108068) -> 6.5886581 | O25: =IFERROR(__xludf.DUMMYFUNCTION("""COMPUTED_VALUE"""),0.41670064651586536) -> 0.41670065 | P25: =IFERROR(__xludf.DUMMYFUNCTION("""COMPUTED_VALUE"""),26.09983871) -> 26.099839 | Q25: =IFERROR(__xludf.DUMMYFUNCTION("""COMPUTED_VALUE"""),3.96) -> 3.96 | R25: =IFERROR(__xludf.DUMMYFUNCTION("""COMPUTED_VALUE"""),5.909677419) -> 5.9096774 | S25: =IFERROR(__xludf.DUMMYFUNCTION("""COMPUTED_VALUE"""),8.492419355) -> 8.4924194 | T25: =IFERROR(__xludf.DUMMYFUNCTION("""COMPUTED_VALUE"""),1.680483871) -> 1.6804839 | U25: =IFERROR(__xludf.DUMMYFUNCTION("""COMPUTED_VALUE"""),0.2917741935) -> 0.29177419 | V25: =IFERROR(__xludf.DUMMYFUNCTION("""COMPUTED_VALUE"""),0.4356151932) -> 0.43561519 | W25: =IFERROR(__xludf.DUMMYFUNCTION("""COMPUTED_VALUE"""),0.846013795) -> 0.84601379 | X25: =IFERROR(__xludf.DUMMYFUNCTION("""COMPUTED_VALUE"""),3.429032258) -> 3.4290323 | Y25: =IFERROR(__xludf.DUMMYFUNCTION("""COMPUTED_VALUE"""),1.5522123169896227) -> 1.5522123 | Z25: =IFERROR(__xludf.DUMMYFUNCTION("""COMPUTED_VALUE"""),2.1934846426626065) -> 2.1934846 | AA25: =IFERROR(__xludf.DUMMYFUNCTION("""COMPUTED_VALUE"""),-0.0680569677825962) -> -0.068056968 | AB25: =IFERROR(__xludf.DUMMYFUNCTION("""COMPUTED_VALUE"""),2.070456074563602) -> 2.0704561 | AC25: =IFERROR(__xludf.DUMMYFUNCTION("""COMPUTED_VALUE"""),2.3306534159165455) -> 2.3306534 | AD25: =IFERROR(__xludf.DUMMYFUNCTION("""COMPUTED_VALUE"""),-0.8149352655050185) -> -0.81493527 | AE25: =IFERROR(__xludf.DUMMYFUNCTION("""COMPUTED_VALUE"""),-1.5010523381290475) -> -1.5010523 | AF25: =IFERROR(__xludf.DUMMYFUNCTION("""COMPUTED_VALUE"""),0.8258962643923514) -> 0.82589626 | AG25: =IFERROR(__xludf.DUMMYFUNCTION("""COMPUTED_VALUE"""),0.0) -> 0 | AJ25: 100 | AK25: {=if(AK$20=$J6,"-", countif(indirect(address(row($J$2)+ VLOOKUP(AK$20,$J$3:$J$14,1),COLUMN($K$4))):indirect(address(row($J$2)+ VLOOKUP(AK$20,$J$3:$J$14,1),COLUMN($S$2)))>indirect(address(row($J6),COLUMN($K$2))):indirect(address(row($J6),COLUMN($S$2))),TRUE()))} -> 7 | AL25: {=if(AL$20=$J6,"-", countif(indirect(address(row($J$2)+ VLOOKUP(AL$20,$J$3:$J$14,1),COLUMN($K$4))):indirect(address(row($J$2)+ VLOOKUP(AL$20,$J$3:$J$14,1),COLUMN($S$2)))>indirect(address(row($J6),COLUMN($K$2))):indirect(address(row($J6),COLUMN($S$2))),TRUE()))} -> 0 | AM25: {=if(AM$20=$J6,"-", countif(indirect(address(row($J$2)+ VLOOKUP(AM$20,$J$3:$J$14,1),COLUMN($K$4))):indirect(address(row($J$2)+ VLOOKUP(AM$20,$J$3:$J$14,1),COLUMN($S$2)))>indirect(address(row($J6),COLUMN($K$2))):indirect(address(row($J6),COLUMN($S$2))),TRUE()))} -> 0 | AN25: {=if(AN$20=$J6,"-", countif(indirect(address(row($J$2)+ VLOOKUP(AN$20,$J$3:$J$14,1),COLUMN($K$4))):indirect(address(row($J$2)+ VLOOKUP(AN$20,$J$3:$J$14,1),COLUMN($S$2)))>indirect(address(row($J6),COLUMN($K$2))):indirect(address(row($J6),COLUMN($S$2))),TRUE()))} -> - | AO25: {=if(AO$20=$J6,"-", countif(indirect(address(row($J$2)+ VLOOKUP(AO$20,$J$3:$J$14,1),COLUMN($K$4))):indirect(address(row($J$2)+ VLOOKUP(AO$20,$J$3:$J$14,1),COLUMN($S$2)))>indirect(address(row($J6),COLUMN($K$2))):indirect(address(row($J6),COLUMN($S$2))),TRUE()))} -> 0 | AP25: {=if(AP$20=$J6,"-", countif(indirect(address(row($J$2)+ VLOOKUP(AP$20,$J$3:$J$14,1),COLUMN($K$4))):indirect(address(row($J$2)+ VLOOKUP(AP$20,$J$3:$J$14,1),COLUMN($S$2)))>indirect(address(row($J6),COLUMN($K$2))):indirect(address(row($J6),COLUMN($S$2))),TRUE()))} -> 0 | AQ25: {=if(AQ$20=$J6,"-", countif(indirect(address(row($J$2)+ VLOOKUP(AQ$20,$J$3:$J$14,1),COLUMN($K$4))):indirect(address(row($J$2)+ VLOOKUP(AQ$20,$J$3:$J$14,1),COLUMN($S$2)))>indirect(address(row($J6),COLUMN($K$2))):indirect(address(row($J6),COLUMN($S$2))),TRUE()))} -> 0 | AR25: {=if(AR$20=$J6,"-", countif(indirect(address(row($J$2)+ VLOOKUP(AR$20,$J$3:$J$14,1),COLUMN($K$4))):indirect(address(row($J$2)+ VLOOKUP(AR$20,$J$3:$J$14,1),COLUMN($S$2)))>indirect(address(row($J6),COLUMN($K$2))):indirect(address(row($J6),COLUMN($S$2))),TRUE()))} -> 0 | ... AV25: {=if(AV$20=$J6,"-", countif(indirect(address(row($J$2)+ VLOOKUP(AV$20,$J$3:$J$14,1),COLUMN($K$4))):indirect(address(row($J$2)+ VLOOKUP(AV$20,$J$3:$J$14,1),COLUMN($S$2)))>indirect(address(row($J6),COLUMN($K$2))):indirect(address(row($J6),COLUMN($S$2))),TRUE()))} -> 0 | AW25: 4 | AX25: {=INDIRECT("Draft!G"&TEXT(15-VLOOKUP(TRUE,I3:J14,2,0),"0"))} | AZ25: =IF($AX25="","", VLOOKUP($AX25,'Final Update'!$P$21:$AD1015,Column(H4),False)) | BA25: =IF($AX25="","", VLOOKUP($AX25,'Final Update'!$P$21:$AD1015,Column(I4),False)) | BB25: =IF($AX25="","", VLOOKUP($AX25,'Final Update'!$P$21:$AD1015,Column(J4),False)) | BC25: =IF($AX25="","", VLOOKUP($AX25,'Final Update'!$P$21:$AD1015,Column(K4),False)) | BD25: =IF($AX25="","", VLOOKUP($AX25,'Final Update'!$P$21:$AD1015,Column(L4),False)) | BE25: =IF($AX25="","", VLOOKUP($AX25,'Final Update'!$P$21:$AD1015,Column(M4),False)) | BF25: =IF($AX25="","", VLOOKUP($AX25,'Final Update'!$P$21:$AD1015,Column(N4),False)) | BG25: =IF($AX25="","", VLOOKUP($AX25,'Final Update'!$P$21:$AD1015,Column(O4),False)) | BH25: =IF($AX25="","", VLOOKUP($AX25,'Final Update'!$P$21:$AD1015,Column(P4),False)) | BI25: =IF($AX25="","", VLOOKUP($AX25,'Final Update'!$P$21:$AD1015,Column(C4),False)) | BJ25: {=COUNTIF(FIND(BK25,$BI$22:$BI$33),">0")} -> 0 | BK25: PF
A26: =VLOOKUP($F26,UpdateHashtag!$V$3:$Y$32,COLUMN(B$15),0) -> 3 | B26: =VLOOKUP($F26,UpdateHashtag!$V$3:$Y$32,COLUMN(C$13),0) -> 4 | C26: =VLOOKUP($F26,UpdateHashtag!$V$3:$Y$32,COLUMN(D$13),0) -> 4 | D26: =SUM(A26:C26) -> 11 | F26: =IF(VLOOKUP(J26,PasteHashtag!$C$2:$P1015,3,)="BRO","BKN",IF(VLOOKUP(J26,PasteHashtag!$C$2:$P1015,3,)="OKL","OKC",VLOOKUP(J26,PasteHashtag!$C$2:$P1015,3,))) -> IND | G26: 7 | H26: =IFERROR(__xludf.DUMMYFUNCTION("""COMPUTED_VALUE"""),8.0) -> 8 | I26: =IFERROR(__xludf.DUMMYFUNCTION("""COMPUTED_VALUE"""),8.4) -> 8.4 | J26: =IFERROR(__xludf.DUMMYFUNCTION("""COMPUTED_VALUE"""),"Tyrese Haliburton") -> Tyrese Haliburton | K26: =IFERROR(__xludf.DUMMYFUNCTION("""COMPUTED_VALUE"""),73.0) -> 73 | L26: =IFERROR(__xludf.DUMMYFUNCTION("""COMPUTED_VALUE"""),"SF,PF") -> SF,PF | M26: =IFERROR(__xludf.DUMMYFUNCTION("""COMPUTED_VALUE"""),5.239584635982243) -> 5.2395846 | N26: =IFERROR(__xludf.DUMMYFUNCTION("""COMPUTED_VALUE"""),5.381228627636958) -> 5.3812286 | O26: =IFERROR(__xludf.DUMMYFUNCTION("""COMPUTED_VALUE"""),0.14164399165471497) -> 0.14164399 | P26: =IFERROR(__xludf.DUMMYFUNCTION("""COMPUTED_VALUE"""),19.71779412) -> 19.717794 | Q26: =IFERROR(__xludf.DUMMYFUNCTION("""COMPUTED_VALUE"""),2.888382353) -> 2.8883824 | R26: =IFERROR(__xludf.DUMMYFUNCTION("""COMPUTED_VALUE"""),3.965441176) -> 3.9654412 | S26: =IFERROR(__xludf.DUMMYFUNCTION("""COMPUTED_VALUE"""),10.62191176) -> 10.621912 | T26: =IFERROR(__xludf.DUMMYFUNCTION("""COMPUTED_VALUE"""),1.416176471) -> 1.4161765 | U26: =IFERROR(__xludf.DUMMYFUNCTION("""COMPUTED_VALUE"""),0.6373529412) -> 0.63735294 | V26: =IFERROR(__xludf.DUMMYFUNCTION("""COMPUTED_VALUE"""),0.4795063553) -> 0.47950636 | W26: =IFERROR(__xludf.DUMMYFUNCTION("""COMPUTED_VALUE"""),0.8569964121) -> 0.85699641 | X26: =IFERROR(__xludf.DUMMYFUNCTION("""COMPUTED_VALUE"""),2.319852941) -> 2.3198529 | Y26: =IFERROR(__xludf.DUMMYFUNCTION("""COMPUTED_VALUE"""),0.40181279293827227) -> 0.40181279 | Z26: =IFERROR(__xludf.DUMMYFUNCTION("""COMPUTED_VALUE"""),1.1305165156649861) -> 1.1305165 | AA26: =IFERROR(__xludf.DUMMYFUNCTION("""COMPUTED_VALUE"""),-0.8300167539469965) -> -0.83001675 | AB26: =IFERROR(__xludf.DUMMYFUNCTION("""COMPUTED_VALUE"""),3.037540368370697) -> 3.0375404 | AC26: =IFERROR(__xludf.DUMMYFUNCTION("""COMPUTED_VALUE"""),1.4562417082537304) -> 1.4562417 | AD26: =IFERROR(__xludf.DUMMYFUNCTION("""COMPUTED_VALUE"""),-0.19854448419516899) -> -0.19854448 | AE26: =IFERROR(__xludf.DUMMYFUNCTION("""COMPUTED_VALUE"""),-0.3039179224619302) -> -0.30391792 | AF26: =IFERROR(__xludf.DUMMYFUNCTION("""COMPUTED_VALUE"""),0.6875964030133674) -> 0.6875964 | AG26: =IFERROR(__xludf.DUMMYFUNCTION("""COMPUTED_VALUE"""),0.0) -> 0 | AJ26: 100 | AK26: {=if(AK$20=$J7,"-", countif(indirect(address(row($J$2)+ VLOOKUP(AK$20,$J$3:$J$14,1),COLUMN($K$4))):indirect(address(row($J$2)+ VLOOKUP(AK$20,$J$3:$J$14,1),COLUMN($S$2)))>indirect(address(row($J7),COLUMN($K$2))):indirect(address(row($J7),COLUMN($S$2))),TRUE()))} -> 7 | AL26: {=if(AL$20=$J7,"-", countif(indirect(address(row($J$2)+ VLOOKUP(AL$20,$J$3:$J$14,1),COLUMN($K$4))):indirect(address(row($J$2)+ VLOOKUP(AL$20,$J$3:$J$14,1),COLUMN($S$2)))>indirect(address(row($J7),COLUMN($K$2))):indirect(address(row($J7),COLUMN($S$2))),TRUE()))} -> 0 | AM26: {=if(AM$20=$J7,"-", countif(indirect(address(row($J$2)+ VLOOKUP(AM$20,$J$3:$J$14,1),COLUMN($K$4))):indirect(address(row($J$2)+ VLOOKUP(AM$20,$J$3:$J$14,1),COLUMN($S$2)))>indirect(address(row($J7),COLUMN($K$2))):indirect(address(row($J7),COLUMN($S$2))),TRUE()))} -> 0 | AN26: {=if(AN$20=$J7,"-", countif(indirect(address(row($J$2)+ VLOOKUP(AN$20,$J$3:$J$14,1),COLUMN($K$4))):indirect(address(row($J$2)+ VLOOKUP(AN$20,$J$3:$J$14,1),COLUMN($S$2)))>indirect(address(row($J7),COLUMN($K$2))):indirect(address(row($J7),COLUMN($S$2))),TRUE()))} -> 0 | AO26: {=if(AO$20=$J7,"-", countif(indirect(address(row($J$2)+ VLOOKUP(AO$20,$J$3:$J$14,1),COLUMN($K$4))):indirect(address(row($J$2)+ VLOOKUP(AO$20,$J$3:$J$14,1),COLUMN($S$2)))>indirect(address(row($J7),COLUMN($K$2))):indirect(address(row($J7),COLUMN($S$2))),TRUE()))} -> - | AP26: {=if(AP$20=$J7,"-", countif(indirect(address(row($J$2)+ VLOOKUP(AP$20,$J$3:$J$14,1),COLUMN($K$4))):indirect(address(row($J$2)+ VLOOKUP(AP$20,$J$3:$J$14,1),COLUMN($S$2)))>indirect(address(row($J7),COLUMN($K$2))):indirect(address(row($J7),COLUMN($S$2))),TRUE()))} -> 0 | AQ26: {=if(AQ$20=$J7,"-", countif(indirect(address(row($J$2)+ VLOOKUP(AQ$20,$J$3:$J$14,1),COLUMN($K$4))):indirect(address(row($J$2)+ VLOOKUP(AQ$20,$J$3:$J$14,1),COLUMN($S$2)))>indirect(address(row($J7),COLUMN($K$2))):indirect(address(row($J7),COLUMN($S$2))),TRUE()))} -> 0 | AR26: {=if(AR$20=$J7,"-", countif(indirect(address(row($J$2)+ VLOOKUP(AR$20,$J$3:$J$14,1),COLUMN($K$4))):indirect(address(row($J$2)+ VLOOKUP(AR$20,$J$3:$J$14,1),COLUMN($S$2)))>indirect(address(row($J7),COLUMN($K$2))):indirect(address(row($J7),COLUMN($S$2))),TRUE()))} -> 0 | ... AV26: {=if(AV$20=$J7,"-", countif(indirect(address(row($J$2)+ VLOOKUP(AV$20,$J$3:$J$14,1),COLUMN($K$4))):indirect(address(row($J$2)+ VLOOKUP(AV$20,$J$3:$J$14,1),COLUMN($S$2)))>indirect(address(row($J7),COLUMN($K$2))):indirect(address(row($J7),COLUMN($S$2))),TRUE()))} -> 0 | AW26: 5 | AX26: {=INDIRECT("Draft!H"&TEXT(VLOOKUP(TRUE,I3:J14,2,0)+2,"0"))} | AZ26: =IF($AX26="","", VLOOKUP($AX26,'Final Update'!$P$21:$AD1015,Column(H5),False)) | BA26: =IF($AX26="","", VLOOKUP($AX26,'Final Update'!$P$21:$AD1015,Column(I5),False)) | BB26: =IF($AX26="","", VLOOKUP($AX26,'Final Update'!$P$21:$AD1015,Column(J5),False)) | BC26: =IF($AX26="","", VLOOKUP($AX26,'Final Update'!$P$21:$AD1015,Column(K5),False)) | BD26: =IF($AX26="","", VLOOKUP($AX26,'Final Update'!$P$21:$AD1015,Column(L5),False)) | BE26: =IF($AX26="","", VLOOKUP($AX26,'Final Update'!$P$21:$AD1015,Column(M5),False)) | BF26: =IF($AX26="","", VLOOKUP($AX26,'Final Update'!$P$21:$AD1015,Column(N5),False)) | BG26: =IF($AX26="","", VLOOKUP($AX26,'Final Update'!$P$21:$AD1015,Column(O5),False)) | BH26: =IF($AX26="","", VLOOKUP($AX26,'Final Update'!$P$21:$AD1015,Column(P5),False)) | BI26: =IF($AX26="","", VLOOKUP($AX26,'Final Update'!$P$21:$AD1015,Column(C5),False)) | BJ26: {=COUNTIF(FIND(BK26,$BI$22:$BI$33),">0")} -> 0 | BK26: C
A27: =VLOOKUP($F27,UpdateHashtag!$V$3:$Y$32,COLUMN(B$15),0) -> 4 | B27: =VLOOKUP($F27,UpdateHashtag!$V$3:$Y$32,COLUMN(C$13),0) -> 3 | C27: =VLOOKUP($F27,UpdateHashtag!$V$3:$Y$32,COLUMN(D$13),0) -> 4 | D27: =SUM(A27:C27) -> 11 | F27: =IF(VLOOKUP(J27,PasteHashtag!$C$2:$P1015,3,)="BRO","BKN",IF(VLOOKUP(J27,PasteHashtag!$C$2:$P1015,3,)="OKL","OKC",VLOOKUP(J27,PasteHashtag!$C$2:$P1015,3,))) -> GS | G27: 8 | H27: =IFERROR(__xludf.DUMMYFUNCTION("""COMPUTED_VALUE"""),9.0) -> 9 | I27: =IFERROR(__xludf.DUMMYFUNCTION("""COMPUTED_VALUE"""),12.4) -> 12.4 | J27: =IFERROR(__xludf.DUMMYFUNCTION("""COMPUTED_VALUE"""),"Stephen Curry") -> Stephen Curry | K27: =IFERROR(__xludf.DUMMYFUNCTION("""COMPUTED_VALUE"""),72.0) -> 72 | L27: =IFERROR(__xludf.DUMMYFUNCTION("""COMPUTED_VALUE"""),"C") -> C | M27: =IFERROR(__xludf.DUMMYFUNCTION("""COMPUTED_VALUE"""),4.89836431834699) -> 4.8983643 | N27: =IFERROR(__xludf.DUMMYFUNCTION("""COMPUTED_VALUE"""),5.214872183012166) -> 5.2148722 | O27: =IFERROR(__xludf.DUMMYFUNCTION("""COMPUTED_VALUE"""),0.31650786466517644) -> 0.31650786 | P27: =IFERROR(__xludf.DUMMYFUNCTION("""COMPUTED_VALUE"""),27.32397059) -> 27.323971 | Q27: =IFERROR(__xludf.DUMMYFUNCTION("""COMPUTED_VALUE"""),5.063235294) -> 5.0632353 | R27: =IFERROR(__xludf.DUMMYFUNCTION("""COMPUTED_VALUE"""),4.8125) -> 4.8125 | S27: =IFERROR(__xludf.DUMMYFUNCTION("""COMPUTED_VALUE"""),6.1875) -> 6.1875 | T27: =IFERROR(__xludf.DUMMYFUNCTION("""COMPUTED_VALUE"""),0.825) -> 0.825 | U27: =IFERROR(__xludf.DUMMYFUNCTION("""COMPUTED_VALUE"""),0.3408823529) -> 0.34088235 | V27: =IFERROR(__xludf.DUMMYFUNCTION("""COMPUTED_VALUE"""),0.4492422534) -> 0.44924225 | W27: =IFERROR(__xludf.DUMMYFUNCTION("""COMPUTED_VALUE"""),0.9219855811) -> 0.92198558 | X27: =IFERROR(__xludf.DUMMYFUNCTION("""COMPUTED_VALUE"""),3.025) -> 3.025 | Y27: =IFERROR(__xludf.DUMMYFUNCTION("""COMPUTED_VALUE"""),1.7728689909236546) -> 1.772869 | Z27: =IFERROR(__xludf.DUMMYFUNCTION("""COMPUTED_VALUE"""),3.287815216056803) -> 3.2878152 | AA27: =IFERROR(__xludf.DUMMYFUNCTION("""COMPUTED_VALUE"""),-0.4980484745120841) -> -0.49804847 | AB27: =IFERROR(__xludf.DUMMYFUNCTION("""COMPUTED_VALUE"""),1.0237036647035267) -> 1.0237037 | AC27: =IFERROR(__xludf.DUMMYFUNCTION("""COMPUTED_VALUE"""),-0.4995553202713378) -> -0.49955532 | AD27: =IFERROR(__xludf.DUMMYFUNCTION("""COMPUTED_VALUE"""),-0.727343603857086) -> -0.7273436 | AE27: =IFERROR(__xludf.DUMMYFUNCTION("""COMPUTED_VALUE"""),-1.1286194805856642) -> -1.1286195 | AF27: =IFERROR(__xludf.DUMMYFUNCTION("""COMPUTED_VALUE"""),1.9840511905543525) -> 1.9840512 | AG27: =IFERROR(__xludf.DUMMYFUNCTION("""COMPUTED_VALUE"""),0.0) -> 0 | AJ27: 100 | AK27: {=if(AK$20=$J8,"-", countif(indirect(address(row($J$2)+ VLOOKUP(AK$20,$J$3:$J$14,1),COLUMN($K$4))):indirect(address(row($J$2)+ VLOOKUP(AK$20,$J$3:$J$14,1),COLUMN($S$2)))>indirect(address(row($J8),COLUMN($K$2))):indirect(address(row($J8),COLUMN($S$2))),TRUE()))} -> 7 | AL27: {=if(AL$20=$J8,"-", countif(indirect(address(row($J$2)+ VLOOKUP(AL$20,$J$3:$J$14,1),COLUMN($K$4))):indirect(address(row($J$2)+ VLOOKUP(AL$20,$J$3:$J$14,1),COLUMN($S$2)))>indirect(address(row($J8),COLUMN($K$2))):indirect(address(row($J8),COLUMN($S$2))),TRUE()))} -> 0 | AM27: {=if(AM$20=$J8,"-", countif(indirect(address(row($J$2)+ VLOOKUP(AM$20,$J$3:$J$14,1),COLUMN($K$4))):indirect(address(row($J$2)+ VLOOKUP(AM$20,$J$3:$J$14,1),COLUMN($S$2)))>indirect(address(row($J8),COLUMN($K$2))):indirect(address(row($J8),COLUMN($S$2))),TRUE()))} -> 0 | AN27: {=if(AN$20=$J8,"-", countif(indirect(address(row($J$2)+ VLOOKUP(AN$20,$J$3:$J$14,1),COLUMN($K$4))):indirect(address(row($J$2)+ VLOOKUP(AN$20,$J$3:$J$14,1),COLUMN($S$2)))>indirect(address(row($J8),COLUMN($K$2))):indirect(address(row($J8),COLUMN($S$2))),TRUE()))} -> 0 | AO27: {=if(AO$20=$J8,"-", countif(indirect(address(row($J$2)+ VLOOKUP(AO$20,$J$3:$J$14,1),COLUMN($K$4))):indirect(address(row($J$2)+ VLOOKUP(AO$20,$J$3:$J$14,1),COLUMN($S$2)))>indirect(address(row($J8),COLUMN($K$2))):indirect(address(row($J8),COLUMN($S$2))),TRUE()))} -> 0 | AP27: {=if(AP$20=$J8,"-", countif(indirect(address(row($J$2)+ VLOOKUP(AP$20,$J$3:$J$14,1),COLUMN($K$4))):indirect(address(row($J$2)+ VLOOKUP(AP$20,$J$3:$J$14,1),COLUMN($S$2)))>indirect(address(row($J8),COLUMN($K$2))):indirect(address(row($J8),COLUMN($S$2))),TRUE()))} -> - | AQ27: {=if(AQ$20=$J8,"-", countif(indirect(address(row($J$2)+ VLOOKUP(AQ$20,$J$3:$J$14,1),COLUMN($K$4))):indirect(address(row($J$2)+ VLOOKUP(AQ$20,$J$3:$J$14,1),COLUMN($S$2)))>indirect(address(row($J8),COLUMN($K$2))):indirect(address(row($J8),COLUMN($S$2))),TRUE()))} -> 0 | AR27: {=if(AR$20=$J8,"-", countif(indirect(address(row($J$2)+ VLOOKUP(AR$20,$J$3:$J$14,1),COLUMN($K$4))):indirect(address(row($J$2)+ VLOOKUP(AR$20,$J$3:$J$14,1),COLUMN($S$2)))>indirect(address(row($J8),COLUMN($K$2))):indirect(address(row($J8),COLUMN($S$2))),TRUE()))} -> 0 | ... AV27: {=if(AV$20=$J8,"-", countif(indirect(address(row($J$2)+ VLOOKUP(AV$20,$J$3:$J$14,1),COLUMN($K$4))):indirect(address(row($J$2)+ VLOOKUP(AV$20,$J$3:$J$14,1),COLUMN($S$2)))>indirect(address(row($J8),COLUMN($K$2))):indirect(address(row($J8),COLUMN($S$2))),TRUE()))} -> 0 | AW27: 6 | AX27: {=INDIRECT("Draft!I"&TEXT(15-VLOOKUP(TRUE,I3:J14,2,0),"0"))} | AZ27: =IF($AX27="","", VLOOKUP($AX27,'Final Update'!$P$21:$AD1015,Column(H6),False)) | BA27: =IF($AX27="","", VLOOKUP($AX27,'Final Update'!$P$21:$AD1015,Column(I6),False)) | BB27: =IF($AX27="","", VLOOKUP($AX27,'Final Update'!$P$21:$AD1015,Column(J6),False)) | BC27: =IF($AX27="","", VLOOKUP($AX27,'Final Update'!$P$21:$AD1015,Column(K6),False)) | BD27: =IF($AX27="","", VLOOKUP($AX27,'Final Update'!$P$21:$AD1015,Column(L6),False)) | BE27: =IF($AX27="","", VLOOKUP($AX27,'Final Update'!$P$21:$AD1015,Column(M6),False)) | BF27: =IF($AX27="","", VLOOKUP($AX27,'Final Update'!$P$21:$AD1015,Column(N6),False)) | BG27: =IF($AX27="","", VLOOKUP($AX27,'Final Update'!$P$21:$AD1015,Column(O6),False)) | BH27: =IF($AX27="","", VLOOKUP($AX27,'Final Update'!$P$21:$AD1015,Column(P6),False)) | BI27: =IF($AX27="","", VLOOKUP($AX27,'Final Update'!$P$21:$AD1015,Column(C6),False))
A28: =VLOOKUP($F28,UpdateHashtag!$V$3:$Y$32,COLUMN(B$15),0) -> 4 | B28: =VLOOKUP($F28,UpdateHashtag!$V$3:$Y$32,COLUMN(C$13),0) -> 4 | C28: =VLOOKUP($F28,UpdateHashtag!$V$3:$Y$32,COLUMN(D$13),0) -> 4 | D28: =SUM(A28:C28) -> 12 | F28: =IF(VLOOKUP(J28,PasteHashtag!$C$2:$P1015,3,)="BRO","BKN",IF(VLOOKUP(J28,PasteHashtag!$C$2:$P1015,3,)="OKL","OKC",VLOOKUP(J28,PasteHashtag!$C$2:$P1015,3,))) -> LAC | G28: 9 | H28: =IFERROR(__xludf.DUMMYFUNCTION("""COMPUTED_VALUE"""),10.0) -> 10 | I28: =IFERROR(__xludf.DUMMYFUNCTION("""COMPUTED_VALUE"""),16.2) -> 16.2 | J28: =IFERROR(__xludf.DUMMYFUNCTION("""COMPUTED_VALUE"""),"James Harden") -> James Harden | K28: =IFERROR(__xludf.DUMMYFUNCTION("""COMPUTED_VALUE"""),67.0) -> 67 | L28: =IFERROR(__xludf.DUMMYFUNCTION("""COMPUTED_VALUE"""),"PG,SG") -> PG,SG | M28: =IFERROR(__xludf.DUMMYFUNCTION("""COMPUTED_VALUE"""),4.551259773101705) -> 4.5512598 | N28: =IFERROR(__xludf.DUMMYFUNCTION("""COMPUTED_VALUE"""),4.926699862777106) -> 4.9266999 | O28: =IFERROR(__xludf.DUMMYFUNCTION("""COMPUTED_VALUE"""),0.37544008967540066) -> 0.37544009 | P28: =IFERROR(__xludf.DUMMYFUNCTION("""COMPUTED_VALUE"""),22.65044118) -> 22.650441 | Q28: =IFERROR(__xludf.DUMMYFUNCTION("""COMPUTED_VALUE"""),2.797941176) -> 2.7979412 | R28: =IFERROR(__xludf.DUMMYFUNCTION("""COMPUTED_VALUE"""),5.900441176) -> 5.9004412 | S28: =IFERROR(__xludf.DUMMYFUNCTION("""COMPUTED_VALUE"""),9.440735294) -> 9.4407353 | T28: =IFERROR(__xludf.DUMMYFUNCTION("""COMPUTED_VALUE"""),0.9710294118) -> 0.97102941 | U28: =IFERROR(__xludf.DUMMYFUNCTION("""COMPUTED_VALUE"""),0.5552941176) -> 0.55529412 | V28: =IFERROR(__xludf.DUMMYFUNCTION("""COMPUTED_VALUE"""),0.4337920333) -> 0.43379203 | W28: =IFERROR(__xludf.DUMMYFUNCTION("""COMPUTED_VALUE"""),0.8789990497) -> 0.87899905 | X28: =IFERROR(__xludf.DUMMYFUNCTION("""COMPUTED_VALUE"""),3.262647059) -> 3.2626471 | Y28: =IFERROR(__xludf.DUMMYFUNCTION("""COMPUTED_VALUE"""),0.9304389619438688) -> 0.93043896 | Z28: =IFERROR(__xludf.DUMMYFUNCTION("""COMPUTED_VALUE"""),1.0408053310943666) -> 1.0408053 | AA28: =IFERROR(__xludf.DUMMYFUNCTION("""COMPUTED_VALUE"""),-0.0716767160341684) -> -0.071676716 | AB28: =IFERROR(__xludf.DUMMYFUNCTION("""COMPUTED_VALUE"""),2.501122766785887) -> 2.5011228 | AC28: =IFERROR(__xludf.DUMMYFUNCTION("""COMPUTED_VALUE"""),-0.01644426344495128) -> -0.016444263 | AD28: =IFERROR(__xludf.DUMMYFUNCTION("""COMPUTED_VALUE"""),-0.3449085263384095) -> -0.34490853 | AE28: =IFERROR(__xludf.DUMMYFUNCTION("""COMPUTED_VALUE"""),-1.1681525032923803) -> -1.1681525 | AF28: =IFERROR(__xludf.DUMMYFUNCTION("""COMPUTED_VALUE"""),2.0555148120628925) -> 2.0555148 | AG28: =IFERROR(__xludf.DUMMYFUNCTION("""COMPUTED_VALUE"""),0.0) -> 0 | AJ28: 100 | AK28: {=if(AK$20=$J9,"-", countif(indirect(address(row($J$2)+ VLOOKUP(AK$20,$J$3:$J$14,1),COLUMN($K$4))):indirect(address(row($J$2)+ VLOOKUP(AK$20,$J$3:$J$14,1),COLUMN($S$2)))>indirect(address(row($J9),COLUMN($K$2))):indirect(address(row($J9),COLUMN($S$2))),TRUE()))} -> 7 | AL28: {=if(AL$20=$J9,"-", countif(indirect(address(row($J$2)+ VLOOKUP(AL$20,$J$3:$J$14,1),COLUMN($K$4))):indirect(address(row($J$2)+ VLOOKUP(AL$20,$J$3:$J$14,1),COLUMN($S$2)))>indirect(address(row($J9),COLUMN($K$2))):indirect(address(row($J9),COLUMN($S$2))),TRUE()))} -> 0 | AM28: {=if(AM$20=$J9,"-", countif(indirect(address(row($J$2)+ VLOOKUP(AM$20,$J$3:$J$14,1),COLUMN($K$4))):indirect(address(row($J$2)+ VLOOKUP(AM$20,$J$3:$J$14,1),COLUMN($S$2)))>indirect(address(row($J9),COLUMN($K$2))):indirect(address(row($J9),COLUMN($S$2))),TRUE()))} -> 0 | AN28: {=if(AN$20=$J9,"-", countif(indirect(address(row($J$2)+ VLOOKUP(AN$20,$J$3:$J$14,1),COLUMN($K$4))):indirect(address(row($J$2)+ VLOOKUP(AN$20,$J$3:$J$14,1),COLUMN($S$2)))>indirect(address(row($J9),COLUMN($K$2))):indirect(address(row($J9),COLUMN($S$2))),TRUE()))} -> 0 | AO28: {=if(AO$20=$J9,"-", countif(indirect(address(row($J$2)+ VLOOKUP(AO$20,$J$3:$J$14,1),COLUMN($K$4))):indirect(address(row($J$2)+ VLOOKUP(AO$20,$J$3:$J$14,1),COLUMN($S$2)))>indirect(address(row($J9),COLUMN($K$2))):indirect(address(row($J9),COLUMN($S$2))),TRUE()))} -> 0 | AP28: {=if(AP$20=$J9,"-", countif(indirect(address(row($J$2)+ VLOOKUP(AP$20,$J$3:$J$14,1),COLUMN($K$4))):indirect(address(row($J$2)+ VLOOKUP(AP$20,$J$3:$J$14,1),COLUMN($S$2)))>indirect(address(row($J9),COLUMN($K$2))):indirect(address(row($J9),COLUMN($S$2))),TRUE()))} -> 0 | AQ28: {=if(AQ$20=$J9,"-", countif(indirect(address(row($J$2)+ VLOOKUP(AQ$20,$J$3:$J$14,1),COLUMN($K$4))):indirect(address(row($J$2)+ VLOOKUP(AQ$20,$J$3:$J$14,1),COLUMN($S$2)))>indirect(address(row($J9),COLUMN($K$2))):indirect(address(row($J9),COLUMN($S$2))),TRUE()))} -> - | AR28: {=if(AR$20=$J9,"-", countif(indirect(address(row($J$2)+ VLOOKUP(AR$20,$J$3:$J$14,1),COLUMN($K$4))):indirect(address(row($J$2)+ VLOOKUP(AR$20,$J$3:$J$14,1),COLUMN($S$2)))>indirect(address(row($J9),COLUMN($K$2))):indirect(address(row($J9),COLUMN($S$2))),TRUE()))} -> 0 | ... AV28: {=if(AV$20=$J9,"-", countif(indirect(address(row($J$2)+ VLOOKUP(AV$20,$J$3:$J$14,1),COLUMN($K$4))):indirect(address(row($J$2)+ VLOOKUP(AV$20,$J$3:$J$14,1),COLUMN($S$2)))>indirect(address(row($J9),COLUMN($K$2))):indirect(address(row($J9),COLUMN($S$2))),TRUE()))} -> 0 | AW28: 7 | AX28: {=INDIRECT("Draft!J"&TEXT(VLOOKUP(TRUE,I3:J14,2,0)+2,"0"))} | AZ28: =IF($AX28="","", VLOOKUP($AX28,'Final Update'!$P$21:$AD1015,Column(H7),False)) | BA28: =IF($AX28="","", VLOOKUP($AX28,'Final Update'!$P$21:$AD1015,Column(I7),False)) | BB28: =IF($AX28="","", VLOOKUP($AX28,'Final Update'!$P$21:$AD1015,Column(J7),False)) | BC28: =IF($AX28="","", VLOOKUP($AX28,'Final Update'!$P$21:$AD1015,Column(K7),False)) | BD28: =IF($AX28="","", VLOOKUP($AX28,'Final Update'!$P$21:$AD1015,Column(L7),False)) | BE28: =IF($AX28="","", VLOOKUP($AX28,'Final Update'!$P$21:$AD1015,Column(M7),False)) | BF28: =IF($AX28="","", VLOOKUP($AX28,'Final Update'!$P$21:$AD1015,Column(N7),False)) | BG28: =IF($AX28="","", VLOOKUP($AX28,'Final Update'!$P$21:$AD1015,Column(O7),False)) | BH28: =IF($AX28="","", VLOOKUP($AX28,'Final Update'!$P$21:$AD1015,Column(P7),False)) | BI28: =IF($AX28="","", VLOOKUP($AX28,'Final Update'!$P$21:$AD1015,Column(C7),False))
A29: =VLOOKUP($F29,UpdateHashtag!$V$3:$Y$32,COLUMN(B$15),0) -> 4 | B29: =VLOOKUP($F29,UpdateHashtag!$V$3:$Y$32,COLUMN(C$13),0) -> 4 | C29: =VLOOKUP($F29,UpdateHashtag!$V$3:$Y$32,COLUMN(D$13),0) -> 4 | D29: =SUM(A29:C29) -> 12 | F29: =IF(VLOOKUP(J29,PasteHashtag!$C$2:$P1015,3,)="BRO","BKN",IF(VLOOKUP(J29,PasteHashtag!$C$2:$P1015,3,)="OKL","OKC",VLOOKUP(J29,PasteHashtag!$C$2:$P1015,3,))) -> PHI | G29: 10 | H29: =IFERROR(__xludf.DUMMYFUNCTION("""COMPUTED_VALUE"""),13.0) -> 13 | I29: =IFERROR(__xludf.DUMMYFUNCTION("""COMPUTED_VALUE"""),32.1) -> 32.1 | J29: =IFERROR(__xludf.DUMMYFUNCTION("""COMPUTED_VALUE"""),"Paul George") -> Paul George | K29: =IFERROR(__xludf.DUMMYFUNCTION("""COMPUTED_VALUE"""),69.0) -> 69 | L29: =IFERROR(__xludf.DUMMYFUNCTION("""COMPUTED_VALUE"""),"C") -> C | M29: =IFERROR(__xludf.DUMMYFUNCTION("""COMPUTED_VALUE"""),4.378452010478854) -> 4.378452 | N29: =IFERROR(__xludf.DUMMYFUNCTION("""COMPUTED_VALUE"""),4.618205404732) -> 4.6182054 | O29: =IFERROR(__xludf.DUMMYFUNCTION("""COMPUTED_VALUE"""),0.239753394253146) -> 0.23975339 | P29: =IFERROR(__xludf.DUMMYFUNCTION("""COMPUTED_VALUE"""),20.82370968) -> 20.82371 | Q29: =IFERROR(__xludf.DUMMYFUNCTION("""COMPUTED_VALUE"""),2.860322581) -> 2.8603226 | R29: =IFERROR(__xludf.DUMMYFUNCTION("""COMPUTED_VALUE"""),6.431290323) -> 6.4312903 | S29: =IFERROR(__xludf.DUMMYFUNCTION("""COMPUTED_VALUE"""),4.787741935) -> 4.7877419 | T29: =IFERROR(__xludf.DUMMYFUNCTION("""COMPUTED_VALUE"""),1.589032258) -> 1.5890323 | U29: =IFERROR(__xludf.DUMMYFUNCTION("""COMPUTED_VALUE"""),0.5001612903) -> 0.50016129 | V29: =IFERROR(__xludf.DUMMYFUNCTION("""COMPUTED_VALUE"""),0.4722811616) -> 0.47228116 | W29: =IFERROR(__xludf.DUMMYFUNCTION("""COMPUTED_VALUE"""),0.8910028604) -> 0.89100286 | X29: =IFERROR(__xludf.DUMMYFUNCTION("""COMPUTED_VALUE"""),2.715483871) -> 2.7154839 | Y29: =IFERROR(__xludf.DUMMYFUNCTION("""COMPUTED_VALUE"""),0.6011603086009578) -> 0.60116031 | Z29: =IFERROR(__xludf.DUMMYFUNCTION("""COMPUTED_VALUE"""),1.1026832270192457) -> 1.1026832 | AA29: =IFERROR(__xludf.DUMMYFUNCTION("""COMPUTED_VALUE"""),0.13636677867486113) -> 0.13636678 | AB29: =IFERROR(__xludf.DUMMYFUNCTION("""COMPUTED_VALUE"""),0.3880197634071937) -> 0.38801976 | AC29: =IFERROR(__xludf.DUMMYFUNCTION("""COMPUTED_VALUE"""),2.028102821071873) -> 2.0281028 | AD29: =IFERROR(__xludf.DUMMYFUNCTION("""COMPUTED_VALUE"""),-0.4432460737756995) -> -0.44324607 | AE29: =IFERROR(__xludf.DUMMYFUNCTION("""COMPUTED_VALUE"""),-0.45030925961514695) -> -0.45030926 | AF29: =IFERROR(__xludf.DUMMYFUNCTION("""COMPUTED_VALUE"""),1.2554278393487148) -> 1.2554278 | AG29: =IFERROR(__xludf.DUMMYFUNCTION("""COMPUTED_VALUE"""),0.0) -> 0 | AJ29: 100 | AK29: {=if(AK$20=$J10,"-", countif(indirect(address(row($J$2)+ VLOOKUP(AK$20,$J$3:$J$14,1),COLUMN($K$4))):indirect(address(row($J$2)+ VLOOKUP(AK$20,$J$3:$J$14,1),COLUMN($S$2)))>indirect(address(row($J10),COLUMN($K$2))):indirect(address(row($J10),COLUMN($S$2))),TRUE()))} -> 7 | AL29: {=if(AL$20=$J10,"-", countif(indirect(address(row($J$2)+ VLOOKUP(AL$20,$J$3:$J$14,1),COLUMN($K$4))):indirect(address(row($J$2)+ VLOOKUP(AL$20,$J$3:$J$14,1),COLUMN($S$2)))>indirect(address(row($J10),COLUMN($K$2))):indirect(address(row($J10),COLUMN($S$2))),TRUE()))} -> 0 | AM29: {=if(AM$20=$J10,"-", countif(indirect(address(row($J$2)+ VLOOKUP(AM$20,$J$3:$J$14,1),COLUMN($K$4))):indirect(address(row($J$2)+ VLOOKUP(AM$20,$J$3:$J$14,1),COLUMN($S$2)))>indirect(address(row($J10),COLUMN($K$2))):indirect(address(row($J10),COLUMN($S$2))),TRUE()))} -> 0 | AN29: {=if(AN$20=$J10,"-", countif(indirect(address(row($J$2)+ VLOOKUP(AN$20,$J$3:$J$14,1),COLUMN($K$4))):indirect(address(row($J$2)+ VLOOKUP(AN$20,$J$3:$J$14,1),COLUMN($S$2)))>indirect(address(row($J10),COLUMN($K$2))):indirect(address(row($J10),COLUMN($S$2))),TRUE()))} -> 0 | AO29: {=if(AO$20=$J10,"-", countif(indirect(address(row($J$2)+ VLOOKUP(AO$20,$J$3:$J$14,1),COLUMN($K$4))):indirect(address(row($J$2)+ VLOOKUP(AO$20,$J$3:$J$14,1),COLUMN($S$2)))>indirect(address(row($J10),COLUMN($K$2))):indirect(address(row($J10),COLUMN($S$2))),TRUE()))} -> 0 | AP29: {=if(AP$20=$J10,"-", countif(indirect(address(row($J$2)+ VLOOKUP(AP$20,$J$3:$J$14,1),COLUMN($K$4))):indirect(address(row($J$2)+ VLOOKUP(AP$20,$J$3:$J$14,1),COLUMN($S$2)))>indirect(address(row($J10),COLUMN($K$2))):indirect(address(row($J10),COLUMN($S$2))),TRUE()))} -> 0 | AQ29: {=if(AQ$20=$J10,"-", countif(indirect(address(row($J$2)+ VLOOKUP(AQ$20,$J$3:$J$14,1),COLUMN($K$4))):indirect(address(row($J$2)+ VLOOKUP(AQ$20,$J$3:$J$14,1),COLUMN($S$2)))>indirect(address(row($J10),COLUMN($K$2))):indirect(address(row($J10),COLUMN($S$2))),TRUE()))} -> 0 | AR29: {=if(AR$20=$J10,"-", countif(indirect(address(row($J$2)+ VLOOKUP(AR$20,$J$3:$J$14,1),COLUMN($K$4))):indirect(address(row($J$2)+ VLOOKUP(AR$20,$J$3:$J$14,1),COLUMN($S$2)))>indirect(address(row($J10),COLUMN($K$2))):indirect(address(row($J10),COLUMN($S$2))),TRUE()))} -> - | ... AV29: {=if(AV$20=$J10,"-", countif(indirect(address(row($J$2)+ VLOOKUP(AV$20,$J$3:$J$14,1),COLUMN($K$4))):indirect(address(row($J$2)+ VLOOKUP(AV$20,$J$3:$J$14,1),COLUMN($S$2)))>indirect(address(row($J10),COLUMN($K$2))):indirect(address(row($J10),COLUMN($S$2))),TRUE()))} -> 0 | AW29: 8 | AX29: {=INDIRECT("Draft!K"&TEXT(15-VLOOKUP(TRUE,I3:J14,2,0),"0"))} | AZ29: =IF($AX29="","", VLOOKUP($AX29,'Final Update'!$P$21:$AD1015,Column(H8),False)) | BA29: =IF($AX29="","", VLOOKUP($AX29,'Final Update'!$P$21:$AD1015,Column(I8),False)) | BB29: =IF($AX29="","", VLOOKUP($AX29,'Final Update'!$P$21:$AD1015,Column(J8),False)) | BC29: =IF($AX29="","", VLOOKUP($AX29,'Final Update'!$P$21:$AD1015,Column(K8),False)) | BD29: =IF($AX29="","", VLOOKUP($AX29,'Final Update'!$P$21:$AD1015,Column(L8),False)) | BE29: =IF($AX29="","", VLOOKUP($AX29,'Final Update'!$P$21:$AD1015,Column(M8),False)) | BF29: =IF($AX29="","", VLOOKUP($AX29,'Final Update'!$P$21:$AD1015,Column(N8),False)) | BG29: =IF($AX29="","", VLOOKUP($AX29,'Final Update'!$P$21:$AD1015,Column(O8),False)) | BH29: =IF($AX29="","", VLOOKUP($AX29,'Final Update'!$P$21:$AD1015,Column(P8),False)) | BI29: =IF($AX29="","", VLOOKUP($AX29,'Final Update'!$P$21:$AD1015,Column(AH16),False))
A30: =VLOOKUP($F30,UpdateHashtag!$V$3:$Y$32,COLUMN(B$15),0) -> 4 | B30: =VLOOKUP($F30,UpdateHashtag!$V$3:$Y$32,COLUMN(C$13),0) -> 3 | C30: =VLOOKUP($F30,UpdateHashtag!$V$3:$Y$32,COLUMN(D$13),0) -> 4 | D30: =SUM(A30:C30) -> 11 | F30: =IF(VLOOKUP(J30,PasteHashtag!$C$2:$P1015,3,)="BRO","BKN",IF(VLOOKUP(J30,PasteHashtag!$C$2:$P1015,3,)="OKL","OKC",VLOOKUP(J30,PasteHashtag!$C$2:$P1015,3,))) -> CLE | G30: 11 | H30: =IFERROR(__xludf.DUMMYFUNCTION("""COMPUTED_VALUE"""),14.0) -> 14 | I30: =IFERROR(__xludf.DUMMYFUNCTION("""COMPUTED_VALUE"""),17.0) -> 17 | J30: =IFERROR(__xludf.DUMMYFUNCTION("""COMPUTED_VALUE"""),"Donovan Mitchell") -> Donovan Mitchell | K30: =IFERROR(__xludf.DUMMYFUNCTION("""COMPUTED_VALUE"""),70.0) -> 70 | L30: =IFERROR(__xludf.DUMMYFUNCTION("""COMPUTED_VALUE"""),"PG,SG") -> PG,SG | M30: =IFERROR(__xludf.DUMMYFUNCTION("""COMPUTED_VALUE"""),4.362182127322641) -> 4.3621821 | N30: =IFERROR(__xludf.DUMMYFUNCTION("""COMPUTED_VALUE"""),4.611588943831613) -> 4.6115889 | O30: =IFERROR(__xludf.DUMMYFUNCTION("""COMPUTED_VALUE"""),0.249406816508972) -> 0.24940682 | P30: =IFERROR(__xludf.DUMMYFUNCTION("""COMPUTED_VALUE"""),25.3975) -> 25.3975 | Q30: =IFERROR(__xludf.DUMMYFUNCTION("""COMPUTED_VALUE"""),3.406617647) -> 3.4066176 | R30: =IFERROR(__xludf.DUMMYFUNCTION("""COMPUTED_VALUE"""),4.2075) -> 4.2075 | S30: =IFERROR(__xludf.DUMMYFUNCTION("""COMPUTED_VALUE"""),5.469705882) -> 5.4697059 | T30: =IFERROR(__xludf.DUMMYFUNCTION("""COMPUTED_VALUE"""),1.472647059) -> 1.4726471 | U30: =IFERROR(__xludf.DUMMYFUNCTION("""COMPUTED_VALUE"""),0.4908823529) -> 0.49088235 | V30: =IFERROR(__xludf.DUMMYFUNCTION("""COMPUTED_VALUE"""),0.4648033924) -> 0.46480339 | W30: =IFERROR(__xludf.DUMMYFUNCTION("""COMPUTED_VALUE"""),0.8589983098) -> 0.85899831 | X30: =IFERROR(__xludf.DUMMYFUNCTION("""COMPUTED_VALUE"""),2.754411765) -> 2.7544118 | Y30: =IFERROR(__xludf.DUMMYFUNCTION("""COMPUTED_VALUE"""),1.4256118042052333) -> 1.4256118 | Z30: =IFERROR(__xludf.DUMMYFUNCTION("""COMPUTED_VALUE"""),1.6445688937210945) -> 1.6445689 | AA30: =IFERROR(__xludf.DUMMYFUNCTION("""COMPUTED_VALUE"""),-0.7351522072961985) -> -0.73515221 | AB30: =IFERROR(__xludf.DUMMYFUNCTION("""COMPUTED_VALUE"""),0.6977257856206867) -> 0.69772579 | AC30: =IFERROR(__xludf.DUMMYFUNCTION("""COMPUTED_VALUE"""),1.6430641100699614) -> 1.6430641 | AD30: =IFERROR(__xludf.DUMMYFUNCTION("""COMPUTED_VALUE"""),-0.45979643027700934) -> -0.45979643 | AE30: =IFERROR(__xludf.DUMMYFUNCTION("""COMPUTED_VALUE"""),-0.7197733541183869) -> -0.71977335 | AF30: =IFERROR(__xludf.DUMMYFUNCTION("""COMPUTED_VALUE"""),1.1153403419062318) -> 1.1153403 | AG30: =IFERROR(__xludf.DUMMYFUNCTION("""COMPUTED_VALUE"""),0.0) -> 0 | AJ30: 100 | AK30: {=if(AK$20=$J11,"-", countif(indirect(address(row($J$2)+ VLOOKUP(AK$20,$J$3:$J$14,1),COLUMN($K$4))):indirect(address(row($J$2)+ VLOOKUP(AK$20,$J$3:$J$14,1),COLUMN($S$2)))>indirect(address(row($J11),COLUMN($K$2))):indirect(address(row($J11),COLUMN($S$2))),TRUE()))} -> 7 | AL30: {=if(AL$20=$J11,"-", countif(indirect(address(row($J$2)+ VLOOKUP(AL$20,$J$3:$J$14,1),COLUMN($K$4))):indirect(address(row($J$2)+ VLOOKUP(AL$20,$J$3:$J$14,1),COLUMN($S$2)))>indirect(address(row($J11),COLUMN($K$2))):indirect(address(row($J11),COLUMN($S$2))),TRUE()))} -> 0 | AM30: {=if(AM$20=$J11,"-", countif(indirect(address(row($J$2)+ VLOOKUP(AM$20,$J$3:$J$14,1),COLUMN($K$4))):indirect(address(row($J$2)+ VLOOKUP(AM$20,$J$3:$J$14,1),COLUMN($S$2)))>indirect(address(row($J11),COLUMN($K$2))):indirect(address(row($J11),COLUMN($S$2))),TRUE()))} -> 0 | AN30: {=if(AN$20=$J11,"-", countif(indirect(address(row($J$2)+ VLOOKUP(AN$20,$J$3:$J$14,1),COLUMN($K$4))):indirect(address(row($J$2)+ VLOOKUP(AN$20,$J$3:$J$14,1),COLUMN($S$2)))>indirect(address(row($J11),COLUMN($K$2))):indirect(address(row($J11),COLUMN($S$2))),TRUE()))} -> 0 | AO30: {=if(AO$20=$J11,"-", countif(indirect(address(row($J$2)+ VLOOKUP(AO$20,$J$3:$J$14,1),COLUMN($K$4))):indirect(address(row($J$2)+ VLOOKUP(AO$20,$J$3:$J$14,1),COLUMN($S$2)))>indirect(address(row($J11),COLUMN($K$2))):indirect(address(row($J11),COLUMN($S$2))),TRUE()))} -> 0 | AP30: {=if(AP$20=$J11,"-", countif(indirect(address(row($J$2)+ VLOOKUP(AP$20,$J$3:$J$14,1),COLUMN($K$4))):indirect(address(row($J$2)+ VLOOKUP(AP$20,$J$3:$J$14,1),COLUMN($S$2)))>indirect(address(row($J11),COLUMN($K$2))):indirect(address(row($J11),COLUMN($S$2))),TRUE()))} -> 0 | AQ30: {=if(AQ$20=$J11,"-", countif(indirect(address(row($J$2)+ VLOOKUP(AQ$20,$J$3:$J$14,1),COLUMN($K$4))):indirect(address(row($J$2)+ VLOOKUP(AQ$20,$J$3:$J$14,1),COLUMN($S$2)))>indirect(address(row($J11),COLUMN($K$2))):indirect(address(row($J11),COLUMN($S$2))),TRUE()))} -> 0 | AR30: {=if(AR$20=$J11,"-", countif(indirect(address(row($J$2)+ VLOOKUP(AR$20,$J$3:$J$14,1),COLUMN($K$4))):indirect(address(row($J$2)+ VLOOKUP(AR$20,$J$3:$J$14,1),COLUMN($S$2)))>indirect(address(row($J11),COLUMN($K$2))):indirect(address(row($J11),COLUMN($S$2))),TRUE()))} -> 0 | ... AV30: {=if(AV$20=$J11,"-", countif(indirect(address(row($J$2)+ VLOOKUP(AV$20,$J$3:$J$14,1),COLUMN($K$4))):indirect(address(row($J$2)+ VLOOKUP(AV$20,$J$3:$J$14,1),COLUMN($S$2)))>indirect(address(row($J11),COLUMN($K$2))):indirect(address(row($J11),COLUMN($S$2))),TRUE()))} -> 0 | AW30: 9 | AX30: {=INDIRECT("Draft!L"&TEXT(VLOOKUP(TRUE,I3:J14,2,0)+2,"0"))} | AZ30: =IF($AX30="","", VLOOKUP($AX30,'Final Update'!$P$21:$AD1015,Column(H9),False)) | BA30: =IF($AX30="","", VLOOKUP($AX30,'Final Update'!$P$21:$AD1015,Column(I9),False)) | BB30: =IF($AX30="","", VLOOKUP($AX30,'Final Update'!$P$21:$AD1015,Column(J9),False)) | BC30: =IF($AX30="","", VLOOKUP($AX30,'Final Update'!$P$21:$AD1015,Column(K9),False)) | BD30: =IF($AX30="","", VLOOKUP($AX30,'Final Update'!$P$21:$AD1015,Column(L9),False)) | BE30: =IF($AX30="","", VLOOKUP($AX30,'Final Update'!$P$21:$AD1015,Column(M9),False)) | BF30: =IF($AX30="","", VLOOKUP($AX30,'Final Update'!$P$21:$AD1015,Column(N9),False)) | BG30: =IF($AX30="","", VLOOKUP($AX30,'Final Update'!$P$21:$AD1015,Column(O9),False)) | BH30: =IF($AX30="","", VLOOKUP($AX30,'Final Update'!$P$21:$AD1015,Column(P9),False)) | BI30: =IF($AX30="","", VLOOKUP($AX30,'Final Update'!$P$21:$AD1015,Column(AH17),False))
A31: =VLOOKUP($F31,UpdateHashtag!$V$3:$Y$32,COLUMN(B$15),0) -> 4 | B31: =VLOOKUP($F31,UpdateHashtag!$V$3:$Y$32,COLUMN(C$13),0) -> 4 | C31: =VLOOKUP($F31,UpdateHashtag!$V$3:$Y$32,COLUMN(D$13),0) -> 2 | D31: =SUM(A31:C31) -> 10 | F31: =IF(VLOOKUP(J31,PasteHashtag!$C$2:$P1015,3,)="BRO","BKN",IF(VLOOKUP(J31,PasteHashtag!$C$2:$P1015,3,)="OKL","OKC",VLOOKUP(J31,PasteHashtag!$C$2:$P1015,3,))) -> DAL | G31: 12 | H31: =IFERROR(__xludf.DUMMYFUNCTION("""COMPUTED_VALUE"""),12.0) -> 12 | I31: =IFERROR(__xludf.DUMMYFUNCTION("""COMPUTED_VALUE"""),26.6) -> 26.6 | J31: =IFERROR(__xludf.DUMMYFUNCTION("""COMPUTED_VALUE"""),"Kyrie Irving") -> Kyrie Irving | K31: =IFERROR(__xludf.DUMMYFUNCTION("""COMPUTED_VALUE"""),78.0) -> 78 | L31: =IFERROR(__xludf.DUMMYFUNCTION("""COMPUTED_VALUE"""),"SG,SF,PF") -> SG,SF,PF | M31: =IFERROR(__xludf.DUMMYFUNCTION("""COMPUTED_VALUE"""),4.39070431745973) -> 4.3907043 | N31: =IFERROR(__xludf.DUMMYFUNCTION("""COMPUTED_VALUE"""),4.464262626069749) -> 4.4642626 | O31: =IFERROR(__xludf.DUMMYFUNCTION("""COMPUTED_VALUE"""),0.07355830861001866) -> 0.073558309 | P31: =IFERROR(__xludf.DUMMYFUNCTION("""COMPUTED_VALUE"""),24.8325) -> 24.8325 | Q31: =IFERROR(__xludf.DUMMYFUNCTION("""COMPUTED_VALUE"""),2.898382353) -> 2.8983824 | R31: =IFERROR(__xludf.DUMMYFUNCTION("""COMPUTED_VALUE"""),4.999558824) -> 4.9995588 | S31: =IFERROR(__xludf.DUMMYFUNCTION("""COMPUTED_VALUE"""),4.999558824) -> 4.9995588 | T31: =IFERROR(__xludf.DUMMYFUNCTION("""COMPUTED_VALUE"""),1.212205882) -> 1.2122059 | U31: =IFERROR(__xludf.DUMMYFUNCTION("""COMPUTED_VALUE"""),0.5301470588) -> 0.53014706 | V31: =IFERROR(__xludf.DUMMYFUNCTION("""COMPUTED_VALUE"""),0.5067040208) -> 0.50670402 | W31: =IFERROR(__xludf.DUMMYFUNCTION("""COMPUTED_VALUE"""),0.9090032436) -> 0.90900324 | X31: =IFERROR(__xludf.DUMMYFUNCTION("""COMPUTED_VALUE"""),2.045294118) -> 2.0452941 | Y31: =IFERROR(__xludf.DUMMYFUNCTION("""COMPUTED_VALUE"""),1.3237673683159166) -> 1.3237674 | Z31: =IFERROR(__xludf.DUMMYFUNCTION("""COMPUTED_VALUE"""),1.140435801055381) -> 1.1404358 | AA31: =IFERROR(__xludf.DUMMYFUNCTION("""COMPUTED_VALUE"""),-0.42473881265984165) -> -0.42473881 | AB31: =IFERROR(__xludf.DUMMYFUNCTION("""COMPUTED_VALUE"""),0.48421394847872073) -> 0.48421395 | AC31: =IFERROR(__xludf.DUMMYFUNCTION("""COMPUTED_VALUE"""),0.7814430796853277) -> 0.78144308 | AD31: =IFERROR(__xludf.DUMMYFUNCTION("""COMPUTED_VALUE"""),-0.3897620230436895) -> -0.38976202 | AE31: =IFERROR(__xludf.DUMMYFUNCTION("""COMPUTED_VALUE"""),0.20498816631263686) -> 0.20498817 | AF31: =IFERROR(__xludf.DUMMYFUNCTION("""COMPUTED_VALUE"""),1.343915097925297) -> 1.3439151 | AG31: =IFERROR(__xludf.DUMMYFUNCTION("""COMPUTED_VALUE"""),0.0) -> 0 | AJ31: 100 | AK31: {=if(AK$20=$J12,"-", countif(indirect(address(row($J$2)+ VLOOKUP(AK$20,$J$3:$J$14,1),COLUMN($K$4))):indirect(address(row($J$2)+ VLOOKUP(AK$20,$J$3:$J$14,1),COLUMN($S$2)))>indirect(address(row($J12),COLUMN($K$2))):indirect(address(row($J12),COLUMN($S$2))),TRUE()))} -> 7 | AL31: {=if(AL$20=$J12,"-", countif(indirect(address(row($J$2)+ VLOOKUP(AL$20,$J$3:$J$14,1),COLUMN($K$4))):indirect(address(row($J$2)+ VLOOKUP(AL$20,$J$3:$J$14,1),COLUMN($S$2)))>indirect(address(row($J12),COLUMN($K$2))):indirect(address(row($J12),COLUMN($S$2))),TRUE()))} -> 0 | AM31: {=if(AM$20=$J12,"-", countif(indirect(address(row($J$2)+ VLOOKUP(AM$20,$J$3:$J$14,1),COLUMN($K$4))):indirect(address(row($J$2)+ VLOOKUP(AM$20,$J$3:$J$14,1),COLUMN($S$2)))>indirect(address(row($J12),COLUMN($K$2))):indirect(address(row($J12),COLUMN($S$2))),TRUE()))} -> 0 | AN31: {=if(AN$20=$J12,"-", countif(indirect(address(row($J$2)+ VLOOKUP(AN$20,$J$3:$J$14,1),COLUMN($K$4))):indirect(address(row($J$2)+ VLOOKUP(AN$20,$J$3:$J$14,1),COLUMN($S$2)))>indirect(address(row($J12),COLUMN($K$2))):indirect(address(row($J12),COLUMN($S$2))),TRUE()))} -> 0 | AO31: {=if(AO$20=$J12,"-", countif(indirect(address(row($J$2)+ VLOOKUP(AO$20,$J$3:$J$14,1),COLUMN($K$4))):indirect(address(row($J$2)+ VLOOKUP(AO$20,$J$3:$J$14,1),COLUMN($S$2)))>indirect(address(row($J12),COLUMN($K$2))):indirect(address(row($J12),COLUMN($S$2))),TRUE()))} -> 0 | AP31: {=if(AP$20=$J12,"-", countif(indirect(address(row($J$2)+ VLOOKUP(AP$20,$J$3:$J$14,1),COLUMN($K$4))):indirect(address(row($J$2)+ VLOOKUP(AP$20,$J$3:$J$14,1),COLUMN($S$2)))>indirect(address(row($J12),COLUMN($K$2))):indirect(address(row($J12),COLUMN($S$2))),TRUE()))} -> 0 | AQ31: {=if(AQ$20=$J12,"-", countif(indirect(address(row($J$2)+ VLOOKUP(AQ$20,$J$3:$J$14,1),COLUMN($K$4))):indirect(address(row($J$2)+ VLOOKUP(AQ$20,$J$3:$J$14,1),COLUMN($S$2)))>indirect(address(row($J12),COLUMN($K$2))):indirect(address(row($J12),COLUMN($S$2))),TRUE()))} -> 0 | AR31: {=if(AR$20=$J12,"-", countif(indirect(address(row($J$2)+ VLOOKUP(AR$20,$J$3:$J$14,1),COLUMN($K$4))):indirect(address(row($J$2)+ VLOOKUP(AR$20,$J$3:$J$14,1),COLUMN($S$2)))>indirect(address(row($J12),COLUMN($K$2))):indirect(address(row($J12),COLUMN($S$2))),TRUE()))} -> 0 | ... AV31: {=if(AV$20=$J12,"-", countif(indirect(address(row($J$2)+ VLOOKUP(AV$20,$J$3:$J$14,1),COLUMN($K$4))):indirect(address(row($J$2)+ VLOOKUP(AV$20,$J$3:$J$14,1),COLUMN($S$2)))>indirect(address(row($J12),COLUMN($K$2))):indirect(address(row($J12),COLUMN($S$2))),TRUE()))} -> 0 | AW31: 10 | AX31: {=INDIRECT("Draft!M"&TEXT(15-VLOOKUP(TRUE,I3:J14,2,0),"0"))} | AZ31: =IF($AX31="","", VLOOKUP($AX31,'Final Update'!$P$21:$AD1015,Column(H10),False)) | BA31: =IF($AX31="","", VLOOKUP($AX31,'Final Update'!$P$21:$AD1015,Column(I10),False)) | BB31: =IF($AX31="","", VLOOKUP($AX31,'Final Update'!$P$21:$AD1015,Column(J10),False)) | BC31: =IF($AX31="","", VLOOKUP($AX31,'Final Update'!$P$21:$AD1015,Column(K10),False)) | BD31: =IF($AX31="","", VLOOKUP($AX31,'Final Update'!$P$21:$AD1015,Column(L10),False)) | BE31: =IF($AX31="","", VLOOKUP($AX31,'Final Update'!$P$21:$AD1015,Column(M10),False)) | BF31: =IF($AX31="","", VLOOKUP($AX31,'Final Update'!$P$21:$AD1015,Column(N10),False)) | BG31: =IF($AX31="","", VLOOKUP($AX31,'Final Update'!$P$21:$AD1015,Column(O10),False)) | BH31: =IF($AX31="","", VLOOKUP($AX31,'Final Update'!$P$21:$AD1015,Column(P10),False)) | BI31: =IF($AX31="","", VLOOKUP($AX31,'Final Update'!$P$21:$AD1015,Column(C10),False))
A32: =VLOOKUP($F32,UpdateHashtag!$V$3:$Y$32,COLUMN(B$15),0) -> 3 | B32: =VLOOKUP($F32,UpdateHashtag!$V$3:$Y$32,COLUMN(C$13),0) -> 4 | C32: =VLOOKUP($F32,UpdateHashtag!$V$3:$Y$32,COLUMN(D$13),0) -> 3 | D32: =SUM(A32:C32) -> 10 | F32: =IF(VLOOKUP(J32,PasteHashtag!$C$2:$P1015,3,)="BRO","BKN",IF(VLOOKUP(J32,PasteHashtag!$C$2:$P1015,3,)="OKL","OKC",VLOOKUP(J32,PasteHashtag!$C$2:$P1015,3,))) -> LAL | G32: 13 | H32: =IFERROR(__xludf.DUMMYFUNCTION("""COMPUTED_VALUE"""),11.0) -> 11 | I32: =IFERROR(__xludf.DUMMYFUNCTION("""COMPUTED_VALUE"""),24.2) -> 24.2 | J32: =IFERROR(__xludf.DUMMYFUNCTION("""COMPUTED_VALUE"""),"LeBron James") -> LeBron James | K32: =IFERROR(__xludf.DUMMYFUNCTION("""COMPUTED_VALUE"""),62.0) -> 62 | L32: =IFERROR(__xludf.DUMMYFUNCTION("""COMPUTED_VALUE"""),"SF,PF") -> SF,PF | M32: =IFERROR(__xludf.DUMMYFUNCTION("""COMPUTED_VALUE"""),3.923392389951665) -> 3.9233924 | N32: =IFERROR(__xludf.DUMMYFUNCTION("""COMPUTED_VALUE"""),4.393498885867384) -> 4.3934989 | O32: =IFERROR(__xludf.DUMMYFUNCTION("""COMPUTED_VALUE"""),0.47010649591571907) -> 0.4701065 | P32: =IFERROR(__xludf.DUMMYFUNCTION("""COMPUTED_VALUE"""),24.64166667) -> 24.641667 | Q32: =IFERROR(__xludf.DUMMYFUNCTION("""COMPUTED_VALUE"""),1.924848485) -> 1.9248485 | R32: =IFERROR(__xludf.DUMMYFUNCTION("""COMPUTED_VALUE"""),7.14) -> 7.14 | S32: =IFERROR(__xludf.DUMMYFUNCTION("""COMPUTED_VALUE"""),8.776212121) -> 8.7762121 | T32: =IFERROR(__xludf.DUMMYFUNCTION("""COMPUTED_VALUE"""),1.109242424) -> 1.1092424 | U32: =IFERROR(__xludf.DUMMYFUNCTION("""COMPUTED_VALUE"""),0.5227272727) -> 0.52272727 | V32: =IFERROR(__xludf.DUMMYFUNCTION("""COMPUTED_VALUE"""),0.5371077316) -> 0.53710773 | W32: =IFERROR(__xludf.DUMMYFUNCTION("""COMPUTED_VALUE"""),0.7690098505) -> 0.76900985 | X32: =IFERROR(__xludf.DUMMYFUNCTION("""COMPUTED_VALUE"""),3.644393939) -> 3.6443939 | Y32: =IFERROR(__xludf.DUMMYFUNCTION("""COMPUTED_VALUE"""),1.2893685845234746) -> 1.2893686 | Z32: =IFERROR(__xludf.DUMMYFUNCTION("""COMPUTED_VALUE"""),0.17475977366470033) -> 0.17475977 | AA32: =IFERROR(__xludf.DUMMYFUNCTION("""COMPUTED_VALUE"""),0.414115059463165) -> 0.41411506 | AB32: =IFERROR(__xludf.DUMMYFUNCTION("""COMPUTED_VALUE"""),2.19933726993686) -> 2.1993373 | AC32: =IFERROR(__xludf.DUMMYFUNCTION("""COMPUTED_VALUE"""),0.44080769400695324) -> 0.44080769 | AD32: =IFERROR(__xludf.DUMMYFUNCTION("""COMPUTED_VALUE"""),-0.40299630837451456) -> -0.40299631 | AE32: =IFERROR(__xludf.DUMMYFUNCTION("""COMPUTED_VALUE"""),0.7931270720514652) -> 0.79312707 | AF32: =IFERROR(__xludf.DUMMYFUNCTION("""COMPUTED_VALUE"""),-0.5150202594047202) -> -0.51502026 | AG32: =IFERROR(__xludf.DUMMYFUNCTION("""COMPUTED_VALUE"""),0.0) -> 0 | AJ32: 100 | AK32: {=if(AK$20=$J13,"-", countif(indirect(address(row($J$2)+ VLOOKUP(AK$20,$J$3:$J$14,1),COLUMN($K$4))):indirect(address(row($J$2)+ VLOOKUP(AK$20,$J$3:$J$14,1),COLUMN($S$2)))>indirect(address(row($J13),COLUMN($K$2))):indirect(address(row($J13),COLUMN($S$2))),TRUE()))} -> 7 | AL32: {=if(AL$20=$J13,"-", countif(indirect(address(row($J$2)+ VLOOKUP(AL$20,$J$3:$J$14,1),COLUMN($K$4))):indirect(address(row($J$2)+ VLOOKUP(AL$20,$J$3:$J$14,1),COLUMN($S$2)))>indirect(address(row($J13),COLUMN($K$2))):indirect(address(row($J13),COLUMN($S$2))),TRUE()))} -> 0 | AM32: {=if(AM$20=$J13,"-", countif(indirect(address(row($J$2)+ VLOOKUP(AM$20,$J$3:$J$14,1),COLUMN($K$4))):indirect(address(row($J$2)+ VLOOKUP(AM$20,$J$3:$J$14,1),COLUMN($S$2)))>indirect(address(row($J13),COLUMN($K$2))):indirect(address(row($J13),COLUMN($S$2))),TRUE()))} -> 0 | AN32: {=if(AN$20=$J13,"-", countif(indirect(address(row($J$2)+ VLOOKUP(AN$20,$J$3:$J$14,1),COLUMN($K$4))):indirect(address(row($J$2)+ VLOOKUP(AN$20,$J$3:$J$14,1),COLUMN($S$2)))>indirect(address(row($J13),COLUMN($K$2))):indirect(address(row($J13),COLUMN($S$2))),TRUE()))} -> 0 | AO32: {=if(AO$20=$J13,"-", countif(indirect(address(row($J$2)+ VLOOKUP(AO$20,$J$3:$J$14,1),COLUMN($K$4))):indirect(address(row($J$2)+ VLOOKUP(AO$20,$J$3:$J$14,1),COLUMN($S$2)))>indirect(address(row($J13),COLUMN($K$2))):indirect(address(row($J13),COLUMN($S$2))),TRUE()))} -> 0 | AP32: {=if(AP$20=$J13,"-", countif(indirect(address(row($J$2)+ VLOOKUP(AP$20,$J$3:$J$14,1),COLUMN($K$4))):indirect(address(row($J$2)+ VLOOKUP(AP$20,$J$3:$J$14,1),COLUMN($S$2)))>indirect(address(row($J13),COLUMN($K$2))):indirect(address(row($J13),COLUMN($S$2))),TRUE()))} -> 0 | AQ32: {=if(AQ$20=$J13,"-", countif(indirect(address(row($J$2)+ VLOOKUP(AQ$20,$J$3:$J$14,1),COLUMN($K$4))):indirect(address(row($J$2)+ VLOOKUP(AQ$20,$J$3:$J$14,1),COLUMN($S$2)))>indirect(address(row($J13),COLUMN($K$2))):indirect(address(row($J13),COLUMN($S$2))),TRUE()))} -> 0 | AR32: {=if(AR$20=$J13,"-", countif(indirect(address(row($J$2)+ VLOOKUP(AR$20,$J$3:$J$14,1),COLUMN($K$4))):indirect(address(row($J$2)+ VLOOKUP(AR$20,$J$3:$J$14,1),COLUMN($S$2)))>indirect(address(row($J13),COLUMN($K$2))):indirect(address(row($J13),COLUMN($S$2))),TRUE()))} -> 0 | ... AV32: {=if(AV$20=$J13,"-", countif(indirect(address(row($J$2)+ VLOOKUP(AV$20,$J$3:$J$14,1),COLUMN($K$4))):indirect(address(row($J$2)+ VLOOKUP(AV$20,$J$3:$J$14,1),COLUMN($S$2)))>indirect(address(row($J13),COLUMN($K$2))):indirect(address(row($J13),COLUMN($S$2))),TRUE()))} -> 0 | AW32: 11 | AX32: {=INDIRECT("Draft!N"&TEXT(VLOOKUP(TRUE,I3:J14,2,0)+2,"0"))} | AZ32: =IF($AX32="","", VLOOKUP($AX32,'Final Update'!$P$21:$AD1015,Column(H11),False)) | BA32: =IF($AX32="","", VLOOKUP($AX32,'Final Update'!$P$21:$AD1015,Column(I11),False)) | BB32: =IF($AX32="","", VLOOKUP($AX32,'Final Update'!$P$21:$AD1015,Column(J11),False)) | BC32: =IF($AX32="","", VLOOKUP($AX32,'Final Update'!$P$21:$AD1015,Column(K11),False)) | BD32: =IF($AX32="","", VLOOKUP($AX32,'Final Update'!$P$21:$AD1015,Column(L11),False)) | BE32: =IF($AX32="","", VLOOKUP($AX32,'Final Update'!$P$21:$AD1015,Column(M11),False)) | BF32: =IF($AX32="","", VLOOKUP($AX32,'Final Update'!$P$21:$AD1015,Column(N11),False)) | BG32: =IF($AX32="","", VLOOKUP($AX32,'Final Update'!$P$21:$AD1015,Column(O11),False)) | BH32: =IF($AX32="","", VLOOKUP($AX32,'Final Update'!$P$21:$AD1015,Column(P11),False)) | BI32: =IF($AX32="","", VLOOKUP($AX32,'Final Update'!$P$21:$AD1015,Column(C11),False))
A33: =VLOOKUP($F33,UpdateHashtag!$V$3:$Y$32,COLUMN(B$15),0) -> 4 | B33: =VLOOKUP($F33,UpdateHashtag!$V$3:$Y$32,COLUMN(C$13),0) -> 4 | C33: =VLOOKUP($F33,UpdateHashtag!$V$3:$Y$32,COLUMN(D$13),0) -> 3 | D33: =SUM(A33:C33) -> 11 | F33: =IF(VLOOKUP(J33,PasteHashtag!$C$2:$P1015,3,)="BRO","BKN",IF(VLOOKUP(J33,PasteHashtag!$C$2:$P1015,3,)="OKL","OKC",VLOOKUP(J33,PasteHashtag!$C$2:$P1015,3,))) -> ATL | G33: 14 | H33: =IFERROR(__xludf.DUMMYFUNCTION("""COMPUTED_VALUE"""),19.0) -> 19 | I33: =IFERROR(__xludf.DUMMYFUNCTION("""COMPUTED_VALUE"""),12.5) -> 12.5 | J33: =IFERROR(__xludf.DUMMYFUNCTION("""COMPUTED_VALUE"""),"Trae Young") -> Trae Young | K33: =IFERROR(__xludf.DUMMYFUNCTION("""COMPUTED_VALUE"""),78.0) -> 78 | L33: =IFERROR(__xludf.DUMMYFUNCTION("""COMPUTED_VALUE"""),"SG,SF") -> SG,SF | M33: =IFERROR(__xludf.DUMMYFUNCTION("""COMPUTED_VALUE"""),3.503772975657455) -> 3.503773 | N33: =IFERROR(__xludf.DUMMYFUNCTION("""COMPUTED_VALUE"""),4.074462528451495) -> 4.0744625 | O33: =IFERROR(__xludf.DUMMYFUNCTION("""COMPUTED_VALUE"""),0.5706895527940397) -> 0.57068955 | P33: =IFERROR(__xludf.DUMMYFUNCTION("""COMPUTED_VALUE"""),26.75866667) -> 26.758667 | Q33: =IFERROR(__xludf.DUMMYFUNCTION("""COMPUTED_VALUE"""),2.7916) -> 2.7916 | R33: =IFERROR(__xludf.DUMMYFUNCTION("""COMPUTED_VALUE"""),3.374933333) -> 3.3749333 | S33: =IFERROR(__xludf.DUMMYFUNCTION("""COMPUTED_VALUE"""),10.05) -> 10.05 | T33: =IFERROR(__xludf.DUMMYFUNCTION("""COMPUTED_VALUE"""),1.05) -> 1.05 | U33: =IFERROR(__xludf.DUMMYFUNCTION("""COMPUTED_VALUE"""),0.2248) -> 0.2248 | V33: =IFERROR(__xludf.DUMMYFUNCTION("""COMPUTED_VALUE"""),0.4390615812) -> 0.43906158 | W33: =IFERROR(__xludf.DUMMYFUNCTION("""COMPUTED_VALUE"""),0.8540079193) -> 0.85400792 | X33: =IFERROR(__xludf.DUMMYFUNCTION("""COMPUTED_VALUE"""),4.05) -> 4.05 | Y33: =IFERROR(__xludf.DUMMYFUNCTION("""COMPUTED_VALUE"""),1.6709697717406122) -> 1.6709698 | Z33: =IFERROR(__xludf.DUMMYFUNCTION("""COMPUTED_VALUE"""),1.0345153376488943) -> 1.0345153 | AA33: =IFERROR(__xludf.DUMMYFUNCTION("""COMPUTED_VALUE"""),-1.061440909010791) -> -1.0614409 | AB33: =IFERROR(__xludf.DUMMYFUNCTION("""COMPUTED_VALUE"""),2.7778132713212145) -> 2.7778133 | AC33: =IFERROR(__xludf.DUMMYFUNCTION("""COMPUTED_VALUE"""),0.24481519006675123) -> 0.24481519 | AD33: =IFERROR(__xludf.DUMMYFUNCTION("""COMPUTED_VALUE"""),-0.9343936399965528) -> -0.93439364 | AE33: =IFERROR(__xludf.DUMMYFUNCTION("""COMPUTED_VALUE"""),-1.319697620128027) -> -1.3196976 | AF33: =IFERROR(__xludf.DUMMYFUNCTION("""COMPUTED_VALUE"""),1.6618811268093934) -> 1.6618811 | AG33: =IFERROR(__xludf.DUMMYFUNCTION("""COMPUTED_VALUE"""),0.0) -> 0 | AJ33: 100 | AK33: {=if(AK$20=$J14,"-", countif(indirect(address(row($J$2)+ VLOOKUP(AK$20,$J$3:$J$14,1),COLUMN($K$4))):indirect(address(row($J$2)+ VLOOKUP(AK$20,$J$3:$J$14,1),COLUMN($S$2)))>indirect(address(row($J14),COLUMN($K$2))):indirect(address(row($J14),COLUMN($S$2))),TRUE()))} -> 7 | AL33: {=if(AL$20=$J14,"-", countif(indirect(address(row($J$2)+ VLOOKUP(AL$20,$J$3:$J$14,1),COLUMN($K$4))):indirect(address(row($J$2)+ VLOOKUP(AL$20,$J$3:$J$14,1),COLUMN($S$2)))>indirect(address(row($J14),COLUMN($K$2))):indirect(address(row($J14),COLUMN($S$2))),TRUE()))} -> 0 | AM33: {=if(AM$20=$J14,"-", countif(indirect(address(row($J$2)+ VLOOKUP(AM$20,$J$3:$J$14,1),COLUMN($K$4))):indirect(address(row($J$2)+ VLOOKUP(AM$20,$J$3:$J$14,1),COLUMN($S$2)))>indirect(address(row($J14),COLUMN($K$2))):indirect(address(row($J14),COLUMN($S$2))),TRUE()))} -> 0 | AN33: {=if(AN$20=$J14,"-", countif(indirect(address(row($J$2)+ VLOOKUP(AN$20,$J$3:$J$14,1),COLUMN($K$4))):indirect(address(row($J$2)+ VLOOKUP(AN$20,$J$3:$J$14,1),COLUMN($S$2)))>indirect(address(row($J14),COLUMN($K$2))):indirect(address(row($J14),COLUMN($S$2))),TRUE()))} -> 0 | AO33: {=if(AO$20=$J14,"-", countif(indirect(address(row($J$2)+ VLOOKUP(AO$20,$J$3:$J$14,1),COLUMN($K$4))):indirect(address(row($J$2)+ VLOOKUP(AO$20,$J$3:$J$14,1),COLUMN($S$2)))>indirect(address(row($J14),COLUMN($K$2))):indirect(address(row($J14),COLUMN($S$2))),TRUE()))} -> 0 | AP33: {=if(AP$20=$J14,"-", countif(indirect(address(row($J$2)+ VLOOKUP(AP$20,$J$3:$J$14,1),COLUMN($K$4))):indirect(address(row($J$2)+ VLOOKUP(AP$20,$J$3:$J$14,1),COLUMN($S$2)))>indirect(address(row($J14),COLUMN($K$2))):indirect(address(row($J14),COLUMN($S$2))),TRUE()))} -> 0 | AQ33: {=if(AQ$20=$J14,"-", countif(indirect(address(row($J$2)+ VLOOKUP(AQ$20,$J$3:$J$14,1),COLUMN($K$4))):indirect(address(row($J$2)+ VLOOKUP(AQ$20,$J$3:$J$14,1),COLUMN($S$2)))>indirect(address(row($J14),COLUMN($K$2))):indirect(address(row($J14),COLUMN($S$2))),TRUE()))} -> 0 | AR33: {=if(AR$20=$J14,"-", countif(indirect(address(row($J$2)+ VLOOKUP(AR$20,$J$3:$J$14,1),COLUMN($K$4))):indirect(address(row($J$2)+ VLOOKUP(AR$20,$J$3:$J$14,1),COLUMN($S$2)))>indirect(address(row($J14),COLUMN($K$2))):indirect(address(row($J14),COLUMN($S$2))),TRUE()))} -> 0 | ... AV33: {=if(AV$20=$J14,"-", countif(indirect(address(row($J$2)+ VLOOKUP(AV$20,$J$3:$J$14,1),COLUMN($K$4))):indirect(address(row($J$2)+ VLOOKUP(AV$20,$J$3:$J$14,1),COLUMN($S$2)))>indirect(address(row($J14),COLUMN($K$2))):indirect(address(row($J14),COLUMN($S$2))),TRUE()))} -> - | AW33: 12 | AX33: {=INDIRECT("Draft!O"&TEXT(15-VLOOKUP(TRUE,I3:J14,2,0),"0"))} | AZ33: =IF($AX33="","", VLOOKUP($AX33,'Final Update'!$P$21:$AD1015,Column(H12),False)) | BA33: =IF($AX33="","", VLOOKUP($AX33,'Final Update'!$P$21:$AD1015,Column(I12),False)) | BB33: =IF($AX33="","", VLOOKUP($AX33,'Final Update'!$P$21:$AD1015,Column(J12),False)) | BC33: =IF($AX33="","", VLOOKUP($AX33,'Final Update'!$P$21:$AD1015,Column(K12),False)) | BD33: =IF($AX33="","", VLOOKUP($AX33,'Final Update'!$P$21:$AD1015,Column(L12),False)) | BE33: =IF($AX33="","", VLOOKUP($AX33,'Final Update'!$P$21:$AD1015,Column(M12),False)) | BF33: =IF($AX33="","", VLOOKUP($AX33,'Final Update'!$P$21:$AD1015,Column(N12),False)) | BG33: =IF($AX33="","", VLOOKUP($AX33,'Final Update'!$P$21:$AD1015,Column(O12),False)) | BH33: =IF($AX33="","", VLOOKUP($AX33,'Final Update'!$P$21:$AD1015,Column(P12),False)) | BI33: =IF($AX33="","", VLOOKUP($AX33,'Final Update'!$P$21:$AD1015,Column(C12),False))
A34: =VLOOKUP($F34,UpdateHashtag!$V$3:$Y$32,COLUMN(B$15),0) -> 4 | B34: =VLOOKUP($F34,UpdateHashtag!$V$3:$Y$32,COLUMN(C$13),0) -> 3 | C34: =VLOOKUP($F34,UpdateHashtag!$V$3:$Y$32,COLUMN(D$13),0) -> 3 | D34: =SUM(A34:C34) -> 10 | F34: =IF(VLOOKUP(J34,PasteHashtag!$C$2:$P1015,3,)="BRO","BKN",IF(VLOOKUP(J34,PasteHashtag!$C$2:$P1015,3,)="OKL","OKC",VLOOKUP(J34,PasteHashtag!$C$2:$P1015,3,))) -> MIN | G34: 15 | H34: =IFERROR(__xludf.DUMMYFUNCTION("""COMPUTED_VALUE"""),16.0) -> 16 | I34: =IFERROR(__xludf.DUMMYFUNCTION("""COMPUTED_VALUE"""),10.1) -> 10.1 | J34: =IFERROR(__xludf.DUMMYFUNCTION("""COMPUTED_VALUE"""),"Anthony Edwards") -> Anthony Edwards | K34: =IFERROR(__xludf.DUMMYFUNCTION("""COMPUTED_VALUE"""),58.0) -> 58 | L34: =IFERROR(__xludf.DUMMYFUNCTION("""COMPUTED_VALUE"""),"SG,SF") -> SG,SF | M34: =IFERROR(__xludf.DUMMYFUNCTION("""COMPUTED_VALUE"""),3.814227079343934) -> 3.8142271 | N34: =IFERROR(__xludf.DUMMYFUNCTION("""COMPUTED_VALUE"""),4.054424077926738) -> 4.0544241 | O34: =IFERROR(__xludf.DUMMYFUNCTION("""COMPUTED_VALUE"""),0.24019699858280408) -> 0.240197 | P34: =IFERROR(__xludf.DUMMYFUNCTION("""COMPUTED_VALUE"""),26.24675325) -> 26.246753 | Q34: =IFERROR(__xludf.DUMMYFUNCTION("""COMPUTED_VALUE"""),2.313246753) -> 2.3132468 | R34: =IFERROR(__xludf.DUMMYFUNCTION("""COMPUTED_VALUE"""),5.359350649) -> 5.3593506 | S34: =IFERROR(__xludf.DUMMYFUNCTION("""COMPUTED_VALUE"""),5.359350649) -> 5.3593506 | T34: =IFERROR(__xludf.DUMMYFUNCTION("""COMPUTED_VALUE"""),1.356103896) -> 1.3561039 | U34: =IFERROR(__xludf.DUMMYFUNCTION("""COMPUTED_VALUE"""),0.5720779221) -> 0.57207792 | V34: =IFERROR(__xludf.DUMMYFUNCTION("""COMPUTED_VALUE"""),0.4670996365) -> 0.46709964 | W34: =IFERROR(__xludf.DUMMYFUNCTION("""COMPUTED_VALUE"""),0.8489939292) -> 0.84899393 | X34: =IFERROR(__xludf.DUMMYFUNCTION("""COMPUTED_VALUE"""),2.717272727) -> 2.7172727 | Y34: =IFERROR(__xludf.DUMMYFUNCTION("""COMPUTED_VALUE"""),1.5786944912378325) -> 1.5786945 | Z34: =IFERROR(__xludf.DUMMYFUNCTION("""COMPUTED_VALUE"""),0.5600231002073994) -> 0.5600231 | AA34: =IFERROR(__xludf.DUMMYFUNCTION("""COMPUTED_VALUE"""),-0.28373387921734805) -> -0.28373388 | AB34: =IFERROR(__xludf.DUMMYFUNCTION("""COMPUTED_VALUE"""),0.6476092356282376) -> 0.64760924 | AC34: =IFERROR(__xludf.DUMMYFUNCTION("""COMPUTED_VALUE"""),1.2575028046534056) -> 1.2575028 | AD34: =IFERROR(__xludf.DUMMYFUNCTION("""COMPUTED_VALUE"""),-0.3149721299657725) -> -0.31497213 | AE34: =IFERROR(__xludf.DUMMYFUNCTION("""COMPUTED_VALUE"""),-0.6815711239581117) -> -0.68157112 | AF34: =IFERROR(__xludf.DUMMYFUNCTION("""COMPUTED_VALUE"""),1.2908715793410945) -> 1.2908716 | AG34: =IFERROR(__xludf.DUMMYFUNCTION("""COMPUTED_VALUE"""),0.0) -> 0 | AJ34: 100 | AW34: 13 | AX34: {=INDIRECT("Draft!P"&TEXT(VLOOKUP(TRUE,I3:J14,2,0)+2,"0"))}
A35: =VLOOKUP($F35,UpdateHashtag!$V$3:$Y$32,COLUMN(B$15),0) -> 3 | B35: =VLOOKUP($F35,UpdateHashtag!$V$3:$Y$32,COLUMN(C$13),0) -> 4 | C35: =VLOOKUP($F35,UpdateHashtag!$V$3:$Y$32,COLUMN(D$13),0) -> 3 | D35: =SUM(A35:C35) -> 10 | F35: =IF(VLOOKUP(J35,PasteHashtag!$C$2:$P1015,3,)="BRO","BKN",IF(VLOOKUP(J35,PasteHashtag!$C$2:$P1015,3,)="OKL","OKC",VLOOKUP(J35,PasteHashtag!$C$2:$P1015,3,))) -> BOS | G35: 16 | H35: =IFERROR(__xludf.DUMMYFUNCTION("""COMPUTED_VALUE"""),17.0) -> 17 | I35: =IFERROR(__xludf.DUMMYFUNCTION("""COMPUTED_VALUE"""),9.5) -> 9.5 | J35: =IFERROR(__xludf.DUMMYFUNCTION("""COMPUTED_VALUE"""),"Jayson Tatum") -> Jayson Tatum | K35: =IFERROR(__xludf.DUMMYFUNCTION("""COMPUTED_VALUE"""),60.0) -> 60 | L35: =IFERROR(__xludf.DUMMYFUNCTION("""COMPUTED_VALUE"""),"PG,SG") -> PG,SG | M35: =IFERROR(__xludf.DUMMYFUNCTION("""COMPUTED_VALUE"""),3.818833214530949) -> 3.8188332 | N35: =IFERROR(__xludf.DUMMYFUNCTION("""COMPUTED_VALUE"""),4.0053949477535875) -> 4.0053949 | O35: =IFERROR(__xludf.DUMMYFUNCTION("""COMPUTED_VALUE"""),0.18656173322263836) -> 0.18656173 | P35: =IFERROR(__xludf.DUMMYFUNCTION("""COMPUTED_VALUE"""),25.77873239) -> 25.778732 | Q35: =IFERROR(__xludf.DUMMYFUNCTION("""COMPUTED_VALUE"""),2.897605634) -> 2.8976056 | R35: =IFERROR(__xludf.DUMMYFUNCTION("""COMPUTED_VALUE"""),7.717464789) -> 7.7174648 | S35: =IFERROR(__xludf.DUMMYFUNCTION("""COMPUTED_VALUE"""),5.245211268) -> 5.2452113 | T35: =IFERROR(__xludf.DUMMYFUNCTION("""COMPUTED_VALUE"""),0.9969014085) -> 0.99690141 | U35: =IFERROR(__xludf.DUMMYFUNCTION("""COMPUTED_VALUE"""),0.5730985915) -> 0.57309859 | V35: =IFERROR(__xludf.DUMMYFUNCTION("""COMPUTED_VALUE"""),0.4581999526) -> 0.45819995 | W35: =IFERROR(__xludf.DUMMYFUNCTION("""COMPUTED_VALUE"""),0.8500109577) -> 0.85001096 | X35: =IFERROR(__xludf.DUMMYFUNCTION("""COMPUTED_VALUE"""),2.500985915) -> 2.5009859 | Y35: =IFERROR(__xludf.DUMMYFUNCTION("""COMPUTED_VALUE"""),1.4943310921738802) -> 1.4943311 | Z35: =IFERROR(__xludf.DUMMYFUNCTION("""COMPUTED_VALUE"""),1.1396653513124666) -> 1.1396654 | AA35: =IFERROR(__xludf.DUMMYFUNCTION("""COMPUTED_VALUE"""),0.6404275504107535) -> 0.64042755 | AB35: =IFERROR(__xludf.DUMMYFUNCTION("""COMPUTED_VALUE"""),0.595774158681831) -> 0.59577416 | AC35: =IFERROR(__xludf.DUMMYFUNCTION("""COMPUTED_VALUE"""),0.06914840938635679) -> 0.069148409 | AD35: =IFERROR(__xludf.DUMMYFUNCTION("""COMPUTED_VALUE"""),-0.31315161521157464) -> -0.31315162 | AE35: =IFERROR(__xludf.DUMMYFUNCTION("""COMPUTED_VALUE"""),-0.8632677014460912) -> -0.8632677 | AF35: =IFERROR(__xludf.DUMMYFUNCTION("""COMPUTED_VALUE"""),1.2424677024459658) -> 1.2424677 | AG35: =IFERROR(__xludf.DUMMYFUNCTION("""COMPUTED_VALUE"""),0.0) -> 0 | AJ35: 50 | AW35: 14 | AX35: {=INDIRECT("Draft!Q"&TEXT(15-VLOOKUP(TRUE,I3:J14,2,0),"0"))}
A36: =VLOOKUP($F36,UpdateHashtag!$V$3:$Y$32,COLUMN(B$15),0) -> 3 | B36: =VLOOKUP($F36,UpdateHashtag!$V$3:$Y$32,COLUMN(C$13),0) -> 3 | C36: =VLOOKUP($F36,UpdateHashtag!$V$3:$Y$32,COLUMN(D$13),0) -> 4 | D36: =SUM(A36:C36) -> 10 | F36: =IF(VLOOKUP(J36,PasteHashtag!$C$2:$P1015,3,)="BRO","BKN",IF(VLOOKUP(J36,PasteHashtag!$C$2:$P1015,3,)="OKL","OKC",VLOOKUP(J36,PasteHashtag!$C$2:$P1015,3,))) -> NY | G36: 17 | H36: =IFERROR(__xludf.DUMMYFUNCTION("""COMPUTED_VALUE"""),15.0) -> 15 | I36: =IFERROR(__xludf.DUMMYFUNCTION("""COMPUTED_VALUE"""),22.1) -> 22.1 | J36: =IFERROR(__xludf.DUMMYFUNCTION("""COMPUTED_VALUE"""),"Karl-Anthony Towns") -> Karl-Anthony Towns | K36: =IFERROR(__xludf.DUMMYFUNCTION("""COMPUTED_VALUE"""),50.0) -> 50 | L36: =IFERROR(__xludf.DUMMYFUNCTION("""COMPUTED_VALUE"""),"C") -> C | M36: =IFERROR(__xludf.DUMMYFUNCTION("""COMPUTED_VALUE"""),3.543467632532436) -> 3.5434676 | N36: =IFERROR(__xludf.DUMMYFUNCTION("""COMPUTED_VALUE"""),3.8492903846992776) -> 3.8492904 | O36: =IFERROR(__xludf.DUMMYFUNCTION("""COMPUTED_VALUE"""),0.30582275216684174) -> 0.30582275 | P36: =IFERROR(__xludf.DUMMYFUNCTION("""COMPUTED_VALUE"""),22.99985294) -> 22.999853 | Q36: =IFERROR(__xludf.DUMMYFUNCTION("""COMPUTED_VALUE"""),2.154264706) -> 2.1542647 | R36: =IFERROR(__xludf.DUMMYFUNCTION("""COMPUTED_VALUE"""),10.5) -> 10.5 | S36: =IFERROR(__xludf.DUMMYFUNCTION("""COMPUTED_VALUE"""),3.488235294) -> 3.4882353 | T36: =IFERROR(__xludf.DUMMYFUNCTION("""COMPUTED_VALUE"""),0.6401470588) -> 0.64014706 | U36: =IFERROR(__xludf.DUMMYFUNCTION("""COMPUTED_VALUE"""),1.05) -> 1.05 | V36: =IFERROR(__xludf.DUMMYFUNCTION("""COMPUTED_VALUE"""),0.5164562794) -> 0.51645628 | W36: =IFERROR(__xludf.DUMMYFUNCTION("""COMPUTED_VALUE"""),0.8590137336) -> 0.85901373 | X36: =IFERROR(__xludf.DUMMYFUNCTION("""COMPUTED_VALUE"""),2.981911765) -> 2.9819118 | Y36: =IFERROR(__xludf.DUMMYFUNCTION("""COMPUTED_VALUE"""),0.9934224019266884) -> 0.9934224 | Z36: =IFERROR(__xludf.DUMMYFUNCTION("""COMPUTED_VALUE"""),0.40232427059318576) -> 0.40232427 | AA36: =IFERROR(__xludf.DUMMYFUNCTION("""COMPUTED_VALUE"""),1.730922567156758) -> 1.7309226 | AB36: =IFERROR(__xludf.DUMMYFUNCTION("""COMPUTED_VALUE"""),-0.20213611564564307) -> -0.20213612 | AC36: =IFERROR(__xludf.DUMMYFUNCTION("""COMPUTED_VALUE"""),-1.1111067788426296) -> -1.1111068 | AD36: =IFERROR(__xludf.DUMMYFUNCTION("""COMPUTED_VALUE"""),0.5374725442586427) -> 0.53747254 | AE36: =IFERROR(__xludf.DUMMYFUNCTION("""COMPUTED_VALUE"""),0.35661493195132526) -> 0.35661493 | AF36: =IFERROR(__xludf.DUMMYFUNCTION("""COMPUTED_VALUE"""),1.1417765633009507) -> 1.1417766 | AG36: =IFERROR(__xludf.DUMMYFUNCTION("""COMPUTED_VALUE"""),0.0) -> 0 | AY36: Average | AZ36: =IFERROR(AVERAGE(SUMPRODUCT(AZ$22:AZ$35,$AJ$22:$AJ$35/100))/(SUM(OFFSET($AJ$22,0,0,COUNT($AZ$22:$AZ$35)))/100),"") | BA36: =IFERROR(AVERAGE(SUMPRODUCT(BA$22:BA$35,$AJ$22:$AJ$35/100))/(SUM(OFFSET($AJ$22,0,0,COUNT($AZ$22:$AZ$35)))/100),"") | BB36: =IFERROR(AVERAGE(SUMPRODUCT(BB$22:BB$35,$AJ$22:$AJ$35/100))/(SUM(OFFSET($AJ$22,0,0,COUNT($AZ$22:$AZ$35)))/100),"") | BC36: =IFERROR(AVERAGE(SUMPRODUCT(BC$22:BC$35,$AJ$22:$AJ$35/100))/(SUM(OFFSET($AJ$22,0,0,COUNT($AZ$22:$AZ$35)))/100),"") | BD36: =IFERROR(AVERAGE(SUMPRODUCT(BD$22:BD$35,$AJ$22:$AJ$35/100))/(SUM(OFFSET($AJ$22,0,0,COUNT($AZ$22:$AZ$35)))/100),"") | BE36: =IFERROR(AVERAGE(SUMPRODUCT(BE$22:BE$35,$AJ$22:$AJ$35/100))/(SUM(OFFSET($AJ$22,0,0,COUNT($AZ$22:$AZ$35)))/100),"") | BF36: {=IFERROR(100*SUMPRODUCT(IFERROR(VLOOKUP(AX22:AX35,UpdateHashtag!$C:$S,6,False),"")*AJ22:AJ35/100)/SUMPRODUCT(IFERROR(VLOOKUP(AX22:AX35,UpdateHashtag!$C:$S,17,False),"")*AJ22:AJ35/100),"")} | BG36: {=IFERROR(100*SUMPRODUCT(IFERROR(VLOOKUP(AX22:AX35,UpdateHashtag!$C:$T,8,False),"")*AJ22:AJ35/100)/SUMPRODUCT(IFERROR(VLOOKUP(AX22:AX35,UpdateHashtag!$C:$T,18,False),"")*AJ22:AJ35/100),"")} | BH36: =AVERAGE(SUMPRODUCT(BG22:BG35,$B22:$B35/100))/(SUM(OFFSET($B22,0,0,COUNT(BG22:BG35)))/100) -> #VALUE!
A37: =VLOOKUP($F37,UpdateHashtag!$V$3:$Y$32,COLUMN(B$15),0) -> 4 | B37: =VLOOKUP($F37,UpdateHashtag!$V$3:$Y$32,COLUMN(C$13),0) -> 4 | C37: =VLOOKUP($F37,UpdateHashtag!$V$3:$Y$32,COLUMN(D$13),0) -> 4 | D37: =SUM(A37:C37) -> 12 | F37: =IF(VLOOKUP(J37,PasteHashtag!$C$2:$P1015,3,)="BRO","BKN",IF(VLOOKUP(J37,PasteHashtag!$C$2:$P1015,3,)="OKL","OKC",VLOOKUP(J37,PasteHashtag!$C$2:$P1015,3,))) -> HOU | G37: 18 | H37: =IFERROR(__xludf.DUMMYFUNCTION("""COMPUTED_VALUE"""),24.0) -> 24 | I37: =IFERROR(__xludf.DUMMYFUNCTION("""COMPUTED_VALUE"""),38.4) -> 38.4 | J37: =IFERROR(__xludf.DUMMYFUNCTION("""COMPUTED_VALUE"""),"Fred VanVleet") -> Fred VanVleet | K37: =IFERROR(__xludf.DUMMYFUNCTION("""COMPUTED_VALUE"""),78.0) -> 78 | L37: =IFERROR(__xludf.DUMMYFUNCTION("""COMPUTED_VALUE"""),"SF,PF") -> SF,PF | M37: =IFERROR(__xludf.DUMMYFUNCTION("""COMPUTED_VALUE"""),3.7303233124940434) -> 3.7303233 | N37: =IFERROR(__xludf.DUMMYFUNCTION("""COMPUTED_VALUE"""),3.6911466646783366) -> 3.6911467 | O37: =IFERROR(__xludf.DUMMYFUNCTION("""COMPUTED_VALUE"""),-0.03917664781570673) -> -0.039176648 | P37: =IFERROR(__xludf.DUMMYFUNCTION("""COMPUTED_VALUE"""),17.75273973) -> 17.75274 | Q37: =IFERROR(__xludf.DUMMYFUNCTION("""COMPUTED_VALUE"""),3.176027397) -> 3.1760274 | R37: =IFERROR(__xludf.DUMMYFUNCTION("""COMPUTED_VALUE"""),3.711780822) -> 3.7117808 | S37: =IFERROR(__xludf.DUMMYFUNCTION("""COMPUTED_VALUE"""),7.347808219) -> 7.3478082 | T37: =IFERROR(__xludf.DUMMYFUNCTION("""COMPUTED_VALUE"""),1.742191781) -> 1.7421918 | U37: =IFERROR(__xludf.DUMMYFUNCTION("""COMPUTED_VALUE"""),0.5302739726) -> 0.53027397 | V37: =IFERROR(__xludf.DUMMYFUNCTION("""COMPUTED_VALUE"""),0.4186914797) -> 0.41869148 | W37: =IFERROR(__xludf.DUMMYFUNCTION("""COMPUTED_VALUE"""),0.8609991087) -> 0.86099911 | X37: =IFERROR(__xludf.DUMMYFUNCTION("""COMPUTED_VALUE"""),1.590684932) -> 1.5906849 | Y37: =IFERROR(__xludf.DUMMYFUNCTION("""COMPUTED_VALUE"""),0.04760065870575043) -> 0.047600659 | Z37: =IFERROR(__xludf.DUMMYFUNCTION("""COMPUTED_VALUE"""),1.4158398439218491) -> 1.4158398 | AA37: =IFERROR(__xludf.DUMMYFUNCTION("""COMPUTED_VALUE"""),-0.9294280213730127) -> -0.92942802 | AB37: =IFERROR(__xludf.DUMMYFUNCTION("""COMPUTED_VALUE"""),1.5506441937871147) -> 1.5506442 | AC37: =IFERROR(__xludf.DUMMYFUNCTION("""COMPUTED_VALUE"""),2.534802520176976) -> 2.5348025 | AD37: =IFERROR(__xludf.DUMMYFUNCTION("""COMPUTED_VALUE"""),-0.38953565352050085) -> -0.38953565 | AE37: =IFERROR(__xludf.DUMMYFUNCTION("""COMPUTED_VALUE"""),-1.2873365613008023) -> -1.2873366 | AF37: =IFERROR(__xludf.DUMMYFUNCTION("""COMPUTED_VALUE"""),0.7485596842809622) -> 0.74855968 | AG37: =IFERROR(__xludf.DUMMYFUNCTION("""COMPUTED_VALUE"""),0.0) -> 0 | AY37: ZScore | AZ37: =IFERROR((SUM(OFFSET(AJ22,0,0,COUNT(AZ22:AZ35)))/100)*(AZ36-'Final Update'!$B$1)/'Final Update'!$B$2,"") | BA37: =IFERROR((SUM(OFFSET(AJ22,0,0,COUNT(AZ22:AZ35)))/100)*(BA36-'Final Update'!$C$1)/'Final Update'!$C$2,"") | BB37: =IFERROR((SUM(OFFSET(AJ22,0,0,COUNT(AZ22:AZ35)))/100)*(BB36-'Final Update'!$D$1)/'Final Update'!$D$2,"") | BC37: =IFERROR((SUM(OFFSET(AJ22,0,0,COUNT(AZ22:AZ35)))/100)*(BC36-'Final Update'!$E$1)/'Final Update'!$E$2,"") | BD37: =IFERROR((SUM(OFFSET(AJ22,0,0,COUNT(AZ22:AZ35)))/100)*(BD36-'Final Update'!$F$1)/'Final Update'!$F$2,"") | BE37: =IFERROR((SUM(OFFSET(AJ22,0,0,COUNT(AZ22:AZ35)))/100)*(BE36-'Final Update'!$G$1)/'Final Update'!$G$2,"") | BF37: {=SUMPRODUCT(IFERROR(VLOOKUP(AX22:AX35,'Final Update'!$A$4:$L$403,8,False)*AJ22:AJ35/100,""))} -> 0 | BG37: {=SUMPRODUCT(IFERROR(VLOOKUP(AX22:AX35,'Final Update'!$A$4:$L$403,10,False)*AJ22:AJ35/100,""))} -> 0 | BH37: =-(SUM(OFFSET(AJ22,0,0,COUNT(AZ22:AZ35)))/100)*(BH36-'Final Update'!$L$1)/'Final Update'!$L$2 -> #VALUE!
A38: =VLOOKUP($F38,UpdateHashtag!$V$3:$Y$32,COLUMN(B$15),0) -> 3 | B38: =VLOOKUP($F38,UpdateHashtag!$V$3:$Y$32,COLUMN(C$13),0) -> 3 | C38: =VLOOKUP($F38,UpdateHashtag!$V$3:$Y$32,COLUMN(D$13),0) -> 4 | D38: =SUM(A38:C38) -> 10 | F38: =IF(VLOOKUP(J38,PasteHashtag!$C$2:$P1015,3,)="BRO","BKN",IF(VLOOKUP(J38,PasteHashtag!$C$2:$P1015,3,)="OKL","OKC",VLOOKUP(J38,PasteHashtag!$C$2:$P1015,3,))) -> NY | G38: 19 | H38: =IFERROR(__xludf.DUMMYFUNCTION("""COMPUTED_VALUE"""),20.0) -> 20 | I38: =IFERROR(__xludf.DUMMYFUNCTION("""COMPUTED_VALUE"""),19.1) -> 19.1 | J38: =IFERROR(__xludf.DUMMYFUNCTION("""COMPUTED_VALUE"""),"Jalen Brunson") -> Jalen Brunson | K38: =IFERROR(__xludf.DUMMYFUNCTION("""COMPUTED_VALUE"""),55.0) -> 55 | L38: =IFERROR(__xludf.DUMMYFUNCTION("""COMPUTED_VALUE"""),"C") -> C | M38: =IFERROR(__xludf.DUMMYFUNCTION("""COMPUTED_VALUE"""),3.474301773061553) -> 3.4743018 | N38: =IFERROR(__xludf.DUMMYFUNCTION("""COMPUTED_VALUE"""),3.6823938865748813) -> 3.6823939 | O38: =IFERROR(__xludf.DUMMYFUNCTION("""COMPUTED_VALUE"""),0.20809211351332824) -> 0.20809211 | P38: =IFERROR(__xludf.DUMMYFUNCTION("""COMPUTED_VALUE"""),29.39794521) -> 29.397945 | Q38: =IFERROR(__xludf.DUMMYFUNCTION("""COMPUTED_VALUE"""),2.575890411) -> 2.5758904 | R38: =IFERROR(__xludf.DUMMYFUNCTION("""COMPUTED_VALUE"""),3.527945205) -> 3.5279452 | S38: =IFERROR(__xludf.DUMMYFUNCTION("""COMPUTED_VALUE"""),7.703972603) -> 7.7039726 | T38: =IFERROR(__xludf.DUMMYFUNCTION("""COMPUTED_VALUE"""),0.9384931507) -> 0.93849315 | U38: =IFERROR(__xludf.DUMMYFUNCTION("""COMPUTED_VALUE"""),0.1436986301) -> 0.14369863 | V38: =IFERROR(__xludf.DUMMYFUNCTION("""COMPUTED_VALUE"""),0.4834350148) -> 0.48343501 | W38: =IFERROR(__xludf.DUMMYFUNCTION("""COMPUTED_VALUE"""),0.8589916366) -> 0.85899164 | X38: =IFERROR(__xludf.DUMMYFUNCTION("""COMPUTED_VALUE"""),2.587808219) -> 2.5878082 | Y38: =IFERROR(__xludf.DUMMYFUNCTION("""COMPUTED_VALUE"""),2.1467146107867685) -> 2.1467146 | Z38: =IFERROR(__xludf.DUMMYFUNCTION("""COMPUTED_VALUE"""),0.8205468401753206) -> 0.82054684 | AA38: =IFERROR(__xludf.DUMMYFUNCTION("""COMPUTED_VALUE"""),-1.0014744858513116) -> -1.0014745 | AB38: =IFERROR(__xludf.DUMMYFUNCTION("""COMPUTED_VALUE"""),1.7123921206504085) -> 1.7123921 | AC38: =IFERROR(__xludf.DUMMYFUNCTION("""COMPUTED_VALUE"""),-0.12408441135384177) -> -0.12408441 | AD38: =IFERROR(__xludf.DUMMYFUNCTION("""COMPUTED_VALUE"""),-1.079049921931335) -> -1.0790499 | AE38: =IFERROR(__xludf.DUMMYFUNCTION("""COMPUTED_VALUE"""),-0.347012330112926) -> -0.34701233 | AF38: =IFERROR(__xludf.DUMMYFUNCTION("""COMPUTED_VALUE"""),1.554361464211798) -> 1.5543615 | AG38: =IFERROR(__xludf.DUMMYFUNCTION("""COMPUTED_VALUE"""),0.0) -> 0
A39: =VLOOKUP($F39,UpdateHashtag!$V$3:$Y$32,COLUMN(B$15),0) -> 4 | B39: =VLOOKUP($F39,UpdateHashtag!$V$3:$Y$32,COLUMN(C$13),0) -> 4 | C39: =VLOOKUP($F39,UpdateHashtag!$V$3:$Y$32,COLUMN(D$13),0) -> 4 | D39: =SUM(A39:C39) -> 12 | F39: =IF(VLOOKUP(J39,PasteHashtag!$C$2:$P1015,3,)="BRO","BKN",IF(VLOOKUP(J39,PasteHashtag!$C$2:$P1015,3,)="OKL","OKC",VLOOKUP(J39,PasteHashtag!$C$2:$P1015,3,))) -> LAC | G39: 20 | H39: =IFERROR(__xludf.DUMMYFUNCTION("""COMPUTED_VALUE"""),18.0) -> 18 | I39: =IFERROR(__xludf.DUMMYFUNCTION("""COMPUTED_VALUE"""),49.1) -> 49.1 | J39: =IFERROR(__xludf.DUMMYFUNCTION("""COMPUTED_VALUE"""),"Kawhi Leonard") -> Kawhi Leonard | K39: =IFERROR(__xludf.DUMMYFUNCTION("""COMPUTED_VALUE"""),60.0) -> 60 | L39: =IFERROR(__xludf.DUMMYFUNCTION("""COMPUTED_VALUE"""),"SG,SF,PF") -> SG,SF,PF | M39: =IFERROR(__xludf.DUMMYFUNCTION("""COMPUTED_VALUE"""),3.6743426861757884) -> 3.6743427 | N39: =IFERROR(__xludf.DUMMYFUNCTION("""COMPUTED_VALUE"""),3.6801773227569505) -> 3.6801773 | O39: =IFERROR(__xludf.DUMMYFUNCTION("""COMPUTED_VALUE"""),0.005834636581162123) -> 0.0058346366 | P39: =IFERROR(__xludf.DUMMYFUNCTION("""COMPUTED_VALUE"""),22.2904878) -> 22.290488 | Q39: =IFERROR(__xludf.DUMMYFUNCTION("""COMPUTED_VALUE"""),1.713414634) -> 1.7134146 | R39: =IFERROR(__xludf.DUMMYFUNCTION("""COMPUTED_VALUE"""),6.265853659) -> 6.2658537 | S39: =IFERROR(__xludf.DUMMYFUNCTION("""COMPUTED_VALUE"""),3.797560976) -> 3.797561 | T39: =IFERROR(__xludf.DUMMYFUNCTION("""COMPUTED_VALUE"""),1.390243902) -> 1.3902439 | U39: =IFERROR(__xludf.DUMMYFUNCTION("""COMPUTED_VALUE"""),0.6329268293) -> 0.63292683 | V39: =IFERROR(__xludf.DUMMYFUNCTION("""COMPUTED_VALUE"""),0.5124108633) -> 0.51241086 | W39: =IFERROR(__xludf.DUMMYFUNCTION("""COMPUTED_VALUE"""),0.8799832583) -> 0.87998326 | X39: =IFERROR(__xludf.DUMMYFUNCTION("""COMPUTED_VALUE"""),1.772195122) -> 1.7721951 | Y39: =IFERROR(__xludf.DUMMYFUNCTION("""COMPUTED_VALUE"""),0.8655553355145719) -> 0.86555534 | Z39: =IFERROR(__xludf.DUMMYFUNCTION("""COMPUTED_VALUE"""),-0.03496749726121787) -> -0.034967497 | AA39: =IFERROR(__xludf.DUMMYFUNCTION("""COMPUTED_VALUE"""),0.07153099260254513) -> 0.071530993 | AB39: =IFERROR(__xludf.DUMMYFUNCTION("""COMPUTED_VALUE"""),-0.061659442410751567) -> -0.061659442 | AC39: =IFERROR(__xludf.DUMMYFUNCTION("""COMPUTED_VALUE"""),1.3704486432719183) -> 1.3704486 | AD39: =IFERROR(__xludf.DUMMYFUNCTION("""COMPUTED_VALUE"""),-0.20643910905379656) -> -0.20643911 | AE39: =IFERROR(__xludf.DUMMYFUNCTION("""COMPUTED_VALUE"""),0.28354819439449463) -> 0.28354819 | AF39: =IFERROR(__xludf.DUMMYFUNCTION("""COMPUTED_VALUE"""),1.3921602056991869) -> 1.3921602 | AG39: =IFERROR(__xludf.DUMMYFUNCTION("""COMPUTED_VALUE"""),0.0) -> 0
A40: =VLOOKUP($F40,UpdateHashtag!$V$3:$Y$32,COLUMN(B$15),0) -> 3 | B40: =VLOOKUP($F40,UpdateHashtag!$V$3:$Y$32,COLUMN(C$13),0) -> 4 | C40: =VLOOKUP($F40,UpdateHashtag!$V$3:$Y$32,COLUMN(D$13),0) -> 3 | D40: =SUM(A40:C40) -> 10 | F40: =IF(VLOOKUP(J40,PasteHashtag!$C$2:$P1015,3,)="BRO","BKN",IF(VLOOKUP(J40,PasteHashtag!$C$2:$P1015,3,)="OKL","OKC",VLOOKUP(J40,PasteHashtag!$C$2:$P1015,3,))) -> PHO | G40: 21 | H40: =IFERROR(__xludf.DUMMYFUNCTION("""COMPUTED_VALUE"""),21.0) -> 21 | I40: =IFERROR(__xludf.DUMMYFUNCTION("""COMPUTED_VALUE"""),20.0) -> 20 | J40: =IFERROR(__xludf.DUMMYFUNCTION("""COMPUTED_VALUE"""),"Devin Booker") -> Devin Booker | K40: =IFERROR(__xludf.DUMMYFUNCTION("""COMPUTED_VALUE"""),78.0) -> 78 | L40: =IFERROR(__xludf.DUMMYFUNCTION("""COMPUTED_VALUE"""),"PF,C") -> PF,C | M40: =IFERROR(__xludf.DUMMYFUNCTION("""COMPUTED_VALUE"""),3.4023707844651803) -> 3.4023708 | N40: =IFERROR(__xludf.DUMMYFUNCTION("""COMPUTED_VALUE"""),3.5860043860535904) -> 3.5860044 | O40: =IFERROR(__xludf.DUMMYFUNCTION("""COMPUTED_VALUE"""),0.18363360158841013) -> 0.1836336 | P40: =IFERROR(__xludf.DUMMYFUNCTION("""COMPUTED_VALUE"""),26.43630137) -> 26.436301 | Q40: =IFERROR(__xludf.DUMMYFUNCTION("""COMPUTED_VALUE"""),2.919589041) -> 2.919589 | R40: =IFERROR(__xludf.DUMMYFUNCTION("""COMPUTED_VALUE"""),4.15630137) -> 4.1563014 | S40: =IFERROR(__xludf.DUMMYFUNCTION("""COMPUTED_VALUE"""),5.90630137) -> 5.9063014 | T40: =IFERROR(__xludf.DUMMYFUNCTION("""COMPUTED_VALUE"""),0.9415068493) -> 0.94150685 | U40: =IFERROR(__xludf.DUMMYFUNCTION("""COMPUTED_VALUE"""),0.3663013699) -> 0.36630137 | V40: =IFERROR(__xludf.DUMMYFUNCTION("""COMPUTED_VALUE"""),0.4664797607) -> 0.46647976 | W40: =IFERROR(__xludf.DUMMYFUNCTION("""COMPUTED_VALUE"""),0.8880078459) -> 0.88800785 | X40: =IFERROR(__xludf.DUMMYFUNCTION("""COMPUTED_VALUE"""),2.489178082) -> 2.4891781 | Y40: =IFERROR(__xludf.DUMMYFUNCTION("""COMPUTED_VALUE"""),1.6128616086808063) -> 1.6128616 | Z40: =IFERROR(__xludf.DUMMYFUNCTION("""COMPUTED_VALUE"""),1.1614713201010867) -> 1.1614713 | AA40: =IFERROR(__xludf.DUMMYFUNCTION("""COMPUTED_VALUE"""),-0.7552173085960869) -> -0.75521731 | AB40: =IFERROR(__xludf.DUMMYFUNCTION("""COMPUTED_VALUE"""),0.8960005661272853) -> 0.89600057 | AC40: =IFERROR(__xludf.DUMMYFUNCTION("""COMPUTED_VALUE"""),-0.11411415195434317) -> -0.11411415 | AD40: =IFERROR(__xludf.DUMMYFUNCTION("""COMPUTED_VALUE"""),-0.6820050295001931) -> -0.68200503 | AE40: =IFERROR(__xludf.DUMMYFUNCTION("""COMPUTED_VALUE"""),-0.6784506294748801) -> -0.67845063 | AF40: =IFERROR(__xludf.DUMMYFUNCTION("""COMPUTED_VALUE"""),2.1454580106699153) -> 2.145458 | AG40: =IFERROR(__xludf.DUMMYFUNCTION("""COMPUTED_VALUE"""),0.0) -> 0
A41: =VLOOKUP($F41,UpdateHashtag!$V$3:$Y$32,COLUMN(B$15),0) -> 3 | B41: =VLOOKUP($F41,UpdateHashtag!$V$3:$Y$32,COLUMN(C$13),0) -> 4 | C41: =VLOOKUP($F41,UpdateHashtag!$V$3:$Y$32,COLUMN(D$13),0) -> 3 | D41: =SUM(A41:C41) -> 10 | F41: =IF(VLOOKUP(J41,PasteHashtag!$C$2:$P1015,3,)="BRO","BKN",IF(VLOOKUP(J41,PasteHashtag!$C$2:$P1015,3,)="OKL","OKC",VLOOKUP(J41,PasteHashtag!$C$2:$P1015,3,))) -> TOR | G41: 22 | H41: =IFERROR(__xludf.DUMMYFUNCTION("""COMPUTED_VALUE"""),23.0) -> 23 | I41: =IFERROR(__xludf.DUMMYFUNCTION("""COMPUTED_VALUE"""),19.0) -> 19 | J41: =IFERROR(__xludf.DUMMYFUNCTION("""COMPUTED_VALUE"""),"Scottie Barnes") -> Scottie Barnes | K41: =IFERROR(__xludf.DUMMYFUNCTION("""COMPUTED_VALUE"""),68.0) -> 68 | L41: =IFERROR(__xludf.DUMMYFUNCTION("""COMPUTED_VALUE"""),"SF,PF") -> SF,PF | M41: =IFERROR(__xludf.DUMMYFUNCTION("""COMPUTED_VALUE"""),2.9758235571961023) -> 2.9758236 | N41: =IFERROR(__xludf.DUMMYFUNCTION("""COMPUTED_VALUE"""),3.3457569846009347) -> 3.345757 | O41: =IFERROR(__xludf.DUMMYFUNCTION("""COMPUTED_VALUE"""),0.3699334274048325) -> 0.36993343 | P41: =IFERROR(__xludf.DUMMYFUNCTION("""COMPUTED_VALUE"""),20.39897059) -> 20.398971 | Q41: =IFERROR(__xludf.DUMMYFUNCTION("""COMPUTED_VALUE"""),1.265735294) -> 1.2657353 | R41: =IFERROR(__xludf.DUMMYFUNCTION("""COMPUTED_VALUE"""),7.585588235) -> 7.5855882 | S41: =IFERROR(__xludf.DUMMYFUNCTION("""COMPUTED_VALUE"""),6.554411765) -> 6.5544118 | T41: =IFERROR(__xludf.DUMMYFUNCTION("""COMPUTED_VALUE"""),1.180441176) -> 1.1804412 | U41: =IFERROR(__xludf.DUMMYFUNCTION("""COMPUTED_VALUE"""),1.325588235) -> 1.3255882 | V41: =IFERROR(__xludf.DUMMYFUNCTION("""COMPUTED_VALUE"""),0.4873241251) -> 0.48732413 | W41: =IFERROR(__xludf.DUMMYFUNCTION("""COMPUTED_VALUE"""),0.7949914552) -> 0.79499146 | X41: =IFERROR(__xludf.DUMMYFUNCTION("""COMPUTED_VALUE"""),3.240441176) -> 3.2404412 | Y41: =IFERROR(__xludf.DUMMYFUNCTION("""COMPUTED_VALUE"""),0.5245986926342472) -> 0.52459869 | Z41: =IFERROR(__xludf.DUMMYFUNCTION("""COMPUTED_VALUE"""),-0.47903341094557045) -> -0.47903341 | AA41: =IFERROR(__xludf.DUMMYFUNCTION("""COMPUTED_VALUE"""),0.5887442062452894) -> 0.58874421 | AB41: =IFERROR(__xludf.DUMMYFUNCTION("""COMPUTED_VALUE"""),1.190332390080239) -> 1.1903324 | AC41: =IFERROR(__xludf.DUMMYFUNCTION("""COMPUTED_VALUE"""),0.6763554778366198) -> 0.67635548 | AD41: =IFERROR(__xludf.DUMMYFUNCTION("""COMPUTED_VALUE"""),1.0290248998997888) -> 1.0290249 | AE41: =IFERROR(__xludf.DUMMYFUNCTION("""COMPUTED_VALUE"""),-0.18444534601068677) -> -0.18444535 | AF41: =IFERROR(__xludf.DUMMYFUNCTION("""COMPUTED_VALUE"""),1.80074861008132E-4) -> 0.00018007486 | AG41: =IFERROR(__xludf.DUMMYFUNCTION("""COMPUTED_VALUE"""),0.0) -> 0
A42: =VLOOKUP($F42,UpdateHashtag!$V$3:$Y$32,COLUMN(B$15),0) -> 4 | B42: =VLOOKUP($F42,UpdateHashtag!$V$3:$Y$32,COLUMN(C$13),0) -> 4 | C42: =VLOOKUP($F42,UpdateHashtag!$V$3:$Y$32,COLUMN(D$13),0) -> 3 | D42: =SUM(A42:C42) -> 11 | F42: =IF(VLOOKUP(J42,PasteHashtag!$C$2:$P1015,3,)="BRO","BKN",IF(VLOOKUP(J42,PasteHashtag!$C$2:$P1015,3,)="OKL","OKC",VLOOKUP(J42,PasteHashtag!$C$2:$P1015,3,))) -> MIL | G42: 23 | H42: =IFERROR(__xludf.DUMMYFUNCTION("""COMPUTED_VALUE"""),28.0) -> 28 | I42: =IFERROR(__xludf.DUMMYFUNCTION("""COMPUTED_VALUE"""),24.3) -> 24.3 | J42: =IFERROR(__xludf.DUMMYFUNCTION("""COMPUTED_VALUE"""),"Damian Lillard") -> Damian Lillard | K42: =IFERROR(__xludf.DUMMYFUNCTION("""COMPUTED_VALUE"""),68.0) -> 68 | L42: =IFERROR(__xludf.DUMMYFUNCTION("""COMPUTED_VALUE"""),"SG,SF") -> SG,SF | M42: =IFERROR(__xludf.DUMMYFUNCTION("""COMPUTED_VALUE"""),2.96621614223755) -> 2.9662161 | N42: =IFERROR(__xludf.DUMMYFUNCTION("""COMPUTED_VALUE"""),3.2149705318849504) -> 3.2149705 | O42: =IFERROR(__xludf.DUMMYFUNCTION("""COMPUTED_VALUE"""),0.2487543896474005) -> 0.24875439 | P42: =IFERROR(__xludf.DUMMYFUNCTION("""COMPUTED_VALUE"""),23.52205479) -> 23.522055 | Q42: =IFERROR(__xludf.DUMMYFUNCTION("""COMPUTED_VALUE"""),3.035342466) -> 3.0353425 | R42: =IFERROR(__xludf.DUMMYFUNCTION("""COMPUTED_VALUE"""),4.331232877) -> 4.3312329 | S42: =IFERROR(__xludf.DUMMYFUNCTION("""COMPUTED_VALUE"""),6.916575342) -> 6.9165753 | T42: =IFERROR(__xludf.DUMMYFUNCTION("""COMPUTED_VALUE"""),0.8616438356) -> 0.86164384 | U42: =IFERROR(__xludf.DUMMYFUNCTION("""COMPUTED_VALUE"""),0.2898630137) -> 0.28986301 | V42: =IFERROR(__xludf.DUMMYFUNCTION("""COMPUTED_VALUE"""),0.433900243) -> 0.43390024 | W42: =IFERROR(__xludf.DUMMYFUNCTION("""COMPUTED_VALUE"""),0.921002059) -> 0.92100206 | X42: =IFERROR(__xludf.DUMMYFUNCTION("""COMPUTED_VALUE"""),2.751780822) -> 2.7517808 | Y42: =IFERROR(__xludf.DUMMYFUNCTION("""COMPUTED_VALUE"""),1.0875522299507718) -> 1.0875522 | Z42: =IFERROR(__xludf.DUMMYFUNCTION("""COMPUTED_VALUE"""),1.276290445850151) -> 1.2762904 | AA42: =IFERROR(__xludf.DUMMYFUNCTION("""COMPUTED_VALUE"""),-0.6866604271229461) -> -0.68666043 | AB42: =IFERROR(__xludf.DUMMYFUNCTION("""COMPUTED_VALUE"""),1.3548047809107178) -> 1.3548048 | AC42: =IFERROR(__xludf.DUMMYFUNCTION("""COMPUTED_VALUE"""),-0.3783260286877064) -> -0.37832603 | AD42: =IFERROR(__xludf.DUMMYFUNCTION("""COMPUTED_VALUE"""),-0.8183441371963074) -> -0.81834414 | AE42: =IFERROR(__xludf.DUMMYFUNCTION("""COMPUTED_VALUE"""),-1.2712285668018568) -> -1.2712286 | AF42: =IFERROR(__xludf.DUMMYFUNCTION("""COMPUTED_VALUE"""),2.650882234982127) -> 2.6508822 | AG42: =IFERROR(__xludf.DUMMYFUNCTION("""COMPUTED_VALUE"""),0.0) -> 0
A43: =VLOOKUP($F43,UpdateHashtag!$V$3:$Y$32,COLUMN(B$15),0) -> 3 | B43: =VLOOKUP($F43,UpdateHashtag!$V$3:$Y$32,COLUMN(C$13),0) -> 4 | C43: =VLOOKUP($F43,UpdateHashtag!$V$3:$Y$32,COLUMN(D$13),0) -> 3 | D43: =SUM(A43:C43) -> 10 | F43: =IF(VLOOKUP(J43,PasteHashtag!$C$2:$P1015,3,)="BRO","BKN",IF(VLOOKUP(J43,PasteHashtag!$C$2:$P1015,3,)="OKL","OKC",VLOOKUP(J43,PasteHashtag!$C$2:$P1015,3,))) -> PHO | G43: 24 | H43: =IFERROR(__xludf.DUMMYFUNCTION("""COMPUTED_VALUE"""),25.0) -> 25 | I43: =IFERROR(__xludf.DUMMYFUNCTION("""COMPUTED_VALUE"""),18.3) -> 18.3 | J43: =IFERROR(__xludf.DUMMYFUNCTION("""COMPUTED_VALUE"""),"Kevin Durant") -> Kevin Durant | K43: =IFERROR(__xludf.DUMMYFUNCTION("""COMPUTED_VALUE"""),68.0) -> 68 | L43: =IFERROR(__xludf.DUMMYFUNCTION("""COMPUTED_VALUE"""),"SG,SF") -> SG,SF | M43: =IFERROR(__xludf.DUMMYFUNCTION("""COMPUTED_VALUE"""),2.727684495596219) -> 2.7276845 | N43: =IFERROR(__xludf.DUMMYFUNCTION("""COMPUTED_VALUE"""),3.0399256089126094) -> 3.0399256 | O43: =IFERROR(__xludf.DUMMYFUNCTION("""COMPUTED_VALUE"""),0.31224111331639026) -> 0.31224111 | P43: =IFERROR(__xludf.DUMMYFUNCTION("""COMPUTED_VALUE"""),24.575) -> 24.575 | Q43: =IFERROR(__xludf.DUMMYFUNCTION("""COMPUTED_VALUE"""),2.611323529) -> 2.6113235 | R43: =IFERROR(__xludf.DUMMYFUNCTION("""COMPUTED_VALUE"""),6.020882353) -> 6.0208824 | S43: =IFERROR(__xludf.DUMMYFUNCTION("""COMPUTED_VALUE"""),3.754117647) -> 3.7541176 | T43: =IFERROR(__xludf.DUMMYFUNCTION("""COMPUTED_VALUE"""),0.765) -> 0.765 | U43: =IFERROR(__xludf.DUMMYFUNCTION("""COMPUTED_VALUE"""),1.076323529) -> 1.0763235 | V43: =IFERROR(__xludf.DUMMYFUNCTION("""COMPUTED_VALUE"""),0.5002442519) -> 0.50024425 | W43: =IFERROR(__xludf.DUMMYFUNCTION("""COMPUTED_VALUE"""),0.8620139386) -> 0.86201394 | X43: =IFERROR(__xludf.DUMMYFUNCTION("""COMPUTED_VALUE"""),3.007794118) -> 3.0077941 | Y43: =IFERROR(__xludf.DUMMYFUNCTION("""COMPUTED_VALUE"""),1.2773515413398122) -> 1.2773515 | Z43: =IFERROR(__xludf.DUMMYFUNCTION("""COMPUTED_VALUE"""),0.8556939611466735) -> 0.85569396 | AA43: =IFERROR(__xludf.DUMMYFUNCTION("""COMPUTED_VALUE"""),-0.024474976120759804) -> -0.024474976 | AB43: =IFERROR(__xludf.DUMMYFUNCTION("""COMPUTED_VALUE"""),-0.0813887267453413) -> -0.081388727 | AC43: =IFERROR(__xludf.DUMMYFUNCTION("""COMPUTED_VALUE"""),-0.6980541230281613) -> -0.69805412 | AD43: =IFERROR(__xludf.DUMMYFUNCTION("""COMPUTED_VALUE"""),0.584424449475997) -> 0.58442445 | AE43: =IFERROR(__xludf.DUMMYFUNCTION("""COMPUTED_VALUE"""),0.06297756845591759) -> 0.062977568 | AF43: =IFERROR(__xludf.DUMMYFUNCTION("""COMPUTED_VALUE"""),1.0633959143884713) -> 1.0633959 | AG43: =IFERROR(__xludf.DUMMYFUNCTION("""COMPUTED_VALUE"""),0.0) -> 0
A44: =VLOOKUP($F44,UpdateHashtag!$V$3:$Y$32,COLUMN(B$15),0) -> 4 | B44: =VLOOKUP($F44,UpdateHashtag!$V$3:$Y$32,COLUMN(C$13),0) -> 3 | C44: =VLOOKUP($F44,UpdateHashtag!$V$3:$Y$32,COLUMN(D$13),0) -> 4 | D44: =SUM(A44:C44) -> 11 | F44: =IF(VLOOKUP(J44,PasteHashtag!$C$2:$P1015,3,)="BRO","BKN",IF(VLOOKUP(J44,PasteHashtag!$C$2:$P1015,3,)="OKL","OKC",VLOOKUP(J44,PasteHashtag!$C$2:$P1015,3,))) -> SAC | G44: 25 | H44: =IFERROR(__xludf.DUMMYFUNCTION("""COMPUTED_VALUE"""),30.0) -> 30 | I44: =IFERROR(__xludf.DUMMYFUNCTION("""COMPUTED_VALUE"""),26.1) -> 26.1 | J44: =IFERROR(__xludf.DUMMYFUNCTION("""COMPUTED_VALUE"""),"De'Aaron Fox") -> De'Aaron Fox | K44: =IFERROR(__xludf.DUMMYFUNCTION("""COMPUTED_VALUE"""),76.0) -> 76 | L44: =IFERROR(__xludf.DUMMYFUNCTION("""COMPUTED_VALUE"""),"SF,PF") -> SF,PF | M44: =IFERROR(__xludf.DUMMYFUNCTION("""COMPUTED_VALUE"""),2.7908804349554908) -> 2.7908804 | N44: =IFERROR(__xludf.DUMMYFUNCTION("""COMPUTED_VALUE"""),2.958344242663441) -> 2.9583442 | O44: =IFERROR(__xludf.DUMMYFUNCTION("""COMPUTED_VALUE"""),0.16746380770795044) -> 0.16746381 | P44: =IFERROR(__xludf.DUMMYFUNCTION("""COMPUTED_VALUE"""),25.08767123) -> 25.087671 | Q44: =IFERROR(__xludf.DUMMYFUNCTION("""COMPUTED_VALUE"""),2.718219178) -> 2.7182192 | R44: =IFERROR(__xludf.DUMMYFUNCTION("""COMPUTED_VALUE"""),4.696438356) -> 4.6964384 | S44: =IFERROR(__xludf.DUMMYFUNCTION("""COMPUTED_VALUE"""),5.075205479) -> 5.0752055 | T44: =IFERROR(__xludf.DUMMYFUNCTION("""COMPUTED_VALUE"""),1.666438356) -> 1.6664384 | U44: =IFERROR(__xludf.DUMMYFUNCTION("""COMPUTED_VALUE"""),0.4553424658) -> 0.45534247 | V44: =IFERROR(__xludf.DUMMYFUNCTION("""COMPUTED_VALUE"""),0.4634715994) -> 0.4634716 | W44: =IFERROR(__xludf.DUMMYFUNCTION("""COMPUTED_VALUE"""),0.7749920559) -> 0.77499206 | X44: =IFERROR(__xludf.DUMMYFUNCTION("""COMPUTED_VALUE"""),2.423972603) -> 2.4239726 | Y44: =IFERROR(__xludf.DUMMYFUNCTION("""COMPUTED_VALUE"""),1.3697634213681877) -> 1.3697634 | Z44: =IFERROR(__xludf.DUMMYFUNCTION("""COMPUTED_VALUE"""),0.9617268060889191) -> 0.96172681 | AA44: =IFERROR(__xludf.DUMMYFUNCTION("""COMPUTED_VALUE"""),-0.5435338448021023) -> -0.54353384 | AB44: =IFERROR(__xludf.DUMMYFUNCTION("""COMPUTED_VALUE"""),0.5185680000629262) -> 0.518568 | AC44: =IFERROR(__xludf.DUMMYFUNCTION("""COMPUTED_VALUE"""),2.284186450723162) -> 2.2841865 | AD44: =IFERROR(__xludf.DUMMYFUNCTION("""COMPUTED_VALUE"""),-0.5231870725634095) -> -0.52318707 | AE44: =IFERROR(__xludf.DUMMYFUNCTION("""COMPUTED_VALUE"""),-0.806468710933035) -> -0.80646871 | AF44: =IFERROR(__xludf.DUMMYFUNCTION("""COMPUTED_VALUE"""),-0.30271080728120703) -> -0.30271081 | AG44: =IFERROR(__xludf.DUMMYFUNCTION("""COMPUTED_VALUE"""),0.0) -> 0
A45: =VLOOKUP($F45,UpdateHashtag!$V$3:$Y$32,COLUMN(B$15),0) -> 4 | B45: =VLOOKUP($F45,UpdateHashtag!$V$3:$Y$32,COLUMN(C$13),0) -> 3 | C45: =VLOOKUP($F45,UpdateHashtag!$V$3:$Y$32,COLUMN(D$13),0) -> 4 | D45: =SUM(A45:C45) -> 11 | F45: =IF(VLOOKUP(J45,PasteHashtag!$C$2:$P1015,3,)="BRO","BKN",IF(VLOOKUP(J45,PasteHashtag!$C$2:$P1015,3,)="OKL","OKC",VLOOKUP(J45,PasteHashtag!$C$2:$P1015,3,))) -> SAC | G45: 26 | H45: =IFERROR(__xludf.DUMMYFUNCTION("""COMPUTED_VALUE"""),22.0) -> 22 | I45: =IFERROR(__xludf.DUMMYFUNCTION("""COMPUTED_VALUE"""),14.6) -> 14.6 | J45: =IFERROR(__xludf.DUMMYFUNCTION("""COMPUTED_VALUE"""),"Domantas Sabonis") -> Domantas Sabonis | K45: =IFERROR(__xludf.DUMMYFUNCTION("""COMPUTED_VALUE"""),67.0) -> 67 | L45: =IFERROR(__xludf.DUMMYFUNCTION("""COMPUTED_VALUE"""),"C") -> C | M45: =IFERROR(__xludf.DUMMYFUNCTION("""COMPUTED_VALUE"""),2.6726699753926044) -> 2.67267 | N45: =IFERROR(__xludf.DUMMYFUNCTION("""COMPUTED_VALUE"""),2.934058174717424) -> 2.9340582 | O45: =IFERROR(__xludf.DUMMYFUNCTION("""COMPUTED_VALUE"""),0.2613881993248195) -> 0.2613882 | P45: =IFERROR(__xludf.DUMMYFUNCTION("""COMPUTED_VALUE"""),18.4612987) -> 18.461299 | Q45: =IFERROR(__xludf.DUMMYFUNCTION("""COMPUTED_VALUE"""),0.3036363636) -> 0.30363636 | R45: =IFERROR(__xludf.DUMMYFUNCTION("""COMPUTED_VALUE"""),14.01376623) -> 14.013766 | S45: =IFERROR(__xludf.DUMMYFUNCTION("""COMPUTED_VALUE"""),6.968961039) -> 6.968961 | T45: =IFERROR(__xludf.DUMMYFUNCTION("""COMPUTED_VALUE"""),0.9853246753) -> 0.98532468 | U45: =IFERROR(__xludf.DUMMYFUNCTION("""COMPUTED_VALUE"""),0.6814285714) -> 0.68142857 | V45: =IFERROR(__xludf.DUMMYFUNCTION("""COMPUTED_VALUE"""),0.5834030467) -> 0.58340305 | W45: =IFERROR(__xludf.DUMMYFUNCTION("""COMPUTED_VALUE"""),0.71) -> 0.71 | X45: =IFERROR(__xludf.DUMMYFUNCTION("""COMPUTED_VALUE"""),2.802727273) -> 2.8027273 | Y45: =IFERROR(__xludf.DUMMYFUNCTION("""COMPUTED_VALUE"""),0.1753224084295827) -> 0.17532241 | Z45: =IFERROR(__xludf.DUMMYFUNCTION("""COMPUTED_VALUE"""),-1.4333667973886757) -> -1.4333668 | AA45: =IFERROR(__xludf.DUMMYFUNCTION("""COMPUTED_VALUE"""),3.1079921361877734) -> 3.1079921 | AB45: =IFERROR(__xludf.DUMMYFUNCTION("""COMPUTED_VALUE"""),1.378595138025815) -> 1.3785951 | AC45: =IFERROR(__xludf.DUMMYFUNCTION("""COMPUTED_VALUE"""),0.03084894805243736) -> 0.030848948 | AD45: =IFERROR(__xludf.DUMMYFUNCTION("""COMPUTED_VALUE"""),-0.11992908230336444) -> -0.11992908 | AE45: =IFERROR(__xludf.DUMMYFUNCTION("""COMPUTED_VALUE"""),1.260155813700897) -> 1.2601558 | AF45: =IFERROR(__xludf.DUMMYFUNCTION("""COMPUTED_VALUE"""),-1.4655603899870406) -> -1.4655604 | AG45: =IFERROR(__xludf.DUMMYFUNCTION("""COMPUTED_VALUE"""),0.0) -> 0
A46: =VLOOKUP($F46,UpdateHashtag!$V$3:$Y$32,COLUMN(B$15),0) -> 4 | B46: =VLOOKUP($F46,UpdateHashtag!$V$3:$Y$32,COLUMN(C$13),0) -> 4 | C46: =VLOOKUP($F46,UpdateHashtag!$V$3:$Y$32,COLUMN(D$13),0) -> 3 | D46: =SUM(A46:C46) -> 11 | F46: =IF(VLOOKUP(J46,PasteHashtag!$C$2:$P1015,3,)="BRO","BKN",IF(VLOOKUP(J46,PasteHashtag!$C$2:$P1015,3,)="OKL","OKC",VLOOKUP(J46,PasteHashtag!$C$2:$P1015,3,))) -> OKC | G46: 27 | H46: =IFERROR(__xludf.DUMMYFUNCTION("""COMPUTED_VALUE"""),26.0) -> 26 | I46: =IFERROR(__xludf.DUMMYFUNCTION("""COMPUTED_VALUE"""),17.6) -> 17.6 | J46: =IFERROR(__xludf.DUMMYFUNCTION("""COMPUTED_VALUE"""),"Chet Holmgren") -> Chet Holmgren | K46: =IFERROR(__xludf.DUMMYFUNCTION("""COMPUTED_VALUE"""),72.0) -> 72 | L46: =IFERROR(__xludf.DUMMYFUNCTION("""COMPUTED_VALUE"""),"PG,SG") -> PG,SG | M46: =IFERROR(__xludf.DUMMYFUNCTION("""COMPUTED_VALUE"""),2.9213476665866014) -> 2.9213477 | N46: =IFERROR(__xludf.DUMMYFUNCTION("""COMPUTED_VALUE"""),2.871742180929906) -> 2.8717422 | O46: =IFERROR(__xludf.DUMMYFUNCTION("""COMPUTED_VALUE"""),-0.049605485656695425) -> -0.049605486 | P46: =IFERROR(__xludf.DUMMYFUNCTION("""COMPUTED_VALUE"""),19.0290411) -> 19.029041 | Q46: =IFERROR(__xludf.DUMMYFUNCTION("""COMPUTED_VALUE"""),1.748630137) -> 1.7486301 | R46: =IFERROR(__xludf.DUMMYFUNCTION("""COMPUTED_VALUE"""),9.09) -> 9.09 | S46: =IFERROR(__xludf.DUMMYFUNCTION("""COMPUTED_VALUE"""),2.356712329) -> 2.3567123 | T46: =IFERROR(__xludf.DUMMYFUNCTION("""COMPUTED_VALUE"""),0.7565753425) -> 0.75657534 | U46: =IFERROR(__xludf.DUMMYFUNCTION("""COMPUTED_VALUE"""),2.222054795) -> 2.2220548 | V46: =IFERROR(__xludf.DUMMYFUNCTION("""COMPUTED_VALUE"""),0.5130794838) -> 0.51307948 | W46: =IFERROR(__xludf.DUMMYFUNCTION("""COMPUTED_VALUE"""),0.7939860985) -> 0.7939861 | X46: =IFERROR(__xludf.DUMMYFUNCTION("""COMPUTED_VALUE"""),1.548630137) -> 1.5486301 | Y46: =IFERROR(__xludf.DUMMYFUNCTION("""COMPUTED_VALUE"""),0.2776611773825855) -> 0.27766118 | Z46: =IFERROR(__xludf.DUMMYFUNCTION("""COMPUTED_VALUE"""),-3.623481888805206E-5) -> -3.6234819e-05 | AA46: =IFERROR(__xludf.DUMMYFUNCTION("""COMPUTED_VALUE"""),1.1783337023210538) -> 1.1783337 | AB46: =IFERROR(__xludf.DUMMYFUNCTION("""COMPUTED_VALUE"""),-0.7160041552611845) -> -0.71600416 | AC46: =IFERROR(__xludf.DUMMYFUNCTION("""COMPUTED_VALUE"""),-0.7259255301512662) -> -0.72592553 | AD46: =IFERROR(__xludf.DUMMYFUNCTION("""COMPUTED_VALUE"""),2.6280055288134845) -> 2.6280055 | AE46: =IFERROR(__xludf.DUMMYFUNCTION("""COMPUTED_VALUE"""),0.24553485911638928) -> 0.24553486 | AF46: =IFERROR(__xludf.DUMMYFUNCTION("""COMPUTED_VALUE"""),-0.015827166472268086) -> -0.015827166 | AG46: =IFERROR(__xludf.DUMMYFUNCTION("""COMPUTED_VALUE"""),0.0) -> 0
A47: =VLOOKUP($F47,UpdateHashtag!$V$3:$Y$32,COLUMN(B$15),0) -> 4 | B47: =VLOOKUP($F47,UpdateHashtag!$V$3:$Y$32,COLUMN(C$13),0) -> 2 | C47: =VLOOKUP($F47,UpdateHashtag!$V$3:$Y$32,COLUMN(D$13),0) -> 4 | D47: =SUM(A47:C47) -> 10 | F47: =IF(VLOOKUP(J47,PasteHashtag!$C$2:$P1015,3,)="BRO","BKN",IF(VLOOKUP(J47,PasteHashtag!$C$2:$P1015,3,)="OKL","OKC",VLOOKUP(J47,PasteHashtag!$C$2:$P1015,3,))) -> NO | G47: 28 | H47: =IFERROR(__xludf.DUMMYFUNCTION("""COMPUTED_VALUE"""),33.0) -> 33 | I47: =IFERROR(__xludf.DUMMYFUNCTION("""COMPUTED_VALUE"""),35.6) -> 35.6 | J47: =IFERROR(__xludf.DUMMYFUNCTION("""COMPUTED_VALUE"""),"Dejounte Murray") -> Dejounte Murray | K47: =IFERROR(__xludf.DUMMYFUNCTION("""COMPUTED_VALUE"""),76.0) -> 76 | L47: =IFERROR(__xludf.DUMMYFUNCTION("""COMPUTED_VALUE"""),"PG,SG") -> PG,SG | M47: =IFERROR(__xludf.DUMMYFUNCTION("""COMPUTED_VALUE"""),2.4154533157720603) -> 2.4154533 | N47: =IFERROR(__xludf.DUMMYFUNCTION("""COMPUTED_VALUE"""),2.7336766732329356) -> 2.7336767 | O47: =IFERROR(__xludf.DUMMYFUNCTION("""COMPUTED_VALUE"""),0.31822335746087527) -> 0.31822336 | P47: =IFERROR(__xludf.DUMMYFUNCTION("""COMPUTED_VALUE"""),18.69739726) -> 18.697397 | Q47: =IFERROR(__xludf.DUMMYFUNCTION("""COMPUTED_VALUE"""),2.435616438) -> 2.4356164 | R47: =IFERROR(__xludf.DUMMYFUNCTION("""COMPUTED_VALUE"""),6.496849315) -> 6.4968493 | S47: =IFERROR(__xludf.DUMMYFUNCTION("""COMPUTED_VALUE"""),7.868493151) -> 7.8684932 | T47: =IFERROR(__xludf.DUMMYFUNCTION("""COMPUTED_VALUE"""),1.499589041) -> 1.499589 | U47: =IFERROR(__xludf.DUMMYFUNCTION("""COMPUTED_VALUE"""),0.2909589041) -> 0.2909589 | V47: =IFERROR(__xludf.DUMMYFUNCTION("""COMPUTED_VALUE"""),0.450156026) -> 0.45015603 | W47: =IFERROR(__xludf.DUMMYFUNCTION("""COMPUTED_VALUE"""),0.7759828727) -> 0.77598287 | X47: =IFERROR(__xludf.DUMMYFUNCTION("""COMPUTED_VALUE"""),3.031917808) -> 3.0319178 | Y47: =IFERROR(__xludf.DUMMYFUNCTION("""COMPUTED_VALUE"""),0.2178805051684849) -> 0.21788051 | Z47: =IFERROR(__xludf.DUMMYFUNCTION("""COMPUTED_VALUE"""),0.6814050830721688) -> 0.68140508 | AA47: =IFERROR(__xludf.DUMMYFUNCTION("""COMPUTED_VALUE"""),0.16205980631248762) -> 0.16205981 | AB47: =IFERROR(__xludf.DUMMYFUNCTION("""COMPUTED_VALUE"""),1.7871072206459568) -> 1.7871072 | AC47: =IFERROR(__xludf.DUMMYFUNCTION("""COMPUTED_VALUE"""),1.7321966295848925) -> 1.7321966 | AD47: =IFERROR(__xludf.DUMMYFUNCTION("""COMPUTED_VALUE"""),-0.8163894546691505) -> -0.81638945 | AE47: =IFERROR(__xludf.DUMMYFUNCTION("""COMPUTED_VALUE"""),-0.8896651577810943) -> -0.88966516 | AF47: =IFERROR(__xludf.DUMMYFUNCTION("""COMPUTED_VALUE"""),-0.14091795910081045) -> -0.14091796 | AG47: =IFERROR(__xludf.DUMMYFUNCTION("""COMPUTED_VALUE"""),0.0) -> 0
A48: =VLOOKUP($F48,UpdateHashtag!$V$3:$Y$32,COLUMN(B$15),0) -> 4 | B48: =VLOOKUP($F48,UpdateHashtag!$V$3:$Y$32,COLUMN(C$13),0) -> 4 | C48: =VLOOKUP($F48,UpdateHashtag!$V$3:$Y$32,COLUMN(D$13),0) -> 3 | D48: =SUM(A48:C48) -> 11 | F48: =IF(VLOOKUP(J48,PasteHashtag!$C$2:$P1015,3,)="BRO","BKN",IF(VLOOKUP(J48,PasteHashtag!$C$2:$P1015,3,)="OKL","OKC",VLOOKUP(J48,PasteHashtag!$C$2:$P1015,3,))) -> OKC | G48: 29 | H48: =IFERROR(__xludf.DUMMYFUNCTION("""COMPUTED_VALUE"""),29.0) -> 29 | I48: =IFERROR(__xludf.DUMMYFUNCTION("""COMPUTED_VALUE"""),36.0) -> 36 | J48: =IFERROR(__xludf.DUMMYFUNCTION("""COMPUTED_VALUE"""),"Jalen Williams") -> Jalen Williams | K48: =IFERROR(__xludf.DUMMYFUNCTION("""COMPUTED_VALUE"""),72.0) -> 72 | L48: =IFERROR(__xludf.DUMMYFUNCTION("""COMPUTED_VALUE"""),"PG,SG") -> PG,SG | M48: =IFERROR(__xludf.DUMMYFUNCTION("""COMPUTED_VALUE"""),2.5114576136794775) -> 2.5114576 | N48: =IFERROR(__xludf.DUMMYFUNCTION("""COMPUTED_VALUE"""),2.5771808057264765) -> 2.5771808 | O48: =IFERROR(__xludf.DUMMYFUNCTION("""COMPUTED_VALUE"""),0.06572319204699895) -> 0.065723192 | P48: =IFERROR(__xludf.DUMMYFUNCTION("""COMPUTED_VALUE"""),21.86369863) -> 21.863699 | Q48: =IFERROR(__xludf.DUMMYFUNCTION("""COMPUTED_VALUE"""),1.781232877) -> 1.7812329 | R48: =IFERROR(__xludf.DUMMYFUNCTION("""COMPUTED_VALUE"""),4.305068493) -> 4.3050685 | S48: =IFERROR(__xludf.DUMMYFUNCTION("""COMPUTED_VALUE"""),5.555068493) -> 5.5550685 | T48: =IFERROR(__xludf.DUMMYFUNCTION("""COMPUTED_VALUE"""),1.319315068) -> 1.3193151 | U48: =IFERROR(__xludf.DUMMYFUNCTION("""COMPUTED_VALUE"""),0.6876712329) -> 0.68767123 | V48: =IFERROR(__xludf.DUMMYFUNCTION("""COMPUTED_VALUE"""),0.5155965468) -> 0.51559655 | W48: =IFERROR(__xludf.DUMMYFUNCTION("""COMPUTED_VALUE"""),0.8190065086) -> 0.81900651 | X48: =IFERROR(__xludf.DUMMYFUNCTION("""COMPUTED_VALUE"""),2.01369863) -> 2.0136986 | Y48: =IFERROR(__xludf.DUMMYFUNCTION("""COMPUTED_VALUE"""),0.7886241810679882) -> 0.78862418 | Z48: =IFERROR(__xludf.DUMMYFUNCTION("""COMPUTED_VALUE"""),0.0323033534379957) -> 0.032303353 | AA48: =IFERROR(__xludf.DUMMYFUNCTION("""COMPUTED_VALUE"""),-0.6969144322674037) -> -0.69691443 | AB48: =IFERROR(__xludf.DUMMYFUNCTION("""COMPUTED_VALUE"""),0.7364922260093129) -> 0.73649223 | AC48: =IFERROR(__xludf.DUMMYFUNCTION("""COMPUTED_VALUE"""),1.1357938327729606) -> 1.1357938 | AD48: =IFERROR(__xludf.DUMMYFUNCTION("""COMPUTED_VALUE"""),-0.10879437270375009) -> -0.10879437 | AE48: =IFERROR(__xludf.DUMMYFUNCTION("""COMPUTED_VALUE"""),0.3468116436552771) -> 0.34681164 | AF48: =IFERROR(__xludf.DUMMYFUNCTION("""COMPUTED_VALUE"""),0.34286437375409584) -> 0.34286437 | AG48: =IFERROR(__xludf.DUMMYFUNCTION("""COMPUTED_VALUE"""),0.0) -> 0
A49: =VLOOKUP($F49,UpdateHashtag!$V$3:$Y$32,COLUMN(B$15),0) -> 4 | B49: =VLOOKUP($F49,UpdateHashtag!$V$3:$Y$32,COLUMN(C$13),0) -> 4 | C49: =VLOOKUP($F49,UpdateHashtag!$V$3:$Y$32,COLUMN(D$13),0) -> 4 | D49: =SUM(A49:C49) -> 12 | F49: =IF(VLOOKUP(J49,PasteHashtag!$C$2:$P1015,3,)="BRO","BKN",IF(VLOOKUP(J49,PasteHashtag!$C$2:$P1015,3,)="OKL","OKC",VLOOKUP(J49,PasteHashtag!$C$2:$P1015,3,))) -> UTA | G49: 30 | H49: =IFERROR(__xludf.DUMMYFUNCTION("""COMPUTED_VALUE"""),31.0) -> 31 | I49: =IFERROR(__xludf.DUMMYFUNCTION("""COMPUTED_VALUE"""),30.1) -> 30.1 | J49: =IFERROR(__xludf.DUMMYFUNCTION("""COMPUTED_VALUE"""),"Lauri Markkanen") -> Lauri Markkanen | K49: =IFERROR(__xludf.DUMMYFUNCTION("""COMPUTED_VALUE"""),71.0) -> 71 | L49: =IFERROR(__xludf.DUMMYFUNCTION("""COMPUTED_VALUE"""),"SF,PF") -> SF,PF | M49: =IFERROR(__xludf.DUMMYFUNCTION("""COMPUTED_VALUE"""),2.590648298054223) -> 2.5906483 | N49: =IFERROR(__xludf.DUMMYFUNCTION("""COMPUTED_VALUE"""),2.5364228712533987) -> 2.5364229 | O49: =IFERROR(__xludf.DUMMYFUNCTION("""COMPUTED_VALUE"""),-0.054225426800824206) -> -0.054225427 | P49: =IFERROR(__xludf.DUMMYFUNCTION("""COMPUTED_VALUE"""),22.97387097) -> 22.973871 | Q49: =IFERROR(__xludf.DUMMYFUNCTION("""COMPUTED_VALUE"""),3.162741935) -> 3.1627419 | R49: =IFERROR(__xludf.DUMMYFUNCTION("""COMPUTED_VALUE"""),7.290967742) -> 7.2909677 | S49: =IFERROR(__xludf.DUMMYFUNCTION("""COMPUTED_VALUE"""),2.139354839) -> 2.1393548 | T49: =IFERROR(__xludf.DUMMYFUNCTION("""COMPUTED_VALUE"""),0.9027419355) -> 0.90274194 | U49: =IFERROR(__xludf.DUMMYFUNCTION("""COMPUTED_VALUE"""),0.4174193548) -> 0.41741935 | V49: =IFERROR(__xludf.DUMMYFUNCTION("""COMPUTED_VALUE"""),0.4787610083) -> 0.47876101 | W49: =IFERROR(__xludf.DUMMYFUNCTION("""COMPUTED_VALUE"""),0.8879979717) -> 0.88799797 | X49: =IFERROR(__xludf.DUMMYFUNCTION("""COMPUTED_VALUE"""),1.53) -> 1.53 | Y49: =IFERROR(__xludf.DUMMYFUNCTION("""COMPUTED_VALUE"""),0.988739005328559) -> 0.98873901 | Z49: =IFERROR(__xludf.DUMMYFUNCTION("""COMPUTED_VALUE"""),1.4026616150097249) -> 1.4026616 | AA49: =IFERROR(__xludf.DUMMYFUNCTION("""COMPUTED_VALUE"""),0.47328037377422166) -> 0.47328037 | AB49: =IFERROR(__xludf.DUMMYFUNCTION("""COMPUTED_VALUE"""),-0.8147145400584164) -> -0.81471454 | AC49: =IFERROR(__xludf.DUMMYFUNCTION("""COMPUTED_VALUE"""),-0.24236063492553409) -> -0.24236063 | AD49: =IFERROR(__xludf.DUMMYFUNCTION("""COMPUTED_VALUE"""),-0.5908285469728329) -> -0.59082855 | AE49: =IFERROR(__xludf.DUMMYFUNCTION("""COMPUTED_VALUE"""),-0.3433907836126116) -> -0.34339078 | AF49: =IFERROR(__xludf.DUMMYFUNCTION("""COMPUTED_VALUE"""),1.6630363827102883) -> 1.6630364 | AG49: =IFERROR(__xludf.DUMMYFUNCTION("""COMPUTED_VALUE"""),0.0) -> 0
A50: =VLOOKUP($F50,UpdateHashtag!$V$3:$Y$32,COLUMN(B$15),0) -> 4 | B50: =VLOOKUP($F50,UpdateHashtag!$V$3:$Y$32,COLUMN(C$13),0) -> 4 | C50: =VLOOKUP($F50,UpdateHashtag!$V$3:$Y$32,COLUMN(D$13),0) -> 3 | D50: =SUM(A50:C50) -> 11 | F50: =IF(VLOOKUP(J50,PasteHashtag!$C$2:$P1015,3,)="BRO","BKN",IF(VLOOKUP(J50,PasteHashtag!$C$2:$P1015,3,)="OKL","OKC",VLOOKUP(J50,PasteHashtag!$C$2:$P1015,3,))) -> MIL | G50: 31 | H50: =IFERROR(__xludf.DUMMYFUNCTION("""COMPUTED_VALUE"""),27.0) -> 27 | I50: =IFERROR(__xludf.DUMMYFUNCTION("""COMPUTED_VALUE"""),6.7) -> 6.7 | J50: =IFERROR(__xludf.DUMMYFUNCTION("""COMPUTED_VALUE"""),"Giannis Antetokounmpo") -> Giannis Antetokounmpo | K50: =IFERROR(__xludf.DUMMYFUNCTION("""COMPUTED_VALUE"""),60.0) -> 60 | L50: =IFERROR(__xludf.DUMMYFUNCTION("""COMPUTED_VALUE"""),"SF,PF") -> SF,PF | M50: =IFERROR(__xludf.DUMMYFUNCTION("""COMPUTED_VALUE"""),2.0807463649067497) -> 2.0807464 | N50: =IFERROR(__xludf.DUMMYFUNCTION("""COMPUTED_VALUE"""),2.4884606001056886) -> 2.4884606 | O50: =IFERROR(__xludf.DUMMYFUNCTION("""COMPUTED_VALUE"""),0.4077142351989389) -> 0.40771424 | P50: =IFERROR(__xludf.DUMMYFUNCTION("""COMPUTED_VALUE"""),27.78514706) -> 27.785147 | Q50: =IFERROR(__xludf.DUMMYFUNCTION("""COMPUTED_VALUE"""),0.4780882353) -> 0.47808824 | R50: =IFERROR(__xludf.DUMMYFUNCTION("""COMPUTED_VALUE"""),11.83867647) -> 11.838676 | S50: =IFERROR(__xludf.DUMMYFUNCTION("""COMPUTED_VALUE"""),6.785588235) -> 6.7855882 | T50: =IFERROR(__xludf.DUMMYFUNCTION("""COMPUTED_VALUE"""),1.080588235) -> 1.0805882 | U50: =IFERROR(__xludf.DUMMYFUNCTION("""COMPUTED_VALUE"""),1.082794118) -> 1.0827941 | V50: =IFERROR(__xludf.DUMMYFUNCTION("""COMPUTED_VALUE"""),0.6018925424) -> 0.60189254 | W50: =IFERROR(__xludf.DUMMYFUNCTION("""COMPUTED_VALUE"""),0.6429979628) -> 0.64299796 | X50: =IFERROR(__xludf.DUMMYFUNCTION("""COMPUTED_VALUE"""),3.392794118) -> 3.3927941 | Y50: =IFERROR(__xludf.DUMMYFUNCTION("""COMPUTED_VALUE"""),1.8559986500963561) -> 1.8559987 | Z50: =IFERROR(__xludf.DUMMYFUNCTION("""COMPUTED_VALUE"""),-1.2603230071605942) -> -1.260323 | AA50: =IFERROR(__xludf.DUMMYFUNCTION("""COMPUTED_VALUE"""),2.255559241581983) -> 2.2555592 | AB50: =IFERROR(__xludf.DUMMYFUNCTION("""COMPUTED_VALUE"""),1.2953185044753108) -> 1.2953185 | AC50: =IFERROR(__xludf.DUMMYFUNCTION("""COMPUTED_VALUE"""),0.34601065716582396) -> 0.34601066 | AD50: =IFERROR(__xludf.DUMMYFUNCTION("""COMPUTED_VALUE"""),0.5959657014649861) -> 0.5959657 | AE50: =IFERROR(__xludf.DUMMYFUNCTION("""COMPUTED_VALUE"""),2.179164888368954) -> 2.1791649 | AF50: =IFERROR(__xludf.DUMMYFUNCTION("""COMPUTED_VALUE"""),-4.779234035887131) -> -4.779234 | AG50: =IFERROR(__xludf.DUMMYFUNCTION("""COMPUTED_VALUE"""),0.0) -> 0
A51: =VLOOKUP($F51,UpdateHashtag!$V$3:$Y$32,COLUMN(B$15),0) -> 4 | B51: =VLOOKUP($F51,UpdateHashtag!$V$3:$Y$32,COLUMN(C$13),0) -> 3 | C51: =VLOOKUP($F51,UpdateHashtag!$V$3:$Y$32,COLUMN(D$13),0) -> 4 | D51: =SUM(A51:C51) -> 11 | F51: =IF(VLOOKUP(J51,PasteHashtag!$C$2:$P1015,3,)="BRO","BKN",IF(VLOOKUP(J51,PasteHashtag!$C$2:$P1015,3,)="OKL","OKC",VLOOKUP(J51,PasteHashtag!$C$2:$P1015,3,))) -> DET | G51: 32 | H51: =IFERROR(__xludf.DUMMYFUNCTION("""COMPUTED_VALUE"""),34.0) -> 34 | I51: =IFERROR(__xludf.DUMMYFUNCTION("""COMPUTED_VALUE"""),34.0) -> 34 | J51: =IFERROR(__xludf.DUMMYFUNCTION("""COMPUTED_VALUE"""),"Cade Cunningham") -> Cade Cunningham | K51: =IFERROR(__xludf.DUMMYFUNCTION("""COMPUTED_VALUE"""),75.0) -> 75 | L51: =IFERROR(__xludf.DUMMYFUNCTION("""COMPUTED_VALUE"""),"PF,C") -> PF,C | M51: =IFERROR(__xludf.DUMMYFUNCTION("""COMPUTED_VALUE"""),1.9962353133828568) -> 1.9962353 | N51: =IFERROR(__xludf.DUMMYFUNCTION("""COMPUTED_VALUE"""),2.3502687098088497) -> 2.3502687 | O51: =IFERROR(__xludf.DUMMYFUNCTION("""COMPUTED_VALUE"""),0.35403339642599296) -> 0.3540334 | P51: =IFERROR(__xludf.DUMMYFUNCTION("""COMPUTED_VALUE"""),23.43279412) -> 23.432794 | Q51: =IFERROR(__xludf.DUMMYFUNCTION("""COMPUTED_VALUE"""),1.937058824) -> 1.9370588 | R51: =IFERROR(__xludf.DUMMYFUNCTION("""COMPUTED_VALUE"""),5.053088235) -> 5.0530882 | S51: =IFERROR(__xludf.DUMMYFUNCTION("""COMPUTED_VALUE"""),8.0575) -> 8.0575 | T51: =IFERROR(__xludf.DUMMYFUNCTION("""COMPUTED_VALUE"""),0.9517647059) -> 0.95176471 | U51: =IFERROR(__xludf.DUMMYFUNCTION("""COMPUTED_VALUE"""),0.4289705882) -> 0.42897059 | V51: =IFERROR(__xludf.DUMMYFUNCTION("""COMPUTED_VALUE"""),0.4586624621) -> 0.45866246 | W51: =IFERROR(__xludf.DUMMYFUNCTION("""COMPUTED_VALUE"""),0.8599861907) -> 0.85998619 | X51: =IFERROR(__xludf.DUMMYFUNCTION("""COMPUTED_VALUE"""),3.176323529) -> 3.1763235 | Y51: =IFERROR(__xludf.DUMMYFUNCTION("""COMPUTED_VALUE"""),1.0714624908653698) -> 1.0714625 | Z51: =IFERROR(__xludf.DUMMYFUNCTION("""COMPUTED_VALUE"""),0.18687155739014685) -> 0.18687156 | AA51: =IFERROR(__xludf.DUMMYFUNCTION("""COMPUTED_VALUE"""),-0.4037602619791228) -> -0.40376026 | AB51: =IFERROR(__xludf.DUMMYFUNCTION("""COMPUTED_VALUE"""),1.8729424904317011) -> 1.8729425 | AC51: =IFERROR(__xludf.DUMMYFUNCTION("""COMPUTED_VALUE"""),-0.08017794772182346) -> -0.080177948 | AD51: =IFERROR(__xludf.DUMMYFUNCTION("""COMPUTED_VALUE"""),-0.5702252146559411) -> -0.57022521 | AE51: =IFERROR(__xludf.DUMMYFUNCTION("""COMPUTED_VALUE"""),-0.8455592277925625) -> -0.84555923 | AF51: =IFERROR(__xludf.DUMMYFUNCTION("""COMPUTED_VALUE"""),1.1187148232710822) -> 1.1187148 | AG51: =IFERROR(__xludf.DUMMYFUNCTION("""COMPUTED_VALUE"""),0.0) -> 0
A52: =VLOOKUP($F52,UpdateHashtag!$V$3:$Y$32,COLUMN(B$15),0) -> 4 | B52: =VLOOKUP($F52,UpdateHashtag!$V$3:$Y$32,COLUMN(C$13),0) -> 4 | C52: =VLOOKUP($F52,UpdateHashtag!$V$3:$Y$32,COLUMN(D$13),0) -> 4 | D52: =SUM(A52:C52) -> 12 | F52: =IF(VLOOKUP(J52,PasteHashtag!$C$2:$P1015,3,)="BRO","BKN",IF(VLOOKUP(J52,PasteHashtag!$C$2:$P1015,3,)="OKL","OKC",VLOOKUP(J52,PasteHashtag!$C$2:$P1015,3,))) -> PHI | G52: 33 | H52: =IFERROR(__xludf.DUMMYFUNCTION("""COMPUTED_VALUE"""),36.0) -> 36 | I52: =IFERROR(__xludf.DUMMYFUNCTION("""COMPUTED_VALUE"""),27.8) -> 27.8 | J52: =IFERROR(__xludf.DUMMYFUNCTION("""COMPUTED_VALUE"""),"Tyrese Maxey") -> Tyrese Maxey | K52: =IFERROR(__xludf.DUMMYFUNCTION("""COMPUTED_VALUE"""),74.0) -> 74 | L52: =IFERROR(__xludf.DUMMYFUNCTION("""COMPUTED_VALUE"""),"SF,PF") -> SF,PF | M52: =IFERROR(__xludf.DUMMYFUNCTION("""COMPUTED_VALUE"""),2.246965456900757) -> 2.2469655 | N52: =IFERROR(__xludf.DUMMYFUNCTION("""COMPUTED_VALUE"""),2.2554149668920367) -> 2.255415 | O52: =IFERROR(__xludf.DUMMYFUNCTION("""COMPUTED_VALUE"""),0.00844950999127958) -> 0.00844951 | P52: =IFERROR(__xludf.DUMMYFUNCTION("""COMPUTED_VALUE"""),25.06109589) -> 25.061096 | Q52: =IFERROR(__xludf.DUMMYFUNCTION("""COMPUTED_VALUE"""),2.966712329) -> 2.9667123 | R52: =IFERROR(__xludf.DUMMYFUNCTION("""COMPUTED_VALUE"""),3.723972603) -> 3.7239726 | S52: =IFERROR(__xludf.DUMMYFUNCTION("""COMPUTED_VALUE"""),6.206712329) -> 6.2067123 | T52: =IFERROR(__xludf.DUMMYFUNCTION("""COMPUTED_VALUE"""),0.9324657534) -> 0.93246575 | U52: =IFERROR(__xludf.DUMMYFUNCTION("""COMPUTED_VALUE"""),0.3875342466) -> 0.38753425 | V52: =IFERROR(__xludf.DUMMYFUNCTION("""COMPUTED_VALUE"""),0.4652092312) -> 0.46520923 | W52: =IFERROR(__xludf.DUMMYFUNCTION("""COMPUTED_VALUE"""),0.867005814) -> 0.86700581 | X52: =IFERROR(__xludf.DUMMYFUNCTION("""COMPUTED_VALUE"""),1.782739726) -> 1.7827397 | Y52: =IFERROR(__xludf.DUMMYFUNCTION("""COMPUTED_VALUE"""),1.3649730664816977) -> 1.3649731 | Z52: =IFERROR(__xludf.DUMMYFUNCTION("""COMPUTED_VALUE"""),1.2082142543216625) -> 1.2082143 | AA52: =IFERROR(__xludf.DUMMYFUNCTION("""COMPUTED_VALUE"""),-0.9246499771012997) -> -0.92464998 | AB52: =IFERROR(__xludf.DUMMYFUNCTION("""COMPUTED_VALUE"""),1.032428721237999) -> 1.0324287 | AC52: =IFERROR(__xludf.DUMMYFUNCTION("""COMPUTED_VALUE"""),-0.14402493048367) -> -0.14402493 | AD52: =IFERROR(__xludf.DUMMYFUNCTION("""COMPUTED_VALUE"""),-0.644133055179798) -> -0.64413306 | AE52: =IFERROR(__xludf.DUMMYFUNCTION("""COMPUTED_VALUE"""),-0.7343700627300155) -> -0.73437006 | AF52: =IFERROR(__xludf.DUMMYFUNCTION("""COMPUTED_VALUE"""),1.0969769503454612) -> 1.0969769 | AG52: =IFERROR(__xludf.DUMMYFUNCTION("""COMPUTED_VALUE"""),0.0) -> 0
A53: =VLOOKUP($F53,UpdateHashtag!$V$3:$Y$32,COLUMN(B$15),0) -> 4 | B53: =VLOOKUP($F53,UpdateHashtag!$V$3:$Y$32,COLUMN(C$13),0) -> 4 | C53: =VLOOKUP($F53,UpdateHashtag!$V$3:$Y$32,COLUMN(D$13),0) -> 3 | D53: =SUM(A53:C53) -> 11 | F53: =IF(VLOOKUP(J53,PasteHashtag!$C$2:$P1015,3,)="BRO","BKN",IF(VLOOKUP(J53,PasteHashtag!$C$2:$P1015,3,)="OKL","OKC",VLOOKUP(J53,PasteHashtag!$C$2:$P1015,3,))) -> MEM | G53: 34 | H53: =IFERROR(__xludf.DUMMYFUNCTION("""COMPUTED_VALUE"""),35.0) -> 35 | I53: =IFERROR(__xludf.DUMMYFUNCTION("""COMPUTED_VALUE"""),37.3) -> 37.3 | J53: =IFERROR(__xludf.DUMMYFUNCTION("""COMPUTED_VALUE"""),"Jaren Jackson Jr.") -> Jaren Jackson Jr. | K53: =IFERROR(__xludf.DUMMYFUNCTION("""COMPUTED_VALUE"""),58.0) -> 58 | L53: =IFERROR(__xludf.DUMMYFUNCTION("""COMPUTED_VALUE"""),"PF,C") -> PF,C | M53: =IFERROR(__xludf.DUMMYFUNCTION("""COMPUTED_VALUE"""),2.1294274104812625) -> 2.1294274 | N53: =IFERROR(__xludf.DUMMYFUNCTION("""COMPUTED_VALUE"""),2.2072524704400673) -> 2.2072525 | O53: =IFERROR(__xludf.DUMMYFUNCTION("""COMPUTED_VALUE"""),0.07782505995880484) -> 0.07782506 | P53: =IFERROR(__xludf.DUMMYFUNCTION("""COMPUTED_VALUE"""),18.67691176) -> 18.676912 | Q53: =IFERROR(__xludf.DUMMYFUNCTION("""COMPUTED_VALUE"""),1.729705882) -> 1.7297059 | R53: =IFERROR(__xludf.DUMMYFUNCTION("""COMPUTED_VALUE"""),6.1875) -> 6.1875 | S53: =IFERROR(__xludf.DUMMYFUNCTION("""COMPUTED_VALUE"""),1.856323529) -> 1.8563235 | T53: =IFERROR(__xludf.DUMMYFUNCTION("""COMPUTED_VALUE"""),1.2375) -> 1.2375 | U53: =IFERROR(__xludf.DUMMYFUNCTION("""COMPUTED_VALUE"""),2.131176471) -> 2.1311765 | V53: =IFERROR(__xludf.DUMMYFUNCTION("""COMPUTED_VALUE"""),0.4709663351) -> 0.47096634 | W53: =IFERROR(__xludf.DUMMYFUNCTION("""COMPUTED_VALUE"""),0.7959958466) -> 0.79599585 | X53: =IFERROR(__xludf.DUMMYFUNCTION("""COMPUTED_VALUE"""),2.0625) -> 2.0625 | Y53: =IFERROR(__xludf.DUMMYFUNCTION("""COMPUTED_VALUE"""),0.2141878782810326) -> 0.21418788 | Z53: =IFERROR(__xludf.DUMMYFUNCTION("""COMPUTED_VALUE"""),-0.018807743433448314) -> -0.018807743 | AA53: =IFERROR(__xludf.DUMMYFUNCTION("""COMPUTED_VALUE"""),0.04082364545181181) -> 0.040823645 | AB53: =IFERROR(__xludf.DUMMYFUNCTION("""COMPUTED_VALUE"""),-0.9432499290149442) -> -0.94324993 | AC53: =IFERROR(__xludf.DUMMYFUNCTION("""COMPUTED_VALUE"""),0.8651239486818252) -> 0.86512395 | AD53: =IFERROR(__xludf.DUMMYFUNCTION("""COMPUTED_VALUE"""),2.4659106039741876) -> 2.4659106 | AE53: =IFERROR(__xludf.DUMMYFUNCTION("""COMPUTED_VALUE"""),-0.43290964108118263) -> -0.43290964 | AF53: =IFERROR(__xludf.DUMMYFUNCTION("""COMPUTED_VALUE"""),0.016173707580785086) -> 0.016173708 | AG53: =IFERROR(__xludf.DUMMYFUNCTION("""COMPUTED_VALUE"""),0.0) -> 0
A54: =VLOOKUP($F54,UpdateHashtag!$V$3:$Y$32,COLUMN(B$15),0) -> 4 | B54: =VLOOKUP($F54,UpdateHashtag!$V$3:$Y$32,COLUMN(C$13),0) -> 3 | C54: =VLOOKUP($F54,UpdateHashtag!$V$3:$Y$32,COLUMN(D$13),0) -> 4 | D54: =SUM(A54:C54) -> 11 | F54: =IF(VLOOKUP(J54,PasteHashtag!$C$2:$P1015,3,)="BRO","BKN",IF(VLOOKUP(J54,PasteHashtag!$C$2:$P1015,3,)="OKL","OKC",VLOOKUP(J54,PasteHashtag!$C$2:$P1015,3,))) -> CLE | G54: 35 | H54: =IFERROR(__xludf.DUMMYFUNCTION("""COMPUTED_VALUE"""),32.0) -> 32 | I54: =IFERROR(__xludf.DUMMYFUNCTION("""COMPUTED_VALUE"""),39.0) -> 39 | J54: =IFERROR(__xludf.DUMMYFUNCTION("""COMPUTED_VALUE"""),"Evan Mobley") -> Evan Mobley | K54: =IFERROR(__xludf.DUMMYFUNCTION("""COMPUTED_VALUE"""),67.0) -> 67 | L54: =IFERROR(__xludf.DUMMYFUNCTION("""COMPUTED_VALUE"""),"PF,C") -> PF,C | M54: =IFERROR(__xludf.DUMMYFUNCTION("""COMPUTED_VALUE"""),2.1101174309394866) -> 2.1101174 | N54: =IFERROR(__xludf.DUMMYFUNCTION("""COMPUTED_VALUE"""),2.112554223501651) -> 2.1125542 | O54: =IFERROR(__xludf.DUMMYFUNCTION("""COMPUTED_VALUE"""),0.002436792562164225) -> 0.0024367926 | P54: =IFERROR(__xludf.DUMMYFUNCTION("""COMPUTED_VALUE"""),18.58328767) -> 18.583288 | Q54: =IFERROR(__xludf.DUMMYFUNCTION("""COMPUTED_VALUE"""),0.73) -> 0.73 | R54: =IFERROR(__xludf.DUMMYFUNCTION("""COMPUTED_VALUE"""),9.52) -> 9.52 | S54: =IFERROR(__xludf.DUMMYFUNCTION("""COMPUTED_VALUE"""),3.943972603) -> 3.9439726 | T54: =IFERROR(__xludf.DUMMYFUNCTION("""COMPUTED_VALUE"""),0.9609589041) -> 0.9609589 | U54: =IFERROR(__xludf.DUMMYFUNCTION("""COMPUTED_VALUE"""),1.554109589) -> 1.5541096 | V54: =IFERROR(__xludf.DUMMYFUNCTION("""COMPUTED_VALUE"""),0.5641756499) -> 0.56417565 | W54: =IFERROR(__xludf.DUMMYFUNCTION("""COMPUTED_VALUE"""),0.7449994047) -> 0.7449994 | X54: =IFERROR(__xludf.DUMMYFUNCTION("""COMPUTED_VALUE"""),1.758493151) -> 1.7584932 | Y54: =IFERROR(__xludf.DUMMYFUNCTION("""COMPUTED_VALUE"""),0.19731160813643003) -> 0.19731161 | Z54: =IFERROR(__xludf.DUMMYFUNCTION("""COMPUTED_VALUE"""),-1.0104445384348693) -> -1.0104445 | AA54: =IFERROR(__xludf.DUMMYFUNCTION("""COMPUTED_VALUE"""),1.3468537107461267) -> 1.3468537 | AB54: =IFERROR(__xludf.DUMMYFUNCTION("""COMPUTED_VALUE"""),0.004831701004452462) -> 0.004831701 | AC54: =IFERROR(__xludf.DUMMYFUNCTION("""COMPUTED_VALUE"""),-0.049760658805007726) -> -0.049760659 | AD54: =IFERROR(__xludf.DUMMYFUNCTION("""COMPUTED_VALUE"""),1.43662651566907) -> 1.4366265 | AE54: =IFERROR(__xludf.DUMMYFUNCTION("""COMPUTED_VALUE"""),0.9952115986273099) -> 0.9952116 | AF54: =IFERROR(__xludf.DUMMYFUNCTION("""COMPUTED_VALUE"""),-0.8080757134418611) -> -0.80807571 | AG54: =IFERROR(__xludf.DUMMYFUNCTION("""COMPUTED_VALUE"""),0.0) -> 0
A55: =VLOOKUP($F55,UpdateHashtag!$V$3:$Y$32,COLUMN(B$15),0) -> 3 | B55: =VLOOKUP($F55,UpdateHashtag!$V$3:$Y$32,COLUMN(C$13),0) -> 4 | C55: =VLOOKUP($F55,UpdateHashtag!$V$3:$Y$32,COLUMN(D$13),0) -> 3 | D55: =SUM(A55:C55) -> 10 | F55: =IF(VLOOKUP(J55,PasteHashtag!$C$2:$P1015,3,)="BRO","BKN",IF(VLOOKUP(J55,PasteHashtag!$C$2:$P1015,3,)="OKL","OKC",VLOOKUP(J55,PasteHashtag!$C$2:$P1015,3,))) -> BOS | G55: 36 | H55: =IFERROR(__xludf.DUMMYFUNCTION("""COMPUTED_VALUE"""),37.0) -> 37 | I55: =IFERROR(__xludf.DUMMYFUNCTION("""COMPUTED_VALUE"""),103.3) -> 103.3 | J55: =IFERROR(__xludf.DUMMYFUNCTION("""COMPUTED_VALUE"""),"Kristaps Porzingis") -> Kristaps Porzingis | K55: =IFERROR(__xludf.DUMMYFUNCTION("""COMPUTED_VALUE"""),68.0) -> 68 | L55: =IFERROR(__xludf.DUMMYFUNCTION("""COMPUTED_VALUE"""),"C") -> C | M55: =IFERROR(__xludf.DUMMYFUNCTION("""COMPUTED_VALUE"""),1.9648311103430747) -> 1.9648311 | N55: =IFERROR(__xludf.DUMMYFUNCTION("""COMPUTED_VALUE"""),1.8856008183699582) -> 1.8856008 | O55: =IFERROR(__xludf.DUMMYFUNCTION("""COMPUTED_VALUE"""),-0.07923029197311648) -> -0.079230292 | P55: =IFERROR(__xludf.DUMMYFUNCTION("""COMPUTED_VALUE"""),18.43694444) -> 18.436944 | Q55: =IFERROR(__xludf.DUMMYFUNCTION("""COMPUTED_VALUE"""),1.805277778) -> 1.8052778 | R55: =IFERROR(__xludf.DUMMYFUNCTION("""COMPUTED_VALUE"""),6.802777778) -> 6.8027778 | S55: =IFERROR(__xludf.DUMMYFUNCTION("""COMPUTED_VALUE"""),1.943611111) -> 1.9436111 | T55: =IFERROR(__xludf.DUMMYFUNCTION("""COMPUTED_VALUE"""),0.7430555556) -> 0.74305556 | U55: =IFERROR(__xludf.DUMMYFUNCTION("""COMPUTED_VALUE"""),1.783333333) -> 1.7833333 | V55: =IFERROR(__xludf.DUMMYFUNCTION("""COMPUTED_VALUE"""),0.5063670087) -> 0.50636701 | W55: =IFERROR(__xludf.DUMMYFUNCTION("""COMPUTED_VALUE"""),0.8670216262) -> 0.86702163 | X55: =IFERROR(__xludf.DUMMYFUNCTION("""COMPUTED_VALUE"""),1.429166667) -> 1.4291667 | Y55: =IFERROR(__xludf.DUMMYFUNCTION("""COMPUTED_VALUE"""),0.1709324157371904) -> 0.17093242 | Z55: =IFERROR(__xludf.DUMMYFUNCTION("""COMPUTED_VALUE"""),0.056154176958274196) -> 0.056154177 | AA55: =IFERROR(__xludf.DUMMYFUNCTION("""COMPUTED_VALUE"""),0.2819553113409285) -> 0.28195531 | AB55: =IFERROR(__xludf.DUMMYFUNCTION("""COMPUTED_VALUE"""),-0.9036092853580823) -> -0.90360929 | AC55: =IFERROR(__xludf.DUMMYFUNCTION("""COMPUTED_VALUE"""),-0.7706532220375559) -> -0.77065322 | AD55: =IFERROR(__xludf.DUMMYFUNCTION("""COMPUTED_VALUE"""),1.8454809478333571) -> 1.8454809 | AE55: =IFERROR(__xludf.DUMMYFUNCTION("""COMPUTED_VALUE"""),0.13583801010857285) -> 0.13583801 | AF55: =IFERROR(__xludf.DUMMYFUNCTION("""COMPUTED_VALUE"""),1.069502463787273) -> 1.0695025 | AG55: =IFERROR(__xludf.DUMMYFUNCTION("""COMPUTED_VALUE"""),0.0) -> 0
A56: =VLOOKUP($F56,UpdateHashtag!$V$3:$Y$32,COLUMN(B$15),0) -> 4 | B56: =VLOOKUP($F56,UpdateHashtag!$V$3:$Y$32,COLUMN(C$13),0) -> 4 | C56: =VLOOKUP($F56,UpdateHashtag!$V$3:$Y$32,COLUMN(D$13),0) -> 4 | D56: =SUM(A56:C56) -> 12 | F56: =IF(VLOOKUP(J56,PasteHashtag!$C$2:$P1015,3,)="BRO","BKN",IF(VLOOKUP(J56,PasteHashtag!$C$2:$P1015,3,)="OKL","OKC",VLOOKUP(J56,PasteHashtag!$C$2:$P1015,3,))) -> MIA | G56: 37 | H56: =IFERROR(__xludf.DUMMYFUNCTION("""COMPUTED_VALUE"""),38.0) -> 38 | I56: =IFERROR(__xludf.DUMMYFUNCTION("""COMPUTED_VALUE"""),46.0) -> 46 | J56: =IFERROR(__xludf.DUMMYFUNCTION("""COMPUTED_VALUE"""),"Jimmy Butler") -> Jimmy Butler | K56: =IFERROR(__xludf.DUMMYFUNCTION("""COMPUTED_VALUE"""),63.0) -> 63 | L56: =IFERROR(__xludf.DUMMYFUNCTION("""COMPUTED_VALUE"""),"PF,C") -> PF,C | M56: =IFERROR(__xludf.DUMMYFUNCTION("""COMPUTED_VALUE"""),1.7687044167560737) -> 1.7687044 | N56: =IFERROR(__xludf.DUMMYFUNCTION("""COMPUTED_VALUE"""),1.727243972014689) -> 1.727244 | O56: =IFERROR(__xludf.DUMMYFUNCTION("""COMPUTED_VALUE"""),-0.04146044474138466) -> -0.041460445 | P56: =IFERROR(__xludf.DUMMYFUNCTION("""COMPUTED_VALUE"""),19.37639344) -> 19.376393 | Q56: =IFERROR(__xludf.DUMMYFUNCTION("""COMPUTED_VALUE"""),0.8672131148) -> 0.86721311 | R56: =IFERROR(__xludf.DUMMYFUNCTION("""COMPUTED_VALUE"""),5.153114754) -> 5.1531148 | S56: =IFERROR(__xludf.DUMMYFUNCTION("""COMPUTED_VALUE"""),5.274098361) -> 5.2740984 | T56: =IFERROR(__xludf.DUMMYFUNCTION("""COMPUTED_VALUE"""),1.440983607) -> 1.4409836 | U56: =IFERROR(__xludf.DUMMYFUNCTION("""COMPUTED_VALUE"""),0.2750819672) -> 0.27508197 | V56: =IFERROR(__xludf.DUMMYFUNCTION("""COMPUTED_VALUE"""),0.4986563192) -> 0.49865632 | W56: =IFERROR(__xludf.DUMMYFUNCTION("""COMPUTED_VALUE"""),0.8470101196) -> 0.84701012 | X56: =IFERROR(__xludf.DUMMYFUNCTION("""COMPUTED_VALUE"""),1.58147541) -> 1.5814754 | Y56: =IFERROR(__xludf.DUMMYFUNCTION("""COMPUTED_VALUE"""),0.34027339529786704) -> 0.3402734 | Z56: =IFERROR(__xludf.DUMMYFUNCTION("""COMPUTED_VALUE"""),-0.8743389339342508) -> -0.87433893 | AA56: =IFERROR(__xludf.DUMMYFUNCTION("""COMPUTED_VALUE"""),-0.36455916936374905) -> -0.36455917 | AB56: =IFERROR(__xludf.DUMMYFUNCTION("""COMPUTED_VALUE"""),0.6088928971513606) -> 0.6088929 | AC56: =IFERROR(__xludf.DUMMYFUNCTION("""COMPUTED_VALUE"""),1.5383114881841586) -> 1.5383115 | AD56: =IFERROR(__xludf.DUMMYFUNCTION("""COMPUTED_VALUE"""),-0.844708318620512) -> -0.84470832 | AE56: =IFERROR(__xludf.DUMMYFUNCTION("""COMPUTED_VALUE"""),0.020504539936560165) -> 0.02050454 | AF56: =IFERROR(__xludf.DUMMYFUNCTION("""COMPUTED_VALUE"""),1.3028680733632545) -> 1.3028681 | AG56: =IFERROR(__xludf.DUMMYFUNCTION("""COMPUTED_VALUE"""),0.0) -> 0
A57: =VLOOKUP($F57,UpdateHashtag!$V$3:$Y$32,COLUMN(B$15),0) -> 3 | B57: =VLOOKUP($F57,UpdateHashtag!$V$3:$Y$32,COLUMN(C$13),0) -> 4 | C57: =VLOOKUP($F57,UpdateHashtag!$V$3:$Y$32,COLUMN(D$13),0) -> 3 | D57: =SUM(A57:C57) -> 10 | F57: =IF(VLOOKUP(J57,PasteHashtag!$C$2:$P1015,3,)="BRO","BKN",IF(VLOOKUP(J57,PasteHashtag!$C$2:$P1015,3,)="OKL","OKC",VLOOKUP(J57,PasteHashtag!$C$2:$P1015,3,))) -> TOR | G57: 38 | H57: =IFERROR(__xludf.DUMMYFUNCTION("""COMPUTED_VALUE"""),41.0) -> 41 | I57: =IFERROR(__xludf.DUMMYFUNCTION("""COMPUTED_VALUE"""),53.8) -> 53.8 | J57: =IFERROR(__xludf.DUMMYFUNCTION("""COMPUTED_VALUE"""),"Immanuel Quickley") -> Immanuel Quickley | K57: =IFERROR(__xludf.DUMMYFUNCTION("""COMPUTED_VALUE"""),65.0) -> 65 | L57: =IFERROR(__xludf.DUMMYFUNCTION("""COMPUTED_VALUE"""),"PG,SG") -> PG,SG | M57: =IFERROR(__xludf.DUMMYFUNCTION("""COMPUTED_VALUE"""),1.6461272906673718) -> 1.6461273 | N57: =IFERROR(__xludf.DUMMYFUNCTION("""COMPUTED_VALUE"""),1.7015614961341547) -> 1.7015615 | O57: =IFERROR(__xludf.DUMMYFUNCTION("""COMPUTED_VALUE"""),0.055434205466782904) -> 0.055434205 | P57: =IFERROR(__xludf.DUMMYFUNCTION("""COMPUTED_VALUE"""),20.93103896) -> 20.931039 | Q57: =IFERROR(__xludf.DUMMYFUNCTION("""COMPUTED_VALUE"""),2.955974026) -> 2.955974 | R57: =IFERROR(__xludf.DUMMYFUNCTION("""COMPUTED_VALUE"""),4.787012987) -> 4.787013 | S57: =IFERROR(__xludf.DUMMYFUNCTION("""COMPUTED_VALUE"""),7.07) -> 7.07 | T57: =IFERROR(__xludf.DUMMYFUNCTION("""COMPUTED_VALUE"""),1.045454545) -> 1.0454545 | U57: =IFERROR(__xludf.DUMMYFUNCTION("""COMPUTED_VALUE"""),0.2188311688) -> 0.21883117 | V57: =IFERROR(__xludf.DUMMYFUNCTION("""COMPUTED_VALUE"""),0.434168524) -> 0.43416852 | W57: =IFERROR(__xludf.DUMMYFUNCTION("""COMPUTED_VALUE"""),0.8440125359) -> 0.84401254 | X57: =IFERROR(__xludf.DUMMYFUNCTION("""COMPUTED_VALUE"""),1.972207792) -> 1.9722078 | Y57: =IFERROR(__xludf.DUMMYFUNCTION("""COMPUTED_VALUE"""),0.6205070165230928) -> 0.62050702 | Z57: =IFERROR(__xludf.DUMMYFUNCTION("""COMPUTED_VALUE"""),1.1975626251151092) -> 1.1975626 | AA57: =IFERROR(__xludf.DUMMYFUNCTION("""COMPUTED_VALUE"""),-0.5080370132225259) -> -0.50803701 | AB57: =IFERROR(__xludf.DUMMYFUNCTION("""COMPUTED_VALUE"""),1.424480811069898) -> 1.4244808 | AC57: =IFERROR(__xludf.DUMMYFUNCTION("""COMPUTED_VALUE"""),0.2297774004753338) -> 0.2297774 | AD57: =IFERROR(__xludf.DUMMYFUNCTION("""COMPUTED_VALUE"""),-0.9450399327774633) -> -0.94503993 | AE57: =IFERROR(__xludf.DUMMYFUNCTION("""COMPUTED_VALUE"""),-1.1671272085234643) -> -1.1671272 | AF57: =IFERROR(__xludf.DUMMYFUNCTION("""COMPUTED_VALUE"""),0.8494377974741747) -> 0.8494378 | AG57: =IFERROR(__xludf.DUMMYFUNCTION("""COMPUTED_VALUE"""),0.0) -> 0
A58: =VLOOKUP($F58,UpdateHashtag!$V$3:$Y$32,COLUMN(B$15),0) -> 4 | B58: =VLOOKUP($F58,UpdateHashtag!$V$3:$Y$32,COLUMN(C$13),0) -> 4 | C58: =VLOOKUP($F58,UpdateHashtag!$V$3:$Y$32,COLUMN(D$13),0) -> 3 | D58: =SUM(A58:C58) -> 11 | F58: =IF(VLOOKUP(J58,PasteHashtag!$C$2:$P1015,3,)="BRO","BKN",IF(VLOOKUP(J58,PasteHashtag!$C$2:$P1015,3,)="OKL","OKC",VLOOKUP(J58,PasteHashtag!$C$2:$P1015,3,))) -> MEM | G58: 39 | H58: =IFERROR(__xludf.DUMMYFUNCTION("""COMPUTED_VALUE"""),40.0) -> 40 | I58: =IFERROR(__xludf.DUMMYFUNCTION("""COMPUTED_VALUE"""),44.1) -> 44.1 | J58: =IFERROR(__xludf.DUMMYFUNCTION("""COMPUTED_VALUE"""),"Desmond Bane") -> Desmond Bane | K58: =IFERROR(__xludf.DUMMYFUNCTION("""COMPUTED_VALUE"""),68.0) -> 68 | L58: =IFERROR(__xludf.DUMMYFUNCTION("""COMPUTED_VALUE"""),"SG,SF") -> SG,SF | M58: =IFERROR(__xludf.DUMMYFUNCTION("""COMPUTED_VALUE"""),1.4725520317509155) -> 1.472552 | N58: =IFERROR(__xludf.DUMMYFUNCTION("""COMPUTED_VALUE"""),1.5834555305859963) -> 1.5834555 | O58: =IFERROR(__xludf.DUMMYFUNCTION("""COMPUTED_VALUE"""),0.11090349883508077) -> 0.1109035 | P58: =IFERROR(__xludf.DUMMYFUNCTION("""COMPUTED_VALUE"""),21.32273973) -> 21.32274 | Q58: =IFERROR(__xludf.DUMMYFUNCTION("""COMPUTED_VALUE"""),2.957671233) -> 2.9576712 | R58: =IFERROR(__xludf.DUMMYFUNCTION("""COMPUTED_VALUE"""),4.887534247) -> 4.8875342 | S58: =IFERROR(__xludf.DUMMYFUNCTION("""COMPUTED_VALUE"""),4.816712329) -> 4.8167123 | T58: =IFERROR(__xludf.DUMMYFUNCTION("""COMPUTED_VALUE"""),0.9191780822) -> 0.91917808 | U58: =IFERROR(__xludf.DUMMYFUNCTION("""COMPUTED_VALUE"""),0.4254794521) -> 0.42547945 | V58: =IFERROR(__xludf.DUMMYFUNCTION("""COMPUTED_VALUE"""),0.474470924) -> 0.47447092 | W58: =IFERROR(__xludf.DUMMYFUNCTION("""COMPUTED_VALUE"""),0.8749848772) -> 0.87498488 | X58: =IFERROR(__xludf.DUMMYFUNCTION("""COMPUTED_VALUE"""),2.195890411) -> 2.1958904 | Y58: =IFERROR(__xludf.DUMMYFUNCTION("""COMPUTED_VALUE"""),0.6911132890152358) -> 0.69111329 | Z58: =IFERROR(__xludf.DUMMYFUNCTION("""COMPUTED_VALUE"""),1.1992461331750672) -> 1.1992461 | AA58: =IFERROR(__xludf.DUMMYFUNCTION("""COMPUTED_VALUE"""),-0.4686420281478773) -> -0.46864203 | AB58: =IFERROR(__xludf.DUMMYFUNCTION("""COMPUTED_VALUE"""),0.40117633206037145) -> 0.40117633 | AC58: =IFERROR(__xludf.DUMMYFUNCTION("""COMPUTED_VALUE"""),-0.18798471089410898) -> -0.18798471 | AD58: =IFERROR(__xludf.DUMMYFUNCTION("""COMPUTED_VALUE"""),-0.5764521719635303) -> -0.57645217 | AE58: =IFERROR(__xludf.DUMMYFUNCTION("""COMPUTED_VALUE"""),-0.4297271198730037) -> -0.42972712 | AF58: =IFERROR(__xludf.DUMMYFUNCTION("""COMPUTED_VALUE"""),0.9547258072138423) -> 0.95472581 | AG58: =IFERROR(__xludf.DUMMYFUNCTION("""COMPUTED_VALUE"""),0.0) -> 0
A59: =VLOOKUP($F59,UpdateHashtag!$V$3:$Y$32,COLUMN(B$15),0) -> 3 | B59: =VLOOKUP($F59,UpdateHashtag!$V$3:$Y$32,COLUMN(C$13),0) -> 4 | C59: =VLOOKUP($F59,UpdateHashtag!$V$3:$Y$32,COLUMN(D$13),0) -> 3 | D59: =SUM(A59:C59) -> 10 | F59: =IF(VLOOKUP(J59,PasteHashtag!$C$2:$P1015,3,)="BRO","BKN",IF(VLOOKUP(J59,PasteHashtag!$C$2:$P1015,3,)="OKL","OKC",VLOOKUP(J59,PasteHashtag!$C$2:$P1015,3,))) -> BOS | G59: 40 | H59: =IFERROR(__xludf.DUMMYFUNCTION("""COMPUTED_VALUE"""),42.0) -> 42 | I59: =IFERROR(__xludf.DUMMYFUNCTION("""COMPUTED_VALUE"""),48.4) -> 48.4 | J59: =IFERROR(__xludf.DUMMYFUNCTION("""COMPUTED_VALUE"""),"Derrick White") -> Derrick White | K59: =IFERROR(__xludf.DUMMYFUNCTION("""COMPUTED_VALUE"""),70.0) -> 70 | L59: =IFERROR(__xludf.DUMMYFUNCTION("""COMPUTED_VALUE"""),"C") -> C | M59: =IFERROR(__xludf.DUMMYFUNCTION("""COMPUTED_VALUE"""),1.4242579331885532) -> 1.4242579 | N59: =IFERROR(__xludf.DUMMYFUNCTION("""COMPUTED_VALUE"""),1.3585544762211246) -> 1.3585545 | O59: =IFERROR(__xludf.DUMMYFUNCTION("""COMPUTED_VALUE"""),-0.06570345696742863) -> -0.065703457 | P59: =IFERROR(__xludf.DUMMYFUNCTION("""COMPUTED_VALUE"""),15.688) -> 15.688 | Q59: =IFERROR(__xludf.DUMMYFUNCTION("""COMPUTED_VALUE"""),2.864857143) -> 2.8648571 | R59: =IFERROR(__xludf.DUMMYFUNCTION("""COMPUTED_VALUE"""),4.312) -> 4.312 | S59: =IFERROR(__xludf.DUMMYFUNCTION("""COMPUTED_VALUE"""),5.39) -> 5.39 | T59: =IFERROR(__xludf.DUMMYFUNCTION("""COMPUTED_VALUE"""),0.9417142857) -> 0.94171429 | U59: =IFERROR(__xludf.DUMMYFUNCTION("""COMPUTED_VALUE"""),1.078) -> 1.078 | V59: =IFERROR(__xludf.DUMMYFUNCTION("""COMPUTED_VALUE"""),0.4605479809) -> 0.46054798 | W59: =IFERROR(__xludf.DUMMYFUNCTION("""COMPUTED_VALUE"""),0.8910332542) -> 0.89103325 | X59: =IFERROR(__xludf.DUMMYFUNCTION("""COMPUTED_VALUE"""),1.483714286) -> 1.4837143 | Y59: =IFERROR(__xludf.DUMMYFUNCTION("""COMPUTED_VALUE"""),-0.3245803201616992) -> -0.32458032 | Z59: =IFERROR(__xludf.DUMMYFUNCTION("""COMPUTED_VALUE"""),1.1071811884790896) -> 1.1071812 | AA59: =IFERROR(__xludf.DUMMYFUNCTION("""COMPUTED_VALUE"""),-0.6941979261789422) -> -0.69419793 | AB59: =IFERROR(__xludf.DUMMYFUNCTION("""COMPUTED_VALUE"""),0.6615282831429813) -> 0.66152828 | AC59: =IFERROR(__xludf.DUMMYFUNCTION("""COMPUTED_VALUE"""),-0.1134278873368731) -> -0.11342789 | AD59: =IFERROR(__xludf.DUMMYFUNCTION("""COMPUTED_VALUE"""),0.5874146833269236) -> 0.58741468 | AE59: =IFERROR(__xludf.DUMMYFUNCTION("""COMPUTED_VALUE"""),-0.5147930781920822) -> -0.51479308 | AF59: =IFERROR(__xludf.DUMMYFUNCTION("""COMPUTED_VALUE"""),0.6494295331417268) -> 0.64942953 | AG59: =IFERROR(__xludf.DUMMYFUNCTION("""COMPUTED_VALUE"""),0.0) -> 0
A60: =VLOOKUP($F60,UpdateHashtag!$V$3:$Y$32,COLUMN(B$15),0) -> 4 | B60: =VLOOKUP($F60,UpdateHashtag!$V$3:$Y$32,COLUMN(C$13),0) -> 2 | C60: =VLOOKUP($F60,UpdateHashtag!$V$3:$Y$32,COLUMN(D$13),0) -> 4 | D60: =SUM(A60:C60) -> 10 | F60: =IF(VLOOKUP(J60,PasteHashtag!$C$2:$P1015,3,)="BRO","BKN",IF(VLOOKUP(J60,PasteHashtag!$C$2:$P1015,3,)="OKL","OKC",VLOOKUP(J60,PasteHashtag!$C$2:$P1015,3,))) -> NO | G60: 41 | H60: =IFERROR(__xludf.DUMMYFUNCTION("""COMPUTED_VALUE"""),39.0) -> 39 | I60: =IFERROR(__xludf.DUMMYFUNCTION("""COMPUTED_VALUE"""),46.6) -> 46.6 | J60: =IFERROR(__xludf.DUMMYFUNCTION("""COMPUTED_VALUE"""),"Zion Williamson") -> Zion Williamson | K60: =IFERROR(__xludf.DUMMYFUNCTION("""COMPUTED_VALUE"""),69.0) -> 69 | L60: =IFERROR(__xludf.DUMMYFUNCTION("""COMPUTED_VALUE"""),"SG") -> SG | M60: =IFERROR(__xludf.DUMMYFUNCTION("""COMPUTED_VALUE"""),1.0409685266674964) -> 1.0409685 | N60: =IFERROR(__xludf.DUMMYFUNCTION("""COMPUTED_VALUE"""),1.3493692830046058) -> 1.3493693 | O60: =IFERROR(__xludf.DUMMYFUNCTION("""COMPUTED_VALUE"""),0.3084007563371094) -> 0.30840076 | P60: =IFERROR(__xludf.DUMMYFUNCTION("""COMPUTED_VALUE"""),24.63276923) -> 24.632769 | Q60: =IFERROR(__xludf.DUMMYFUNCTION("""COMPUTED_VALUE"""),0.09169230769) -> 0.091692308 | R60: =IFERROR(__xludf.DUMMYFUNCTION("""COMPUTED_VALUE"""),6.466) -> 6.466 | S60: =IFERROR(__xludf.DUMMYFUNCTION("""COMPUTED_VALUE"""),5.376923077) -> 5.3769231 | T60: =IFERROR(__xludf.DUMMYFUNCTION("""COMPUTED_VALUE"""),1.361230769) -> 1.3612308 | U60: =IFERROR(__xludf.DUMMYFUNCTION("""COMPUTED_VALUE"""),0.816) -> 0.816 | V60: =IFERROR(__xludf.DUMMYFUNCTION("""COMPUTED_VALUE"""),0.5759092177) -> 0.57590922 | W60: =IFERROR(__xludf.DUMMYFUNCTION("""COMPUTED_VALUE"""),0.7200072636) -> 0.72000726 | X60: =IFERROR(__xludf.DUMMYFUNCTION("""COMPUTED_VALUE"""),2.992307692) -> 2.9923077 | Y60: =IFERROR(__xludf.DUMMYFUNCTION("""COMPUTED_VALUE"""),1.2877647707931048) -> 1.2877648 | Z60: =IFERROR(__xludf.DUMMYFUNCTION("""COMPUTED_VALUE"""),-1.6436001551255808) -> -1.6436002 | AA60: =IFERROR(__xludf.DUMMYFUNCTION("""COMPUTED_VALUE"""),0.1499697439317719) -> 0.14996974 | AB60: =IFERROR(__xludf.DUMMYFUNCTION("""COMPUTED_VALUE"""),0.655589550130865) -> 0.65558955 | AC60: =IFERROR(__xludf.DUMMYFUNCTION("""COMPUTED_VALUE"""),1.274464107193177) -> 1.2744641 | AD60: =IFERROR(__xludf.DUMMYFUNCTION("""COMPUTED_VALUE"""),0.12009895347372276) -> 0.12009895 | AE60: =IFERROR(__xludf.DUMMYFUNCTION("""COMPUTED_VALUE"""),1.5133645463762242) -> 1.5133645 | AF60: =IFERROR(__xludf.DUMMYFUNCTION("""COMPUTED_VALUE"""),-2.008282233768679) -> -2.0082822 | AG60: =IFERROR(__xludf.DUMMYFUNCTION("""COMPUTED_VALUE"""),0.0) -> 0
A61: =VLOOKUP($F61,UpdateHashtag!$V$3:$Y$32,COLUMN(B$15),0) -> 4 | B61: =VLOOKUP($F61,UpdateHashtag!$V$3:$Y$32,COLUMN(C$13),0) -> 3 | C61: =VLOOKUP($F61,UpdateHashtag!$V$3:$Y$32,COLUMN(D$13),0) -> 4 | D61: =SUM(A61:C61) -> 11 | F61: =IF(VLOOKUP(J61,PasteHashtag!$C$2:$P1015,3,)="BRO","BKN",IF(VLOOKUP(J61,PasteHashtag!$C$2:$P1015,3,)="OKL","OKC",VLOOKUP(J61,PasteHashtag!$C$2:$P1015,3,))) -> CLE | G61: 42 | H61: =IFERROR(__xludf.DUMMYFUNCTION("""COMPUTED_VALUE"""),49.0) -> 49 | I61: =IFERROR(__xludf.DUMMYFUNCTION("""COMPUTED_VALUE"""),62.6) -> 62.6 | J61: =IFERROR(__xludf.DUMMYFUNCTION("""COMPUTED_VALUE"""),"Darius Garland") -> Darius Garland | K61: =IFERROR(__xludf.DUMMYFUNCTION("""COMPUTED_VALUE"""),68.0) -> 68 | L61: =IFERROR(__xludf.DUMMYFUNCTION("""COMPUTED_VALUE"""),"PF") -> PF | M61: =IFERROR(__xludf.DUMMYFUNCTION("""COMPUTED_VALUE"""),0.8088117132889285) -> 0.80881171 | N61: =IFERROR(__xludf.DUMMYFUNCTION("""COMPUTED_VALUE"""),1.109273675204225) -> 1.1092737 | O61: =IFERROR(__xludf.DUMMYFUNCTION("""COMPUTED_VALUE"""),0.3004619619152964) -> 0.30046196 | P61: =IFERROR(__xludf.DUMMYFUNCTION("""COMPUTED_VALUE"""),19.48102941) -> 19.481029 | Q61: =IFERROR(__xludf.DUMMYFUNCTION("""COMPUTED_VALUE"""),2.7025) -> 2.7025 | R61: =IFERROR(__xludf.DUMMYFUNCTION("""COMPUTED_VALUE"""),2.805) -> 2.805 | S61: =IFERROR(__xludf.DUMMYFUNCTION("""COMPUTED_VALUE"""),7.503382353) -> 7.5033824 | T61: =IFERROR(__xludf.DUMMYFUNCTION("""COMPUTED_VALUE"""),1.251176471) -> 1.2511765 | U61: =IFERROR(__xludf.DUMMYFUNCTION("""COMPUTED_VALUE"""),0.1410294118) -> 0.14102941 | V61: =IFERROR(__xludf.DUMMYFUNCTION("""COMPUTED_VALUE"""),0.4490716254) -> 0.44907163 | W61: =IFERROR(__xludf.DUMMYFUNCTION("""COMPUTED_VALUE"""),0.8449892557) -> 0.84498926 | X61: =IFERROR(__xludf.DUMMYFUNCTION("""COMPUTED_VALUE"""),2.960294118) -> 2.9602941 | Y61: =IFERROR(__xludf.DUMMYFUNCTION("""COMPUTED_VALUE"""),0.3591346189056218) -> 0.35913462 | Z61: =IFERROR(__xludf.DUMMYFUNCTION("""COMPUTED_VALUE"""),0.946134504820478) -> 0.9461345 | AA61: =IFERROR(__xludf.DUMMYFUNCTION("""COMPUTED_VALUE"""),-1.284801769659372) -> -1.2848018 | AB61: =IFERROR(__xludf.DUMMYFUNCTION("""COMPUTED_VALUE"""),1.621296383558151) -> 1.6212964 | AC61: =IFERROR(__xludf.DUMMYFUNCTION("""COMPUTED_VALUE"""),0.9103700006724652) -> 0.91037 | AD61: =IFERROR(__xludf.DUMMYFUNCTION("""COMPUTED_VALUE"""),-1.0838108673435563) -> -1.0838109 | AE61: =IFERROR(__xludf.DUMMYFUNCTION("""COMPUTED_VALUE"""),-0.8880697137438002) -> -0.88806971 | AF61: =IFERROR(__xludf.DUMMYFUNCTION("""COMPUTED_VALUE"""),0.5290205179942371) -> 0.52902052 | AG61: =IFERROR(__xludf.DUMMYFUNCTION("""COMPUTED_VALUE"""),0.0) -> 0
A62: =VLOOKUP($F62,UpdateHashtag!$V$3:$Y$32,COLUMN(B$15),0) -> 4 | B62: =VLOOKUP($F62,UpdateHashtag!$V$3:$Y$32,COLUMN(C$13),0) -> 3 | C62: =VLOOKUP($F62,UpdateHashtag!$V$3:$Y$32,COLUMN(D$13),0) -> 4 | D62: =SUM(A62:C62) -> 11 | F62: =IF(VLOOKUP(J62,PasteHashtag!$C$2:$P1015,3,)="BRO","BKN",IF(VLOOKUP(J62,PasteHashtag!$C$2:$P1015,3,)="OKL","OKC",VLOOKUP(J62,PasteHashtag!$C$2:$P1015,3,))) -> SAC | G62: 43 | H62: =IFERROR(__xludf.DUMMYFUNCTION("""COMPUTED_VALUE"""),45.0) -> 45 | I62: =IFERROR(__xludf.DUMMYFUNCTION("""COMPUTED_VALUE"""),54.1) -> 54.1 | J62: =IFERROR(__xludf.DUMMYFUNCTION("""COMPUTED_VALUE"""),"DeMar DeRozan") -> DeMar DeRozan | K62: =IFERROR(__xludf.DUMMYFUNCTION("""COMPUTED_VALUE"""),62.0) -> 62 | L62: =IFERROR(__xludf.DUMMYFUNCTION("""COMPUTED_VALUE"""),"SF") -> SF | M62: =IFERROR(__xludf.DUMMYFUNCTION("""COMPUTED_VALUE"""),1.105147830822949) -> 1.1051478 | N62: =IFERROR(__xludf.DUMMYFUNCTION("""COMPUTED_VALUE"""),1.096235503259514) -> 1.0962355 | O62: =IFERROR(__xludf.DUMMYFUNCTION("""COMPUTED_VALUE"""),-0.008912327563435074) -> -0.0089123276 | P62: =IFERROR(__xludf.DUMMYFUNCTION("""COMPUTED_VALUE"""),22.87337662) -> 22.873377 | Q62: =IFERROR(__xludf.DUMMYFUNCTION("""COMPUTED_VALUE"""),0.9087012987) -> 0.9087013 | R62: =IFERROR(__xludf.DUMMYFUNCTION("""COMPUTED_VALUE"""),4.593376623) -> 4.5933766 | S62: =IFERROR(__xludf.DUMMYFUNCTION("""COMPUTED_VALUE"""),4.904805195) -> 4.9048052 | T62: =IFERROR(__xludf.DUMMYFUNCTION("""COMPUTED_VALUE"""),1.08) -> 1.08 | U62: =IFERROR(__xludf.DUMMYFUNCTION("""COMPUTED_VALUE"""),0.4702597403) -> 0.47025974 | V62: =IFERROR(__xludf.DUMMYFUNCTION("""COMPUTED_VALUE"""),0.4843079597) -> 0.48430796 | W62: =IFERROR(__xludf.DUMMYFUNCTION("""COMPUTED_VALUE"""),0.8590049462) -> 0.85900495 | X62: =IFERROR(__xludf.DUMMYFUNCTION("""COMPUTED_VALUE"""),1.712727273) -> 1.7127273 | Y62: =IFERROR(__xludf.DUMMYFUNCTION("""COMPUTED_VALUE"""),0.9706243320793312) -> 0.97062433 | Z62: =IFERROR(__xludf.DUMMYFUNCTION("""COMPUTED_VALUE"""),-0.833185620290923) -> -0.83318562 | AA62: =IFERROR(__xludf.DUMMYFUNCTION("""COMPUTED_VALUE"""),-0.5839244590194571) -> -0.58392446 | AB62: =IFERROR(__xludf.DUMMYFUNCTION("""COMPUTED_VALUE"""),0.44118268611217343) -> 0.44118269 | AC62: =IFERROR(__xludf.DUMMYFUNCTION("""COMPUTED_VALUE"""),0.34406459144516316) -> 0.34406459 | AD62: =IFERROR(__xludf.DUMMYFUNCTION("""COMPUTED_VALUE"""),-0.4965799083634551) -> -0.49657991 | AE62: =IFERROR(__xludf.DUMMYFUNCTION("""COMPUTED_VALUE"""),-0.25191225232023257) -> -0.25191225 | AF62: =IFERROR(__xludf.DUMMYFUNCTION("""COMPUTED_VALUE"""),1.505966133616914) -> 1.5059661 | AG62: =IFERROR(__xludf.DUMMYFUNCTION("""COMPUTED_VALUE"""),0.0) -> 0
A63: =VLOOKUP($F63,UpdateHashtag!$V$3:$Y$32,COLUMN(B$15),0) -> 4 | B63: =VLOOKUP($F63,UpdateHashtag!$V$3:$Y$32,COLUMN(C$13),0) -> 4 | C63: =VLOOKUP($F63,UpdateHashtag!$V$3:$Y$32,COLUMN(D$13),0) -> 4 | D63: =SUM(A63:C63) -> 12 | F63: =IF(VLOOKUP(J63,PasteHashtag!$C$2:$P1015,3,)="BRO","BKN",IF(VLOOKUP(J63,PasteHashtag!$C$2:$P1015,3,)="OKL","OKC",VLOOKUP(J63,PasteHashtag!$C$2:$P1015,3,))) -> MIA | G63: 44 | H63: =IFERROR(__xludf.DUMMYFUNCTION("""COMPUTED_VALUE"""),44.0) -> 44 | I63: =IFERROR(__xludf.DUMMYFUNCTION("""COMPUTED_VALUE"""),32.2) -> 32.2 | J63: =IFERROR(__xludf.DUMMYFUNCTION("""COMPUTED_VALUE"""),"Bam Adebayo") -> Bam Adebayo | K63: =IFERROR(__xludf.DUMMYFUNCTION("""COMPUTED_VALUE"""),72.0) -> 72 | L63: =IFERROR(__xludf.DUMMYFUNCTION("""COMPUTED_VALUE"""),"C") -> C | M63: =IFERROR(__xludf.DUMMYFUNCTION("""COMPUTED_VALUE"""),0.9848735326096558) -> 0.98487353 | N63: =IFERROR(__xludf.DUMMYFUNCTION("""COMPUTED_VALUE"""),1.0948598372816498) -> 1.0948598 | O63: =IFERROR(__xludf.DUMMYFUNCTION("""COMPUTED_VALUE"""),0.109986304671994) -> 0.1099863 | P63: =IFERROR(__xludf.DUMMYFUNCTION("""COMPUTED_VALUE"""),17.94493151) -> 17.944932 | Q63: =IFERROR(__xludf.DUMMYFUNCTION("""COMPUTED_VALUE"""),0.8771232877) -> 0.87712329 | R63: =IFERROR(__xludf.DUMMYFUNCTION("""COMPUTED_VALUE"""),9.344383562) -> 9.3443836 | S63: =IFERROR(__xludf.DUMMYFUNCTION("""COMPUTED_VALUE"""),3.893150685) -> 3.8931507 | T63: =IFERROR(__xludf.DUMMYFUNCTION("""COMPUTED_VALUE"""),1.243013699) -> 1.2430137 | U63: =IFERROR(__xludf.DUMMYFUNCTION("""COMPUTED_VALUE"""),0.8901369863) -> 0.89013699 | V63: =IFERROR(__xludf.DUMMYFUNCTION("""COMPUTED_VALUE"""),0.5157986357) -> 0.51579864 | W63: =IFERROR(__xludf.DUMMYFUNCTION("""COMPUTED_VALUE"""),0.7400019588) -> 0.74000196 | X63: =IFERROR(__xludf.DUMMYFUNCTION("""COMPUTED_VALUE"""),2.192191781) -> 2.1921918 | Y63: =IFERROR(__xludf.DUMMYFUNCTION("""COMPUTED_VALUE"""),0.08224431077064204) -> 0.082244311 | Z63: =IFERROR(__xludf.DUMMYFUNCTION("""COMPUTED_VALUE"""),-0.8645087506079252) -> -0.86450875 | AA63: =IFERROR(__xludf.DUMMYFUNCTION("""COMPUTED_VALUE"""),1.2780284000220776) -> 1.2780284 | AB63: =IFERROR(__xludf.DUMMYFUNCTION("""COMPUTED_VALUE"""),-0.018248484002806153) -> -0.018248484 | AC63: =IFERROR(__xludf.DUMMYFUNCTION("""COMPUTED_VALUE"""),0.8833649928528501) -> 0.88336499 | AD63: =IFERROR(__xludf.DUMMYFUNCTION("""COMPUTED_VALUE"""),0.25233322775578876) -> 0.25233323 | AE63: =IFERROR(__xludf.DUMMYFUNCTION("""COMPUTED_VALUE"""),0.2920723817743216) -> 0.29207238 | AF63: =IFERROR(__xludf.DUMMYFUNCTION("""COMPUTED_VALUE"""),-0.8104262412832989) -> -0.81042624 | AG63: =IFERROR(__xludf.DUMMYFUNCTION("""COMPUTED_VALUE"""),0.0) -> 0
A64: =VLOOKUP($F64,UpdateHashtag!$V$3:$Y$32,COLUMN(B$15),0) -> 4 | B64: =VLOOKUP($F64,UpdateHashtag!$V$3:$Y$32,COLUMN(C$13),0) -> 4 | C64: =VLOOKUP($F64,UpdateHashtag!$V$3:$Y$32,COLUMN(D$13),0) -> 3 | D64: =SUM(A64:C64) -> 11 | F64: =IF(VLOOKUP(J64,PasteHashtag!$C$2:$P1015,3,)="BRO","BKN",IF(VLOOKUP(J64,PasteHashtag!$C$2:$P1015,3,)="OKL","OKC",VLOOKUP(J64,PasteHashtag!$C$2:$P1015,3,))) -> MEM | G64: 45 | H64: =IFERROR(__xludf.DUMMYFUNCTION("""COMPUTED_VALUE"""),48.0) -> 48 | I64: =IFERROR(__xludf.DUMMYFUNCTION("""COMPUTED_VALUE"""),35.2) -> 35.2 | J64: =IFERROR(__xludf.DUMMYFUNCTION("""COMPUTED_VALUE"""),"Ja Morant") -> Ja Morant | K64: =IFERROR(__xludf.DUMMYFUNCTION("""COMPUTED_VALUE"""),73.0) -> 73 | L64: =IFERROR(__xludf.DUMMYFUNCTION("""COMPUTED_VALUE"""),"PG") -> PG | M64: =IFERROR(__xludf.DUMMYFUNCTION("""COMPUTED_VALUE"""),0.6639316044415485) -> 0.6639316 | N64: =IFERROR(__xludf.DUMMYFUNCTION("""COMPUTED_VALUE"""),1.071755243406772) -> 1.0717552 | O64: =IFERROR(__xludf.DUMMYFUNCTION("""COMPUTED_VALUE"""),0.40782363896522356) -> 0.40782364 | P64: =IFERROR(__xludf.DUMMYFUNCTION("""COMPUTED_VALUE"""),24.52617647) -> 24.526176 | Q64: =IFERROR(__xludf.DUMMYFUNCTION("""COMPUTED_VALUE"""),1.453382353) -> 1.4533824 | R64: =IFERROR(__xludf.DUMMYFUNCTION("""COMPUTED_VALUE"""),5.614558824) -> 5.6145588 | S64: =IFERROR(__xludf.DUMMYFUNCTION("""COMPUTED_VALUE"""),8.3125) -> 8.3125 | T64: =IFERROR(__xludf.DUMMYFUNCTION("""COMPUTED_VALUE"""),1.020882353) -> 1.0208824 | U64: =IFERROR(__xludf.DUMMYFUNCTION("""COMPUTED_VALUE"""),0.3602941176) -> 0.36029412 | V64: =IFERROR(__xludf.DUMMYFUNCTION("""COMPUTED_VALUE"""),0.4676800162) -> 0.46768002 | W64: =IFERROR(__xludf.DUMMYFUNCTION("""COMPUTED_VALUE"""),0.7739919185) -> 0.77399192 | X64: =IFERROR(__xludf.DUMMYFUNCTION("""COMPUTED_VALUE"""),3.393235294) -> 3.3932353 | Y64: =IFERROR(__xludf.DUMMYFUNCTION("""COMPUTED_VALUE"""),1.2685508247540156) -> 1.2685508 | Z64: =IFERROR(__xludf.DUMMYFUNCTION("""COMPUTED_VALUE"""),-0.2929009378566478) -> -0.29290094 | AA64: =IFERROR(__xludf.DUMMYFUNCTION("""COMPUTED_VALUE"""),-0.18371600991235357) -> -0.18371601 | AB64: =IFERROR(__xludf.DUMMYFUNCTION("""COMPUTED_VALUE"""),1.98874778484918) -> 1.9887478 | AC64: =IFERROR(__xludf.DUMMYFUNCTION("""COMPUTED_VALUE"""),0.14848488892348735) -> 0.14848489 | AD64: =IFERROR(__xludf.DUMMYFUNCTION("""COMPUTED_VALUE"""),-0.6927198519925093) -> -0.69271985 | AE64: =IFERROR(__xludf.DUMMYFUNCTION("""COMPUTED_VALUE"""),-0.6494751247502945) -> -0.64947512 | AF64: =IFERROR(__xludf.DUMMYFUNCTION("""COMPUTED_VALUE"""),-0.515216330608106) -> -0.51521633 | AG64: =IFERROR(__xludf.DUMMYFUNCTION("""COMPUTED_VALUE"""),0.0) -> 0
A65: =VLOOKUP($F65,UpdateHashtag!$V$3:$Y$32,COLUMN(B$15),0) -> 4 | B65: =VLOOKUP($F65,UpdateHashtag!$V$3:$Y$32,COLUMN(C$13),0) -> 4 | C65: =VLOOKUP($F65,UpdateHashtag!$V$3:$Y$32,COLUMN(D$13),0) -> 4 | D65: =SUM(A65:C65) -> 12 | F65: =IF(VLOOKUP(J65,PasteHashtag!$C$2:$P1015,3,)="BRO","BKN",IF(VLOOKUP(J65,PasteHashtag!$C$2:$P1015,3,)="OKL","OKC",VLOOKUP(J65,PasteHashtag!$C$2:$P1015,3,))) -> HOU | G65: 46 | H65: =IFERROR(__xludf.DUMMYFUNCTION("""COMPUTED_VALUE"""),43.0) -> 43 | I65: =IFERROR(__xludf.DUMMYFUNCTION("""COMPUTED_VALUE"""),27.7) -> 27.7 | J65: =IFERROR(__xludf.DUMMYFUNCTION("""COMPUTED_VALUE"""),"Alperen Sengün") -> Alperen Sengün | K65: =IFERROR(__xludf.DUMMYFUNCTION("""COMPUTED_VALUE"""),55.0) -> 55 | L65: =IFERROR(__xludf.DUMMYFUNCTION("""COMPUTED_VALUE"""),"SF,PF") -> SF,PF | M65: =IFERROR(__xludf.DUMMYFUNCTION("""COMPUTED_VALUE"""),0.7978128523016272) -> 0.79781285 | N65: =IFERROR(__xludf.DUMMYFUNCTION("""COMPUTED_VALUE"""),1.0198666997374608) -> 1.0198667 | O65: =IFERROR(__xludf.DUMMYFUNCTION("""COMPUTED_VALUE"""),0.22205384743583356) -> 0.22205385 | P65: =IFERROR(__xludf.DUMMYFUNCTION("""COMPUTED_VALUE"""),22.21575342) -> 22.215753 | Q65: =IFERROR(__xludf.DUMMYFUNCTION("""COMPUTED_VALUE"""),0.4330136986) -> 0.4330137 | R65: =IFERROR(__xludf.DUMMYFUNCTION("""COMPUTED_VALUE"""),9.860136986) -> 9.860137 | S65: =IFERROR(__xludf.DUMMYFUNCTION("""COMPUTED_VALUE"""),5.207808219) -> 5.2078082 | T65: =IFERROR(__xludf.DUMMYFUNCTION("""COMPUTED_VALUE"""),1.180410959) -> 1.180411 | U65: =IFERROR(__xludf.DUMMYFUNCTION("""COMPUTED_VALUE"""),0.8332876712) -> 0.83328767 | V65: =IFERROR(__xludf.DUMMYFUNCTION("""COMPUTED_VALUE"""),0.5407574959) -> 0.5407575 | W65: =IFERROR(__xludf.DUMMYFUNCTION("""COMPUTED_VALUE"""),0.6940083726) -> 0.69400837 | X65: =IFERROR(__xludf.DUMMYFUNCTION("""COMPUTED_VALUE"""),2.644109589) -> 2.6441096 | Y65: =IFERROR(__xludf.DUMMYFUNCTION("""COMPUTED_VALUE"""),0.8520840421116727) -> 0.85208404 | Z65: =IFERROR(__xludf.DUMMYFUNCTION("""COMPUTED_VALUE"""),-1.305033726497306) -> -1.3050337 | AA65: =IFERROR(__xludf.DUMMYFUNCTION("""COMPUTED_VALUE"""),1.4801557752726362) -> 1.4801558 | AB65: =IFERROR(__xludf.DUMMYFUNCTION("""COMPUTED_VALUE"""),0.5787879974992571) -> 0.578788 | AC65: =IFERROR(__xludf.DUMMYFUNCTION("""COMPUTED_VALUE"""),0.6762555105312382) -> 0.67625551 | AD65: =IFERROR(__xludf.DUMMYFUNCTION("""COMPUTED_VALUE"""),0.1509340705893342) -> 0.15093407 | AE65: =IFERROR(__xludf.DUMMYFUNCTION("""COMPUTED_VALUE"""),0.815294400615669) -> 0.8152944 | AF65: =IFERROR(__xludf.DUMMYFUNCTION("""COMPUTED_VALUE"""),-2.2286113703850403) -> -2.2286114 | AG65: =IFERROR(__xludf.DUMMYFUNCTION("""COMPUTED_VALUE"""),0.0) -> 0
A66: =VLOOKUP($F66,UpdateHashtag!$V$3:$Y$32,COLUMN(B$15),0) -> 4 | B66: =VLOOKUP($F66,UpdateHashtag!$V$3:$Y$32,COLUMN(C$13),0) -> 4 | C66: =VLOOKUP($F66,UpdateHashtag!$V$3:$Y$32,COLUMN(D$13),0) -> 3 | D66: =SUM(A66:C66) -> 11 | F66: =IF(VLOOKUP(J66,PasteHashtag!$C$2:$P1015,3,)="BRO","BKN",IF(VLOOKUP(J66,PasteHashtag!$C$2:$P1015,3,)="OKL","OKC",VLOOKUP(J66,PasteHashtag!$C$2:$P1015,3,))) -> ATL | G66: 47 | H66: =IFERROR(__xludf.DUMMYFUNCTION("""COMPUTED_VALUE"""),47.0) -> 47 | I66: =IFERROR(__xludf.DUMMYFUNCTION("""COMPUTED_VALUE"""),41.4) -> 41.4 | J66: =IFERROR(__xludf.DUMMYFUNCTION("""COMPUTED_VALUE"""),"Jalen Johnson") -> Jalen Johnson | K66: =IFERROR(__xludf.DUMMYFUNCTION("""COMPUTED_VALUE"""),74.0) -> 74 | L66: =IFERROR(__xludf.DUMMYFUNCTION("""COMPUTED_VALUE"""),"C") -> C | M66: =IFERROR(__xludf.DUMMYFUNCTION("""COMPUTED_VALUE"""),0.9736096532581026) -> 0.97360965 | N66: =IFERROR(__xludf.DUMMYFUNCTION("""COMPUTED_VALUE"""),1.0101165134251815) -> 1.0101165 | O66: =IFERROR(__xludf.DUMMYFUNCTION("""COMPUTED_VALUE"""),0.036506860167078936) -> 0.03650686 | P66: =IFERROR(__xludf.DUMMYFUNCTION("""COMPUTED_VALUE"""),19.71161765) -> 19.711618 | Q66: =IFERROR(__xludf.DUMMYFUNCTION("""COMPUTED_VALUE"""),1.545588235) -> 1.5455882 | R66: =IFERROR(__xludf.DUMMYFUNCTION("""COMPUTED_VALUE"""),8.968823529) -> 8.9688235 | S66: =IFERROR(__xludf.DUMMYFUNCTION("""COMPUTED_VALUE"""),4.375) -> 4.375 | T66: =IFERROR(__xludf.DUMMYFUNCTION("""COMPUTED_VALUE"""),1.093823529) -> 1.0938235 | U66: =IFERROR(__xludf.DUMMYFUNCTION("""COMPUTED_VALUE"""),0.8020588235) -> 0.80205882 | V66: =IFERROR(__xludf.DUMMYFUNCTION("""COMPUTED_VALUE"""),0.4891252998) -> 0.4891253 | W66: =IFERROR(__xludf.DUMMYFUNCTION("""COMPUTED_VALUE"""),0.7200090847) -> 0.72000908 | X66: =IFERROR(__xludf.DUMMYFUNCTION("""COMPUTED_VALUE"""),1.895882353) -> 1.8958824 | Y66: =IFERROR(__xludf.DUMMYFUNCTION("""COMPUTED_VALUE"""),0.40069944939325053) -> 0.40069945 | Z66: =IFERROR(__xludf.DUMMYFUNCTION("""COMPUTED_VALUE"""),-0.20143929203354236) -> -0.20143929 | AA66: =IFERROR(__xludf.DUMMYFUNCTION("""COMPUTED_VALUE"""),1.1308437955446804) -> 1.1308438 | AB66: =IFERROR(__xludf.DUMMYFUNCTION("""COMPUTED_VALUE"""),0.2005777975204694) -> 0.2005778 | AC66: =IFERROR(__xludf.DUMMYFUNCTION("""COMPUTED_VALUE"""),0.38979715738473353) -> 0.38979716 | AD66: =IFERROR(__xludf.DUMMYFUNCTION("""COMPUTED_VALUE"""),0.09523280434734965) -> 0.095232804 | AE66: =IFERROR(__xludf.DUMMYFUNCTION("""COMPUTED_VALUE"""),-0.15291042590809184) -> -0.15291043 | AF66: =IFERROR(__xludf.DUMMYFUNCTION("""COMPUTED_VALUE"""),-0.8526847728236681) -> -0.85268477 | AG66: =IFERROR(__xludf.DUMMYFUNCTION("""COMPUTED_VALUE"""),0.0) -> 0
A67: =VLOOKUP($F67,UpdateHashtag!$V$3:$Y$32,COLUMN(B$15),0) -> 2 | B67: =VLOOKUP($F67,UpdateHashtag!$V$3:$Y$32,COLUMN(C$13),0) -> 4 | C67: =VLOOKUP($F67,UpdateHashtag!$V$3:$Y$32,COLUMN(D$13),0) -> 3 | D67: =SUM(A67:C67) -> 9 | F67: =IF(VLOOKUP(J67,PasteHashtag!$C$2:$P1015,3,)="BRO","BKN",IF(VLOOKUP(J67,PasteHashtag!$C$2:$P1015,3,)="OKL","OKC",VLOOKUP(J67,PasteHashtag!$C$2:$P1015,3,))) -> ORL | G67: 48 | H67: =IFERROR(__xludf.DUMMYFUNCTION("""COMPUTED_VALUE"""),46.0) -> 46 | I67: =IFERROR(__xludf.DUMMYFUNCTION("""COMPUTED_VALUE"""),46.1) -> 46.1 | J67: =IFERROR(__xludf.DUMMYFUNCTION("""COMPUTED_VALUE"""),"Franz Wagner") -> Franz Wagner | K67: =IFERROR(__xludf.DUMMYFUNCTION("""COMPUTED_VALUE"""),72.0) -> 72 | L67: =IFERROR(__xludf.DUMMYFUNCTION("""COMPUTED_VALUE"""),"PG") -> PG | M67: =IFERROR(__xludf.DUMMYFUNCTION("""COMPUTED_VALUE"""),0.9021191865089622) -> 0.90211919 | N67: =IFERROR(__xludf.DUMMYFUNCTION("""COMPUTED_VALUE"""),0.8984413509039105) -> 0.89844135 | O67: =IFERROR(__xludf.DUMMYFUNCTION("""COMPUTED_VALUE"""),-0.003677835605051638) -> -0.0036778356 | P67: =IFERROR(__xludf.DUMMYFUNCTION("""COMPUTED_VALUE"""),21.69534247) -> 21.695342 | Q67: =IFERROR(__xludf.DUMMYFUNCTION("""COMPUTED_VALUE"""),1.582054795) -> 1.5820548 | R67: =IFERROR(__xludf.DUMMYFUNCTION("""COMPUTED_VALUE"""),5.201643836) -> 5.2016438 | S67: =IFERROR(__xludf.DUMMYFUNCTION("""COMPUTED_VALUE"""),3.467808219) -> 3.4678082 | T67: =IFERROR(__xludf.DUMMYFUNCTION("""COMPUTED_VALUE"""),1.076027397) -> 1.0760274 | U67: =IFERROR(__xludf.DUMMYFUNCTION("""COMPUTED_VALUE"""),0.3978082192) -> 0.39780822 | V67: =IFERROR(__xludf.DUMMYFUNCTION("""COMPUTED_VALUE"""),0.5151407827) -> 0.51514078 | W67: =IFERROR(__xludf.DUMMYFUNCTION("""COMPUTED_VALUE"""),0.8430037907) -> 0.84300379 | X67: =IFERROR(__xludf.DUMMYFUNCTION("""COMPUTED_VALUE"""),1.733835616) -> 1.7338356 | Y67: =IFERROR(__xludf.DUMMYFUNCTION("""COMPUTED_VALUE"""),0.7582770339110124) -> 0.75827703 | Z67: =IFERROR(__xludf.DUMMYFUNCTION("""COMPUTED_VALUE"""),-0.1652670704489475) -> -0.16526707 | AA67: =IFERROR(__xludf.DUMMYFUNCTION("""COMPUTED_VALUE"""),-0.34554028260211866) -> -0.34554028 | AB67: =IFERROR(__xludf.DUMMYFUNCTION("""COMPUTED_VALUE"""),-0.2114128349964779) -> -0.21141283 | AC67: =IFERROR(__xludf.DUMMYFUNCTION("""COMPUTED_VALUE"""),0.3309219757896937) -> 0.33092198 | AD67: =IFERROR(__xludf.DUMMYFUNCTION("""COMPUTED_VALUE"""),-0.6258079063093371) -> -0.62580791 | AE67: =IFERROR(__xludf.DUMMYFUNCTION("""COMPUTED_VALUE"""),0.3220143282391967) -> 0.32201433 | AF67: =IFERROR(__xludf.DUMMYFUNCTION("""COMPUTED_VALUE"""),0.835256107320889) -> 0.83525611 | AG67: =IFERROR(__xludf.DUMMYFUNCTION("""COMPUTED_VALUE"""),0.0) -> 0
A68: =VLOOKUP($F68,UpdateHashtag!$V$3:$Y$32,COLUMN(B$15),0) -> 3 | B68: =VLOOKUP($F68,UpdateHashtag!$V$3:$Y$32,COLUMN(C$13),0) -> 3 | C68: =VLOOKUP($F68,UpdateHashtag!$V$3:$Y$32,COLUMN(D$13),0) -> 4 | D68: =SUM(A68:C68) -> 10 | F68: =IF(VLOOKUP(J68,PasteHashtag!$C$2:$P1015,3,)="BRO","BKN",IF(VLOOKUP(J68,PasteHashtag!$C$2:$P1015,3,)="OKL","OKC",VLOOKUP(J68,PasteHashtag!$C$2:$P1015,3,))) -> NY | G68: 49 | H68: =IFERROR(__xludf.DUMMYFUNCTION("""COMPUTED_VALUE"""),51.0) -> 51 | I68: =IFERROR(__xludf.DUMMYFUNCTION("""COMPUTED_VALUE"""),82.6) -> 82.6 | J68: =IFERROR(__xludf.DUMMYFUNCTION("""COMPUTED_VALUE"""),"OG Anunoby") -> OG Anunoby | K68: =IFERROR(__xludf.DUMMYFUNCTION("""COMPUTED_VALUE"""),69.0) -> 69 | L68: =IFERROR(__xludf.DUMMYFUNCTION("""COMPUTED_VALUE"""),"SG,SF") -> SG,SF | M68: =IFERROR(__xludf.DUMMYFUNCTION("""COMPUTED_VALUE"""),0.811353023661122) -> 0.81135302 | N68: =IFERROR(__xludf.DUMMYFUNCTION("""COMPUTED_VALUE"""),0.7687244084855955) -> 0.76872441 | O68: =IFERROR(__xludf.DUMMYFUNCTION("""COMPUTED_VALUE"""),-0.04262861517552652) -> -0.042628615 | P68: =IFERROR(__xludf.DUMMYFUNCTION("""COMPUTED_VALUE"""),15.46573529) -> 15.465735 | Q68: =IFERROR(__xludf.DUMMYFUNCTION("""COMPUTED_VALUE"""),1.850735294) -> 1.8507353 | R68: =IFERROR(__xludf.DUMMYFUNCTION("""COMPUTED_VALUE"""),5.183970588) -> 5.1839706 | S68: =IFERROR(__xludf.DUMMYFUNCTION("""COMPUTED_VALUE"""),1.872058824) -> 1.8720588 | T68: =IFERROR(__xludf.DUMMYFUNCTION("""COMPUTED_VALUE"""),1.656029412) -> 1.6560294 | U68: =IFERROR(__xludf.DUMMYFUNCTION("""COMPUTED_VALUE"""),0.8639705882) -> 0.86397059 | V68: =IFERROR(__xludf.DUMMYFUNCTION("""COMPUTED_VALUE"""),0.4973988682) -> 0.49739887 | W68: =IFERROR(__xludf.DUMMYFUNCTION("""COMPUTED_VALUE"""),0.7740148758) -> 0.77401488 | X68: =IFERROR(__xludf.DUMMYFUNCTION("""COMPUTED_VALUE"""),1.576764706) -> 1.5767647 | Y68: =IFERROR(__xludf.DUMMYFUNCTION("""COMPUTED_VALUE"""),-0.36464478743258877) -> -0.36464479 | Z68: =IFERROR(__xludf.DUMMYFUNCTION("""COMPUTED_VALUE"""),0.10124478439251729) -> 0.10124478 | AA68: =IFERROR(__xludf.DUMMYFUNCTION("""COMPUTED_VALUE"""),-0.35246655214132405) -> -0.35246655 | AB68: =IFERROR(__xludf.DUMMYFUNCTION("""COMPUTED_VALUE"""),-0.9361039271709409) -> -0.93610393 | AC68: =IFERROR(__xludf.DUMMYFUNCTION("""COMPUTED_VALUE"""),2.249750402023782) -> 2.2497504 | AD68: =IFERROR(__xludf.DUMMYFUNCTION("""COMPUTED_VALUE"""),0.2056615887262813) -> 0.20566159 | AE68: =IFERROR(__xludf.DUMMYFUNCTION("""COMPUTED_VALUE"""),0.00216693401655425) -> 0.002166934 | AF68: =IFERROR(__xludf.DUMMYFUNCTION("""COMPUTED_VALUE"""),-0.13688403392868534) -> -0.13688403 | AG68: =IFERROR(__xludf.DUMMYFUNCTION("""COMPUTED_VALUE"""),0.0) -> 0
