Workbook

Sheet Draft
B2: Pick | C2: Your Pick | D2: Round 1 | E2: Round 2 | F2: Round 3 | G2: Round 4 | H2: Round 5 | I2: Round 6 | J2: Round 7 | K2: Round 8 | L2: Round 9 | M2: Round 10 | N2: Round 11 | O2: Round 12 | P2: Round 13 | Q2: Round 14
B3: 1 | C3: =IF(B3=Projections!$G$3,TRUE) -> FALSE | D3: Victor Wembanyama | E3: James Harden | F3: Cooper Flagg | G3: Brandon Miller | H3: O.G. Anunoby | I3: Alexandre Sarr | J3: Paul George | K3: Cam Johnson | L3: Jaden McDaniels | M3: Jrue Holiday | N3: Zaccharie Risacher | O3: Nikola Jovic | P3: Alex Caruso
B4: 2 | C4: =IF(B4=Projections!$G$3,TRUE) -> FALSE | D4: Nikola Jokic | E4: Stephen Curry | F4: Jalen Brunson | G4: Julius Randle | H4: Kristaps Porzingis | I4: Jalen Duren | J4: Michael Porter Jr. | K4: PJ Washington | L4: Naz Reid | M4: Klay Thompson | N4: Kyrie Irving | O4: Duncan Robinson | P4: Keon Ellis
B5: 3 | C5: =IF(B5=Projections!$G$3,TRUE) -> FALSE | D5: Shai Gilgeous-Alexander | E5: Alperen Sengun | F5: Pascal Siakam | G5: Nikola Vucevic | H5: Lauri Markkanen | I5: Deandre Ayton | J5: Isaiah Hartenstein | K5: R.J. Barrett | L5: Andrew Wiggins | M5: Jabari Smith Jr. | N5: Collin Sexton | O5: Stephon Castle | P5: Dylan Harper
B6: 4 | C6: =IF(B6=Projections!$G$3,TRUE) -> TRUE | D6: Luka Doncic | E6: Kevin Durant | F6: Bam Adebayo | G6: Kawhi Leonard | H6: Joel Embiid | I6: Matas Buzelis | J6: Jordan Poole | K6: Donovan Clingan | L6: Bobby Portis | M6: Andrew Nembhard | N6: Cason Wallace | O6: Mitchell Robinson | P6: Sam Hauser
B7: 5 | C7: =IF(B7=Projections!$G$3,TRUE) -> FALSE | D7: Giannis Antetokounmpo | E7: Evan Mobley | F7: LeBron James | G7: Dyson Daniels | H7: Rudy Gobert | I7: Miles Bridges | J7: Immanuel Quickley | K7: John Collins | L7: Anfernee Simons | M7: Jonathan Kuminga | N7: Tobias Harris | O7: Chris Boucher | P7: Malik Monk
B8: 6 | C8: =IF(B8=Projections!$G$3,TRUE) -> FALSE | D8: Cade Cunningham | E8: Donovan Mitchell | F8: Scottie Barnes | G8: Austin Reaves | H8: Walker Kessler | I8: Ausar Thompson | J8: Shaedon Sharpe | K8: Draymond Green | L8: Kevin Porter Jr. | M8: Donte DiVincenzo | N8: Jaden Ivey | O8: Santi Aldama | P8: VJ Edgecombe
B9: 7 | C9: =IF(B9=Projections!$G$3,TRUE) -> FALSE | D9: Anthony Edwards | E9: Tyrese Maxey | F9: Jaren Jackson Jr. | G9: Myles Turner | H9: Coby White | I9: Jakob Poeltl | J9: Tari Eason | K9: Cam Thomas | L9: Brandin Podziemski | M9: Bennedict Mathurin | N9: Aaron Nesmith | O9: Cam Whitmore | P9: Taylor Hendricks
B10: 8 | C10: =IF(B10=Projections!$G$3,TRUE) -> FALSE | D10: Karl-Anthony Towns | E10: Jalen Johnson | F10: Franz Wagner | G10: Zion Williamson | H10: Ivica Zubac | I10: Mark Williams | J10: Onyeka Okongwu | K10: C.J. McCollum | L10: Keyonte George | M10: D'Angelo Russell | N10: Isaiah Jackson | O10: Neemias Queta | P10: Gradey Dick
B11: 9 | C11: =IF(B11=Projections!$G$3,TRUE) -> FALSE | D11: Devin Booker | E11: Josh Giddey | F11: Jamal Murray | G11: Ja Morant | H11: Jimmy Butler | I11: Payton Pritchard | J11: Toumani Camara | K11: Jalen Green | L11: Nicolas Claxton | M11: Reed Sheppard | N11: Davion Mitchell | O11: Keegan Murray | P11: Ace Bailey
B12: 10 | C12: =IF(B12=Projections!$G$3,TRUE) -> FALSE | D12: Domantas Sabonis | E12: Jalen Williams | F12: Paolo Banchero | G12: Jaylen Brown | H12: Desmond Bane | I12: Jarrett Allen | J12: Brandon Ingram | K12: Mikal Bridges | L12: Aaron Gordon | M12: Norman Powell | N12: Kel'el Ware | O12: De'Andre Hunter | P12: Dennis Schroder
B13: 11 | C13: =IF(B13=Projections!$G$3,TRUE) -> FALSE | D13: Trae Young | E13: Derrick White | F13: Chet Holmgren | G13: Trey Murphy | H13: Zach LaVine | I13: Tyler Herro | J13: Josh Hart | K13: James Harden | L13: Chris Paul | M13: Jalen Suggs | N13: Brook Lopez | O13: Dereck Lively II | P13: Jerami Grant
B14: 12 | C14: =IF(B14=Projections!$G$3,TRUE) -> FALSE | D14: Anthony Davis | E14: LaMelo Ball | F14: Amen Thompson | G14: De'Aaron Fox | H14: Deni Avdija | I14: DeMar DeRozan | J14: Darius Garland | K14: Bradley Beal | L14: Zach Edey | M14: Devin Vassell | N14: Herb Jones | O14: Miles McBride | P14: Bilal Coulibaly
C16: Pick # | D16: =IF(C3=TRUE,"1",IF(C4=TRUE,"2", IF(C5=True, "3",IF(C6=True, "4",IF(C7=True, "5",IF(C8=True, "6",IF(C9=True, "7",IF(C10=True, "8",IF(C11=True, "9",IF(C12=True, "10",IF(C13=True, "11",IF(C14=True, "12"))))))))))))*1 -> 4 | E16: =IF(C3=TRUE,"24",IF(C4=TRUE,"23", IF(C5=True, "22",IF(C6=True, "21",IF(C7=True, "20",IF(C8=True, "19",IF(C9=True, "18",IF(C10=True, "17",IF(C11=True, "16",IF(C12=True, "15",IF(C13=True, "14",IF(C14=True, "13"))))))))))))*1 -> 21 | F16: =IF(C3=TRUE,"25",IF(C4=TRUE,"26", IF(C5=True, "27",IF(C6=True, "28",IF(C7=True, "29",IF(C8=True, "30",IF(C9=True, "31",IF(C10=True, "32",IF(C11=True, "33",IF(C12=True, "34",IF(C13=True, "35",IF(C14=True, "36"))))))))))))*1 -> 28 | G16: =IF(C3=TRUE,"48",IF(C4=TRUE,"47", IF(C5=True, "46",IF(C6=True, "45",IF(C7=True, "44",IF(C8=True, "43",IF(C9=True, "42",IF(C10=True, "41",IF(C11=True, "40",IF(C12=True, "39",IF(C13=True, "38",IF(C14=True, "37"))))))))))))*1 -> 45 | H16: =IF(C3=TRUE,"49",IF(C4=TRUE,"50", IF(C5=True, "51",IF(C6=True, "52",IF(C7=True, "53",IF(C8=True, "54",IF(C9=True, "55",IF(C10=True, "56",IF(C11=True, "57",IF(C12=True, "58",IF(C13=True, "59",IF(C14=True, "60"))))))))))))*1 -> 52 | I16: =IF(C3=TRUE,"72",IF(C4=TRUE,"71", IF(C5=True, "70",IF(C6=True, "69",IF(C7=True, "68",IF(C8=True, "67",IF(C9=True, "66",IF(C10=True, "65",IF(C11=True, "64",IF(C12=True, "63",IF(C13=True, "62",IF(C14=True, "61"))))))))))))*1 -> 69 | J16: =IF(C3=TRUE,"73",IF(C4=TRUE,"74", IF(C5=True, "75",IF(C6=True, "76",IF(C7=True, "77",IF(C8=True, "78",IF(C9=True, "79",IF(C10=True, "80",IF(C11=True, "81",IF(C12=True, "82",IF(C13=True, "83",IF(C14=True, "84"))))))))))))*1 -> 76 | K16: =IF(C3=TRUE,"96",IF(C4=TRUE,"95", IF(C5=True, "94",IF(C6=True, "93",IF(C7=True, "92",IF(C8=True, "91",IF(C9=True, "90",IF(C10=True, "89",IF(C11=True, "88",IF(C12=True, "87",IF(C13=True, "86",IF(C14=True, "85"))))))))))))*1 -> 93 | L16: =IF(C3=TRUE,"97",IF(C4=TRUE,"98", IF(C5=True, "99",IF(C6=True, "100",IF(C7=True, "101",IF(C8=True, "102",IF(C9=True, "103",IF(C10=True, "104",IF(C11=True, "105",IF(C12=True, "106",IF(C13=True, "107",IF(C14=True, "108"))))))))))))*1 -> 100 | M16: =IF(C3=TRUE,"120",IF(C4=TRUE,"119", IF(C5=True, "118",IF(C6=True, "117",IF(C7=True, "116",IF(C8=True, "115",IF(C9=True, "114",IF(C10=True, "113",IF(C11=True, "112",IF(C12=True, "111",IF(C13=True, "110",IF(C14=True, "109"))))))))))))*1 -> 117 | N16: =IF(C3=TRUE,"121",IF(C4=TRUE,"122", IF(C5=True, "123",IF(C6=True, "124",IF(C7=True, "125",IF(C8=True, "126",IF(C9=True, "127",IF(C10=True, "128",IF(C11=True, "129",IF(C12=True, "130",IF(C13=True, "131",IF(C14=True, "132"))))))))))))*1 -> 124 | O16: =IF(C3=TRUE,"144",IF(C4=TRUE,"143", IF(C5=True, "142",IF(C6=True, "141",IF(C7=True, "140",IF(C8=True, "139",IF(C9=True, "138",IF(C10=True, "137",IF(C11=True, "136",IF(C12=True, "135",IF(C13=True, "134",IF(C14=True, "133"))))))))))))*1 -> 141 | P16: =IF(C3=TRUE,"145",IF(C4=TRUE,"146", IF(C5=True, "147",IF(C6=True, "148",IF(C7=True, "149",IF(C8=True, "150",IF(C9=True, "151",IF(C10=True, "152",IF(C11=True, "153",IF(C12=True, "154",IF(C13=True, "155",IF(C14=True, "156")))))))))))) -> 148 | Q16: =IF(C3=TRUE,"168",IF(C4=TRUE,"167", IF(C5=True, "166",IF(C6=True, "165",IF(C7=True, "164",IF(C8=True, "163",IF(C9=True, "162",IF(C10=True, "161",IF(C11=True, "160",IF(C12=True, "159",IF(C13=True, "158",IF(C14=True, "157")))))))))))) -> 165
C17: 3RR | D17: =D16 -> 4 | E17: =E16 -> 21 | F17: =F16+IF($C$3,11, IF($C$4,9,IF($C$5,7,IF($C$6,5,IF($C$7,3,IF($C$8,1,IF($C$9,-1,IF($C$10,-3,IF($C$11,-5,IF($C$12,-7, IF($C$13,-9, IF($C$14,-11))))))))))))*1 -> 33 | G17: =G16-IF($C$3,11, IF($C$4,9,IF($C$5,7,IF($C$6,5,IF($C$7,3,IF($C$8,1,IF($C$9,-1,IF($C$10,-3,IF($C$11,-5,IF($C$12,-7, IF($C$13,-9, IF($C$14,-11))))))))))))*1 -> 40 | H17: =H16+IF($C$3,11, IF($C$4,9,IF($C$5,7,IF($C$6,5,IF($C$7,3,IF($C$8,1,IF($C$9,-1,IF($C$10,-3,IF($C$11,-5,IF($C$12,-7, IF($C$13,-9, IF($C$14,-11))))))))))))*1 -> 57 | I17: =I16-IF($C$3,11, IF($C$4,9,IF($C$5,7,IF($C$6,5,IF($C$7,3,IF($C$8,1,IF($C$9,-1,IF($C$10,-3,IF($C$11,-5,IF($C$12,-7, IF($C$13,-9, IF($C$14,-11))))))))))))*1 -> 64 | J17: =J16+IF($C$3,11, IF($C$4,9,IF($C$5,7,IF($C$6,5,IF($C$7,3,IF($C$8,1,IF($C$9,-1,IF($C$10,-3,IF($C$11,-5,IF($C$12,-7, IF($C$13,-9, IF($C$14,-11))))))))))))*1 -> 81 | K17: =K16-IF($C$3,11, IF($C$4,9,IF($C$5,7,IF($C$6,5,IF($C$7,3,IF($C$8,1,IF($C$9,-1,IF($C$10,-3,IF($C$11,-5,IF($C$12,-7, IF($C$13,-9, IF($C$14,-11))))))))))))*1 -> 88 | L17: =L16+IF($C$3,11, IF($C$4,9,IF($C$5,7,IF($C$6,5,IF($C$7,3,IF($C$8,1,IF($C$9,-1,IF($C$10,-3,IF($C$11,-5,IF($C$12,-7, IF($C$13,-9, IF($C$14,-11))))))))))))*1 -> 105 | M17: =M16-IF($C$3,11, IF($C$4,9,IF($C$5,7,IF($C$6,5,IF($C$7,3,IF($C$8,1,IF($C$9,-1,IF($C$10,-3,IF($C$11,-5,IF($C$12,-7, IF($C$13,-9, IF($C$14,-11))))))))))))*1 -> 112 | N17: =N16+IF($C$3,11, IF($C$4,9,IF($C$5,7,IF($C$6,5,IF($C$7,3,IF($C$8,1,IF($C$9,-1,IF($C$10,-3,IF($C$11,-5,IF($C$12,-7, IF($C$13,-9, IF($C$14,-11))))))))))))*1 -> 129 | O17: =O16-IF($C$3,11, IF($C$4,9,IF($C$5,7,IF($C$6,5,IF($C$7,3,IF($C$8,1,IF($C$9,-1,IF($C$10,-3,IF($C$11,-5,IF($C$12,-7, IF($C$13,-9, IF($C$14,-11))))))))))))*1 -> 136 | P17: =P16+IF($B$3,11, IF($B$4,9,IF($B$5,7,IF($B$6,5,IF($B$7,3,IF($B$8,1,IF($B$9,-1,IF($B$10,-3,IF($B$11,-5,IF($B$12,-7, IF($B$13,-9, IF($B$14,-11)))))))))))) -> 159 | Q17: =Q16-IF($B$3,11, IF($B$4,9,IF($B$5,7,IF($B$6,5,IF($B$7,3,IF($B$8,1,IF($B$9,-1,IF($B$10,-3,IF($B$11,-5,IF($B$12,-7, IF($B$13,-9, IF($B$14,-11)))))))))))) -> 154
D19: MAKE A COPY
D20: File -> Make a copy

Sheet Projections
I2: Pick # | J2: Team | K2: PTS | L2: 3P | M2: REB | N2: AST | O2: STL | P2: BLK | Q2: FG% | R2: FT% | S2: TO | T2: Cats Won | U2: Winrate | V2: Punt Sum | W2: Total LeagV | X2: ="Round "&Column(A1) -> Round 1 | Z2: ="Round "&Column(B1) -> Round 2 | AB2: ="Round "&Column(C1) -> Round 3 | AD2: ="Round "&Column(D1) -> Round 4 | AF2: ="Round "&Column(E1) -> Round 5 | AH2: ="Round "&Column(F1) -> Round 6 | AJ2: ="Round "&Column(G1) -> Round 7 | AL2: ="Round "&Column(P1) -> Round 16 | AN2: ="Round "&Column(R1) -> Round 18 | AP2: ="Round "&Column(T1) -> Round 20 | AR2: ="Round "&Column(V1) -> Round 22 | AT2: ="Round "&Column(Y1) -> Round 25 | AV2: ="Round "&Column(AA1) -> Round 27 | AX2: ="Round "&Column(H1) -> Round 8 | AY2: ="Round "&Column(I1) -> Round 9 | AZ2: ="Round "&Column(J1) -> Round 10 | BA2: ="Round "&Column(K1) -> Round 11 | BB2: ="Round "&Column(L1) -> Round 12 | BC2: ="Round "&Column(M1) -> Round 13 | BD2: ="Round "&Column(N1) -> Round 14 | BE2: =Draft!AK3 | BF2: =Draft!AL3 | BG2: =Draft!AM3 | BH2: =Draft!AN3 | BI2: =Draft!AO3
F3: Your Pick # | G3: 4 | I3: =Draft!C3 -> FALSE | J3: 1 | K3: ='All Teams'!E18 -> -34.708945 | L3: ='All Teams'!F18 -> -19.147552 | M3: ='All Teams'!G18 -> -26.18659 | N3: ='All Teams'!H18 -> -19.725229 | O3: ='All Teams'!I18 -> -35.642096 | P3: ='All Teams'!J18 -> -14.620014 | Q3: ='All Teams'!K18 -> -5.2478343 | R3: ='All Teams'!L18 -> 2.9962745 | S3: ='All Teams'!M18 -> 19.080076 | T3: {=if(Team!D$1=$J3,"-", countif(indirect(address(row($J$2)+ VLOOKUP(Team!D$1,$J$3:$J$14,1),COLUMN($K$2))):indirect(address(row($J$2)+ VLOOKUP(Team!D$1,$J$3:$J$14,1),COLUMN($S$2)))>indirect(address(row($J3),COLUMN($K$2))):indirect(address(row($J3),COLUMN($S$2))),TRUE()))} -> 7 | U3: =SUM(AL$22:AL$33)/99 -> 0.50505051 | V3: =SUMIF(K3:R3,">-2.5") -> 2.9962745 | W3: ='All Teams'!N18 -> 20.181353 | X3: =Draft!D3 -> Victor Wembanyama | Z3: =Draft!E3 -> James Harden | AB3: =Draft!F3 -> Cooper Flagg | AD3: =Draft!G3 -> Brandon Miller | AF3: =Draft!H3 -> O.G. Anunoby | AH3: =Draft!I3 -> Alexandre Sarr | AJ3: =Draft!J3 -> Paul George | AL3: =Draft!R4 | AM3: =Draft!S4 | AN3: =Draft!T4 | AO3: =Draft!U4 | AP3: =Draft!V4 | AQ3: =Draft!W4 | AR3: =Draft!X4 | AS3: =Draft!Y4 | ... AW3: =Draft!AC4 | AX3: =Draft!K3 -> Cam Johnson | AY3: =Draft!L3 -> Jaden McDaniels | AZ3: =Draft!M3 -> Jrue Holiday | BA3: =Draft!N3 -> Zaccharie Risacher | BB3: =Draft!O3 -> Nikola Jovic | BC3: =Draft!P3 -> Alex Caruso | BD3: =Draft!AJ4 | BE3: =Draft!AK4 | BF3: =Draft!AL4 | BG3: =Draft!AM4 | BH3: =Draft!AN4 | BI3: =Draft!AO4
I4: =Draft!C4 -> FALSE | J4: 2 | K4: ='All Teams'!E35 -> -37.864303 | L4: ='All Teams'!F35 -> -20.888239 | M4: ='All Teams'!G35 -> -28.567189 | N4: ='All Teams'!H35 -> -21.518432 | O4: ='All Teams'!I35 -> -38.882286 | P4: ='All Teams'!J35 -> -15.949106 | Q4: ='All Teams'!K35 -> -0.72657459 | R4: ='All Teams'!L35 -> 4.6952454 | S4: ='All Teams'!M35 -> 20.814628 | T4: {=if(Team!D$1=$J4,"-", countif(indirect(address(row($J$2)+ VLOOKUP(Team!D$1,$J$3:$J$14,1),COLUMN($K$2))):indirect(address(row($J$2)+ VLOOKUP(Team!D$1,$J$3:$J$14,1),COLUMN($S$2)))>indirect(address(row($J4),COLUMN($K$2))):indirect(address(row($J4),COLUMN($S$2))),TRUE()))} -> 6 | U4: =SUM(AM$22:AM$33)/99 -> 0.22222222 | V4: =SUMIF(K4:R4,">-2.5") -> 3.9686708 | W4: ='All Teams'!N35 -> 28.059191 | X4: =Draft!D4 -> Nikola Jokic | Z4: =Draft!E4 -> Stephen Curry | AB4: =Draft!F4 -> Jalen Brunson | AD4: =Draft!G4 -> Julius Randle | AF4: =Draft!H4 -> Kristaps Porzingis | AH4: =Draft!I4 -> Jalen Duren | AJ4: =Draft!J4 -> Michael Porter Jr. | AL4: =Draft!R5 | AM4: =Draft!S5 | AN4: =Draft!T5 | AO4: =Draft!U5 | AP4: =Draft!V5 | AQ4: =Draft!W5 | AR4: =Draft!X5 | AS4: =Draft!Y5 | ... AU4: =Draft!AA5 | AW4: =Draft!AC5 | AX4: =Draft!K4 -> PJ Washington | AY4: =Draft!L4 -> Naz Reid | AZ4: =Draft!M4 -> Klay Thompson | BA4: =Draft!N4 -> Kyrie Irving | BB4: =Draft!O4 -> Duncan Robinson | BC4: =Draft!P4 -> Keon Ellis | BD4: =Draft!AJ5 | BE4: =Draft!AK5 | BF4: =Draft!AL5 | BG4: =Draft!AM5 | BH4: =Draft!AN5 | BI4: =Draft!AO5
F5: Next Pick Simulation | I5: =Draft!C5 -> FALSE | J5: 3 | K5: ='All Teams'!E52 -> -37.864303 | L5: ='All Teams'!F52 -> -20.888239 | M5: ='All Teams'!G52 -> -28.567189 | N5: ='All Teams'!H52 -> -21.518432 | O5: ='All Teams'!I52 -> -38.882286 | P5: ='All Teams'!J52 -> -15.949106 | Q5: ='All Teams'!K52 -> 2.1706373 | R5: ='All Teams'!L52 -> 2.9487046 | S5: ='All Teams'!M52 -> 20.814628 | T5: {=if(Team!D$1=$J5,"-", countif(indirect(address(row($J$2)+ VLOOKUP(Team!D$1,$J$3:$J$14,1),COLUMN($K$2))):indirect(address(row($J$2)+ VLOOKUP(Team!D$1,$J$3:$J$14,1),COLUMN($S$2)))>indirect(address(row($J5),COLUMN($K$2))):indirect(address(row($J5),COLUMN($S$2))),TRUE()))} -> 7 | U5: =SUM(AN$22:AN$33)/99 -> 0.23232323 | V5: =SUMIF(K5:R5,">-2.5") -> 5.1193419 | W5: ='All Teams'!N52 -> 11.268646 | X5: =Draft!D5 -> Shai Gilgeous-Alexander | Z5: =Draft!E5 -> Alperen Sengun | AB5: =Draft!F5 -> Pascal Siakam | AD5: =Draft!G5 -> Nikola Vucevic | AF5: =Draft!H5 -> Lauri Markkanen | AH5: =Draft!I5 -> Deandre Ayton | AJ5: =Draft!J5 -> Isaiah Hartenstein | AL5: =Draft!R6 | AM5: =Draft!S6 | AN5: =Draft!T6 | AO5: =Draft!U6 | AP5: =Draft!V6 | AQ5: =Draft!W6 | AR5: =Draft!X6 | AS5: =Draft!Y6 | ... AW5: =Draft!AC6 | AX5: =Draft!K5 -> R.J. Barrett | AY5: =Draft!L5 -> Andrew Wiggins | AZ5: =Draft!M5 -> Jabari Smith Jr. | BA5: =Draft!N5 -> Collin Sexton | BB5: =Draft!O5 -> Stephon Castle | BC5: =Draft!P5 -> Dylan Harper | BD5: =Draft!AJ6 | BE5: =Draft!AK6 | BF5: =Draft!AL6 | BG5: =Draft!AM6 | BH5: =Draft!AN6 | BI5: =Draft!AO6
F6: Round # | G6: 1 | I6: =Draft!C6 -> TRUE | J6: 4 | K6: ='All Teams'!E69 -> 0.50530601 | L6: ='All Teams'!F69 -> 1.4432671 | M6: ='All Teams'!G69 -> -0.5994361 | N6: ='All Teams'!H69 -> 1.1477191 | O6: ='All Teams'!I69 -> -1.2315582 | P6: ='All Teams'!J69 -> -4.8151532 | Q6: ='All Teams'!K69 -> -4.2549158 | R6: ='All Teams'!L69 -> 2.9594596 | S6: ='All Teams'!M69 -> -3.1538368 | T6: {=if(Team!D$1=$J6,"-", countif(indirect(address(row($J$2)+ VLOOKUP(Team!D$1,$J$3:$J$14,1),COLUMN($K$2))):indirect(address(row($J$2)+ VLOOKUP(Team!D$1,$J$3:$J$14,1),COLUMN($S$2)))>indirect(address(row($J6),COLUMN($K$2))):indirect(address(row($J6),COLUMN($S$2))),TRUE()))} -> - | U6: =SUM(AO$22:AO$33)/99 -> 0.74747475 | V6: =SUMIF(K6:R6,">-2.5") -> 4.2247575 | W6: ='All Teams'!N69 -> 8.7608866 | X6: =Draft!D6 -> Luka Doncic | Z6: =Draft!E6 -> Kevin Durant | AB6: =Draft!F6 -> Bam Adebayo | AD6: =Draft!G6 -> Kawhi Leonard | AF6: =Draft!H6 -> Joel Embiid | AH6: =Draft!I6 -> Matas Buzelis | AJ6: =Draft!J6 -> Jordan Poole | AL6: =Draft!R7 | AM6: =Draft!S7 | AN6: =Draft!T7 | AO6: =Draft!U7 | AP6: =Draft!V7 | AQ6: =Draft!W7 | AR6: =Draft!X7 | AS6: =Draft!Y7 | ... AW6: =Draft!AC7 | AX6: =Draft!K6 -> Donovan Clingan | AY6: =Draft!L6 -> Bobby Portis | AZ6: =Draft!M6 -> Andrew Nembhard | BA6: =Draft!N6 -> Cason Wallace | BB6: =Draft!O6 -> Mitchell Robinson | BC6: =Draft!P6 -> Sam Hauser | BD6: =Draft!AJ7 | BE6: =Draft!AK7 | BF6: =Draft!AL7 | BG6: =Draft!AM7 | BH6: =Draft!AN7 | BI6: =Draft!AO7
F7: T.J. McConnell | I7: =Draft!C7 -> FALSE | J7: 5 | K7: ='All Teams'!E86 -> -37.864303 | L7: ='All Teams'!F86 -> -20.888239 | M7: ='All Teams'!G86 -> -28.567189 | N7: ='All Teams'!H86 -> -21.518432 | O7: ='All Teams'!I86 -> -38.882286 | P7: ='All Teams'!J86 -> -15.949106 | Q7: ='All Teams'!K86 -> 4.8228994 | R7: ='All Teams'!L86 -> -8.293296 | S7: ='All Teams'!M86 -> 20.814628 | T7: {=if(Team!D$1=$J7,"-", countif(indirect(address(row($J$2)+ VLOOKUP(Team!D$1,$J$3:$J$14,1),COLUMN($K$2))):indirect(address(row($J$2)+ VLOOKUP(Team!D$1,$J$3:$J$14,1),COLUMN($S$2)))>indirect(address(row($J7),COLUMN($K$2))):indirect(address(row($J7),COLUMN($S$2))),TRUE()))} -> 7 | U7: =SUM(AP$22:AP$33)/99 -> 0.17171717 | V7: =SUMIF(K7:R7,">-2.5") -> 4.8228994 | W7: ='All Teams'!N86 -> 16.234371 | X7: =Draft!D7 -> Giannis Antetokounmpo | Z7: =Draft!E7 -> Evan Mobley | AB7: =Draft!F7 -> LeBron James | AD7: =Draft!G7 -> Dyson Daniels | AF7: =Draft!H7 -> Rudy Gobert | AH7: =Draft!I7 -> Miles Bridges | AJ7: =Draft!J7 -> Immanuel Quickley | AL7: =Draft!R8 | AM7: =Draft!S8 | AN7: =Draft!T8 | AO7: =Draft!U8 | AP7: =Draft!V8 | AQ7: =Draft!W8 | AR7: =Draft!X8 | AS7: =Draft!Y8 | ... AW7: =Draft!AC8 | AX7: =Draft!K7 -> John Collins | AY7: =Draft!L7 -> Anfernee Simons | AZ7: =Draft!M7 -> Jonathan Kuminga | BA7: =Draft!N7 -> Tobias Harris | BB7: =Draft!O7 -> Chris Boucher | BC7: =Draft!P7 -> Malik Monk | BD7: =Draft!AJ8 | BE7: =Draft!AK8 | BF7: =Draft!AL8 | BG7: =Draft!AM8 | BH7: =Draft!AN8 | BI7: =Draft!AO8
I8: =Draft!C8 -> FALSE | J8: 6 | K8: ='All Teams'!E103 -> -37.864303 | L8: ='All Teams'!F103 -> -20.888239 | M8: ='All Teams'!G103 -> -28.567189 | N8: ='All Teams'!H103 -> -21.518432 | O8: ='All Teams'!I103 -> -38.882286 | P8: ='All Teams'!J103 -> -15.949106 | Q8: ='All Teams'!K103 -> -4.3715673 | R8: ='All Teams'!L103 -> -1.1279605 | S8: ='All Teams'!M103 -> 20.814628 | T8: {=if(Team!D$1=$J8,"-", countif(indirect(address(row($J$2)+ VLOOKUP(Team!D$1,$J$3:$J$14,1),COLUMN($K$2))):indirect(address(row($J$2)+ VLOOKUP(Team!D$1,$J$3:$J$14,1),COLUMN($S$2)))>indirect(address(row($J8),COLUMN($K$2))):indirect(address(row($J8),COLUMN($S$2))),TRUE()))} -> 8 | U8: =SUM(AQ$22:AQ$33)/99 -> 0.12121212 | V8: =SUMIF(K8:R8,">-2.5") -> -1.1279605 | W8: ='All Teams'!N103 -> -4.0213622 | X8: =Draft!D8 -> Cade Cunningham | Z8: =Draft!E8 -> Donovan Mitchell | AB8: =Draft!F8 -> Scottie Barnes | AD8: =Draft!G8 -> Austin Reaves | AF8: =Draft!H8 -> Walker Kessler | AH8: =Draft!I8 -> Ausar Thompson | AJ8: =Draft!J8 -> Shaedon Sharpe | AL8: =Draft!R9 | AM8: =Draft!S9 | AN8: =Draft!T9 | AO8: =Draft!U9 | AP8: =Draft!V9 | AQ8: =Draft!W9 | AR8: =Draft!X9 | AS8: =Draft!Y9 | ... AW8: =Draft!AC9 | AX8: =Draft!K8 -> Draymond Green | AY8: =Draft!L8 -> Kevin Porter Jr. | AZ8: =Draft!M8 -> Donte DiVincenzo | BA8: =Draft!N8 -> Jaden Ivey | BB8: =Draft!O8 -> Santi Aldama | BC8: =Draft!P8 -> VJ Edgecombe | BD8: =Draft!AJ9 | BE8: =Draft!AK9 | BF8: =Draft!AL9 | BG8: =Draft!AM9 | BH8: =Draft!AN9 | BI8: =Draft!AO9
I9: =Draft!C9 -> FALSE | J9: 7 | K9: ='All Teams'!E120 -> -5.9528607 | L9: ='All Teams'!F120 -> 0.79635917 | M9: ='All Teams'!G120 -> -2.4038492 | N9: ='All Teams'!H120 -> -3.1350873 | O9: ='All Teams'!I120 -> 6.2369271 | P9: ='All Teams'!J120 -> -1.3810744 | Q9: ='All Teams'!K120 -> -5.2753818 | R9: ='All Teams'!L120 -> 0.18693412 | S9: ='All Teams'!M120 -> -0.35163867 | T9: {=if(Team!D$1=$J9,"-", countif(indirect(address(row($J$2)+ VLOOKUP(Team!D$1,$J$3:$J$14,1),COLUMN($K$2))):indirect(address(row($J$2)+ VLOOKUP(Team!D$1,$J$3:$J$14,1),COLUMN($S$2)))>indirect(address(row($J9),COLUMN($K$2))):indirect(address(row($J9),COLUMN($S$2))),TRUE()))} -> 6 | U9: =SUM(AR$22:AR$33)/99 -> 0.67676768 | V9: =SUMIF(K9:R9,">-2.5") -> 3.4352968 | W9: ='All Teams'!N120 -> 3.3428336 | X9: =Draft!D9 -> Anthony Edwards | Z9: =Draft!E9 -> Tyrese Maxey | AB9: =Draft!F9 -> Jaren Jackson Jr. | AD9: =Draft!G9 -> Myles Turner | AF9: =Draft!H9 -> Coby White | AH9: =Draft!I9 -> Jakob Poeltl | AJ9: =Draft!J9 -> Tari Eason | AL9: =Draft!R10 | AM9: =Draft!S10 | AN9: =Draft!T10 | AO9: =Draft!U10 | AP9: =Draft!V10 | AQ9: =Draft!W10 | AR9: =Draft!X10 | AS9: =Draft!Y10 | ... AW9: =Draft!AC10 | AX9: =Draft!K9 -> Cam Thomas | AY9: =Draft!L9 -> Brandin Podziemski | AZ9: =Draft!M9 -> Bennedict Mathurin | BA9: =Draft!N9 -> Aaron Nesmith | BB9: =Draft!O9 -> Cam Whitmore | BC9: =Draft!P9 -> Taylor Hendricks | BD9: =Draft!AJ10 | BE9: =Draft!AK10 | BF9: =Draft!AL10 | BG9: =Draft!AM10 | BH9: =Draft!AN10 | BI9: =Draft!AO10
I10: =Draft!C10 -> FALSE | J10: 8 | K10: ='All Teams'!E137 -> -8.4999978 | L10: ='All Teams'!F137 -> -8.260352 | M10: ='All Teams'!G137 -> 1.0971044 | N10: ='All Teams'!H137 -> -8.7277946 | O10: ='All Teams'!I137 -> -8.4510939 | P10: ='All Teams'!J137 -> 1.071839 | Q10: ='All Teams'!K137 -> 1.7067832 | R10: ='All Teams'!L137 -> -0.73045859 | S10: ='All Teams'!M137 -> 1.9545952 | T10: {=if(Team!D$1=$J10,"-", countif(indirect(address(row($J$2)+ VLOOKUP(Team!D$1,$J$3:$J$14,1),COLUMN($K$2))):indirect(address(row($J$2)+ VLOOKUP(Team!D$1,$J$3:$J$14,1),COLUMN($S$2)))>indirect(address(row($J10),COLUMN($K$2))):indirect(address(row($J10),COLUMN($S$2))),TRUE()))} -> 5 | U10: =SUM(AS$22:AS$33)/99 -> 0.73737374 | V10: =SUMIF(K10:R10,">-2.5") -> 3.145268 | W10: ='All Teams'!N137 -> -14.61334 | X10: =Draft!D10 -> Karl-Anthony Towns | Z10: =Draft!E10 -> Jalen Johnson | AB10: =Draft!F10 -> Franz Wagner | AD10: =Draft!G10 -> Zion Williamson | AF10: =Draft!H10 -> Ivica Zubac | AH10: =Draft!I10 -> Mark Williams | AJ10: =Draft!J10 -> Onyeka Okongwu | AL10: =Draft!R11 | AM10: =Draft!S11 | AN10: =Draft!T11 | AO10: =Draft!U11 | AP10: =Draft!V11 | AQ10: =Draft!W11 | AR10: =Draft!X11 | AS10: =Draft!Y11 | ... AW10: =Draft!AC11 | AX10: =Draft!K10 -> C.J. McCollum | AY10: =Draft!L10 -> Keyonte George | AZ10: =Draft!M10 -> D'Angelo Russell | BA10: =Draft!N10 -> Isaiah Jackson | BB10: =Draft!O10 -> Neemias Queta | BC10: =Draft!P10 -> Gradey Dick | BD10: =Draft!AJ11 | BE10: =Draft!AK11 | BF10: =Draft!AL11 | BG10: =Draft!AM11 | BH10: =Draft!AN11 | BI10: =Draft!AO11
F11: Input Draft Picks | I11: =Draft!C11 -> FALSE | J11: 9 | K11: ='All Teams'!E154 -> -37.864303 | L11: ='All Teams'!F154 -> -20.888239 | M11: ='All Teams'!G154 -> -28.567189 | N11: ='All Teams'!H154 -> -21.518432 | O11: ='All Teams'!I154 -> -38.882286 | P11: ='All Teams'!J154 -> -15.949106 | Q11: ='All Teams'!K154 -> 1.8485008 | R11: ='All Teams'!L154 -> -1.6771829 | S11: ='All Teams'!M154 -> 20.814628 | T11: {=if(Team!D$1=$J11,"-", countif(indirect(address(row($J$2)+ VLOOKUP(Team!D$1,$J$3:$J$14,1),COLUMN($K$2))):indirect(address(row($J$2)+ VLOOKUP(Team!D$1,$J$3:$J$14,1),COLUMN($S$2)))>indirect(address(row($J11),COLUMN($K$2))):indirect(address(row($J11),COLUMN($S$2))),TRUE()))} -> 7 | U11: =SUM(AT$22:AT$33)/99 -> 0.17171717 | V11: =SUMIF(K11:R11,">-2.5") -> 0.17131787 | W11: ='All Teams'!N154 -> -6.0699979 | X11: =Draft!D11 -> Devin Booker | Z11: =Draft!E11 -> Josh Giddey | AB11: =Draft!F11 -> Jamal Murray | AD11: =Draft!G11 -> Ja Morant | AF11: =Draft!H11 -> Jimmy Butler | AH11: =Draft!I11 -> Payton Pritchard | AJ11: =Draft!J11 -> Toumani Camara | AL11: =Draft!R12 | AM11: =Draft!S12 | AN11: =Draft!T12 | AO11: =Draft!U12 | AP11: =Draft!V12 | AQ11: =Draft!W12 | AR11: =Draft!X12 | AS11: =Draft!Y12 | ... AW11: =Draft!AC12 | AX11: =Draft!K11 -> Jalen Green | AY11: =Draft!L11 -> Nicolas Claxton | AZ11: =Draft!M11 -> Reed Sheppard | BA11: =Draft!N11 -> Davion Mitchell | BB11: =Draft!O11 -> Keegan Murray | BC11: =Draft!P11 -> Ace Bailey | BD11: =Draft!AJ12 | BE11: =Draft!AK12 | BF11: =Draft!AL12 | BG11: =Draft!AM12 | BH11: =Draft!AN12 | BI11: =Draft!AO12
F12: 3RR | G12: TRUE | I12: =Draft!C12 -> FALSE | J12: 10 | K12: ='All Teams'!E171 -> -31.553586 | L12: ='All Teams'!F171 -> -17.406866 | M12: ='All Teams'!G171 -> -23.805991 | N12: ='All Teams'!H171 -> -17.932027 | O12: ='All Teams'!I171 -> -32.401905 | P12: ='All Teams'!J171 -> -13.290922 | Q12: ='All Teams'!K171 -> 1.3061477 | R12: ='All Teams'!L171 -> -5.2055638 | S12: ='All Teams'!M171 -> 17.345524 | T12: {=if(Team!D$1=$J12,"-", countif(indirect(address(row($J$2)+ VLOOKUP(Team!D$1,$J$3:$J$14,1),COLUMN($K$2))):indirect(address(row($J$2)+ VLOOKUP(Team!D$1,$J$3:$J$14,1),COLUMN($S$2)))>indirect(address(row($J12),COLUMN($K$2))):indirect(address(row($J12),COLUMN($S$2))),TRUE()))} -> 7 | U12: =SUM(AU$22:AU$33)/99 -> 0.5959596 | V12: =SUMIF(K12:R12,">-2.5") -> 1.3061477 | W12: ='All Teams'!N171 -> -3.8365097 | X12: =Draft!D12 -> Domantas Sabonis | Z12: =Draft!E12 -> Jalen Williams | AB12: =Draft!F12 -> Paolo Banchero | AD12: =Draft!G12 -> Jaylen Brown | AF12: =Draft!H12 -> Desmond Bane | AH12: =Draft!I12 -> Jarrett Allen | AJ12: =Draft!J12 -> Brandon Ingram | AL12: =Draft!R13 | AM12: =Draft!S13 | AN12: =Draft!T13 | AO12: =Draft!U13 | AP12: =Draft!V13 | AQ12: =Draft!W13 | AR12: =Draft!X13 | AS12: =Draft!Y13 | ... AW12: =Draft!AC13 | AX12: =Draft!K12 -> Mikal Bridges | AY12: =Draft!L12 -> Aaron Gordon | AZ12: =Draft!M12 -> Norman Powell | BA12: =Draft!N12 -> Kel'el Ware | BB12: =Draft!O12 -> De'Andre Hunter | BC12: =Draft!P12 -> Dennis Schroder | BD12: =Draft!AJ13 | BE12: =Draft!AK13 | BF12: =Draft!AL13 | BG12: =Draft!AM13 | BH12: =Draft!AN13 | BI12: =Draft!AO13
F13: Current Pick #1 | G13: 145 | I13: =Draft!C13 -> FALSE | J13: 11 | K13: ='All Teams'!E188 -> -37.864303 | L13: ='All Teams'!F188 -> -20.888239 | M13: ='All Teams'!G188 -> -28.567189 | N13: ='All Teams'!H188 -> -21.518432 | O13: ='All Teams'!I188 -> -38.882286 | P13: ='All Teams'!J188 -> -15.949106 | Q13: ='All Teams'!K188 -> -4.7756018 | R13: ='All Teams'!L188 -> 6.407941 | S13: ='All Teams'!M188 -> 20.814628 | T13: {=if(Team!D$1=$J13,"-", countif(indirect(address(row($J$2)+ VLOOKUP(Team!D$1,$J$3:$J$14,1),COLUMN($K$2))):indirect(address(row($J$2)+ VLOOKUP(Team!D$1,$J$3:$J$14,1),COLUMN($S$2)))>indirect(address(row($J13),COLUMN($K$2))):indirect(address(row($J13),COLUMN($S$2))),TRUE()))} -> 7 | U13: =SUM(AV$22:AV$33)/99 -> 0.19191919 | V13: =SUMIF(K13:R13,">-2.5") -> 6.407941 | W13: ='All Teams'!N188 -> 8.3093883 | X13: =Draft!D13 -> Trae Young | Z13: =Draft!E13 -> Derrick White | AB13: =Draft!F13 -> Chet Holmgren | AD13: =Draft!G13 -> Trey Murphy | AF13: =Draft!H13 -> Zach LaVine | AH13: =Draft!I13 -> Tyler Herro | AJ13: =Draft!J13 -> Josh Hart | AL13: =Draft!R14 | AM13: =Draft!S14 | AN13: =Draft!T14 | AO13: =Draft!U14 | AP13: =Draft!V14 | AQ13: =Draft!W14 | AR13: =Draft!X14 | AS13: =Draft!Y14 | ... AW13: =Draft!AC14 | AX13: =Draft!K13 -> James Harden | AY13: =Draft!L13 -> Chris Paul | AZ13: =Draft!M13 -> Jalen Suggs | BA13: =Draft!N13 -> Brook Lopez | BB13: =Draft!O13 -> Dereck Lively II | BC13: =Draft!P13 -> Jerami Grant | BD13: =Draft!AJ14 | BE13: =Draft!AK14 | BF13: =Draft!AL14 | BG13: =Draft!AM14 | BH13: =Draft!AN14 | BI13: =Draft!AO14
F14: Your Next Pick # | G14: =IFERROR(__xludf.DUMMYFUNCTION("MIN(FILTER(IF(G12,Draft!D17:O17,Draft!D16:O16),IF(G12,Draft!D17:O17,Draft!D16:O16)>G13))"),"#N/A") -> #N/A | I14: =Draft!C14 -> FALSE | J14: 12 | K14: ='All Teams'!E205 -> -34.708945 | L14: ='All Teams'!F205 -> -19.147552 | M14: ='All Teams'!G205 -> -26.18659 | N14: ='All Teams'!H205 -> -19.725229 | O14: ='All Teams'!I205 -> -35.642096 | P14: ='All Teams'!J205 -> -14.620014 | Q14: ='All Teams'!K205 -> -2.5876042 | R14: ='All Teams'!L205 -> -1.0314651 | S14: ='All Teams'!M205 -> 19.080076 | T14: {=if(Team!D$1=$J14,"-", countif(indirect(address(row($J$2)+ VLOOKUP(Team!D$1,$J$3:$J$14,1),COLUMN($K$2))):indirect(address(row($J$2)+ VLOOKUP(Team!D$1,$J$3:$J$14,1),COLUMN($S$2)))>indirect(address(row($J14),COLUMN($K$2))):indirect(address(row($J14),COLUMN($S$2))),TRUE()))} -> 7 | U14: =SUM(AW$22:AW$33)/99 -> 0.49494949 | V14: =SUMIF(K14:R14,">-2.5") -> -1.0314651 | W14: ='All Teams'!N205 -> 5.3315954 | X14: =Draft!D14 -> Anthony Davis | Z14: =Draft!E14 -> LaMelo Ball | AB14: =Draft!F14 -> Amen Thompson | AD14: =Draft!G14 -> De'Aaron Fox | AF14: =Draft!H14 -> Deni Avdija | AH14: =Draft!I14 -> DeMar DeRozan | AJ14: =Draft!J14 -> Darius Garland | AL14: =Draft!R15 | AM14: =Draft!S15 | AN14: =Draft!T15 | AO14: =Draft!U15 | AP14: =Draft!V15 | AQ14: =Draft!W15 | AR14: =Draft!X15 | AS14: =Draft!Y15 | ... AW14: =Draft!AC15 | AX14: =Draft!K14 -> Bradley Beal | AY14: =Draft!L14 -> Zach Edey | AZ14: =Draft!M14 -> Devin Vassell | BA14: =Draft!N14 -> Herb Jones | BB14: =Draft!O14 -> Miles McBride | BC14: =Draft!P14 -> Bilal Coulibaly | BD14: =Draft!AJ15 | BE14: =Draft!AK15 | BF14: =Draft!AL15 | BG14: =Draft!AM15 | BH14: =Draft!AN15 | BI14: =Draft!AO15
F15: Player Name | G15: Ace Bailey | J15: Avg Zscore Available | K15: =SUM(Y20:Y1015)/ COUNT($K$20:$K1015) -> -0.061992885 | L15: =SUM(Z20:Z1015)/ COUNT($K$20:$K1015) -> -0.01751266 | M15: =SUM(AA20:AA1015)/ COUNT($K$20:$K1015) -> -0.016707343 | N15: =SUM(AB20:AB1015)/ COUNT($K$20:$K1015) -> 0.0067793346 | O15: =SUM(AC20:AC1015)/ COUNT($K$20:$K1015) -> 0.091902909 | P15: =SUM(AD20:AD1015)/ COUNT($K$20:$K1015) -> -0.010579725 | Q15: =SUM(AE20:AE1015)/ COUNT($K$20:$K1015) -> -0.1525195 | R15: =SUM(AF20:AF1015)/ COUNT($K$20:$K1015) -> 0.029303554 | S15: =SUM(AG20:AG1015)/ COUNT($K$20:$K1015) -> -0.04611196 | X15: =IF($G$12,Draft!D17,Draft!D16) -> 4 | Z15: =IF($G$12,Draft!E17,Draft!E16) -> 21 | AB15: =IF($G$12,Draft!F17,Draft!F16) -> 33 | AD15: =IF($G$12,Draft!G17,Draft!G16) -> 40 | AF15: =IF($G$12,Draft!H17,Draft!H16) -> 57 | AH15: =IF($G$12,Draft!I17,Draft!I16) -> 64 | AJ15: =IF($G$12,Draft!J17,Draft!J16) -> 81 | AL15: =IF($G$12,Draft!R16,Draft!R16) | AN15: =IF($G$12,Draft!T16,Draft!T16) | AP15: =IF($G$12,Draft!V16,Draft!V16) | AR15: =IF($G$12,Draft!X16,Draft!X16) | AT15: =IF($G$12,Draft!Z16,Draft!Z16) | AV15: =IF($G$12,Draft!AB16,Draft!AB16) | AX15: =IF($G$12,Draft!K17,Draft!K16) -> 88 | AY15: =IF($G$12,Draft!L17,Draft!L16) -> 105 | AZ15: =IF($G$12,Draft!M17,Draft!M16) -> 112 | BA15: =IF($G$12,Draft!N17,Draft!N16) -> 129 | BB15: =IF($G$12,Draft!O17,Draft!O16) -> 136 | BC15: =IF($G$12,Draft!P17,Draft!P16) -> 159 | BD15: =IF($G$12,Draft!Q17,Draft!Q16) -> 154
I16: -1 Cat | J16: -2 Cat | K16: PTS | L16: 3P | M16: REB | N16: AST | O16: STL | P16: BLK | Q16: FG% | R16: FT% | S16: TO | T16: PG | U16: SG | V16: SF | W16: PF | X16: C | AA16: Sort by | AC16: Remove Drafted | AF16: Top | AH16: Projections
I17: TRUE | J17: FALSE | K17: 1 | L17: 1 | M17: 1 | N17: 1 | O17: 1 | P17: 1 | Q17: 1 | R17: 1 | S17: 0.25 | T17: PG | U17: SG | V17: SF | W17: PF | X17: C | AA17: PuntV | AC17: FALSE | AF17: 156 | AH17: HASHTAG
A19: W18 | B19: W19 | C19: W20 | D19: Total | F19: Team | G19: PuntRank | H19: LgRank | I19: ADP | J19: Player | K19: GP | L19: Pos | M19: LeagV | N19: PuntV | O19: Punt+ | P19: PTS | Q19: 3P | R19: REB | S19: AST | T19: STL | U19: BLK | V19: FG% | W19: FT% | X19: TO | Y19: z p/g | Z19: z 3/g | AA19: z r/g | AB19: z a/g | AC19: z s/g | AD19: z b/g | AE19: z fg% | AF19: z ft% | AG19: z to/g
A20: =VLOOKUP($F20,UpdateHashtag!$V$3:$Y$32,COLUMN(B$15),0) -> #N/A | B20: =VLOOKUP($F20,UpdateHashtag!$V$3:$Y$32,COLUMN(C$13),0) -> #N/A | C20: =VLOOKUP($F20,UpdateHashtag!$V$3:$Y$32,COLUMN(D$13),0) -> #N/A | D20: =SUM(A20:C20) -> #N/A | F20: =VLOOKUP(J20,UpdateBBM!$C$2:E1015,3,0) -> SAS | G20: 1 | H20: =IFERROR(__xludf.DUMMYFUNCTION("Filter('NO USAR3'!B5:AA420,IF('NO USAR3'!AB5:AB420="""",FALSE,TRUE),NOT(COUNTIF('NO USAR3'!A5:A200,'NO USAR3'!D5:D420)),IF('NO USAR3'!B5:B420>AF17,FALSE,TRUE))"),1.0) -> 1 | I20: =IFERROR(__xludf.DUMMYFUNCTION("""COMPUTED_VALUE"""),2.0) -> 2 | J20: =IFERROR(__xludf.DUMMYFUNCTION("""COMPUTED_VALUE"""),"Victor Wembanyama") -> Victor Wembanyama | K20: =IFERROR(__xludf.DUMMYFUNCTION("""COMPUTED_VALUE"""),71.0) -> 71 | L20: =IFERROR(__xludf.DUMMYFUNCTION("""COMPUTED_VALUE"""),"C") -> C | M20: =IFERROR(__xludf.DUMMYFUNCTION("""COMPUTED_VALUE"""),10.595392267107387) -> 10.595392 | N20: =IFERROR(__xludf.DUMMYFUNCTION("""COMPUTED_VALUE"""),10.595392267107387) -> 10.595392 | O20: =IFERROR(__xludf.DUMMYFUNCTION("""COMPUTED_VALUE"""),0.0) -> 0 | P20: =IFERROR(__xludf.DUMMYFUNCTION("""COMPUTED_VALUE"""),24.1) -> 24.1 | Q20: =IFERROR(__xludf.DUMMYFUNCTION("""COMPUTED_VALUE"""),2.0) -> 2 | R20: =IFERROR(__xludf.DUMMYFUNCTION("""COMPUTED_VALUE"""),11.6) -> 11.6 | S20: =IFERROR(__xludf.DUMMYFUNCTION("""COMPUTED_VALUE"""),4.4) -> 4.4 | T20: =IFERROR(__xludf.DUMMYFUNCTION("""COMPUTED_VALUE"""),1.4) -> 1.4 | U20: =IFERROR(__xludf.DUMMYFUNCTION("""COMPUTED_VALUE"""),3.9) -> 3.9 | V20: =IFERROR(__xludf.DUMMYFUNCTION("""COMPUTED_VALUE"""),0.473) -> 0.473 | W20: =IFERROR(__xludf.DUMMYFUNCTION("""COMPUTED_VALUE"""),0.802) -> 0.802 | X20: =IFERROR(__xludf.DUMMYFUNCTION("""COMPUTED_VALUE"""),3.4) -> 3.4 | Y20: =IFERROR(__xludf.DUMMYFUNCTION("""COMPUTED_VALUE"""),1.1982586520799683) -> 1.1982587 | Z20: =IFERROR(__xludf.DUMMYFUNCTION("""COMPUTED_VALUE"""),0.2497993995559884) -> 0.2497994 | AA20: =IFERROR(__xludf.DUMMYFUNCTION("""COMPUTED_VALUE"""),2.169659944607731) -> 2.1696599 | AB20: =IFERROR(__xludf.DUMMYFUNCTION("""COMPUTED_VALUE"""),0.2115152388471211) -> 0.21151524 | AC20: =IFERROR(__xludf.DUMMYFUNCTION("""COMPUTED_VALUE"""),1.4068669802785894) -> 1.406867 | AD20: =IFERROR(__xludf.DUMMYFUNCTION("""COMPUTED_VALUE"""),5.628262228999039) -> 5.6282622 | AE20: =IFERROR(__xludf.DUMMYFUNCTION("""COMPUTED_VALUE"""),-0.5205826258886787) -> -0.52058263 | AF20: =IFERROR(__xludf.DUMMYFUNCTION("""COMPUTED_VALUE"""),0.14053098793907753) -> 0.14053099 | AG20: =IFERROR(__xludf.DUMMYFUNCTION("""COMPUTED_VALUE"""),-0.40950116520012636) -> -0.40950117 | AL20: 1 | AM20: 2 | AN20: 3 | AO20: 4 | AP20: 5 | AQ20: 6 | AR20: 7 | AS20: 8 | AT20: 9 | AU20: 10 | AV20: 11 | AW20: 12
A21: =VLOOKUP($F21,UpdateHashtag!$V$3:$Y$32,COLUMN(B$15),0) -> 3 | B21: =VLOOKUP($F21,UpdateHashtag!$V$3:$Y$32,COLUMN(C$13),0) -> 4 | C21: =VLOOKUP($F21,UpdateHashtag!$V$3:$Y$32,COLUMN(D$13),0) -> 3 | D21: =SUM(A21:C21) -> 10 | F21: =VLOOKUP(J21,UpdateBBM!$C$2:E1015,3,0) -> LAL | G21: 2 | H21: =IFERROR(__xludf.DUMMYFUNCTION("""COMPUTED_VALUE"""),2.0) -> 2 | I21: =IFERROR(__xludf.DUMMYFUNCTION("""COMPUTED_VALUE"""),3.8) -> 3.8 | J21: =IFERROR(__xludf.DUMMYFUNCTION("""COMPUTED_VALUE"""),"Luka Doncic") -> Luka Doncic | K21: =IFERROR(__xludf.DUMMYFUNCTION("""COMPUTED_VALUE"""),66.0) -> 66 | L21: =IFERROR(__xludf.DUMMYFUNCTION("""COMPUTED_VALUE"""),"PG,SG") -> PG,SG | M21: =IFERROR(__xludf.DUMMYFUNCTION("""COMPUTED_VALUE"""),10.094731628301643) -> 10.094732 | N21: =IFERROR(__xludf.DUMMYFUNCTION("""COMPUTED_VALUE"""),10.094731628301643) -> 10.094732 | O21: =IFERROR(__xludf.DUMMYFUNCTION("""COMPUTED_VALUE"""),0.0) -> 0 | P21: =IFERROR(__xludf.DUMMYFUNCTION("""COMPUTED_VALUE"""),34.4) -> 34.4 | Q21: =IFERROR(__xludf.DUMMYFUNCTION("""COMPUTED_VALUE"""),4.1) -> 4.1 | R21: =IFERROR(__xludf.DUMMYFUNCTION("""COMPUTED_VALUE"""),9.3) -> 9.3 | S21: =IFERROR(__xludf.DUMMYFUNCTION("""COMPUTED_VALUE"""),9.9) -> 9.9 | T21: =IFERROR(__xludf.DUMMYFUNCTION("""COMPUTED_VALUE"""),1.4) -> 1.4 | U21: =IFERROR(__xludf.DUMMYFUNCTION("""COMPUTED_VALUE"""),0.5) -> 0.5 | V21: =IFERROR(__xludf.DUMMYFUNCTION("""COMPUTED_VALUE"""),0.491) -> 0.491 | W21: =IFERROR(__xludf.DUMMYFUNCTION("""COMPUTED_VALUE"""),0.792) -> 0.792 | X21: =IFERROR(__xludf.DUMMYFUNCTION("""COMPUTED_VALUE"""),3.8) -> 3.8 | Y21: =IFERROR(__xludf.DUMMYFUNCTION("""COMPUTED_VALUE"""),3.05893325429639) -> 3.0589333 | Z21: =IFERROR(__xludf.DUMMYFUNCTION("""COMPUTED_VALUE"""),2.3398096792183596) -> 2.3398097 | AA21: =IFERROR(__xludf.DUMMYFUNCTION("""COMPUTED_VALUE"""),1.2674534087333724) -> 1.2674534 | AB21: =IFERROR(__xludf.DUMMYFUNCTION("""COMPUTED_VALUE"""),2.7174126120644333) -> 2.7174126 | AC21: =IFERROR(__xludf.DUMMYFUNCTION("""COMPUTED_VALUE"""),1.4068669802785894) -> 1.406867 | AD21: =IFERROR(__xludf.DUMMYFUNCTION("""COMPUTED_VALUE"""),-0.4371236407912776) -> -0.43712364 | AE21: =IFERROR(__xludf.DUMMYFUNCTION("""COMPUTED_VALUE"""),-0.15852282562441422) -> -0.15852283 | AF21: =IFERROR(__xludf.DUMMYFUNCTION("""COMPUTED_VALUE"""),-0.1000978398738095) -> -0.10009784 | AG21: =IFERROR(__xludf.DUMMYFUNCTION("""COMPUTED_VALUE"""),-0.508694019104073) -> -0.50869402 | AK21: % Games/Week | AL21: Categories won | AX21: Round | AY21: Player Name | BA21: PTS | BB21: 3P | BC21: REB | BD21: AST | BE21: STL | BF21: BLK | BG21: FG% | BH21: FT% | BI21: TO | BJ21: POS | BK21: Count | BL21: POS
A22: =VLOOKUP($F22,UpdateHashtag!$V$3:$Y$32,COLUMN(B$15),0) -> 3 | B22: =VLOOKUP($F22,UpdateHashtag!$V$3:$Y$32,COLUMN(C$13),0) -> 4 | C22: =VLOOKUP($F22,UpdateHashtag!$V$3:$Y$32,COLUMN(D$13),0) -> 4 | D22: =SUM(A22:C22) -> 11 | F22: =VLOOKUP(J22,UpdateBBM!$C$2:E1015,3,0) -> DEN | G22: 3 | H22: =IFERROR(__xludf.DUMMYFUNCTION("""COMPUTED_VALUE"""),3.0) -> 3 | I22: =IFERROR(__xludf.DUMMYFUNCTION("""COMPUTED_VALUE"""),2.4) -> 2.4 | J22: =IFERROR(__xludf.DUMMYFUNCTION("""COMPUTED_VALUE"""),"Nikola Jokic") -> Nikola Jokic | K22: =IFERROR(__xludf.DUMMYFUNCTION("""COMPUTED_VALUE"""),71.0) -> 71 | L22: =IFERROR(__xludf.DUMMYFUNCTION("""COMPUTED_VALUE"""),"C") -> C | M22: =IFERROR(__xludf.DUMMYFUNCTION("""COMPUTED_VALUE"""),10.047144673140297) -> 10.047145 | N22: =IFERROR(__xludf.DUMMYFUNCTION("""COMPUTED_VALUE"""),10.047144673140297) -> 10.047145 | O22: =IFERROR(__xludf.DUMMYFUNCTION("""COMPUTED_VALUE"""),0.0) -> 0 | P22: =IFERROR(__xludf.DUMMYFUNCTION("""COMPUTED_VALUE"""),26.7) -> 26.7 | Q22: =IFERROR(__xludf.DUMMYFUNCTION("""COMPUTED_VALUE"""),1.1) -> 1.1 | R22: =IFERROR(__xludf.DUMMYFUNCTION("""COMPUTED_VALUE"""),12.1) -> 12.1 | S22: =IFERROR(__xludf.DUMMYFUNCTION("""COMPUTED_VALUE"""),9.0) -> 9 | T22: =IFERROR(__xludf.DUMMYFUNCTION("""COMPUTED_VALUE"""),1.4) -> 1.4 | U22: =IFERROR(__xludf.DUMMYFUNCTION("""COMPUTED_VALUE"""),0.9) -> 0.9 | V22: =IFERROR(__xludf.DUMMYFUNCTION("""COMPUTED_VALUE"""),0.585) -> 0.585 | W22: =IFERROR(__xludf.DUMMYFUNCTION("""COMPUTED_VALUE"""),0.819) -> 0.819 | X22: =IFERROR(__xludf.DUMMYFUNCTION("""COMPUTED_VALUE"""),3.0) -> 3 | Y22: =IFERROR(__xludf.DUMMYFUNCTION("""COMPUTED_VALUE"""),1.66794350312489) -> 1.6679435 | Z22: =IFERROR(__xludf.DUMMYFUNCTION("""COMPUTED_VALUE"""),-0.645919291727885) -> -0.64591929 | AA22: =IFERROR(__xludf.DUMMYFUNCTION("""COMPUTED_VALUE"""),2.3657918002325915) -> 2.3657918 | AB22: =IFERROR(__xludf.DUMMYFUNCTION("""COMPUTED_VALUE"""),2.307356678265237) -> 2.3073567 | AC22: =IFERROR(__xludf.DUMMYFUNCTION("""COMPUTED_VALUE"""),1.4068669802785894) -> 1.406867 | AD22: =IFERROR(__xludf.DUMMYFUNCTION("""COMPUTED_VALUE"""),0.27645116741934783) -> 0.27645117 | AE22: =IFERROR(__xludf.DUMMYFUNCTION("""COMPUTED_VALUE"""),1.8383090470084225) -> 1.838309 | AF22: =IFERROR(__xludf.DUMMYFUNCTION("""COMPUTED_VALUE"""),0.4947338081073987) -> 0.49473381 | AG22: =IFERROR(__xludf.DUMMYFUNCTION("""COMPUTED_VALUE"""),-0.31030831129617975) -> -0.31030831 | AK22: 100 | AL22: {=if(AL$20=$J3,"-", countif(indirect(address(row($J$2)+ VLOOKUP(AL$20,$J$3:$J$14,1),COLUMN($K$4))):indirect(address(row($J$2)+ VLOOKUP(AL$20,$J$3:$J$14,1),COLUMN($S$2)))>indirect(address(row($J3),COLUMN($K$2))):indirect(address(row($J3),COLUMN($S$2))),TRUE()))} -> - | AM22: {=if(AM$20=$J3,"-", countif(indirect(address(row($J$2)+ VLOOKUP(AM$20,$J$3:$J$14,1),COLUMN($K$4))):indirect(address(row($J$2)+ VLOOKUP(AM$20,$J$3:$J$14,1),COLUMN($S$2)))>indirect(address(row($J3),COLUMN($K$2))):indirect(address(row($J3),COLUMN($S$2))),TRUE()))} -> 3 | AN22: {=if(AN$20=$J3,"-", countif(indirect(address(row($J$2)+ VLOOKUP(AN$20,$J$3:$J$14,1),COLUMN($K$4))):indirect(address(row($J$2)+ VLOOKUP(AN$20,$J$3:$J$14,1),COLUMN($S$2)))>indirect(address(row($J3),COLUMN($K$2))):indirect(address(row($J3),COLUMN($S$2))),TRUE()))} -> 2 | AO22: {=if(AO$20=$J3,"-", countif(indirect(address(row($J$2)+ VLOOKUP(AO$20,$J$3:$J$14,1),COLUMN($K$4))):indirect(address(row($J$2)+ VLOOKUP(AO$20,$J$3:$J$14,1),COLUMN($S$2)))>indirect(address(row($J3),COLUMN($K$2))):indirect(address(row($J3),COLUMN($S$2))),TRUE()))} -> 7 | AP22: {=if(AP$20=$J3,"-", countif(indirect(address(row($J$2)+ VLOOKUP(AP$20,$J$3:$J$14,1),COLUMN($K$4))):indirect(address(row($J$2)+ VLOOKUP(AP$20,$J$3:$J$14,1),COLUMN($S$2)))>indirect(address(row($J3),COLUMN($K$2))):indirect(address(row($J3),COLUMN($S$2))),TRUE()))} -> 2 | AQ22: {=if(AQ$20=$J3,"-", countif(indirect(address(row($J$2)+ VLOOKUP(AQ$20,$J$3:$J$14,1),COLUMN($K$4))):indirect(address(row($J$2)+ VLOOKUP(AQ$20,$J$3:$J$14,1),COLUMN($S$2)))>indirect(address(row($J3),COLUMN($K$2))):indirect(address(row($J3),COLUMN($S$2))),TRUE()))} -> 2 | AR22: {=if(AR$20=$J3,"-", countif(indirect(address(row($J$2)+ VLOOKUP(AR$20,$J$3:$J$14,1),COLUMN($K$4))):indirect(address(row($J$2)+ VLOOKUP(AR$20,$J$3:$J$14,1),COLUMN($S$2)))>indirect(address(row($J3),COLUMN($K$2))):indirect(address(row($J3),COLUMN($S$2))),TRUE()))} -> 6 | AS22: {=if(AS$20=$J3,"-", countif(indirect(address(row($J$2)+ VLOOKUP(AS$20,$J$3:$J$14,1),COLUMN($K$4))):indirect(address(row($J$2)+ VLOOKUP(AS$20,$J$3:$J$14,1),COLUMN($S$2)))>indirect(address(row($J3),COLUMN($K$2))):indirect(address(row($J3),COLUMN($S$2))),TRUE()))} -> 7 | ... AW22: {=if(AW$20=$J3,"-", countif(indirect(address(row($J$2)+ VLOOKUP(AW$20,$J$3:$J$14,1),COLUMN($K$4))):indirect(address(row($J$2)+ VLOOKUP(AW$20,$J$3:$J$14,1),COLUMN($S$2)))>indirect(address(row($J3),COLUMN($K$2))):indirect(address(row($J3),COLUMN($S$2))),TRUE()))} -> 1 | AX22: 1 | AY22: {=INDIRECT("Draft!D"&TEXT(VLOOKUP(TRUE,I3:J14,2,0)+2,"0"))} -> Luka Doncic | BA22: =IF($AY22="","", VLOOKUP($AY22,'Final Update'!$P$21:$AD1015,Column(G1),False)) -> 34.4 | BB22: =IF($AY22="","", VLOOKUP($AY22,'Final Update'!$P$21:$AD1015,Column(H1),False)) -> 4.1 | BC22: =IF($AY22="","", VLOOKUP($AY22,'Final Update'!$P$21:$AD1015,Column(I1),False)) -> 9.3 | BD22: =IF($AY22="","", VLOOKUP($AY22,'Final Update'!$P$21:$AD1015,Column(J1),False)) -> 9.9 | BE22: =IF($AY22="","", VLOOKUP($AY22,'Final Update'!$P$21:$AD1015,Column(K1),False)) -> 1.4 | BF22: =IF($AY22="","", VLOOKUP($AY22,'Final Update'!$P$21:$AD1015,Column(L1),False)) -> 0.5 | BG22: =IF($AY22="","", VLOOKUP($AY22,'Final Update'!$P$21:$AD1015,Column(M1),False)) -> 0.491 | BH22: =IF($AY22="","", VLOOKUP($AY22,'Final Update'!$P$21:$AD1015,Column(N1),False)) -> 0.792 | BI22: =IF($AY22="","", VLOOKUP($AY22,'Final Update'!$P$21:$AD1015,Column(O1),False)) -> 3.8 | BJ22: =IF($AY22="","", VLOOKUP($AY22,'Final Update'!$P$21:$AD1015,Column(C1),False)) -> PG,SG | BK22: {=COUNTIF(FIND(BL22,$BJ$22:$BJ$33),">0")} -> 6 | BL22: PG
A23: =VLOOKUP($F23,UpdateHashtag!$V$3:$Y$32,COLUMN(B$15),0) -> 4 | B23: =VLOOKUP($F23,UpdateHashtag!$V$3:$Y$32,COLUMN(C$13),0) -> 4 | C23: =VLOOKUP($F23,UpdateHashtag!$V$3:$Y$32,COLUMN(D$13),0) -> 3 | D23: =SUM(A23:C23) -> 11 | F23: =VLOOKUP(J23,UpdateBBM!$C$2:E1015,3,0) -> OKC | G23: 4 | H23: =IFERROR(__xludf.DUMMYFUNCTION("""COMPUTED_VALUE"""),4.0) -> 4 | I23: =IFERROR(__xludf.DUMMYFUNCTION("""COMPUTED_VALUE"""),4.5) -> 4.5 | J23: =IFERROR(__xludf.DUMMYFUNCTION("""COMPUTED_VALUE"""),"Shai Gilgeous-Alexander") -> Shai Gilgeous-Alexander | K23: =IFERROR(__xludf.DUMMYFUNCTION("""COMPUTED_VALUE"""),71.0) -> 71 | L23: =IFERROR(__xludf.DUMMYFUNCTION("""COMPUTED_VALUE"""),"PG") -> PG | M23: =IFERROR(__xludf.DUMMYFUNCTION("""COMPUTED_VALUE"""),9.640422694612987) -> 9.6404227 | N23: =IFERROR(__xludf.DUMMYFUNCTION("""COMPUTED_VALUE"""),9.640422694612987) -> 9.6404227 | O23: =IFERROR(__xludf.DUMMYFUNCTION("""COMPUTED_VALUE"""),0.0) -> 0 | P23: =IFERROR(__xludf.DUMMYFUNCTION("""COMPUTED_VALUE"""),29.9) -> 29.9 | Q23: =IFERROR(__xludf.DUMMYFUNCTION("""COMPUTED_VALUE"""),1.4) -> 1.4 | R23: =IFERROR(__xludf.DUMMYFUNCTION("""COMPUTED_VALUE"""),5.1) -> 5.1 | S23: =IFERROR(__xludf.DUMMYFUNCTION("""COMPUTED_VALUE"""),6.5) -> 6.5 | T23: =IFERROR(__xludf.DUMMYFUNCTION("""COMPUTED_VALUE"""),1.9) -> 1.9 | U23: =IFERROR(__xludf.DUMMYFUNCTION("""COMPUTED_VALUE"""),0.9) -> 0.9 | V23: =IFERROR(__xludf.DUMMYFUNCTION("""COMPUTED_VALUE"""),0.524) -> 0.524 | W23: =IFERROR(__xludf.DUMMYFUNCTION("""COMPUTED_VALUE"""),0.88) -> 0.88 | X23: =IFERROR(__xludf.DUMMYFUNCTION("""COMPUTED_VALUE"""),2.4) -> 2.4 | Y23: =IFERROR(__xludf.DUMMYFUNCTION("""COMPUTED_VALUE"""),2.2460171659494095) -> 2.2460172 | Z23: =IFERROR(__xludf.DUMMYFUNCTION("""COMPUTED_VALUE"""),-0.34734639463326067) -> -0.34734639 | AA23: =IFERROR(__xludf.DUMMYFUNCTION("""COMPUTED_VALUE"""),-0.38005417851545714) -> -0.38005418 | AB23: =IFERROR(__xludf.DUMMYFUNCTION("""COMPUTED_VALUE"""),1.1683124177119129) -> 1.1683124 | AC23: =IFERROR(__xludf.DUMMYFUNCTION("""COMPUTED_VALUE"""),3.066530371075986) -> 3.0665304 | AD23: =IFERROR(__xludf.DUMMYFUNCTION("""COMPUTED_VALUE"""),0.27645116741934783) -> 0.27645117 | AE23: =IFERROR(__xludf.DUMMYFUNCTION("""COMPUTED_VALUE"""),0.6197828012717082) -> 0.6197828 | AF23: =IFERROR(__xludf.DUMMYFUNCTION("""COMPUTED_VALUE"""),2.772194196258142) -> 2.7721942 | AG23: =IFERROR(__xludf.DUMMYFUNCTION("""COMPUTED_VALUE"""),-0.1615190304402598) -> -0.16151903 | AK23: 100 | AL23: {=if(AL$20=$J4,"-", countif(indirect(address(row($J$2)+ VLOOKUP(AL$20,$J$3:$J$14,1),COLUMN($K$4))):indirect(address(row($J$2)+ VLOOKUP(AL$20,$J$3:$J$14,1),COLUMN($S$2)))>indirect(address(row($J4),COLUMN($K$2))):indirect(address(row($J4),COLUMN($S$2))),TRUE()))} -> 6 | AM23: {=if(AM$20=$J4,"-", countif(indirect(address(row($J$2)+ VLOOKUP(AM$20,$J$3:$J$14,1),COLUMN($K$4))):indirect(address(row($J$2)+ VLOOKUP(AM$20,$J$3:$J$14,1),COLUMN($S$2)))>indirect(address(row($J4),COLUMN($K$2))):indirect(address(row($J4),COLUMN($S$2))),TRUE()))} -> - | AN23: {=if(AN$20=$J4,"-", countif(indirect(address(row($J$2)+ VLOOKUP(AN$20,$J$3:$J$14,1),COLUMN($K$4))):indirect(address(row($J$2)+ VLOOKUP(AN$20,$J$3:$J$14,1),COLUMN($S$2)))>indirect(address(row($J4),COLUMN($K$2))):indirect(address(row($J4),COLUMN($S$2))),TRUE()))} -> 1 | AO23: {=if(AO$20=$J4,"-", countif(indirect(address(row($J$2)+ VLOOKUP(AO$20,$J$3:$J$14,1),COLUMN($K$4))):indirect(address(row($J$2)+ VLOOKUP(AO$20,$J$3:$J$14,1),COLUMN($S$2)))>indirect(address(row($J4),COLUMN($K$2))):indirect(address(row($J4),COLUMN($S$2))),TRUE()))} -> 6 | AP23: {=if(AP$20=$J4,"-", countif(indirect(address(row($J$2)+ VLOOKUP(AP$20,$J$3:$J$14,1),COLUMN($K$4))):indirect(address(row($J$2)+ VLOOKUP(AP$20,$J$3:$J$14,1),COLUMN($S$2)))>indirect(address(row($J4),COLUMN($K$2))):indirect(address(row($J4),COLUMN($S$2))),TRUE()))} -> 1 | AQ23: {=if(AQ$20=$J4,"-", countif(indirect(address(row($J$2)+ VLOOKUP(AQ$20,$J$3:$J$14,1),COLUMN($K$4))):indirect(address(row($J$2)+ VLOOKUP(AQ$20,$J$3:$J$14,1),COLUMN($S$2)))>indirect(address(row($J4),COLUMN($K$2))):indirect(address(row($J4),COLUMN($S$2))),TRUE()))} -> 0 | AR23: {=if(AR$20=$J4,"-", countif(indirect(address(row($J$2)+ VLOOKUP(AR$20,$J$3:$J$14,1),COLUMN($K$4))):indirect(address(row($J$2)+ VLOOKUP(AR$20,$J$3:$J$14,1),COLUMN($S$2)))>indirect(address(row($J4),COLUMN($K$2))):indirect(address(row($J4),COLUMN($S$2))),TRUE()))} -> 6 | AS23: {=if(AS$20=$J4,"-", countif(indirect(address(row($J$2)+ VLOOKUP(AS$20,$J$3:$J$14,1),COLUMN($K$4))):indirect(address(row($J$2)+ VLOOKUP(AS$20,$J$3:$J$14,1),COLUMN($S$2)))>indirect(address(row($J4),COLUMN($K$2))):indirect(address(row($J4),COLUMN($S$2))),TRUE()))} -> 7 | ... AW23: {=if(AW$20=$J4,"-", countif(indirect(address(row($J$2)+ VLOOKUP(AW$20,$J$3:$J$14,1),COLUMN($K$4))):indirect(address(row($J$2)+ VLOOKUP(AW$20,$J$3:$J$14,1),COLUMN($S$2)))>indirect(address(row($J4),COLUMN($K$2))):indirect(address(row($J4),COLUMN($S$2))),TRUE()))} -> 6 | AX23: 2 | AY23: {=INDIRECT("Draft!E"&TEXT(15-VLOOKUP(TRUE,I3:J14,2,0),"0"))} -> Josh Giddey | BA23: =IF($AY23="","", VLOOKUP($AY23,'Final Update'!$P$21:$AD1015,Column(G2),False)) -> 16.1 | BB23: =IF($AY23="","", VLOOKUP($AY23,'Final Update'!$P$21:$AD1015,Column(H2),False)) -> 1.1 | BC23: =IF($AY23="","", VLOOKUP($AY23,'Final Update'!$P$21:$AD1015,Column(I2),False)) -> 7.4 | BD23: =IF($AY23="","", VLOOKUP($AY23,'Final Update'!$P$21:$AD1015,Column(J2),False)) -> 6.1 | BE23: =IF($AY23="","", VLOOKUP($AY23,'Final Update'!$P$21:$AD1015,Column(K2),False)) -> 0.8 | BF23: =IF($AY23="","", VLOOKUP($AY23,'Final Update'!$P$21:$AD1015,Column(L2),False)) -> 0.5 | BG23: =IF($AY23="","", VLOOKUP($AY23,'Final Update'!$P$21:$AD1015,Column(M2),False)) -> 0.479 | BH23: =IF($AY23="","", VLOOKUP($AY23,'Final Update'!$P$21:$AD1015,Column(N2),False)) -> 0.795 | BI23: =IF($AY23="","", VLOOKUP($AY23,'Final Update'!$P$21:$AD1015,Column(O2),False)) -> 2.7 | BJ23: =IF($AY23="","", VLOOKUP($AY23,'Final Update'!$P$21:$AD1015,Column(C2),False)) -> SG,SF | BK23: {=COUNTIF(FIND(BL23,$BJ$22:$BJ$33),">0")} -> 6 | BL23: SG
A24: =VLOOKUP($F24,UpdateHashtag!$V$3:$Y$32,COLUMN(B$15),0) -> 4 | B24: =VLOOKUP($F24,UpdateHashtag!$V$3:$Y$32,COLUMN(C$13),0) -> 4 | C24: =VLOOKUP($F24,UpdateHashtag!$V$3:$Y$32,COLUMN(D$13),0) -> 2 | D24: =SUM(A24:C24) -> 10 | F24: =VLOOKUP(J24,UpdateBBM!$C$2:E1015,3,0) -> DAL | G24: 5 | H24: =IFERROR(__xludf.DUMMYFUNCTION("""COMPUTED_VALUE"""),5.0) -> 5 | I24: =IFERROR(__xludf.DUMMYFUNCTION("""COMPUTED_VALUE"""),7.4) -> 7.4 | J24: =IFERROR(__xludf.DUMMYFUNCTION("""COMPUTED_VALUE"""),"Anthony Davis") -> Anthony Davis | K24: =IFERROR(__xludf.DUMMYFUNCTION("""COMPUTED_VALUE"""),58.0) -> 58 | L24: =IFERROR(__xludf.DUMMYFUNCTION("""COMPUTED_VALUE"""),"PF,C") -> PF,C | M24: =IFERROR(__xludf.DUMMYFUNCTION("""COMPUTED_VALUE"""),8.69583899859487) -> 8.695839 | N24: =IFERROR(__xludf.DUMMYFUNCTION("""COMPUTED_VALUE"""),8.69583899859487) -> 8.695839 | O24: =IFERROR(__xludf.DUMMYFUNCTION("""COMPUTED_VALUE"""),0.0) -> 0 | P24: =IFERROR(__xludf.DUMMYFUNCTION("""COMPUTED_VALUE"""),25.2) -> 25.2 | Q24: =IFERROR(__xludf.DUMMYFUNCTION("""COMPUTED_VALUE"""),0.4) -> 0.4 | R24: =IFERROR(__xludf.DUMMYFUNCTION("""COMPUTED_VALUE"""),12.7) -> 12.7 | S24: =IFERROR(__xludf.DUMMYFUNCTION("""COMPUTED_VALUE"""),3.6) -> 3.6 | T24: =IFERROR(__xludf.DUMMYFUNCTION("""COMPUTED_VALUE"""),1.2) -> 1.2 | U24: =IFERROR(__xludf.DUMMYFUNCTION("""COMPUTED_VALUE"""),2.3) -> 2.3 | V24: =IFERROR(__xludf.DUMMYFUNCTION("""COMPUTED_VALUE"""),0.559) -> 0.559 | W24: =IFERROR(__xludf.DUMMYFUNCTION("""COMPUTED_VALUE"""),0.802) -> 0.802 | X24: =IFERROR(__xludf.DUMMYFUNCTION("""COMPUTED_VALUE"""),2.1) -> 2.1 | Y24: =IFERROR(__xludf.DUMMYFUNCTION("""COMPUTED_VALUE"""),1.3969714736758965) -> 1.3969715 | Z24: =IFERROR(__xludf.DUMMYFUNCTION("""COMPUTED_VALUE"""),-1.3425893849486756) -> -1.3425894 | AA24: =IFERROR(__xludf.DUMMYFUNCTION("""COMPUTED_VALUE"""),2.6011500269824244) -> 2.60115 | AB24: =IFERROR(__xludf.DUMMYFUNCTION("""COMPUTED_VALUE"""),-0.1529789245299426) -> -0.15297892 | AC24: =IFERROR(__xludf.DUMMYFUNCTION("""COMPUTED_VALUE"""),0.7430016239596308) -> 0.74300162 | AD24: =IFERROR(__xludf.DUMMYFUNCTION("""COMPUTED_VALUE"""),2.7739629961565364) -> 2.773963 | AE24: =IFERROR(__xludf.DUMMYFUNCTION("""COMPUTED_VALUE"""),1.2376640116563253) -> 1.237664 | AF24: =IFERROR(__xludf.DUMMYFUNCTION("""COMPUTED_VALUE"""),0.18319218070629753) -> 0.18319218 | AG24: =IFERROR(__xludf.DUMMYFUNCTION("""COMPUTED_VALUE"""),-0.08712439001229988) -> -0.08712439 | AK24: 100 | AL24: {=if(AL$20=$J5,"-", countif(indirect(address(row($J$2)+ VLOOKUP(AL$20,$J$3:$J$14,1),COLUMN($K$4))):indirect(address(row($J$2)+ VLOOKUP(AL$20,$J$3:$J$14,1),COLUMN($S$2)))>indirect(address(row($J5),COLUMN($K$2))):indirect(address(row($J5),COLUMN($S$2))),TRUE()))} -> 7 | AM24: {=if(AM$20=$J5,"-", countif(indirect(address(row($J$2)+ VLOOKUP(AM$20,$J$3:$J$14,1),COLUMN($K$4))):indirect(address(row($J$2)+ VLOOKUP(AM$20,$J$3:$J$14,1),COLUMN($S$2)))>indirect(address(row($J5),COLUMN($K$2))):indirect(address(row($J5),COLUMN($S$2))),TRUE()))} -> 1 | AN24: {=if(AN$20=$J5,"-", countif(indirect(address(row($J$2)+ VLOOKUP(AN$20,$J$3:$J$14,1),COLUMN($K$4))):indirect(address(row($J$2)+ VLOOKUP(AN$20,$J$3:$J$14,1),COLUMN($S$2)))>indirect(address(row($J5),COLUMN($K$2))):indirect(address(row($J5),COLUMN($S$2))),TRUE()))} -> - | AO24: {=if(AO$20=$J5,"-", countif(indirect(address(row($J$2)+ VLOOKUP(AO$20,$J$3:$J$14,1),COLUMN($K$4))):indirect(address(row($J$2)+ VLOOKUP(AO$20,$J$3:$J$14,1),COLUMN($S$2)))>indirect(address(row($J5),COLUMN($K$2))):indirect(address(row($J5),COLUMN($S$2))),TRUE()))} -> 7 | AP24: {=if(AP$20=$J5,"-", countif(indirect(address(row($J$2)+ VLOOKUP(AP$20,$J$3:$J$14,1),COLUMN($K$4))):indirect(address(row($J$2)+ VLOOKUP(AP$20,$J$3:$J$14,1),COLUMN($S$2)))>indirect(address(row($J5),COLUMN($K$2))):indirect(address(row($J5),COLUMN($S$2))),TRUE()))} -> 1 | AQ24: {=if(AQ$20=$J5,"-", countif(indirect(address(row($J$2)+ VLOOKUP(AQ$20,$J$3:$J$14,1),COLUMN($K$4))):indirect(address(row($J$2)+ VLOOKUP(AQ$20,$J$3:$J$14,1),COLUMN($S$2)))>indirect(address(row($J5),COLUMN($K$2))):indirect(address(row($J5),COLUMN($S$2))),TRUE()))} -> 0 | AR24: {=if(AR$20=$J5,"-", countif(indirect(address(row($J$2)+ VLOOKUP(AR$20,$J$3:$J$14,1),COLUMN($K$4))):indirect(address(row($J$2)+ VLOOKUP(AR$20,$J$3:$J$14,1),COLUMN($S$2)))>indirect(address(row($J5),COLUMN($K$2))):indirect(address(row($J5),COLUMN($S$2))),TRUE()))} -> 6 | AS24: {=if(AS$20=$J5,"-", countif(indirect(address(row($J$2)+ VLOOKUP(AS$20,$J$3:$J$14,1),COLUMN($K$4))):indirect(address(row($J$2)+ VLOOKUP(AS$20,$J$3:$J$14,1),COLUMN($S$2)))>indirect(address(row($J5),COLUMN($K$2))):indirect(address(row($J5),COLUMN($S$2))),TRUE()))} -> 6 | ... AW24: {=if(AW$20=$J5,"-", countif(indirect(address(row($J$2)+ VLOOKUP(AW$20,$J$3:$J$14,1),COLUMN($K$4))):indirect(address(row($J$2)+ VLOOKUP(AW$20,$J$3:$J$14,1),COLUMN($S$2)))>indirect(address(row($J5),COLUMN($K$2))):indirect(address(row($J5),COLUMN($S$2))),TRUE()))} -> 6 | AX24: 3 | AY24: {=INDIRECT("Draft!F"&TEXT(VLOOKUP(TRUE,I3:J14,2,0)+2,"0"))} -> Bam Adebayo | BA24: =IF($AY24="","", VLOOKUP($AY24,'Final Update'!$P$21:$AD1015,Column(G3),False)) -> 20 | BB24: =IF($AY24="","", VLOOKUP($AY24,'Final Update'!$P$21:$AD1015,Column(H3),False)) -> 0.2 | BC24: =IF($AY24="","", VLOOKUP($AY24,'Final Update'!$P$21:$AD1015,Column(I3),False)) -> 10.4 | BD24: =IF($AY24="","", VLOOKUP($AY24,'Final Update'!$P$21:$AD1015,Column(J3),False)) -> 3.9 | BE24: =IF($AY24="","", VLOOKUP($AY24,'Final Update'!$P$21:$AD1015,Column(K3),False)) -> 1.2 | BF24: =IF($AY24="","", VLOOKUP($AY24,'Final Update'!$P$21:$AD1015,Column(L3),False)) -> 0.9 | BG24: =IF($AY24="","", VLOOKUP($AY24,'Final Update'!$P$21:$AD1015,Column(M3),False)) -> 0.531 | BH24: =IF($AY24="","", VLOOKUP($AY24,'Final Update'!$P$21:$AD1015,Column(N3),False)) -> 0.743 | BI24: =IF($AY24="","", VLOOKUP($AY24,'Final Update'!$P$21:$AD1015,Column(O3),False)) -> 2.4 | BJ24: =IF($AY24="","", VLOOKUP($AY24,'Final Update'!$P$21:$AD1015,Column(C3),False)) -> C | BK24: {=COUNTIF(FIND(BL24,$BJ$22:$BJ$33),">0")} -> 2 | BL24: SF
A25: =VLOOKUP($F25,UpdateHashtag!$V$3:$Y$32,COLUMN(B$15),0) -> 4 | B25: =VLOOKUP($F25,UpdateHashtag!$V$3:$Y$32,COLUMN(C$13),0) -> 4 | C25: =VLOOKUP($F25,UpdateHashtag!$V$3:$Y$32,COLUMN(D$13),0) -> 3 | D25: =SUM(A25:C25) -> 11 | F25: =VLOOKUP(J25,UpdateBBM!$C$2:E1015,3,0) -> MIL | G25: 6 | H25: =IFERROR(__xludf.DUMMYFUNCTION("""COMPUTED_VALUE"""),6.0) -> 6 | I25: =IFERROR(__xludf.DUMMYFUNCTION("""COMPUTED_VALUE"""),6.7) -> 6.7 | J25: =IFERROR(__xludf.DUMMYFUNCTION("""COMPUTED_VALUE"""),"Giannis Antetokounmpo") -> Giannis Antetokounmpo | K25: =IFERROR(__xludf.DUMMYFUNCTION("""COMPUTED_VALUE"""),66.0) -> 66 | L25: =IFERROR(__xludf.DUMMYFUNCTION("""COMPUTED_VALUE"""),"PF,C") -> PF,C | M25: =IFERROR(__xludf.DUMMYFUNCTION("""COMPUTED_VALUE"""),8.429006939113258) -> 8.4290069 | N25: =IFERROR(__xludf.DUMMYFUNCTION("""COMPUTED_VALUE"""),8.429006939113258) -> 8.4290069 | O25: =IFERROR(__xludf.DUMMYFUNCTION("""COMPUTED_VALUE"""),0.0) -> 0 | P25: =IFERROR(__xludf.DUMMYFUNCTION("""COMPUTED_VALUE"""),31.1) -> 31.1 | Q25: =IFERROR(__xludf.DUMMYFUNCTION("""COMPUTED_VALUE"""),0.6) -> 0.6 | R25: =IFERROR(__xludf.DUMMYFUNCTION("""COMPUTED_VALUE"""),11.8) -> 11.8 | S25: =IFERROR(__xludf.DUMMYFUNCTION("""COMPUTED_VALUE"""),6.7) -> 6.7 | T25: =IFERROR(__xludf.DUMMYFUNCTION("""COMPUTED_VALUE"""),1.2) -> 1.2 | U25: =IFERROR(__xludf.DUMMYFUNCTION("""COMPUTED_VALUE"""),1.1) -> 1.1 | V25: =IFERROR(__xludf.DUMMYFUNCTION("""COMPUTED_VALUE"""),0.614) -> 0.614 | W25: =IFERROR(__xludf.DUMMYFUNCTION("""COMPUTED_VALUE"""),0.671) -> 0.671 | X25: =IFERROR(__xludf.DUMMYFUNCTION("""COMPUTED_VALUE"""),3.4) -> 3.4 | Y25: =IFERROR(__xludf.DUMMYFUNCTION("""COMPUTED_VALUE"""),2.462794789508605) -> 2.4627948 | Z25: =IFERROR(__xludf.DUMMYFUNCTION("""COMPUTED_VALUE"""),-1.1435407868855925) -> -1.1435408 | AA25: =IFERROR(__xludf.DUMMYFUNCTION("""COMPUTED_VALUE"""),2.2481126868576755) -> 2.2481127 | AB25: =IFERROR(__xludf.DUMMYFUNCTION("""COMPUTED_VALUE"""),1.2594359585561787) -> 1.259436 | AC25: =IFERROR(__xludf.DUMMYFUNCTION("""COMPUTED_VALUE"""),0.7430016239596308) -> 0.74300162 | AD25: =IFERROR(__xludf.DUMMYFUNCTION("""COMPUTED_VALUE"""),0.6332385715246607) -> 0.63323857 | AE25: =IFERROR(__xludf.DUMMYFUNCTION("""COMPUTED_VALUE"""),2.635465260792226) -> 2.6354653 | AF25: =IFERROR(__xludf.DUMMYFUNCTION("""COMPUTED_VALUE"""),-4.607725435738178) -> -4.6077254 | AG25: =IFERROR(__xludf.DUMMYFUNCTION("""COMPUTED_VALUE"""),-0.40950116520012636) -> -0.40950117 | AK25: 100 | AL25: {=if(AL$20=$J6,"-", countif(indirect(address(row($J$2)+ VLOOKUP(AL$20,$J$3:$J$14,1),COLUMN($K$4))):indirect(address(row($J$2)+ VLOOKUP(AL$20,$J$3:$J$14,1),COLUMN($S$2)))>indirect(address(row($J6),COLUMN($K$2))):indirect(address(row($J6),COLUMN($S$2))),TRUE()))} -> 2 | AM25: {=if(AM$20=$J6,"-", countif(indirect(address(row($J$2)+ VLOOKUP(AM$20,$J$3:$J$14,1),COLUMN($K$4))):indirect(address(row($J$2)+ VLOOKUP(AM$20,$J$3:$J$14,1),COLUMN($S$2)))>indirect(address(row($J6),COLUMN($K$2))):indirect(address(row($J6),COLUMN($S$2))),TRUE()))} -> 3 | AN25: {=if(AN$20=$J6,"-", countif(indirect(address(row($J$2)+ VLOOKUP(AN$20,$J$3:$J$14,1),COLUMN($K$4))):indirect(address(row($J$2)+ VLOOKUP(AN$20,$J$3:$J$14,1),COLUMN($S$2)))>indirect(address(row($J6),COLUMN($K$2))):indirect(address(row($J6),COLUMN($S$2))),TRUE()))} -> 2 | AO25: {=if(AO$20=$J6,"-", countif(indirect(address(row($J$2)+ VLOOKUP(AO$20,$J$3:$J$14,1),COLUMN($K$4))):indirect(address(row($J$2)+ VLOOKUP(AO$20,$J$3:$J$14,1),COLUMN($S$2)))>indirect(address(row($J6),COLUMN($K$2))):indirect(address(row($J6),COLUMN($S$2))),TRUE()))} -> - | AP25: {=if(AP$20=$J6,"-", countif(indirect(address(row($J$2)+ VLOOKUP(AP$20,$J$3:$J$14,1),COLUMN($K$4))):indirect(address(row($J$2)+ VLOOKUP(AP$20,$J$3:$J$14,1),COLUMN($S$2)))>indirect(address(row($J6),COLUMN($K$2))):indirect(address(row($J6),COLUMN($S$2))),TRUE()))} -> 2 | AQ25: {=if(AQ$20=$J6,"-", countif(indirect(address(row($J$2)+ VLOOKUP(AQ$20,$J$3:$J$14,1),COLUMN($K$4))):indirect(address(row($J$2)+ VLOOKUP(AQ$20,$J$3:$J$14,1),COLUMN($S$2)))>indirect(address(row($J6),COLUMN($K$2))):indirect(address(row($J6),COLUMN($S$2))),TRUE()))} -> 1 | AR25: {=if(AR$20=$J6,"-", countif(indirect(address(row($J$2)+ VLOOKUP(AR$20,$J$3:$J$14,1),COLUMN($K$4))):indirect(address(row($J$2)+ VLOOKUP(AR$20,$J$3:$J$14,1),COLUMN($S$2)))>indirect(address(row($J6),COLUMN($K$2))):indirect(address(row($J6),COLUMN($S$2))),TRUE()))} -> 3 | AS25: {=if(AS$20=$J6,"-", countif(indirect(address(row($J$2)+ VLOOKUP(AS$20,$J$3:$J$14,1),COLUMN($K$4))):indirect(address(row($J$2)+ VLOOKUP(AS$20,$J$3:$J$14,1),COLUMN($S$2)))>indirect(address(row($J6),COLUMN($K$2))):indirect(address(row($J6),COLUMN($S$2))),TRUE()))} -> 4 | ... AW25: {=if(AW$20=$J6,"-", countif(indirect(address(row($J$2)+ VLOOKUP(AW$20,$J$3:$J$14,1),COLUMN($K$4))):indirect(address(row($J$2)+ VLOOKUP(AW$20,$J$3:$J$14,1),COLUMN($S$2)))>indirect(address(row($J6),COLUMN($K$2))):indirect(address(row($J6),COLUMN($S$2))),TRUE()))} -> 2 | AX25: 4 | AY25: {=INDIRECT("Draft!G"&TEXT(15-VLOOKUP(TRUE,I3:J14,2,0),"0"))} -> Ja Morant | BA25: =IF($AY25="","", VLOOKUP($AY25,'Final Update'!$P$21:$AD1015,Column(G4),False)) -> 25.8 | BB25: =IF($AY25="","", VLOOKUP($AY25,'Final Update'!$P$21:$AD1015,Column(H4),False)) -> 1.5 | BC25: =IF($AY25="","", VLOOKUP($AY25,'Final Update'!$P$21:$AD1015,Column(I4),False)) -> 5.9 | BD25: =IF($AY25="","", VLOOKUP($AY25,'Final Update'!$P$21:$AD1015,Column(J4),False)) -> 8.2 | BE25: =IF($AY25="","", VLOOKUP($AY25,'Final Update'!$P$21:$AD1015,Column(K4),False)) -> 0.9 | BF25: =IF($AY25="","", VLOOKUP($AY25,'Final Update'!$P$21:$AD1015,Column(L4),False)) -> 0.5 | BG25: =IF($AY25="","", VLOOKUP($AY25,'Final Update'!$P$21:$AD1015,Column(M4),False)) -> 0.47 | BH25: =IF($AY25="","", VLOOKUP($AY25,'Final Update'!$P$21:$AD1015,Column(N4),False)) -> 0.788 | BI25: =IF($AY25="","", VLOOKUP($AY25,'Final Update'!$P$21:$AD1015,Column(O4),False)) -> 3 | BJ25: =IF($AY25="","", VLOOKUP($AY25,'Final Update'!$P$21:$AD1015,Column(C4),False)) -> PG | BK25: {=COUNTIF(FIND(BL25,$BJ$22:$BJ$33),">0")} -> 2 | BL25: PF
A26: =VLOOKUP($F26,UpdateHashtag!$V$3:$Y$32,COLUMN(B$15),0) -> 4 | B26: =VLOOKUP($F26,UpdateHashtag!$V$3:$Y$32,COLUMN(C$13),0) -> 4 | C26: =VLOOKUP($F26,UpdateHashtag!$V$3:$Y$32,COLUMN(D$13),0) -> 3 | D26: =SUM(A26:C26) -> 11 | F26: =VLOOKUP(J26,UpdateBBM!$C$2:E1015,3,0) -> ATL | G26: 7 | H26: =IFERROR(__xludf.DUMMYFUNCTION("""COMPUTED_VALUE"""),7.0) -> 7 | I26: =IFERROR(__xludf.DUMMYFUNCTION("""COMPUTED_VALUE"""),12.5) -> 12.5 | J26: =IFERROR(__xludf.DUMMYFUNCTION("""COMPUTED_VALUE"""),"Trae Young") -> Trae Young | K26: =IFERROR(__xludf.DUMMYFUNCTION("""COMPUTED_VALUE"""),71.0) -> 71 | L26: =IFERROR(__xludf.DUMMYFUNCTION("""COMPUTED_VALUE"""),"PG") -> PG | M26: =IFERROR(__xludf.DUMMYFUNCTION("""COMPUTED_VALUE"""),7.19847521079153) -> 7.1984752 | N26: =IFERROR(__xludf.DUMMYFUNCTION("""COMPUTED_VALUE"""),7.19847521079153) -> 7.1984752 | O26: =IFERROR(__xludf.DUMMYFUNCTION("""COMPUTED_VALUE"""),0.0) -> 0 | P26: =IFERROR(__xludf.DUMMYFUNCTION("""COMPUTED_VALUE"""),28.1) -> 28.1 | Q26: =IFERROR(__xludf.DUMMYFUNCTION("""COMPUTED_VALUE"""),3.4) -> 3.4 | R26: =IFERROR(__xludf.DUMMYFUNCTION("""COMPUTED_VALUE"""),2.9) -> 2.9 | S26: =IFERROR(__xludf.DUMMYFUNCTION("""COMPUTED_VALUE"""),10.8) -> 10.8 | T26: =IFERROR(__xludf.DUMMYFUNCTION("""COMPUTED_VALUE"""),1.2) -> 1.2 | U26: =IFERROR(__xludf.DUMMYFUNCTION("""COMPUTED_VALUE"""),0.2) -> 0.2 | V26: =IFERROR(__xludf.DUMMYFUNCTION("""COMPUTED_VALUE"""),0.432) -> 0.432 | W26: =IFERROR(__xludf.DUMMYFUNCTION("""COMPUTED_VALUE"""),0.877) -> 0.877 | X26: =IFERROR(__xludf.DUMMYFUNCTION("""COMPUTED_VALUE"""),4.2) -> 4.2 | Y26: =IFERROR(__xludf.DUMMYFUNCTION("""COMPUTED_VALUE"""),1.9208507306106177) -> 1.9208507 | Z26: =IFERROR(__xludf.DUMMYFUNCTION("""COMPUTED_VALUE"""),1.6431395859975693) -> 1.6431396 | AA26: =IFERROR(__xludf.DUMMYFUNCTION("""COMPUTED_VALUE"""),-1.2430343432648439) -> -1.2430343 | AB26: =IFERROR(__xludf.DUMMYFUNCTION("""COMPUTED_VALUE"""),3.12746854586363) -> 3.1274685 | AC26: =IFERROR(__xludf.DUMMYFUNCTION("""COMPUTED_VALUE"""),0.7430016239596308) -> 0.74300162 | AD26: =IFERROR(__xludf.DUMMYFUNCTION("""COMPUTED_VALUE"""),-0.9723047469492465) -> -0.97230475 | AE26: =IFERROR(__xludf.DUMMYFUNCTION("""COMPUTED_VALUE"""),-1.4827868385980316) -> -1.4827868 | AF26: =IFERROR(__xludf.DUMMYFUNCTION("""COMPUTED_VALUE"""),2.587240687582191) -> 2.5872407 | AG26: =IFERROR(__xludf.DUMMYFUNCTION("""COMPUTED_VALUE"""),-0.6078868730080197) -> -0.60788687 | AK26: 100 | AL26: {=if(AL$20=$J7,"-", countif(indirect(address(row($J$2)+ VLOOKUP(AL$20,$J$3:$J$14,1),COLUMN($K$4))):indirect(address(row($J$2)+ VLOOKUP(AL$20,$J$3:$J$14,1),COLUMN($S$2)))>indirect(address(row($J7),COLUMN($K$2))):indirect(address(row($J7),COLUMN($S$2))),TRUE()))} -> 7 | AM26: {=if(AM$20=$J7,"-", countif(indirect(address(row($J$2)+ VLOOKUP(AM$20,$J$3:$J$14,1),COLUMN($K$4))):indirect(address(row($J$2)+ VLOOKUP(AM$20,$J$3:$J$14,1),COLUMN($S$2)))>indirect(address(row($J7),COLUMN($K$2))):indirect(address(row($J7),COLUMN($S$2))),TRUE()))} -> 1 | AN26: {=if(AN$20=$J7,"-", countif(indirect(address(row($J$2)+ VLOOKUP(AN$20,$J$3:$J$14,1),COLUMN($K$4))):indirect(address(row($J$2)+ VLOOKUP(AN$20,$J$3:$J$14,1),COLUMN($S$2)))>indirect(address(row($J7),COLUMN($K$2))):indirect(address(row($J7),COLUMN($S$2))),TRUE()))} -> 1 | AO26: {=if(AO$20=$J7,"-", countif(indirect(address(row($J$2)+ VLOOKUP(AO$20,$J$3:$J$14,1),COLUMN($K$4))):indirect(address(row($J$2)+ VLOOKUP(AO$20,$J$3:$J$14,1),COLUMN($S$2)))>indirect(address(row($J7),COLUMN($K$2))):indirect(address(row($J7),COLUMN($S$2))),TRUE()))} -> 7 | AP26: {=if(AP$20=$J7,"-", countif(indirect(address(row($J$2)+ VLOOKUP(AP$20,$J$3:$J$14,1),COLUMN($K$4))):indirect(address(row($J$2)+ VLOOKUP(AP$20,$J$3:$J$14,1),COLUMN($S$2)))>indirect(address(row($J7),COLUMN($K$2))):indirect(address(row($J7),COLUMN($S$2))),TRUE()))} -> - | AQ26: {=if(AQ$20=$J7,"-", countif(indirect(address(row($J$2)+ VLOOKUP(AQ$20,$J$3:$J$14,1),COLUMN($K$4))):indirect(address(row($J$2)+ VLOOKUP(AQ$20,$J$3:$J$14,1),COLUMN($S$2)))>indirect(address(row($J7),COLUMN($K$2))):indirect(address(row($J7),COLUMN($S$2))),TRUE()))} -> 1 | AR26: {=if(AR$20=$J7,"-", countif(indirect(address(row($J$2)+ VLOOKUP(AR$20,$J$3:$J$14,1),COLUMN($K$4))):indirect(address(row($J$2)+ VLOOKUP(AR$20,$J$3:$J$14,1),COLUMN($S$2)))>indirect(address(row($J7),COLUMN($K$2))):indirect(address(row($J7),COLUMN($S$2))),TRUE()))} -> 7 | AS26: {=if(AS$20=$J7,"-", countif(indirect(address(row($J$2)+ VLOOKUP(AS$20,$J$3:$J$14,1),COLUMN($K$4))):indirect(address(row($J$2)+ VLOOKUP(AS$20,$J$3:$J$14,1),COLUMN($S$2)))>indirect(address(row($J7),COLUMN($K$2))):indirect(address(row($J7),COLUMN($S$2))),TRUE()))} -> 7 | ... AW26: {=if(AW$20=$J7,"-", countif(indirect(address(row($J$2)+ VLOOKUP(AW$20,$J$3:$J$14,1),COLUMN($K$4))):indirect(address(row($J$2)+ VLOOKUP(AW$20,$J$3:$J$14,1),COLUMN($S$2)))>indirect(address(row($J7),COLUMN($K$2))):indirect(address(row($J7),COLUMN($S$2))),TRUE()))} -> 7 | AX26: 5 | AY26: {=INDIRECT("Draft!H"&TEXT(VLOOKUP(TRUE,I3:J14,2,0)+2,"0"))} -> Joel Embiid | BA26: =IF($AY26="","", VLOOKUP($AY26,'Final Update'!$P$21:$AD1015,Column(G5),False)) -> 28.1 | BB26: =IF($AY26="","", VLOOKUP($AY26,'Final Update'!$P$21:$AD1015,Column(H5),False)) -> 1.3 | BC26: =IF($AY26="","", VLOOKUP($AY26,'Final Update'!$P$21:$AD1015,Column(I5),False)) -> 10 | BD26: =IF($AY26="","", VLOOKUP($AY26,'Final Update'!$P$21:$AD1015,Column(J5),False)) -> 3.9 | BE26: =IF($AY26="","", VLOOKUP($AY26,'Final Update'!$P$21:$AD1015,Column(K5),False)) -> 0.9 | BF26: =IF($AY26="","", VLOOKUP($AY26,'Final Update'!$P$21:$AD1015,Column(L5),False)) -> 1.4 | BG26: =IF($AY26="","", VLOOKUP($AY26,'Final Update'!$P$21:$AD1015,Column(M5),False)) -> 0.518 | BH26: =IF($AY26="","", VLOOKUP($AY26,'Final Update'!$P$21:$AD1015,Column(N5),False)) -> 0.871 | BI26: =IF($AY26="","", VLOOKUP($AY26,'Final Update'!$P$21:$AD1015,Column(O5),False)) -> 3.3 | BJ26: =IF($AY26="","", VLOOKUP($AY26,'Final Update'!$P$21:$AD1015,Column(C5),False)) -> C | BK26: {=COUNTIF(FIND(BL26,$BJ$22:$BJ$33),">0")} -> 3 | BL26: C
A27: =VLOOKUP($F27,UpdateHashtag!$V$3:$Y$32,COLUMN(B$15),0) -> 4 | B27: =VLOOKUP($F27,UpdateHashtag!$V$3:$Y$32,COLUMN(C$13),0) -> 4 | C27: =VLOOKUP($F27,UpdateHashtag!$V$3:$Y$32,COLUMN(D$13),0) -> 4 | D27: =SUM(A27:C27) -> 12 | F27: =VLOOKUP(J27,UpdateBBM!$C$2:E1015,3,0) -> PHI | G27: 8 | H27: =IFERROR(__xludf.DUMMYFUNCTION("""COMPUTED_VALUE"""),8.0) -> 8 | I27: =IFERROR(__xludf.DUMMYFUNCTION("""COMPUTED_VALUE"""),9.6) -> 9.6 | J27: =IFERROR(__xludf.DUMMYFUNCTION("""COMPUTED_VALUE"""),"Joel Embiid") -> Joel Embiid | K27: =IFERROR(__xludf.DUMMYFUNCTION("""COMPUTED_VALUE"""),54.0) -> 54 | L27: =IFERROR(__xludf.DUMMYFUNCTION("""COMPUTED_VALUE"""),"C") -> C | M27: =IFERROR(__xludf.DUMMYFUNCTION("""COMPUTED_VALUE"""),7.080727484907011) -> 7.0807275 | N27: =IFERROR(__xludf.DUMMYFUNCTION("""COMPUTED_VALUE"""),7.080727484907011) -> 7.0807275 | O27: =IFERROR(__xludf.DUMMYFUNCTION("""COMPUTED_VALUE"""),0.0) -> 0 | P27: =IFERROR(__xludf.DUMMYFUNCTION("""COMPUTED_VALUE"""),28.1) -> 28.1 | Q27: =IFERROR(__xludf.DUMMYFUNCTION("""COMPUTED_VALUE"""),1.3) -> 1.3 | R27: =IFERROR(__xludf.DUMMYFUNCTION("""COMPUTED_VALUE"""),10.0) -> 10 | S27: =IFERROR(__xludf.DUMMYFUNCTION("""COMPUTED_VALUE"""),3.9) -> 3.9 | T27: =IFERROR(__xludf.DUMMYFUNCTION("""COMPUTED_VALUE"""),0.9) -> 0.9 | U27: =IFERROR(__xludf.DUMMYFUNCTION("""COMPUTED_VALUE"""),1.4) -> 1.4 | V27: =IFERROR(__xludf.DUMMYFUNCTION("""COMPUTED_VALUE"""),0.518) -> 0.518 | W27: =IFERROR(__xludf.DUMMYFUNCTION("""COMPUTED_VALUE"""),0.871) -> 0.871 | X27: =IFERROR(__xludf.DUMMYFUNCTION("""COMPUTED_VALUE"""),3.3) -> 3.3 | Y27: =IFERROR(__xludf.DUMMYFUNCTION("""COMPUTED_VALUE"""),1.9208507306106177) -> 1.9208507 | Z27: =IFERROR(__xludf.DUMMYFUNCTION("""COMPUTED_VALUE"""),-0.44687069366480203) -> -0.44687069 | AA27: =IFERROR(__xludf.DUMMYFUNCTION("""COMPUTED_VALUE"""),1.5420380066081771) -> 1.542038 | AB27: =IFERROR(__xludf.DUMMYFUNCTION("""COMPUTED_VALUE"""),-0.016293613263543852) -> -0.016293613 | AC27: =IFERROR(__xludf.DUMMYFUNCTION("""COMPUTED_VALUE"""),-0.25279641051880714) -> -0.25279641 | AD27: =IFERROR(__xludf.DUMMYFUNCTION("""COMPUTED_VALUE"""),1.1684196776826294) -> 1.1684197 | AE27: =IFERROR(__xludf.DUMMYFUNCTION("""COMPUTED_VALUE"""),0.43563041128701513) -> 0.43563041 | AF27: =IFERROR(__xludf.DUMMYFUNCTION("""COMPUTED_VALUE"""),2.667581634225062) -> 2.6675816 | AG27: =IFERROR(__xludf.DUMMYFUNCTION("""COMPUTED_VALUE"""),-0.3847029517241397) -> -0.38470295 | AK27: 100 | AL27: {=if(AL$20=$J8,"-", countif(indirect(address(row($J$2)+ VLOOKUP(AL$20,$J$3:$J$14,1),COLUMN($K$4))):indirect(address(row($J$2)+ VLOOKUP(AL$20,$J$3:$J$14,1),COLUMN($S$2)))>indirect(address(row($J8),COLUMN($K$2))):indirect(address(row($J8),COLUMN($S$2))),TRUE()))} -> 7 | AM27: {=if(AM$20=$J8,"-", countif(indirect(address(row($J$2)+ VLOOKUP(AM$20,$J$3:$J$14,1),COLUMN($K$4))):indirect(address(row($J$2)+ VLOOKUP(AM$20,$J$3:$J$14,1),COLUMN($S$2)))>indirect(address(row($J8),COLUMN($K$2))):indirect(address(row($J8),COLUMN($S$2))),TRUE()))} -> 2 | AN27: {=if(AN$20=$J8,"-", countif(indirect(address(row($J$2)+ VLOOKUP(AN$20,$J$3:$J$14,1),COLUMN($K$4))):indirect(address(row($J$2)+ VLOOKUP(AN$20,$J$3:$J$14,1),COLUMN($S$2)))>indirect(address(row($J8),COLUMN($K$2))):indirect(address(row($J8),COLUMN($S$2))),TRUE()))} -> 2 | AO27: {=if(AO$20=$J8,"-", countif(indirect(address(row($J$2)+ VLOOKUP(AO$20,$J$3:$J$14,1),COLUMN($K$4))):indirect(address(row($J$2)+ VLOOKUP(AO$20,$J$3:$J$14,1),COLUMN($S$2)))>indirect(address(row($J8),COLUMN($K$2))):indirect(address(row($J8),COLUMN($S$2))),TRUE()))} -> 8 | AP27: {=if(AP$20=$J8,"-", countif(indirect(address(row($J$2)+ VLOOKUP(AP$20,$J$3:$J$14,1),COLUMN($K$4))):indirect(address(row($J$2)+ VLOOKUP(AP$20,$J$3:$J$14,1),COLUMN($S$2)))>indirect(address(row($J8),COLUMN($K$2))):indirect(address(row($J8),COLUMN($S$2))),TRUE()))} -> 1 | AQ27: {=if(AQ$20=$J8,"-", countif(indirect(address(row($J$2)+ VLOOKUP(AQ$20,$J$3:$J$14,1),COLUMN($K$4))):indirect(address(row($J$2)+ VLOOKUP(AQ$20,$J$3:$J$14,1),COLUMN($S$2)))>indirect(address(row($J8),COLUMN($K$2))):indirect(address(row($J8),COLUMN($S$2))),TRUE()))} -> - | AR27: {=if(AR$20=$J8,"-", countif(indirect(address(row($J$2)+ VLOOKUP(AR$20,$J$3:$J$14,1),COLUMN($K$4))):indirect(address(row($J$2)+ VLOOKUP(AR$20,$J$3:$J$14,1),COLUMN($S$2)))>indirect(address(row($J8),COLUMN($K$2))):indirect(address(row($J8),COLUMN($S$2))),TRUE()))} -> 7 | AS27: {=if(AS$20=$J8,"-", countif(indirect(address(row($J$2)+ VLOOKUP(AS$20,$J$3:$J$14,1),COLUMN($K$4))):indirect(address(row($J$2)+ VLOOKUP(AS$20,$J$3:$J$14,1),COLUMN($S$2)))>indirect(address(row($J8),COLUMN($K$2))):indirect(address(row($J8),COLUMN($S$2))),TRUE()))} -> 8 | ... AW27: {=if(AW$20=$J8,"-", countif(indirect(address(row($J$2)+ VLOOKUP(AW$20,$J$3:$J$14,1),COLUMN($K$4))):indirect(address(row($J$2)+ VLOOKUP(AW$20,$J$3:$J$14,1),COLUMN($S$2)))>indirect(address(row($J8),COLUMN($K$2))):indirect(address(row($J8),COLUMN($S$2))),TRUE()))} -> 8 | AX27: 6 | AY27: {=INDIRECT("Draft!I"&TEXT(15-VLOOKUP(TRUE,I3:J14,2,0),"0"))} -> Payton Pritchard | BA27: =IF($AY27="","", VLOOKUP($AY27,'Final Update'!$P$21:$AD1015,Column(G6),False)) -> 10.5 | BB27: =IF($AY27="","", VLOOKUP($AY27,'Final Update'!$P$21:$AD1015,Column(H6),False)) -> 2 | BC27: =IF($AY27="","", VLOOKUP($AY27,'Final Update'!$P$21:$AD1015,Column(I6),False)) -> 3.5 | BD27: =IF($AY27="","", VLOOKUP($AY27,'Final Update'!$P$21:$AD1015,Column(J6),False)) -> 3.4 | BE27: =IF($AY27="","", VLOOKUP($AY27,'Final Update'!$P$21:$AD1015,Column(K6),False)) -> 0.5 | BF27: =IF($AY27="","", VLOOKUP($AY27,'Final Update'!$P$21:$AD1015,Column(L6),False)) -> 0.1 | BG27: =IF($AY27="","", VLOOKUP($AY27,'Final Update'!$P$21:$AD1015,Column(M6),False)) -> 0.453 | BH27: =IF($AY27="","", VLOOKUP($AY27,'Final Update'!$P$21:$AD1015,Column(N6),False)) -> 0.806 | BI27: =IF($AY27="","", VLOOKUP($AY27,'Final Update'!$P$21:$AD1015,Column(O6),False)) -> 1 | BJ27: =IF($AY27="","", VLOOKUP($AY27,'Final Update'!$P$21:$AD1015,Column(C6),False)) -> PG
A28: =VLOOKUP($F28,UpdateHashtag!$V$3:$Y$32,COLUMN(B$15),0) -> 3 | B28: =VLOOKUP($F28,UpdateHashtag!$V$3:$Y$32,COLUMN(C$13),0) -> 4 | C28: =VLOOKUP($F28,UpdateHashtag!$V$3:$Y$32,COLUMN(D$13),0) -> 4 | D28: =SUM(A28:C28) -> 11 | F28: =VLOOKUP(J28,UpdateBBM!$C$2:E1015,3,0) -> IND | G28: 9 | H28: =IFERROR(__xludf.DUMMYFUNCTION("""COMPUTED_VALUE"""),9.0) -> 9 | I28: =IFERROR(__xludf.DUMMYFUNCTION("""COMPUTED_VALUE"""),8.4) -> 8.4 | J28: =IFERROR(__xludf.DUMMYFUNCTION("""COMPUTED_VALUE"""),"Tyrese Haliburton") -> Tyrese Haliburton | K28: =IFERROR(__xludf.DUMMYFUNCTION("""COMPUTED_VALUE"""),61.0) -> 61 | L28: =IFERROR(__xludf.DUMMYFUNCTION("""COMPUTED_VALUE"""),"PG,SG") -> PG,SG | M28: =IFERROR(__xludf.DUMMYFUNCTION("""COMPUTED_VALUE"""),6.883468532105739) -> 6.8834685 | N28: =IFERROR(__xludf.DUMMYFUNCTION("""COMPUTED_VALUE"""),6.883468532105739) -> 6.8834685 | O28: =IFERROR(__xludf.DUMMYFUNCTION("""COMPUTED_VALUE"""),0.0) -> 0 | P28: =IFERROR(__xludf.DUMMYFUNCTION("""COMPUTED_VALUE"""),21.1) -> 21.1 | Q28: =IFERROR(__xludf.DUMMYFUNCTION("""COMPUTED_VALUE"""),3.0) -> 3 | R28: =IFERROR(__xludf.DUMMYFUNCTION("""COMPUTED_VALUE"""),3.9) -> 3.9 | S28: =IFERROR(__xludf.DUMMYFUNCTION("""COMPUTED_VALUE"""),11.1) -> 11.1 | T28: =IFERROR(__xludf.DUMMYFUNCTION("""COMPUTED_VALUE"""),1.4) -> 1.4 | U28: =IFERROR(__xludf.DUMMYFUNCTION("""COMPUTED_VALUE"""),0.7) -> 0.7 | V28: =IFERROR(__xludf.DUMMYFUNCTION("""COMPUTED_VALUE"""),0.483) -> 0.483 | W28: =IFERROR(__xludf.DUMMYFUNCTION("""COMPUTED_VALUE"""),0.862) -> 0.862 | X28: =IFERROR(__xludf.DUMMYFUNCTION("""COMPUTED_VALUE"""),2.5) -> 2.5 | Y28: =IFERROR(__xludf.DUMMYFUNCTION("""COMPUTED_VALUE"""),0.6563145931819813) -> 0.65631459 | Z28: =IFERROR(__xludf.DUMMYFUNCTION("""COMPUTED_VALUE"""),1.2450423898714034) -> 1.2450424 | AA28: =IFERROR(__xludf.DUMMYFUNCTION("""COMPUTED_VALUE"""),-0.8507706320151226) -> -0.85077063 | AB28: =IFERROR(__xludf.DUMMYFUNCTION("""COMPUTED_VALUE"""),3.2641538571300286) -> 3.2641539 | AC28: =IFERROR(__xludf.DUMMYFUNCTION("""COMPUTED_VALUE"""),1.4068669802785894) -> 1.406867 | AD28: =IFERROR(__xludf.DUMMYFUNCTION("""COMPUTED_VALUE"""),-0.08033623668596498) -> -0.080336237 | AE28: =IFERROR(__xludf.DUMMYFUNCTION("""COMPUTED_VALUE"""),-0.2537855436318455) -> -0.25378554 | AF28: =IFERROR(__xludf.DUMMYFUNCTION("""COMPUTED_VALUE"""),0.8315297358777928) -> 0.83152974 | AG28: =IFERROR(__xludf.DUMMYFUNCTION("""COMPUTED_VALUE"""),-0.1863172439162465) -> -0.18631724 | AK28: 100 | AL28: {=if(AL$20=$J9,"-", countif(indirect(address(row($J$2)+ VLOOKUP(AL$20,$J$3:$J$14,1),COLUMN($K$4))):indirect(address(row($J$2)+ VLOOKUP(AL$20,$J$3:$J$14,1),COLUMN($S$2)))>indirect(address(row($J9),COLUMN($K$2))):indirect(address(row($J9),COLUMN($S$2))),TRUE()))} -> 3 | AM28: {=if(AM$20=$J9,"-", countif(indirect(address(row($J$2)+ VLOOKUP(AM$20,$J$3:$J$14,1),COLUMN($K$4))):indirect(address(row($J$2)+ VLOOKUP(AM$20,$J$3:$J$14,1),COLUMN($S$2)))>indirect(address(row($J9),COLUMN($K$2))):indirect(address(row($J9),COLUMN($S$2))),TRUE()))} -> 3 | AN28: {=if(AN$20=$J9,"-", countif(indirect(address(row($J$2)+ VLOOKUP(AN$20,$J$3:$J$14,1),COLUMN($K$4))):indirect(address(row($J$2)+ VLOOKUP(AN$20,$J$3:$J$14,1),COLUMN($S$2)))>indirect(address(row($J9),COLUMN($K$2))):indirect(address(row($J9),COLUMN($S$2))),TRUE()))} -> 3 | AO28: {=if(AO$20=$J9,"-", countif(indirect(address(row($J$2)+ VLOOKUP(AO$20,$J$3:$J$14,1),COLUMN($K$4))):indirect(address(row($J$2)+ VLOOKUP(AO$20,$J$3:$J$14,1),COLUMN($S$2)))>indirect(address(row($J9),COLUMN($K$2))):indirect(address(row($J9),COLUMN($S$2))),TRUE()))} -> 6 | AP28: {=if(AP$20=$J9,"-", countif(indirect(address(row($J$2)+ VLOOKUP(AP$20,$J$3:$J$14,1),COLUMN($K$4))):indirect(address(row($J$2)+ VLOOKUP(AP$20,$J$3:$J$14,1),COLUMN($S$2)))>indirect(address(row($J9),COLUMN($K$2))):indirect(address(row($J9),COLUMN($S$2))),TRUE()))} -> 2 | AQ28: {=if(AQ$20=$J9,"-", countif(indirect(address(row($J$2)+ VLOOKUP(AQ$20,$J$3:$J$14,1),COLUMN($K$4))):indirect(address(row($J$2)+ VLOOKUP(AQ$20,$J$3:$J$14,1),COLUMN($S$2)))>indirect(address(row($J9),COLUMN($K$2))):indirect(address(row($J9),COLUMN($S$2))),TRUE()))} -> 2 | AR28: {=if(AR$20=$J9,"-", countif(indirect(address(row($J$2)+ VLOOKUP(AR$20,$J$3:$J$14,1),COLUMN($K$4))):indirect(address(row($J$2)+ VLOOKUP(AR$20,$J$3:$J$14,1),COLUMN($S$2)))>indirect(address(row($J9),COLUMN($K$2))):indirect(address(row($J9),COLUMN($S$2))),TRUE()))} -> - | AS28: {=if(AS$20=$J9,"-", countif(indirect(address(row($J$2)+ VLOOKUP(AS$20,$J$3:$J$14,1),COLUMN($K$4))):indirect(address(row($J$2)+ VLOOKUP(AS$20,$J$3:$J$14,1),COLUMN($S$2)))>indirect(address(row($J9),COLUMN($K$2))):indirect(address(row($J9),COLUMN($S$2))),TRUE()))} -> 4 | ... AW28: {=if(AW$20=$J9,"-", countif(indirect(address(row($J$2)+ VLOOKUP(AW$20,$J$3:$J$14,1),COLUMN($K$4))):indirect(address(row($J$2)+ VLOOKUP(AW$20,$J$3:$J$14,1),COLUMN($S$2)))>indirect(address(row($J9),COLUMN($K$2))):indirect(address(row($J9),COLUMN($S$2))),TRUE()))} -> 2 | AX28: 7 | AY28: {=INDIRECT("Draft!J"&TEXT(VLOOKUP(TRUE,I3:J14,2,0)+2,"0"))} -> Jordan Poole | BA28: =IF($AY28="","", VLOOKUP($AY28,'Final Update'!$P$21:$AD1015,Column(G7),False)) -> 20.1 | BB28: =IF($AY28="","", VLOOKUP($AY28,'Final Update'!$P$21:$AD1015,Column(H7),False)) -> 2.6 | BC28: =IF($AY28="","", VLOOKUP($AY28,'Final Update'!$P$21:$AD1015,Column(I7),False)) -> 2.9 | BD28: =IF($AY28="","", VLOOKUP($AY28,'Final Update'!$P$21:$AD1015,Column(J7),False)) -> 5.7 | BE28: =IF($AY28="","", VLOOKUP($AY28,'Final Update'!$P$21:$AD1015,Column(K7),False)) -> 1.1 | BF28: =IF($AY28="","", VLOOKUP($AY28,'Final Update'!$P$21:$AD1015,Column(L7),False)) -> 0.3 | BG28: =IF($AY28="","", VLOOKUP($AY28,'Final Update'!$P$21:$AD1015,Column(M7),False)) -> 0.422 | BH28: =IF($AY28="","", VLOOKUP($AY28,'Final Update'!$P$21:$AD1015,Column(N7),False)) -> 0.871 | BI28: =IF($AY28="","", VLOOKUP($AY28,'Final Update'!$P$21:$AD1015,Column(O7),False)) -> 2.9 | BJ28: =IF($AY28="","", VLOOKUP($AY28,'Final Update'!$P$21:$AD1015,Column(C7),False)) -> PG,SG
A29: =VLOOKUP($F29,UpdateHashtag!$V$3:$Y$32,COLUMN(B$15),0) -> 4 | B29: =VLOOKUP($F29,UpdateHashtag!$V$3:$Y$32,COLUMN(C$13),0) -> 3 | C29: =VLOOKUP($F29,UpdateHashtag!$V$3:$Y$32,COLUMN(D$13),0) -> 4 | D29: =SUM(A29:C29) -> 11 | F29: =VLOOKUP(J29,UpdateBBM!$C$2:E1015,3,0) -> CHA | G29: 10 | H29: =IFERROR(__xludf.DUMMYFUNCTION("""COMPUTED_VALUE"""),10.0) -> 10 | I29: =IFERROR(__xludf.DUMMYFUNCTION("""COMPUTED_VALUE"""),22.3) -> 22.3 | J29: =IFERROR(__xludf.DUMMYFUNCTION("""COMPUTED_VALUE"""),"LaMelo Ball") -> LaMelo Ball | K29: =IFERROR(__xludf.DUMMYFUNCTION("""COMPUTED_VALUE"""),75.0) -> 75 | L29: =IFERROR(__xludf.DUMMYFUNCTION("""COMPUTED_VALUE"""),"PG,SG") -> PG,SG | M29: =IFERROR(__xludf.DUMMYFUNCTION("""COMPUTED_VALUE"""),6.5143286563032285) -> 6.5143287 | N29: =IFERROR(__xludf.DUMMYFUNCTION("""COMPUTED_VALUE"""),6.5143286563032285) -> 6.5143287 | O29: =IFERROR(__xludf.DUMMYFUNCTION("""COMPUTED_VALUE"""),0.0) -> 0 | P29: =IFERROR(__xludf.DUMMYFUNCTION("""COMPUTED_VALUE"""),23.2) -> 23.2 | Q29: =IFERROR(__xludf.DUMMYFUNCTION("""COMPUTED_VALUE"""),3.6) -> 3.6 | R29: =IFERROR(__xludf.DUMMYFUNCTION("""COMPUTED_VALUE"""),5.7) -> 5.7 | S29: =IFERROR(__xludf.DUMMYFUNCTION("""COMPUTED_VALUE"""),8.6) -> 8.6 | T29: =IFERROR(__xludf.DUMMYFUNCTION("""COMPUTED_VALUE"""),1.6) -> 1.6 | U29: =IFERROR(__xludf.DUMMYFUNCTION("""COMPUTED_VALUE"""),0.3) -> 0.3 | V29: =IFERROR(__xludf.DUMMYFUNCTION("""COMPUTED_VALUE"""),0.427) -> 0.427 | W29: =IFERROR(__xludf.DUMMYFUNCTION("""COMPUTED_VALUE"""),0.857) -> 0.857 | X29: =IFERROR(__xludf.DUMMYFUNCTION("""COMPUTED_VALUE"""),3.5) -> 3.5 | Y29: =IFERROR(__xludf.DUMMYFUNCTION("""COMPUTED_VALUE"""),1.0356754344105719) -> 1.0356754 | Z29: =IFERROR(__xludf.DUMMYFUNCTION("""COMPUTED_VALUE"""),1.8421881840606524) -> 1.8421882 | AA29: =IFERROR(__xludf.DUMMYFUNCTION("""COMPUTED_VALUE"""),-0.1446959517656242) -> -0.14469595 | AB29: =IFERROR(__xludf.DUMMYFUNCTION("""COMPUTED_VALUE"""),2.1251095965767046) -> 2.1251096 | AC29: =IFERROR(__xludf.DUMMYFUNCTION("""COMPUTED_VALUE"""),2.0707323365975485) -> 2.0707323 | AD29: =IFERROR(__xludf.DUMMYFUNCTION("""COMPUTED_VALUE"""),-0.7939110448965904) -> -0.79391104 | AE29: =IFERROR(__xludf.DUMMYFUNCTION("""COMPUTED_VALUE"""),-1.5724868211410579) -> -1.5724868 | AF29: =IFERROR(__xludf.DUMMYFUNCTION("""COMPUTED_VALUE"""),0.813529479996078) -> 0.81352948 | AG29: =IFERROR(__xludf.DUMMYFUNCTION("""COMPUTED_VALUE"""),-0.43429937867611307) -> -0.43429938 | AK29: 100 | AL29: {=if(AL$20=$J10,"-", countif(indirect(address(row($J$2)+ VLOOKUP(AL$20,$J$3:$J$14,1),COLUMN($K$4))):indirect(address(row($J$2)+ VLOOKUP(AL$20,$J$3:$J$14,1),COLUMN($S$2)))>indirect(address(row($J10),COLUMN($K$2))):indirect(address(row($J10),COLUMN($S$2))),TRUE()))} -> 2 | AM29: {=if(AM$20=$J10,"-", countif(indirect(address(row($J$2)+ VLOOKUP(AM$20,$J$3:$J$14,1),COLUMN($K$4))):indirect(address(row($J$2)+ VLOOKUP(AM$20,$J$3:$J$14,1),COLUMN($S$2)))>indirect(address(row($J10),COLUMN($K$2))):indirect(address(row($J10),COLUMN($S$2))),TRUE()))} -> 2 | AN29: {=if(AN$20=$J10,"-", countif(indirect(address(row($J$2)+ VLOOKUP(AN$20,$J$3:$J$14,1),COLUMN($K$4))):indirect(address(row($J$2)+ VLOOKUP(AN$20,$J$3:$J$14,1),COLUMN($S$2)))>indirect(address(row($J10),COLUMN($K$2))):indirect(address(row($J10),COLUMN($S$2))),TRUE()))} -> 3 | AO29: {=if(AO$20=$J10,"-", countif(indirect(address(row($J$2)+ VLOOKUP(AO$20,$J$3:$J$14,1),COLUMN($K$4))):indirect(address(row($J$2)+ VLOOKUP(AO$20,$J$3:$J$14,1),COLUMN($S$2)))>indirect(address(row($J10),COLUMN($K$2))):indirect(address(row($J10),COLUMN($S$2))),TRUE()))} -> 5 | AP29: {=if(AP$20=$J10,"-", countif(indirect(address(row($J$2)+ VLOOKUP(AP$20,$J$3:$J$14,1),COLUMN($K$4))):indirect(address(row($J$2)+ VLOOKUP(AP$20,$J$3:$J$14,1),COLUMN($S$2)))>indirect(address(row($J10),COLUMN($K$2))):indirect(address(row($J10),COLUMN($S$2))),TRUE()))} -> 2 | AQ29: {=if(AQ$20=$J10,"-", countif(indirect(address(row($J$2)+ VLOOKUP(AQ$20,$J$3:$J$14,1),COLUMN($K$4))):indirect(address(row($J$2)+ VLOOKUP(AQ$20,$J$3:$J$14,1),COLUMN($S$2)))>indirect(address(row($J10),COLUMN($K$2))):indirect(address(row($J10),COLUMN($S$2))),TRUE()))} -> 1 | AR29: {=if(AR$20=$J10,"-", countif(indirect(address(row($J$2)+ VLOOKUP(AR$20,$J$3:$J$14,1),COLUMN($K$4))):indirect(address(row($J$2)+ VLOOKUP(AR$20,$J$3:$J$14,1),COLUMN($S$2)))>indirect(address(row($J10),COLUMN($K$2))):indirect(address(row($J10),COLUMN($S$2))),TRUE()))} -> 5 | AS29: {=if(AS$20=$J10,"-", countif(indirect(address(row($J$2)+ VLOOKUP(AS$20,$J$3:$J$14,1),COLUMN($K$4))):indirect(address(row($J$2)+ VLOOKUP(AS$20,$J$3:$J$14,1),COLUMN($S$2)))>indirect(address(row($J10),COLUMN($K$2))):indirect(address(row($J10),COLUMN($S$2))),TRUE()))} -> - | ... AW29: {=if(AW$20=$J10,"-", countif(indirect(address(row($J$2)+ VLOOKUP(AW$20,$J$3:$J$14,1),COLUMN($K$4))):indirect(address(row($J$2)+ VLOOKUP(AW$20,$J$3:$J$14,1),COLUMN($S$2)))>indirect(address(row($J10),COLUMN($K$2))):indirect(address(row($J10),COLUMN($S$2))),TRUE()))} -> 1 | AX29: 8 | AY29: {=INDIRECT("Draft!K"&TEXT(15-VLOOKUP(TRUE,I3:J14,2,0),"0"))} -> Jalen Green | BA29: =IF($AY29="","", VLOOKUP($AY29,'Final Update'!$P$21:$AD1015,Column(G8),False)) -> 20.5 | BB29: =IF($AY29="","", VLOOKUP($AY29,'Final Update'!$P$21:$AD1015,Column(H8),False)) -> 2.4 | BC29: =IF($AY29="","", VLOOKUP($AY29,'Final Update'!$P$21:$AD1015,Column(I8),False)) -> 4.9 | BD29: =IF($AY29="","", VLOOKUP($AY29,'Final Update'!$P$21:$AD1015,Column(J8),False)) -> 3.7 | BE29: =IF($AY29="","", VLOOKUP($AY29,'Final Update'!$P$21:$AD1015,Column(K8),False)) -> 0.9 | BF29: =IF($AY29="","", VLOOKUP($AY29,'Final Update'!$P$21:$AD1015,Column(L8),False)) -> 0.3 | BG29: =IF($AY29="","", VLOOKUP($AY29,'Final Update'!$P$21:$AD1015,Column(M8),False)) -> 0.429 | BH29: =IF($AY29="","", VLOOKUP($AY29,'Final Update'!$P$21:$AD1015,Column(N8),False)) -> 0.807 | BI29: =IF($AY29="","", VLOOKUP($AY29,'Final Update'!$P$21:$AD1015,Column(O8),False)) -> 2.4 | BJ29: =IF($AY29="","", VLOOKUP($AY29,'Final Update'!$P$21:$AD1015,Column(C8),False)) -> PG,SG
A30: =VLOOKUP($F30,UpdateHashtag!$V$3:$Y$32,COLUMN(B$15),0) -> 4 | B30: =VLOOKUP($F30,UpdateHashtag!$V$3:$Y$32,COLUMN(C$13),0) -> 4 | C30: =VLOOKUP($F30,UpdateHashtag!$V$3:$Y$32,COLUMN(D$13),0) -> 4 | D30: =SUM(A30:C30) -> 12 | F30: =VLOOKUP(J30,UpdateBBM!$C$2:E1015,3,0) -> LAC | G30: 11 | H30: =IFERROR(__xludf.DUMMYFUNCTION("""COMPUTED_VALUE"""),11.0) -> 11 | I30: =IFERROR(__xludf.DUMMYFUNCTION("""COMPUTED_VALUE"""),16.2) -> 16.2 | J30: =IFERROR(__xludf.DUMMYFUNCTION("""COMPUTED_VALUE"""),"James Harden") -> James Harden | K30: =IFERROR(__xludf.DUMMYFUNCTION("""COMPUTED_VALUE"""),62.0) -> 62 | L30: =IFERROR(__xludf.DUMMYFUNCTION("""COMPUTED_VALUE"""),"PG,SG") -> PG,SG | M30: =IFERROR(__xludf.DUMMYFUNCTION("""COMPUTED_VALUE"""),6.006607638177341) -> 6.0066076 | N30: =IFERROR(__xludf.DUMMYFUNCTION("""COMPUTED_VALUE"""),6.006607638177341) -> 6.0066076 | O30: =IFERROR(__xludf.DUMMYFUNCTION("""COMPUTED_VALUE"""),0.0) -> 0 | P30: =IFERROR(__xludf.DUMMYFUNCTION("""COMPUTED_VALUE"""),20.4) -> 20.4 | Q30: =IFERROR(__xludf.DUMMYFUNCTION("""COMPUTED_VALUE"""),2.8) -> 2.8 | R30: =IFERROR(__xludf.DUMMYFUNCTION("""COMPUTED_VALUE"""),6.1) -> 6.1 | S30: =IFERROR(__xludf.DUMMYFUNCTION("""COMPUTED_VALUE"""),10.4) -> 10.4 | T30: =IFERROR(__xludf.DUMMYFUNCTION("""COMPUTED_VALUE"""),1.1) -> 1.1 | U30: =IFERROR(__xludf.DUMMYFUNCTION("""COMPUTED_VALUE"""),0.7) -> 0.7 | V30: =IFERROR(__xludf.DUMMYFUNCTION("""COMPUTED_VALUE"""),0.438) -> 0.438 | W30: =IFERROR(__xludf.DUMMYFUNCTION("""COMPUTED_VALUE"""),0.871) -> 0.871 | X30: =IFERROR(__xludf.DUMMYFUNCTION("""COMPUTED_VALUE"""),2.9) -> 2.9 | Y30: =IFERROR(__xludf.DUMMYFUNCTION("""COMPUTED_VALUE"""),0.529860979439117) -> 0.52986098 | Z30: =IFERROR(__xludf.DUMMYFUNCTION("""COMPUTED_VALUE"""),1.0459937918083202) -> 1.0459938 | AA30: =IFERROR(__xludf.DUMMYFUNCTION("""COMPUTED_VALUE"""),0.012209532734264103) -> 0.012209533 | AB30: =IFERROR(__xludf.DUMMYFUNCTION("""COMPUTED_VALUE"""),2.945221464175098) -> 2.9452215 | AC30: =IFERROR(__xludf.DUMMYFUNCTION("""COMPUTED_VALUE"""),0.41106894580015185) -> 0.41106895 | AD30: =IFERROR(__xludf.DUMMYFUNCTION("""COMPUTED_VALUE"""),-0.08033623668596498) -> -0.080336237 | AE30: =IFERROR(__xludf.DUMMYFUNCTION("""COMPUTED_VALUE"""),-1.0213235091497475) -> -1.0213235 | AF30: =IFERROR(__xludf.DUMMYFUNCTION("""COMPUTED_VALUE"""),1.4280992587265482) -> 1.4280993 | AG30: =IFERROR(__xludf.DUMMYFUNCTION("""COMPUTED_VALUE"""),-0.2855100978201931) -> -0.2855101 | AK30: 100 | AL30: {=if(AL$20=$J11,"-", countif(indirect(address(row($J$2)+ VLOOKUP(AL$20,$J$3:$J$14,1),COLUMN($K$4))):indirect(address(row($J$2)+ VLOOKUP(AL$20,$J$3:$J$14,1),COLUMN($S$2)))>indirect(address(row($J11),COLUMN($K$2))):indirect(address(row($J11),COLUMN($S$2))),TRUE()))} -> 7 | AM30: {=if(AM$20=$J11,"-", countif(indirect(address(row($J$2)+ VLOOKUP(AM$20,$J$3:$J$14,1),COLUMN($K$4))):indirect(address(row($J$2)+ VLOOKUP(AM$20,$J$3:$J$14,1),COLUMN($S$2)))>indirect(address(row($J11),COLUMN($K$2))):indirect(address(row($J11),COLUMN($S$2))),TRUE()))} -> 1 | AN30: {=if(AN$20=$J11,"-", countif(indirect(address(row($J$2)+ VLOOKUP(AN$20,$J$3:$J$14,1),COLUMN($K$4))):indirect(address(row($J$2)+ VLOOKUP(AN$20,$J$3:$J$14,1),COLUMN($S$2)))>indirect(address(row($J11),COLUMN($K$2))):indirect(address(row($J11),COLUMN($S$2))),TRUE()))} -> 2 | AO30: {=if(AO$20=$J11,"-", countif(indirect(address(row($J$2)+ VLOOKUP(AO$20,$J$3:$J$14,1),COLUMN($K$4))):indirect(address(row($J$2)+ VLOOKUP(AO$20,$J$3:$J$14,1),COLUMN($S$2)))>indirect(address(row($J11),COLUMN($K$2))):indirect(address(row($J11),COLUMN($S$2))),TRUE()))} -> 7 | AP30: {=if(AP$20=$J11,"-", countif(indirect(address(row($J$2)+ VLOOKUP(AP$20,$J$3:$J$14,1),COLUMN($K$4))):indirect(address(row($J$2)+ VLOOKUP(AP$20,$J$3:$J$14,1),COLUMN($S$2)))>indirect(address(row($J11),COLUMN($K$2))):indirect(address(row($J11),COLUMN($S$2))),TRUE()))} -> 1 | AQ30: {=if(AQ$20=$J11,"-", countif(indirect(address(row($J$2)+ VLOOKUP(AQ$20,$J$3:$J$14,1),COLUMN($K$4))):indirect(address(row($J$2)+ VLOOKUP(AQ$20,$J$3:$J$14,1),COLUMN($S$2)))>indirect(address(row($J11),COLUMN($K$2))):indirect(address(row($J11),COLUMN($S$2))),TRUE()))} -> 1 | AR30: {=if(AR$20=$J11,"-", countif(indirect(address(row($J$2)+ VLOOKUP(AR$20,$J$3:$J$14,1),COLUMN($K$4))):indirect(address(row($J$2)+ VLOOKUP(AR$20,$J$3:$J$14,1),COLUMN($S$2)))>indirect(address(row($J11),COLUMN($K$2))):indirect(address(row($J11),COLUMN($S$2))),TRUE()))} -> 7 | AS30: {=if(AS$20=$J11,"-", countif(indirect(address(row($J$2)+ VLOOKUP(AS$20,$J$3:$J$14,1),COLUMN($K$4))):indirect(address(row($J$2)+ VLOOKUP(AS$20,$J$3:$J$14,1),COLUMN($S$2)))>indirect(address(row($J11),COLUMN($K$2))):indirect(address(row($J11),COLUMN($S$2))),TRUE()))} -> 7 | ... AW30: {=if(AW$20=$J11,"-", countif(indirect(address(row($J$2)+ VLOOKUP(AW$20,$J$3:$J$14,1),COLUMN($K$4))):indirect(address(row($J$2)+ VLOOKUP(AW$20,$J$3:$J$14,1),COLUMN($S$2)))>indirect(address(row($J11),COLUMN($K$2))):indirect(address(row($J11),COLUMN($S$2))),TRUE()))} -> 7 | AX30: 9 | AY30: {=INDIRECT("Draft!L"&TEXT(VLOOKUP(TRUE,I3:J14,2,0)+2,"0"))} -> Bobby Portis | BA30: =IF($AY30="","", VLOOKUP($AY30,'Final Update'!$P$21:$AD1015,Column(G9),False)) -> 14.1 | BB30: =IF($AY30="","", VLOOKUP($AY30,'Final Update'!$P$21:$AD1015,Column(H9),False)) -> 1.3 | BC30: =IF($AY30="","", VLOOKUP($AY30,'Final Update'!$P$21:$AD1015,Column(I9),False)) -> 8.3 | BD30: =IF($AY30="","", VLOOKUP($AY30,'Final Update'!$P$21:$AD1015,Column(J9),False)) -> 1.4 | BE30: =IF($AY30="","", VLOOKUP($AY30,'Final Update'!$P$21:$AD1015,Column(K9),False)) -> 0.7 | BF30: =IF($AY30="","", VLOOKUP($AY30,'Final Update'!$P$21:$AD1015,Column(L9),False)) -> 0.3 | BG30: =IF($AY30="","", VLOOKUP($AY30,'Final Update'!$P$21:$AD1015,Column(M9),False)) -> 0.502 | BH30: =IF($AY30="","", VLOOKUP($AY30,'Final Update'!$P$21:$AD1015,Column(N9),False)) -> 0.777 | BI30: =IF($AY30="","", VLOOKUP($AY30,'Final Update'!$P$21:$AD1015,Column(O9),False)) -> 1.1 | BJ30: =IF($AY30="","", VLOOKUP($AY30,'Final Update'!$P$21:$AD1015,Column(C9),False)) -> PF,C
A31: =VLOOKUP($F31,UpdateHashtag!$V$3:$Y$32,COLUMN(B$15),0) -> 3 | B31: =VLOOKUP($F31,UpdateHashtag!$V$3:$Y$32,COLUMN(C$13),0) -> 4 | C31: =VLOOKUP($F31,UpdateHashtag!$V$3:$Y$32,COLUMN(D$13),0) -> 3 | D31: =SUM(A31:C31) -> 10 | F31: =VLOOKUP(J31,UpdateBBM!$C$2:E1015,3,0) -> BOS | G31: 12 | H31: =IFERROR(__xludf.DUMMYFUNCTION("""COMPUTED_VALUE"""),12.0) -> 12 | I31: =IFERROR(__xludf.DUMMYFUNCTION("""COMPUTED_VALUE"""),9.5) -> 9.5 | J31: =IFERROR(__xludf.DUMMYFUNCTION("""COMPUTED_VALUE"""),"Jayson Tatum") -> Jayson Tatum | K31: =IFERROR(__xludf.DUMMYFUNCTION("""COMPUTED_VALUE"""),66.0) -> 66 | L31: =IFERROR(__xludf.DUMMYFUNCTION("""COMPUTED_VALUE"""),"SF,PF") -> SF,PF | M31: =IFERROR(__xludf.DUMMYFUNCTION("""COMPUTED_VALUE"""),5.917048842687828) -> 5.9170488 | N31: =IFERROR(__xludf.DUMMYFUNCTION("""COMPUTED_VALUE"""),5.917048842687828) -> 5.9170488 | O31: =IFERROR(__xludf.DUMMYFUNCTION("""COMPUTED_VALUE"""),0.0) -> 0 | P31: =IFERROR(__xludf.DUMMYFUNCTION("""COMPUTED_VALUE"""),27.9) -> 27.9 | Q31: =IFERROR(__xludf.DUMMYFUNCTION("""COMPUTED_VALUE"""),2.9) -> 2.9 | R31: =IFERROR(__xludf.DUMMYFUNCTION("""COMPUTED_VALUE"""),9.0) -> 9 | S31: =IFERROR(__xludf.DUMMYFUNCTION("""COMPUTED_VALUE"""),5.1) -> 5.1 | T31: =IFERROR(__xludf.DUMMYFUNCTION("""COMPUTED_VALUE"""),1.1) -> 1.1 | U31: =IFERROR(__xludf.DUMMYFUNCTION("""COMPUTED_VALUE"""),0.7) -> 0.7 | V31: =IFERROR(__xludf.DUMMYFUNCTION("""COMPUTED_VALUE"""),0.469) -> 0.469 | W31: =IFERROR(__xludf.DUMMYFUNCTION("""COMPUTED_VALUE"""),0.836) -> 0.836 | X31: =IFERROR(__xludf.DUMMYFUNCTION("""COMPUTED_VALUE"""),2.5) -> 2.5 | Y31: =IFERROR(__xludf.DUMMYFUNCTION("""COMPUTED_VALUE"""),1.8847211266840846) -> 1.8847211 | Z31: =IFERROR(__xludf.DUMMYFUNCTION("""COMPUTED_VALUE"""),1.145518090839862) -> 1.1455181 | AA31: =IFERROR(__xludf.DUMMYFUNCTION("""COMPUTED_VALUE"""),1.149774295358456) -> 1.1497743 | AB31: =IFERROR(__xludf.DUMMYFUNCTION("""COMPUTED_VALUE"""),0.5304476318020513) -> 0.53044763 | AC31: =IFERROR(__xludf.DUMMYFUNCTION("""COMPUTED_VALUE"""),0.41106894580015185) -> 0.41106895 | AD31: =IFERROR(__xludf.DUMMYFUNCTION("""COMPUTED_VALUE"""),-0.08033623668596498) -> -0.080336237 | AE31: =IFERROR(__xludf.DUMMYFUNCTION("""COMPUTED_VALUE"""),-0.6567939692109008) -> -0.65679397 | AF31: =IFERROR(__xludf.DUMMYFUNCTION("""COMPUTED_VALUE"""),1.0621722328054333) -> 1.0621722 | AG31: =IFERROR(__xludf.DUMMYFUNCTION("""COMPUTED_VALUE"""),-0.1863172439162465) -> -0.18631724 | AK31: 100 | AL31: {=if(AL$20=$J12,"-", countif(indirect(address(row($J$2)+ VLOOKUP(AL$20,$J$3:$J$14,1),COLUMN($K$4))):indirect(address(row($J$2)+ VLOOKUP(AL$20,$J$3:$J$14,1),COLUMN($S$2)))>indirect(address(row($J12),COLUMN($K$2))):indirect(address(row($J12),COLUMN($S$2))),TRUE()))} -> 2 | AM31: {=if(AM$20=$J12,"-", countif(indirect(address(row($J$2)+ VLOOKUP(AM$20,$J$3:$J$14,1),COLUMN($K$4))):indirect(address(row($J$2)+ VLOOKUP(AM$20,$J$3:$J$14,1),COLUMN($S$2)))>indirect(address(row($J12),COLUMN($K$2))):indirect(address(row($J12),COLUMN($S$2))),TRUE()))} -> 2 | AN31: {=if(AN$20=$J12,"-", countif(indirect(address(row($J$2)+ VLOOKUP(AN$20,$J$3:$J$14,1),COLUMN($K$4))):indirect(address(row($J$2)+ VLOOKUP(AN$20,$J$3:$J$14,1),COLUMN($S$2)))>indirect(address(row($J12),COLUMN($K$2))):indirect(address(row($J12),COLUMN($S$2))),TRUE()))} -> 3 | AO31: {=if(AO$20=$J12,"-", countif(indirect(address(row($J$2)+ VLOOKUP(AO$20,$J$3:$J$14,1),COLUMN($K$4))):indirect(address(row($J$2)+ VLOOKUP(AO$20,$J$3:$J$14,1),COLUMN($S$2)))>indirect(address(row($J12),COLUMN($K$2))):indirect(address(row($J12),COLUMN($S$2))),TRUE()))} -> 7 | AP31: {=if(AP$20=$J12,"-", countif(indirect(address(row($J$2)+ VLOOKUP(AP$20,$J$3:$J$14,1),COLUMN($K$4))):indirect(address(row($J$2)+ VLOOKUP(AP$20,$J$3:$J$14,1),COLUMN($S$2)))>indirect(address(row($J12),COLUMN($K$2))):indirect(address(row($J12),COLUMN($S$2))),TRUE()))} -> 2 | AQ31: {=if(AQ$20=$J12,"-", countif(indirect(address(row($J$2)+ VLOOKUP(AQ$20,$J$3:$J$14,1),COLUMN($K$4))):indirect(address(row($J$2)+ VLOOKUP(AQ$20,$J$3:$J$14,1),COLUMN($S$2)))>indirect(address(row($J12),COLUMN($K$2))):indirect(address(row($J12),COLUMN($S$2))),TRUE()))} -> 2 | AR31: {=if(AR$20=$J12,"-", countif(indirect(address(row($J$2)+ VLOOKUP(AR$20,$J$3:$J$14,1),COLUMN($K$4))):indirect(address(row($J$2)+ VLOOKUP(AR$20,$J$3:$J$14,1),COLUMN($S$2)))>indirect(address(row($J12),COLUMN($K$2))):indirect(address(row($J12),COLUMN($S$2))),TRUE()))} -> 7 | AS31: {=if(AS$20=$J12,"-", countif(indirect(address(row($J$2)+ VLOOKUP(AS$20,$J$3:$J$14,1),COLUMN($K$4))):indirect(address(row($J$2)+ VLOOKUP(AS$20,$J$3:$J$14,1),COLUMN($S$2)))>indirect(address(row($J12),COLUMN($K$2))):indirect(address(row($J12),COLUMN($S$2))),TRUE()))} -> 8 | ... AW31: {=if(AW$20=$J12,"-", countif(indirect(address(row($J$2)+ VLOOKUP(AW$20,$J$3:$J$14,1),COLUMN($K$4))):indirect(address(row($J$2)+ VLOOKUP(AW$20,$J$3:$J$14,1),COLUMN($S$2)))>indirect(address(row($J12),COLUMN($K$2))):indirect(address(row($J12),COLUMN($S$2))),TRUE()))} -> 2 | AX31: 10 | AY31: {=INDIRECT("Draft!M"&TEXT(15-VLOOKUP(TRUE,I3:J14,2,0),"0"))} -> Reed Sheppard | BA31: =IF($AY31="","", VLOOKUP($AY31,'Final Update'!$P$21:$AD1015,Column(G10),False)) -> 6.7 | BB31: =IF($AY31="","", VLOOKUP($AY31,'Final Update'!$P$21:$AD1015,Column(H10),False)) -> 1.3 | BC31: =IF($AY31="","", VLOOKUP($AY31,'Final Update'!$P$21:$AD1015,Column(I10),False)) -> 2.5 | BD31: =IF($AY31="","", VLOOKUP($AY31,'Final Update'!$P$21:$AD1015,Column(J10),False)) -> 2.4 | BE31: =IF($AY31="","", VLOOKUP($AY31,'Final Update'!$P$21:$AD1015,Column(K10),False)) -> 1.3 | BF31: =IF($AY31="","", VLOOKUP($AY31,'Final Update'!$P$21:$AD1015,Column(L10),False)) -> 0.4 | BG31: =IF($AY31="","", VLOOKUP($AY31,'Final Update'!$P$21:$AD1015,Column(M10),False)) -> 0.472 | BH31: =IF($AY31="","", VLOOKUP($AY31,'Final Update'!$P$21:$AD1015,Column(N10),False)) -> 0.835 | BI31: =IF($AY31="","", VLOOKUP($AY31,'Final Update'!$P$21:$AD1015,Column(O10),False)) -> 1.1 | BJ31: =IF($AY31="","", VLOOKUP($AY31,'Final Update'!$P$21:$AD1015,Column(C10),False)) -> SG
A32: =VLOOKUP($F32,UpdateHashtag!$V$3:$Y$32,COLUMN(B$15),0) -> 4 | B32: =VLOOKUP($F32,UpdateHashtag!$V$3:$Y$32,COLUMN(C$13),0) -> 3 | C32: =VLOOKUP($F32,UpdateHashtag!$V$3:$Y$32,COLUMN(D$13),0) -> 4 | D32: =SUM(A32:C32) -> 11 | F32: =VLOOKUP(J32,UpdateBBM!$C$2:E1015,3,0) -> CLE | G32: 13 | H32: =IFERROR(__xludf.DUMMYFUNCTION("""COMPUTED_VALUE"""),13.0) -> 13 | I32: =IFERROR(__xludf.DUMMYFUNCTION("""COMPUTED_VALUE"""),17.0) -> 17 | J32: =IFERROR(__xludf.DUMMYFUNCTION("""COMPUTED_VALUE"""),"Donovan Mitchell") -> Donovan Mitchell | K32: =IFERROR(__xludf.DUMMYFUNCTION("""COMPUTED_VALUE"""),71.0) -> 71 | L32: =IFERROR(__xludf.DUMMYFUNCTION("""COMPUTED_VALUE"""),"PG,SG") -> PG,SG | M32: =IFERROR(__xludf.DUMMYFUNCTION("""COMPUTED_VALUE"""),5.687658286753553) -> 5.6876583 | N32: =IFERROR(__xludf.DUMMYFUNCTION("""COMPUTED_VALUE"""),5.687658286753553) -> 5.6876583 | O32: =IFERROR(__xludf.DUMMYFUNCTION("""COMPUTED_VALUE"""),0.0) -> 0 | P32: =IFERROR(__xludf.DUMMYFUNCTION("""COMPUTED_VALUE"""),26.2) -> 26.2 | Q32: =IFERROR(__xludf.DUMMYFUNCTION("""COMPUTED_VALUE"""),3.3) -> 3.3 | R32: =IFERROR(__xludf.DUMMYFUNCTION("""COMPUTED_VALUE"""),4.4) -> 4.4 | S32: =IFERROR(__xludf.DUMMYFUNCTION("""COMPUTED_VALUE"""),5.4) -> 5.4 | T32: =IFERROR(__xludf.DUMMYFUNCTION("""COMPUTED_VALUE"""),1.6) -> 1.6 | U32: =IFERROR(__xludf.DUMMYFUNCTION("""COMPUTED_VALUE"""),0.4) -> 0.4 | V32: =IFERROR(__xludf.DUMMYFUNCTION("""COMPUTED_VALUE"""),0.468) -> 0.468 | W32: =IFERROR(__xludf.DUMMYFUNCTION("""COMPUTED_VALUE"""),0.866) -> 0.866 | X32: =IFERROR(__xludf.DUMMYFUNCTION("""COMPUTED_VALUE"""),2.8) -> 2.8 | Y32: =IFERROR(__xludf.DUMMYFUNCTION("""COMPUTED_VALUE"""),1.5776194933085588) -> 1.5776195 | Z32: =IFERROR(__xludf.DUMMYFUNCTION("""COMPUTED_VALUE"""),1.5436152869660278) -> 1.5436153 | AA32: =IFERROR(__xludf.DUMMYFUNCTION("""COMPUTED_VALUE"""),-0.6546387763902618) -> -0.65463878 | AB32: =IFERROR(__xludf.DUMMYFUNCTION("""COMPUTED_VALUE"""),0.6671329430684506) -> 0.66713294 | AC32: =IFERROR(__xludf.DUMMYFUNCTION("""COMPUTED_VALUE"""),2.0707323365975485) -> 2.0707323 | AD32: =IFERROR(__xludf.DUMMYFUNCTION("""COMPUTED_VALUE"""),-0.6155173428439339) -> -0.61551734 | AE32: =IFERROR(__xludf.DUMMYFUNCTION("""COMPUTED_VALUE"""),-0.6600421969098721) -> -0.6600422 | AF32: =IFERROR(__xludf.DUMMYFUNCTION("""COMPUTED_VALUE"""),1.35942623039137) -> 1.3594262 | AG32: =IFERROR(__xludf.DUMMYFUNCTION("""COMPUTED_VALUE"""),-0.2607118843442064) -> -0.26071188 | AK32: 100 | AL32: {=if(AL$20=$J13,"-", countif(indirect(address(row($J$2)+ VLOOKUP(AL$20,$J$3:$J$14,1),COLUMN($K$4))):indirect(address(row($J$2)+ VLOOKUP(AL$20,$J$3:$J$14,1),COLUMN($S$2)))>indirect(address(row($J13),COLUMN($K$2))):indirect(address(row($J13),COLUMN($S$2))),TRUE()))} -> 6 | AM32: {=if(AM$20=$J13,"-", countif(indirect(address(row($J$2)+ VLOOKUP(AM$20,$J$3:$J$14,1),COLUMN($K$4))):indirect(address(row($J$2)+ VLOOKUP(AM$20,$J$3:$J$14,1),COLUMN($S$2)))>indirect(address(row($J13),COLUMN($K$2))):indirect(address(row($J13),COLUMN($S$2))),TRUE()))} -> 1 | AN32: {=if(AN$20=$J13,"-", countif(indirect(address(row($J$2)+ VLOOKUP(AN$20,$J$3:$J$14,1),COLUMN($K$4))):indirect(address(row($J$2)+ VLOOKUP(AN$20,$J$3:$J$14,1),COLUMN($S$2)))>indirect(address(row($J13),COLUMN($K$2))):indirect(address(row($J13),COLUMN($S$2))),TRUE()))} -> 1 | AO32: {=if(AO$20=$J13,"-", countif(indirect(address(row($J$2)+ VLOOKUP(AO$20,$J$3:$J$14,1),COLUMN($K$4))):indirect(address(row($J$2)+ VLOOKUP(AO$20,$J$3:$J$14,1),COLUMN($S$2)))>indirect(address(row($J13),COLUMN($K$2))):indirect(address(row($J13),COLUMN($S$2))),TRUE()))} -> 7 | AP32: {=if(AP$20=$J13,"-", countif(indirect(address(row($J$2)+ VLOOKUP(AP$20,$J$3:$J$14,1),COLUMN($K$4))):indirect(address(row($J$2)+ VLOOKUP(AP$20,$J$3:$J$14,1),COLUMN($S$2)))>indirect(address(row($J13),COLUMN($K$2))):indirect(address(row($J13),COLUMN($S$2))),TRUE()))} -> 1 | AQ32: {=if(AQ$20=$J13,"-", countif(indirect(address(row($J$2)+ VLOOKUP(AQ$20,$J$3:$J$14,1),COLUMN($K$4))):indirect(address(row($J$2)+ VLOOKUP(AQ$20,$J$3:$J$14,1),COLUMN($S$2)))>indirect(address(row($J13),COLUMN($K$2))):indirect(address(row($J13),COLUMN($S$2))),TRUE()))} -> 1 | AR32: {=if(AR$20=$J13,"-", countif(indirect(address(row($J$2)+ VLOOKUP(AR$20,$J$3:$J$14,1),COLUMN($K$4))):indirect(address(row($J$2)+ VLOOKUP(AR$20,$J$3:$J$14,1),COLUMN($S$2)))>indirect(address(row($J13),COLUMN($K$2))):indirect(address(row($J13),COLUMN($S$2))),TRUE()))} -> 6 | AS32: {=if(AS$20=$J13,"-", countif(indirect(address(row($J$2)+ VLOOKUP(AS$20,$J$3:$J$14,1),COLUMN($K$4))):indirect(address(row($J$2)+ VLOOKUP(AS$20,$J$3:$J$14,1),COLUMN($S$2)))>indirect(address(row($J13),COLUMN($K$2))):indirect(address(row($J13),COLUMN($S$2))),TRUE()))} -> 7 | ... AW32: {=if(AW$20=$J13,"-", countif(indirect(address(row($J$2)+ VLOOKUP(AW$20,$J$3:$J$14,1),COLUMN($K$4))):indirect(address(row($J$2)+ VLOOKUP(AW$20,$J$3:$J$14,1),COLUMN($S$2)))>indirect(address(row($J13),COLUMN($K$2))):indirect(address(row($J13),COLUMN($S$2))),TRUE()))} -> 7 | AX32: 11 | AY32: {=INDIRECT("Draft!N"&TEXT(VLOOKUP(TRUE,I3:J14,2,0)+2,"0"))} -> Cason Wallace | BA32: =IF($AY32="","", VLOOKUP($AY32,'Final Update'!$P$21:$AD1015,Column(G11),False)) -> 7.4 | BB32: =IF($AY32="","", VLOOKUP($AY32,'Final Update'!$P$21:$AD1015,Column(H11),False)) -> 1.3 | BC32: =IF($AY32="","", VLOOKUP($AY32,'Final Update'!$P$21:$AD1015,Column(I11),False)) -> 2.5 | BD32: =IF($AY32="","", VLOOKUP($AY32,'Final Update'!$P$21:$AD1015,Column(J11),False)) -> 1.6 | BE32: =IF($AY32="","", VLOOKUP($AY32,'Final Update'!$P$21:$AD1015,Column(K11),False)) -> 1 | BF32: =IF($AY32="","", VLOOKUP($AY32,'Final Update'!$P$21:$AD1015,Column(L11),False)) -> 0.5 | BG32: =IF($AY32="","", VLOOKUP($AY32,'Final Update'!$P$21:$AD1015,Column(M11),False)) -> 0.491 | BH32: =IF($AY32="","", VLOOKUP($AY32,'Final Update'!$P$21:$AD1015,Column(N11),False)) -> 0.776 | BI32: =IF($AY32="","", VLOOKUP($AY32,'Final Update'!$P$21:$AD1015,Column(O11),False)) -> 0.6 | BJ32: =IF($AY32="","", VLOOKUP($AY32,'Final Update'!$P$21:$AD1015,Column(C11),False)) -> PG,SG
A33: =VLOOKUP($F33,UpdateHashtag!$V$3:$Y$32,COLUMN(B$15),0) -> 4 | B33: =VLOOKUP($F33,UpdateHashtag!$V$3:$Y$32,COLUMN(C$13),0) -> 3 | C33: =VLOOKUP($F33,UpdateHashtag!$V$3:$Y$32,COLUMN(D$13),0) -> 4 | D33: =SUM(A33:C33) -> 11 | F33: =VLOOKUP(J33,UpdateBBM!$C$2:E1015,3,0) -> POR | G33: 14 | H33: =IFERROR(__xludf.DUMMYFUNCTION("""COMPUTED_VALUE"""),14.0) -> 14 | I33: =IFERROR(__xludf.DUMMYFUNCTION("""COMPUTED_VALUE"""),24.3) -> 24.3 | J33: =IFERROR(__xludf.DUMMYFUNCTION("""COMPUTED_VALUE"""),"Damian Lillard") -> Damian Lillard | K33: =IFERROR(__xludf.DUMMYFUNCTION("""COMPUTED_VALUE"""),71.0) -> 71 | L33: =IFERROR(__xludf.DUMMYFUNCTION("""COMPUTED_VALUE"""),"PG") -> PG | M33: =IFERROR(__xludf.DUMMYFUNCTION("""COMPUTED_VALUE"""),5.2326923312314175) -> 5.2326923 | N33: =IFERROR(__xludf.DUMMYFUNCTION("""COMPUTED_VALUE"""),5.2326923312314175) -> 5.2326923 | O33: =IFERROR(__xludf.DUMMYFUNCTION("""COMPUTED_VALUE"""),0.0) -> 0 | P33: =IFERROR(__xludf.DUMMYFUNCTION("""COMPUTED_VALUE"""),24.9) -> 24.9 | Q33: =IFERROR(__xludf.DUMMYFUNCTION("""COMPUTED_VALUE"""),3.1) -> 3.1 | R33: =IFERROR(__xludf.DUMMYFUNCTION("""COMPUTED_VALUE"""),4.5) -> 4.5 | S33: =IFERROR(__xludf.DUMMYFUNCTION("""COMPUTED_VALUE"""),7.1) -> 7.1 | T33: =IFERROR(__xludf.DUMMYFUNCTION("""COMPUTED_VALUE"""),0.9) -> 0.9 | U33: =IFERROR(__xludf.DUMMYFUNCTION("""COMPUTED_VALUE"""),0.3) -> 0.3 | V33: =IFERROR(__xludf.DUMMYFUNCTION("""COMPUTED_VALUE"""),0.432) -> 0.432 | W33: =IFERROR(__xludf.DUMMYFUNCTION("""COMPUTED_VALUE"""),0.918) -> 0.918 | X33: =IFERROR(__xludf.DUMMYFUNCTION("""COMPUTED_VALUE"""),2.9) -> 2.9 | Y33: =IFERROR(__xludf.DUMMYFUNCTION("""COMPUTED_VALUE"""),1.3427770677860977) -> 1.3427771 | Z33: =IFERROR(__xludf.DUMMYFUNCTION("""COMPUTED_VALUE"""),1.344566688902945) -> 1.3445667 | AA33: =IFERROR(__xludf.DUMMYFUNCTION("""COMPUTED_VALUE"""),-0.6154124052652897) -> -0.61541241 | AB33: =IFERROR(__xludf.DUMMYFUNCTION("""COMPUTED_VALUE"""),1.4416830402447103) -> 1.441683 | AC33: =IFERROR(__xludf.DUMMYFUNCTION("""COMPUTED_VALUE"""),-0.25279641051880714) -> -0.25279641 | AD33: =IFERROR(__xludf.DUMMYFUNCTION("""COMPUTED_VALUE"""),-0.7939110448965904) -> -0.79391104 | AE33: =IFERROR(__xludf.DUMMYFUNCTION("""COMPUTED_VALUE"""),-1.3535182424125622) -> -1.3535182 | AF33: =IFERROR(__xludf.DUMMYFUNCTION("""COMPUTED_VALUE"""),3.0512954927985443) -> 3.0512955 | AG33: =IFERROR(__xludf.DUMMYFUNCTION("""COMPUTED_VALUE"""),-0.2855100978201931) -> -0.2855101 | AK33: 100 | AL33: {=if(AL$20=$J14,"-", countif(indirect(address(row($J$2)+ VLOOKUP(AL$20,$J$3:$J$14,1),COLUMN($K$4))):indirect(address(row($J$2)+ VLOOKUP(AL$20,$J$3:$J$14,1),COLUMN($S$2)))>indirect(address(row($J14),COLUMN($K$2))):indirect(address(row($J14),COLUMN($S$2))),TRUE()))} -> 1 | AM33: {=if(AM$20=$J14,"-", countif(indirect(address(row($J$2)+ VLOOKUP(AM$20,$J$3:$J$14,1),COLUMN($K$4))):indirect(address(row($J$2)+ VLOOKUP(AM$20,$J$3:$J$14,1),COLUMN($S$2)))>indirect(address(row($J14),COLUMN($K$2))):indirect(address(row($J14),COLUMN($S$2))),TRUE()))} -> 3 | AN33: {=if(AN$20=$J14,"-", countif(indirect(address(row($J$2)+ VLOOKUP(AN$20,$J$3:$J$14,1),COLUMN($K$4))):indirect(address(row($J$2)+ VLOOKUP(AN$20,$J$3:$J$14,1),COLUMN($S$2)))>indirect(address(row($J14),COLUMN($K$2))):indirect(address(row($J14),COLUMN($S$2))),TRUE()))} -> 3 | AO33: {=if(AO$20=$J14,"-", countif(indirect(address(row($J$2)+ VLOOKUP(AO$20,$J$3:$J$14,1),COLUMN($K$4))):indirect(address(row($J$2)+ VLOOKUP(AO$20,$J$3:$J$14,1),COLUMN($S$2)))>indirect(address(row($J14),COLUMN($K$2))):indirect(address(row($J14),COLUMN($S$2))),TRUE()))} -> 7 | AP33: {=if(AP$20=$J14,"-", countif(indirect(address(row($J$2)+ VLOOKUP(AP$20,$J$3:$J$14,1),COLUMN($K$4))):indirect(address(row($J$2)+ VLOOKUP(AP$20,$J$3:$J$14,1),COLUMN($S$2)))>indirect(address(row($J14),COLUMN($K$2))):indirect(address(row($J14),COLUMN($S$2))),TRUE()))} -> 2 | AQ33: {=if(AQ$20=$J14,"-", countif(indirect(address(row($J$2)+ VLOOKUP(AQ$20,$J$3:$J$14,1),COLUMN($K$4))):indirect(address(row($J$2)+ VLOOKUP(AQ$20,$J$3:$J$14,1),COLUMN($S$2)))>indirect(address(row($J14),COLUMN($K$2))):indirect(address(row($J14),COLUMN($S$2))),TRUE()))} -> 1 | AR33: {=if(AR$20=$J14,"-", countif(indirect(address(row($J$2)+ VLOOKUP(AR$20,$J$3:$J$14,1),COLUMN($K$4))):indirect(address(row($J$2)+ VLOOKUP(AR$20,$J$3:$J$14,1),COLUMN($S$2)))>indirect(address(row($J14),COLUMN($K$2))):indirect(address(row($J14),COLUMN($S$2))),TRUE()))} -> 7 | AS33: {=if(AS$20=$J14,"-", countif(indirect(address(row($J$2)+ VLOOKUP(AS$20,$J$3:$J$14,1),COLUMN($K$4))):indirect(address(row($J$2)+ VLOOKUP(AS$20,$J$3:$J$14,1),COLUMN($S$2)))>indirect(address(row($J14),COLUMN($K$2))):indirect(address(row($J14),COLUMN($S$2))),TRUE()))} -> 8 | ... AW33: {=if(AW$20=$J14,"-", countif(indirect(address(row($J$2)+ VLOOKUP(AW$20,$J$3:$J$14,1),COLUMN($K$4))):indirect(address(row($J$2)+ VLOOKUP(AW$20,$J$3:$J$14,1),COLUMN($S$2)))>indirect(address(row($J14),COLUMN($K$2))):indirect(address(row($J14),COLUMN($S$2))),TRUE()))} -> - | AX33: 12 | AY33: {=INDIRECT("Draft!O"&TEXT(15-VLOOKUP(TRUE,I3:J14,2,0),"0"))} -> Keegan Murray | BA33: =IF($AY33="","", VLOOKUP($AY33,'Final Update'!$P$21:$AD1015,Column(G12),False)) -> 14.6 | BB33: =IF($AY33="","", VLOOKUP($AY33,'Final Update'!$P$21:$AD1015,Column(H12),False)) -> 2.7 | BC33: =IF($AY33="","", VLOOKUP($AY33,'Final Update'!$P$21:$AD1015,Column(I12),False)) -> 5.4 | BD33: =IF($AY33="","", VLOOKUP($AY33,'Final Update'!$P$21:$AD1015,Column(J12),False)) -> 1.6 | BE33: =IF($AY33="","", VLOOKUP($AY33,'Final Update'!$P$21:$AD1015,Column(K12),False)) -> 1 | BF33: =IF($AY33="","", VLOOKUP($AY33,'Final Update'!$P$21:$AD1015,Column(L12),False)) -> 0.8 | BG33: =IF($AY33="","", VLOOKUP($AY33,'Final Update'!$P$21:$AD1015,Column(M12),False)) -> 0.454 | BH33: =IF($AY33="","", VLOOKUP($AY33,'Final Update'!$P$21:$AD1015,Column(N12),False)) -> 0.836 | BI33: =IF($AY33="","", VLOOKUP($AY33,'Final Update'!$P$21:$AD1015,Column(O12),False)) -> 0.8 | BJ33: =IF($AY33="","", VLOOKUP($AY33,'Final Update'!$P$21:$AD1015,Column(C12),False)) -> SF,PF
A34: =VLOOKUP($F34,UpdateHashtag!$V$3:$Y$32,COLUMN(B$15),0) -> #N/A | B34: =VLOOKUP($F34,UpdateHashtag!$V$3:$Y$32,COLUMN(C$13),0) -> #N/A | C34: =VLOOKUP($F34,UpdateHashtag!$V$3:$Y$32,COLUMN(D$13),0) -> #N/A | D34: =SUM(A34:C34) -> #N/A | F34: =VLOOKUP(J34,UpdateBBM!$C$2:E1015,3,0) -> GSW | G34: 15 | H34: =IFERROR(__xludf.DUMMYFUNCTION("""COMPUTED_VALUE"""),15.0) -> 15 | I34: =IFERROR(__xludf.DUMMYFUNCTION("""COMPUTED_VALUE"""),12.4) -> 12.4 | J34: =IFERROR(__xludf.DUMMYFUNCTION("""COMPUTED_VALUE"""),"Stephen Curry") -> Stephen Curry | K34: =IFERROR(__xludf.DUMMYFUNCTION("""COMPUTED_VALUE"""),42.0) -> 42 | L34: =IFERROR(__xludf.DUMMYFUNCTION("""COMPUTED_VALUE"""),"PG,SG") -> PG,SG | M34: =IFERROR(__xludf.DUMMYFUNCTION("""COMPUTED_VALUE"""),5.117856705350448) -> 5.1178567 | N34: =IFERROR(__xludf.DUMMYFUNCTION("""COMPUTED_VALUE"""),5.117856705350448) -> 5.1178567 | O34: =IFERROR(__xludf.DUMMYFUNCTION("""COMPUTED_VALUE"""),0.0) -> 0 | P34: =IFERROR(__xludf.DUMMYFUNCTION("""COMPUTED_VALUE"""),26.4) -> 26.4 | Q34: =IFERROR(__xludf.DUMMYFUNCTION("""COMPUTED_VALUE"""),4.8) -> 4.8 | R34: =IFERROR(__xludf.DUMMYFUNCTION("""COMPUTED_VALUE"""),4.5) -> 4.5 | S34: =IFERROR(__xludf.DUMMYFUNCTION("""COMPUTED_VALUE"""),5.3) -> 5.3 | T34: =IFERROR(__xludf.DUMMYFUNCTION("""COMPUTED_VALUE"""),0.8) -> 0.8 | U34: =IFERROR(__xludf.DUMMYFUNCTION("""COMPUTED_VALUE"""),0.4) -> 0.4 | V34: =IFERROR(__xludf.DUMMYFUNCTION("""COMPUTED_VALUE"""),0.469) -> 0.469 | W34: =IFERROR(__xludf.DUMMYFUNCTION("""COMPUTED_VALUE"""),0.918) -> 0.918 | X34: =IFERROR(__xludf.DUMMYFUNCTION("""COMPUTED_VALUE"""),2.8) -> 2.8 | Y34: =IFERROR(__xludf.DUMMYFUNCTION("""COMPUTED_VALUE"""),1.6137490972350912) -> 1.6137491 | Z34: =IFERROR(__xludf.DUMMYFUNCTION("""COMPUTED_VALUE"""),3.0364797724391503) -> 3.0364798 | AA34: =IFERROR(__xludf.DUMMYFUNCTION("""COMPUTED_VALUE"""),-0.6154124052652897) -> -0.61541241 | AB34: =IFERROR(__xludf.DUMMYFUNCTION("""COMPUTED_VALUE"""),0.6215711726463173) -> 0.62157117 | AC34: =IFERROR(__xludf.DUMMYFUNCTION("""COMPUTED_VALUE"""),-0.5847290886782864) -> -0.58472909 | AD34: =IFERROR(__xludf.DUMMYFUNCTION("""COMPUTED_VALUE"""),-0.6155173428439339) -> -0.61551734 | AE34: =IFERROR(__xludf.DUMMYFUNCTION("""COMPUTED_VALUE"""),-0.6110471255842709) -> -0.61104713 | AF34: =IFERROR(__xludf.DUMMYFUNCTION("""COMPUTED_VALUE"""),1.9179571669019424) -> 1.9179572 | AG34: =IFERROR(__xludf.DUMMYFUNCTION("""COMPUTED_VALUE"""),-0.2607118843442064) -> -0.26071188 | AK34: 100 | AX34: 13 | AY34: {=INDIRECT("Draft!P"&TEXT(VLOOKUP(TRUE,I3:J14,2,0)+2,"0"))} -> Sam Hauser | BA34: =IF($AY34="","", VLOOKUP($AY34,'Final Update'!$P$21:$AD1015,Column(G13),False)) -> 9.6 | BB34: =IF($AY34="","", VLOOKUP($AY34,'Final Update'!$P$21:$AD1015,Column(H13),False)) -> 2.6 | BC34: =IF($AY34="","", VLOOKUP($AY34,'Final Update'!$P$21:$AD1015,Column(I13),False)) -> 3.8 | BD34: =IF($AY34="","", VLOOKUP($AY34,'Final Update'!$P$21:$AD1015,Column(J13),False)) -> 1.2 | BE34: =IF($AY34="","", VLOOKUP($AY34,'Final Update'!$P$21:$AD1015,Column(K13),False)) -> 0.5 | BF34: =IF($AY34="","", VLOOKUP($AY34,'Final Update'!$P$21:$AD1015,Column(L13),False)) -> 0.4 | BG34: =IF($AY34="","", VLOOKUP($AY34,'Final Update'!$P$21:$AD1015,Column(M13),False)) -> 0.45 | BH34: =IF($AY34="","", VLOOKUP($AY34,'Final Update'!$P$21:$AD1015,Column(N13),False)) -> 0.821 | BI34: =IF($AY34="","", VLOOKUP($AY34,'Final Update'!$P$21:$AD1015,Column(O13),False)) -> 0.5 | BJ34: =IF($AY34="","", VLOOKUP($AY34,'Final Update'!$P$21:$AD1015,Column(C13),False)) -> SF,PF
A35: =VLOOKUP($F35,UpdateHashtag!$V$3:$Y$32,COLUMN(B$15),0) -> 4 | B35: =VLOOKUP($F35,UpdateHashtag!$V$3:$Y$32,COLUMN(C$13),0) -> 4 | C35: =VLOOKUP($F35,UpdateHashtag!$V$3:$Y$32,COLUMN(D$13),0) -> 2 | D35: =SUM(A35:C35) -> 10 | F35: =VLOOKUP(J35,UpdateBBM!$C$2:E1015,3,0) -> DAL | G35: 16 | H35: =IFERROR(__xludf.DUMMYFUNCTION("""COMPUTED_VALUE"""),16.0) -> 16 | I35: =IFERROR(__xludf.DUMMYFUNCTION("""COMPUTED_VALUE"""),26.6) -> 26.6 | J35: =IFERROR(__xludf.DUMMYFUNCTION("""COMPUTED_VALUE"""),"Kyrie Irving") -> Kyrie Irving | K35: =IFERROR(__xludf.DUMMYFUNCTION("""COMPUTED_VALUE"""),66.0) -> 66 | L35: =IFERROR(__xludf.DUMMYFUNCTION("""COMPUTED_VALUE"""),"PG,SG") -> PG,SG | M35: =IFERROR(__xludf.DUMMYFUNCTION("""COMPUTED_VALUE"""),4.969174050321719) -> 4.9691741 | N35: =IFERROR(__xludf.DUMMYFUNCTION("""COMPUTED_VALUE"""),4.969174050321719) -> 4.9691741 | O35: =IFERROR(__xludf.DUMMYFUNCTION("""COMPUTED_VALUE"""),0.0) -> 0 | P35: =IFERROR(__xludf.DUMMYFUNCTION("""COMPUTED_VALUE"""),24.6) -> 24.6 | Q35: =IFERROR(__xludf.DUMMYFUNCTION("""COMPUTED_VALUE"""),3.0) -> 3 | R35: =IFERROR(__xludf.DUMMYFUNCTION("""COMPUTED_VALUE"""),4.9) -> 4.9 | S35: =IFERROR(__xludf.DUMMYFUNCTION("""COMPUTED_VALUE"""),5.2) -> 5.2 | T35: =IFERROR(__xludf.DUMMYFUNCTION("""COMPUTED_VALUE"""),1.2) -> 1.2 | U35: =IFERROR(__xludf.DUMMYFUNCTION("""COMPUTED_VALUE"""),0.6) -> 0.6 | V35: =IFERROR(__xludf.DUMMYFUNCTION("""COMPUTED_VALUE"""),0.495) -> 0.495 | W35: =IFERROR(__xludf.DUMMYFUNCTION("""COMPUTED_VALUE"""),0.907) -> 0.907 | X35: =IFERROR(__xludf.DUMMYFUNCTION("""COMPUTED_VALUE"""),1.8) -> 1.8 | Y35: =IFERROR(__xludf.DUMMYFUNCTION("""COMPUTED_VALUE"""),1.2885826618962994) -> 1.2885827 | Z35: =IFERROR(__xludf.DUMMYFUNCTION("""COMPUTED_VALUE"""),1.2450423898714034) -> 1.2450424 | AA35: =IFERROR(__xludf.DUMMYFUNCTION("""COMPUTED_VALUE"""),-0.4585069207654011) -> -0.45850692 | AB35: =IFERROR(__xludf.DUMMYFUNCTION("""COMPUTED_VALUE"""),0.5760094022241846) -> 0.5760094 | AC35: =IFERROR(__xludf.DUMMYFUNCTION("""COMPUTED_VALUE"""),0.7430016239596308) -> 0.74300162 | AD35: =IFERROR(__xludf.DUMMYFUNCTION("""COMPUTED_VALUE"""),-0.25872993873862127) -> -0.25872994 | AE35: =IFERROR(__xludf.DUMMYFUNCTION("""COMPUTED_VALUE"""),-0.04099985184481126) -> -0.040999852 | AF35: =IFERROR(__xludf.DUMMYFUNCTION("""COMPUTED_VALUE"""),1.4289975125379728) -> 1.4289975 | AG35: =IFERROR(__xludf.DUMMYFUNCTION("""COMPUTED_VALUE"""),-0.012729749584339901) -> -0.01272975 | AK35: 50 | AX35: 14 | AY35: {=INDIRECT("Draft!Q"&TEXT(15-VLOOKUP(TRUE,I3:J14,2,0),"0"))}
A36: =VLOOKUP($F36,UpdateHashtag!$V$3:$Y$32,COLUMN(B$15),0) -> 3 | B36: =VLOOKUP($F36,UpdateHashtag!$V$3:$Y$32,COLUMN(C$13),0) -> 4 | C36: =VLOOKUP($F36,UpdateHashtag!$V$3:$Y$32,COLUMN(D$13),0) -> 3 | D36: =SUM(A36:C36) -> 10 | F36: =VLOOKUP(J36,UpdateBBM!$C$2:E1015,3,0) -> LAL | G36: 17 | H36: =IFERROR(__xludf.DUMMYFUNCTION("""COMPUTED_VALUE"""),17.0) -> 17 | I36: =IFERROR(__xludf.DUMMYFUNCTION("""COMPUTED_VALUE"""),24.2) -> 24.2 | J36: =IFERROR(__xludf.DUMMYFUNCTION("""COMPUTED_VALUE"""),"LeBron James") -> LeBron James | K36: =IFERROR(__xludf.DUMMYFUNCTION("""COMPUTED_VALUE"""),65.0) -> 65 | L36: =IFERROR(__xludf.DUMMYFUNCTION("""COMPUTED_VALUE"""),"SF,PF") -> SF,PF | M36: =IFERROR(__xludf.DUMMYFUNCTION("""COMPUTED_VALUE"""),4.508392740326748) -> 4.5083927 | N36: =IFERROR(__xludf.DUMMYFUNCTION("""COMPUTED_VALUE"""),4.508392740326748) -> 4.5083927 | O36: =IFERROR(__xludf.DUMMYFUNCTION("""COMPUTED_VALUE"""),0.0) -> 0 | P36: =IFERROR(__xludf.DUMMYFUNCTION("""COMPUTED_VALUE"""),25.2) -> 25.2 | Q36: =IFERROR(__xludf.DUMMYFUNCTION("""COMPUTED_VALUE"""),2.1) -> 2.1 | R36: =IFERROR(__xludf.DUMMYFUNCTION("""COMPUTED_VALUE"""),7.2) -> 7.2 | S36: =IFERROR(__xludf.DUMMYFUNCTION("""COMPUTED_VALUE"""),8.2) -> 8.2 | T36: =IFERROR(__xludf.DUMMYFUNCTION("""COMPUTED_VALUE"""),1.1) -> 1.1 | U36: =IFERROR(__xludf.DUMMYFUNCTION("""COMPUTED_VALUE"""),0.5) -> 0.5 | V36: =IFERROR(__xludf.DUMMYFUNCTION("""COMPUTED_VALUE"""),0.535) -> 0.535 | W36: =IFERROR(__xludf.DUMMYFUNCTION("""COMPUTED_VALUE"""),0.758) -> 0.758 | X36: =IFERROR(__xludf.DUMMYFUNCTION("""COMPUTED_VALUE"""),3.3) -> 3.3 | Y36: =IFERROR(__xludf.DUMMYFUNCTION("""COMPUTED_VALUE"""),1.3969714736758965) -> 1.3969715 | Z36: =IFERROR(__xludf.DUMMYFUNCTION("""COMPUTED_VALUE"""),0.34932369858753) -> 0.3493237 | AA36: =IFERROR(__xludf.DUMMYFUNCTION("""COMPUTED_VALUE"""),0.44369961510895767) -> 0.44369962 | AB36: =IFERROR(__xludf.DUMMYFUNCTION("""COMPUTED_VALUE"""),1.9428625148881729) -> 1.9428625 | AC36: =IFERROR(__xludf.DUMMYFUNCTION("""COMPUTED_VALUE"""),0.41106894580015185) -> 0.41106895 | AD36: =IFERROR(__xludf.DUMMYFUNCTION("""COMPUTED_VALUE"""),-0.4371236407912776) -> -0.43712364 | AE36: =IFERROR(__xludf.DUMMYFUNCTION("""COMPUTED_VALUE"""),0.7862930847814558) -> 0.78629308 | AF36: =IFERROR(__xludf.DUMMYFUNCTION("""COMPUTED_VALUE"""),-0.7320745110022108) -> -0.73207451 | AG36: =IFERROR(__xludf.DUMMYFUNCTION("""COMPUTED_VALUE"""),-0.3847029517241397) -> -0.38470295 | AZ36: Average | BA36: =IFERROR(AVERAGE(SUMPRODUCT(BA$22:BA$35,$AK$22:$AK$35/100))/(SUM(OFFSET($AK$22,0,0,COUNT($BA$22:$BA$35)))/100),"") -> 17.530769 | BB36: =IFERROR(AVERAGE(SUMPRODUCT(BB$22:BB$35,$AK$22:$AK$35/100))/(SUM(OFFSET($AK$22,0,0,COUNT($BA$22:$BA$35)))/100),"") -> 1.8769231 | BC36: =IFERROR(AVERAGE(SUMPRODUCT(BC$22:BC$35,$AK$22:$AK$35/100))/(SUM(OFFSET($AK$22,0,0,COUNT($BA$22:$BA$35)))/100),"") -> 5.9076923 | BD36: =IFERROR(AVERAGE(SUMPRODUCT(BD$22:BD$35,$AK$22:$AK$35/100))/(SUM(OFFSET($AK$22,0,0,COUNT($BA$22:$BA$35)))/100),"") -> 4.0769231 | BE36: =IFERROR(AVERAGE(SUMPRODUCT(BE$22:BE$35,$AK$22:$AK$35/100))/(SUM(OFFSET($AK$22,0,0,COUNT($BA$22:$BA$35)))/100),"") -> 0.93846154 | BF36: =IFERROR(AVERAGE(SUMPRODUCT(BF$22:BF$35,$AK$22:$AK$35/100))/(SUM(OFFSET($AK$22,0,0,COUNT($BA$22:$BA$35)))/100),"") -> 0.53076923 | BG36: {=IFERROR(100*SUMPRODUCT(IFERROR(VLOOKUP(AY22:AY35,UpdateHashtag!$C:$S,6,False),"")*AK22:AK35/100)/SUMPRODUCT(IFERROR(VLOOKUP(AY22:AY35,UpdateHashtag!$C:$S,17,False),"")*AK22:AK35/100),"")} -> 47.444832 | BH36: {=IFERROR(100*SUMPRODUCT(IFERROR(VLOOKUP(AY22:AY35,UpdateHashtag!$C:$T,8,False),"")*AK22:AK35/100)/SUMPRODUCT(IFERROR(VLOOKUP(AY22:AY35,UpdateHashtag!$C:$T,18,False),"")*AK22:AK35/100),"")} -> 81.262729 | BI36: =AVERAGE(SUMPRODUCT(BH22:BH35,$B22:$B35/100))/(SUM(OFFSET($B22,0,0,COUNT(BH22:BH35)))/100) -> #N/A
A37: =VLOOKUP($F37,UpdateHashtag!$V$3:$Y$32,COLUMN(B$15),0) -> 4 | B37: =VLOOKUP($F37,UpdateHashtag!$V$3:$Y$32,COLUMN(C$13),0) -> 4 | C37: =VLOOKUP($F37,UpdateHashtag!$V$3:$Y$32,COLUMN(D$13),0) -> 4 | D37: =SUM(A37:C37) -> 12 | F37: =VLOOKUP(J37,UpdateBBM!$C$2:E1015,3,0) -> HOU | G37: 18 | H37: =IFERROR(__xludf.DUMMYFUNCTION("""COMPUTED_VALUE"""),18.0) -> 18 | I37: =IFERROR(__xludf.DUMMYFUNCTION("""COMPUTED_VALUE"""),18.3) -> 18.3 | J37: =IFERROR(__xludf.DUMMYFUNCTION("""COMPUTED_VALUE"""),"Kevin Durant") -> Kevin Durant | K37: =IFERROR(__xludf.DUMMYFUNCTION("""COMPUTED_VALUE"""),71.0) -> 71 | L37: =IFERROR(__xludf.DUMMYFUNCTION("""COMPUTED_VALUE"""),"SF,PF") -> SF,PF | M37: =IFERROR(__xludf.DUMMYFUNCTION("""COMPUTED_VALUE"""),4.3028943022364885) -> 4.3028943 | N37: =IFERROR(__xludf.DUMMYFUNCTION("""COMPUTED_VALUE"""),4.3028943022364885) -> 4.3028943 | O37: =IFERROR(__xludf.DUMMYFUNCTION("""COMPUTED_VALUE"""),0.0) -> 0 | P37: =IFERROR(__xludf.DUMMYFUNCTION("""COMPUTED_VALUE"""),25.7) -> 25.7 | Q37: =IFERROR(__xludf.DUMMYFUNCTION("""COMPUTED_VALUE"""),2.1) -> 2.1 | R37: =IFERROR(__xludf.DUMMYFUNCTION("""COMPUTED_VALUE"""),6.4) -> 6.4 | S37: =IFERROR(__xludf.DUMMYFUNCTION("""COMPUTED_VALUE"""),4.8) -> 4.8 | T37: =IFERROR(__xludf.DUMMYFUNCTION("""COMPUTED_VALUE"""),0.8) -> 0.8 | U37: =IFERROR(__xludf.DUMMYFUNCTION("""COMPUTED_VALUE"""),1.2) -> 1.2 | V37: =IFERROR(__xludf.DUMMYFUNCTION("""COMPUTED_VALUE"""),0.52) -> 0.52 | W37: =IFERROR(__xludf.DUMMYFUNCTION("""COMPUTED_VALUE"""),0.846) -> 0.846 | X37: =IFERROR(__xludf.DUMMYFUNCTION("""COMPUTED_VALUE"""),3.2) -> 3.2 | Y37: =IFERROR(__xludf.DUMMYFUNCTION("""COMPUTED_VALUE"""),1.4872954834922276) -> 1.4872955 | Z37: =IFERROR(__xludf.DUMMYFUNCTION("""COMPUTED_VALUE"""),0.34932369858753) -> 0.3493237 | AA37: =IFERROR(__xludf.DUMMYFUNCTION("""COMPUTED_VALUE"""),0.12988864610918074) -> 0.12988865 | AB37: =IFERROR(__xludf.DUMMYFUNCTION("""COMPUTED_VALUE"""),0.39376232053565263) -> 0.39376232 | AC37: =IFERROR(__xludf.DUMMYFUNCTION("""COMPUTED_VALUE"""),-0.5847290886782864) -> -0.58472909 | AD37: =IFERROR(__xludf.DUMMYFUNCTION("""COMPUTED_VALUE"""),0.8116322735773168) -> 0.81163227 | AE37: =IFERROR(__xludf.DUMMYFUNCTION("""COMPUTED_VALUE"""),0.49585185428237616) -> 0.49585185 | AF37: =IFERROR(__xludf.DUMMYFUNCTION("""COMPUTED_VALUE"""),0.9950447639003571) -> 0.99504476 | AG37: =IFERROR(__xludf.DUMMYFUNCTION("""COMPUTED_VALUE"""),-0.3599047382481531) -> -0.35990474 | AZ37: ZScore | BA37: =IFERROR((SUM(OFFSET(AK22,0,0,COUNT(BA22:BA35)))/100)*(BA36-'Final Update'!$B$1)/'Final Update'!$B$2,"") -> 0.1500216 | BB37: =IFERROR((SUM(OFFSET(AK22,0,0,COUNT(BA22:BA35)))/100)*(BB36-'Final Update'!$C$1)/'Final Update'!$C$2,"") -> 1.6550034 | BC37: =IFERROR((SUM(OFFSET(AK22,0,0,COUNT(BA22:BA35)))/100)*(BC36-'Final Update'!$D$1)/'Final Update'!$D$2,"") -> -0.82193535 | BD37: =IFERROR((SUM(OFFSET(AK22,0,0,COUNT(BA22:BA35)))/100)*(BD36-'Final Update'!$E$1)/'Final Update'!$E$2,"") -> 0.83610375 | BE37: =IFERROR((SUM(OFFSET(AK22,0,0,COUNT(BA22:BA35)))/100)*(BE36-'Final Update'!$F$1)/'Final Update'!$F$2,"") -> -1.6266899 | BF37: =IFERROR((SUM(OFFSET(AK22,0,0,COUNT(BA22:BA35)))/100)*(BF36-'Final Update'!$G$1)/'Final Update'!$G$2,"") -> -4.9690325 | BG37: {=SUMPRODUCT(IFERROR(VLOOKUP(AY22:AY35,'Final Update'!$A$4:$L$403,8,False)*AK22:AK35/100,""))} -> -4.3579364 | BH37: {=SUMPRODUCT(IFERROR(VLOOKUP(AY22:AY35,'Final Update'!$A$4:$L$403,10,False)*AK22:AK35/100,""))} -> 2.9663882 | BI37: =-(SUM(OFFSET(AK22,0,0,COUNT(BA22:BA35)))/100)*(BI36-'Final Update'!$L$1)/'Final Update'!$L$2 -> #N/A
A38: =VLOOKUP($F38,UpdateHashtag!$V$3:$Y$32,COLUMN(B$15),0) -> 4 | B38: =VLOOKUP($F38,UpdateHashtag!$V$3:$Y$32,COLUMN(C$13),0) -> 3 | C38: =VLOOKUP($F38,UpdateHashtag!$V$3:$Y$32,COLUMN(D$13),0) -> 3 | D38: =SUM(A38:C38) -> 10 | F38: =VLOOKUP(J38,UpdateBBM!$C$2:E1015,3,0) -> MIN | G38: 19 | H38: =IFERROR(__xludf.DUMMYFUNCTION("""COMPUTED_VALUE"""),19.0) -> 19 | I38: =IFERROR(__xludf.DUMMYFUNCTION("""COMPUTED_VALUE"""),10.1) -> 10.1 | J38: =IFERROR(__xludf.DUMMYFUNCTION("""COMPUTED_VALUE"""),"Anthony Edwards") -> Anthony Edwards | K38: =IFERROR(__xludf.DUMMYFUNCTION("""COMPUTED_VALUE"""),71.0) -> 71 | L38: =IFERROR(__xludf.DUMMYFUNCTION("""COMPUTED_VALUE"""),"SG,SF") -> SG,SF | M38: =IFERROR(__xludf.DUMMYFUNCTION("""COMPUTED_VALUE"""),4.276059412361503) -> 4.2760594 | N38: =IFERROR(__xludf.DUMMYFUNCTION("""COMPUTED_VALUE"""),4.276059412361503) -> 4.2760594 | O38: =IFERROR(__xludf.DUMMYFUNCTION("""COMPUTED_VALUE"""),0.0) -> 0 | P38: =IFERROR(__xludf.DUMMYFUNCTION("""COMPUTED_VALUE"""),26.2) -> 26.2 | Q38: =IFERROR(__xludf.DUMMYFUNCTION("""COMPUTED_VALUE"""),2.5) -> 2.5 | R38: =IFERROR(__xludf.DUMMYFUNCTION("""COMPUTED_VALUE"""),5.5) -> 5.5 | S38: =IFERROR(__xludf.DUMMYFUNCTION("""COMPUTED_VALUE"""),5.2) -> 5.2 | T38: =IFERROR(__xludf.DUMMYFUNCTION("""COMPUTED_VALUE"""),1.4) -> 1.4 | U38: =IFERROR(__xludf.DUMMYFUNCTION("""COMPUTED_VALUE"""),0.7) -> 0.7 | V38: =IFERROR(__xludf.DUMMYFUNCTION("""COMPUTED_VALUE"""),0.46) -> 0.46 | W38: =IFERROR(__xludf.DUMMYFUNCTION("""COMPUTED_VALUE"""),0.823) -> 0.823 | X38: =IFERROR(__xludf.DUMMYFUNCTION("""COMPUTED_VALUE"""),3.1) -> 3.1 | Y38: =IFERROR(__xludf.DUMMYFUNCTION("""COMPUTED_VALUE"""),1.5776194933085588) -> 1.5776195 | Z38: =IFERROR(__xludf.DUMMYFUNCTION("""COMPUTED_VALUE"""),0.7474208947136959) -> 0.74742089 | AA38: =IFERROR(__xludf.DUMMYFUNCTION("""COMPUTED_VALUE"""),-0.2231486940155685) -> -0.22314869 | AB38: =IFERROR(__xludf.DUMMYFUNCTION("""COMPUTED_VALUE"""),0.5760094022241846) -> 0.5760094 | AC38: =IFERROR(__xludf.DUMMYFUNCTION("""COMPUTED_VALUE"""),1.4068669802785894) -> 1.406867 | AD38: =IFERROR(__xludf.DUMMYFUNCTION("""COMPUTED_VALUE"""),-0.08033623668596498) -> -0.080336237 | AE38: =IFERROR(__xludf.DUMMYFUNCTION("""COMPUTED_VALUE"""),-0.8774537995895894) -> -0.8774538 | AF38: =IFERROR(__xludf.DUMMYFUNCTION("""COMPUTED_VALUE"""),0.6067340973101739) -> 0.6067341 | AG38: =IFERROR(__xludf.DUMMYFUNCTION("""COMPUTED_VALUE"""),-0.33510652477216646) -> -0.33510652
A39: =VLOOKUP($F39,UpdateHashtag!$V$3:$Y$32,COLUMN(B$15),0) -> 3 | B39: =VLOOKUP($F39,UpdateHashtag!$V$3:$Y$32,COLUMN(C$13),0) -> 4 | C39: =VLOOKUP($F39,UpdateHashtag!$V$3:$Y$32,COLUMN(D$13),0) -> 3 | D39: =SUM(A39:C39) -> 10 | F39: =VLOOKUP(J39,UpdateBBM!$C$2:E1015,3,0) -> TOR | G39: 20 | H39: =IFERROR(__xludf.DUMMYFUNCTION("""COMPUTED_VALUE"""),20.0) -> 20 | I39: =IFERROR(__xludf.DUMMYFUNCTION("""COMPUTED_VALUE"""),19.0) -> 19 | J39: =IFERROR(__xludf.DUMMYFUNCTION("""COMPUTED_VALUE"""),"Scottie Barnes") -> Scottie Barnes | K39: =IFERROR(__xludf.DUMMYFUNCTION("""COMPUTED_VALUE"""),66.0) -> 66 | L39: =IFERROR(__xludf.DUMMYFUNCTION("""COMPUTED_VALUE"""),"SG,SF,PF") -> SG,SF,PF | M39: =IFERROR(__xludf.DUMMYFUNCTION("""COMPUTED_VALUE"""),4.261179524108578) -> 4.2611795 | N39: =IFERROR(__xludf.DUMMYFUNCTION("""COMPUTED_VALUE"""),4.261179524108578) -> 4.2611795 | O39: =IFERROR(__xludf.DUMMYFUNCTION("""COMPUTED_VALUE"""),0.0) -> 0 | P39: =IFERROR(__xludf.DUMMYFUNCTION("""COMPUTED_VALUE"""),19.1) -> 19.1 | Q39: =IFERROR(__xludf.DUMMYFUNCTION("""COMPUTED_VALUE"""),1.7) -> 1.7 | R39: =IFERROR(__xludf.DUMMYFUNCTION("""COMPUTED_VALUE"""),8.3) -> 8.3 | S39: =IFERROR(__xludf.DUMMYFUNCTION("""COMPUTED_VALUE"""),6.0) -> 6 | T39: =IFERROR(__xludf.DUMMYFUNCTION("""COMPUTED_VALUE"""),1.3) -> 1.3 | U39: =IFERROR(__xludf.DUMMYFUNCTION("""COMPUTED_VALUE"""),1.5) -> 1.5 | V39: =IFERROR(__xludf.DUMMYFUNCTION("""COMPUTED_VALUE"""),0.479) -> 0.479 | W39: =IFERROR(__xludf.DUMMYFUNCTION("""COMPUTED_VALUE"""),0.791) -> 0.791 | X39: =IFERROR(__xludf.DUMMYFUNCTION("""COMPUTED_VALUE"""),2.4) -> 2.4 | Y39: =IFERROR(__xludf.DUMMYFUNCTION("""COMPUTED_VALUE"""),0.2950185539166565) -> 0.29501855 | Z39: =IFERROR(__xludf.DUMMYFUNCTION("""COMPUTED_VALUE"""),-0.04877349753863613) -> -0.048773498 | AA39: =IFERROR(__xludf.DUMMYFUNCTION("""COMPUTED_VALUE"""),0.8751896974836513) -> 0.8751897 | AB39: =IFERROR(__xludf.DUMMYFUNCTION("""COMPUTED_VALUE"""),0.940503565601248) -> 0.94050357 | AC39: =IFERROR(__xludf.DUMMYFUNCTION("""COMPUTED_VALUE"""),1.0749343021191105) -> 1.0749343 | AD39: =IFERROR(__xludf.DUMMYFUNCTION("""COMPUTED_VALUE"""),1.346813379735286) -> 1.3468134 | AE39: =IFERROR(__xludf.DUMMYFUNCTION("""COMPUTED_VALUE"""),-0.30386646216195506) -> -0.30386646 | AF39: =IFERROR(__xludf.DUMMYFUNCTION("""COMPUTED_VALUE"""),-0.060987446768477845) -> -0.060987447 | AG39: =IFERROR(__xludf.DUMMYFUNCTION("""COMPUTED_VALUE"""),-0.1615190304402598) -> -0.16151903
A40: =VLOOKUP($F40,UpdateHashtag!$V$3:$Y$32,COLUMN(B$15),0) -> 4 | B40: =VLOOKUP($F40,UpdateHashtag!$V$3:$Y$32,COLUMN(C$13),0) -> 4 | C40: =VLOOKUP($F40,UpdateHashtag!$V$3:$Y$32,COLUMN(D$13),0) -> 4 | D40: =SUM(A40:C40) -> 12 | F40: =VLOOKUP(J40,UpdateBBM!$C$2:E1015,3,0) -> HOU | G40: 21 | H40: =IFERROR(__xludf.DUMMYFUNCTION("""COMPUTED_VALUE"""),21.0) -> 21 | I40: =IFERROR(__xludf.DUMMYFUNCTION("""COMPUTED_VALUE"""),38.4) -> 38.4 | J40: =IFERROR(__xludf.DUMMYFUNCTION("""COMPUTED_VALUE"""),"Fred VanVleet") -> Fred VanVleet | K40: =IFERROR(__xludf.DUMMYFUNCTION("""COMPUTED_VALUE"""),71.0) -> 71 | L40: =IFERROR(__xludf.DUMMYFUNCTION("""COMPUTED_VALUE"""),"PG") -> PG | M40: =IFERROR(__xludf.DUMMYFUNCTION("""COMPUTED_VALUE"""),4.1217013365184005) -> 4.1217013 | N40: =IFERROR(__xludf.DUMMYFUNCTION("""COMPUTED_VALUE"""),4.1217013365184005) -> 4.1217013 | O40: =IFERROR(__xludf.DUMMYFUNCTION("""COMPUTED_VALUE"""),0.0) -> 0 | P40: =IFERROR(__xludf.DUMMYFUNCTION("""COMPUTED_VALUE"""),17.3) -> 17.3 | Q40: =IFERROR(__xludf.DUMMYFUNCTION("""COMPUTED_VALUE"""),2.9) -> 2.9 | R40: =IFERROR(__xludf.DUMMYFUNCTION("""COMPUTED_VALUE"""),3.7) -> 3.7 | S40: =IFERROR(__xludf.DUMMYFUNCTION("""COMPUTED_VALUE"""),7.6) -> 7.6 | T40: =IFERROR(__xludf.DUMMYFUNCTION("""COMPUTED_VALUE"""),1.4) -> 1.4 | U40: =IFERROR(__xludf.DUMMYFUNCTION("""COMPUTED_VALUE"""),0.7) -> 0.7 | V40: =IFERROR(__xludf.DUMMYFUNCTION("""COMPUTED_VALUE"""),0.406) -> 0.406 | W40: =IFERROR(__xludf.DUMMYFUNCTION("""COMPUTED_VALUE"""),0.874) -> 0.874 | X40: =IFERROR(__xludf.DUMMYFUNCTION("""COMPUTED_VALUE"""),1.8) -> 1.8 | Y40: =IFERROR(__xludf.DUMMYFUNCTION("""COMPUTED_VALUE"""),-0.03014788142213587) -> -0.030147881 | Z40: =IFERROR(__xludf.DUMMYFUNCTION("""COMPUTED_VALUE"""),1.145518090839862) -> 1.1455181 | AA40: =IFERROR(__xludf.DUMMYFUNCTION("""COMPUTED_VALUE"""),-0.9292233742650667) -> -0.92922337 | AB40: =IFERROR(__xludf.DUMMYFUNCTION("""COMPUTED_VALUE"""),1.669491892355375) -> 1.6694919 | AC40: =IFERROR(__xludf.DUMMYFUNCTION("""COMPUTED_VALUE"""),1.4068669802785894) -> 1.406867 | AD40: =IFERROR(__xludf.DUMMYFUNCTION("""COMPUTED_VALUE"""),-0.08033623668596498) -> -0.080336237 | AE40: =IFERROR(__xludf.DUMMYFUNCTION("""COMPUTED_VALUE"""),-1.5018244799362386) -> -1.5018245 | AF40: =IFERROR(__xludf.DUMMYFUNCTION("""COMPUTED_VALUE"""),0.9522616150020821) -> 0.95226161 | AG40: =IFERROR(__xludf.DUMMYFUNCTION("""COMPUTED_VALUE"""),-0.012729749584339901) -> -0.01272975
A41: =VLOOKUP($F41,UpdateHashtag!$V$3:$Y$32,COLUMN(B$15),0) -> 4 | B41: =VLOOKUP($F41,UpdateHashtag!$V$3:$Y$32,COLUMN(C$13),0) -> 3 | C41: =VLOOKUP($F41,UpdateHashtag!$V$3:$Y$32,COLUMN(D$13),0) -> 4 | D41: =SUM(A41:C41) -> 11 | F41: =VLOOKUP(J41,UpdateBBM!$C$2:E1015,3,0) -> SAC | G41: 22 | H41: =IFERROR(__xludf.DUMMYFUNCTION("""COMPUTED_VALUE"""),22.0) -> 22 | I41: =IFERROR(__xludf.DUMMYFUNCTION("""COMPUTED_VALUE"""),14.6) -> 14.6 | J41: =IFERROR(__xludf.DUMMYFUNCTION("""COMPUTED_VALUE"""),"Domantas Sabonis") -> Domantas Sabonis | K41: =IFERROR(__xludf.DUMMYFUNCTION("""COMPUTED_VALUE"""),66.0) -> 66 | L41: =IFERROR(__xludf.DUMMYFUNCTION("""COMPUTED_VALUE"""),"C") -> C | M41: =IFERROR(__xludf.DUMMYFUNCTION("""COMPUTED_VALUE"""),4.098197606086671) -> 4.0981976 | N41: =IFERROR(__xludf.DUMMYFUNCTION("""COMPUTED_VALUE"""),4.098197606086671) -> 4.0981976 | O41: =IFERROR(__xludf.DUMMYFUNCTION("""COMPUTED_VALUE"""),0.0) -> 0 | P41: =IFERROR(__xludf.DUMMYFUNCTION("""COMPUTED_VALUE"""),18.8) -> 18.8 | Q41: =IFERROR(__xludf.DUMMYFUNCTION("""COMPUTED_VALUE"""),0.4) -> 0.4 | R41: =IFERROR(__xludf.DUMMYFUNCTION("""COMPUTED_VALUE"""),13.2) -> 13.2 | S41: =IFERROR(__xludf.DUMMYFUNCTION("""COMPUTED_VALUE"""),7.9) -> 7.9 | T41: =IFERROR(__xludf.DUMMYFUNCTION("""COMPUTED_VALUE"""),0.9) -> 0.9 | U41: =IFERROR(__xludf.DUMMYFUNCTION("""COMPUTED_VALUE"""),0.6) -> 0.6 | V41: =IFERROR(__xludf.DUMMYFUNCTION("""COMPUTED_VALUE"""),0.6) -> 0.6 | W41: =IFERROR(__xludf.DUMMYFUNCTION("""COMPUTED_VALUE"""),0.725) -> 0.725 | X41: =IFERROR(__xludf.DUMMYFUNCTION("""COMPUTED_VALUE"""),3.2) -> 3.2 | Y41: =IFERROR(__xludf.DUMMYFUNCTION("""COMPUTED_VALUE"""),0.24082414802685767) -> 0.24082415 | Z41: =IFERROR(__xludf.DUMMYFUNCTION("""COMPUTED_VALUE"""),-1.3425893849486756) -> -1.3425894 | AA41: =IFERROR(__xludf.DUMMYFUNCTION("""COMPUTED_VALUE"""),2.797281882607285) -> 2.7972819 | AB41: =IFERROR(__xludf.DUMMYFUNCTION("""COMPUTED_VALUE"""),1.8061772036217743) -> 1.8061772 | AC41: =IFERROR(__xludf.DUMMYFUNCTION("""COMPUTED_VALUE"""),-0.25279641051880714) -> -0.25279641 | AD41: =IFERROR(__xludf.DUMMYFUNCTION("""COMPUTED_VALUE"""),-0.25872993873862127) -> -0.25872994 | AE41: =IFERROR(__xludf.DUMMYFUNCTION("""COMPUTED_VALUE"""),1.46235521471565) -> 1.4623552 | AF41: =IFERROR(__xludf.DUMMYFUNCTION("""COMPUTED_VALUE"""),-1.3370097553793137) -> -1.3370098 | AG41: =IFERROR(__xludf.DUMMYFUNCTION("""COMPUTED_VALUE"""),-0.3599047382481531) -> -0.35990474
A42: =VLOOKUP($F42,UpdateHashtag!$V$3:$Y$32,COLUMN(B$15),0) -> 4 | B42: =VLOOKUP($F42,UpdateHashtag!$V$3:$Y$32,COLUMN(C$13),0) -> 4 | C42: =VLOOKUP($F42,UpdateHashtag!$V$3:$Y$32,COLUMN(D$13),0) -> 4 | D42: =SUM(A42:C42) -> 12 | F42: =VLOOKUP(J42,UpdateBBM!$C$2:E1015,3,0) -> UTA | G42: 23 | H42: =IFERROR(__xludf.DUMMYFUNCTION("""COMPUTED_VALUE"""),23.0) -> 23 | I42: =IFERROR(__xludf.DUMMYFUNCTION("""COMPUTED_VALUE"""),30.1) -> 30.1 | J42: =IFERROR(__xludf.DUMMYFUNCTION("""COMPUTED_VALUE"""),"Lauri Markkanen") -> Lauri Markkanen | K42: =IFERROR(__xludf.DUMMYFUNCTION("""COMPUTED_VALUE"""),62.0) -> 62 | L42: =IFERROR(__xludf.DUMMYFUNCTION("""COMPUTED_VALUE"""),"SF,PF") -> SF,PF | M42: =IFERROR(__xludf.DUMMYFUNCTION("""COMPUTED_VALUE"""),4.008278678991504) -> 4.0082787 | N42: =IFERROR(__xludf.DUMMYFUNCTION("""COMPUTED_VALUE"""),4.008278678991504) -> 4.0082787 | O42: =IFERROR(__xludf.DUMMYFUNCTION("""COMPUTED_VALUE"""),0.0) -> 0 | P42: =IFERROR(__xludf.DUMMYFUNCTION("""COMPUTED_VALUE"""),24.5) -> 24.5 | Q42: =IFERROR(__xludf.DUMMYFUNCTION("""COMPUTED_VALUE"""),3.1) -> 3.1 | R42: =IFERROR(__xludf.DUMMYFUNCTION("""COMPUTED_VALUE"""),8.4) -> 8.4 | S42: =IFERROR(__xludf.DUMMYFUNCTION("""COMPUTED_VALUE"""),1.9) -> 1.9 | T42: =IFERROR(__xludf.DUMMYFUNCTION("""COMPUTED_VALUE"""),0.8) -> 0.8 | U42: =IFERROR(__xludf.DUMMYFUNCTION("""COMPUTED_VALUE"""),0.5) -> 0.5 | V42: =IFERROR(__xludf.DUMMYFUNCTION("""COMPUTED_VALUE"""),0.483) -> 0.483 | W42: =IFERROR(__xludf.DUMMYFUNCTION("""COMPUTED_VALUE"""),0.884) -> 0.884 | X42: =IFERROR(__xludf.DUMMYFUNCTION("""COMPUTED_VALUE"""),1.7) -> 1.7 | Y42: =IFERROR(__xludf.DUMMYFUNCTION("""COMPUTED_VALUE"""),1.270517859933033) -> 1.2705179 | Z42: =IFERROR(__xludf.DUMMYFUNCTION("""COMPUTED_VALUE"""),1.344566688902945) -> 1.3445667 | AA42: =IFERROR(__xludf.DUMMYFUNCTION("""COMPUTED_VALUE"""),0.9144160686086232) -> 0.91441607 | AB42: =IFERROR(__xludf.DUMMYFUNCTION("""COMPUTED_VALUE"""),-0.9275290217062028) -> -0.92752902 | AC42: =IFERROR(__xludf.DUMMYFUNCTION("""COMPUTED_VALUE"""),-0.5847290886782864) -> -0.58472909 | AD42: =IFERROR(__xludf.DUMMYFUNCTION("""COMPUTED_VALUE"""),-0.4371236407912776) -> -0.43712364 | AE42: =IFERROR(__xludf.DUMMYFUNCTION("""COMPUTED_VALUE"""),-0.27818799975029224) -> -0.278188 | AF42: =IFERROR(__xludf.DUMMYFUNCTION("""COMPUTED_VALUE"""),1.7667503268751126) -> 1.7667503 | AG42: =IFERROR(__xludf.DUMMYFUNCTION("""COMPUTED_VALUE"""),0.012068463891646777) -> 0.012068464
A43: =VLOOKUP($F43,UpdateHashtag!$V$3:$Y$32,COLUMN(B$15),0) -> 3 | B43: =VLOOKUP($F43,UpdateHashtag!$V$3:$Y$32,COLUMN(C$13),0) -> 4 | C43: =VLOOKUP($F43,UpdateHashtag!$V$3:$Y$32,COLUMN(D$13),0) -> 3 | D43: =SUM(A43:C43) -> 10 | F43: =VLOOKUP(J43,UpdateBBM!$C$2:E1015,3,0) -> PHO | G43: 24 | H43: =IFERROR(__xludf.DUMMYFUNCTION("""COMPUTED_VALUE"""),24.0) -> 24 | I43: =IFERROR(__xludf.DUMMYFUNCTION("""COMPUTED_VALUE"""),20.0) -> 20 | J43: =IFERROR(__xludf.DUMMYFUNCTION("""COMPUTED_VALUE"""),"Devin Booker") -> Devin Booker | K43: =IFERROR(__xludf.DUMMYFUNCTION("""COMPUTED_VALUE"""),66.0) -> 66 | L43: =IFERROR(__xludf.DUMMYFUNCTION("""COMPUTED_VALUE"""),"PG,SG") -> PG,SG | M43: =IFERROR(__xludf.DUMMYFUNCTION("""COMPUTED_VALUE"""),3.9743584287034825) -> 3.9743584 | N43: =IFERROR(__xludf.DUMMYFUNCTION("""COMPUTED_VALUE"""),3.9743584287034825) -> 3.9743584 | O43: =IFERROR(__xludf.DUMMYFUNCTION("""COMPUTED_VALUE"""),0.0) -> 0 | P43: =IFERROR(__xludf.DUMMYFUNCTION("""COMPUTED_VALUE"""),27.8) -> 27.8 | Q43: =IFERROR(__xludf.DUMMYFUNCTION("""COMPUTED_VALUE"""),2.2) -> 2.2 | R43: =IFERROR(__xludf.DUMMYFUNCTION("""COMPUTED_VALUE"""),4.5) -> 4.5 | S43: =IFERROR(__xludf.DUMMYFUNCTION("""COMPUTED_VALUE"""),5.5) -> 5.5 | T43: =IFERROR(__xludf.DUMMYFUNCTION("""COMPUTED_VALUE"""),1.0) -> 1 | U43: =IFERROR(__xludf.DUMMYFUNCTION("""COMPUTED_VALUE"""),0.4) -> 0.4 | V43: =IFERROR(__xludf.DUMMYFUNCTION("""COMPUTED_VALUE"""),0.49) -> 0.49 | W43: =IFERROR(__xludf.DUMMYFUNCTION("""COMPUTED_VALUE"""),0.873) -> 0.873 | X43: =IFERROR(__xludf.DUMMYFUNCTION("""COMPUTED_VALUE"""),2.7) -> 2.7 | Y43: =IFERROR(__xludf.DUMMYFUNCTION("""COMPUTED_VALUE"""),1.866656324720819) -> 1.8666563 | Z43: =IFERROR(__xludf.DUMMYFUNCTION("""COMPUTED_VALUE"""),0.44884799761907157) -> 0.448848 | AA43: =IFERROR(__xludf.DUMMYFUNCTION("""COMPUTED_VALUE"""),-0.6154124052652897) -> -0.61541241 | AB43: =IFERROR(__xludf.DUMMYFUNCTION("""COMPUTED_VALUE"""),0.7126947134905833) -> 0.71269471 | AC43: =IFERROR(__xludf.DUMMYFUNCTION("""COMPUTED_VALUE"""),0.07913626764067216) -> 0.079136268 | AD43: =IFERROR(__xludf.DUMMYFUNCTION("""COMPUTED_VALUE"""),-0.6155173428439339) -> -0.61551734 | AE43: =IFERROR(__xludf.DUMMYFUNCTION("""COMPUTED_VALUE"""),-0.162092383375328) -> -0.16209238 | AF43: =IFERROR(__xludf.DUMMYFUNCTION("""COMPUTED_VALUE"""),1.8804415847411744) -> 1.8804416 | AG43: =IFERROR(__xludf.DUMMYFUNCTION("""COMPUTED_VALUE"""),-0.23591367086821985) -> -0.23591367
A44: =VLOOKUP($F44,UpdateHashtag!$V$3:$Y$32,COLUMN(B$15),0) -> #N/A | B44: =VLOOKUP($F44,UpdateHashtag!$V$3:$Y$32,COLUMN(C$13),0) -> #N/A | C44: =VLOOKUP($F44,UpdateHashtag!$V$3:$Y$32,COLUMN(D$13),0) -> #N/A | D44: =SUM(A44:C44) -> #N/A | F44: =VLOOKUP(J44,UpdateBBM!$C$2:E1015,3,0) -> NYK | G44: 25 | H44: =IFERROR(__xludf.DUMMYFUNCTION("""COMPUTED_VALUE"""),25.0) -> 25 | I44: =IFERROR(__xludf.DUMMYFUNCTION("""COMPUTED_VALUE"""),22.1) -> 22.1 | J44: =IFERROR(__xludf.DUMMYFUNCTION("""COMPUTED_VALUE"""),"Karl-Anthony Towns") -> Karl-Anthony Towns | K44: =IFERROR(__xludf.DUMMYFUNCTION("""COMPUTED_VALUE"""),66.0) -> 66 | L44: =IFERROR(__xludf.DUMMYFUNCTION("""COMPUTED_VALUE"""),"PF,C") -> PF,C | M44: =IFERROR(__xludf.DUMMYFUNCTION("""COMPUTED_VALUE"""),3.866715015229273) -> 3.866715 | N44: =IFERROR(__xludf.DUMMYFUNCTION("""COMPUTED_VALUE"""),3.866715015229273) -> 3.866715 | O44: =IFERROR(__xludf.DUMMYFUNCTION("""COMPUTED_VALUE"""),0.0) -> 0 | P44: =IFERROR(__xludf.DUMMYFUNCTION("""COMPUTED_VALUE"""),21.4) -> 21.4 | Q44: =IFERROR(__xludf.DUMMYFUNCTION("""COMPUTED_VALUE"""),2.2) -> 2.2 | R44: =IFERROR(__xludf.DUMMYFUNCTION("""COMPUTED_VALUE"""),9.5) -> 9.5 | S44: =IFERROR(__xludf.DUMMYFUNCTION("""COMPUTED_VALUE"""),3.3) -> 3.3 | T44: =IFERROR(__xludf.DUMMYFUNCTION("""COMPUTED_VALUE"""),0.7) -> 0.7 | U44: =IFERROR(__xludf.DUMMYFUNCTION("""COMPUTED_VALUE"""),1.0) -> 1 | V44: =IFERROR(__xludf.DUMMYFUNCTION("""COMPUTED_VALUE"""),0.501) -> 0.501 | W44: =IFERROR(__xludf.DUMMYFUNCTION("""COMPUTED_VALUE"""),0.873) -> 0.873 | X44: =IFERROR(__xludf.DUMMYFUNCTION("""COMPUTED_VALUE"""),2.9) -> 2.9 | Y44: =IFERROR(__xludf.DUMMYFUNCTION("""COMPUTED_VALUE"""),0.7105089990717794) -> 0.710509 | Z44: =IFERROR(__xludf.DUMMYFUNCTION("""COMPUTED_VALUE"""),0.44884799761907157) -> 0.448848 | AA44: =IFERROR(__xludf.DUMMYFUNCTION("""COMPUTED_VALUE"""),1.3459061509833166) -> 1.3459062 | AB44: =IFERROR(__xludf.DUMMYFUNCTION("""COMPUTED_VALUE"""),-0.2896642357963416) -> -0.28966424 | AC44: =IFERROR(__xludf.DUMMYFUNCTION("""COMPUTED_VALUE"""),-0.9166617668377661) -> -0.91666177 | AD44: =IFERROR(__xludf.DUMMYFUNCTION("""COMPUTED_VALUE"""),0.45484486947200414) -> 0.45484487 | AE44: =IFERROR(__xludf.DUMMYFUNCTION("""COMPUTED_VALUE"""),0.07145014314375582) -> 0.071450143 | AF44: =IFERROR(__xludf.DUMMYFUNCTION("""COMPUTED_VALUE"""),1.4103311885558807) -> 1.4103312 | AG44: =IFERROR(__xludf.DUMMYFUNCTION("""COMPUTED_VALUE"""),-0.2855100978201931) -> -0.2855101
A45: =VLOOKUP($F45,UpdateHashtag!$V$3:$Y$32,COLUMN(B$15),0) -> #N/A | B45: =VLOOKUP($F45,UpdateHashtag!$V$3:$Y$32,COLUMN(C$13),0) -> #N/A | C45: =VLOOKUP($F45,UpdateHashtag!$V$3:$Y$32,COLUMN(D$13),0) -> #N/A | D45: =SUM(A45:C45) -> #N/A | F45: =VLOOKUP(J45,UpdateBBM!$C$2:E1015,3,0) -> NYK | G45: 26 | H45: =IFERROR(__xludf.DUMMYFUNCTION("""COMPUTED_VALUE"""),26.0) -> 26 | I45: =IFERROR(__xludf.DUMMYFUNCTION("""COMPUTED_VALUE"""),19.1) -> 19.1 | J45: =IFERROR(__xludf.DUMMYFUNCTION("""COMPUTED_VALUE"""),"Jalen Brunson") -> Jalen Brunson | K45: =IFERROR(__xludf.DUMMYFUNCTION("""COMPUTED_VALUE"""),71.0) -> 71 | L45: =IFERROR(__xludf.DUMMYFUNCTION("""COMPUTED_VALUE"""),"PG") -> PG | M45: =IFERROR(__xludf.DUMMYFUNCTION("""COMPUTED_VALUE"""),3.5652014548200865) -> 3.5652015 | N45: =IFERROR(__xludf.DUMMYFUNCTION("""COMPUTED_VALUE"""),3.5652014548200865) -> 3.5652015 | O45: =IFERROR(__xludf.DUMMYFUNCTION("""COMPUTED_VALUE"""),0.0) -> 0 | P45: =IFERROR(__xludf.DUMMYFUNCTION("""COMPUTED_VALUE"""),27.7) -> 27.7 | Q45: =IFERROR(__xludf.DUMMYFUNCTION("""COMPUTED_VALUE"""),2.7) -> 2.7 | R45: =IFERROR(__xludf.DUMMYFUNCTION("""COMPUTED_VALUE"""),3.7) -> 3.7 | S45: =IFERROR(__xludf.DUMMYFUNCTION("""COMPUTED_VALUE"""),7.0) -> 7 | T45: =IFERROR(__xludf.DUMMYFUNCTION("""COMPUTED_VALUE"""),0.9) -> 0.9 | U45: =IFERROR(__xludf.DUMMYFUNCTION("""COMPUTED_VALUE"""),0.2) -> 0.2 | V45: =IFERROR(__xludf.DUMMYFUNCTION("""COMPUTED_VALUE"""),0.484) -> 0.484 | W45: =IFERROR(__xludf.DUMMYFUNCTION("""COMPUTED_VALUE"""),0.839) -> 0.839 | X45: =IFERROR(__xludf.DUMMYFUNCTION("""COMPUTED_VALUE"""),2.3) -> 2.3 | Y45: =IFERROR(__xludf.DUMMYFUNCTION("""COMPUTED_VALUE"""),1.8485915227575525) -> 1.8485915 | Z45: =IFERROR(__xludf.DUMMYFUNCTION("""COMPUTED_VALUE"""),0.946469492776779) -> 0.94646949 | AA45: =IFERROR(__xludf.DUMMYFUNCTION("""COMPUTED_VALUE"""),-0.9292233742650667) -> -0.92922337 | AB45: =IFERROR(__xludf.DUMMYFUNCTION("""COMPUTED_VALUE"""),1.3961212698225776) -> 1.3961213 | AC45: =IFERROR(__xludf.DUMMYFUNCTION("""COMPUTED_VALUE"""),-0.25279641051880714) -> -0.25279641 | AD45: =IFERROR(__xludf.DUMMYFUNCTION("""COMPUTED_VALUE"""),-0.9723047469492465) -> -0.97230475 | AE45: =IFERROR(__xludf.DUMMYFUNCTION("""COMPUTED_VALUE"""),-0.3064549542470388) -> -0.30645495 | AF45: =IFERROR(__xludf.DUMMYFUNCTION("""COMPUTED_VALUE"""),0.9992147254583632) -> 0.99921473 | AG45: =IFERROR(__xludf.DUMMYFUNCTION("""COMPUTED_VALUE"""),-0.13672081696427313) -> -0.13672082
A46: =VLOOKUP($F46,UpdateHashtag!$V$3:$Y$32,COLUMN(B$15),0) -> 4 | B46: =VLOOKUP($F46,UpdateHashtag!$V$3:$Y$32,COLUMN(C$13),0) -> 4 | C46: =VLOOKUP($F46,UpdateHashtag!$V$3:$Y$32,COLUMN(D$13),0) -> 4 | D46: =SUM(A46:C46) -> 12 | F46: =VLOOKUP(J46,UpdateBBM!$C$2:E1015,3,0) -> PHI | G46: 27 | H46: =IFERROR(__xludf.DUMMYFUNCTION("""COMPUTED_VALUE"""),27.0) -> 27 | I46: =IFERROR(__xludf.DUMMYFUNCTION("""COMPUTED_VALUE"""),32.1) -> 32.1 | J46: =IFERROR(__xludf.DUMMYFUNCTION("""COMPUTED_VALUE"""),"Paul George") -> Paul George | K46: =IFERROR(__xludf.DUMMYFUNCTION("""COMPUTED_VALUE"""),66.0) -> 66 | L46: =IFERROR(__xludf.DUMMYFUNCTION("""COMPUTED_VALUE"""),"SG,SF,PF") -> SG,SF,PF | M46: =IFERROR(__xludf.DUMMYFUNCTION("""COMPUTED_VALUE"""),3.481204948854153) -> 3.4812049 | N46: =IFERROR(__xludf.DUMMYFUNCTION("""COMPUTED_VALUE"""),3.481204948854153) -> 3.4812049 | O46: =IFERROR(__xludf.DUMMYFUNCTION("""COMPUTED_VALUE"""),0.0) -> 0 | P46: =IFERROR(__xludf.DUMMYFUNCTION("""COMPUTED_VALUE"""),22.1) -> 22.1 | Q46: =IFERROR(__xludf.DUMMYFUNCTION("""COMPUTED_VALUE"""),3.0) -> 3 | R46: =IFERROR(__xludf.DUMMYFUNCTION("""COMPUTED_VALUE"""),5.0) -> 5 | S46: =IFERROR(__xludf.DUMMYFUNCTION("""COMPUTED_VALUE"""),3.4) -> 3.4 | T46: =IFERROR(__xludf.DUMMYFUNCTION("""COMPUTED_VALUE"""),1.4) -> 1.4 | U46: =IFERROR(__xludf.DUMMYFUNCTION("""COMPUTED_VALUE"""),0.4) -> 0.4 | V46: =IFERROR(__xludf.DUMMYFUNCTION("""COMPUTED_VALUE"""),0.465) -> 0.465 | W46: =IFERROR(__xludf.DUMMYFUNCTION("""COMPUTED_VALUE"""),0.889) -> 0.889 | X46: =IFERROR(__xludf.DUMMYFUNCTION("""COMPUTED_VALUE"""),2.4) -> 2.4 | Y46: =IFERROR(__xludf.DUMMYFUNCTION("""COMPUTED_VALUE"""),0.8369626128146436) -> 0.83696261 | Z46: =IFERROR(__xludf.DUMMYFUNCTION("""COMPUTED_VALUE"""),1.2450423898714034) -> 1.2450424 | AA46: =IFERROR(__xludf.DUMMYFUNCTION("""COMPUTED_VALUE"""),-0.41928054964042916) -> -0.41928055 | AB46: =IFERROR(__xludf.DUMMYFUNCTION("""COMPUTED_VALUE"""),-0.2441024653742086) -> -0.24410247 | AC46: =IFERROR(__xludf.DUMMYFUNCTION("""COMPUTED_VALUE"""),1.4068669802785894) -> 1.406867 | AD46: =IFERROR(__xludf.DUMMYFUNCTION("""COMPUTED_VALUE"""),-0.6155173428439339) -> -0.61551734 | AE46: =IFERROR(__xludf.DUMMYFUNCTION("""COMPUTED_VALUE"""),-0.6165112887863645) -> -0.61651129 | AF46: =IFERROR(__xludf.DUMMYFUNCTION("""COMPUTED_VALUE"""),1.4327523541883482) -> 1.4327524 | AG46: =IFERROR(__xludf.DUMMYFUNCTION("""COMPUTED_VALUE"""),-0.1615190304402598) -> -0.16151903
A47: =VLOOKUP($F47,UpdateHashtag!$V$3:$Y$32,COLUMN(B$15),0) -> 4 | B47: =VLOOKUP($F47,UpdateHashtag!$V$3:$Y$32,COLUMN(C$13),0) -> 4 | C47: =VLOOKUP($F47,UpdateHashtag!$V$3:$Y$32,COLUMN(D$13),0) -> 3 | D47: =SUM(A47:C47) -> 11 | F47: =VLOOKUP(J47,UpdateBBM!$C$2:E1015,3,0) -> OKC | G47: 28 | H47: =IFERROR(__xludf.DUMMYFUNCTION("""COMPUTED_VALUE"""),28.0) -> 28 | I47: =IFERROR(__xludf.DUMMYFUNCTION("""COMPUTED_VALUE"""),17.6) -> 17.6 | J47: =IFERROR(__xludf.DUMMYFUNCTION("""COMPUTED_VALUE"""),"Chet Holmgren") -> Chet Holmgren | K47: =IFERROR(__xludf.DUMMYFUNCTION("""COMPUTED_VALUE"""),66.0) -> 66 | L47: =IFERROR(__xludf.DUMMYFUNCTION("""COMPUTED_VALUE"""),"PF,C") -> PF,C | M47: =IFERROR(__xludf.DUMMYFUNCTION("""COMPUTED_VALUE"""),3.3631444111060267) -> 3.3631444 | N47: =IFERROR(__xludf.DUMMYFUNCTION("""COMPUTED_VALUE"""),3.3631444111060267) -> 3.3631444 | O47: =IFERROR(__xludf.DUMMYFUNCTION("""COMPUTED_VALUE"""),0.0) -> 0 | P47: =IFERROR(__xludf.DUMMYFUNCTION("""COMPUTED_VALUE"""),17.4) -> 17.4 | Q47: =IFERROR(__xludf.DUMMYFUNCTION("""COMPUTED_VALUE"""),1.7) -> 1.7 | R47: =IFERROR(__xludf.DUMMYFUNCTION("""COMPUTED_VALUE"""),8.1) -> 8.1 | S47: =IFERROR(__xludf.DUMMYFUNCTION("""COMPUTED_VALUE"""),2.6) -> 2.6 | T47: =IFERROR(__xludf.DUMMYFUNCTION("""COMPUTED_VALUE"""),0.7) -> 0.7 | U47: =IFERROR(__xludf.DUMMYFUNCTION("""COMPUTED_VALUE"""),2.3) -> 2.3 | V47: =IFERROR(__xludf.DUMMYFUNCTION("""COMPUTED_VALUE"""),0.53) -> 0.53 | W47: =IFERROR(__xludf.DUMMYFUNCTION("""COMPUTED_VALUE"""),0.793) -> 0.793 | X47: =IFERROR(__xludf.DUMMYFUNCTION("""COMPUTED_VALUE"""),1.7) -> 1.7 | Y47: =IFERROR(__xludf.DUMMYFUNCTION("""COMPUTED_VALUE"""),-0.012083079458870018) -> -0.012083079 | Z47: =IFERROR(__xludf.DUMMYFUNCTION("""COMPUTED_VALUE"""),-0.04877349753863613) -> -0.048773498 | AA47: =IFERROR(__xludf.DUMMYFUNCTION("""COMPUTED_VALUE"""),0.7967369552337066) -> 0.79673696 | AB47: =IFERROR(__xludf.DUMMYFUNCTION("""COMPUTED_VALUE"""),-0.6085966287512721) -> -0.60859663 | AC47: =IFERROR(__xludf.DUMMYFUNCTION("""COMPUTED_VALUE"""),-0.9166617668377661) -> -0.91666177 | AD47: =IFERROR(__xludf.DUMMYFUNCTION("""COMPUTED_VALUE"""),2.7739629961565364) -> 2.773963 | AE47: =IFERROR(__xludf.DUMMYFUNCTION("""COMPUTED_VALUE"""),0.47355201437337247) -> 0.47355201 | AF47: =IFERROR(__xludf.DUMMYFUNCTION("""COMPUTED_VALUE"""),-0.02372281280045713) -> -0.023722813 | AG47: =IFERROR(__xludf.DUMMYFUNCTION("""COMPUTED_VALUE"""),0.012068463891646777) -> 0.012068464
A48: =VLOOKUP($F48,UpdateHashtag!$V$3:$Y$32,COLUMN(B$15),0) -> #N/A | B48: =VLOOKUP($F48,UpdateHashtag!$V$3:$Y$32,COLUMN(C$13),0) -> #N/A | C48: =VLOOKUP($F48,UpdateHashtag!$V$3:$Y$32,COLUMN(D$13),0) -> #N/A | D48: =SUM(A48:C48) -> #N/A | F48: =VLOOKUP(J48,UpdateBBM!$C$2:E1015,3,0) -> SAS | G48: 29 | H48: =IFERROR(__xludf.DUMMYFUNCTION("""COMPUTED_VALUE"""),29.0) -> 29 | I48: =IFERROR(__xludf.DUMMYFUNCTION("""COMPUTED_VALUE"""),26.1) -> 26.1 | J48: =IFERROR(__xludf.DUMMYFUNCTION("""COMPUTED_VALUE"""),"De'Aaron Fox") -> De'Aaron Fox | K48: =IFERROR(__xludf.DUMMYFUNCTION("""COMPUTED_VALUE"""),66.0) -> 66 | L48: =IFERROR(__xludf.DUMMYFUNCTION("""COMPUTED_VALUE"""),"PG") -> PG | M48: =IFERROR(__xludf.DUMMYFUNCTION("""COMPUTED_VALUE"""),3.161900045871504) -> 3.1619 | N48: =IFERROR(__xludf.DUMMYFUNCTION("""COMPUTED_VALUE"""),3.161900045871504) -> 3.1619 | O48: =IFERROR(__xludf.DUMMYFUNCTION("""COMPUTED_VALUE"""),0.0) -> 0 | P48: =IFERROR(__xludf.DUMMYFUNCTION("""COMPUTED_VALUE"""),25.1) -> 25.1 | Q48: =IFERROR(__xludf.DUMMYFUNCTION("""COMPUTED_VALUE"""),2.5) -> 2.5 | R48: =IFERROR(__xludf.DUMMYFUNCTION("""COMPUTED_VALUE"""),4.2) -> 4.2 | S48: =IFERROR(__xludf.DUMMYFUNCTION("""COMPUTED_VALUE"""),5.5) -> 5.5 | T48: =IFERROR(__xludf.DUMMYFUNCTION("""COMPUTED_VALUE"""),1.7) -> 1.7 | U48: =IFERROR(__xludf.DUMMYFUNCTION("""COMPUTED_VALUE"""),0.4) -> 0.4 | V48: =IFERROR(__xludf.DUMMYFUNCTION("""COMPUTED_VALUE"""),0.472) -> 0.472 | W48: =IFERROR(__xludf.DUMMYFUNCTION("""COMPUTED_VALUE"""),0.759) -> 0.759 | X48: =IFERROR(__xludf.DUMMYFUNCTION("""COMPUTED_VALUE"""),2.5) -> 2.5 | Y48: =IFERROR(__xludf.DUMMYFUNCTION("""COMPUTED_VALUE"""),1.3789066717126306) -> 1.3789067 | Z48: =IFERROR(__xludf.DUMMYFUNCTION("""COMPUTED_VALUE"""),0.7474208947136959) -> 0.74742089 | AA48: =IFERROR(__xludf.DUMMYFUNCTION("""COMPUTED_VALUE"""),-0.733091518640206) -> -0.73309152 | AB48: =IFERROR(__xludf.DUMMYFUNCTION("""COMPUTED_VALUE"""),0.7126947134905833) -> 0.71269471 | AC48: =IFERROR(__xludf.DUMMYFUNCTION("""COMPUTED_VALUE"""),2.402665014757028) -> 2.402665 | AD48: =IFERROR(__xludf.DUMMYFUNCTION("""COMPUTED_VALUE"""),-0.6155173428439339) -> -0.61551734 | AE48: =IFERROR(__xludf.DUMMYFUNCTION("""COMPUTED_VALUE"""),-0.5657100941977983) -> -0.56571009 | AF48: =IFERROR(__xludf.DUMMYFUNCTION("""COMPUTED_VALUE"""),-0.7122425678444542) -> -0.71224257 | AG48: =IFERROR(__xludf.DUMMYFUNCTION("""COMPUTED_VALUE"""),-0.1863172439162465) -> -0.18631724
A49: =VLOOKUP($F49,UpdateHashtag!$V$3:$Y$32,COLUMN(B$15),0) -> 4 | B49: =VLOOKUP($F49,UpdateHashtag!$V$3:$Y$32,COLUMN(C$13),0) -> 4 | C49: =VLOOKUP($F49,UpdateHashtag!$V$3:$Y$32,COLUMN(D$13),0) -> 3 | D49: =SUM(A49:C49) -> 11 | F49: =VLOOKUP(J49,UpdateBBM!$C$2:E1015,3,0) -> MEM | G49: 30 | H49: =IFERROR(__xludf.DUMMYFUNCTION("""COMPUTED_VALUE"""),30.0) -> 30 | I49: =IFERROR(__xludf.DUMMYFUNCTION("""COMPUTED_VALUE"""),37.3) -> 37.3 | J49: =IFERROR(__xludf.DUMMYFUNCTION("""COMPUTED_VALUE"""),"Jaren Jackson Jr.") -> Jaren Jackson Jr. | K49: =IFERROR(__xludf.DUMMYFUNCTION("""COMPUTED_VALUE"""),71.0) -> 71 | L49: =IFERROR(__xludf.DUMMYFUNCTION("""COMPUTED_VALUE"""),"PF,C") -> PF,C | M49: =IFERROR(__xludf.DUMMYFUNCTION("""COMPUTED_VALUE"""),3.0541492707603997) -> 3.0541493 | N49: =IFERROR(__xludf.DUMMYFUNCTION("""COMPUTED_VALUE"""),3.0541492707603997) -> 3.0541493 | O49: =IFERROR(__xludf.DUMMYFUNCTION("""COMPUTED_VALUE"""),0.0) -> 0 | P49: =IFERROR(__xludf.DUMMYFUNCTION("""COMPUTED_VALUE"""),21.3) -> 21.3 | Q49: =IFERROR(__xludf.DUMMYFUNCTION("""COMPUTED_VALUE"""),1.7) -> 1.7 | R49: =IFERROR(__xludf.DUMMYFUNCTION("""COMPUTED_VALUE"""),6.3) -> 6.3 | S49: =IFERROR(__xludf.DUMMYFUNCTION("""COMPUTED_VALUE"""),1.7) -> 1.7 | T49: =IFERROR(__xludf.DUMMYFUNCTION("""COMPUTED_VALUE"""),1.2) -> 1.2 | U49: =IFERROR(__xludf.DUMMYFUNCTION("""COMPUTED_VALUE"""),1.9) -> 1.9 | V49: =IFERROR(__xludf.DUMMYFUNCTION("""COMPUTED_VALUE"""),0.47) -> 0.47 | W49: =IFERROR(__xludf.DUMMYFUNCTION("""COMPUTED_VALUE"""),0.8) -> 0.8 | X49: =IFERROR(__xludf.DUMMYFUNCTION("""COMPUTED_VALUE"""),2.1) -> 2.1 | Y49: =IFERROR(__xludf.DUMMYFUNCTION("""COMPUTED_VALUE"""),0.6924441971085136) -> 0.6924442 | Z49: =IFERROR(__xludf.DUMMYFUNCTION("""COMPUTED_VALUE"""),-0.04877349753863613) -> -0.048773498 | AA49: =IFERROR(__xludf.DUMMYFUNCTION("""COMPUTED_VALUE"""),0.09066227498420842) -> 0.090662275 | AB49: =IFERROR(__xludf.DUMMYFUNCTION("""COMPUTED_VALUE"""),-1.0186525625504688) -> -1.0186526 | AC49: =IFERROR(__xludf.DUMMYFUNCTION("""COMPUTED_VALUE"""),0.7430016239596308) -> 0.74300162 | AD49: =IFERROR(__xludf.DUMMYFUNCTION("""COMPUTED_VALUE"""),2.0603881879459114) -> 2.0603882 | AE49: =IFERROR(__xludf.DUMMYFUNCTION("""COMPUTED_VALUE"""),-0.5009186237970484) -> -0.50091862 | AF49: =IFERROR(__xludf.DUMMYFUNCTION("""COMPUTED_VALUE"""),0.10446949811012032) -> 0.1044695 | AG49: =IFERROR(__xludf.DUMMYFUNCTION("""COMPUTED_VALUE"""),-0.08712439001229988) -> -0.08712439
A50: =VLOOKUP($F50,UpdateHashtag!$V$3:$Y$32,COLUMN(B$15),0) -> 4 | B50: =VLOOKUP($F50,UpdateHashtag!$V$3:$Y$32,COLUMN(C$13),0) -> 4 | C50: =VLOOKUP($F50,UpdateHashtag!$V$3:$Y$32,COLUMN(D$13),0) -> 4 | D50: =SUM(A50:C50) -> 12 | F50: =VLOOKUP(J50,UpdateBBM!$C$2:E1015,3,0) -> PHI | G50: 31 | H50: =IFERROR(__xludf.DUMMYFUNCTION("""COMPUTED_VALUE"""),31.0) -> 31 | I50: =IFERROR(__xludf.DUMMYFUNCTION("""COMPUTED_VALUE"""),27.8) -> 27.8 | J50: =IFERROR(__xludf.DUMMYFUNCTION("""COMPUTED_VALUE"""),"Tyrese Maxey") -> Tyrese Maxey | K50: =IFERROR(__xludf.DUMMYFUNCTION("""COMPUTED_VALUE"""),66.0) -> 66 | L50: =IFERROR(__xludf.DUMMYFUNCTION("""COMPUTED_VALUE"""),"PG,SG") -> PG,SG | M50: =IFERROR(__xludf.DUMMYFUNCTION("""COMPUTED_VALUE"""),3.035366278078892) -> 3.0353663 | N50: =IFERROR(__xludf.DUMMYFUNCTION("""COMPUTED_VALUE"""),3.035366278078892) -> 3.0353663 | O50: =IFERROR(__xludf.DUMMYFUNCTION("""COMPUTED_VALUE"""),0.0) -> 0 | P50: =IFERROR(__xludf.DUMMYFUNCTION("""COMPUTED_VALUE"""),24.4) -> 24.4 | Q50: =IFERROR(__xludf.DUMMYFUNCTION("""COMPUTED_VALUE"""),3.0) -> 3 | R50: =IFERROR(__xludf.DUMMYFUNCTION("""COMPUTED_VALUE"""),3.5) -> 3.5 | S50: =IFERROR(__xludf.DUMMYFUNCTION("""COMPUTED_VALUE"""),5.9) -> 5.9 | T50: =IFERROR(__xludf.DUMMYFUNCTION("""COMPUTED_VALUE"""),1.0) -> 1 | U50: =IFERROR(__xludf.DUMMYFUNCTION("""COMPUTED_VALUE"""),0.3) -> 0.3 | V50: =IFERROR(__xludf.DUMMYFUNCTION("""COMPUTED_VALUE"""),0.462) -> 0.462 | W50: =IFERROR(__xludf.DUMMYFUNCTION("""COMPUTED_VALUE"""),0.859) -> 0.859 | X50: =IFERROR(__xludf.DUMMYFUNCTION("""COMPUTED_VALUE"""),1.6) -> 1.6 | Y50: =IFERROR(__xludf.DUMMYFUNCTION("""COMPUTED_VALUE"""),1.2524530579697666) -> 1.2524531 | Z50: =IFERROR(__xludf.DUMMYFUNCTION("""COMPUTED_VALUE"""),1.2450423898714034) -> 1.2450424 | AA50: =IFERROR(__xludf.DUMMYFUNCTION("""COMPUTED_VALUE"""),-1.007676116515011) -> -1.0076761 | AB50: =IFERROR(__xludf.DUMMYFUNCTION("""COMPUTED_VALUE"""),0.8949417951791153) -> 0.8949418 | AC50: =IFERROR(__xludf.DUMMYFUNCTION("""COMPUTED_VALUE"""),0.07913626764067216) -> 0.079136268 | AD50: =IFERROR(__xludf.DUMMYFUNCTION("""COMPUTED_VALUE"""),-0.7939110448965904) -> -0.79391104 | AE50: =IFERROR(__xludf.DUMMYFUNCTION("""COMPUTED_VALUE"""),-0.7685500775655639) -> -0.76855008 | AF50: =IFERROR(__xludf.DUMMYFUNCTION("""COMPUTED_VALUE"""),1.089387212512456) -> 1.0893872 | AG50: =IFERROR(__xludf.DUMMYFUNCTION("""COMPUTED_VALUE"""),0.036866677367633396) -> 0.036866677
A51: =VLOOKUP($F51,UpdateHashtag!$V$3:$Y$32,COLUMN(B$15),0) -> #N/A | B51: =VLOOKUP($F51,UpdateHashtag!$V$3:$Y$32,COLUMN(C$13),0) -> #N/A | C51: =VLOOKUP($F51,UpdateHashtag!$V$3:$Y$32,COLUMN(D$13),0) -> #N/A | D51: =SUM(A51:C51) -> #N/A | F51: =VLOOKUP(J51,UpdateBBM!$C$2:E1015,3,0) -> GSW | G51: 32 | H51: =IFERROR(__xludf.DUMMYFUNCTION("""COMPUTED_VALUE"""),32.0) -> 32 | I51: =IFERROR(__xludf.DUMMYFUNCTION("""COMPUTED_VALUE"""),46.0) -> 46 | J51: =IFERROR(__xludf.DUMMYFUNCTION("""COMPUTED_VALUE"""),"Jimmy Butler") -> Jimmy Butler | K51: =IFERROR(__xludf.DUMMYFUNCTION("""COMPUTED_VALUE"""),45.0) -> 45 | L51: =IFERROR(__xludf.DUMMYFUNCTION("""COMPUTED_VALUE"""),"SF,PF") -> SF,PF | M51: =IFERROR(__xludf.DUMMYFUNCTION("""COMPUTED_VALUE"""),2.818108945605094) -> 2.8181089 | N51: =IFERROR(__xludf.DUMMYFUNCTION("""COMPUTED_VALUE"""),2.818108945605094) -> 2.8181089 | O51: =IFERROR(__xludf.DUMMYFUNCTION("""COMPUTED_VALUE"""),0.0) -> 0 | P51: =IFERROR(__xludf.DUMMYFUNCTION("""COMPUTED_VALUE"""),20.7) -> 20.7 | Q51: =IFERROR(__xludf.DUMMYFUNCTION("""COMPUTED_VALUE"""),0.8) -> 0.8 | R51: =IFERROR(__xludf.DUMMYFUNCTION("""COMPUTED_VALUE"""),5.4) -> 5.4 | S51: =IFERROR(__xludf.DUMMYFUNCTION("""COMPUTED_VALUE"""),5.1) -> 5.1 | T51: =IFERROR(__xludf.DUMMYFUNCTION("""COMPUTED_VALUE"""),1.3) -> 1.3 | U51: =IFERROR(__xludf.DUMMYFUNCTION("""COMPUTED_VALUE"""),0.3) -> 0.3 | V51: =IFERROR(__xludf.DUMMYFUNCTION("""COMPUTED_VALUE"""),0.492) -> 0.492 | W51: =IFERROR(__xludf.DUMMYFUNCTION("""COMPUTED_VALUE"""),0.855) -> 0.855 | X51: =IFERROR(__xludf.DUMMYFUNCTION("""COMPUTED_VALUE"""),1.6) -> 1.6 | Y51: =IFERROR(__xludf.DUMMYFUNCTION("""COMPUTED_VALUE"""),0.5840553853289159) -> 0.58405539 | Z51: =IFERROR(__xludf.DUMMYFUNCTION("""COMPUTED_VALUE"""),-0.9444921888225095) -> -0.94449219 | AA51: =IFERROR(__xludf.DUMMYFUNCTION("""COMPUTED_VALUE"""),-0.2623750651405405) -> -0.26237507 | AB51: =IFERROR(__xludf.DUMMYFUNCTION("""COMPUTED_VALUE"""),0.5304476318020513) -> 0.53044763 | AC51: =IFERROR(__xludf.DUMMYFUNCTION("""COMPUTED_VALUE"""),1.0749343021191105) -> 1.0749343 | AD51: =IFERROR(__xludf.DUMMYFUNCTION("""COMPUTED_VALUE"""),-0.7939110448965904) -> -0.79391104 | AE51: =IFERROR(__xludf.DUMMYFUNCTION("""COMPUTED_VALUE"""),-0.07550790524894999) -> -0.075507905 | AF51: =IFERROR(__xludf.DUMMYFUNCTION("""COMPUTED_VALUE"""),1.7235989642734637) -> 1.723599 | AG51: =IFERROR(__xludf.DUMMYFUNCTION("""COMPUTED_VALUE"""),0.036866677367633396) -> 0.036866677
A52: =VLOOKUP($F52,UpdateHashtag!$V$3:$Y$32,COLUMN(B$15),0) -> 4 | B52: =VLOOKUP($F52,UpdateHashtag!$V$3:$Y$32,COLUMN(C$13),0) -> 4 | C52: =VLOOKUP($F52,UpdateHashtag!$V$3:$Y$32,COLUMN(D$13),0) -> 4 | D52: =SUM(A52:C52) -> 12 | F52: =VLOOKUP(J52,UpdateBBM!$C$2:E1015,3,0) -> MIA | G52: 33 | H52: =IFERROR(__xludf.DUMMYFUNCTION("""COMPUTED_VALUE"""),33.0) -> 33 | I52: =IFERROR(__xludf.DUMMYFUNCTION("""COMPUTED_VALUE"""),32.2) -> 32.2 | J52: =IFERROR(__xludf.DUMMYFUNCTION("""COMPUTED_VALUE"""),"Bam Adebayo") -> Bam Adebayo | K52: =IFERROR(__xludf.DUMMYFUNCTION("""COMPUTED_VALUE"""),71.0) -> 71 | L52: =IFERROR(__xludf.DUMMYFUNCTION("""COMPUTED_VALUE"""),"C") -> C | M52: =IFERROR(__xludf.DUMMYFUNCTION("""COMPUTED_VALUE"""),2.578835187755121) -> 2.5788352 | N52: =IFERROR(__xludf.DUMMYFUNCTION("""COMPUTED_VALUE"""),2.578835187755121) -> 2.5788352 | O52: =IFERROR(__xludf.DUMMYFUNCTION("""COMPUTED_VALUE"""),0.0) -> 0 | P52: =IFERROR(__xludf.DUMMYFUNCTION("""COMPUTED_VALUE"""),20.0) -> 20 | Q52: =IFERROR(__xludf.DUMMYFUNCTION("""COMPUTED_VALUE"""),0.2) -> 0.2 | R52: =IFERROR(__xludf.DUMMYFUNCTION("""COMPUTED_VALUE"""),10.4) -> 10.4 | S52: =IFERROR(__xludf.DUMMYFUNCTION("""COMPUTED_VALUE"""),3.9) -> 3.9 | T52: =IFERROR(__xludf.DUMMYFUNCTION("""COMPUTED_VALUE"""),1.2) -> 1.2 | U52: =IFERROR(__xludf.DUMMYFUNCTION("""COMPUTED_VALUE"""),0.9) -> 0.9 | V52: =IFERROR(__xludf.DUMMYFUNCTION("""COMPUTED_VALUE"""),0.531) -> 0.531 | W52: =IFERROR(__xludf.DUMMYFUNCTION("""COMPUTED_VALUE"""),0.743) -> 0.743 | X52: =IFERROR(__xludf.DUMMYFUNCTION("""COMPUTED_VALUE"""),2.4) -> 2.4 | Y52: =IFERROR(__xludf.DUMMYFUNCTION("""COMPUTED_VALUE"""),0.45760177158605236) -> 0.45760177 | Z52: =IFERROR(__xludf.DUMMYFUNCTION("""COMPUTED_VALUE"""),-1.5416379830117586) -> -1.541638 | AA52: =IFERROR(__xludf.DUMMYFUNCTION("""COMPUTED_VALUE"""),1.6989434911080659) -> 1.6989435 | AB52: =IFERROR(__xludf.DUMMYFUNCTION("""COMPUTED_VALUE"""),-0.016293613263543852) -> -0.016293613 | AC52: =IFERROR(__xludf.DUMMYFUNCTION("""COMPUTED_VALUE"""),0.7430016239596308) -> 0.74300162 | AD52: =IFERROR(__xludf.DUMMYFUNCTION("""COMPUTED_VALUE"""),0.27645116741934783) -> 0.27645117 | AE52: =IFERROR(__xludf.DUMMYFUNCTION("""COMPUTED_VALUE"""),0.5918185489978054) -> 0.59181855 | AF52: =IFERROR(__xludf.DUMMYFUNCTION("""COMPUTED_VALUE"""),-1.0111687716119777) -> -1.0111688 | AG52: =IFERROR(__xludf.DUMMYFUNCTION("""COMPUTED_VALUE"""),-0.1615190304402598) -> -0.16151903
A53: =VLOOKUP($F53,UpdateHashtag!$V$3:$Y$32,COLUMN(B$15),0) -> #N/A | B53: =VLOOKUP($F53,UpdateHashtag!$V$3:$Y$32,COLUMN(C$13),0) -> #N/A | C53: =VLOOKUP($F53,UpdateHashtag!$V$3:$Y$32,COLUMN(D$13),0) -> #N/A | D53: =SUM(A53:C53) -> #N/A | F53: =VLOOKUP(J53,UpdateBBM!$C$2:E1015,3,0) -> #N/A | G53: 34 | H53: =IFERROR(__xludf.DUMMYFUNCTION("""COMPUTED_VALUE"""),34.0) -> 34 | I53: =IFERROR(__xludf.DUMMYFUNCTION("""COMPUTED_VALUE"""),27.7) -> 27.7 | J53: =IFERROR(__xludf.DUMMYFUNCTION("""COMPUTED_VALUE"""),"Alperen Sengün") -> Alperen Sengün | K53: =IFERROR(__xludf.DUMMYFUNCTION("""COMPUTED_VALUE"""),58.0) -> 58 | L53: =IFERROR(__xludf.DUMMYFUNCTION("""COMPUTED_VALUE"""),"C") -> C | M53: =IFERROR(__xludf.DUMMYFUNCTION("""COMPUTED_VALUE"""),2.5245255067472074) -> 2.5245255 | N53: =IFERROR(__xludf.DUMMYFUNCTION("""COMPUTED_VALUE"""),2.5245255067472074) -> 2.5245255 | O53: =IFERROR(__xludf.DUMMYFUNCTION("""COMPUTED_VALUE"""),0.0) -> 0 | P53: =IFERROR(__xludf.DUMMYFUNCTION("""COMPUTED_VALUE"""),19.4) -> 19.4 | Q53: =IFERROR(__xludf.DUMMYFUNCTION("""COMPUTED_VALUE"""),0.4) -> 0.4 | R53: =IFERROR(__xludf.DUMMYFUNCTION("""COMPUTED_VALUE"""),9.9) -> 9.9 | S53: =IFERROR(__xludf.DUMMYFUNCTION("""COMPUTED_VALUE"""),5.4) -> 5.4 | T53: =IFERROR(__xludf.DUMMYFUNCTION("""COMPUTED_VALUE"""),1.2) -> 1.2 | U53: =IFERROR(__xludf.DUMMYFUNCTION("""COMPUTED_VALUE"""),0.8) -> 0.8 | V53: =IFERROR(__xludf.DUMMYFUNCTION("""COMPUTED_VALUE"""),0.544) -> 0.544 | W53: =IFERROR(__xludf.DUMMYFUNCTION("""COMPUTED_VALUE"""),0.713) -> 0.713 | X53: =IFERROR(__xludf.DUMMYFUNCTION("""COMPUTED_VALUE"""),2.8) -> 2.8 | Y53: =IFERROR(__xludf.DUMMYFUNCTION("""COMPUTED_VALUE"""),0.34921295980645467) -> 0.34921296 | Z53: =IFERROR(__xludf.DUMMYFUNCTION("""COMPUTED_VALUE"""),-1.3425893849486756) -> -1.3425894 | AA53: =IFERROR(__xludf.DUMMYFUNCTION("""COMPUTED_VALUE"""),1.502811635483205) -> 1.5028116 | AB53: =IFERROR(__xludf.DUMMYFUNCTION("""COMPUTED_VALUE"""),0.6671329430684506) -> 0.66713294 | AC53: =IFERROR(__xludf.DUMMYFUNCTION("""COMPUTED_VALUE"""),0.7430016239596308) -> 0.74300162 | AD53: =IFERROR(__xludf.DUMMYFUNCTION("""COMPUTED_VALUE"""),0.09805746536669153) -> 0.098057465 | AE53: =IFERROR(__xludf.DUMMYFUNCTION("""COMPUTED_VALUE"""),0.7676101483556568) -> 0.76761015 | AF53: =IFERROR(__xludf.DUMMYFUNCTION("""COMPUTED_VALUE"""),-1.5664936690619253) -> -1.5664937 | AG53: =IFERROR(__xludf.DUMMYFUNCTION("""COMPUTED_VALUE"""),-0.2607118843442064) -> -0.26071188
A54: =VLOOKUP($F54,UpdateHashtag!$V$3:$Y$32,COLUMN(B$15),0) -> 4 | B54: =VLOOKUP($F54,UpdateHashtag!$V$3:$Y$32,COLUMN(C$13),0) -> 4 | C54: =VLOOKUP($F54,UpdateHashtag!$V$3:$Y$32,COLUMN(D$13),0) -> 3 | D54: =SUM(A54:C54) -> 11 | F54: =VLOOKUP(J54,UpdateBBM!$C$2:E1015,3,0) -> ATL | G54: 35 | H54: =IFERROR(__xludf.DUMMYFUNCTION("""COMPUTED_VALUE"""),35.0) -> 35 | I54: =IFERROR(__xludf.DUMMYFUNCTION("""COMPUTED_VALUE"""),41.4) -> 41.4 | J54: =IFERROR(__xludf.DUMMYFUNCTION("""COMPUTED_VALUE"""),"Jalen Johnson") -> Jalen Johnson | K54: =IFERROR(__xludf.DUMMYFUNCTION("""COMPUTED_VALUE"""),71.0) -> 71 | L54: =IFERROR(__xludf.DUMMYFUNCTION("""COMPUTED_VALUE"""),"PF") -> PF | M54: =IFERROR(__xludf.DUMMYFUNCTION("""COMPUTED_VALUE"""),2.460612775692953) -> 2.4606128 | N54: =IFERROR(__xludf.DUMMYFUNCTION("""COMPUTED_VALUE"""),2.460612775692953) -> 2.4606128 | O54: =IFERROR(__xludf.DUMMYFUNCTION("""COMPUTED_VALUE"""),0.0) -> 0 | P54: =IFERROR(__xludf.DUMMYFUNCTION("""COMPUTED_VALUE"""),18.2) -> 18.2 | Q54: =IFERROR(__xludf.DUMMYFUNCTION("""COMPUTED_VALUE"""),1.4) -> 1.4 | R54: =IFERROR(__xludf.DUMMYFUNCTION("""COMPUTED_VALUE"""),9.2) -> 9.2 | S54: =IFERROR(__xludf.DUMMYFUNCTION("""COMPUTED_VALUE"""),3.5) -> 3.5 | T54: =IFERROR(__xludf.DUMMYFUNCTION("""COMPUTED_VALUE"""),1.3) -> 1.3 | U54: =IFERROR(__xludf.DUMMYFUNCTION("""COMPUTED_VALUE"""),1.0) -> 1 | V54: =IFERROR(__xludf.DUMMYFUNCTION("""COMPUTED_VALUE"""),0.503) -> 0.503 | W54: =IFERROR(__xludf.DUMMYFUNCTION("""COMPUTED_VALUE"""),0.747) -> 0.747 | X54: =IFERROR(__xludf.DUMMYFUNCTION("""COMPUTED_VALUE"""),1.7) -> 1.7 | Y54: =IFERROR(__xludf.DUMMYFUNCTION("""COMPUTED_VALUE"""),0.13243533624726) -> 0.13243534 | Z54: =IFERROR(__xludf.DUMMYFUNCTION("""COMPUTED_VALUE"""),-0.34734639463326067) -> -0.34734639 | AA54: =IFERROR(__xludf.DUMMYFUNCTION("""COMPUTED_VALUE"""),1.2282270376084) -> 1.228227 | AB54: =IFERROR(__xludf.DUMMYFUNCTION("""COMPUTED_VALUE"""),-0.1985406949520756) -> -0.19854069 | AC54: =IFERROR(__xludf.DUMMYFUNCTION("""COMPUTED_VALUE"""),1.0749343021191105) -> 1.0749343 | AD54: =IFERROR(__xludf.DUMMYFUNCTION("""COMPUTED_VALUE"""),0.45484486947200414) -> 0.45484487 | AE54: =IFERROR(__xludf.DUMMYFUNCTION("""COMPUTED_VALUE"""),0.1039898559398676) -> 0.10398986 | AF54: =IFERROR(__xludf.DUMMYFUNCTION("""COMPUTED_VALUE"""),-0.49208126225693666) -> -0.49208126 | AG54: =IFERROR(__xludf.DUMMYFUNCTION("""COMPUTED_VALUE"""),0.012068463891646777) -> 0.012068464
A55: =VLOOKUP($F55,UpdateHashtag!$V$3:$Y$32,COLUMN(B$15),0) -> #N/A | B55: =VLOOKUP($F55,UpdateHashtag!$V$3:$Y$32,COLUMN(C$13),0) -> #N/A | C55: =VLOOKUP($F55,UpdateHashtag!$V$3:$Y$32,COLUMN(D$13),0) -> #N/A | D55: =SUM(A55:C55) -> #N/A | F55: =VLOOKUP(J55,UpdateBBM!$C$2:E1015,3,0) -> NOR | G55: 36 | H55: =IFERROR(__xludf.DUMMYFUNCTION("""COMPUTED_VALUE"""),36.0) -> 36 | I55: =IFERROR(__xludf.DUMMYFUNCTION("""COMPUTED_VALUE"""),35.6) -> 35.6 | J55: =IFERROR(__xludf.DUMMYFUNCTION("""COMPUTED_VALUE"""),"Dejounte Murray") -> Dejounte Murray | K55: =IFERROR(__xludf.DUMMYFUNCTION("""COMPUTED_VALUE"""),71.0) -> 71 | L55: =IFERROR(__xludf.DUMMYFUNCTION("""COMPUTED_VALUE"""),"PG,SG") -> PG,SG | M55: =IFERROR(__xludf.DUMMYFUNCTION("""COMPUTED_VALUE"""),2.427604478469864) -> 2.4276045 | N55: =IFERROR(__xludf.DUMMYFUNCTION("""COMPUTED_VALUE"""),2.427604478469864) -> 2.4276045 | O55: =IFERROR(__xludf.DUMMYFUNCTION("""COMPUTED_VALUE"""),0.0) -> 0 | P55: =IFERROR(__xludf.DUMMYFUNCTION("""COMPUTED_VALUE"""),19.5) -> 19.5 | Q55: =IFERROR(__xludf.DUMMYFUNCTION("""COMPUTED_VALUE"""),2.2) -> 2.2 | R55: =IFERROR(__xludf.DUMMYFUNCTION("""COMPUTED_VALUE"""),5.2) -> 5.2 | S55: =IFERROR(__xludf.DUMMYFUNCTION("""COMPUTED_VALUE"""),6.5) -> 6.5 | T55: =IFERROR(__xludf.DUMMYFUNCTION("""COMPUTED_VALUE"""),1.4) -> 1.4 | U55: =IFERROR(__xludf.DUMMYFUNCTION("""COMPUTED_VALUE"""),0.3) -> 0.3 | V55: =IFERROR(__xludf.DUMMYFUNCTION("""COMPUTED_VALUE"""),0.462) -> 0.462 | W55: =IFERROR(__xludf.DUMMYFUNCTION("""COMPUTED_VALUE"""),0.809) -> 0.809 | X55: =IFERROR(__xludf.DUMMYFUNCTION("""COMPUTED_VALUE"""),2.1) -> 2.1 | Y55: =IFERROR(__xludf.DUMMYFUNCTION("""COMPUTED_VALUE"""),0.3672777617697212) -> 0.36727776 | Z55: =IFERROR(__xludf.DUMMYFUNCTION("""COMPUTED_VALUE"""),0.44884799761907157) -> 0.448848 | AA55: =IFERROR(__xludf.DUMMYFUNCTION("""COMPUTED_VALUE"""),-0.3408278073904848) -> -0.34082781 | AB55: =IFERROR(__xludf.DUMMYFUNCTION("""COMPUTED_VALUE"""),1.1683124177119129) -> 1.1683124 | AC55: =IFERROR(__xludf.DUMMYFUNCTION("""COMPUTED_VALUE"""),1.4068669802785894) -> 1.406867 | AD55: =IFERROR(__xludf.DUMMYFUNCTION("""COMPUTED_VALUE"""),-0.7939110448965904) -> -0.79391104 | AE55: =IFERROR(__xludf.DUMMYFUNCTION("""COMPUTED_VALUE"""),-0.6704373017061303) -> -0.6704373 | AF55: =IFERROR(__xludf.DUMMYFUNCTION("""COMPUTED_VALUE"""),0.1346888201994836) -> 0.13468882 | AG55: =IFERROR(__xludf.DUMMYFUNCTION("""COMPUTED_VALUE"""),-0.08712439001229988) -> -0.08712439
A56: =VLOOKUP($F56,UpdateHashtag!$V$3:$Y$32,COLUMN(B$15),0) -> 4 | B56: =VLOOKUP($F56,UpdateHashtag!$V$3:$Y$32,COLUMN(C$13),0) -> 4 | C56: =VLOOKUP($F56,UpdateHashtag!$V$3:$Y$32,COLUMN(D$13),0) -> 3 | D56: =SUM(A56:C56) -> 11 | F56: =VLOOKUP(J56,UpdateBBM!$C$2:E1015,3,0) -> OKC | G56: 37 | H56: =IFERROR(__xludf.DUMMYFUNCTION("""COMPUTED_VALUE"""),37.0) -> 37 | I56: =IFERROR(__xludf.DUMMYFUNCTION("""COMPUTED_VALUE"""),36.0) -> 36 | J56: =IFERROR(__xludf.DUMMYFUNCTION("""COMPUTED_VALUE"""),"Jalen Williams") -> Jalen Williams | K56: =IFERROR(__xludf.DUMMYFUNCTION("""COMPUTED_VALUE"""),75.0) -> 75 | L56: =IFERROR(__xludf.DUMMYFUNCTION("""COMPUTED_VALUE"""),"SG,SF,PF") -> SG,SF,PF | M56: =IFERROR(__xludf.DUMMYFUNCTION("""COMPUTED_VALUE"""),2.310625432136085) -> 2.3106254 | N56: =IFERROR(__xludf.DUMMYFUNCTION("""COMPUTED_VALUE"""),2.310625432136085) -> 2.3106254 | O56: =IFERROR(__xludf.DUMMYFUNCTION("""COMPUTED_VALUE"""),0.0) -> 0 | P56: =IFERROR(__xludf.DUMMYFUNCTION("""COMPUTED_VALUE"""),20.0) -> 20 | Q56: =IFERROR(__xludf.DUMMYFUNCTION("""COMPUTED_VALUE"""),1.7) -> 1.7 | R56: =IFERROR(__xludf.DUMMYFUNCTION("""COMPUTED_VALUE"""),4.6) -> 4.6 | S56: =IFERROR(__xludf.DUMMYFUNCTION("""COMPUTED_VALUE"""),4.9) -> 4.9 | T56: =IFERROR(__xludf.DUMMYFUNCTION("""COMPUTED_VALUE"""),1.2) -> 1.2 | U56: =IFERROR(__xludf.DUMMYFUNCTION("""COMPUTED_VALUE"""),0.6) -> 0.6 | V56: =IFERROR(__xludf.DUMMYFUNCTION("""COMPUTED_VALUE"""),0.536) -> 0.536 | W56: =IFERROR(__xludf.DUMMYFUNCTION("""COMPUTED_VALUE"""),0.822) -> 0.822 | X56: =IFERROR(__xludf.DUMMYFUNCTION("""COMPUTED_VALUE"""),1.8) -> 1.8 | Y56: =IFERROR(__xludf.DUMMYFUNCTION("""COMPUTED_VALUE"""),0.45760177158605236) -> 0.45760177 | Z56: =IFERROR(__xludf.DUMMYFUNCTION("""COMPUTED_VALUE"""),-0.04877349753863613) -> -0.048773498 | AA56: =IFERROR(__xludf.DUMMYFUNCTION("""COMPUTED_VALUE"""),-0.5761860341403178) -> -0.57618603 | AB56: =IFERROR(__xludf.DUMMYFUNCTION("""COMPUTED_VALUE"""),0.43932409095778585) -> 0.43932409 | AC56: =IFERROR(__xludf.DUMMYFUNCTION("""COMPUTED_VALUE"""),0.7430016239596308) -> 0.74300162 | AD56: =IFERROR(__xludf.DUMMYFUNCTION("""COMPUTED_VALUE"""),-0.25872993873862127) -> -0.25872994 | AE56: =IFERROR(__xludf.DUMMYFUNCTION("""COMPUTED_VALUE"""),0.6647922933298738) -> 0.66479229 | AF56: =IFERROR(__xludf.DUMMYFUNCTION("""COMPUTED_VALUE"""),0.32613883816433964) -> 0.32613884 | AG56: =IFERROR(__xludf.DUMMYFUNCTION("""COMPUTED_VALUE"""),-0.012729749584339901) -> -0.01272975
A57: =VLOOKUP($F57,UpdateHashtag!$V$3:$Y$32,COLUMN(B$15),0) -> 4 | B57: =VLOOKUP($F57,UpdateHashtag!$V$3:$Y$32,COLUMN(C$13),0) -> 3 | C57: =VLOOKUP($F57,UpdateHashtag!$V$3:$Y$32,COLUMN(D$13),0) -> 4 | D57: =SUM(A57:C57) -> 11 | F57: =VLOOKUP(J57,UpdateBBM!$C$2:E1015,3,0) -> DET | G57: 38 | H57: =IFERROR(__xludf.DUMMYFUNCTION("""COMPUTED_VALUE"""),38.0) -> 38 | I57: =IFERROR(__xludf.DUMMYFUNCTION("""COMPUTED_VALUE"""),34.0) -> 34 | J57: =IFERROR(__xludf.DUMMYFUNCTION("""COMPUTED_VALUE"""),"Cade Cunningham") -> Cade Cunningham | K57: =IFERROR(__xludf.DUMMYFUNCTION("""COMPUTED_VALUE"""),53.0) -> 53 | L57: =IFERROR(__xludf.DUMMYFUNCTION("""COMPUTED_VALUE"""),"PG,SG") -> PG,SG | M57: =IFERROR(__xludf.DUMMYFUNCTION("""COMPUTED_VALUE"""),2.199091564198683) -> 2.1990916 | N57: =IFERROR(__xludf.DUMMYFUNCTION("""COMPUTED_VALUE"""),2.199091564198683) -> 2.1990916 | O57: =IFERROR(__xludf.DUMMYFUNCTION("""COMPUTED_VALUE"""),0.0) -> 0 | P57: =IFERROR(__xludf.DUMMYFUNCTION("""COMPUTED_VALUE"""),23.2) -> 23.2 | Q57: =IFERROR(__xludf.DUMMYFUNCTION("""COMPUTED_VALUE"""),1.9) -> 1.9 | R57: =IFERROR(__xludf.DUMMYFUNCTION("""COMPUTED_VALUE"""),4.7) -> 4.7 | S57: =IFERROR(__xludf.DUMMYFUNCTION("""COMPUTED_VALUE"""),7.8) -> 7.8 | T57: =IFERROR(__xludf.DUMMYFUNCTION("""COMPUTED_VALUE"""),0.9) -> 0.9 | U57: =IFERROR(__xludf.DUMMYFUNCTION("""COMPUTED_VALUE"""),0.4) -> 0.4 | V57: =IFERROR(__xludf.DUMMYFUNCTION("""COMPUTED_VALUE"""),0.45) -> 0.45 | W57: =IFERROR(__xludf.DUMMYFUNCTION("""COMPUTED_VALUE"""),0.865) -> 0.865 | X57: =IFERROR(__xludf.DUMMYFUNCTION("""COMPUTED_VALUE"""),3.5) -> 3.5 | Y57: =IFERROR(__xludf.DUMMYFUNCTION("""COMPUTED_VALUE"""),1.0356754344105719) -> 1.0356754 | Z57: =IFERROR(__xludf.DUMMYFUNCTION("""COMPUTED_VALUE"""),0.15027510052444681) -> 0.1502751 | AA57: =IFERROR(__xludf.DUMMYFUNCTION("""COMPUTED_VALUE"""),-0.5369596630153455) -> -0.53695966 | AB57: =IFERROR(__xludf.DUMMYFUNCTION("""COMPUTED_VALUE"""),1.760615433199641) -> 1.7606154 | AC57: =IFERROR(__xludf.DUMMYFUNCTION("""COMPUTED_VALUE"""),-0.25279641051880714) -> -0.25279641 | AD57: =IFERROR(__xludf.DUMMYFUNCTION("""COMPUTED_VALUE"""),-0.6155173428439339) -> -0.61551734 | AE57: =IFERROR(__xludf.DUMMYFUNCTION("""COMPUTED_VALUE"""),-1.0714145177539518) -> -1.0714145 | AF57: =IFERROR(__xludf.DUMMYFUNCTION("""COMPUTED_VALUE"""),1.092098391118223) -> 1.0920984 | AG57: =IFERROR(__xludf.DUMMYFUNCTION("""COMPUTED_VALUE"""),-0.43429937867611307) -> -0.43429938
A58: =VLOOKUP($F58,UpdateHashtag!$V$3:$Y$32,COLUMN(B$15),0) -> 4 | B58: =VLOOKUP($F58,UpdateHashtag!$V$3:$Y$32,COLUMN(C$13),0) -> 3 | C58: =VLOOKUP($F58,UpdateHashtag!$V$3:$Y$32,COLUMN(D$13),0) -> 3 | D58: =SUM(A58:C58) -> 10 | F58: =VLOOKUP(J58,UpdateBBM!$C$2:E1015,3,0) -> MIN | G58: 39 | H58: =IFERROR(__xludf.DUMMYFUNCTION("""COMPUTED_VALUE"""),39.0) -> 39 | I58: =IFERROR(__xludf.DUMMYFUNCTION("""COMPUTED_VALUE"""),46.4) -> 46.4 | J58: =IFERROR(__xludf.DUMMYFUNCTION("""COMPUTED_VALUE"""),"Rudy Gobert") -> Rudy Gobert | K58: =IFERROR(__xludf.DUMMYFUNCTION("""COMPUTED_VALUE"""),71.0) -> 71 | L58: =IFERROR(__xludf.DUMMYFUNCTION("""COMPUTED_VALUE"""),"C") -> C | M58: =IFERROR(__xludf.DUMMYFUNCTION("""COMPUTED_VALUE"""),2.1075798541550443) -> 2.1075799 | N58: =IFERROR(__xludf.DUMMYFUNCTION("""COMPUTED_VALUE"""),2.1075798541550443) -> 2.1075799 | O58: =IFERROR(__xludf.DUMMYFUNCTION("""COMPUTED_VALUE"""),0.0) -> 0 | P58: =IFERROR(__xludf.DUMMYFUNCTION("""COMPUTED_VALUE"""),14.3) -> 14.3 | Q58: =IFERROR(__xludf.DUMMYFUNCTION("""COMPUTED_VALUE"""),0.0) -> 0 | R58: =IFERROR(__xludf.DUMMYFUNCTION("""COMPUTED_VALUE"""),12.9) -> 12.9 | S58: =IFERROR(__xludf.DUMMYFUNCTION("""COMPUTED_VALUE"""),1.4) -> 1.4 | T58: =IFERROR(__xludf.DUMMYFUNCTION("""COMPUTED_VALUE"""),0.8) -> 0.8 | U58: =IFERROR(__xludf.DUMMYFUNCTION("""COMPUTED_VALUE"""),1.8) -> 1.8 | V58: =IFERROR(__xludf.DUMMYFUNCTION("""COMPUTED_VALUE"""),0.66) -> 0.66 | W58: =IFERROR(__xludf.DUMMYFUNCTION("""COMPUTED_VALUE"""),0.642) -> 0.642 | X58: =IFERROR(__xludf.DUMMYFUNCTION("""COMPUTED_VALUE"""),1.7) -> 1.7 | Y58: =IFERROR(__xludf.DUMMYFUNCTION("""COMPUTED_VALUE"""),-0.5720919403201229) -> -0.57209194 | Z58: =IFERROR(__xludf.DUMMYFUNCTION("""COMPUTED_VALUE"""),-1.7406865810748415) -> -1.7406866 | AA58: =IFERROR(__xludf.DUMMYFUNCTION("""COMPUTED_VALUE"""),2.679602769232369) -> 2.6796028 | AB58: =IFERROR(__xludf.DUMMYFUNCTION("""COMPUTED_VALUE"""),-1.1553378738168676) -> -1.1553379 | AC58: =IFERROR(__xludf.DUMMYFUNCTION("""COMPUTED_VALUE"""),-0.5847290886782864) -> -0.58472909 | AD58: =IFERROR(__xludf.DUMMYFUNCTION("""COMPUTED_VALUE"""),1.881994485893255) -> 1.8819945 | AE58: =IFERROR(__xludf.DUMMYFUNCTION("""COMPUTED_VALUE"""),1.586759619027892) -> 1.5867596 | AF58: =IFERROR(__xludf.DUMMYFUNCTION("""COMPUTED_VALUE"""),-2.8159670660661136) -> -2.8159671 | AG58: =IFERROR(__xludf.DUMMYFUNCTION("""COMPUTED_VALUE"""),0.012068463891646777) -> 0.012068464
A59: =VLOOKUP($F59,UpdateHashtag!$V$3:$Y$32,COLUMN(B$15),0) -> 3 | B59: =VLOOKUP($F59,UpdateHashtag!$V$3:$Y$32,COLUMN(C$13),0) -> 4 | C59: =VLOOKUP($F59,UpdateHashtag!$V$3:$Y$32,COLUMN(D$13),0) -> 3 | D59: =SUM(A59:C59) -> 10 | F59: =VLOOKUP(J59,UpdateBBM!$C$2:E1015,3,0) -> TOR | G59: 40 | H59: =IFERROR(__xludf.DUMMYFUNCTION("""COMPUTED_VALUE"""),40.0) -> 40 | I59: =IFERROR(__xludf.DUMMYFUNCTION("""COMPUTED_VALUE"""),53.8) -> 53.8 | J59: =IFERROR(__xludf.DUMMYFUNCTION("""COMPUTED_VALUE"""),"Immanuel Quickley") -> Immanuel Quickley | K59: =IFERROR(__xludf.DUMMYFUNCTION("""COMPUTED_VALUE"""),46.0) -> 46 | L59: =IFERROR(__xludf.DUMMYFUNCTION("""COMPUTED_VALUE"""),"PG,SG") -> PG,SG | M59: =IFERROR(__xludf.DUMMYFUNCTION("""COMPUTED_VALUE"""),2.002004754105327) -> 2.0020048 | N59: =IFERROR(__xludf.DUMMYFUNCTION("""COMPUTED_VALUE"""),2.002004754105327) -> 2.0020048 | O59: =IFERROR(__xludf.DUMMYFUNCTION("""COMPUTED_VALUE"""),0.0) -> 0 | P59: =IFERROR(__xludf.DUMMYFUNCTION("""COMPUTED_VALUE"""),18.7) -> 18.7 | Q59: =IFERROR(__xludf.DUMMYFUNCTION("""COMPUTED_VALUE"""),2.6) -> 2.6 | R59: =IFERROR(__xludf.DUMMYFUNCTION("""COMPUTED_VALUE"""),4.6) -> 4.6 | S59: =IFERROR(__xludf.DUMMYFUNCTION("""COMPUTED_VALUE"""),6.8) -> 6.8 | T59: =IFERROR(__xludf.DUMMYFUNCTION("""COMPUTED_VALUE"""),1.1) -> 1.1 | U59: =IFERROR(__xludf.DUMMYFUNCTION("""COMPUTED_VALUE"""),0.2) -> 0.2 | V59: =IFERROR(__xludf.DUMMYFUNCTION("""COMPUTED_VALUE"""),0.44) -> 0.44 | W59: =IFERROR(__xludf.DUMMYFUNCTION("""COMPUTED_VALUE"""),0.849) -> 0.849 | X59: =IFERROR(__xludf.DUMMYFUNCTION("""COMPUTED_VALUE"""),1.6) -> 1.6 | Y59: =IFERROR(__xludf.DUMMYFUNCTION("""COMPUTED_VALUE"""),0.22275934606359118) -> 0.22275935 | Z59: =IFERROR(__xludf.DUMMYFUNCTION("""COMPUTED_VALUE"""),0.8469451937452375) -> 0.84694519 | AA59: =IFERROR(__xludf.DUMMYFUNCTION("""COMPUTED_VALUE"""),-0.5761860341403178) -> -0.57618603 | AB59: =IFERROR(__xludf.DUMMYFUNCTION("""COMPUTED_VALUE"""),1.3049977289783117) -> 1.3049977 | AC59: =IFERROR(__xludf.DUMMYFUNCTION("""COMPUTED_VALUE"""),0.41106894580015185) -> 0.41106895 | AD59: =IFERROR(__xludf.DUMMYFUNCTION("""COMPUTED_VALUE"""),-0.9723047469492465) -> -0.97230475 | AE59: =IFERROR(__xludf.DUMMYFUNCTION("""COMPUTED_VALUE"""),-0.9799658477543457) -> -0.97996585 | AF59: =IFERROR(__xludf.DUMMYFUNCTION("""COMPUTED_VALUE"""),0.7278576432399655) -> 0.72785764 | AG59: =IFERROR(__xludf.DUMMYFUNCTION("""COMPUTED_VALUE"""),0.036866677367633396) -> 0.036866677
A60: =VLOOKUP($F60,UpdateHashtag!$V$3:$Y$32,COLUMN(B$15),0) -> 4 | B60: =VLOOKUP($F60,UpdateHashtag!$V$3:$Y$32,COLUMN(C$13),0) -> 3 | C60: =VLOOKUP($F60,UpdateHashtag!$V$3:$Y$32,COLUMN(D$13),0) -> 4 | D60: =SUM(A60:C60) -> 11 | F60: =VLOOKUP(J60,UpdateBBM!$C$2:E1015,3,0) -> CLE | G60: 41 | H60: =IFERROR(__xludf.DUMMYFUNCTION("""COMPUTED_VALUE"""),41.0) -> 41 | I60: =IFERROR(__xludf.DUMMYFUNCTION("""COMPUTED_VALUE"""),39.0) -> 39 | J60: =IFERROR(__xludf.DUMMYFUNCTION("""COMPUTED_VALUE"""),"Evan Mobley") -> Evan Mobley | K60: =IFERROR(__xludf.DUMMYFUNCTION("""COMPUTED_VALUE"""),64.0) -> 64 | L60: =IFERROR(__xludf.DUMMYFUNCTION("""COMPUTED_VALUE"""),"PF,C") -> PF,C | M60: =IFERROR(__xludf.DUMMYFUNCTION("""COMPUTED_VALUE"""),1.9569098276328871) -> 1.9569098 | N60: =IFERROR(__xludf.DUMMYFUNCTION("""COMPUTED_VALUE"""),1.9569098276328871) -> 1.9569098 | O60: =IFERROR(__xludf.DUMMYFUNCTION("""COMPUTED_VALUE"""),0.0) -> 0 | P60: =IFERROR(__xludf.DUMMYFUNCTION("""COMPUTED_VALUE"""),16.1) -> 16.1 | Q60: =IFERROR(__xludf.DUMMYFUNCTION("""COMPUTED_VALUE"""),0.4) -> 0.4 | R60: =IFERROR(__xludf.DUMMYFUNCTION("""COMPUTED_VALUE"""),9.2) -> 9.2 | S60: =IFERROR(__xludf.DUMMYFUNCTION("""COMPUTED_VALUE"""),3.4) -> 3.4 | T60: =IFERROR(__xludf.DUMMYFUNCTION("""COMPUTED_VALUE"""),0.9) -> 0.9 | U60: =IFERROR(__xludf.DUMMYFUNCTION("""COMPUTED_VALUE"""),1.5) -> 1.5 | V60: =IFERROR(__xludf.DUMMYFUNCTION("""COMPUTED_VALUE"""),0.573) -> 0.573 | W60: =IFERROR(__xludf.DUMMYFUNCTION("""COMPUTED_VALUE"""),0.726) -> 0.726 | X60: =IFERROR(__xludf.DUMMYFUNCTION("""COMPUTED_VALUE"""),1.8) -> 1.8 | Y60: =IFERROR(__xludf.DUMMYFUNCTION("""COMPUTED_VALUE"""),-0.24692550498133056) -> -0.2469255 | Z60: =IFERROR(__xludf.DUMMYFUNCTION("""COMPUTED_VALUE"""),-1.3425893849486756) -> -1.3425894 | AA60: =IFERROR(__xludf.DUMMYFUNCTION("""COMPUTED_VALUE"""),1.2282270376084) -> 1.228227 | AB60: =IFERROR(__xludf.DUMMYFUNCTION("""COMPUTED_VALUE"""),-0.2441024653742086) -> -0.24410247 | AC60: =IFERROR(__xludf.DUMMYFUNCTION("""COMPUTED_VALUE"""),-0.25279641051880714) -> -0.25279641 | AD60: =IFERROR(__xludf.DUMMYFUNCTION("""COMPUTED_VALUE"""),1.346813379735286) -> 1.3468134 | AE60: =IFERROR(__xludf.DUMMYFUNCTION("""COMPUTED_VALUE"""),1.0170142713517292) -> 1.0170143 | AF60: =IFERROR(__xludf.DUMMYFUNCTION("""COMPUTED_VALUE"""),-0.8785907306038417) -> -0.87859073 | AG60: =IFERROR(__xludf.DUMMYFUNCTION("""COMPUTED_VALUE"""),-0.012729749584339901) -> -0.01272975
A61: =VLOOKUP($F61,UpdateHashtag!$V$3:$Y$32,COLUMN(B$15),0) -> 4 | B61: =VLOOKUP($F61,UpdateHashtag!$V$3:$Y$32,COLUMN(C$13),0) -> 4 | C61: =VLOOKUP($F61,UpdateHashtag!$V$3:$Y$32,COLUMN(D$13),0) -> 3 | D61: =SUM(A61:C61) -> 11 | F61: =VLOOKUP(J61,UpdateBBM!$C$2:E1015,3,0) -> MEM | G61: 42 | H61: =IFERROR(__xludf.DUMMYFUNCTION("""COMPUTED_VALUE"""),42.0) -> 42 | I61: =IFERROR(__xludf.DUMMYFUNCTION("""COMPUTED_VALUE"""),35.2) -> 35.2 | J61: =IFERROR(__xludf.DUMMYFUNCTION("""COMPUTED_VALUE"""),"Ja Morant") -> Ja Morant | K61: =IFERROR(__xludf.DUMMYFUNCTION("""COMPUTED_VALUE"""),64.0) -> 64 | L61: =IFERROR(__xludf.DUMMYFUNCTION("""COMPUTED_VALUE"""),"PG") -> PG | M61: =IFERROR(__xludf.DUMMYFUNCTION("""COMPUTED_VALUE"""),1.9527398468352886) -> 1.9527398 | N61: =IFERROR(__xludf.DUMMYFUNCTION("""COMPUTED_VALUE"""),1.9527398468352886) -> 1.9527398 | O61: =IFERROR(__xludf.DUMMYFUNCTION("""COMPUTED_VALUE"""),0.0) -> 0 | P61: =IFERROR(__xludf.DUMMYFUNCTION("""COMPUTED_VALUE"""),25.8) -> 25.8 | Q61: =IFERROR(__xludf.DUMMYFUNCTION("""COMPUTED_VALUE"""),1.5) -> 1.5 | R61: =IFERROR(__xludf.DUMMYFUNCTION("""COMPUTED_VALUE"""),5.9) -> 5.9 | S61: =IFERROR(__xludf.DUMMYFUNCTION("""COMPUTED_VALUE"""),8.2) -> 8.2 | T61: =IFERROR(__xludf.DUMMYFUNCTION("""COMPUTED_VALUE"""),0.9) -> 0.9 | U61: =IFERROR(__xludf.DUMMYFUNCTION("""COMPUTED_VALUE"""),0.5) -> 0.5 | V61: =IFERROR(__xludf.DUMMYFUNCTION("""COMPUTED_VALUE"""),0.47) -> 0.47 | W61: =IFERROR(__xludf.DUMMYFUNCTION("""COMPUTED_VALUE"""),0.788) -> 0.788 | X61: =IFERROR(__xludf.DUMMYFUNCTION("""COMPUTED_VALUE"""),3.0) -> 3 | Y61: =IFERROR(__xludf.DUMMYFUNCTION("""COMPUTED_VALUE"""),1.5053602854554942) -> 1.5053603 | Z61: =IFERROR(__xludf.DUMMYFUNCTION("""COMPUTED_VALUE"""),-0.24782209560171908) -> -0.2478221 | AA61: =IFERROR(__xludf.DUMMYFUNCTION("""COMPUTED_VALUE"""),-0.06624320951567987) -> -0.06624321 | AB61: =IFERROR(__xludf.DUMMYFUNCTION("""COMPUTED_VALUE"""),1.9428625148881729) -> 1.9428625 | AC61: =IFERROR(__xludf.DUMMYFUNCTION("""COMPUTED_VALUE"""),-0.25279641051880714) -> -0.25279641 | AD61: =IFERROR(__xludf.DUMMYFUNCTION("""COMPUTED_VALUE"""),-0.4371236407912776) -> -0.43712364 | AE61: =IFERROR(__xludf.DUMMYFUNCTION("""COMPUTED_VALUE"""),-0.617484592856739) -> -0.61748459 | AF61: =IFERROR(__xludf.DUMMYFUNCTION("""COMPUTED_VALUE"""),-0.18118928578471516) -> -0.18118929 | AG61: =IFERROR(__xludf.DUMMYFUNCTION("""COMPUTED_VALUE"""),-0.31030831129617975) -> -0.31030831
A62: =VLOOKUP($F62,UpdateHashtag!$V$3:$Y$32,COLUMN(B$15),0) -> 2 | B62: =VLOOKUP($F62,UpdateHashtag!$V$3:$Y$32,COLUMN(C$13),0) -> 4 | C62: =VLOOKUP($F62,UpdateHashtag!$V$3:$Y$32,COLUMN(D$13),0) -> 3 | D62: =SUM(A62:C62) -> 9 | F62: =VLOOKUP(J62,UpdateBBM!$C$2:E1015,3,0) -> ORL | G62: 43 | H62: =IFERROR(__xludf.DUMMYFUNCTION("""COMPUTED_VALUE"""),43.0) -> 43 | I62: =IFERROR(__xludf.DUMMYFUNCTION("""COMPUTED_VALUE"""),44.1) -> 44.1 | J62: =IFERROR(__xludf.DUMMYFUNCTION("""COMPUTED_VALUE"""),"Desmond Bane") -> Desmond Bane | K62: =IFERROR(__xludf.DUMMYFUNCTION("""COMPUTED_VALUE"""),71.0) -> 71 | L62: =IFERROR(__xludf.DUMMYFUNCTION("""COMPUTED_VALUE"""),"SG,SF") -> SG,SF | M62: =IFERROR(__xludf.DUMMYFUNCTION("""COMPUTED_VALUE"""),1.9337704253555552) -> 1.9337704 | N62: =IFERROR(__xludf.DUMMYFUNCTION("""COMPUTED_VALUE"""),1.9337704253555552) -> 1.9337704 | O62: =IFERROR(__xludf.DUMMYFUNCTION("""COMPUTED_VALUE"""),0.0) -> 0 | P62: =IFERROR(__xludf.DUMMYFUNCTION("""COMPUTED_VALUE"""),21.4) -> 21.4 | Q62: =IFERROR(__xludf.DUMMYFUNCTION("""COMPUTED_VALUE"""),2.9) -> 2.9 | R62: =IFERROR(__xludf.DUMMYFUNCTION("""COMPUTED_VALUE"""),4.5) -> 4.5 | S62: =IFERROR(__xludf.DUMMYFUNCTION("""COMPUTED_VALUE"""),4.4) -> 4.4 | T62: =IFERROR(__xludf.DUMMYFUNCTION("""COMPUTED_VALUE"""),1.0) -> 1 | U62: =IFERROR(__xludf.DUMMYFUNCTION("""COMPUTED_VALUE"""),0.4) -> 0.4 | V62: =IFERROR(__xludf.DUMMYFUNCTION("""COMPUTED_VALUE"""),0.472) -> 0.472 | W62: =IFERROR(__xludf.DUMMYFUNCTION("""COMPUTED_VALUE"""),0.877) -> 0.877 | X62: =IFERROR(__xludf.DUMMYFUNCTION("""COMPUTED_VALUE"""),2.3) -> 2.3 | Y62: =IFERROR(__xludf.DUMMYFUNCTION("""COMPUTED_VALUE"""),0.7105089990717794) -> 0.710509 | Z62: =IFERROR(__xludf.DUMMYFUNCTION("""COMPUTED_VALUE"""),1.145518090839862) -> 1.1455181 | AA62: =IFERROR(__xludf.DUMMYFUNCTION("""COMPUTED_VALUE"""),-0.6154124052652897) -> -0.61541241 | AB62: =IFERROR(__xludf.DUMMYFUNCTION("""COMPUTED_VALUE"""),0.2115152388471211) -> 0.21151524 | AC62: =IFERROR(__xludf.DUMMYFUNCTION("""COMPUTED_VALUE"""),0.07913626764067216) -> 0.079136268 | AD62: =IFERROR(__xludf.DUMMYFUNCTION("""COMPUTED_VALUE"""),-0.6155173428439339) -> -0.61551734 | AE62: =IFERROR(__xludf.DUMMYFUNCTION("""COMPUTED_VALUE"""),-0.47822915179607683) -> -0.47822915 | AF62: =IFERROR(__xludf.DUMMYFUNCTION("""COMPUTED_VALUE"""),1.0174542029817606) -> 1.0174542 | AG62: =IFERROR(__xludf.DUMMYFUNCTION("""COMPUTED_VALUE"""),-0.13672081696427313) -> -0.13672082
A63: =VLOOKUP($F63,UpdateHashtag!$V$3:$Y$32,COLUMN(B$15),0) -> 3 | B63: =VLOOKUP($F63,UpdateHashtag!$V$3:$Y$32,COLUMN(C$13),0) -> 4 | C63: =VLOOKUP($F63,UpdateHashtag!$V$3:$Y$32,COLUMN(D$13),0) -> 3 | D63: =SUM(A63:C63) -> 10 | F63: =VLOOKUP(J63,UpdateBBM!$C$2:E1015,3,0) -> BOS | G63: 44 | H63: =IFERROR(__xludf.DUMMYFUNCTION("""COMPUTED_VALUE"""),44.0) -> 44 | I63: =IFERROR(__xludf.DUMMYFUNCTION("""COMPUTED_VALUE"""),48.4) -> 48.4 | J63: =IFERROR(__xludf.DUMMYFUNCTION("""COMPUTED_VALUE"""),"Derrick White") -> Derrick White | K63: =IFERROR(__xludf.DUMMYFUNCTION("""COMPUTED_VALUE"""),60.0) -> 60 | L63: =IFERROR(__xludf.DUMMYFUNCTION("""COMPUTED_VALUE"""),"PG,SG") -> PG,SG | M63: =IFERROR(__xludf.DUMMYFUNCTION("""COMPUTED_VALUE"""),1.9127706800117394) -> 1.9127707 | N63: =IFERROR(__xludf.DUMMYFUNCTION("""COMPUTED_VALUE"""),1.9127706800117394) -> 1.9127707 | O63: =IFERROR(__xludf.DUMMYFUNCTION("""COMPUTED_VALUE"""),0.0) -> 0 | P63: =IFERROR(__xludf.DUMMYFUNCTION("""COMPUTED_VALUE"""),15.2) -> 15.2 | Q63: =IFERROR(__xludf.DUMMYFUNCTION("""COMPUTED_VALUE"""),2.7) -> 2.7 | R63: =IFERROR(__xludf.DUMMYFUNCTION("""COMPUTED_VALUE"""),4.3) -> 4.3 | S63: =IFERROR(__xludf.DUMMYFUNCTION("""COMPUTED_VALUE"""),4.9) -> 4.9 | T63: =IFERROR(__xludf.DUMMYFUNCTION("""COMPUTED_VALUE"""),0.9) -> 0.9 | U63: =IFERROR(__xludf.DUMMYFUNCTION("""COMPUTED_VALUE"""),1.2) -> 1.2 | V63: =IFERROR(__xludf.DUMMYFUNCTION("""COMPUTED_VALUE"""),0.461) -> 0.461 | W63: =IFERROR(__xludf.DUMMYFUNCTION("""COMPUTED_VALUE"""),0.888) -> 0.888 | X63: =IFERROR(__xludf.DUMMYFUNCTION("""COMPUTED_VALUE"""),1.5) -> 1.5 | Y63: =IFERROR(__xludf.DUMMYFUNCTION("""COMPUTED_VALUE"""),-0.4095087226507271) -> -0.40950872 | Z63: =IFERROR(__xludf.DUMMYFUNCTION("""COMPUTED_VALUE"""),0.946469492776779) -> 0.94646949 | AA63: =IFERROR(__xludf.DUMMYFUNCTION("""COMPUTED_VALUE"""),-0.6938651475152341) -> -0.69386515 | AB63: =IFERROR(__xludf.DUMMYFUNCTION("""COMPUTED_VALUE"""),0.43932409095778585) -> 0.43932409 | AC63: =IFERROR(__xludf.DUMMYFUNCTION("""COMPUTED_VALUE"""),-0.25279641051880714) -> -0.25279641 | AD63: =IFERROR(__xludf.DUMMYFUNCTION("""COMPUTED_VALUE"""),0.8116322735773168) -> 0.81163227 | AE63: =IFERROR(__xludf.DUMMYFUNCTION("""COMPUTED_VALUE"""),-0.475191263334002) -> -0.47519126 | AF63: =IFERROR(__xludf.DUMMYFUNCTION("""COMPUTED_VALUE"""),0.7911763283597737) -> 0.79117633 | AG63: =IFERROR(__xludf.DUMMYFUNCTION("""COMPUTED_VALUE"""),0.06166489084362008) -> 0.061664891
A64: =VLOOKUP($F64,UpdateHashtag!$V$3:$Y$32,COLUMN(B$15),0) -> 4 | B64: =VLOOKUP($F64,UpdateHashtag!$V$3:$Y$32,COLUMN(C$13),0) -> 3 | C64: =VLOOKUP($F64,UpdateHashtag!$V$3:$Y$32,COLUMN(D$13),0) -> 4 | D64: =SUM(A64:C64) -> 11 | F64: =VLOOKUP(J64,UpdateBBM!$C$2:E1015,3,0) -> SAC | G64: 45 | H64: =IFERROR(__xludf.DUMMYFUNCTION("""COMPUTED_VALUE"""),45.0) -> 45 | I64: =IFERROR(__xludf.DUMMYFUNCTION("""COMPUTED_VALUE"""),54.1) -> 54.1 | J64: =IFERROR(__xludf.DUMMYFUNCTION("""COMPUTED_VALUE"""),"DeMar DeRozan") -> DeMar DeRozan | K64: =IFERROR(__xludf.DUMMYFUNCTION("""COMPUTED_VALUE"""),66.0) -> 66 | L64: =IFERROR(__xludf.DUMMYFUNCTION("""COMPUTED_VALUE"""),"SF,PF") -> SF,PF | M64: =IFERROR(__xludf.DUMMYFUNCTION("""COMPUTED_VALUE"""),1.8306211388938802) -> 1.8306211 | N64: =IFERROR(__xludf.DUMMYFUNCTION("""COMPUTED_VALUE"""),1.8306211388938802) -> 1.8306211 | O64: =IFERROR(__xludf.DUMMYFUNCTION("""COMPUTED_VALUE"""),0.0) -> 0 | P64: =IFERROR(__xludf.DUMMYFUNCTION("""COMPUTED_VALUE"""),22.1) -> 22.1 | Q64: =IFERROR(__xludf.DUMMYFUNCTION("""COMPUTED_VALUE"""),1.1) -> 1.1 | R64: =IFERROR(__xludf.DUMMYFUNCTION("""COMPUTED_VALUE"""),3.8) -> 3.8 | S64: =IFERROR(__xludf.DUMMYFUNCTION("""COMPUTED_VALUE"""),3.9) -> 3.9 | T64: =IFERROR(__xludf.DUMMYFUNCTION("""COMPUTED_VALUE"""),1.1) -> 1.1 | U64: =IFERROR(__xludf.DUMMYFUNCTION("""COMPUTED_VALUE"""),0.6) -> 0.6 | V64: =IFERROR(__xludf.DUMMYFUNCTION("""COMPUTED_VALUE"""),0.486) -> 0.486 | W64: =IFERROR(__xludf.DUMMYFUNCTION("""COMPUTED_VALUE"""),0.863) -> 0.863 | X64: =IFERROR(__xludf.DUMMYFUNCTION("""COMPUTED_VALUE"""),1.7) -> 1.7 | Y64: =IFERROR(__xludf.DUMMYFUNCTION("""COMPUTED_VALUE"""),0.8369626128146436) -> 0.83696261 | Z64: =IFERROR(__xludf.DUMMYFUNCTION("""COMPUTED_VALUE"""),-0.645919291727885) -> -0.64591929 | AA64: =IFERROR(__xludf.DUMMYFUNCTION("""COMPUTED_VALUE"""),-0.8899970031400947) -> -0.889997 | AB64: =IFERROR(__xludf.DUMMYFUNCTION("""COMPUTED_VALUE"""),-0.016293613263543852) -> -0.016293613 | AC64: =IFERROR(__xludf.DUMMYFUNCTION("""COMPUTED_VALUE"""),0.41106894580015185) -> 0.41106895 | AD64: =IFERROR(__xludf.DUMMYFUNCTION("""COMPUTED_VALUE"""),-0.25872993873862127) -> -0.25872994 | AE64: =IFERROR(__xludf.DUMMYFUNCTION("""COMPUTED_VALUE"""),-0.19638544058529345) -> -0.19638544 | AF64: =IFERROR(__xludf.DUMMYFUNCTION("""COMPUTED_VALUE"""),1.6878494007027816) -> 1.6878494 | AG64: =IFERROR(__xludf.DUMMYFUNCTION("""COMPUTED_VALUE"""),0.012068463891646777) -> 0.012068464
A65: =VLOOKUP($F65,UpdateHashtag!$V$3:$Y$32,COLUMN(B$15),0) -> 3 | B65: =VLOOKUP($F65,UpdateHashtag!$V$3:$Y$32,COLUMN(C$13),0) -> 4 | C65: =VLOOKUP($F65,UpdateHashtag!$V$3:$Y$32,COLUMN(D$13),0) -> 4 | D65: =SUM(A65:C65) -> 11 | F65: =VLOOKUP(J65,UpdateBBM!$C$2:E1015,3,0) -> DEN | G65: 46 | H65: =IFERROR(__xludf.DUMMYFUNCTION("""COMPUTED_VALUE"""),46.0) -> 46 | I65: =IFERROR(__xludf.DUMMYFUNCTION("""COMPUTED_VALUE"""),52.7) -> 52.7 | J65: =IFERROR(__xludf.DUMMYFUNCTION("""COMPUTED_VALUE"""),"Jamal Murray") -> Jamal Murray | K65: =IFERROR(__xludf.DUMMYFUNCTION("""COMPUTED_VALUE"""),71.0) -> 71 | L65: =IFERROR(__xludf.DUMMYFUNCTION("""COMPUTED_VALUE"""),"PG,SG") -> PG,SG | M65: =IFERROR(__xludf.DUMMYFUNCTION("""COMPUTED_VALUE"""),1.7726770882562053) -> 1.7726771 | N65: =IFERROR(__xludf.DUMMYFUNCTION("""COMPUTED_VALUE"""),1.7726770882562053) -> 1.7726771 | O65: =IFERROR(__xludf.DUMMYFUNCTION("""COMPUTED_VALUE"""),0.0) -> 0 | P65: =IFERROR(__xludf.DUMMYFUNCTION("""COMPUTED_VALUE"""),20.0) -> 20 | Q65: =IFERROR(__xludf.DUMMYFUNCTION("""COMPUTED_VALUE"""),2.5) -> 2.5 | R65: =IFERROR(__xludf.DUMMYFUNCTION("""COMPUTED_VALUE"""),3.9) -> 3.9 | S65: =IFERROR(__xludf.DUMMYFUNCTION("""COMPUTED_VALUE"""),6.1) -> 6.1 | T65: =IFERROR(__xludf.DUMMYFUNCTION("""COMPUTED_VALUE"""),1.0) -> 1 | U65: =IFERROR(__xludf.DUMMYFUNCTION("""COMPUTED_VALUE"""),0.5) -> 0.5 | V65: =IFERROR(__xludf.DUMMYFUNCTION("""COMPUTED_VALUE"""),0.471) -> 0.471 | W65: =IFERROR(__xludf.DUMMYFUNCTION("""COMPUTED_VALUE"""),0.841) -> 0.841 | X65: =IFERROR(__xludf.DUMMYFUNCTION("""COMPUTED_VALUE"""),2.1) -> 2.1 | Y65: =IFERROR(__xludf.DUMMYFUNCTION("""COMPUTED_VALUE"""),0.45760177158605236) -> 0.45760177 | Z65: =IFERROR(__xludf.DUMMYFUNCTION("""COMPUTED_VALUE"""),0.7474208947136959) -> 0.74742089 | AA65: =IFERROR(__xludf.DUMMYFUNCTION("""COMPUTED_VALUE"""),-0.8507706320151226) -> -0.85077063 | AB65: =IFERROR(__xludf.DUMMYFUNCTION("""COMPUTED_VALUE"""),0.9860653360233809) -> 0.98606534 | AC65: =IFERROR(__xludf.DUMMYFUNCTION("""COMPUTED_VALUE"""),0.07913626764067216) -> 0.079136268 | AD65: =IFERROR(__xludf.DUMMYFUNCTION("""COMPUTED_VALUE"""),-0.4371236407912776) -> -0.43712364 | AE65: =IFERROR(__xludf.DUMMYFUNCTION("""COMPUTED_VALUE"""),-0.47925057775828667) -> -0.47925058 | AF65: =IFERROR(__xludf.DUMMYFUNCTION("""COMPUTED_VALUE"""),0.505951426854268) -> 0.50595143 | AG65: =IFERROR(__xludf.DUMMYFUNCTION("""COMPUTED_VALUE"""),-0.08712439001229988) -> -0.08712439
A66: =VLOOKUP($F66,UpdateHashtag!$V$3:$Y$32,COLUMN(B$15),0) -> 4 | B66: =VLOOKUP($F66,UpdateHashtag!$V$3:$Y$32,COLUMN(C$13),0) -> 3 | C66: =VLOOKUP($F66,UpdateHashtag!$V$3:$Y$32,COLUMN(D$13),0) -> 4 | D66: =SUM(A66:C66) -> 11 | F66: =VLOOKUP(J66,UpdateBBM!$C$2:E1015,3,0) -> CLE | G66: 47 | H66: =IFERROR(__xludf.DUMMYFUNCTION("""COMPUTED_VALUE"""),47.0) -> 47 | I66: =IFERROR(__xludf.DUMMYFUNCTION("""COMPUTED_VALUE"""),62.6) -> 62.6 | J66: =IFERROR(__xludf.DUMMYFUNCTION("""COMPUTED_VALUE"""),"Darius Garland") -> Darius Garland | K66: =IFERROR(__xludf.DUMMYFUNCTION("""COMPUTED_VALUE"""),52.0) -> 52 | L66: =IFERROR(__xludf.DUMMYFUNCTION("""COMPUTED_VALUE"""),"PG") -> PG | M66: =IFERROR(__xludf.DUMMYFUNCTION("""COMPUTED_VALUE"""),1.5825764566259903) -> 1.5825765 | N66: =IFERROR(__xludf.DUMMYFUNCTION("""COMPUTED_VALUE"""),1.5825764566259903) -> 1.5825765 | O66: =IFERROR(__xludf.DUMMYFUNCTION("""COMPUTED_VALUE"""),0.0) -> 0 | P66: =IFERROR(__xludf.DUMMYFUNCTION("""COMPUTED_VALUE"""),19.3) -> 19.3 | Q66: =IFERROR(__xludf.DUMMYFUNCTION("""COMPUTED_VALUE"""),2.3) -> 2.3 | R66: =IFERROR(__xludf.DUMMYFUNCTION("""COMPUTED_VALUE"""),2.6) -> 2.6 | S66: =IFERROR(__xludf.DUMMYFUNCTION("""COMPUTED_VALUE"""),7.0) -> 7 | T66: =IFERROR(__xludf.DUMMYFUNCTION("""COMPUTED_VALUE"""),1.2) -> 1.2 | U66: =IFERROR(__xludf.DUMMYFUNCTION("""COMPUTED_VALUE"""),0.1) -> 0.1 | V66: =IFERROR(__xludf.DUMMYFUNCTION("""COMPUTED_VALUE"""),0.455) -> 0.455 | W66: =IFERROR(__xludf.DUMMYFUNCTION("""COMPUTED_VALUE"""),0.85) -> 0.85 | X66: =IFERROR(__xludf.DUMMYFUNCTION("""COMPUTED_VALUE"""),2.9) -> 2.9 | Y66: =IFERROR(__xludf.DUMMYFUNCTION("""COMPUTED_VALUE"""),0.33114815784318885) -> 0.33114816 | Z66: =IFERROR(__xludf.DUMMYFUNCTION("""COMPUTED_VALUE"""),0.5483722966506127) -> 0.5483723 | AA66: =IFERROR(__xludf.DUMMYFUNCTION("""COMPUTED_VALUE"""),-1.36071345663976) -> -1.3607135 | AB66: =IFERROR(__xludf.DUMMYFUNCTION("""COMPUTED_VALUE"""),1.3961212698225776) -> 1.3961213 | AC66: =IFERROR(__xludf.DUMMYFUNCTION("""COMPUTED_VALUE"""),0.7430016239596308) -> 0.74300162 | AD66: =IFERROR(__xludf.DUMMYFUNCTION("""COMPUTED_VALUE"""),-1.150698449001903) -> -1.1506984 | AE66: =IFERROR(__xludf.DUMMYFUNCTION("""COMPUTED_VALUE"""),-0.7411733780677952) -> -0.74117338 | AF66: =IFERROR(__xludf.DUMMYFUNCTION("""COMPUTED_VALUE"""),0.7413150332398716) -> 0.74131503 | AG66: =IFERROR(__xludf.DUMMYFUNCTION("""COMPUTED_VALUE"""),-0.2855100978201931) -> -0.2855101
A67: =VLOOKUP($F67,UpdateHashtag!$V$3:$Y$32,COLUMN(B$15),0) -> 4 | B67: =VLOOKUP($F67,UpdateHashtag!$V$3:$Y$32,COLUMN(C$13),0) -> 4 | C67: =VLOOKUP($F67,UpdateHashtag!$V$3:$Y$32,COLUMN(D$13),0) -> 3 | D67: =SUM(A67:C67) -> 11 | F67: =VLOOKUP(J67,UpdateBBM!$C$2:E1015,3,0) -> ATL | G67: 48 | H67: =IFERROR(__xludf.DUMMYFUNCTION("""COMPUTED_VALUE"""),48.0) -> 48 | I67: =IFERROR(__xludf.DUMMYFUNCTION("""COMPUTED_VALUE"""),103.3) -> 103.3 | J67: =IFERROR(__xludf.DUMMYFUNCTION("""COMPUTED_VALUE"""),"Kristaps Porzingis") -> Kristaps Porzingis | K67: =IFERROR(__xludf.DUMMYFUNCTION("""COMPUTED_VALUE"""),62.0) -> 62 | L67: =IFERROR(__xludf.DUMMYFUNCTION("""COMPUTED_VALUE"""),"PF,C") -> PF,C | M67: =IFERROR(__xludf.DUMMYFUNCTION("""COMPUTED_VALUE"""),1.5159943752021188) -> 1.5159944 | N67: =IFERROR(__xludf.DUMMYFUNCTION("""COMPUTED_VALUE"""),1.5159943752021188) -> 1.5159944 | O67: =IFERROR(__xludf.DUMMYFUNCTION("""COMPUTED_VALUE"""),0.0) -> 0 | P67: =IFERROR(__xludf.DUMMYFUNCTION("""COMPUTED_VALUE"""),17.8) -> 17.8 | Q67: =IFERROR(__xludf.DUMMYFUNCTION("""COMPUTED_VALUE"""),1.8) -> 1.8 | R67: =IFERROR(__xludf.DUMMYFUNCTION("""COMPUTED_VALUE"""),6.7) -> 6.7 | S67: =IFERROR(__xludf.DUMMYFUNCTION("""COMPUTED_VALUE"""),2.0) -> 2 | T67: =IFERROR(__xludf.DUMMYFUNCTION("""COMPUTED_VALUE"""),0.7) -> 0.7 | U67: =IFERROR(__xludf.DUMMYFUNCTION("""COMPUTED_VALUE"""),1.5) -> 1.5 | V67: =IFERROR(__xludf.DUMMYFUNCTION("""COMPUTED_VALUE"""),0.484) -> 0.484 | W67: =IFERROR(__xludf.DUMMYFUNCTION("""COMPUTED_VALUE"""),0.848) -> 0.848 | X67: =IFERROR(__xludf.DUMMYFUNCTION("""COMPUTED_VALUE"""),1.6) -> 1.6 | Y67: =IFERROR(__xludf.DUMMYFUNCTION("""COMPUTED_VALUE"""),0.06017612839419531) -> 0.060176128 | Z67: =IFERROR(__xludf.DUMMYFUNCTION("""COMPUTED_VALUE"""),0.05075080149290546) -> 0.050750801 | AA67: =IFERROR(__xludf.DUMMYFUNCTION("""COMPUTED_VALUE"""),0.24756775948409707) -> 0.24756776 | AB67: =IFERROR(__xludf.DUMMYFUNCTION("""COMPUTED_VALUE"""),-0.8819672512840698) -> -0.88196725 | AC67: =IFERROR(__xludf.DUMMYFUNCTION("""COMPUTED_VALUE"""),-0.9166617668377661) -> -0.91666177 | AD67: =IFERROR(__xludf.DUMMYFUNCTION("""COMPUTED_VALUE"""),1.346813379735286) -> 1.3468134 | AE67: =IFERROR(__xludf.DUMMYFUNCTION("""COMPUTED_VALUE"""),-0.19021341987747237) -> -0.19021342 | AF67: =IFERROR(__xludf.DUMMYFUNCTION("""COMPUTED_VALUE"""),0.8460002998895438) -> 0.8460003 | AG67: =IFERROR(__xludf.DUMMYFUNCTION("""COMPUTED_VALUE"""),0.036866677367633396) -> 0.036866677
A68: =VLOOKUP($F68,UpdateHashtag!$V$3:$Y$32,COLUMN(B$15),0) -> 4 | B68: =VLOOKUP($F68,UpdateHashtag!$V$3:$Y$32,COLUMN(C$13),0) -> 4 | C68: =VLOOKUP($F68,UpdateHashtag!$V$3:$Y$32,COLUMN(D$13),0) -> 3 | D68: =SUM(A68:C68) -> 11 | F68: =VLOOKUP(J68,UpdateBBM!$C$2:E1015,3,0) -> MIL | G68: 49 | H68: =IFERROR(__xludf.DUMMYFUNCTION("""COMPUTED_VALUE"""),49.0) -> 49 | I68: =IFERROR(__xludf.DUMMYFUNCTION("""COMPUTED_VALUE"""),45.0) -> 45 | J68: =IFERROR(__xludf.DUMMYFUNCTION("""COMPUTED_VALUE"""),"Myles Turner") -> Myles Turner | K68: =IFERROR(__xludf.DUMMYFUNCTION("""COMPUTED_VALUE"""),64.0) -> 64 | L68: =IFERROR(__xludf.DUMMYFUNCTION("""COMPUTED_VALUE"""),"C") -> C | M68: =IFERROR(__xludf.DUMMYFUNCTION("""COMPUTED_VALUE"""),1.4008138626613764) -> 1.4008139 | N68: =IFERROR(__xludf.DUMMYFUNCTION("""COMPUTED_VALUE"""),1.4008138626613764) -> 1.4008139 | O68: =IFERROR(__xludf.DUMMYFUNCTION("""COMPUTED_VALUE"""),0.0) -> 0 | P68: =IFERROR(__xludf.DUMMYFUNCTION("""COMPUTED_VALUE"""),17.0) -> 17 | Q68: =IFERROR(__xludf.DUMMYFUNCTION("""COMPUTED_VALUE"""),1.5) -> 1.5 | R68: =IFERROR(__xludf.DUMMYFUNCTION("""COMPUTED_VALUE"""),7.0) -> 7 | S68: =IFERROR(__xludf.DUMMYFUNCTION("""COMPUTED_VALUE"""),1.3) -> 1.3 | T68: =IFERROR(__xludf.DUMMYFUNCTION("""COMPUTED_VALUE"""),0.5) -> 0.5 | U68: =IFERROR(__xludf.DUMMYFUNCTION("""COMPUTED_VALUE"""),2.0) -> 2 | V68: =IFERROR(__xludf.DUMMYFUNCTION("""COMPUTED_VALUE"""),0.535) -> 0.535 | W68: =IFERROR(__xludf.DUMMYFUNCTION("""COMPUTED_VALUE"""),0.778) -> 0.778 | X68: =IFERROR(__xludf.DUMMYFUNCTION("""COMPUTED_VALUE"""),1.5) -> 1.5 | Y68: =IFERROR(__xludf.DUMMYFUNCTION("""COMPUTED_VALUE"""),-0.0843422873119347) -> -0.084342287 | Z68: =IFERROR(__xludf.DUMMYFUNCTION("""COMPUTED_VALUE"""),-0.24782209560171908) -> -0.2478221 | AA68: =IFERROR(__xludf.DUMMYFUNCTION("""COMPUTED_VALUE"""),0.36524687285901336) -> 0.36524687 | AB68: =IFERROR(__xludf.DUMMYFUNCTION("""COMPUTED_VALUE"""),-1.2008996442390003) -> -1.2008996 | AC68: =IFERROR(__xludf.DUMMYFUNCTION("""COMPUTED_VALUE"""),-1.5805271231567248) -> -1.5805271 | AD68: =IFERROR(__xludf.DUMMYFUNCTION("""COMPUTED_VALUE"""),2.2387818899985676) -> 2.2387819 | AE68: =IFERROR(__xludf.DUMMYFUNCTION("""COMPUTED_VALUE"""),0.5137710497151557) -> 0.51377105 | AF68: =IFERROR(__xludf.DUMMYFUNCTION("""COMPUTED_VALUE"""),-0.2455868136023262) -> -0.24558681 | AG68: =IFERROR(__xludf.DUMMYFUNCTION("""COMPUTED_VALUE"""),0.06166489084362008) -> 0.061664891
